Workbook

Sheet Datos Personales
A1: CODIGO | B1: NOMBRE ESTUDIANTE | C1: COD. PROYECTO | D1: PROYECTO CURRICULAR | E1: ESTADO | F1: ESTADOS | G1: ESTRATO | H1: CORREO INSTITUCIONAL | I1: CORREO PERSONAL | J1: ID | K1: DOCUMENTO | L1: CELULAR | M1: FECHA NAC | N1: GRUPO DE INVESTIGACION
A2: 9929531 | B2: =VLOOKUP(A2,'ESTADOS ESTUDIANTES'!B:L,2,0) -> PAEZ PISCO SAMUEL | C2: =VLOOKUP(A2,'ESTADOS ESTUDIANTES'!B:L,3,0) -> 195 | D2: =VLOOKUP(A2,'ESTADOS ESTUDIANTES'!B:L,4,0) -> MAE. EN CIENCIAS DE LA INF. Y LAS COMUNICACIONES ENFASIS EN TELEINF. | E2: =VLOOKUP(A2,'ESTADOS ESTUDIANTES'!B:L,5,0) -> X | F2: =VLOOKUP(E2,Listas!B1:C1004,2,0) -> EXCLUIDO | G2: =VLOOKUP(A2,'ESTADOS ESTUDIANTES'!B:L,7,0) -> 3 | H2: =VLOOKUP(A2,'ESTADOS ESTUDIANTES'!B:L,8,0) -> spaezp@correo.udistrital.edu.co | I2: =VLOOKUP(A2,'ESTADOS ESTUDIANTES'!B:L,9,0) -> samuel.paez@fiscalia.gov.co | J2: =VLOOKUP(A2,'ESTADOS ESTUDIANTES'!B:L,10,0) -> CC | K2: =VLOOKUP(A2,'ESTADOS ESTUDIANTES'!B:L,11,0) -> 79472385 | L2: 3174861160
A3: 9929539 | B3: =VLOOKUP(A3,'ESTADOS ESTUDIANTES'!B:L,2,0) -> RODRIGUEZ RENGIFO JORGE | C3: =VLOOKUP(A3,'ESTADOS ESTUDIANTES'!B:L,3,0) -> 195 | D3: =VLOOKUP(A3,'ESTADOS ESTUDIANTES'!B:L,4,0) -> MAE. EN CIENCIAS DE LA INF. Y LAS COMUNICACIONES ENFASIS EN TELEINF. | E3: =VLOOKUP(A3,'ESTADOS ESTUDIANTES'!B:L,5,0) -> X | F3: =VLOOKUP(E3,Listas!B1:C1004,2,0) -> EXCLUIDO | G3: =VLOOKUP(A3,'ESTADOS ESTUDIANTES'!B:L,7,0) -> 3 | H3: =VLOOKUP(A3,'ESTADOS ESTUDIANTES'!B:L,8,0) -> jrodriguezr@udistrital.edu.co | I3: =VLOOKUP(A3,'ESTADOS ESTUDIANTES'!B:L,9,0) -> jorge.rodriguez@engineer.com | J3: =VLOOKUP(A3,'ESTADOS ESTUDIANTES'!B:L,10,0) -> CC | K3: =VLOOKUP(A3,'ESTADOS ESTUDIANTES'!B:L,11,0) -> 7545588 | L3: 3012399398
A4: 20012095004 | B4: =VLOOKUP(A4,'ESTADOS ESTUDIANTES'!B:L,2,0) -> BECERRA FINO JOSE YASIS | C4: =VLOOKUP(A4,'ESTADOS ESTUDIANTES'!B:L,3,0) -> 195 | D4: =VLOOKUP(A4,'ESTADOS ESTUDIANTES'!B:L,4,0) -> MAE. EN CIENCIAS DE LA INF. Y LAS COMUNICACIONES ENFASIS EN TELEINF. | E4: =VLOOKUP(A4,'ESTADOS ESTUDIANTES'!B:L,5,0) -> X | F4: =VLOOKUP(E4,Listas!B1:C1004,2,0) -> EXCLUIDO | G4: =VLOOKUP(A4,'ESTADOS ESTUDIANTES'!B:L,7,0) -> 3 | H4: =VLOOKUP(A4,'ESTADOS ESTUDIANTES'!B:L,8,0) -> jybecerraf@correo.udistrital.edu.co | I4: =VLOOKUP(A4,'ESTADOS ESTUDIANTES'!B:L,9,0) -> jybecerra@gmail.com | J4: =VLOOKUP(A4,'ESTADOS ESTUDIANTES'!B:L,10,0) -> CC | K4: =VLOOKUP(A4,'ESTADOS ESTUDIANTES'!B:L,11,0) -> 79483121 | L4: 3106981701
A5: 20022095016 | B5: =VLOOKUP(A5,'ESTADOS ESTUDIANTES'!B:L,2,0) -> SEGURA ASCENCIO OMAR ENRIQUE | C5: =VLOOKUP(A5,'ESTADOS ESTUDIANTES'!B:L,3,0) -> 295 | D5: =VLOOKUP(A5,'ESTADOS ESTUDIANTES'!B:L,4,0) -> MAE. EN CIENCIAS DE LA INF. Y LAS COMUNICACIONES ENFASIS EN SIS. INFOR | E5: =VLOOKUP(A5,'ESTADOS ESTUDIANTES'!B:L,5,0) -> X | F5: =VLOOKUP(E5,Listas!B1:C1004,2,0) -> EXCLUIDO | G5: =VLOOKUP(A5,'ESTADOS ESTUDIANTES'!B:L,7,0) -> NO REGISTRA | H5: =VLOOKUP(A5,'ESTADOS ESTUDIANTES'!B:L,8,0) -> oeseguraa@correo.udistrital.edu.co | I5: =VLOOKUP(A5,'ESTADOS ESTUDIANTES'!B:L,9,0) -> omarsegura12@hotmail.com | J5: =VLOOKUP(A5,'ESTADOS ESTUDIANTES'!B:L,10,0) -> CC | K5: =VLOOKUP(A5,'ESTADOS ESTUDIANTES'!B:L,11,0) -> 4979940
A6: 20032095001 | B6: =VLOOKUP(A6,'ESTADOS ESTUDIANTES'!B:L,2,0) -> AMAYA CORREDOR YESID | C6: =VLOOKUP(A6,'ESTADOS ESTUDIANTES'!B:L,3,0) -> 195 | D6: =VLOOKUP(A6,'ESTADOS ESTUDIANTES'!B:L,4,0) -> MAE. EN CIENCIAS DE LA INF. Y LAS COMUNICACIONES ENFASIS EN TELEINF. | E6: =VLOOKUP(A6,'ESTADOS ESTUDIANTES'!B:L,5,0) -> Z | F6: =VLOOKUP(E6,Listas!B1:C1004,2,0) -> NO SUP. PRUEBA ACAD. | G6: =VLOOKUP(A6,'ESTADOS ESTUDIANTES'!B:L,7,0) -> NO REGISTRA | H6: =VLOOKUP(A6,'ESTADOS ESTUDIANTES'!B:L,8,0) -> 0 | I6: =VLOOKUP(A6,'ESTADOS ESTUDIANTES'!B:L,9,0) -> 0 | J6: =VLOOKUP(A6,'ESTADOS ESTUDIANTES'!B:L,10,0) -> CC | K6: =VLOOKUP(A6,'ESTADOS ESTUDIANTES'!B:L,11,0) -> 13928471
A7: 20032095004 | B7: =VLOOKUP(A7,'ESTADOS ESTUDIANTES'!B:L,2,0) -> CEDANO GARCIA ROCIO | C7: =VLOOKUP(A7,'ESTADOS ESTUDIANTES'!B:L,3,0) -> 195 | D7: =VLOOKUP(A7,'ESTADOS ESTUDIANTES'!B:L,4,0) -> MAE. EN CIENCIAS DE LA INF. Y LAS COMUNICACIONES ENFASIS EN TELEINF. | E7: =VLOOKUP(A7,'ESTADOS ESTUDIANTES'!B:L,5,0) -> E | F7: =VLOOKUP(E7,Listas!B1:C1004,2,0) -> EGRESADO | G7: =VLOOKUP(A7,'ESTADOS ESTUDIANTES'!B:L,7,0) -> 1 | H7: =VLOOKUP(A7,'ESTADOS ESTUDIANTES'!B:L,8,0) -> rcedanog@correo.udistrital.edu.co | I7: =VLOOKUP(A7,'ESTADOS ESTUDIANTES'!B:L,9,0) -> rociocedano@yahoo.com | J7: =VLOOKUP(A7,'ESTADOS ESTUDIANTES'!B:L,10,0) -> CC | K7: =VLOOKUP(A7,'ESTADOS ESTUDIANTES'!B:L,11,0) -> 51960945
A8: 20032095006 | B8: =VLOOKUP(A8,'ESTADOS ESTUDIANTES'!B:L,2,0) -> FAJARDO ORTEGA OSCAR ALFREDO | C8: =VLOOKUP(A8,'ESTADOS ESTUDIANTES'!B:L,3,0) -> 295 | D8: =VLOOKUP(A8,'ESTADOS ESTUDIANTES'!B:L,4,0) -> MAE. EN CIENCIAS DE LA INF. Y LAS COMUNICACIONES ENFASIS EN SIS. INFOR | E8: =VLOOKUP(A8,'ESTADOS ESTUDIANTES'!B:L,5,0) -> E | F8: =VLOOKUP(E8,Listas!B1:C1004,2,0) -> EGRESADO | G8: =VLOOKUP(A8,'ESTADOS ESTUDIANTES'!B:L,7,0) -> 1 | H8: =VLOOKUP(A8,'ESTADOS ESTUDIANTES'!B:L,8,0) -> oafajardoo@correo.udistrital.edu.co | I8: =VLOOKUP(A8,'ESTADOS ESTUDIANTES'!B:L,9,0) -> fajardo_oscar@hotmail.com | J8: =VLOOKUP(A8,'ESTADOS ESTUDIANTES'!B:L,10,0) -> CC | K8: =VLOOKUP(A8,'ESTADOS ESTUDIANTES'!B:L,11,0) -> 97470859
A9: 20032095007 | B9: =VLOOKUP(A9,'ESTADOS ESTUDIANTES'!B:L,2,0) -> GAMBA AGUIRRE DEISY JUDITH | C9: =VLOOKUP(A9,'ESTADOS ESTUDIANTES'!B:L,3,0) -> 195 | D9: =VLOOKUP(A9,'ESTADOS ESTUDIANTES'!B:L,4,0) -> MAE. EN CIENCIAS DE LA INF. Y LAS COMUNICACIONES ENFASIS EN TELEINF. | E9: =VLOOKUP(A9,'ESTADOS ESTUDIANTES'!B:L,5,0) -> Z | F9: =VLOOKUP(E9,Listas!B1:C1004,2,0) -> NO SUP. PRUEBA ACAD. | G9: =VLOOKUP(A9,'ESTADOS ESTUDIANTES'!B:L,7,0) -> NO REGISTRA | H9: =VLOOKUP(A9,'ESTADOS ESTUDIANTES'!B:L,8,0) -> 0 | I9: =VLOOKUP(A9,'ESTADOS ESTUDIANTES'!B:L,9,0) -> 0 | J9: =VLOOKUP(A9,'ESTADOS ESTUDIANTES'!B:L,10,0) -> CC | K9: =VLOOKUP(A9,'ESTADOS ESTUDIANTES'!B:L,11,0) -> 52396642
A10: 20032095008 | B10: =VLOOKUP(A10,'ESTADOS ESTUDIANTES'!B:L,2,0) -> RENE GEOVANI GONZALEZ CABALLERO | C10: =VLOOKUP(A10,'ESTADOS ESTUDIANTES'!B:L,3,0) -> 195 | D10: =VLOOKUP(A10,'ESTADOS ESTUDIANTES'!B:L,4,0) -> MAE. EN CIENCIAS DE LA INF. Y LAS COMUNICACIONES ENFASIS EN TELEINF. | E10: =VLOOKUP(A10,'ESTADOS ESTUDIANTES'!B:L,5,0) -> E | F10: =VLOOKUP(E10,Listas!B1:C1004,2,0) -> EGRESADO | G10: =VLOOKUP(A10,'ESTADOS ESTUDIANTES'!B:L,7,0) -> 1 | H10: =VLOOKUP(A10,'ESTADOS ESTUDIANTES'!B:L,8,0) -> rggonzalezc@correo.udistrital.edu.co | I10: =VLOOKUP(A10,'ESTADOS ESTUDIANTES'!B:L,9,0) -> rengoca@hotmail.com | J10: =VLOOKUP(A10,'ESTADOS ESTUDIANTES'!B:L,10,0) -> CC | K10: =VLOOKUP(A10,'ESTADOS ESTUDIANTES'!B:L,11,0) -> 13957351
A11: 20032095009 | B11: =VLOOKUP(A11,'ESTADOS ESTUDIANTES'!B:L,2,0) -> LOPEZ HERNANDEZ HERLEDY | C11: =VLOOKUP(A11,'ESTADOS ESTUDIANTES'!B:L,3,0) -> 195 | D11: =VLOOKUP(A11,'ESTADOS ESTUDIANTES'!B:L,4,0) -> MAE. EN CIENCIAS DE LA INF. Y LAS COMUNICACIONES ENFASIS EN TELEINF. | E11: =VLOOKUP(A11,'ESTADOS ESTUDIANTES'!B:L,5,0) -> X | F11: =VLOOKUP(E11,Listas!B1:C1004,2,0) -> EXCLUIDO | G11: =VLOOKUP(A11,'ESTADOS ESTUDIANTES'!B:L,7,0) -> NO REGISTRA | H11: =VLOOKUP(A11,'ESTADOS ESTUDIANTES'!B:L,8,0) -> 0 | I11: =VLOOKUP(A11,'ESTADOS ESTUDIANTES'!B:L,9,0) -> 0 | J11: =VLOOKUP(A11,'ESTADOS ESTUDIANTES'!B:L,10,0) -> CC | K11: =VLOOKUP(A11,'ESTADOS ESTUDIANTES'!B:L,11,0) -> 79414063
A12: 20032095010 | B12: =VLOOKUP(A12,'ESTADOS ESTUDIANTES'!B:L,2,0) -> MEJIA ARIAS GASTON ANTONIO | C12: =VLOOKUP(A12,'ESTADOS ESTUDIANTES'!B:L,3,0) -> 295 | D12: =VLOOKUP(A12,'ESTADOS ESTUDIANTES'!B:L,4,0) -> MAE. EN CIENCIAS DE LA INF. Y LAS COMUNICACIONES ENFASIS EN SIS. INFOR | E12: =VLOOKUP(A12,'ESTADOS ESTUDIANTES'!B:L,5,0) -> E | F12: =VLOOKUP(E12,Listas!B1:C1004,2,0) -> EGRESADO | G12: =VLOOKUP(A12,'ESTADOS ESTUDIANTES'!B:L,7,0) -> NO REGISTRA | H12: =VLOOKUP(A12,'ESTADOS ESTUDIANTES'!B:L,8,0) -> gamejiaa@correo.udistrital.edu.co | I12: =VLOOKUP(A12,'ESTADOS ESTUDIANTES'!B:L,9,0) -> gaston.mejia@gmail.com | J12: =VLOOKUP(A12,'ESTADOS ESTUDIANTES'!B:L,10,0) -> CC | K12: =VLOOKUP(A12,'ESTADOS ESTUDIANTES'!B:L,11,0) -> 79697729
A13: 20032095012 | B13: =VLOOKUP(A13,'ESTADOS ESTUDIANTES'!B:L,2,0) -> PADILLA BAÑOS DOLLY MARCELA | C13: =VLOOKUP(A13,'ESTADOS ESTUDIANTES'!B:L,3,0) -> 195 | D13: =VLOOKUP(A13,'ESTADOS ESTUDIANTES'!B:L,4,0) -> MAE. EN CIENCIAS DE LA INF. Y LAS COMUNICACIONES ENFASIS EN TELEINF. | E13: =VLOOKUP(A13,'ESTADOS ESTUDIANTES'!B:L,5,0) -> E | F13: =VLOOKUP(E13,Listas!B1:C1004,2,0) -> EGRESADO | G13: =VLOOKUP(A13,'ESTADOS ESTUDIANTES'!B:L,7,0) -> 3 | H13: =VLOOKUP(A13,'ESTADOS ESTUDIANTES'!B:L,8,0) -> dmpadillab@correo.udistrital.edu.co | I13: =VLOOKUP(A13,'ESTADOS ESTUDIANTES'!B:L,9,0) -> dollypadilla@hotmail.com | J13: =VLOOKUP(A13,'ESTADOS ESTUDIANTES'!B:L,10,0) -> CC | K13: =VLOOKUP(A13,'ESTADOS ESTUDIANTES'!B:L,11,0) -> 22546893
A14: 20032095013 | B14: =VLOOKUP(A14,'ESTADOS ESTUDIANTES'!B:L,2,0) -> RINCON LEGUIZAMON LIZT MARICELLA | C14: =VLOOKUP(A14,'ESTADOS ESTUDIANTES'!B:L,3,0) -> 195 | D14: =VLOOKUP(A14,'ESTADOS ESTUDIANTES'!B:L,4,0) -> MAE. EN CIENCIAS DE LA INF. Y LAS COMUNICACIONES ENFASIS EN TELEINF. | E14: =VLOOKUP(A14,'ESTADOS ESTUDIANTES'!B:L,5,0) -> Z | F14: =VLOOKUP(E14,Listas!B1:C1004,2,0) -> NO SUP. PRUEBA ACAD. | G14: =VLOOKUP(A14,'ESTADOS ESTUDIANTES'!B:L,7,0) -> NO REGISTRA | H14: =VLOOKUP(A14,'ESTADOS ESTUDIANTES'!B:L,8,0) -> lmrinconl@correo.udistrital.edu.co | I14: =VLOOKUP(A14,'ESTADOS ESTUDIANTES'!B:L,9,0) -> lmrinconl@estudiante.udistrital.edu.co | J14: =VLOOKUP(A14,'ESTADOS ESTUDIANTES'!B:L,10,0) -> CC | K14: =VLOOKUP(A14,'ESTADOS ESTUDIANTES'!B:L,11,0) -> 40031895
A15: 20032095014 | B15: =VLOOKUP(A15,'ESTADOS ESTUDIANTES'!B:L,2,0) -> RINCON BARRERA RAFAEL ANDRES | C15: =VLOOKUP(A15,'ESTADOS ESTUDIANTES'!B:L,3,0) -> 195 | D15: =VLOOKUP(A15,'ESTADOS ESTUDIANTES'!B:L,4,0) -> MAE. EN CIENCIAS DE LA INF. Y LAS COMUNICACIONES ENFASIS EN TELEINF. | E15: =VLOOKUP(A15,'ESTADOS ESTUDIANTES'!B:L,5,0) -> Z | F15: =VLOOKUP(E15,Listas!B1:C1004,2,0) -> NO SUP. PRUEBA ACAD. | G15: =VLOOKUP(A15,'ESTADOS ESTUDIANTES'!B:L,7,0) -> NO REGISTRA | H15: =VLOOKUP(A15,'ESTADOS ESTUDIANTES'!B:L,8,0) -> 0 | I15: =VLOOKUP(A15,'ESTADOS ESTUDIANTES'!B:L,9,0) -> 0 | J15: =VLOOKUP(A15,'ESTADOS ESTUDIANTES'!B:L,10,0) -> CC | K15: =VLOOKUP(A15,'ESTADOS ESTUDIANTES'!B:L,11,0) -> 79185945
A16: 20032095016 | B16: =VLOOKUP(A16,'ESTADOS ESTUDIANTES'!B:L,2,0) -> BARACALDO JULIO CESAR | C16: =VLOOKUP(A16,'ESTADOS ESTUDIANTES'!B:L,3,0) -> 295 | D16: =VLOOKUP(A16,'ESTADOS ESTUDIANTES'!B:L,4,0) -> MAE. EN CIENCIAS DE LA INF. Y LAS COMUNICACIONES ENFASIS EN SIS. INFOR | E16: =VLOOKUP(A16,'ESTADOS ESTUDIANTES'!B:L,5,0) -> X | F16: =VLOOKUP(E16,Listas!B1:C1004,2,0) -> EXCLUIDO | G16: =VLOOKUP(A16,'ESTADOS ESTUDIANTES'!B:L,7,0) -> NO REGISTRA | H16: =VLOOKUP(A16,'ESTADOS ESTUDIANTES'!B:L,8,0) -> jbaracaldo@correo.udistrital.edu.co | I16: =VLOOKUP(A16,'ESTADOS ESTUDIANTES'!B:L,9,0) -> jcbaracaldo@gmail.com | J16: =VLOOKUP(A16,'ESTADOS ESTUDIANTES'!B:L,10,0) -> CC | K16: =VLOOKUP(A16,'ESTADOS ESTUDIANTES'!B:L,11,0) -> 19359635
A17: 20032095017 | B17: =VLOOKUP(A17,'ESTADOS ESTUDIANTES'!B:L,2,0) -> RIVERO PEREZ JUAN CARLOS | C17: =VLOOKUP(A17,'ESTADOS ESTUDIANTES'!B:L,3,0) -> 195 | D17: =VLOOKUP(A17,'ESTADOS ESTUDIANTES'!B:L,4,0) -> MAE. EN CIENCIAS DE LA INF. Y LAS COMUNICACIONES ENFASIS EN TELEINF. | E17: =VLOOKUP(A17,'ESTADOS ESTUDIANTES'!B:L,5,0) -> X | F17: =VLOOKUP(E17,Listas!B1:C1004,2,0) -> EXCLUIDO | G17: =VLOOKUP(A17,'ESTADOS ESTUDIANTES'!B:L,7,0) -> NO REGISTRA | H17: =VLOOKUP(A17,'ESTADOS ESTUDIANTES'!B:L,8,0) -> jucriverop@correo.udistrital.edu.co | I17: =VLOOKUP(A17,'ESTADOS ESTUDIANTES'!B:L,9,0) -> jucriverop@estudiante.udistrital.edu.co | J17: =VLOOKUP(A17,'ESTADOS ESTUDIANTES'!B:L,10,0) -> CC | K17: =VLOOKUP(A17,'ESTADOS ESTUDIANTES'!B:L,11,0) -> 79425695
A18: 20041195001 | B18: =VLOOKUP(A18,'ESTADOS ESTUDIANTES'!B:L,2,0) -> ACERO SOTO DIEGO MAURICIO | C18: =VLOOKUP(A18,'ESTADOS ESTUDIANTES'!B:L,3,0) -> 195 | D18: =VLOOKUP(A18,'ESTADOS ESTUDIANTES'!B:L,4,0) -> MAE. EN CIENCIAS DE LA INF. Y LAS COMUNICACIONES ENFASIS EN TELEINF. | E18: =VLOOKUP(A18,'ESTADOS ESTUDIANTES'!B:L,5,0) -> X | F18: =VLOOKUP(E18,Listas!B1:C1004,2,0) -> EXCLUIDO | G18: =VLOOKUP(A18,'ESTADOS ESTUDIANTES'!B:L,7,0) -> NO REGISTRA | H18: =VLOOKUP(A18,'ESTADOS ESTUDIANTES'!B:L,8,0) -> dmaceros@correo.udistrital.edu.co | I18: =VLOOKUP(A18,'ESTADOS ESTUDIANTES'!B:L,9,0) -> dmaceros@estudiante.udistrital.edu.co | J18: =VLOOKUP(A18,'ESTADOS ESTUDIANTES'!B:L,10,0) -> CC | K18: =VLOOKUP(A18,'ESTADOS ESTUDIANTES'!B:L,11,0) -> 79576183
A19: 20041195002 | B19: =VLOOKUP(A19,'ESTADOS ESTUDIANTES'!B:L,2,0) -> AMAYA CAICEDO HERNAN G. | C19: =VLOOKUP(A19,'ESTADOS ESTUDIANTES'!B:L,3,0) -> 195 | D19: =VLOOKUP(A19,'ESTADOS ESTUDIANTES'!B:L,4,0) -> MAE. EN CIENCIAS DE LA INF. Y LAS COMUNICACIONES ENFASIS EN TELEINF. | E19: =VLOOKUP(A19,'ESTADOS ESTUDIANTES'!B:L,5,0) -> Z | F19: =VLOOKUP(E19,Listas!B1:C1004,2,0) -> NO SUP. PRUEBA ACAD. | G19: =VLOOKUP(A19,'ESTADOS ESTUDIANTES'!B:L,7,0) -> NO REGISTRA | H19: =VLOOKUP(A19,'ESTADOS ESTUDIANTES'!B:L,8,0) -> hgamayac@correo.udistrital.edu.co | I19: =VLOOKUP(A19,'ESTADOS ESTUDIANTES'!B:L,9,0) -> hgamayac@estudiante.udistrital.edu.co | J19: =VLOOKUP(A19,'ESTADOS ESTUDIANTES'!B:L,10,0) -> CC | K19: =VLOOKUP(A19,'ESTADOS ESTUDIANTES'!B:L,11,0) -> 7170256
A20: 20041195003 | B20: =VLOOKUP(A20,'ESTADOS ESTUDIANTES'!B:L,2,0) -> BONILLA OLAYA JOSE EBERT | C20: =VLOOKUP(A20,'ESTADOS ESTUDIANTES'!B:L,3,0) -> 195 | D20: =VLOOKUP(A20,'ESTADOS ESTUDIANTES'!B:L,4,0) -> MAE. EN CIENCIAS DE LA INF. Y LAS COMUNICACIONES ENFASIS EN TELEINF. | E20: =VLOOKUP(A20,'ESTADOS ESTUDIANTES'!B:L,5,0) -> E | F20: =VLOOKUP(E20,Listas!B1:C1004,2,0) -> EGRESADO | G20: =VLOOKUP(A20,'ESTADOS ESTUDIANTES'!B:L,7,0) -> NO REGISTRA | H20: =VLOOKUP(A20,'ESTADOS ESTUDIANTES'!B:L,8,0) -> jebonillao@correo.udistrital.edu.co | I20: =VLOOKUP(A20,'ESTADOS ESTUDIANTES'!B:L,9,0) -> jose.ebert@gmail.com | J20: =VLOOKUP(A20,'ESTADOS ESTUDIANTES'!B:L,10,0) -> CC | K20: =VLOOKUP(A20,'ESTADOS ESTUDIANTES'!B:L,11,0) -> 80269115
A21: 20041195004 | B21: =VLOOKUP(A21,'ESTADOS ESTUDIANTES'!B:L,2,0) -> BUITRAGO BRAVO RONALD YESID | C21: =VLOOKUP(A21,'ESTADOS ESTUDIANTES'!B:L,3,0) -> 195 | D21: =VLOOKUP(A21,'ESTADOS ESTUDIANTES'!B:L,4,0) -> MAE. EN CIENCIAS DE LA INF. Y LAS COMUNICACIONES ENFASIS EN TELEINF. | E21: =VLOOKUP(A21,'ESTADOS ESTUDIANTES'!B:L,5,0) -> E | F21: =VLOOKUP(E21,Listas!B1:C1004,2,0) -> EGRESADO | G21: =VLOOKUP(A21,'ESTADOS ESTUDIANTES'!B:L,7,0) -> NO REGISTRA | H21: =VLOOKUP(A21,'ESTADOS ESTUDIANTES'!B:L,8,0) -> rybuitragob@correo.udistrital.edu.co | I21: =VLOOKUP(A21,'ESTADOS ESTUDIANTES'!B:L,9,0) -> rybuitrago@bancodeoccidente.com.co | J21: =VLOOKUP(A21,'ESTADOS ESTUDIANTES'!B:L,10,0) -> CC | K21: =VLOOKUP(A21,'ESTADOS ESTUDIANTES'!B:L,11,0) -> 79796071
A22: 20041195005 | B22: =VLOOKUP(A22,'ESTADOS ESTUDIANTES'!B:L,2,0) -> CORTES LOPEZ HERNAN ANDRES | C22: =VLOOKUP(A22,'ESTADOS ESTUDIANTES'!B:L,3,0) -> 195 | D22: =VLOOKUP(A22,'ESTADOS ESTUDIANTES'!B:L,4,0) -> MAE. EN CIENCIAS DE LA INF. Y LAS COMUNICACIONES ENFASIS EN TELEINF. | E22: =VLOOKUP(A22,'ESTADOS ESTUDIANTES'!B:L,5,0) -> X | F22: =VLOOKUP(E22,Listas!B1:C1004,2,0) -> EXCLUIDO | G22: =VLOOKUP(A22,'ESTADOS ESTUDIANTES'!B:L,7,0) -> NO REGISTRA | H22: =VLOOKUP(A22,'ESTADOS ESTUDIANTES'!B:L,8,0) -> 0 | I22: =VLOOKUP(A22,'ESTADOS ESTUDIANTES'!B:L,9,0) -> 0 | J22: =VLOOKUP(A22,'ESTADOS ESTUDIANTES'!B:L,10,0) -> CC | K22: =VLOOKUP(A22,'ESTADOS ESTUDIANTES'!B:L,11,0) -> 74187327
A23: 20041195006 | B23: =VLOOKUP(A23,'ESTADOS ESTUDIANTES'!B:L,2,0) -> CUBILLOS SANCHEZ RAFAEL ORLANDO | C23: =VLOOKUP(A23,'ESTADOS ESTUDIANTES'!B:L,3,0) -> 195 | D23: =VLOOKUP(A23,'ESTADOS ESTUDIANTES'!B:L,4,0) -> MAE. EN CIENCIAS DE LA INF. Y LAS COMUNICACIONES ENFASIS EN TELEINF. | E23: =VLOOKUP(A23,'ESTADOS ESTUDIANTES'!B:L,5,0) -> X | F23: =VLOOKUP(E23,Listas!B1:C1004,2,0) -> EXCLUIDO | G23: =VLOOKUP(A23,'ESTADOS ESTUDIANTES'!B:L,7,0) -> NO REGISTRA | H23: =VLOOKUP(A23,'ESTADOS ESTUDIANTES'!B:L,8,0) -> rocubilloss@udistrital.edu.co | I23: =VLOOKUP(A23,'ESTADOS ESTUDIANTES'!B:L,9,0) -> rocubilloss@estudiante.udistrital.edu.co | J23: =VLOOKUP(A23,'ESTADOS ESTUDIANTES'!B:L,10,0) -> CC | K23: =VLOOKUP(A23,'ESTADOS ESTUDIANTES'!B:L,11,0) -> 79578336
A24: 20041195007 | B24: =VLOOKUP(A24,'ESTADOS ESTUDIANTES'!B:L,2,0) -> DIAZ MARTINEZ NEIL ORLANDO | C24: =VLOOKUP(A24,'ESTADOS ESTUDIANTES'!B:L,3,0) -> 195 | D24: =VLOOKUP(A24,'ESTADOS ESTUDIANTES'!B:L,4,0) -> MAE. EN CIENCIAS DE LA INF. Y LAS COMUNICACIONES ENFASIS EN TELEINF. | E24: =VLOOKUP(A24,'ESTADOS ESTUDIANTES'!B:L,5,0) -> E | F24: =VLOOKUP(E24,Listas!B1:C1004,2,0) -> EGRESADO | G24: =VLOOKUP(A24,'ESTADOS ESTUDIANTES'!B:L,7,0) -> NO REGISTRA | H24: =VLOOKUP(A24,'ESTADOS ESTUDIANTES'!B:L,8,0) -> nodiazm@correo.udistrital.edu.co | I24: =VLOOKUP(A24,'ESTADOS ESTUDIANTES'!B:L,9,0) -> neil_or@yahoo.com | J24: =VLOOKUP(A24,'ESTADOS ESTUDIANTES'!B:L,10,0) -> CC | K24: =VLOOKUP(A24,'ESTADOS ESTUDIANTES'!B:L,11,0) -> 72270879
A25: 20041195008 | B25: =VLOOKUP(A25,'ESTADOS ESTUDIANTES'!B:L,2,0) -> GAONA GARCIA ELVIS EDUARDO | C25: =VLOOKUP(A25,'ESTADOS ESTUDIANTES'!B:L,3,0) -> 195 | D25: =VLOOKUP(A25,'ESTADOS ESTUDIANTES'!B:L,4,0) -> MAE. EN CIENCIAS DE LA INF. Y LAS COMUNICACIONES ENFASIS EN TELEINF. | E25: =VLOOKUP(A25,'ESTADOS ESTUDIANTES'!B:L,5,0) -> E | F25: =VLOOKUP(E25,Listas!B1:C1004,2,0) -> EGRESADO | G25: =VLOOKUP(A25,'ESTADOS ESTUDIANTES'!B:L,7,0) -> NO REGISTRA | H25: =VLOOKUP(A25,'ESTADOS ESTUDIANTES'!B:L,8,0) -> eegaonag@correo.udistrital.edu.co | I25: =VLOOKUP(A25,'ESTADOS ESTUDIANTES'!B:L,9,0) -> egaona@udistrital.edu.co | J25: =VLOOKUP(A25,'ESTADOS ESTUDIANTES'!B:L,10,0) -> CC | K25: =VLOOKUP(A25,'ESTADOS ESTUDIANTES'!B:L,11,0) -> 79950025
A26: 20041195009 | B26: =VLOOKUP(A26,'ESTADOS ESTUDIANTES'!B:L,2,0) -> GAONA GARCIA PAULO ALONSO | C26: =VLOOKUP(A26,'ESTADOS ESTUDIANTES'!B:L,3,0) -> 195 | D26: =VLOOKUP(A26,'ESTADOS ESTUDIANTES'!B:L,4,0) -> MAE. EN CIENCIAS DE LA INF. Y LAS COMUNICACIONES ENFASIS EN TELEINF. | E26: =VLOOKUP(A26,'ESTADOS ESTUDIANTES'!B:L,5,0) -> E | F26: =VLOOKUP(E26,Listas!B1:C1004,2,0) -> EGRESADO | G26: =VLOOKUP(A26,'ESTADOS ESTUDIANTES'!B:L,7,0) -> NO REGISTRA | H26: =VLOOKUP(A26,'ESTADOS ESTUDIANTES'!B:L,8,0) -> pagaonag@correo.udistrital.edu.co | I26: =VLOOKUP(A26,'ESTADOS ESTUDIANTES'!B:L,9,0) -> gaoanaalonso@yahoo.es | J26: =VLOOKUP(A26,'ESTADOS ESTUDIANTES'!B:L,10,0) -> CC | K26: =VLOOKUP(A26,'ESTADOS ESTUDIANTES'!B:L,11,0) -> 80092512
A27: 20041195010 | B27: =VLOOKUP(A27,'ESTADOS ESTUDIANTES'!B:L,2,0) -> LOPEZ QUINTERO JOSE FERNANDO | C27: =VLOOKUP(A27,'ESTADOS ESTUDIANTES'!B:L,3,0) -> 195 | D27: =VLOOKUP(A27,'ESTADOS ESTUDIANTES'!B:L,4,0) -> MAE. EN CIENCIAS DE LA INF. Y LAS COMUNICACIONES ENFASIS EN TELEINF. | E27: =VLOOKUP(A27,'ESTADOS ESTUDIANTES'!B:L,5,0) -> X | F27: =VLOOKUP(E27,Listas!B1:C1004,2,0) -> EXCLUIDO | G27: =VLOOKUP(A27,'ESTADOS ESTUDIANTES'!B:L,7,0) -> NO REGISTRA | H27: =VLOOKUP(A27,'ESTADOS ESTUDIANTES'!B:L,8,0) -> jflopezq@correo.udistrital.edu.co | I27: =VLOOKUP(A27,'ESTADOS ESTUDIANTES'!B:L,9,0) -> jflopezq@estudiante.udistrital.edu.co | J27: =VLOOKUP(A27,'ESTADOS ESTUDIANTES'!B:L,10,0) -> CC | K27: =VLOOKUP(A27,'ESTADOS ESTUDIANTES'!B:L,11,0) -> 79788244
A28: 20041195011 | B28: =VLOOKUP(A28,'ESTADOS ESTUDIANTES'!B:L,2,0) -> MACIAS MUNOZ GERMAN | C28: =VLOOKUP(A28,'ESTADOS ESTUDIANTES'!B:L,3,0) -> 195 | D28: =VLOOKUP(A28,'ESTADOS ESTUDIANTES'!B:L,4,0) -> MAE. EN CIENCIAS DE LA INF. Y LAS COMUNICACIONES ENFASIS EN TELEINF. | E28: =VLOOKUP(A28,'ESTADOS ESTUDIANTES'!B:L,5,0) -> E | F28: =VLOOKUP(E28,Listas!B1:C1004,2,0) -> EGRESADO | G28: =VLOOKUP(A28,'ESTADOS ESTUDIANTES'!B:L,7,0) -> NO REGISTRA | H28: =VLOOKUP(A28,'ESTADOS ESTUDIANTES'!B:L,8,0) -> gmaciasm@udistrital.edu.co | I28: =VLOOKUP(A28,'ESTADOS ESTUDIANTES'!B:L,9,0) -> germaci@gmail.com | J28: =VLOOKUP(A28,'ESTADOS ESTUDIANTES'!B:L,10,0) -> CC | K28: =VLOOKUP(A28,'ESTADOS ESTUDIANTES'!B:L,11,0) -> 79453519
A29: 20041195012 | B29: =VLOOKUP(A29,'ESTADOS ESTUDIANTES'!B:L,2,0) -> MARTINEZ WITTINGHAN OSCAR H. | C29: =VLOOKUP(A29,'ESTADOS ESTUDIANTES'!B:L,3,0) -> 195 | D29: =VLOOKUP(A29,'ESTADOS ESTUDIANTES'!B:L,4,0) -> MAE. EN CIENCIAS DE LA INF. Y LAS COMUNICACIONES ENFASIS EN TELEINF. | E29: =VLOOKUP(A29,'ESTADOS ESTUDIANTES'!B:L,5,0) -> X | F29: =VLOOKUP(E29,Listas!B1:C1004,2,0) -> EXCLUIDO | G29: =VLOOKUP(A29,'ESTADOS ESTUDIANTES'!B:L,7,0) -> NO REGISTRA | H29: =VLOOKUP(A29,'ESTADOS ESTUDIANTES'!B:L,8,0) -> ohmartinezw@correo.udistrital.edu.co | I29: =VLOOKUP(A29,'ESTADOS ESTUDIANTES'!B:L,9,0) -> ohmartinezw@estudiante.udistrital.edu.co | J29: =VLOOKUP(A29,'ESTADOS ESTUDIANTES'!B:L,10,0) -> CC | K29: =VLOOKUP(A29,'ESTADOS ESTUDIANTES'!B:L,11,0) -> 74184170
A30: 20041195013 | B30: =VLOOKUP(A30,'ESTADOS ESTUDIANTES'!B:L,2,0) -> MONTENEGRO MARIN CARLOS E. | C30: =VLOOKUP(A30,'ESTADOS ESTUDIANTES'!B:L,3,0) -> 195 | D30: =VLOOKUP(A30,'ESTADOS ESTUDIANTES'!B:L,4,0) -> MAE. EN CIENCIAS DE LA INF. Y LAS COMUNICACIONES ENFASIS EN TELEINF. | E30: =VLOOKUP(A30,'ESTADOS ESTUDIANTES'!B:L,5,0) -> E | F30: =VLOOKUP(E30,Listas!B1:C1004,2,0) -> EGRESADO | G30: =VLOOKUP(A30,'ESTADOS ESTUDIANTES'!B:L,7,0) -> NO REGISTRA | H30: =VLOOKUP(A30,'ESTADOS ESTUDIANTES'!B:L,8,0) -> cemontenegrom@correo.udistrital.edu.co | I30: =VLOOKUP(A30,'ESTADOS ESTUDIANTES'!B:L,9,0) -> cemontenegrom@estudiante.udistrital.edu.co | J30: =VLOOKUP(A30,'ESTADOS ESTUDIANTES'!B:L,10,0) -> CC | K30: =VLOOKUP(A30,'ESTADOS ESTUDIANTES'!B:L,11,0) -> 80093200
A31: 20041195014 | B31: =VLOOKUP(A31,'ESTADOS ESTUDIANTES'!B:L,2,0) -> MUSKUS RINCON ELKIN GABRIEL | C31: =VLOOKUP(A31,'ESTADOS ESTUDIANTES'!B:L,3,0) -> 195 | D31: =VLOOKUP(A31,'ESTADOS ESTUDIANTES'!B:L,4,0) -> MAE. EN CIENCIAS DE LA INF. Y LAS COMUNICACIONES ENFASIS EN TELEINF. | E31: =VLOOKUP(A31,'ESTADOS ESTUDIANTES'!B:L,5,0) -> X | F31: =VLOOKUP(E31,Listas!B1:C1004,2,0) -> EXCLUIDO | G31: =VLOOKUP(A31,'ESTADOS ESTUDIANTES'!B:L,7,0) -> NO REGISTRA | H31: =VLOOKUP(A31,'ESTADOS ESTUDIANTES'!B:L,8,0) -> 0 | I31: =VLOOKUP(A31,'ESTADOS ESTUDIANTES'!B:L,9,0) -> 0 | J31: =VLOOKUP(A31,'ESTADOS ESTUDIANTES'!B:L,10,0) -> CC | K31: =VLOOKUP(A31,'ESTADOS ESTUDIANTES'!B:L,11,0) -> 80021637
A32: 20041195015 | B32: =VLOOKUP(A32,'ESTADOS ESTUDIANTES'!B:L,2,0) -> PAVA DIAZ ROBERTO ALBEIRO | C32: =VLOOKUP(A32,'ESTADOS ESTUDIANTES'!B:L,3,0) -> 195 | D32: =VLOOKUP(A32,'ESTADOS ESTUDIANTES'!B:L,4,0) -> MAE. EN CIENCIAS DE LA INF. Y LAS COMUNICACIONES ENFASIS EN TELEINF. | E32: =VLOOKUP(A32,'ESTADOS ESTUDIANTES'!B:L,5,0) -> X | F32: =VLOOKUP(E32,Listas!B1:C1004,2,0) -> EXCLUIDO | G32: =VLOOKUP(A32,'ESTADOS ESTUDIANTES'!B:L,7,0) -> NO REGISTRA | H32: =VLOOKUP(A32,'ESTADOS ESTUDIANTES'!B:L,8,0) -> 0 | I32: =VLOOKUP(A32,'ESTADOS ESTUDIANTES'!B:L,9,0) -> 0 | J32: =VLOOKUP(A32,'ESTADOS ESTUDIANTES'!B:L,10,0) -> CC | K32: =VLOOKUP(A32,'ESTADOS ESTUDIANTES'!B:L,11,0) -> 79943556
A33: 20041195016 | B33: =VLOOKUP(A33,'ESTADOS ESTUDIANTES'!B:L,2,0) -> PENA SALGADO PIERRE AUGUSTO | C33: =VLOOKUP(A33,'ESTADOS ESTUDIANTES'!B:L,3,0) -> 195 | D33: =VLOOKUP(A33,'ESTADOS ESTUDIANTES'!B:L,4,0) -> MAE. EN CIENCIAS DE LA INF. Y LAS COMUNICACIONES ENFASIS EN TELEINF. | E33: =VLOOKUP(A33,'ESTADOS ESTUDIANTES'!B:L,5,0) -> I | F33: =VLOOKUP(E33,Listas!B1:C1004,2,0) -> INACTIVO | G33: =VLOOKUP(A33,'ESTADOS ESTUDIANTES'!B:L,7,0) -> NO REGISTRA | H33: =VLOOKUP(A33,'ESTADOS ESTUDIANTES'!B:L,8,0) -> 0 | I33: =VLOOKUP(A33,'ESTADOS ESTUDIANTES'!B:L,9,0) -> 0 | J33: =VLOOKUP(A33,'ESTADOS ESTUDIANTES'!B:L,10,0) -> CC | K33: =VLOOKUP(A33,'ESTADOS ESTUDIANTES'!B:L,11,0) -> 78674082
A34: 20041195017 | B34: =VLOOKUP(A34,'ESTADOS ESTUDIANTES'!B:L,2,0) -> PUENTES PARAMO RAFAEL MAURICIO | C34: =VLOOKUP(A34,'ESTADOS ESTUDIANTES'!B:L,3,0) -> 195 | D34: =VLOOKUP(A34,'ESTADOS ESTUDIANTES'!B:L,4,0) -> MAE. EN CIENCIAS DE LA INF. Y LAS COMUNICACIONES ENFASIS EN TELEINF. | E34: =VLOOKUP(A34,'ESTADOS ESTUDIANTES'!B:L,5,0) -> X | F34: =VLOOKUP(E34,Listas!B1:C1004,2,0) -> EXCLUIDO | G34: =VLOOKUP(A34,'ESTADOS ESTUDIANTES'!B:L,7,0) -> NO REGISTRA | H34: =VLOOKUP(A34,'ESTADOS ESTUDIANTES'!B:L,8,0) -> rmpuentesp@correo.udistrital.edu.co | I34: =VLOOKUP(A34,'ESTADOS ESTUDIANTES'!B:L,9,0) -> rpuentes2000@gmail.com | J34: =VLOOKUP(A34,'ESTADOS ESTUDIANTES'!B:L,10,0) -> CC | K34: =VLOOKUP(A34,'ESTADOS ESTUDIANTES'!B:L,11,0) -> 79137742
A35: 20041195018 | B35: =VLOOKUP(A35,'ESTADOS ESTUDIANTES'!B:L,2,0) -> TRIANA PERDOMO FABIO ALEXIS | C35: =VLOOKUP(A35,'ESTADOS ESTUDIANTES'!B:L,3,0) -> 195 | D35: =VLOOKUP(A35,'ESTADOS ESTUDIANTES'!B:L,4,0) -> MAE. EN CIENCIAS DE LA INF. Y LAS COMUNICACIONES ENFASIS EN TELEINF. | E35: =VLOOKUP(A35,'ESTADOS ESTUDIANTES'!B:L,5,0) -> E | F35: =VLOOKUP(E35,Listas!B1:C1004,2,0) -> EGRESADO | G35: =VLOOKUP(A35,'ESTADOS ESTUDIANTES'!B:L,7,0) -> NO REGISTRA | H35: =VLOOKUP(A35,'ESTADOS ESTUDIANTES'!B:L,8,0) -> fatrianap@correo.udistrital.edu.co | I35: =VLOOKUP(A35,'ESTADOS ESTUDIANTES'!B:L,9,0) -> trianafp@gmail.com | J35: =VLOOKUP(A35,'ESTADOS ESTUDIANTES'!B:L,10,0) -> CC | K35: =VLOOKUP(A35,'ESTADOS ESTUDIANTES'!B:L,11,0) -> 80084469
A36: 20041195019 | B36: =VLOOKUP(A36,'ESTADOS ESTUDIANTES'!B:L,2,0) -> URBANO CHAVES DIEGO FERNANDO | C36: =VLOOKUP(A36,'ESTADOS ESTUDIANTES'!B:L,3,0) -> 195 | D36: =VLOOKUP(A36,'ESTADOS ESTUDIANTES'!B:L,4,0) -> MAE. EN CIENCIAS DE LA INF. Y LAS COMUNICACIONES ENFASIS EN TELEINF. | E36: =VLOOKUP(A36,'ESTADOS ESTUDIANTES'!B:L,5,0) -> E | F36: =VLOOKUP(E36,Listas!B1:C1004,2,0) -> EGRESADO | G36: =VLOOKUP(A36,'ESTADOS ESTUDIANTES'!B:L,7,0) -> NO REGISTRA | H36: =VLOOKUP(A36,'ESTADOS ESTUDIANTES'!B:L,8,0) -> dfurbanoc@udistrital.edu.co | I36: =VLOOKUP(A36,'ESTADOS ESTUDIANTES'!B:L,9,0) -> diego.urbano@gmail.com | J36: =VLOOKUP(A36,'ESTADOS ESTUDIANTES'!B:L,10,0) -> CC | K36: =VLOOKUP(A36,'ESTADOS ESTUDIANTES'!B:L,11,0) -> 79965521
A37: 20041195020 | B37: =VLOOKUP(A37,'ESTADOS ESTUDIANTES'!B:L,2,0) -> VARGAS ROJAS HUBER ALVARO | C37: =VLOOKUP(A37,'ESTADOS ESTUDIANTES'!B:L,3,0) -> 195 | D37: =VLOOKUP(A37,'ESTADOS ESTUDIANTES'!B:L,4,0) -> MAE. EN CIENCIAS DE LA INF. Y LAS COMUNICACIONES ENFASIS EN TELEINF. | E37: =VLOOKUP(A37,'ESTADOS ESTUDIANTES'!B:L,5,0) -> I | F37: =VLOOKUP(E37,Listas!B1:C1004,2,0) -> INACTIVO | G37: =VLOOKUP(A37,'ESTADOS ESTUDIANTES'!B:L,7,0) -> NO REGISTRA | H37: =VLOOKUP(A37,'ESTADOS ESTUDIANTES'!B:L,8,0) -> havargasr@correo.udistrital.edu.co | I37: =VLOOKUP(A37,'ESTADOS ESTUDIANTES'!B:L,9,0) -> havargasr@estudiante.udistrital.edu.co | J37: =VLOOKUP(A37,'ESTADOS ESTUDIANTES'!B:L,10,0) -> CC | K37: =VLOOKUP(A37,'ESTADOS ESTUDIANTES'!B:L,11,0) -> 79460726
A38: 20041195021 | B38: =VLOOKUP(A38,'ESTADOS ESTUDIANTES'!B:L,2,0) -> ARDILA NIÑO YAZMIN ALEXANDRA | C38: =VLOOKUP(A38,'ESTADOS ESTUDIANTES'!B:L,3,0) -> 195 | D38: =VLOOKUP(A38,'ESTADOS ESTUDIANTES'!B:L,4,0) -> MAE. EN CIENCIAS DE LA INF. Y LAS COMUNICACIONES ENFASIS EN TELEINF. | E38: =VLOOKUP(A38,'ESTADOS ESTUDIANTES'!B:L,5,0) -> X | F38: =VLOOKUP(E38,Listas!B1:C1004,2,0) -> EXCLUIDO | G38: =VLOOKUP(A38,'ESTADOS ESTUDIANTES'!B:L,7,0) -> NO REGISTRA | H38: =VLOOKUP(A38,'ESTADOS ESTUDIANTES'!B:L,8,0) -> yaardilan@udistrital.edu.co | I38: =VLOOKUP(A38,'ESTADOS ESTUDIANTES'!B:L,9,0) -> yaardilan@estudiante.udistrital.edu.co | J38: =VLOOKUP(A38,'ESTADOS ESTUDIANTES'!B:L,10,0) -> CC | K38: =VLOOKUP(A38,'ESTADOS ESTUDIANTES'!B:L,11,0) -> 52530310
A39: 20041195022 | B39: =VLOOKUP(A39,'ESTADOS ESTUDIANTES'!B:L,2,0) -> DIEZ JIMENEZ GABRIEL HORACIO | C39: =VLOOKUP(A39,'ESTADOS ESTUDIANTES'!B:L,3,0) -> 195 | D39: =VLOOKUP(A39,'ESTADOS ESTUDIANTES'!B:L,4,0) -> MAE. EN CIENCIAS DE LA INF. Y LAS COMUNICACIONES ENFASIS EN TELEINF. | E39: =VLOOKUP(A39,'ESTADOS ESTUDIANTES'!B:L,5,0) -> X | F39: =VLOOKUP(E39,Listas!B1:C1004,2,0) -> EXCLUIDO | G39: =VLOOKUP(A39,'ESTADOS ESTUDIANTES'!B:L,7,0) -> NO REGISTRA | H39: =VLOOKUP(A39,'ESTADOS ESTUDIANTES'!B:L,8,0) -> 0 | I39: =VLOOKUP(A39,'ESTADOS ESTUDIANTES'!B:L,9,0) -> 0 | J39: =VLOOKUP(A39,'ESTADOS ESTUDIANTES'!B:L,10,0) -> CC | K39: =VLOOKUP(A39,'ESTADOS ESTUDIANTES'!B:L,11,0) -> 19457291
A40: 20041195023 | B40: =VLOOKUP(A40,'ESTADOS ESTUDIANTES'!B:L,2,0) -> HERRERA BOLIVAR CLAUDIA YANETH | C40: =VLOOKUP(A40,'ESTADOS ESTUDIANTES'!B:L,3,0) -> 195 | D40: =VLOOKUP(A40,'ESTADOS ESTUDIANTES'!B:L,4,0) -> MAE. EN CIENCIAS DE LA INF. Y LAS COMUNICACIONES ENFASIS EN TELEINF. | E40: =VLOOKUP(A40,'ESTADOS ESTUDIANTES'!B:L,5,0) -> X | F40: =VLOOKUP(E40,Listas!B1:C1004,2,0) -> EXCLUIDO | G40: =VLOOKUP(A40,'ESTADOS ESTUDIANTES'!B:L,7,0) -> NO REGISTRA | H40: =VLOOKUP(A40,'ESTADOS ESTUDIANTES'!B:L,8,0) -> cyherrerab@correo.udistrital.edu.co | I40: =VLOOKUP(A40,'ESTADOS ESTUDIANTES'!B:L,9,0) -> cyherrerab@estudiante.udistrital.edu.co | J40: =VLOOKUP(A40,'ESTADOS ESTUDIANTES'!B:L,10,0) -> CC | K40: =VLOOKUP(A40,'ESTADOS ESTUDIANTES'!B:L,11,0) -> 52228374
A41: 20041195024 | B41: =VLOOKUP(A41,'ESTADOS ESTUDIANTES'!B:L,2,0) -> MONTENEGRO NARVAEZ CARLOS E. | C41: =VLOOKUP(A41,'ESTADOS ESTUDIANTES'!B:L,3,0) -> 195 | D41: =VLOOKUP(A41,'ESTADOS ESTUDIANTES'!B:L,4,0) -> MAE. EN CIENCIAS DE LA INF. Y LAS COMUNICACIONES ENFASIS EN TELEINF. | E41: =VLOOKUP(A41,'ESTADOS ESTUDIANTES'!B:L,5,0) -> X | F41: =VLOOKUP(E41,Listas!B1:C1004,2,0) -> EXCLUIDO | G41: =VLOOKUP(A41,'ESTADOS ESTUDIANTES'!B:L,7,0) -> NO REGISTRA | H41: =VLOOKUP(A41,'ESTADOS ESTUDIANTES'!B:L,8,0) -> 0 | I41: =VLOOKUP(A41,'ESTADOS ESTUDIANTES'!B:L,9,0) -> 0 | J41: =VLOOKUP(A41,'ESTADOS ESTUDIANTES'!B:L,10,0) -> CC | K41: =VLOOKUP(A41,'ESTADOS ESTUDIANTES'!B:L,11,0) -> 98384496
A42: 20041195025 | B42: =VLOOKUP(A42,'ESTADOS ESTUDIANTES'!B:L,2,0) -> OLAYA ALDANA SHEYLA BELEN | C42: =VLOOKUP(A42,'ESTADOS ESTUDIANTES'!B:L,3,0) -> 195 | D42: =VLOOKUP(A42,'ESTADOS ESTUDIANTES'!B:L,4,0) -> MAE. EN CIENCIAS DE LA INF. Y LAS COMUNICACIONES ENFASIS EN TELEINF. | E42: =VLOOKUP(A42,'ESTADOS ESTUDIANTES'!B:L,5,0) -> I | F42: =VLOOKUP(E42,Listas!B1:C1004,2,0) -> INACTIVO | G42: =VLOOKUP(A42,'ESTADOS ESTUDIANTES'!B:L,7,0) -> NO REGISTRA | H42: =VLOOKUP(A42,'ESTADOS ESTUDIANTES'!B:L,8,0) -> 0 | I42: =VLOOKUP(A42,'ESTADOS ESTUDIANTES'!B:L,9,0) -> 0 | J42: =VLOOKUP(A42,'ESTADOS ESTUDIANTES'!B:L,10,0) -> CC | K42: =VLOOKUP(A42,'ESTADOS ESTUDIANTES'!B:L,11,0) -> 36069422
A43: 20041195026 | B43: =VLOOKUP(A43,'ESTADOS ESTUDIANTES'!B:L,2,0) -> SANCHEZ CASTILLO CESAR A. | C43: =VLOOKUP(A43,'ESTADOS ESTUDIANTES'!B:L,3,0) -> 195 | D43: =VLOOKUP(A43,'ESTADOS ESTUDIANTES'!B:L,4,0) -> MAE. EN CIENCIAS DE LA INF. Y LAS COMUNICACIONES ENFASIS EN TELEINF. | E43: =VLOOKUP(A43,'ESTADOS ESTUDIANTES'!B:L,5,0) -> X | F43: =VLOOKUP(E43,Listas!B1:C1004,2,0) -> EXCLUIDO | G43: =VLOOKUP(A43,'ESTADOS ESTUDIANTES'!B:L,7,0) -> NO REGISTRA | H43: =VLOOKUP(A43,'ESTADOS ESTUDIANTES'!B:L,8,0) -> 0 | I43: =VLOOKUP(A43,'ESTADOS ESTUDIANTES'!B:L,9,0) -> 0 | J43: =VLOOKUP(A43,'ESTADOS ESTUDIANTES'!B:L,10,0) -> CC | K43: =VLOOKUP(A43,'ESTADOS ESTUDIANTES'!B:L,11,0) -> 79650761
A44: 20041195027 | B44: =VLOOKUP(A44,'ESTADOS ESTUDIANTES'!B:L,2,0) -> CASTAÑEDA PARRA JAVIER ALFONSO | C44: =VLOOKUP(A44,'ESTADOS ESTUDIANTES'!B:L,3,0) -> 195 | D44: =VLOOKUP(A44,'ESTADOS ESTUDIANTES'!B:L,4,0) -> MAE. EN CIENCIAS DE LA INF. Y LAS COMUNICACIONES ENFASIS EN TELEINF. | E44: =VLOOKUP(A44,'ESTADOS ESTUDIANTES'!B:L,5,0) -> E | F44: =VLOOKUP(E44,Listas!B1:C1004,2,0) -> EGRESADO | G44: =VLOOKUP(A44,'ESTADOS ESTUDIANTES'!B:L,7,0) -> NO REGISTRA | H44: =VLOOKUP(A44,'ESTADOS ESTUDIANTES'!B:L,8,0) -> jacastanedap@correo.udistrital.edu.co | I44: =VLOOKUP(A44,'ESTADOS ESTUDIANTES'!B:L,9,0) -> jacastanedap@estudiante.udistrital.edu.co | J44: =VLOOKUP(A44,'ESTADOS ESTUDIANTES'!B:L,10,0) -> CC | K44: =VLOOKUP(A44,'ESTADOS ESTUDIANTES'!B:L,11,0) -> 79363308
A45: 20041195028 | B45: =VLOOKUP(A45,'ESTADOS ESTUDIANTES'!B:L,2,0) -> LOPEZ CHAVEZ HANS IGOR | C45: =VLOOKUP(A45,'ESTADOS ESTUDIANTES'!B:L,3,0) -> 195 | D45: =VLOOKUP(A45,'ESTADOS ESTUDIANTES'!B:L,4,0) -> MAE. EN CIENCIAS DE LA INF. Y LAS COMUNICACIONES ENFASIS EN TELEINF. | E45: =VLOOKUP(A45,'ESTADOS ESTUDIANTES'!B:L,5,0) -> E | F45: =VLOOKUP(E45,Listas!B1:C1004,2,0) -> EGRESADO | G45: =VLOOKUP(A45,'ESTADOS ESTUDIANTES'!B:L,7,0) -> NO REGISTRA | H45: =VLOOKUP(A45,'ESTADOS ESTUDIANTES'!B:L,8,0) -> hilopezc@correo.udistrital.edu.co | I45: =VLOOKUP(A45,'ESTADOS ESTUDIANTES'!B:L,9,0) -> hanslop@gmail.com | J45: =VLOOKUP(A45,'ESTADOS ESTUDIANTES'!B:L,10,0) -> CC | K45: =VLOOKUP(A45,'ESTADOS ESTUDIANTES'!B:L,11,0) -> 80033827
A46: 20041295001 | B46: =VLOOKUP(A46,'ESTADOS ESTUDIANTES'!B:L,2,0) -> ABDEL AZIZ GALINDO ANIS A. | C46: =VLOOKUP(A46,'ESTADOS ESTUDIANTES'!B:L,3,0) -> 295 | D46: =VLOOKUP(A46,'ESTADOS ESTUDIANTES'!B:L,4,0) -> MAE. EN CIENCIAS DE LA INF. Y LAS COMUNICACIONES ENFASIS EN SIS. INFOR | E46: =VLOOKUP(A46,'ESTADOS ESTUDIANTES'!B:L,5,0) -> X | F46: =VLOOKUP(E46,Listas!B1:C1004,2,0) -> EXCLUIDO | G46: =VLOOKUP(A46,'ESTADOS ESTUDIANTES'!B:L,7,0) -> NO REGISTRA | H46: =VLOOKUP(A46,'ESTADOS ESTUDIANTES'!B:L,8,0) -> 0 | I46: =VLOOKUP(A46,'ESTADOS ESTUDIANTES'!B:L,9,0) -> 0 | J46: =VLOOKUP(A46,'ESTADOS ESTUDIANTES'!B:L,10,0) -> CC | K46: =VLOOKUP(A46,'ESTADOS ESTUDIANTES'!B:L,11,0) -> 79788234
A47: 20041295002 | B47: =VLOOKUP(A47,'ESTADOS ESTUDIANTES'!B:L,2,0) -> CAMARGO MENDOZA JORGE E. | C47: =VLOOKUP(A47,'ESTADOS ESTUDIANTES'!B:L,3,0) -> 295 | D47: =VLOOKUP(A47,'ESTADOS ESTUDIANTES'!B:L,4,0) -> MAE. EN CIENCIAS DE LA INF. Y LAS COMUNICACIONES ENFASIS EN SIS. INFOR | E47: =VLOOKUP(A47,'ESTADOS ESTUDIANTES'!B:L,5,0) -> X | F47: =VLOOKUP(E47,Listas!B1:C1004,2,0) -> EXCLUIDO | G47: =VLOOKUP(A47,'ESTADOS ESTUDIANTES'!B:L,7,0) -> NO REGISTRA | H47: =VLOOKUP(A47,'ESTADOS ESTUDIANTES'!B:L,8,0) -> 0 | I47: =VLOOKUP(A47,'ESTADOS ESTUDIANTES'!B:L,9,0) -> 0 | J47: =VLOOKUP(A47,'ESTADOS ESTUDIANTES'!B:L,10,0) -> CC | K47: =VLOOKUP(A47,'ESTADOS ESTUDIANTES'!B:L,11,0) -> 79755516
A48: 20041295003 | B48: =VLOOKUP(A48,'ESTADOS ESTUDIANTES'!B:L,2,0) -> CANCELADO PACHON JULIO CESAR | C48: =VLOOKUP(A48,'ESTADOS ESTUDIANTES'!B:L,3,0) -> 295 | D48: =VLOOKUP(A48,'ESTADOS ESTUDIANTES'!B:L,4,0) -> MAE. EN CIENCIAS DE LA INF. Y LAS COMUNICACIONES ENFASIS EN SIS. INFOR | E48: =VLOOKUP(A48,'ESTADOS ESTUDIANTES'!B:L,5,0) -> X | F48: =VLOOKUP(E48,Listas!B1:C1004,2,0) -> EXCLUIDO | G48: =VLOOKUP(A48,'ESTADOS ESTUDIANTES'!B:L,7,0) -> NO REGISTRA | H48: =VLOOKUP(A48,'ESTADOS ESTUDIANTES'!B:L,8,0) -> 0 | I48: =VLOOKUP(A48,'ESTADOS ESTUDIANTES'!B:L,9,0) -> 0 | J48: =VLOOKUP(A48,'ESTADOS ESTUDIANTES'!B:L,10,0) -> CC | K48: =VLOOKUP(A48,'ESTADOS ESTUDIANTES'!B:L,11,0) -> 19453135
A49: 20041295004 | B49: =VLOOKUP(A49,'ESTADOS ESTUDIANTES'!B:L,2,0) -> CLAVIJO CUINEME LUIS ALBERTO | C49: =VLOOKUP(A49,'ESTADOS ESTUDIANTES'!B:L,3,0) -> 295 | D49: =VLOOKUP(A49,'ESTADOS ESTUDIANTES'!B:L,4,0) -> MAE. EN CIENCIAS DE LA INF. Y LAS COMUNICACIONES ENFASIS EN SIS. INFOR | E49: =VLOOKUP(A49,'ESTADOS ESTUDIANTES'!B:L,5,0) -> E | F49: =VLOOKUP(E49,Listas!B1:C1004,2,0) -> EGRESADO | G49: =VLOOKUP(A49,'ESTADOS ESTUDIANTES'!B:L,7,0) -> NO REGISTRA | H49: =VLOOKUP(A49,'ESTADOS ESTUDIANTES'!B:L,8,0) -> laclavijog@correo.udistrital.edu.co | I49: =VLOOKUP(A49,'ESTADOS ESTUDIANTES'!B:L,9,0) -> laclavijo@gmail.com | J49: =VLOOKUP(A49,'ESTADOS ESTUDIANTES'!B:L,10,0) -> CC | K49: =VLOOKUP(A49,'ESTADOS ESTUDIANTES'!B:L,11,0) -> 19458790
A50: 20041295005 | B50: =VLOOKUP(A50,'ESTADOS ESTUDIANTES'!B:L,2,0) -> DIAZ CABRERA GLORIA MERCEDES | C50: =VLOOKUP(A50,'ESTADOS ESTUDIANTES'!B:L,3,0) -> 295 | D50: =VLOOKUP(A50,'ESTADOS ESTUDIANTES'!B:L,4,0) -> MAE. EN CIENCIAS DE LA INF. Y LAS COMUNICACIONES ENFASIS EN SIS. INFOR | E50: =VLOOKUP(A50,'ESTADOS ESTUDIANTES'!B:L,5,0) -> X | F50: =VLOOKUP(E50,Listas!B1:C1004,2,0) -> EXCLUIDO | G50: =VLOOKUP(A50,'ESTADOS ESTUDIANTES'!B:L,7,0) -> NO REGISTRA | H50: =VLOOKUP(A50,'ESTADOS ESTUDIANTES'!B:L,8,0) -> gmdiazc@correo.udistrital.edu.co | I50: =VLOOKUP(A50,'ESTADOS ESTUDIANTES'!B:L,9,0) -> gmdiazc@estudiante.udistrital.edu.co | J50: =VLOOKUP(A50,'ESTADOS ESTUDIANTES'!B:L,10,0) -> CC | K50: =VLOOKUP(A50,'ESTADOS ESTUDIANTES'!B:L,11,0) -> 52433428
A51: 20041295006 | B51: =VLOOKUP(A51,'ESTADOS ESTUDIANTES'!B:L,2,0) -> ESPINOSA SALAZAR EDNA CECILIA | C51: =VLOOKUP(A51,'ESTADOS ESTUDIANTES'!B:L,3,0) -> 295 | D51: =VLOOKUP(A51,'ESTADOS ESTUDIANTES'!B:L,4,0) -> MAE. EN CIENCIAS DE LA INF. Y LAS COMUNICACIONES ENFASIS EN SIS. INFOR | E51: =VLOOKUP(A51,'ESTADOS ESTUDIANTES'!B:L,5,0) -> X | F51: =VLOOKUP(E51,Listas!B1:C1004,2,0) -> EXCLUIDO | G51: =VLOOKUP(A51,'ESTADOS ESTUDIANTES'!B:L,7,0) -> NO REGISTRA | H51: =VLOOKUP(A51,'ESTADOS ESTUDIANTES'!B:L,8,0) -> ecespinosas@correo.udistrital.edu.co | I51: =VLOOKUP(A51,'ESTADOS ESTUDIANTES'!B:L,9,0) -> ecespinosa@gmail.com | J51: =VLOOKUP(A51,'ESTADOS ESTUDIANTES'!B:L,10,0) -> CC | K51: =VLOOKUP(A51,'ESTADOS ESTUDIANTES'!B:L,11,0) -> 32785853
A52: 20041295007 | B52: =VLOOKUP(A52,'ESTADOS ESTUDIANTES'!B:L,2,0) -> FLOREZ FERNANDEZ HECTOR A. | C52: =VLOOKUP(A52,'ESTADOS ESTUDIANTES'!B:L,3,0) -> 295 | D52: =VLOOKUP(A52,'ESTADOS ESTUDIANTES'!B:L,4,0) -> MAE. EN CIENCIAS DE LA INF. Y LAS COMUNICACIONES ENFASIS EN SIS. INFOR | E52: =VLOOKUP(A52,'ESTADOS ESTUDIANTES'!B:L,5,0) -> E | F52: =VLOOKUP(E52,Listas!B1:C1004,2,0) -> EGRESADO | G52: =VLOOKUP(A52,'ESTADOS ESTUDIANTES'!B:L,7,0) -> NO REGISTRA | H52: =VLOOKUP(A52,'ESTADOS ESTUDIANTES'!B:L,8,0) -> haflorezf@correo.udistrital.edu.co | I52: =VLOOKUP(A52,'ESTADOS ESTUDIANTES'!B:L,9,0) -> hectorarturo@yahoo.com | J52: =VLOOKUP(A52,'ESTADOS ESTUDIANTES'!B:L,10,0) -> CC | K52: =VLOOKUP(A52,'ESTADOS ESTUDIANTES'!B:L,11,0) -> 80180279
A53: 20041295008 | B53: =VLOOKUP(A53,'ESTADOS ESTUDIANTES'!B:L,2,0) -> FRANCO HELVAR RODOLFO | C53: =VLOOKUP(A53,'ESTADOS ESTUDIANTES'!B:L,3,0) -> 295 | D53: =VLOOKUP(A53,'ESTADOS ESTUDIANTES'!B:L,4,0) -> MAE. EN CIENCIAS DE LA INF. Y LAS COMUNICACIONES ENFASIS EN SIS. INFOR | E53: =VLOOKUP(A53,'ESTADOS ESTUDIANTES'!B:L,5,0) -> X | F53: =VLOOKUP(E53,Listas!B1:C1004,2,0) -> EXCLUIDO | G53: =VLOOKUP(A53,'ESTADOS ESTUDIANTES'!B:L,7,0) -> NO REGISTRA | H53: =VLOOKUP(A53,'ESTADOS ESTUDIANTES'!B:L,8,0) -> 0 | I53: =VLOOKUP(A53,'ESTADOS ESTUDIANTES'!B:L,9,0) -> 0 | J53: =VLOOKUP(A53,'ESTADOS ESTUDIANTES'!B:L,10,0) -> CC | K53: =VLOOKUP(A53,'ESTADOS ESTUDIANTES'!B:L,11,0) -> 79601302
A54: 20041295009 | B54: =VLOOKUP(A54,'ESTADOS ESTUDIANTES'!B:L,2,0) -> GOMEZ MORA MILLER | C54: =VLOOKUP(A54,'ESTADOS ESTUDIANTES'!B:L,3,0) -> 295 | D54: =VLOOKUP(A54,'ESTADOS ESTUDIANTES'!B:L,4,0) -> MAE. EN CIENCIAS DE LA INF. Y LAS COMUNICACIONES ENFASIS EN SIS. INFOR | E54: =VLOOKUP(A54,'ESTADOS ESTUDIANTES'!B:L,5,0) -> E | F54: =VLOOKUP(E54,Listas!B1:C1004,2,0) -> EGRESADO | G54: =VLOOKUP(A54,'ESTADOS ESTUDIANTES'!B:L,7,0) -> NO REGISTRA | H54: =VLOOKUP(A54,'ESTADOS ESTUDIANTES'!B:L,8,0) -> migomezm@correo.udistrital.edu.co | I54: =VLOOKUP(A54,'ESTADOS ESTUDIANTES'!B:L,9,0) -> migomezm@estudiante.udistrital.edu.co | J54: =VLOOKUP(A54,'ESTADOS ESTUDIANTES'!B:L,10,0) -> CC | K54: =VLOOKUP(A54,'ESTADOS ESTUDIANTES'!B:L,11,0) -> 79520182
A55: 20041295010 | B55: =VLOOKUP(A55,'ESTADOS ESTUDIANTES'!B:L,2,0) -> GUEVARA BOLAÑOS JUAN CARLOS | C55: =VLOOKUP(A55,'ESTADOS ESTUDIANTES'!B:L,3,0) -> 295 | D55: =VLOOKUP(A55,'ESTADOS ESTUDIANTES'!B:L,4,0) -> MAE. EN CIENCIAS DE LA INF. Y LAS COMUNICACIONES ENFASIS EN SIS. INFOR | E55: =VLOOKUP(A55,'ESTADOS ESTUDIANTES'!B:L,5,0) -> E | F55: =VLOOKUP(E55,Listas!B1:C1004,2,0) -> EGRESADO | G55: =VLOOKUP(A55,'ESTADOS ESTUDIANTES'!B:L,7,0) -> NO REGISTRA | H55: =VLOOKUP(A55,'ESTADOS ESTUDIANTES'!B:L,8,0) -> jcguevarab@correo.udistrital.edu.co | I55: =VLOOKUP(A55,'ESTADOS ESTUDIANTES'!B:L,9,0) -> jcguevarab@udistrital.edu.co | J55: =VLOOKUP(A55,'ESTADOS ESTUDIANTES'!B:L,10,0) -> CC | K55: =VLOOKUP(A55,'ESTADOS ESTUDIANTES'!B:L,11,0) -> 79422893
A56: 20041295011 | B56: =VLOOKUP(A56,'ESTADOS ESTUDIANTES'!B:L,2,0) -> MARTINEZ GONZALEZ JOSE M | C56: =VLOOKUP(A56,'ESTADOS ESTUDIANTES'!B:L,3,0) -> 295 | D56: =VLOOKUP(A56,'ESTADOS ESTUDIANTES'!B:L,4,0) -> MAE. EN CIENCIAS DE LA INF. Y LAS COMUNICACIONES ENFASIS EN SIS. INFOR | E56: =VLOOKUP(A56,'ESTADOS ESTUDIANTES'!B:L,5,0) -> X | F56: =VLOOKUP(E56,Listas!B1:C1004,2,0) -> EXCLUIDO | G56: =VLOOKUP(A56,'ESTADOS ESTUDIANTES'!B:L,7,0) -> NO REGISTRA | H56: =VLOOKUP(A56,'ESTADOS ESTUDIANTES'!B:L,8,0) -> jmmartinezg@correo.udistrital.edu.co | I56: =VLOOKUP(A56,'ESTADOS ESTUDIANTES'!B:L,9,0) -> jmmartinezg@estudiante.udistrital.edu.co | J56: =VLOOKUP(A56,'ESTADOS ESTUDIANTES'!B:L,10,0) -> CC | K56: =VLOOKUP(A56,'ESTADOS ESTUDIANTES'!B:L,11,0) -> 79715018
A57: 20041295012 | B57: =VLOOKUP(A57,'ESTADOS ESTUDIANTES'!B:L,2,0) -> MURIEL BEJARANO HERNAN A. | C57: =VLOOKUP(A57,'ESTADOS ESTUDIANTES'!B:L,3,0) -> 295 | D57: =VLOOKUP(A57,'ESTADOS ESTUDIANTES'!B:L,4,0) -> MAE. EN CIENCIAS DE LA INF. Y LAS COMUNICACIONES ENFASIS EN SIS. INFOR | E57: =VLOOKUP(A57,'ESTADOS ESTUDIANTES'!B:L,5,0) -> X | F57: =VLOOKUP(E57,Listas!B1:C1004,2,0) -> EXCLUIDO | G57: =VLOOKUP(A57,'ESTADOS ESTUDIANTES'!B:L,7,0) -> NO REGISTRA | H57: =VLOOKUP(A57,'ESTADOS ESTUDIANTES'!B:L,8,0) -> hamurielb@correo.udistrital.edu.co | I57: =VLOOKUP(A57,'ESTADOS ESTUDIANTES'!B:L,9,0) -> hamurielb@estudiante.udistrital.edu.co | J57: =VLOOKUP(A57,'ESTADOS ESTUDIANTES'!B:L,10,0) -> CC | K57: =VLOOKUP(A57,'ESTADOS ESTUDIANTES'!B:L,11,0) -> 79041180
A58: 20041295013 | B58: =VLOOKUP(A58,'ESTADOS ESTUDIANTES'!B:L,2,0) -> OSMA RODRIGUEZ JAIR EDUARDO | C58: =VLOOKUP(A58,'ESTADOS ESTUDIANTES'!B:L,3,0) -> 295 | D58: =VLOOKUP(A58,'ESTADOS ESTUDIANTES'!B:L,4,0) -> MAE. EN CIENCIAS DE LA INF. Y LAS COMUNICACIONES ENFASIS EN SIS. INFOR | E58: =VLOOKUP(A58,'ESTADOS ESTUDIANTES'!B:L,5,0) -> E | F58: =VLOOKUP(E58,Listas!B1:C1004,2,0) -> EGRESADO | G58: =VLOOKUP(A58,'ESTADOS ESTUDIANTES'!B:L,7,0) -> NO REGISTRA | H58: =VLOOKUP(A58,'ESTADOS ESTUDIANTES'!B:L,8,0) -> jaeosmar@correo.udistrital.edu.co | I58: =VLOOKUP(A58,'ESTADOS ESTUDIANTES'!B:L,9,0) -> josma@007mundo.com | J58: =VLOOKUP(A58,'ESTADOS ESTUDIANTES'!B:L,10,0) -> CC | K58: =VLOOKUP(A58,'ESTADOS ESTUDIANTES'!B:L,11,0) -> 79380285
A59: 20041295014 | B59: =VLOOKUP(A59,'ESTADOS ESTUDIANTES'!B:L,2,0) -> OVALLE PULIDO OSCAR IVAN | C59: =VLOOKUP(A59,'ESTADOS ESTUDIANTES'!B:L,3,0) -> 295 | D59: =VLOOKUP(A59,'ESTADOS ESTUDIANTES'!B:L,4,0) -> MAE. EN CIENCIAS DE LA INF. Y LAS COMUNICACIONES ENFASIS EN SIS. INFOR | E59: =VLOOKUP(A59,'ESTADOS ESTUDIANTES'!B:L,5,0) -> X | F59: =VLOOKUP(E59,Listas!B1:C1004,2,0) -> EXCLUIDO | G59: =VLOOKUP(A59,'ESTADOS ESTUDIANTES'!B:L,7,0) -> NO REGISTRA | H59: =VLOOKUP(A59,'ESTADOS ESTUDIANTES'!B:L,8,0) -> 0 | I59: =VLOOKUP(A59,'ESTADOS ESTUDIANTES'!B:L,9,0) -> 0 | J59: =VLOOKUP(A59,'ESTADOS ESTUDIANTES'!B:L,10,0) -> CC | K59: =VLOOKUP(A59,'ESTADOS ESTUDIANTES'!B:L,11,0) -> 79127925
A60: 20041295015 | B60: =VLOOKUP(A60,'ESTADOS ESTUDIANTES'!B:L,2,0) -> PADILLA GIL LUZ MYRIAM | C60: =VLOOKUP(A60,'ESTADOS ESTUDIANTES'!B:L,3,0) -> 295 | D60: =VLOOKUP(A60,'ESTADOS ESTUDIANTES'!B:L,4,0) -> MAE. EN CIENCIAS DE LA INF. Y LAS COMUNICACIONES ENFASIS EN SIS. INFOR | E60: =VLOOKUP(A60,'ESTADOS ESTUDIANTES'!B:L,5,0) -> X | F60: =VLOOKUP(E60,Listas!B1:C1004,2,0) -> EXCLUIDO | G60: =VLOOKUP(A60,'ESTADOS ESTUDIANTES'!B:L,7,0) -> NO REGISTRA | H60: =VLOOKUP(A60,'ESTADOS ESTUDIANTES'!B:L,8,0) -> lmpadillag@correo.udistrital.edu.co | I60: =VLOOKUP(A60,'ESTADOS ESTUDIANTES'!B:L,9,0) -> myriampadilla@yahoo.es | J60: =VLOOKUP(A60,'ESTADOS ESTUDIANTES'!B:L,10,0) -> CC | K60: =VLOOKUP(A60,'ESTADOS ESTUDIANTES'!B:L,11,0) -> 51749112
A61: 20041295016 | B61: =VLOOKUP(A61,'ESTADOS ESTUDIANTES'!B:L,2,0) -> RODRIGUEZ GUERRERO ROCIO | C61: =VLOOKUP(A61,'ESTADOS ESTUDIANTES'!B:L,3,0) -> 295 | D61: =VLOOKUP(A61,'ESTADOS ESTUDIANTES'!B:L,4,0) -> MAE. EN CIENCIAS DE LA INF. Y LAS COMUNICACIONES ENFASIS EN SIS. INFOR | E61: =VLOOKUP(A61,'ESTADOS ESTUDIANTES'!B:L,5,0) -> X | F61: =VLOOKUP(E61,Listas!B1:C1004,2,0) -> EXCLUIDO | G61: =VLOOKUP(A61,'ESTADOS ESTUDIANTES'!B:L,7,0) -> NO REGISTRA | H61: =VLOOKUP(A61,'ESTADOS ESTUDIANTES'!B:L,8,0) -> 0 | I61: =VLOOKUP(A61,'ESTADOS ESTUDIANTES'!B:L,9,0) -> 0 | J61: =VLOOKUP(A61,'ESTADOS ESTUDIANTES'!B:L,10,0) -> CC | K61: =VLOOKUP(A61,'ESTADOS ESTUDIANTES'!B:L,11,0) -> 52369898
A62: 20041295017 | B62: =VLOOKUP(A62,'ESTADOS ESTUDIANTES'!B:L,2,0) -> SANCHEZ IPIA ALBER HAMERSSON | C62: =VLOOKUP(A62,'ESTADOS ESTUDIANTES'!B:L,3,0) -> 295 | D62: =VLOOKUP(A62,'ESTADOS ESTUDIANTES'!B:L,4,0) -> MAE. EN CIENCIAS DE LA INF. Y LAS COMUNICACIONES ENFASIS EN SIS. INFOR | E62: =VLOOKUP(A62,'ESTADOS ESTUDIANTES'!B:L,5,0) -> E | F62: =VLOOKUP(E62,Listas!B1:C1004,2,0) -> EGRESADO | G62: =VLOOKUP(A62,'ESTADOS ESTUDIANTES'!B:L,7,0) -> NO REGISTRA | H62: =VLOOKUP(A62,'ESTADOS ESTUDIANTES'!B:L,8,0) -> ahsanchezi@correo.udistrital.edu.co | I62: =VLOOKUP(A62,'ESTADOS ESTUDIANTES'!B:L,9,0) -> ahsanchezi@estudiante.udistrital.edu.co | J62: =VLOOKUP(A62,'ESTADOS ESTUDIANTES'!B:L,10,0) -> CC | K62: =VLOOKUP(A62,'ESTADOS ESTUDIANTES'!B:L,11,0) -> 79985582
A63: 20041295018 | B63: =VLOOKUP(A63,'ESTADOS ESTUDIANTES'!B:L,2,0) -> SANDOVAL DIAZ RICARDO | C63: =VLOOKUP(A63,'ESTADOS ESTUDIANTES'!B:L,3,0) -> 295 | D63: =VLOOKUP(A63,'ESTADOS ESTUDIANTES'!B:L,4,0) -> MAE. EN CIENCIAS DE LA INF. Y LAS COMUNICACIONES ENFASIS EN SIS. INFOR | E63: =VLOOKUP(A63,'ESTADOS ESTUDIANTES'!B:L,5,0) -> X | F63: =VLOOKUP(E63,Listas!B1:C1004,2,0) -> EXCLUIDO | G63: =VLOOKUP(A63,'ESTADOS ESTUDIANTES'!B:L,7,0) -> NO REGISTRA | H63: =VLOOKUP(A63,'ESTADOS ESTUDIANTES'!B:L,8,0) -> 0 | I63: =VLOOKUP(A63,'ESTADOS ESTUDIANTES'!B:L,9,0) -> 0 | J63: =VLOOKUP(A63,'ESTADOS ESTUDIANTES'!B:L,10,0) -> CC | K63: =VLOOKUP(A63,'ESTADOS ESTUDIANTES'!B:L,11,0) -> 80016936
A64: 20041295019 | B64: =VLOOKUP(A64,'ESTADOS ESTUDIANTES'!B:L,2,0) -> TORRES FUENTES PEDRO A. | C64: =VLOOKUP(A64,'ESTADOS ESTUDIANTES'!B:L,3,0) -> 295 | D64: =VLOOKUP(A64,'ESTADOS ESTUDIANTES'!B:L,4,0) -> MAE. EN CIENCIAS DE LA INF. Y LAS COMUNICACIONES ENFASIS EN SIS. INFOR | E64: =VLOOKUP(A64,'ESTADOS ESTUDIANTES'!B:L,5,0) -> X | F64: =VLOOKUP(E64,Listas!B1:C1004,2,0) -> EXCLUIDO | G64: =VLOOKUP(A64,'ESTADOS ESTUDIANTES'!B:L,7,0) -> NO REGISTRA | H64: =VLOOKUP(A64,'ESTADOS ESTUDIANTES'!B:L,8,0) -> 0 | I64: =VLOOKUP(A64,'ESTADOS ESTUDIANTES'!B:L,9,0) -> 0 | J64: =VLOOKUP(A64,'ESTADOS ESTUDIANTES'!B:L,10,0) -> CC | K64: =VLOOKUP(A64,'ESTADOS ESTUDIANTES'!B:L,11,0) -> 91298791
A65: 20041295020 | B65: =VLOOKUP(A65,'ESTADOS ESTUDIANTES'!B:L,2,0) -> VELASQUEZ OTALORA JOHN FREDY | C65: =VLOOKUP(A65,'ESTADOS ESTUDIANTES'!B:L,3,0) -> 295 | D65: =VLOOKUP(A65,'ESTADOS ESTUDIANTES'!B:L,4,0) -> MAE. EN CIENCIAS DE LA INF. Y LAS COMUNICACIONES ENFASIS EN SIS. INFOR | E65: =VLOOKUP(A65,'ESTADOS ESTUDIANTES'!B:L,5,0) -> X | F65: =VLOOKUP(E65,Listas!B1:C1004,2,0) -> EXCLUIDO | G65: =VLOOKUP(A65,'ESTADOS ESTUDIANTES'!B:L,7,0) -> NO REGISTRA | H65: =VLOOKUP(A65,'ESTADOS ESTUDIANTES'!B:L,8,0) -> jfvelasquezo@correo.udistrital.edu.co | I65: =VLOOKUP(A65,'ESTADOS ESTUDIANTES'!B:L,9,0) -> jfvelasquezo@estudiante.udistrital.edu.co | J65: =VLOOKUP(A65,'ESTADOS ESTUDIANTES'!B:L,10,0) -> CC | K65: =VLOOKUP(A65,'ESTADOS ESTUDIANTES'!B:L,11,0) -> 11187517
A66: 20041295021 | B66: =VLOOKUP(A66,'ESTADOS ESTUDIANTES'!B:L,2,0) -> BARRERA GONZALEZ JAIRO | C66: =VLOOKUP(A66,'ESTADOS ESTUDIANTES'!B:L,3,0) -> 295 | D66: =VLOOKUP(A66,'ESTADOS ESTUDIANTES'!B:L,4,0) -> MAE. EN CIENCIAS DE LA INF. Y LAS COMUNICACIONES ENFASIS EN SIS. INFOR | E66: =VLOOKUP(A66,'ESTADOS ESTUDIANTES'!B:L,5,0) -> X | F66: =VLOOKUP(E66,Listas!B1:C1004,2,0) -> EXCLUIDO | G66: =VLOOKUP(A66,'ESTADOS ESTUDIANTES'!B:L,7,0) -> NO REGISTRA | H66: =VLOOKUP(A66,'ESTADOS ESTUDIANTES'!B:L,8,0) -> 0 | I66: =VLOOKUP(A66,'ESTADOS ESTUDIANTES'!B:L,9,0) -> 0 | J66: =VLOOKUP(A66,'ESTADOS ESTUDIANTES'!B:L,10,0) -> CC | K66: =VLOOKUP(A66,'ESTADOS ESTUDIANTES'!B:L,11,0) -> 91013867
A67: 20041295022 | B67: =VLOOKUP(A67,'ESTADOS ESTUDIANTES'!B:L,2,0) -> BARRERO MORA ANGELICA LORENA | C67: =VLOOKUP(A67,'ESTADOS ESTUDIANTES'!B:L,3,0) -> 295 | D67: =VLOOKUP(A67,'ESTADOS ESTUDIANTES'!B:L,4,0) -> MAE. EN CIENCIAS DE LA INF. Y LAS COMUNICACIONES ENFASIS EN SIS. INFOR | E67: =VLOOKUP(A67,'ESTADOS ESTUDIANTES'!B:L,5,0) -> X | F67: =VLOOKUP(E67,Listas!B1:C1004,2,0) -> EXCLUIDO | G67: =VLOOKUP(A67,'ESTADOS ESTUDIANTES'!B:L,7,0) -> NO REGISTRA | H67: =VLOOKUP(A67,'ESTADOS ESTUDIANTES'!B:L,8,0) -> 0 | I67: =VLOOKUP(A67,'ESTADOS ESTUDIANTES'!B:L,9,0) -> 0 | J67: =VLOOKUP(A67,'ESTADOS ESTUDIANTES'!B:L,10,0) -> CC | K67: =VLOOKUP(A67,'ESTADOS ESTUDIANTES'!B:L,11,0) -> 52429104
A68: 20041295023 | B68: =VLOOKUP(A68,'ESTADOS ESTUDIANTES'!B:L,2,0) -> CABALLERO HERRERA JORGE E. | C68: =VLOOKUP(A68,'ESTADOS ESTUDIANTES'!B:L,3,0) -> 295 | D68: =VLOOKUP(A68,'ESTADOS ESTUDIANTES'!B:L,4,0) -> MAE. EN CIENCIAS DE LA INF. Y LAS COMUNICACIONES ENFASIS EN SIS. INFOR | E68: =VLOOKUP(A68,'ESTADOS ESTUDIANTES'!B:L,5,0) -> X | F68: =VLOOKUP(E68,Listas!B1:C1004,2,0) -> EXCLUIDO | G68: =VLOOKUP(A68,'ESTADOS ESTUDIANTES'!B:L,7,0) -> NO REGISTRA | H68: =VLOOKUP(A68,'ESTADOS ESTUDIANTES'!B:L,8,0) -> 0 | I68: =VLOOKUP(A68,'ESTADOS ESTUDIANTES'!B:L,9,0) -> 0 | J68: =VLOOKUP(A68,'ESTADOS ESTUDIANTES'!B:L,10,0) -> CC | K68: =VLOOKUP(A68,'ESTADOS ESTUDIANTES'!B:L,11,0) -> 79514639
A69: 20041295024 | B69: =VLOOKUP(A69,'ESTADOS ESTUDIANTES'!B:L,2,0) -> PERALTA AMAYA LUIS ALBERTO | C69: =VLOOKUP(A69,'ESTADOS ESTUDIANTES'!B:L,3,0) -> 295 | D69: =VLOOKUP(A69,'ESTADOS ESTUDIANTES'!B:L,4,0) -> MAE. EN CIENCIAS DE LA INF. Y LAS COMUNICACIONES ENFASIS EN SIS. INFOR | E69: =VLOOKUP(A69,'ESTADOS ESTUDIANTES'!B:L,5,0) -> X | F69: =VLOOKUP(E69,Listas!B1:C1004,2,0) -> EXCLUIDO | G69: =VLOOKUP(A69,'ESTADOS ESTUDIANTES'!B:L,7,0) -> NO REGISTRA | H69: =VLOOKUP(A69,'ESTADOS ESTUDIANTES'!B:L,8,0) -> laperaltaa@correo.udistrital.edu.co | I69: =VLOOKUP(A69,'ESTADOS ESTUDIANTES'!B:L,9,0) -> laperaltaa@estudiante.udistrital.edu.co | J69: =VLOOKUP(A69,'ESTADOS ESTUDIANTES'!B:L,10,0) -> CC | K69: =VLOOKUP(A69,'ESTADOS ESTUDIANTES'!B:L,11,0) -> 19422321
A70: 20041295025 | B70: =VLOOKUP(A70,'ESTADOS ESTUDIANTES'!B:L,2,0) -> PINZON NUÑEZ SONIA ALEXANDRA | C70: =VLOOKUP(A70,'ESTADOS ESTUDIANTES'!B:L,3,0) -> 295 | D70: =VLOOKUP(A70,'ESTADOS ESTUDIANTES'!B:L,4,0) -> MAE. EN CIENCIAS DE LA INF. Y LAS COMUNICACIONES ENFASIS EN SIS. INFOR | E70: =VLOOKUP(A70,'ESTADOS ESTUDIANTES'!B:L,5,0) -> E | F70: =VLOOKUP(E70,Listas!B1:C1004,2,0) -> EGRESADO | G70: =VLOOKUP(A70,'ESTADOS ESTUDIANTES'!B:L,7,0) -> 2 | H70: =VLOOKUP(A70,'ESTADOS ESTUDIANTES'!B:L,8,0) -> sapinzonn@correo.udistrital.edu.co | I70: =VLOOKUP(A70,'ESTADOS ESTUDIANTES'!B:L,9,0) -> spinzon@udistrital.edu.co | J70: =VLOOKUP(A70,'ESTADOS ESTUDIANTES'!B:L,10,0) -> CC | K70: =VLOOKUP(A70,'ESTADOS ESTUDIANTES'!B:L,11,0) -> 52204302
A71: 20041295026 | B71: =VLOOKUP(A71,'ESTADOS ESTUDIANTES'!B:L,2,0) -> ROZO BARAJAS DIANA MARCELA | C71: =VLOOKUP(A71,'ESTADOS ESTUDIANTES'!B:L,3,0) -> 295 | D71: =VLOOKUP(A71,'ESTADOS ESTUDIANTES'!B:L,4,0) -> MAE. EN CIENCIAS DE LA INF. Y LAS COMUNICACIONES ENFASIS EN SIS. INFOR | E71: =VLOOKUP(A71,'ESTADOS ESTUDIANTES'!B:L,5,0) -> X | F71: =VLOOKUP(E71,Listas!B1:C1004,2,0) -> EXCLUIDO | G71: =VLOOKUP(A71,'ESTADOS ESTUDIANTES'!B:L,7,0) -> NO REGISTRA | H71: =VLOOKUP(A71,'ESTADOS ESTUDIANTES'!B:L,8,0) -> 0 | I71: =VLOOKUP(A71,'ESTADOS ESTUDIANTES'!B:L,9,0) -> 0 | J71: =VLOOKUP(A71,'ESTADOS ESTUDIANTES'!B:L,10,0) -> CC | K71: =VLOOKUP(A71,'ESTADOS ESTUDIANTES'!B:L,11,0) -> 52436418
A72: 20041295027 | B72: =VLOOKUP(A72,'ESTADOS ESTUDIANTES'!B:L,2,0) -> SABY BELTRAN JORGE ENRIQUE | C72: =VLOOKUP(A72,'ESTADOS ESTUDIANTES'!B:L,3,0) -> 295 | D72: =VLOOKUP(A72,'ESTADOS ESTUDIANTES'!B:L,4,0) -> MAE. EN CIENCIAS DE LA INF. Y LAS COMUNICACIONES ENFASIS EN SIS. INFOR | E72: =VLOOKUP(A72,'ESTADOS ESTUDIANTES'!B:L,5,0) -> Z | F72: =VLOOKUP(E72,Listas!B1:C1004,2,0) -> NO SUP. PRUEBA ACAD. | G72: =VLOOKUP(A72,'ESTADOS ESTUDIANTES'!B:L,7,0) -> NO REGISTRA | H72: =VLOOKUP(A72,'ESTADOS ESTUDIANTES'!B:L,8,0) -> jesabyb@correo.udistrital.edu.co | I72: =VLOOKUP(A72,'ESTADOS ESTUDIANTES'!B:L,9,0) -> jesabyb@estudiante.udistrital.edu.co | J72: =VLOOKUP(A72,'ESTADOS ESTUDIANTES'!B:L,10,0) -> CC | K72: =VLOOKUP(A72,'ESTADOS ESTUDIANTES'!B:L,11,0) -> 19461640
A73: 20042195001 | B73: =VLOOKUP(A73,'ESTADOS ESTUDIANTES'!B:L,2,0) -> ARTEAGA MEZA DIEGO GERMAN | C73: =VLOOKUP(A73,'ESTADOS ESTUDIANTES'!B:L,3,0) -> 195 | D73: =VLOOKUP(A73,'ESTADOS ESTUDIANTES'!B:L,4,0) -> MAE. EN CIENCIAS DE LA INF. Y LAS COMUNICACIONES ENFASIS EN TELEINF. | E73: =VLOOKUP(A73,'ESTADOS ESTUDIANTES'!B:L,5,0) -> E | F73: =VLOOKUP(E73,Listas!B1:C1004,2,0) -> EGRESADO | G73: =VLOOKUP(A73,'ESTADOS ESTUDIANTES'!B:L,7,0) -> NO REGISTRA | H73: =VLOOKUP(A73,'ESTADOS ESTUDIANTES'!B:L,8,0) -> dgarteagam@correo.udistrital.edu.co | I73: =VLOOKUP(A73,'ESTADOS ESTUDIANTES'!B:L,9,0) -> diego.arteaga@gmail.com | J73: =VLOOKUP(A73,'ESTADOS ESTUDIANTES'!B:L,10,0) -> CC | K73: =VLOOKUP(A73,'ESTADOS ESTUDIANTES'!B:L,11,0) -> 98398037
A74: 20042195002 | B74: =VLOOKUP(A74,'ESTADOS ESTUDIANTES'!B:L,2,0) -> BELTRAN PARDO DAVID MAURICIO | C74: =VLOOKUP(A74,'ESTADOS ESTUDIANTES'!B:L,3,0) -> 195 | D74: =VLOOKUP(A74,'ESTADOS ESTUDIANTES'!B:L,4,0) -> MAE. EN CIENCIAS DE LA INF. Y LAS COMUNICACIONES ENFASIS EN TELEINF. | E74: =VLOOKUP(A74,'ESTADOS ESTUDIANTES'!B:L,5,0) -> E | F74: =VLOOKUP(E74,Listas!B1:C1004,2,0) -> EGRESADO | G74: =VLOOKUP(A74,'ESTADOS ESTUDIANTES'!B:L,7,0) -> 1 | H74: =VLOOKUP(A74,'ESTADOS ESTUDIANTES'!B:L,8,0) -> dmbeltranp@correo.udistrital.edu.co | I74: =VLOOKUP(A74,'ESTADOS ESTUDIANTES'!B:L,9,0) -> davidmbpardo@gmail.com | J74: =VLOOKUP(A74,'ESTADOS ESTUDIANTES'!B:L,10,0) -> CC | K74: =VLOOKUP(A74,'ESTADOS ESTUDIANTES'!B:L,11,0) -> 80083236
A75: 20042195003 | B75: =VLOOKUP(A75,'ESTADOS ESTUDIANTES'!B:L,2,0) -> CASTELLANOS CONTRERAS JOSE ULISES | C75: =VLOOKUP(A75,'ESTADOS ESTUDIANTES'!B:L,3,0) -> 195 | D75: =VLOOKUP(A75,'ESTADOS ESTUDIANTES'!B:L,4,0) -> MAE. EN CIENCIAS DE LA INF. Y LAS COMUNICACIONES ENFASIS EN TELEINF. | E75: =VLOOKUP(A75,'ESTADOS ESTUDIANTES'!B:L,5,0) -> X | F75: =VLOOKUP(E75,Listas!B1:C1004,2,0) -> EXCLUIDO | G75: =VLOOKUP(A75,'ESTADOS ESTUDIANTES'!B:L,7,0) -> NO REGISTRA | H75: =VLOOKUP(A75,'ESTADOS ESTUDIANTES'!B:L,8,0) -> jucastellanosc@correo.udistrital.edu.co | I75: =VLOOKUP(A75,'ESTADOS ESTUDIANTES'!B:L,9,0) -> jucastellanosc@estudiante.udistrital.edu.co | J75: =VLOOKUP(A75,'ESTADOS ESTUDIANTES'!B:L,10,0) -> CC | K75: =VLOOKUP(A75,'ESTADOS ESTUDIANTES'!B:L,11,0) -> 79860808
A76: 20042195004 | B76: =VLOOKUP(A76,'ESTADOS ESTUDIANTES'!B:L,2,0) -> CASANOVA CALIMAN PAOLA ANDREA | C76: =VLOOKUP(A76,'ESTADOS ESTUDIANTES'!B:L,3,0) -> 195 | D76: =VLOOKUP(A76,'ESTADOS ESTUDIANTES'!B:L,4,0) -> MAE. EN CIENCIAS DE LA INF. Y LAS COMUNICACIONES ENFASIS EN TELEINF. | E76: =VLOOKUP(A76,'ESTADOS ESTUDIANTES'!B:L,5,0) -> X | F76: =VLOOKUP(E76,Listas!B1:C1004,2,0) -> EXCLUIDO | G76: =VLOOKUP(A76,'ESTADOS ESTUDIANTES'!B:L,7,0) -> NO REGISTRA | H76: =VLOOKUP(A76,'ESTADOS ESTUDIANTES'!B:L,8,0) -> pacasanovac@correo.udistrital.edu.co | I76: =VLOOKUP(A76,'ESTADOS ESTUDIANTES'!B:L,9,0) -> pacasanovac@estudiante.udistrital.edu.co | J76: =VLOOKUP(A76,'ESTADOS ESTUDIANTES'!B:L,10,0) -> CC | K76: =VLOOKUP(A76,'ESTADOS ESTUDIANTES'!B:L,11,0) -> 52856792
A77: 20042195005 | B77: =VLOOKUP(A77,'ESTADOS ESTUDIANTES'!B:L,2,0) -> CUAYAL MUÑOZ JESUS OSWALDO | C77: =VLOOKUP(A77,'ESTADOS ESTUDIANTES'!B:L,3,0) -> 195 | D77: =VLOOKUP(A77,'ESTADOS ESTUDIANTES'!B:L,4,0) -> MAE. EN CIENCIAS DE LA INF. Y LAS COMUNICACIONES ENFASIS EN TELEINF. | E77: =VLOOKUP(A77,'ESTADOS ESTUDIANTES'!B:L,5,0) -> X | F77: =VLOOKUP(E77,Listas!B1:C1004,2,0) -> EXCLUIDO | G77: =VLOOKUP(A77,'ESTADOS ESTUDIANTES'!B:L,7,0) -> NO REGISTRA | H77: =VLOOKUP(A77,'ESTADOS ESTUDIANTES'!B:L,8,0) -> jocuayalm@correo.udistrital.edu.co | I77: =VLOOKUP(A77,'ESTADOS ESTUDIANTES'!B:L,9,0) -> jocuayalm@estudiante.udistrital.edu.co | J77: =VLOOKUP(A77,'ESTADOS ESTUDIANTES'!B:L,10,0) -> CC | K77: =VLOOKUP(A77,'ESTADOS ESTUDIANTES'!B:L,11,0) -> 12966163
A78: 20042195006 | B78: =VLOOKUP(A78,'ESTADOS ESTUDIANTES'!B:L,2,0) -> CORREDOR CAMARGO OSCAR FABIAN | C78: =VLOOKUP(A78,'ESTADOS ESTUDIANTES'!B:L,3,0) -> 195 | D78: =VLOOKUP(A78,'ESTADOS ESTUDIANTES'!B:L,4,0) -> MAE. EN CIENCIAS DE LA INF. Y LAS COMUNICACIONES ENFASIS EN TELEINF. | E78: =VLOOKUP(A78,'ESTADOS ESTUDIANTES'!B:L,5,0) -> E | F78: =VLOOKUP(E78,Listas!B1:C1004,2,0) -> EGRESADO | G78: =VLOOKUP(A78,'ESTADOS ESTUDIANTES'!B:L,7,0) -> NO REGISTRA | H78: =VLOOKUP(A78,'ESTADOS ESTUDIANTES'!B:L,8,0) -> ofcorredorc@udistrital.edu.co | I78: =VLOOKUP(A78,'ESTADOS ESTUDIANTES'!B:L,9,0) -> ofcca@hotmail.com | J78: =VLOOKUP(A78,'ESTADOS ESTUDIANTES'!B:L,10,0) -> CC | K78: =VLOOKUP(A78,'ESTADOS ESTUDIANTES'!B:L,11,0) -> 88244208
A79: 20042195007 | B79: =VLOOKUP(A79,'ESTADOS ESTUDIANTES'!B:L,2,0) -> DELGADO PEÑA PEDRO | C79: =VLOOKUP(A79,'ESTADOS ESTUDIANTES'!B:L,3,0) -> 195 | D79: =VLOOKUP(A79,'ESTADOS ESTUDIANTES'!B:L,4,0) -> MAE. EN CIENCIAS DE LA INF. Y LAS COMUNICACIONES ENFASIS EN TELEINF. | E79: =VLOOKUP(A79,'ESTADOS ESTUDIANTES'!B:L,5,0) -> X | F79: =VLOOKUP(E79,Listas!B1:C1004,2,0) -> EXCLUIDO | G79: =VLOOKUP(A79,'ESTADOS ESTUDIANTES'!B:L,7,0) -> NO REGISTRA | H79: =VLOOKUP(A79,'ESTADOS ESTUDIANTES'!B:L,8,0) -> pdelgadop@correo.udistrital.edu.co | I79: =VLOOKUP(A79,'ESTADOS ESTUDIANTES'!B:L,9,0) -> pdelgadop@estudiante.udistrital.edu.co | J79: =VLOOKUP(A79,'ESTADOS ESTUDIANTES'!B:L,10,0) -> CC | K79: =VLOOKUP(A79,'ESTADOS ESTUDIANTES'!B:L,11,0) -> 79360383
A80: 20042195008 | B80: =VLOOKUP(A80,'ESTADOS ESTUDIANTES'!B:L,2,0) -> CARLOS GALINDO BALLESTEROS | C80: =VLOOKUP(A80,'ESTADOS ESTUDIANTES'!B:L,3,0) -> 195 | D80: =VLOOKUP(A80,'ESTADOS ESTUDIANTES'!B:L,4,0) -> MAE. EN CIENCIAS DE LA INF. Y LAS COMUNICACIONES ENFASIS EN TELEINF. | E80: =VLOOKUP(A80,'ESTADOS ESTUDIANTES'!B:L,5,0) -> E | F80: =VLOOKUP(E80,Listas!B1:C1004,2,0) -> EGRESADO | G80: =VLOOKUP(A80,'ESTADOS ESTUDIANTES'!B:L,7,0) -> NO REGISTRA | H80: =VLOOKUP(A80,'ESTADOS ESTUDIANTES'!B:L,8,0) -> cgalindob@correo.udistrital.edu.co | I80: =VLOOKUP(A80,'ESTADOS ESTUDIANTES'!B:L,9,0) -> galindocarlos@hotmail.com | J80: =VLOOKUP(A80,'ESTADOS ESTUDIANTES'!B:L,10,0) -> CC | K80: =VLOOKUP(A80,'ESTADOS ESTUDIANTES'!B:L,11,0) -> 79330024
A81: 20042195009 | B81: =VLOOKUP(A81,'ESTADOS ESTUDIANTES'!B:L,2,0) -> GARCIA GIRALDO GUSTAVO ANDRES | C81: =VLOOKUP(A81,'ESTADOS ESTUDIANTES'!B:L,3,0) -> 195 | D81: =VLOOKUP(A81,'ESTADOS ESTUDIANTES'!B:L,4,0) -> MAE. EN CIENCIAS DE LA INF. Y LAS COMUNICACIONES ENFASIS EN TELEINF. | E81: =VLOOKUP(A81,'ESTADOS ESTUDIANTES'!B:L,5,0) -> E | F81: =VLOOKUP(E81,Listas!B1:C1004,2,0) -> EGRESADO | G81: =VLOOKUP(A81,'ESTADOS ESTUDIANTES'!B:L,7,0) -> 1 | H81: =VLOOKUP(A81,'ESTADOS ESTUDIANTES'!B:L,8,0) -> guagarciag@correo.udistrital.edu.co | I81: =VLOOKUP(A81,'ESTADOS ESTUDIANTES'!B:L,9,0) -> gustavo_31727@yahoo.es | J81: =VLOOKUP(A81,'ESTADOS ESTUDIANTES'!B:L,10,0) -> CC | K81: =VLOOKUP(A81,'ESTADOS ESTUDIANTES'!B:L,11,0) -> 9728027
A82: 20042195010 | B82: =VLOOKUP(A82,'ESTADOS ESTUDIANTES'!B:L,2,0) -> GARCIA RIAÑO JERONIMO | C82: =VLOOKUP(A82,'ESTADOS ESTUDIANTES'!B:L,3,0) -> 195 | D82: =VLOOKUP(A82,'ESTADOS ESTUDIANTES'!B:L,4,0) -> MAE. EN CIENCIAS DE LA INF. Y LAS COMUNICACIONES ENFASIS EN TELEINF. | E82: =VLOOKUP(A82,'ESTADOS ESTUDIANTES'!B:L,5,0) -> X | F82: =VLOOKUP(E82,Listas!B1:C1004,2,0) -> EXCLUIDO | G82: =VLOOKUP(A82,'ESTADOS ESTUDIANTES'!B:L,7,0) -> NO REGISTRA | H82: =VLOOKUP(A82,'ESTADOS ESTUDIANTES'!B:L,8,0) -> jegarciar@correo.udistrital.edu.co | I82: =VLOOKUP(A82,'ESTADOS ESTUDIANTES'!B:L,9,0) -> jegarciar@estudiante.udistrital.edu.co | J82: =VLOOKUP(A82,'ESTADOS ESTUDIANTES'!B:L,10,0) -> CC | K82: =VLOOKUP(A82,'ESTADOS ESTUDIANTES'!B:L,11,0) -> 43774216
A83: 20042195011 | B83: =VLOOKUP(A83,'ESTADOS ESTUDIANTES'!B:L,2,0) -> GOMEZ HERAZO TANIA | C83: =VLOOKUP(A83,'ESTADOS ESTUDIANTES'!B:L,3,0) -> 195 | D83: =VLOOKUP(A83,'ESTADOS ESTUDIANTES'!B:L,4,0) -> MAE. EN CIENCIAS DE LA INF. Y LAS COMUNICACIONES ENFASIS EN TELEINF. | E83: =VLOOKUP(A83,'ESTADOS ESTUDIANTES'!B:L,5,0) -> X | F83: =VLOOKUP(E83,Listas!B1:C1004,2,0) -> EXCLUIDO | G83: =VLOOKUP(A83,'ESTADOS ESTUDIANTES'!B:L,7,0) -> NO REGISTRA | H83: =VLOOKUP(A83,'ESTADOS ESTUDIANTES'!B:L,8,0) -> tgomezh@correo.udistrital.edu.co | I83: =VLOOKUP(A83,'ESTADOS ESTUDIANTES'!B:L,9,0) -> tgomezh@estudiante.udistrital.edu.co | J83: =VLOOKUP(A83,'ESTADOS ESTUDIANTES'!B:L,10,0) -> CC | K83: =VLOOKUP(A83,'ESTADOS ESTUDIANTES'!B:L,11,0) -> 52262287
A84: 20042195012 | B84: =VLOOKUP(A84,'ESTADOS ESTUDIANTES'!B:L,2,0) -> HERNANDEZ SUAREZ CESAR AUGUSTO | C84: =VLOOKUP(A84,'ESTADOS ESTUDIANTES'!B:L,3,0) -> 195 | D84: =VLOOKUP(A84,'ESTADOS ESTUDIANTES'!B:L,4,0) -> MAE. EN CIENCIAS DE LA INF. Y LAS COMUNICACIONES ENFASIS EN TELEINF. | E84: =VLOOKUP(A84,'ESTADOS ESTUDIANTES'!B:L,5,0) -> E | F84: =VLOOKUP(E84,Listas!B1:C1004,2,0) -> EGRESADO | G84: =VLOOKUP(A84,'ESTADOS ESTUDIANTES'!B:L,7,0) -> NO REGISTRA | H84: =VLOOKUP(A84,'ESTADOS ESTUDIANTES'!B:L,8,0) -> ceahernandezs@correo.udistrital.edu.co | I84: =VLOOKUP(A84,'ESTADOS ESTUDIANTES'!B:L,9,0) -> ceahernandezs@estudiante.udistrital.edu.co | J84: =VLOOKUP(A84,'ESTADOS ESTUDIANTES'!B:L,10,0) -> CC | K84: =VLOOKUP(A84,'ESTADOS ESTUDIANTES'!B:L,11,0) -> 86062285
A85: 20042195013 | B85: =VLOOKUP(A85,'ESTADOS ESTUDIANTES'!B:L,2,0) -> MALDONADO ALARCON JAIRO ORLANDO | C85: =VLOOKUP(A85,'ESTADOS ESTUDIANTES'!B:L,3,0) -> 195 | D85: =VLOOKUP(A85,'ESTADOS ESTUDIANTES'!B:L,4,0) -> MAE. EN CIENCIAS DE LA INF. Y LAS COMUNICACIONES ENFASIS EN TELEINF. | E85: =VLOOKUP(A85,'ESTADOS ESTUDIANTES'!B:L,5,0) -> X | F85: =VLOOKUP(E85,Listas!B1:C1004,2,0) -> EXCLUIDO | G85: =VLOOKUP(A85,'ESTADOS ESTUDIANTES'!B:L,7,0) -> NO REGISTRA | H85: =VLOOKUP(A85,'ESTADOS ESTUDIANTES'!B:L,8,0) -> jaomaldonadoa@correo.udistrital.edu.co | I85: =VLOOKUP(A85,'ESTADOS ESTUDIANTES'!B:L,9,0) -> jaomaldonadoa@estudiante.udistrital.edu.co | J85: =VLOOKUP(A85,'ESTADOS ESTUDIANTES'!B:L,10,0) -> CC | K85: =VLOOKUP(A85,'ESTADOS ESTUDIANTES'!B:L,11,0) -> 79756271
A86: 20042195014 | B86: =VLOOKUP(A86,'ESTADOS ESTUDIANTES'!B:L,2,0) -> MARTINEZ MUÑOZ LUIS CARLOS | C86: =VLOOKUP(A86,'ESTADOS ESTUDIANTES'!B:L,3,0) -> 195 | D86: =VLOOKUP(A86,'ESTADOS ESTUDIANTES'!B:L,4,0) -> MAE. EN CIENCIAS DE LA INF. Y LAS COMUNICACIONES ENFASIS EN TELEINF. | E86: =VLOOKUP(A86,'ESTADOS ESTUDIANTES'!B:L,5,0) -> X | F86: =VLOOKUP(E86,Listas!B1:C1004,2,0) -> EXCLUIDO | G86: =VLOOKUP(A86,'ESTADOS ESTUDIANTES'!B:L,7,0) -> NO REGISTRA | H86: =VLOOKUP(A86,'ESTADOS ESTUDIANTES'!B:L,8,0) -> lucmartinezm@correo.udistrital.edu.co | I86: =VLOOKUP(A86,'ESTADOS ESTUDIANTES'!B:L,9,0) -> lucmartinezm@estudiante.udistrital.edu.co | J86: =VLOOKUP(A86,'ESTADOS ESTUDIANTES'!B:L,10,0) -> CC | K86: =VLOOKUP(A86,'ESTADOS ESTUDIANTES'!B:L,11,0) -> 12985822
A87: 20042195015 | B87: =VLOOKUP(A87,'ESTADOS ESTUDIANTES'!B:L,2,0) -> MELO OSPINA LUIS ALFONSO | C87: =VLOOKUP(A87,'ESTADOS ESTUDIANTES'!B:L,3,0) -> 195 | D87: =VLOOKUP(A87,'ESTADOS ESTUDIANTES'!B:L,4,0) -> MAE. EN CIENCIAS DE LA INF. Y LAS COMUNICACIONES ENFASIS EN TELEINF. | E87: =VLOOKUP(A87,'ESTADOS ESTUDIANTES'!B:L,5,0) -> X | F87: =VLOOKUP(E87,Listas!B1:C1004,2,0) -> EXCLUIDO | G87: =VLOOKUP(A87,'ESTADOS ESTUDIANTES'!B:L,7,0) -> NO REGISTRA | H87: =VLOOKUP(A87,'ESTADOS ESTUDIANTES'!B:L,8,0) -> lameloo@correo.udistrital.edu.co | I87: =VLOOKUP(A87,'ESTADOS ESTUDIANTES'!B:L,9,0) -> lameloo@estudiante.udistrital.edu.co | J87: =VLOOKUP(A87,'ESTADOS ESTUDIANTES'!B:L,10,0) -> CC | K87: =VLOOKUP(A87,'ESTADOS ESTUDIANTES'!B:L,11,0) -> 19371562
A88: 20042195016 | B88: =VLOOKUP(A88,'ESTADOS ESTUDIANTES'!B:L,2,0) -> MORENO DELGADO OSCAR JAVIER | C88: =VLOOKUP(A88,'ESTADOS ESTUDIANTES'!B:L,3,0) -> 195 | D88: =VLOOKUP(A88,'ESTADOS ESTUDIANTES'!B:L,4,0) -> MAE. EN CIENCIAS DE LA INF. Y LAS COMUNICACIONES ENFASIS EN TELEINF. | E88: =VLOOKUP(A88,'ESTADOS ESTUDIANTES'!B:L,5,0) -> X | F88: =VLOOKUP(E88,Listas!B1:C1004,2,0) -> EXCLUIDO | G88: =VLOOKUP(A88,'ESTADOS ESTUDIANTES'!B:L,7,0) -> NO REGISTRA | H88: =VLOOKUP(A88,'ESTADOS ESTUDIANTES'!B:L,8,0) -> ojmorenod@correo.udistrital.edu.co | I88: =VLOOKUP(A88,'ESTADOS ESTUDIANTES'!B:L,9,0) -> richardibague@hotmail.com | J88: =VLOOKUP(A88,'ESTADOS ESTUDIANTES'!B:L,10,0) -> CC | K88: =VLOOKUP(A88,'ESTADOS ESTUDIANTES'!B:L,11,0) -> 93411774
A89: 20042195018 | B89: =VLOOKUP(A89,'ESTADOS ESTUDIANTES'!B:L,2,0) -> PEDRAZA MARTINEZ LUIS FERNANDO | C89: =VLOOKUP(A89,'ESTADOS ESTUDIANTES'!B:L,3,0) -> 195 | D89: =VLOOKUP(A89,'ESTADOS ESTUDIANTES'!B:L,4,0) -> MAE. EN CIENCIAS DE LA INF. Y LAS COMUNICACIONES ENFASIS EN TELEINF. | E89: =VLOOKUP(A89,'ESTADOS ESTUDIANTES'!B:L,5,0) -> E | F89: =VLOOKUP(E89,Listas!B1:C1004,2,0) -> EGRESADO | G89: =VLOOKUP(A89,'ESTADOS ESTUDIANTES'!B:L,7,0) -> NO REGISTRA | H89: =VLOOKUP(A89,'ESTADOS ESTUDIANTES'!B:L,8,0) -> lfpedrazam@correo.udistrital.edu.co | I89: =VLOOKUP(A89,'ESTADOS ESTUDIANTES'!B:L,9,0) -> pedrazaluis2001@yahoo.es | J89: =VLOOKUP(A89,'ESTADOS ESTUDIANTES'!B:L,10,0) -> CC | K89: =VLOOKUP(A89,'ESTADOS ESTUDIANTES'!B:L,11,0) -> 79880251
A90: 20042195019 | B90: =VLOOKUP(A90,'ESTADOS ESTUDIANTES'!B:L,2,0) -> PEREZ HERRERA PABLO GERMAN | C90: =VLOOKUP(A90,'ESTADOS ESTUDIANTES'!B:L,3,0) -> 195 | D90: =VLOOKUP(A90,'ESTADOS ESTUDIANTES'!B:L,4,0) -> MAE. EN CIENCIAS DE LA INF. Y LAS COMUNICACIONES ENFASIS EN TELEINF. | E90: =VLOOKUP(A90,'ESTADOS ESTUDIANTES'!B:L,5,0) -> E | F90: =VLOOKUP(E90,Listas!B1:C1004,2,0) -> EGRESADO | G90: =VLOOKUP(A90,'ESTADOS ESTUDIANTES'!B:L,7,0) -> NO REGISTRA | H90: =VLOOKUP(A90,'ESTADOS ESTUDIANTES'!B:L,8,0) -> pgperezh@correo.udistrital.edu.co | I90: =VLOOKUP(A90,'ESTADOS ESTUDIANTES'!B:L,9,0) -> pgphpollo@yahoo.com.mx | J90: =VLOOKUP(A90,'ESTADOS ESTUDIANTES'!B:L,10,0) -> CC | K90: =VLOOKUP(A90,'ESTADOS ESTUDIANTES'!B:L,11,0) -> 19055103
A91: 20042195020 | B91: =VLOOKUP(A91,'ESTADOS ESTUDIANTES'!B:L,2,0) -> REYES MOZO JOSE VICENTE | C91: =VLOOKUP(A91,'ESTADOS ESTUDIANTES'!B:L,3,0) -> 195 | D91: =VLOOKUP(A91,'ESTADOS ESTUDIANTES'!B:L,4,0) -> MAE. EN CIENCIAS DE LA INF. Y LAS COMUNICACIONES ENFASIS EN TELEINF. | E91: =VLOOKUP(A91,'ESTADOS ESTUDIANTES'!B:L,5,0) -> X | F91: =VLOOKUP(E91,Listas!B1:C1004,2,0) -> EXCLUIDO | G91: =VLOOKUP(A91,'ESTADOS ESTUDIANTES'!B:L,7,0) -> NO REGISTRA | H91: =VLOOKUP(A91,'ESTADOS ESTUDIANTES'!B:L,8,0) -> jvreyesr@correo.udistrital.edu.co | I91: =VLOOKUP(A91,'ESTADOS ESTUDIANTES'!B:L,9,0) -> jovireyesm@yahoo.com | J91: =VLOOKUP(A91,'ESTADOS ESTUDIANTES'!B:L,10,0) -> CC | K91: =VLOOKUP(A91,'ESTADOS ESTUDIANTES'!B:L,11,0) -> 7161428
A92: 20042195021 | B92: =VLOOKUP(A92,'ESTADOS ESTUDIANTES'!B:L,2,0) -> RIOS SENDOYA LUIS FERNANDO | C92: =VLOOKUP(A92,'ESTADOS ESTUDIANTES'!B:L,3,0) -> 195 | D92: =VLOOKUP(A92,'ESTADOS ESTUDIANTES'!B:L,4,0) -> MAE. EN CIENCIAS DE LA INF. Y LAS COMUNICACIONES ENFASIS EN TELEINF. | E92: =VLOOKUP(A92,'ESTADOS ESTUDIANTES'!B:L,5,0) -> E | F92: =VLOOKUP(E92,Listas!B1:C1004,2,0) -> EGRESADO | G92: =VLOOKUP(A92,'ESTADOS ESTUDIANTES'!B:L,7,0) -> 1 | H92: =VLOOKUP(A92,'ESTADOS ESTUDIANTES'!B:L,8,0) -> lfrioss@correo.udistrital.edu.co | I92: =VLOOKUP(A92,'ESTADOS ESTUDIANTES'!B:L,9,0) -> riosjot@gmail.com | J92: =VLOOKUP(A92,'ESTADOS ESTUDIANTES'!B:L,10,0) -> CC | K92: =VLOOKUP(A92,'ESTADOS ESTUDIANTES'!B:L,11,0) -> 19052013
A93: 20042195022 | B93: =VLOOKUP(A93,'ESTADOS ESTUDIANTES'!B:L,2,0) -> RUBIO PLAZAS JAVIER HUMBERTO | C93: =VLOOKUP(A93,'ESTADOS ESTUDIANTES'!B:L,3,0) -> 195 | D93: =VLOOKUP(A93,'ESTADOS ESTUDIANTES'!B:L,4,0) -> MAE. EN CIENCIAS DE LA INF. Y LAS COMUNICACIONES ENFASIS EN TELEINF. | E93: =VLOOKUP(A93,'ESTADOS ESTUDIANTES'!B:L,5,0) -> X | F93: =VLOOKUP(E93,Listas!B1:C1004,2,0) -> EXCLUIDO | G93: =VLOOKUP(A93,'ESTADOS ESTUDIANTES'!B:L,7,0) -> NO REGISTRA | H93: =VLOOKUP(A93,'ESTADOS ESTUDIANTES'!B:L,8,0) -> jhrubiop@correo.udistrital.edu.co | I93: =VLOOKUP(A93,'ESTADOS ESTUDIANTES'!B:L,9,0) -> jhrubiop@estudiante.udistrital.edu.co | J93: =VLOOKUP(A93,'ESTADOS ESTUDIANTES'!B:L,10,0) -> CC | K93: =VLOOKUP(A93,'ESTADOS ESTUDIANTES'!B:L,11,0) -> 76320312
A94: 20042195023 | B94: =VLOOKUP(A94,'ESTADOS ESTUDIANTES'!B:L,2,0) -> GRANADOS HERNANDEZ LUIS ENRIQUE | C94: =VLOOKUP(A94,'ESTADOS ESTUDIANTES'!B:L,3,0) -> 195 | D94: =VLOOKUP(A94,'ESTADOS ESTUDIANTES'!B:L,4,0) -> MAE. EN CIENCIAS DE LA INF. Y LAS COMUNICACIONES ENFASIS EN TELEINF. | E94: =VLOOKUP(A94,'ESTADOS ESTUDIANTES'!B:L,5,0) -> X | F94: =VLOOKUP(E94,Listas!B1:C1004,2,0) -> EXCLUIDO | G94: =VLOOKUP(A94,'ESTADOS ESTUDIANTES'!B:L,7,0) -> NO REGISTRA | H94: =VLOOKUP(A94,'ESTADOS ESTUDIANTES'!B:L,8,0) -> legranadosh@correo.udistrital.edu.co | I94: =VLOOKUP(A94,'ESTADOS ESTUDIANTES'!B:L,9,0) -> legranadosh@estudiante.udistrital.edu.co | J94: =VLOOKUP(A94,'ESTADOS ESTUDIANTES'!B:L,10,0) -> CC | K94: =VLOOKUP(A94,'ESTADOS ESTUDIANTES'!B:L,11,0) -> 19266719
A95: 20042295001 | B95: =VLOOKUP(A95,'ESTADOS ESTUDIANTES'!B:L,2,0) -> BARRAGAN TORRES LAURA EVA | C95: =VLOOKUP(A95,'ESTADOS ESTUDIANTES'!B:L,3,0) -> 295 | D95: =VLOOKUP(A95,'ESTADOS ESTUDIANTES'!B:L,4,0) -> MAE. EN CIENCIAS DE LA INF. Y LAS COMUNICACIONES ENFASIS EN SIS. INFOR | E95: =VLOOKUP(A95,'ESTADOS ESTUDIANTES'!B:L,5,0) -> X | F95: =VLOOKUP(E95,Listas!B1:C1004,2,0) -> EXCLUIDO | G95: =VLOOKUP(A95,'ESTADOS ESTUDIANTES'!B:L,7,0) -> NO REGISTRA | H95: =VLOOKUP(A95,'ESTADOS ESTUDIANTES'!B:L,8,0) -> lebarragant@correo.udistrital.edu.co | I95: =VLOOKUP(A95,'ESTADOS ESTUDIANTES'!B:L,9,0) -> lebarragant@estudiante.udistrital.edu.co | J95: =VLOOKUP(A95,'ESTADOS ESTUDIANTES'!B:L,10,0) -> CC | K95: =VLOOKUP(A95,'ESTADOS ESTUDIANTES'!B:L,11,0) -> 52020395
A96: 20042295002 | B96: =VLOOKUP(A96,'ESTADOS ESTUDIANTES'!B:L,2,0) -> MARIA LUISA BARRETO SANDOVAL | C96: =VLOOKUP(A96,'ESTADOS ESTUDIANTES'!B:L,3,0) -> 295 | D96: =VLOOKUP(A96,'ESTADOS ESTUDIANTES'!B:L,4,0) -> MAE. EN CIENCIAS DE LA INF. Y LAS COMUNICACIONES ENFASIS EN SIS. INFOR | E96: =VLOOKUP(A96,'ESTADOS ESTUDIANTES'!B:L,5,0) -> E | F96: =VLOOKUP(E96,Listas!B1:C1004,2,0) -> EGRESADO | G96: =VLOOKUP(A96,'ESTADOS ESTUDIANTES'!B:L,7,0) -> 1 | H96: =VLOOKUP(A96,'ESTADOS ESTUDIANTES'!B:L,8,0) -> mlbarretos@correo.udistrital.edu.co | I96: =VLOOKUP(A96,'ESTADOS ESTUDIANTES'!B:L,9,0) -> mbarreto93@yahoo.es | J96: =VLOOKUP(A96,'ESTADOS ESTUDIANTES'!B:L,10,0) -> CC | K96: =VLOOKUP(A96,'ESTADOS ESTUDIANTES'!B:L,11,0) -> 52426307
A97: 20042295003 | B97: =VLOOKUP(A97,'ESTADOS ESTUDIANTES'!B:L,2,0) -> CABALLERO HERRERA JORGE ENRIQUE | C97: =VLOOKUP(A97,'ESTADOS ESTUDIANTES'!B:L,3,0) -> 295 | D97: =VLOOKUP(A97,'ESTADOS ESTUDIANTES'!B:L,4,0) -> MAE. EN CIENCIAS DE LA INF. Y LAS COMUNICACIONES ENFASIS EN SIS. INFOR | E97: =VLOOKUP(A97,'ESTADOS ESTUDIANTES'!B:L,5,0) -> X | F97: =VLOOKUP(E97,Listas!B1:C1004,2,0) -> EXCLUIDO | G97: =VLOOKUP(A97,'ESTADOS ESTUDIANTES'!B:L,7,0) -> NO REGISTRA | H97: =VLOOKUP(A97,'ESTADOS ESTUDIANTES'!B:L,8,0) -> jecaballeroh@correo.udistrital.edu.co | I97: =VLOOKUP(A97,'ESTADOS ESTUDIANTES'!B:L,9,0) -> jecaballeroh@estudiante.udistrital.edu.co | J97: =VLOOKUP(A97,'ESTADOS ESTUDIANTES'!B:L,10,0) -> CC | K97: =VLOOKUP(A97,'ESTADOS ESTUDIANTES'!B:L,11,0) -> 79514639
A98: 20042295004 | B98: =VLOOKUP(A98,'ESTADOS ESTUDIANTES'!B:L,2,0) -> CARDENAS QUINTERO BEITMANTT GEOVANNI | C98: =VLOOKUP(A98,'ESTADOS ESTUDIANTES'!B:L,3,0) -> 295 | D98: =VLOOKUP(A98,'ESTADOS ESTUDIANTES'!B:L,4,0) -> MAE. EN CIENCIAS DE LA INF. Y LAS COMUNICACIONES ENFASIS EN SIS. INFOR | E98: =VLOOKUP(A98,'ESTADOS ESTUDIANTES'!B:L,5,0) -> E | F98: =VLOOKUP(E98,Listas!B1:C1004,2,0) -> EGRESADO | G98: =VLOOKUP(A98,'ESTADOS ESTUDIANTES'!B:L,7,0) -> NO REGISTRA | H98: =VLOOKUP(A98,'ESTADOS ESTUDIANTES'!B:L,8,0) -> bgcardenasq@correo.udistrital.edu.co | I98: =VLOOKUP(A98,'ESTADOS ESTUDIANTES'!B:L,9,0) -> bgcardenasq@estudiante.udistrital.edu.co | J98: =VLOOKUP(A98,'ESTADOS ESTUDIANTES'!B:L,10,0) -> CC | K98: =VLOOKUP(A98,'ESTADOS ESTUDIANTES'!B:L,11,0) -> 7164610
A99: 20042295005 | B99: =VLOOKUP(A99,'ESTADOS ESTUDIANTES'!B:L,2,0) -> CASTRO AGREDO ZULMA IBETH | C99: =VLOOKUP(A99,'ESTADOS ESTUDIANTES'!B:L,3,0) -> 295 | D99: =VLOOKUP(A99,'ESTADOS ESTUDIANTES'!B:L,4,0) -> MAE. EN CIENCIAS DE LA INF. Y LAS COMUNICACIONES ENFASIS EN SIS. INFOR | E99: =VLOOKUP(A99,'ESTADOS ESTUDIANTES'!B:L,5,0) -> X | F99: =VLOOKUP(E99,Listas!B1:C1004,2,0) -> EXCLUIDO | G99: =VLOOKUP(A99,'ESTADOS ESTUDIANTES'!B:L,7,0) -> NO REGISTRA | H99: =VLOOKUP(A99,'ESTADOS ESTUDIANTES'!B:L,8,0) -> zicastroa@correo.udistrital.edu.co | I99: =VLOOKUP(A99,'ESTADOS ESTUDIANTES'!B:L,9,0) -> zicazz@gmail.com | J99: =VLOOKUP(A99,'ESTADOS ESTUDIANTES'!B:L,10,0) -> CC | K99: =VLOOKUP(A99,'ESTADOS ESTUDIANTES'!B:L,11,0) -> 52206646
A100: 20042295006 | B100: =VLOOKUP(A100,'ESTADOS ESTUDIANTES'!B:L,2,0) -> GALLO ROMERO JYMI ALEXANDER | C100: =VLOOKUP(A100,'ESTADOS ESTUDIANTES'!B:L,3,0) -> 295 | D100: =VLOOKUP(A100,'ESTADOS ESTUDIANTES'!B:L,4,0) -> MAE. EN CIENCIAS DE LA INF. Y LAS COMUNICACIONES ENFASIS EN SIS. INFOR | E100: =VLOOKUP(A100,'ESTADOS ESTUDIANTES'!B:L,5,0) -> X | F100: =VLOOKUP(E100,Listas!B1:C1004,2,0) -> EXCLUIDO | G100: =VLOOKUP(A100,'ESTADOS ESTUDIANTES'!B:L,7,0) -> NO REGISTRA | H100: =VLOOKUP(A100,'ESTADOS ESTUDIANTES'!B:L,8,0) -> jyagallor@correo.udistrital.edu.co | I100: =VLOOKUP(A100,'ESTADOS ESTUDIANTES'!B:L,9,0) -> jyagallor@estudiante.udistrital.edu.co | J100: =VLOOKUP(A100,'ESTADOS ESTUDIANTES'!B:L,10,0) -> CC | K100: =VLOOKUP(A100,'ESTADOS ESTUDIANTES'!B:L,11,0) -> 79761096
...

Sheet Listas
A1: Grupo Investigacion | B1: Codigo Estado | C1: Descripcion Estado | D1: Codigo Enfasis | E1: Descripcion Enfasis | F1: Puntuacion Ingles | G1: Clasificacion Ingles | H1: Caracter tesis (nuevo) | I1: Caracter tesis (antiguo) | J1: Revisores | K1: Categoría revista | L1: Porcentaje | M1: NOTA | N1: Estado Pasantía | O1: Modalidad | P1: ESTADO ARTICULO | Q1: AMPLIACION | R1: COD. | S1: PROYECTO
A2: ARMOS* | B2: A | C2: ACTIVO | D2: 95 | E2: Sin Enfasis | F2: 300 | G2: C2 | H2: Aprobado | I2: LISTO PARA SUSTENTAR | J2: VIABLE | K2: Revista A1 | L2: 0.8 | M2: =50*L2 -> 40 | N2: Finalizada | O2: Profundización | P2: Enviado | Q2: SI | R2: 95 | S2: MAESTRIA EN TELEINFORMATICA
A3: ARQUISOT | B3: B | C3: PRUEBA ACADEMICA Y MATRICULADO | D3: 195 | E3: Teleinformatica | F3: 250 | G3: C1 | H3: Meritorio | I3: MODIFICABLE | J3: NO VIABLE | K3: Revista A2 | L3: 0.8 | M3: =50*L3 -> 40 | N3: En proceso | O3: Investigación | P3: Publicado | Q3: NO | R3: 195 | S3: EN TELEINF.
A4: CEPMS | B4: C | C4: CANCELADO | D4: 295 | E4: Sis. Informaticos | F4: 200 | G4: B2 | H4: Laureado | I4: RECHAZADO | J4: MODIFICABLE | K4: Libro de investigación | L4: 0.8 | M4: =50*L4 -> 40 | N4: Pendiente | P4: Por publicar | R4: 295 | S4: ENFASIS EN SIS. INFOR
A5: GCEM | B5: D | C5: NO REPORTO NOTAS | D5: 395 | E5: Geomatica | F5: 150 | G5: B1 | K5: Revista B | L5: 0.6 | M5: =50*L5 -> 30 | N5: Perdida | R5: 395 | S5: ENFASIS EN GEOMATICA
A6: GEFEM | B6: E | C6: EGRESADO | D6: 495 | E6: Ing. Software | F6: 70 | G6: A2 | K6: capítulo de un libro | L6: 0.6 | M6: =50*L6 -> 30 | R6: 495 | S6: ENFASIS EN ING. SOFT
A7: GESETIC | B7: F | C7: PRUEBA ACADEM Y NO SE MATRICULO | F7: 45 | G7: A1 | K7: Revista C | L7: 0.4 | M7: =50*L7 -> 20 | R7: 595 | S7: INVESTIGACIÓN
A8: GESDATOS | B8: G | C8: POR DEFINIR DEL 2001/1 | K8: Ponencia | L8: 0.2 | M8: =50*L8 -> 10 | R8: 695 | S8: PROFUNDIZACIÓN
A9: GICOECOL | B9: H | C9: TERMINO MATERIA Y MATRICULADO ACTUAL PERIODO | K9: N/A | L9: N/A | M9: 0
A10: GICOGE | B10: I | C10: INACTIVO
A11: GIDENUTAS¨* | B11: J | C11: PRUEBA ACAD
A12: GIIRA | B12: K | C12: PRUEBA AC.NO REPORTO NOTAS DE SEM ACTIVO
A13: GITEM ++ | B13: L | C13: PASANTIA O TRABAJO DE GRADO
A14: GITUD | B14: M | C14: NO SE MATRICULO
A15: GRECO | B15: N | C15: ERROR DE CODIGO
A16: GINFRA
A17: INTECSE | B17: O | C17: ESTUDIANTE MOVILIDAD ACADEMICA
A18: ITI* | B18: P | C18: APLAZO SEMESTRE
A19: INTERNET INTELIGENTE | B19: Q | C19: ESTUDIANTE MOVILIDAD ACADEMICA EN VACACIONES
A20: LAMIC | B20: R | C20: RETIRADO
A21: LASER | B21: S | C21: PERDIO CUPO DURANTE UN A?O
A22: LIDER | B22: T | C22: TERMINO MATERIAS Y NO SE MATRICULO
A23: LIFAE | B23: U | C23: PERDIDA CALIDAD ESTUDIANTE ACUERDO 004
A24: NIDE | B24: V | C24: VACACIONES
A25: GIICUD | B25: W | C25: ABANDONO
A26: PROPROBOS
A27: FISINFOR | B27: X | C27: EXCLUIDO
A28: Bionanotecnología | C28: Z - NO SUPERO PRUEBA ACADEMICA
A29: LIFAE
A30: NIDE | B30: Z | C30: NO SUP. PRUEBA ACAD.
A31: SIE
A32: IAFT
A33: COMPLEX UD
A34: DIMSI
A35: XUE
A36: INFRAESTRUCTURA SOSTENIBLE

Sheet N-A Investigación
A1: CODIGO | B1: NOMBRE | C1: CEDULA | D1: ENFASIS | E1: PROYECTO | F1: CORREO INSTITUCIONAL | G1: CORREO PERSONAL | H1: ESTADO | I1: RECIBO | J1: MODALIDAD | K1: TITULO DE PROYECTO | L1: DIRECTOR | M1: CO-DIRECTOR | N1: FECHA DE RADICACION ANTEPROYECTO | O1: AÑO | P1: GRUPO DE INVESTIGACION | Q1: DIRECTOR G. INVESTIGACION | R1: FECHA DE ACEPTACION DEL GRUP. INV. | S1: FECHA DE VENCIMIENTO ANTE PROYECTO | T1: ¿PROYECTO VENCIDO? | U1: AMPLIACION | V1: FECHA MAXIMA RADICACIÓN2 | W1: ACTA ACEPTACION PROPUESTA | X1: LINEA DE INVESTIGACIÓN | Y1: Ex. Ingles Historico | Z1: Pts. Ingles Historico | AA1: Ex. Ingles Actual | AB1: Pts. Ingles Actual | AC1: Clasifiacion Ingles | AD1: ACTA COMPONENTE 1 | AE1: FECHA ACTA | AF1: TITULO COMPONENTE 1 | AG1: REVISTA O EVENTO | AH1: AÑO DE PUBLICACIÓN O EVENTO | AI1: Componente 1 | AJ1: % COMPONENTE 1 | AK1: NOTA COMPONENTE 1 | AL1: FECHA DE RADICACION | AM1: ACTA ASIGNACIÓN JURADOS | AN1: FECHA ASIGNACION JURADOS | AO1: JURADO 1 | AP1: FECHA DE RECIBIDO | AQ1: FECHA ENTREGADO | AR1: NOTA 1 INFORME | AS1: NOTA 2 SUSTENTACIÓN | AT1: CONCEPTO JURADO 1 | AU1: JURADO 2 | AV1: FECHA DE RECIBIDO2 | AW1: FECHA ENTREGADO2 | AX1: NOTA 1 INFORME5 | AY1: NOTA 2 SUSTENTACIÓN2 | AZ1: CONCEPTO JURADO 2 | BA1: FECHA SUSTENTACION | BB1: NOTA SUSTENTACION | BC1: PORCENTAJE DE COMPONENTE 2 | BD1: Columna1 | BE1: ESTUDIANTE VERIFICADO | BF1: PAZ Y SALVO FINANCIERO | BG1: DIRECTOR2
A2: 9929531 | B2: =VLOOKUP(A2,'Datos Personales'!A:M,2,FALSE) -> PAEZ PISCO SAMUEL | C2: =VLOOKUP(A2,'ESTADOS ESTUDIANTES'!B:L,11,0) -> 79472385 | D2: =VLOOKUP(A2,'Datos Personales'!$A:$M,3,FALSE) -> 195 | E2: =VLOOKUP(Tabla4[[#This Row],[ENFASIS]],Listas!$R$2:$S$8,2,0) -> EN TELEINF. | F2: =VLOOKUP(A2,'Datos Personales'!A:M,8,0) -> spaezp@correo.udistrital.edu.co | G2: =VLOOKUP(A2,'Datos Personales'!A:M,9,0) -> samuel.paez@fiscalia.gov.co | H2: =VLOOKUP(A2,'Datos Personales'!A:M,5,FALSE) -> X | I2: =VLOOKUP(Tabla4[[#This Row],[CODIGO]],'ESTADOS ESTUDIANTES'!B:M,12,0) -> 2022-1 | S2: =IF(Tabla4[[#This Row],[FECHA DE ACEPTACION DEL GRUP. INV.]]="","",DATE(YEAR(Tabla4[[#This Row],[FECHA DE ACEPTACION DEL GRUP. INV.]])+2,MONTH(Tabla4[[#This Row],[FECHA DE ACEPTACION DEL GRUP. INV.]]),DAY(Tabla4[[#This Row],[FECHA DE ACEPTACION DEL GRUP. INV.]]))) | T2: =IF(Tabla4[[#This Row],[FECHA DE ACEPTACION DEL GRUP. INV.]]="","",IF(Tabla4[[#This Row],[FECHA DE VENCIMIENTO ANTE PROYECTO]]<TODAY(),"SÍ","NO")) | AA2: 44510 | AB2: 101 | AC2: B1 | AJ2: =IFERROR(VLOOKUP(AI2,Listas!K:L,2,0),"") | AK2: =IFERROR(VLOOKUP(AJ2,Listas!L:M,2,0),"") | BB2: =IFERROR(ROUND(AVERAGE(AY2,AX2,AS2,AR2),0),"") | BC2: =BB2*(100%-AJ2) -> #VALUE! | BD2: =SUM(BC2,AK2) -> #VALUE! | BG2: =IF(OR(H2="A",$H2="D",$H2="P",$H2="V"),L2,"")
A3: 9929539 | B3: =VLOOKUP(A3,'Datos Personales'!A:M,2,FALSE) -> RODRIGUEZ RENGIFO JORGE | C3: =VLOOKUP(A3,'ESTADOS ESTUDIANTES'!B:L,11,0) -> 7545588 | D3: =VLOOKUP(A3,'Datos Personales'!$A:$M,3,FALSE) -> 195 | E3: =VLOOKUP(Tabla4[[#This Row],[ENFASIS]],Listas!$R$2:$S$8,2,0) -> EN TELEINF. | F3: =VLOOKUP(A3,'Datos Personales'!A:M,8,0) -> jrodriguezr@udistrital.edu.co | G3: =VLOOKUP(A3,'Datos Personales'!A:M,9,0) -> jorge.rodriguez@engineer.com | H3: =VLOOKUP(A3,'Datos Personales'!A:M,5,FALSE) -> X | I3: =VLOOKUP(Tabla4[[#This Row],[CODIGO]],'ESTADOS ESTUDIANTES'!B:M,12,0) -> 2022-1 | S3: =IF(Tabla4[[#This Row],[FECHA DE ACEPTACION DEL GRUP. INV.]]="","",DATE(YEAR(Tabla4[[#This Row],[FECHA DE ACEPTACION DEL GRUP. INV.]])+2,MONTH(Tabla4[[#This Row],[FECHA DE ACEPTACION DEL GRUP. INV.]]),DAY(Tabla4[[#This Row],[FECHA DE ACEPTACION DEL GRUP. INV.]]))) | T3: =IF(Tabla4[[#This Row],[FECHA DE ACEPTACION DEL GRUP. INV.]]="","",IF(Tabla4[[#This Row],[FECHA DE VENCIMIENTO ANTE PROYECTO]]<TODAY(),"SÍ","NO")) | AJ3: =IFERROR(VLOOKUP(AI3,Listas!K:L,2,0),"") | AK3: =IFERROR(VLOOKUP(AJ3,Listas!L:M,2,0),"") | BB3: =IFERROR(ROUND(AVERAGE(AY3,AX3,AS3,AR3),0),"") | BC3: =BB3*(100%-AJ3) -> #VALUE! | BD3: =SUM(BC3,AK3) -> #VALUE! | BG3: =IF(OR(H3="A",$H3="D",$H3="P",$H3="V"),L3,"")
A4: 20012095004 | B4: =VLOOKUP(A4,'Datos Personales'!A:M,2,FALSE) -> BECERRA FINO JOSE YASIS | C4: =VLOOKUP(A4,'ESTADOS ESTUDIANTES'!B:L,11,0) -> 79483121 | D4: =VLOOKUP(A4,'Datos Personales'!$A:$M,3,FALSE) -> 195 | E4: =VLOOKUP(Tabla4[[#This Row],[ENFASIS]],Listas!$R$2:$S$8,2,0) -> EN TELEINF. | F4: =VLOOKUP(A4,'Datos Personales'!A:M,8,0) -> jybecerraf@correo.udistrital.edu.co | G4: =VLOOKUP(A4,'Datos Personales'!A:M,9,0) -> jybecerra@gmail.com | H4: =VLOOKUP(A4,'Datos Personales'!A:M,5,FALSE) -> X | I4: =VLOOKUP(Tabla4[[#This Row],[CODIGO]],'ESTADOS ESTUDIANTES'!B:M,12,0) -> 2022-3 | J4: Investigación | K4: CODISEÑO HARDWARE-SOFTWARE PARA LA IMPLEMENTACION DE UN ALGORITMO CRIPTOGRAFICO | L4: Elvis Eduardo Gaona Garcia | M4: Edwar Jacinto Gomez | N4: 44367 | O4: 2021 | P4: GIIRA | Q4: Carlos Enrique Montenegro Marin | R4: 44374 | S4: =IF(Tabla4[[#This Row],[FECHA DE ACEPTACION DEL GRUP. INV.]]="","",DATE(YEAR(Tabla4[[#This Row],[FECHA DE ACEPTACION DEL GRUP. INV.]])+2,MONTH(Tabla4[[#This Row],[FECHA DE ACEPTACION DEL GRUP. INV.]]),DAY(Tabla4[[#This Row],[FECHA DE ACEPTACION DEL GRUP. INV.]]))) -> 45104 | T4: =IF(Tabla4[[#This Row],[FECHA DE ACEPTACION DEL GRUP. INV.]]="","",IF(Tabla4[[#This Row],[FECHA DE VENCIMIENTO ANTE PROYECTO]]<TODAY(),"SÍ","NO")) -> SÍ | W4: 08-2021 | AA4: 43964 | AB4: 92.17 | AC4: B1 | AJ4: =IFERROR(VLOOKUP(AI4,Listas!K:L,2,0),"") | AK4: =IFERROR(VLOOKUP(AJ4,Listas!L:M,2,0),"") | BB4: =IFERROR(ROUND(AVERAGE(AY4,AX4,AS4,AR4),0),"") | BC4: =BB4*(100%-AJ4) -> #VALUE! | BD4: =SUM(BC4,AK4) -> #VALUE! | BG4: =IF(OR(H4="A",$H4="D",$H4="P",$H4="V"),L4,"")
A5: 20101295014 | B5: =VLOOKUP(A5,'Datos Personales'!A:M,2,FALSE) -> SANCHEZ JOSE ALEJANDRO | C5: =VLOOKUP(A5,'ESTADOS ESTUDIANTES'!B:L,11,0) -> 79763774 | D5: =VLOOKUP(A5,'Datos Personales'!$A:$M,3,FALSE) -> 295 | E5: =VLOOKUP(Tabla4[[#This Row],[ENFASIS]],Listas!$R$2:$S$8,2,0) -> ENFASIS EN SIS. INFOR | F5: =VLOOKUP(A5,'Datos Personales'!A:M,8,0) -> jrestivang@udistrital.edu.co | G5: =VLOOKUP(A5,'Datos Personales'!A:M,9,0) -> ijasanchez@gmail.com | H5: =VLOOKUP(A5,'Datos Personales'!A:M,5,FALSE) -> E | I5: =VLOOKUP(Tabla4[[#This Row],[CODIGO]],'ESTADOS ESTUDIANTES'!B:M,12,0) -> 2022-1 | J5: Investigación | K5: PROPUESTA DE UN MARCO DE ENSEÑANZAAPRENDIZAJE BASADO EN CASOS DE ESTUDIO PARA LA IMPLEMENTACION AGIL DE PROYECTOS DE ANALITICA GEOESPACIAL | L5: Jose Nelson Perez | Q5: Sandro Javier Bolaños | R5: 43891 | S5: =IF(Tabla4[[#This Row],[FECHA DE ACEPTACION DEL GRUP. INV.]]="","",DATE(YEAR(Tabla4[[#This Row],[FECHA DE ACEPTACION DEL GRUP. INV.]])+2,MONTH(Tabla4[[#This Row],[FECHA DE ACEPTACION DEL GRUP. INV.]]),DAY(Tabla4[[#This Row],[FECHA DE ACEPTACION DEL GRUP. INV.]]))) -> 44621 | T5: =IF(Tabla4[[#This Row],[FECHA DE ACEPTACION DEL GRUP. INV.]]="","",IF(Tabla4[[#This Row],[FECHA DE VENCIMIENTO ANTE PROYECTO]]<TODAY(),"SÍ","NO")) -> SÍ | AA5: 43888 | AB5: 73.04 | AC5: B1 | AD5: 11-2022 | AE5: 44692 | AJ5: =IFERROR(VLOOKUP(AI5,Listas!K:L,2,0),"") | AK5: =IFERROR(VLOOKUP(AJ5,Listas!L:M,2,0),"") | AL5: 44011 | AN5: 44011 | AO5: Sandro Bolaños | AP5: 44011 | AQ5: 44014 | AR5: 47 | AS5: 47 | AT5: Aprobado | AU5: Luz Angela Rocha Salamanca | AV5: 44011 | AW5: 44025 | AX5: 47 | AY5: 47 | AZ5: Aprobado | BA5: 44120 | BB5: =IFERROR(ROUND(AVERAGE(AY5,AX5,AS5,AR5),0),"") -> 47 | BC5: =BB5*(100%-AJ5) -> #VALUE! | BD5: =SUM(BC5,AK5) -> #VALUE! | BG5: =IF(OR(H5="A",$H5="D",$H5="P",$H5="V"),L5,"")
A6: 20102195004 | B6: =VLOOKUP(A6,'Datos Personales'!A:M,2,FALSE) -> MOLINA MONGUI ANDRES MAURICIO | C6: =VLOOKUP(A6,'ESTADOS ESTUDIANTES'!B:L,11,0) -> 80926416 | D6: =VLOOKUP(A6,'Datos Personales'!$A:$M,3,FALSE) -> 195 | E6: =VLOOKUP(Tabla4[[#This Row],[ENFASIS]],Listas!$R$2:$S$8,2,0) -> EN TELEINF. | F6: =VLOOKUP(A6,'Datos Personales'!A:M,8,0) -> ammolinam@udistrital.edu.co | G6: =VLOOKUP(A6,'Datos Personales'!A:M,9,0) -> maomolina@hotmail.com | H6: =VLOOKUP(A6,'Datos Personales'!A:M,5,FALSE) -> X | I6: =VLOOKUP(Tabla4[[#This Row],[CODIGO]],'ESTADOS ESTUDIANTES'!B:M,12,0) -> 2022-3 | S6: =IF(Tabla4[[#This Row],[FECHA DE ACEPTACION DEL GRUP. INV.]]="","",DATE(YEAR(Tabla4[[#This Row],[FECHA DE ACEPTACION DEL GRUP. INV.]])+2,MONTH(Tabla4[[#This Row],[FECHA DE ACEPTACION DEL GRUP. INV.]]),DAY(Tabla4[[#This Row],[FECHA DE ACEPTACION DEL GRUP. INV.]]))) | T6: =IF(Tabla4[[#This Row],[FECHA DE ACEPTACION DEL GRUP. INV.]]="","",IF(Tabla4[[#This Row],[FECHA DE VENCIMIENTO ANTE PROYECTO]]<TODAY(),"SÍ","NO")) | AA6: 44153 | AB6: 84.11 | AC6: B1 | AJ6: =IFERROR(VLOOKUP(AI6,Listas!K:L,2,0),"") | AK6: =IFERROR(VLOOKUP(AJ6,Listas!L:M,2,0),"") | BB6: =IFERROR(ROUND(AVERAGE(AY6,AX6,AS6,AR6),0),"") | BC6: =BB6*(100%-AJ6) -> #VALUE! | BD6: =SUM(BC6,AK6) -> #VALUE! | BG6: =IF(OR(H6="A",$H6="D",$H6="P",$H6="V"),L6,"")
A7: 20121195003 | B7: =VLOOKUP(A7,'Datos Personales'!A:M,2,FALSE) -> AVILA SANCHEZ JAIME ANTONIO | C7: =VLOOKUP(A7,'ESTADOS ESTUDIANTES'!B:L,11,0) -> 7174732 | D7: =VLOOKUP(A7,'Datos Personales'!$A:$M,3,FALSE) -> 195 | E7: =VLOOKUP(Tabla4[[#This Row],[ENFASIS]],Listas!$R$2:$S$8,2,0) -> EN TELEINF. | F7: =VLOOKUP(A7,'Datos Personales'!A:M,8,0) -> jaaavilas@udistrital.edu.co | G7: =VLOOKUP(A7,'Datos Personales'!A:M,9,0) -> jaimejaas@gmail.com | H7: =VLOOKUP(A7,'Datos Personales'!A:M,5,FALSE) -> E | I7: =VLOOKUP(Tabla4[[#This Row],[CODIGO]],'ESTADOS ESTUDIANTES'!B:M,12,0) -> 2023-1 | K7: OPTIMIZACION DE LA OPERACION DE UNA MICRO RED RURAL AISLADA ENFOCADA EN COSTOS/ MODELO DE OPTIMIZACION ENFOCADO EN LA MINIMIZACION DE COSTOS DEGENERACION DE UNA MICRORRED RURAL AISLADA - CASO DE ESTUDIO CORREGIMIENTO NAZARETH URIBIA (LA GUAJIRA). | L7: Elvis Eduardo Gaona Garcia | M7: Jose Guillermo Guarnizo | O7: 2020 | P7: LIFAE | Q7: Nelson Diaz Aldana | R7: 44021 | S7: =IF(Tabla4[[#This Row],[FECHA DE ACEPTACION DEL GRUP. INV.]]="","",DATE(YEAR(Tabla4[[#This Row],[FECHA DE ACEPTACION DEL GRUP. INV.]])+2,MONTH(Tabla4[[#This Row],[FECHA DE ACEPTACION DEL GRUP. INV.]]),DAY(Tabla4[[#This Row],[FECHA DE ACEPTACION DEL GRUP. INV.]]))) -> 44751 | T7: =IF(Tabla4[[#This Row],[FECHA DE ACEPTACION DEL GRUP. INV.]]="","",IF(Tabla4[[#This Row],[FECHA DE VENCIMIENTO ANTE PROYECTO]]<TODAY(),"SÍ","NO")) -> SÍ | W7: 08-2020 | AA7: 44873 | AB7: 88 | AC7: B1 | AD7: 003/2023 | AE7: 44993 | AF7: Optimización de la operación rural aislada enfocada en costos | AG7: Segundo congreso internacional de ingenieria "Ingenieria para todos" | AH7: 2022 | AI7: Ponencia | AJ7: =IFERROR(VLOOKUP(AI7,Listas!K:L,2,0),"") -> 0.2 | AK7: =IFERROR(VLOOKUP(AJ7,Listas!L:M,2,0),"") -> 10 | AL7: 44867 | AM7: 023/2022 | AN7: 44867 | AO7: Javier Guacaneme | AP7: 44869 | AQ7: 44909 | AR7: 41 | AS7: 44 | AT7: Aprobado | AU7: Francisco Santamaria Piedrahita | AV7: 44869 | AW7: 44909 | AX7: 40 | AY7: 40 | AZ7: Aprobado | BA7: 44907 | BB7: =IFERROR(AVERAGE(AR7,AS7,AX7,AY7),"") -> 41.25 | BC7: =BB7*(100%-AJ7) -> 33 | BD7: =SUM(BC7,AK7) -> 43 | BE7: OK | BF7: OK | BG7: =IF(OR(H7="A",$H7="D",$H7="P",$H7="V"),L7,"")
A8: 20121195016 | B8: =VLOOKUP(A8,'Datos Personales'!A:M,2,FALSE) -> BECERRA FINO JOSE YASIS | C8: =VLOOKUP(A8,'ESTADOS ESTUDIANTES'!B:L,11,0) -> 79483121 | D8: =VLOOKUP(A8,'Datos Personales'!$A:$M,3,FALSE) -> 195 | E8: =VLOOKUP(Tabla4[[#This Row],[ENFASIS]],Listas!$R$2:$S$8,2,0) -> EN TELEINF. | F8: =VLOOKUP(A8,'Datos Personales'!A:M,8,0) -> jybecerraf@correo.udistrital.edu.co | G8: =VLOOKUP(A8,'Datos Personales'!A:M,9,0) -> jybecerra@gmail.com | H8: =VLOOKUP(A8,'Datos Personales'!A:M,5,FALSE) -> X | I8: =VLOOKUP(Tabla4[[#This Row],[CODIGO]],'ESTADOS ESTUDIANTES'!B:M,12,0) -> 2013-3 | S8: =IF(Tabla4[[#This Row],[FECHA DE ACEPTACION DEL GRUP. INV.]]="","",DATE(YEAR(Tabla4[[#This Row],[FECHA DE ACEPTACION DEL GRUP. INV.]])+2,MONTH(Tabla4[[#This Row],[FECHA DE ACEPTACION DEL GRUP. INV.]]),DAY(Tabla4[[#This Row],[FECHA DE ACEPTACION DEL GRUP. INV.]]))) | T8: =IF(Tabla4[[#This Row],[FECHA DE ACEPTACION DEL GRUP. INV.]]="","",IF(Tabla4[[#This Row],[FECHA DE VENCIMIENTO ANTE PROYECTO]]<TODAY(),"SÍ","NO")) | AA8: 43964 | AB8: 92.17 | AC8: B1 | AJ8: =IFERROR(VLOOKUP(AI8,Listas!K:L,2,0),"") | AK8: =IFERROR(VLOOKUP(AJ8,Listas!L:M,2,0),"") | BB8: =IFERROR(ROUND(AVERAGE(AY8,AX8,AS8,AR8),0),"") | BC8: =BB8*(100%-AJ8) -> #VALUE! | BD8: =SUM(BC8,AK8) -> #VALUE! | BG8: =IF(OR(H8="A",$H8="D",$H8="P",$H8="V"),L8,"")
A9: 20121395015 | B9: =VLOOKUP(A9,'Datos Personales'!A:M,2,FALSE) -> RODRIGUEZ SABOGAL EDWIN MAURICIO | C9: =VLOOKUP(A9,'ESTADOS ESTUDIANTES'!B:L,11,0) -> 79764993 | D9: =VLOOKUP(A9,'Datos Personales'!$A:$M,3,FALSE) -> 395 | E9: =VLOOKUP(Tabla4[[#This Row],[ENFASIS]],Listas!$R$2:$S$8,2,0) -> ENFASIS EN GEOMATICA | F9: =VLOOKUP(A9,'Datos Personales'!A:M,8,0) -> 0 | G9: =VLOOKUP(A9,'Datos Personales'!A:M,9,0) -> emauriciors@gmail.com | H9: =VLOOKUP(A9,'Datos Personales'!A:M,5,FALSE) -> X | I9: =VLOOKUP(Tabla4[[#This Row],[CODIGO]],'ESTADOS ESTUDIANTES'!B:M,12,0) -> 2021-1 | S9: =IF(Tabla4[[#This Row],[FECHA DE ACEPTACION DEL GRUP. INV.]]="","",DATE(YEAR(Tabla4[[#This Row],[FECHA DE ACEPTACION DEL GRUP. INV.]])+2,MONTH(Tabla4[[#This Row],[FECHA DE ACEPTACION DEL GRUP. INV.]]),DAY(Tabla4[[#This Row],[FECHA DE ACEPTACION DEL GRUP. INV.]]))) | T9: =IF(Tabla4[[#This Row],[FECHA DE ACEPTACION DEL GRUP. INV.]]="","",IF(Tabla4[[#This Row],[FECHA DE VENCIMIENTO ANTE PROYECTO]]<TODAY(),"SÍ","NO")) | AA9: 44097 | AB9: 92.52 | AC9: B1 | AJ9: =IFERROR(VLOOKUP(AI9,Listas!K:L,2,0),"") | AK9: =IFERROR(VLOOKUP(AJ9,Listas!L:M,2,0),"") | BB9: =IFERROR(ROUND(AVERAGE(AY9,AX9,AS9,AR9),0),"") | BC9: =BB9*(100%-AJ9) -> #VALUE! | BD9: =SUM(BC9,AK9) -> #VALUE! | BG9: =IF(OR(H9="A",$H9="D",$H9="P",$H9="V"),L9,"")
A10: 20141295003 | B10: =VLOOKUP(A10,'Datos Personales'!A:M,2,FALSE) -> DIAZ ESCUDERO HUMBERTO ANDRES | C10: =VLOOKUP(A10,'ESTADOS ESTUDIANTES'!B:L,11,0) -> 10323622759 | D10: =VLOOKUP(A10,'Datos Personales'!$A:$M,3,FALSE) -> 295 | E10: =VLOOKUP(Tabla4[[#This Row],[ENFASIS]],Listas!$R$2:$S$8,2,0) -> ENFASIS EN SIS. INFOR | F10: =VLOOKUP(A10,'Datos Personales'!A:M,8,0) -> huadiaze@correo.udistrital.edu.co | G10: =VLOOKUP(A10,'Datos Personales'!A:M,9,0) -> humbertodiaz2@gmail.com | H10: =VLOOKUP(A10,'Datos Personales'!A:M,5,FALSE) -> X | I10: =VLOOKUP(Tabla4[[#This Row],[CODIGO]],'ESTADOS ESTUDIANTES'!B:M,12,0) -> 2021-1 | S10: =IF(Tabla4[[#This Row],[FECHA DE ACEPTACION DEL GRUP. INV.]]="","",DATE(YEAR(Tabla4[[#This Row],[FECHA DE ACEPTACION DEL GRUP. INV.]])+2,MONTH(Tabla4[[#This Row],[FECHA DE ACEPTACION DEL GRUP. INV.]]),DAY(Tabla4[[#This Row],[FECHA DE ACEPTACION DEL GRUP. INV.]]))) | T10: =IF(Tabla4[[#This Row],[FECHA DE ACEPTACION DEL GRUP. INV.]]="","",IF(Tabla4[[#This Row],[FECHA DE VENCIMIENTO ANTE PROYECTO]]<TODAY(),"SÍ","NO")) | AJ10: =IFERROR(VLOOKUP(AI10,Listas!K:L,2,0),"") | AK10: =IFERROR(VLOOKUP(AJ10,Listas!L:M,2,0),"") | BB10: =IFERROR(ROUND(AVERAGE(AY10,AX10,AS10,AR10),0),"") | BC10: =BB10*(100%-AJ10) -> #VALUE! | BD10: =SUM(BC10,AK10) -> #VALUE! | BG10: =IF(OR(H10="A",$H10="D",$H10="P",$H10="V"),L10,"")
A11: 20141395002 | B11: =VLOOKUP(A11,'Datos Personales'!A:M,2,FALSE) -> GONZALEZ RODRIGUEZ ADRIAN ALEJANDRO | C11: =VLOOKUP(A11,'ESTADOS ESTUDIANTES'!B:L,11,0) -> 1013607129 | D11: =VLOOKUP(A11,'Datos Personales'!$A:$M,3,FALSE) -> 395 | E11: =VLOOKUP(Tabla4[[#This Row],[ENFASIS]],Listas!$R$2:$S$8,2,0) -> ENFASIS EN GEOMATICA | F11: =VLOOKUP(A11,'Datos Personales'!A:M,8,0) -> adagonzalezr@correo.udistrital.edu.co | G11: =VLOOKUP(A11,'Datos Personales'!A:M,9,0) -> gerencia@geomap.com.co | H11: =VLOOKUP(A11,'Datos Personales'!A:M,5,FALSE) -> X | I11: =VLOOKUP(Tabla4[[#This Row],[CODIGO]],'ESTADOS ESTUDIANTES'!B:M,12,0) -> 2021-3 | S11: =IF(Tabla4[[#This Row],[FECHA DE ACEPTACION DEL GRUP. INV.]]="","",DATE(YEAR(Tabla4[[#This Row],[FECHA DE ACEPTACION DEL GRUP. INV.]])+2,MONTH(Tabla4[[#This Row],[FECHA DE ACEPTACION DEL GRUP. INV.]]),DAY(Tabla4[[#This Row],[FECHA DE ACEPTACION DEL GRUP. INV.]]))) | T11: =IF(Tabla4[[#This Row],[FECHA DE ACEPTACION DEL GRUP. INV.]]="","",IF(Tabla4[[#This Row],[FECHA DE VENCIMIENTO ANTE PROYECTO]]<TODAY(),"SÍ","NO")) | AJ11: =IFERROR(VLOOKUP(AI11,Listas!K:L,2,0),"") | AK11: =IFERROR(VLOOKUP(AJ11,Listas!L:M,2,0),"") | BB11: =IFERROR(ROUND(AVERAGE(AY11,AX11,AS11,AR11),0),"") | BC11: =BB11*(100%-AJ11) -> #VALUE! | BD11: =SUM(BC11,AK11) -> #VALUE! | BG11: =IF(OR(H11="A",$H11="D",$H11="P",$H11="V"),L11,"")
A12: 20142295002 | B12: =VLOOKUP(A12,'Datos Personales'!A:M,2,FALSE) -> CRISTIAN JHONATAN IZQUIERDO ORTIZ | C12: =VLOOKUP(A12,'ESTADOS ESTUDIANTES'!B:L,11,0) -> 1032379203 | D12: =VLOOKUP(A12,'Datos Personales'!$A:$M,3,FALSE) -> 295 | E12: =VLOOKUP(Tabla4[[#This Row],[ENFASIS]],Listas!$R$2:$S$8,2,0) -> ENFASIS EN SIS. INFOR | F12: =VLOOKUP(A12,'Datos Personales'!A:M,8,0) -> cjizquierdoo@udistrital.edu.co | G12: =VLOOKUP(A12,'Datos Personales'!A:M,9,0) -> izquierdo.cristhian@gmail.com | H12: =VLOOKUP(A12,'Datos Personales'!A:M,5,FALSE) -> E | I12: =VLOOKUP(Tabla4[[#This Row],[CODIGO]],'ESTADOS ESTUDIANTES'!B:M,12,0) -> 2024-1 | J12: Investigación | K12: PREDICCIÓN DE INDICADORES ECONÓMICOS A TRAVES DE NOTICIAS USÁNDO RSS, MINERÍA DE TEXTO E INTELIGENCIA COMPUTACIONAL. | L12: Deicy Alvarado | N12: 44824 | O12: 2022 | P12: COMPLEX UD | Q12: Deicy Alvarado | R12: 5--10-2022 | S12: =IF(Tabla4[[#This Row],[FECHA DE ACEPTACION DEL GRUP. INV.]]="","",DATE(YEAR(Tabla4[[#This Row],[FECHA DE ACEPTACION DEL GRUP. INV.]])+2,MONTH(Tabla4[[#This Row],[FECHA DE ACEPTACION DEL GRUP. INV.]]),DAY(Tabla4[[#This Row],[FECHA DE ACEPTACION DEL GRUP. INV.]]))) -> #VALUE! | T12: =IF(Tabla4[[#This Row],[FECHA DE ACEPTACION DEL GRUP. INV.]]="","",IF(Tabla4[[#This Row],[FECHA DE VENCIMIENTO ANTE PROYECTO]]<TODAY(),"SÍ","NO")) -> #VALUE! | AA12: 44887 | AB12: 167 | AC12: B2 | AD12: 012 de 2023 | AE12: 45191 | AF12: Analysis of economic indicators through news and Twitter using text mining, machine learning and multiagent systems. | AG12: IEEE ColCACI 2023 | AH12: 2023 | AI12: Ponencia | AJ12: =IFERROR(VLOOKUP(AI12,Listas!K:L,2,0),"") -> 0.2 | AK12: =IFERROR(VLOOKUP(AJ12,Listas!L:M,2,0),"") -> 10 | AO12: Cesar Augusto Hernandez Suarez | AQ12: 45252 | AR12: 42 | AS12: 41 | AT12: Aprobado | AU12: Andres Eduardo Gaona Barrera | AW12: 45253 | AX12: 41 | AY12: 42 | AZ12: Aprobado | BA12: 45233 | BB12: =IFERROR(AVERAGE(AR12,AS12,AX12,AY12),"") -> 41.5 | BC12: =BB12*(100%-AJ12) -> 33.2 | BD12: =SUM(BC12,AK12) -> 43.2 | BG12: =IF(OR(H12="A",$H12="D",$H12="P",$H12="V"),L12,"")
A13: 20142395005 | B13: =VLOOKUP(A13,'Datos Personales'!A:M,2,FALSE) -> JESSICA ANDREA ZAPATA GRAJALES | C13: =VLOOKUP(A13,'ESTADOS ESTUDIANTES'!B:L,11,0) -> 1026269883 | D13: =VLOOKUP(A13,'Datos Personales'!$A:$M,3,FALSE) -> 395 | E13: =VLOOKUP(Tabla4[[#This Row],[ENFASIS]],Listas!$R$2:$S$8,2,0) -> ENFASIS EN GEOMATICA | F13: =VLOOKUP(A13,'Datos Personales'!A:M,8,0) -> azapatag@correo.udistrital.edu.co | G13: =VLOOKUP(A13,'Datos Personales'!A:M,9,0) -> jessiandre71@gmail.com | H13: =VLOOKUP(A13,'Datos Personales'!A:M,5,FALSE) -> E | I13: =VLOOKUP(Tabla4[[#This Row],[CODIGO]],'ESTADOS ESTUDIANTES'!B:M,12,0) -> 2022-3 | J13: Investigación | K13: MODELO DE DIAGNOSTICO DE LAS ESTRUCTURAS DE LAS EDIFICACIONES DE CHAPINERO Y BOSA EN EL CASO DE UN EVENTO SISMICO QUE AFECTE A LA CIUDAD DE BOGOTA. / MODELO PROBABILISTICO APLICADO AL COLAPSO DE LAS ESTRUCTURAS DE LAS EDIFICACIONES DE LA UPZ DE EL RETIRO, CHAPINERO Y DE LA UPZ EL PORVENIR EN BOSA, EN CASO DE PRESENTARSE UN EVENTO SISMICO. | L13: Andres Cardenas Contreras | N13: 43054 | Q13: Mauricio Rocha | R13: 43182 | S13: =IF(Tabla4[[#This Row],[FECHA DE ACEPTACION DEL GRUP. INV.]]="","",DATE(YEAR(Tabla4[[#This Row],[FECHA DE ACEPTACION DEL GRUP. INV.]])+2,MONTH(Tabla4[[#This Row],[FECHA DE ACEPTACION DEL GRUP. INV.]]),DAY(Tabla4[[#This Row],[FECHA DE ACEPTACION DEL GRUP. INV.]]))) -> 43913 | T13: =IF(Tabla4[[#This Row],[FECHA DE ACEPTACION DEL GRUP. INV.]]="","",IF(Tabla4[[#This Row],[FECHA DE VENCIMIENTO ANTE PROYECTO]]<TODAY(),"SÍ","NO")) -> SÍ | Y13: 43964 | Z13: 51.3 | AA13: 44097 | AB13: 89.72 | AC13: B1 | AD13: 11-2022 | AE13: 44692 | AJ13: =IFERROR(VLOOKUP(AI13,Listas!K:L,2,0),"") | AK13: =IFERROR(VLOOKUP(AJ13,Listas!L:M,2,0),"") | AL13: 43983 | AO13: ROBINSON QUINTANA | AP13: 44140 | AQ13: 44166 | AR13: 50 | AS13: 50 | AT13: Meritorio | AU13: MAURICIO ROCHA | AV13: 43991 | AW13: 44033 | AX13: 50 | AY13: 50 | AZ13: Meritorio | BA13: 44180 | BB13: =IFERROR(ROUND(AVERAGE(AY13,AX13,AS13,AR13),0),"") -> 50 | BC13: =BB13*(100%-AJ13) -> #VALUE! | BD13: =SUM(BC13,AK13) -> #VALUE! | BE13: SI | BG13: =IF(OR(H13="A",$H13="D",$H13="P",$H13="V"),L13,"")
A14: 20152495005 | B14: =VLOOKUP(A14,'Datos Personales'!A:M,2,FALSE) -> DAZA ESPITIA CARLOS ANDRES | C14: =VLOOKUP(A14,'ESTADOS ESTUDIANTES'!B:L,11,0) -> 1033698113 | D14: =VLOOKUP(A14,'Datos Personales'!$A:$M,3,FALSE) -> 495 | E14: =VLOOKUP(Tabla4[[#This Row],[ENFASIS]],Listas!$R$2:$S$8,2,0) -> ENFASIS EN ING. SOFT | F14: =VLOOKUP(A14,'Datos Personales'!A:M,8,0) -> cadazae@udistrital.edu.co | G14: =VLOOKUP(A14,'Datos Personales'!A:M,9,0) -> cdaza1@outlook.com | H14: =VLOOKUP(A14,'Datos Personales'!A:M,5,FALSE) -> X | I14: =VLOOKUP(Tabla4[[#This Row],[CODIGO]],'ESTADOS ESTUDIANTES'!B:M,12,0) -> 2023-1 | J14: Investigación | K14: SIMULACION BASADA EN AGENTES DEL PROCESO DE APROXIMACION FINAL Y ATERRIZAJE DE UNA AERONAVE, EN UN AERODROMO APLICANDO METAHEURISTICAS // MODELACION METAHEURISTICA DEL PROCESO DE APROXIMACION FINAL Y ATERRIZAJE DE UNA AERONAVE, EN UN AERODROMO | L14: Luz Deyci Alvarado Nieto | N14: 43809 | O14: 2019 | P14: COMPLEXUD | Q14: Deicy Alvarado | R14: 44312 | S14: =IF(Tabla4[[#This Row],[FECHA DE ACEPTACION DEL GRUP. INV.]]="","",DATE(YEAR(Tabla4[[#This Row],[FECHA DE ACEPTACION DEL GRUP. INV.]])+2,MONTH(Tabla4[[#This Row],[FECHA DE ACEPTACION DEL GRUP. INV.]]),DAY(Tabla4[[#This Row],[FECHA DE ACEPTACION DEL GRUP. INV.]]))) -> 45042 | T14: =IF(Tabla4[[#This Row],[FECHA DE ACEPTACION DEL GRUP. INV.]]="","",IF(Tabla4[[#This Row],[FECHA DE VENCIMIENTO ANTE PROYECTO]]<TODAY(),"SÍ","NO")) -> SÍ | W14: 05-2021 | AA14: 44802 | AB14: 137 | AC14: B1 | AJ14: =IFERROR(VLOOKUP(AI14,Listas!K:L,2,0),"") | AK14: =IFERROR(VLOOKUP(AJ14,Listas!L:M,2,0),"") | BB14: =IFERROR(AVERAGE(AR14,AS14,AX14,AY14),"") | BC14: =BB14*(100%-AJ14) -> #VALUE! | BD14: =SUM(BC14,AK14) -> #VALUE! | BG14: =IF(OR(H14="A",$H14="D",$H14="P",$H14="V"),L14,"")
A15: 20161195004 | B15: =VLOOKUP(A15,'Datos Personales'!A:M,2,FALSE) -> CORTES FONSECA DAVID RICAUTE | C15: =VLOOKUP(A15,'ESTADOS ESTUDIANTES'!B:L,11,0) -> 1022953913 | D15: =VLOOKUP(A15,'Datos Personales'!$A:$M,3,FALSE) -> 195 | E15: =VLOOKUP(Tabla4[[#This Row],[ENFASIS]],Listas!$R$2:$S$8,2,0) -> EN TELEINF. | F15: =VLOOKUP(A15,'Datos Personales'!A:M,8,0) -> drcortesf@udistrital.edu.co | G15: =VLOOKUP(A15,'Datos Personales'!A:M,9,0) -> davidcortesfonseca@gmail.com | H15: =VLOOKUP(A15,'Datos Personales'!A:M,5,FALSE) -> X | I15: =VLOOKUP(Tabla4[[#This Row],[CODIGO]],'ESTADOS ESTUDIANTES'!B:M,12,0) -> 2022-1 | J15: Investigación | K15: PRONOSTICO DE OPORTUNIDADES ESPECTRALES CON BASE EN EL MODELO DE PROPAGACION SAKAGAMI-KUBOI | L15: Luis Fernando Pedraza | M15: Abel Antonio Navarrete | N15: 43717 | O15: 2019 | P15: GIDENUTAS | Q15: Luis Fernando Pedraza | R15: 43717 | S15: =IF(Tabla4[[#This Row],[FECHA DE ACEPTACION DEL GRUP. INV.]]="","",DATE(YEAR(Tabla4[[#This Row],[FECHA DE ACEPTACION DEL GRUP. INV.]])+2,MONTH(Tabla4[[#This Row],[FECHA DE ACEPTACION DEL GRUP. INV.]]),DAY(Tabla4[[#This Row],[FECHA DE ACEPTACION DEL GRUP. INV.]]))) -> 44448 | T15: =IF(Tabla4[[#This Row],[FECHA DE ACEPTACION DEL GRUP. INV.]]="","",IF(Tabla4[[#This Row],[FECHA DE VENCIMIENTO ANTE PROYECTO]]<TODAY(),"SÍ","NO")) -> SÍ | W15: 14-2019 | AA15: 44097 | AB15: 92.52 | AC15: B1 | AJ15: =IFERROR(VLOOKUP(AI15,Listas!K:L,2,0),"") | AK15: =IFERROR(VLOOKUP(AJ15,Listas!L:M,2,0),"") | BB15: =IFERROR(ROUND(AVERAGE(AY15,AX15,AS15,AR15),0),"") | BC15: =BB15*(100%-AJ15) -> #VALUE! | BD15: =SUM(BC15,AK15) -> #VALUE! | BG15: =IF(OR(H15="A",$H15="D",$H15="P",$H15="V"),L15,"")
A16: 20161395002 | B16: =VLOOKUP(A16,'Datos Personales'!A:M,2,FALSE) -> CABIATIVA SANCHEZ OSCAR ABRAHAM | C16: =VLOOKUP(A16,'ESTADOS ESTUDIANTES'!B:L,11,0) -> 1019040864 | D16: =VLOOKUP(A16,'Datos Personales'!$A:$M,3,FALSE) -> 395 | E16: =VLOOKUP(Tabla4[[#This Row],[ENFASIS]],Listas!$R$2:$S$8,2,0) -> ENFASIS EN GEOMATICA | F16: =VLOOKUP(A16,'Datos Personales'!A:M,8,0) -> oacabiativas@udistrital.edu.co | G16: =VLOOKUP(A16,'Datos Personales'!A:M,9,0) -> cabiato90@gmail.com | H16: =VLOOKUP(A16,'Datos Personales'!A:M,5,FALSE) -> E | I16: =VLOOKUP(Tabla4[[#This Row],[CODIGO]],'ESTADOS ESTUDIANTES'!B:M,12,0) -> 2023-1 | J16: Investigación | K16: MODELO DE IDENTIDAD DIGITAL PARA DOCUMENTOS ADMINISTRATIVOS MEDIANTE FIRMA ELECTRONICA Y BLOCKCHAIN | L16: Edward Jacinto Gomez | S16: =IF(Tabla4[[#This Row],[FECHA DE ACEPTACION DEL GRUP. INV.]]="","",DATE(YEAR(Tabla4[[#This Row],[FECHA DE ACEPTACION DEL GRUP. INV.]])+2,MONTH(Tabla4[[#This Row],[FECHA DE ACEPTACION DEL GRUP. INV.]]),DAY(Tabla4[[#This Row],[FECHA DE ACEPTACION DEL GRUP. INV.]]))) | T16: =IF(Tabla4[[#This Row],[FECHA DE ACEPTACION DEL GRUP. INV.]]="","",IF(Tabla4[[#This Row],[FECHA DE VENCIMIENTO ANTE PROYECTO]]<TODAY(),"SÍ","NO")) | AD16: 02-2023 | AE16: 44979 | AF16: Modelo de identidad digital con firma digital y Blockchain | AJ16: =IFERROR(VLOOKUP(AI16,Listas!K:L,2,0),"") | AK16: =IFERROR(VLOOKUP(AJ16,Listas!L:M,2,0),"") | BB16: =IFERROR(AVERAGE(AR16,AS16,AX16,AY16),"") | BC16: =BB16*(100%-AJ16) -> #VALUE! | BD16: =SUM(BC16,AK16) -> #VALUE! | BG16: Edward Jacinto Gómez
A17: 20161395005 | B17: =VLOOKUP(A17,'Datos Personales'!A:M,2,FALSE) -> CUELLAR GUTIERREZ JULIO ARMANDO | C17: =VLOOKUP(A17,'ESTADOS ESTUDIANTES'!B:L,11,0) -> 1032423220 | D17: =VLOOKUP(A17,'Datos Personales'!$A:$M,3,FALSE) -> 395 | E17: =VLOOKUP(Tabla4[[#This Row],[ENFASIS]],Listas!$R$2:$S$8,2,0) -> ENFASIS EN GEOMATICA | F17: =VLOOKUP(A17,'Datos Personales'!A:M,8,0) -> jacuellarg@correo.udistrital.edu.co | G17: =VLOOKUP(A17,'Datos Personales'!A:M,9,0) -> ingjuliocuellar@gmail.com | H17: =VLOOKUP(A17,'Datos Personales'!A:M,5,FALSE) -> E | I17: =VLOOKUP(Tabla4[[#This Row],[CODIGO]],'ESTADOS ESTUDIANTES'!B:M,12,0) -> 2021-1 | J17: Investigación | K17: IMPLEMENTACION DE IMAGENES HIPERESPECTRALES Y DE RADAR COMO HERRAMIENTA PARA LA IDENTIFICACION MINERALOGICA PARA GRANDES EXTENSIONES EN ESTUDIOS DE EXPLORACION - ZONA DE ESTUDIO: REGION DEL MAGDALENA MEDIO | L17: Ruben Javier Medina Daza | N17: 44012 | O17: 2020 | P17: GEFEM | Q17: Ruben Javier Medina Daza | R17: 44012 | S17: =IF(Tabla4[[#This Row],[FECHA DE ACEPTACION DEL GRUP. INV.]]="","",DATE(YEAR(Tabla4[[#This Row],[FECHA DE ACEPTACION DEL GRUP. INV.]])+2,MONTH(Tabla4[[#This Row],[FECHA DE ACEPTACION DEL GRUP. INV.]]),DAY(Tabla4[[#This Row],[FECHA DE ACEPTACION DEL GRUP. INV.]]))) -> 44742 | T17: =IF(Tabla4[[#This Row],[FECHA DE ACEPTACION DEL GRUP. INV.]]="","",IF(Tabla4[[#This Row],[FECHA DE VENCIMIENTO ANTE PROYECTO]]<TODAY(),"SÍ","NO")) -> SÍ | W17: 08-2020 | AA17: 43888 | AB17: 73.04 | AC17: B1 | AJ17: =IFERROR(VLOOKUP(AI17,Listas!K:L,2,0),"") | AK17: =IFERROR(VLOOKUP(AJ17,Listas!L:M,2,0),"") | AL17: 44347 | AM17: 44348 | AN17: 44348 | AO17: Nelson Enrique Vera Parra | AP17: 44348 | AQ17: 44371 | AR17: 50 | AS17: 50 | AT17: Aprobado | AU17: Erika Sofia Upegui Cardona | AV17: 44348 | AW17: 44371 | AX17: 50 | AY17: 50 | AZ17: Aprobado | BA17: 44371 | BB17: 50 | BC17: =BB17*(100%-AJ17) -> #VALUE! | BD17: =SUM(BC17,AK17) -> #VALUE! | BF17: OK | BG17: =IF(OR(H17="A",$H17="D",$H17="P",$H17="V"),L17,"")
A18: 20161495001 | B18: =VLOOKUP(A18,'Datos Personales'!A:M,2,FALSE) -> ARCOS MUÑOZ NOÉ | C18: =VLOOKUP(A18,'ESTADOS ESTUDIANTES'!B:L,11,0) -> 80747472 | D18: =VLOOKUP(A18,'Datos Personales'!$A:$M,3,FALSE) -> 495 | E18: =VLOOKUP(Tabla4[[#This Row],[ENFASIS]],Listas!$R$2:$S$8,2,0) -> ENFASIS EN ING. SOFT | F18: =VLOOKUP(A18,'Datos Personales'!A:M,8,0) -> narcosm@udistrital.edu.co | G18: =VLOOKUP(A18,'Datos Personales'!A:M,9,0) -> narcosmunoz@gmail.com | H18: =VLOOKUP(A18,'Datos Personales'!A:M,5,FALSE) -> E | I18: =VLOOKUP(Tabla4[[#This Row],[CODIGO]],'ESTADOS ESTUDIANTES'!B:M,12,0) -> 2023-1 | J18: Investigación | K18: “MODELO DE IDENTIDAD DIGITAL PARA DOCUMENTOS ADMINISTRATIVOS MEDIANTE FIRMA ELECTRONICA Y BLOCKCHAIN” | L18: Edward Jacinto Gomez | M18: Rocio Rodriguez | N18: 44021 | O18: 2020 | P18: ARMOS | Q18: Fredy Hernan Martinez | R18: 44078 | S18: =IF(Tabla4[[#This Row],[FECHA DE ACEPTACION DEL GRUP. INV.]]="","",DATE(YEAR(Tabla4[[#This Row],[FECHA DE ACEPTACION DEL GRUP. INV.]])+2,MONTH(Tabla4[[#This Row],[FECHA DE ACEPTACION DEL GRUP. INV.]]),DAY(Tabla4[[#This Row],[FECHA DE ACEPTACION DEL GRUP. INV.]]))) -> 44808 | T18: =IF(Tabla4[[#This Row],[FECHA DE ACEPTACION DEL GRUP. INV.]]="","",IF(Tabla4[[#This Row],[FECHA DE VENCIMIENTO ANTE PROYECTO]]<TODAY(),"SÍ","NO")) -> SÍ | W18: 12-2020 | AA18: 45059 | AB18: 95 | AC18: B1 | AD18: 002/2023 | AE18: 44979 | AF18: Modelo de identidad digital con firma digital y Blockchain | AG18: 12° Congreso Internacional de Computación CICOM 2022 | AH18: 2022 | AI18: Ponencia | AJ18: =IFERROR(VLOOKUP(AI18,Listas!K:L,2,0),"") -> 0.2 | AK18: =IFERROR(VLOOKUP(AJ18,Listas!L:M,2,0),"") -> 10 | AL18: 44897 | AM18: 002/2023 | AN18: 44979 | AO18: Fredy Hernan Martinez | AP18: 44980 | AQ18: 45012 | AR18: 45 | AS18: 45 | AT18: Aprobado | AU18: Julio Baron Velandia | AV18: 44980 | AW18: 45001 | AX18: 36 | AY18: 45 | AZ18: Aprobado | BA18: 45001 | BB18: =IFERROR(AVERAGE(AR18,AS18,AX18,AY18),"") -> 42.75 | BC18: =BB18*(100%-AJ18) -> 34.2 | BD18: =SUM(BC18,AK18) -> 44.2 | BG18: =IF(OR(H18="A",$H18="D",$H18="P",$H18="V"),L18,"")
A19: 20161495003 | B19: =VLOOKUP(A19,'Datos Personales'!A:M,2,FALSE) -> CALDERÓN COY MILTON VICENTE | C19: =VLOOKUP(A19,'ESTADOS ESTUDIANTES'!B:L,11,0) -> 80730767 | D19: =VLOOKUP(A19,'Datos Personales'!$A:$M,3,FALSE) -> 495 | E19: =VLOOKUP(Tabla4[[#This Row],[ENFASIS]],Listas!$R$2:$S$8,2,0) -> ENFASIS EN ING. SOFT | F19: =VLOOKUP(A19,'Datos Personales'!A:M,8,0) -> mvcalderonc@correo.udistrital.edu.co | G19: =VLOOKUP(A19,'Datos Personales'!A:M,9,0) -> miltonv.calderonc@gmail.com | H19: =VLOOKUP(A19,'Datos Personales'!A:M,5,FALSE) -> E | I19: =VLOOKUP(Tabla4[[#This Row],[CODIGO]],'ESTADOS ESTUDIANTES'!B:M,12,0) -> 2021-3 | J19: Investigación | K19: MODELO DE ENTRENAMIENTO DE UN SISTEMA EXPERTO BASADO EN REGLAS MEDIANTE APRENDIZAJE POR REFUERZO APLICADO A LA GENERACION DE TRAYECTORIAS | L19: Esperanza Camargo Casallas | N19: 43936 | O19: 2020 | P19: DIGITI | Q19: Esperanza Camargo | R19: 43936 | S19: =IF(Tabla4[[#This Row],[FECHA DE ACEPTACION DEL GRUP. INV.]]="","",DATE(YEAR(Tabla4[[#This Row],[FECHA DE ACEPTACION DEL GRUP. INV.]])+2,MONTH(Tabla4[[#This Row],[FECHA DE ACEPTACION DEL GRUP. INV.]]),DAY(Tabla4[[#This Row],[FECHA DE ACEPTACION DEL GRUP. INV.]]))) -> 44666 | T19: =IF(Tabla4[[#This Row],[FECHA DE ACEPTACION DEL GRUP. INV.]]="","",IF(Tabla4[[#This Row],[FECHA DE VENCIMIENTO ANTE PROYECTO]]<TODAY(),"SÍ","NO")) -> SÍ | W19: 04/2020 | AA19: 43964 | AB19: 80.87 | AC19: B1 | AD19: 09-2021 | AE19: 44425 | AI19: Revista A2 | AJ19: =IFERROR(VLOOKUP(AI19,Listas!K:L,2,0),"") -> 0.8 | AK19: =IFERROR(VLOOKUP(AJ19,Listas!L:M,2,0),"") -> 40 | AL19: 44425 | AM19: 009-2021 | AN19: 44426 | AO19: Andres Leonardo Jutinico | AP19: 44426 | AQ19: 44489 | AR19: 42 | AS19: 46 | AT19: Aprobado | AU19: Alejandro Paolo Daza Corredor | AV19: 44426 | AW19: 44505 | AX19: 45 | AY19: 45 | AZ19: Aprobado | BA19: 44489 | BB19: =IFERROR(ROUND(AVERAGE(AY19,AX19,AS19,AR19),0),"") -> 45 | BC19: =BB19*(100%-AJ19) -> 9 | BD19: =SUM(BC19,AK19) -> 49 | BF19: OK | BG19: =IF(OR(H19="A",$H19="D",$H19="P",$H19="V"),L19,"")
A20: 20161495009 | B20: =VLOOKUP(A20,'Datos Personales'!A:M,2,FALSE) -> GUERRERO CALDERÓN ÁRNOL | C20: =VLOOKUP(A20,'ESTADOS ESTUDIANTES'!B:L,11,0) -> 3217282 | D20: =VLOOKUP(A20,'Datos Personales'!$A:$M,3,FALSE) -> 495 | E20: =VLOOKUP(Tabla4[[#This Row],[ENFASIS]],Listas!$R$2:$S$8,2,0) -> ENFASIS EN ING. SOFT | F20: =VLOOKUP(A20,'Datos Personales'!A:M,8,0) -> arguerreroc@udistrital.edu.co | G20: =VLOOKUP(A20,'Datos Personales'!A:M,9,0) -> arnolgc@gmail.com | H20: =VLOOKUP(A20,'Datos Personales'!A:M,5,FALSE) -> E | I20: =VLOOKUP(Tabla4[[#This Row],[CODIGO]],'ESTADOS ESTUDIANTES'!B:M,12,0) -> 2024-1 | J20: Investigación | K20: Aplicación de autómatas celulares y algoritmos genéticos en la creación de una técnica estenográfica. | L20: Lilia Edith Aparicio Pico | N20: 44092 | O20: 2020 | P20: GITEM ++ | Q20: Lilia Edith Aparicio Pico | R20: 44092 | S20: =IF(Tabla4[[#This Row],[FECHA DE ACEPTACION DEL GRUP. INV.]]="","",DATE(YEAR(Tabla4[[#This Row],[FECHA DE ACEPTACION DEL GRUP. INV.]])+2,MONTH(Tabla4[[#This Row],[FECHA DE ACEPTACION DEL GRUP. INV.]]),DAY(Tabla4[[#This Row],[FECHA DE ACEPTACION DEL GRUP. INV.]]))) -> 44822 | T20: =IF(Tabla4[[#This Row],[FECHA DE ACEPTACION DEL GRUP. INV.]]="","",IF(Tabla4[[#This Row],[FECHA DE VENCIMIENTO ANTE PROYECTO]]<TODAY(),"SÍ","NO")) -> SÍ | W20: 12-2020 | AA20: 44299 | AB20: 76.52 | AC20: B1 | AD20: 010-2023 | AE20: 45161 | AF20: Técnica estenográfica basada en Modelos Matemáticos Dinámicos y Métodos de Inteligencia Artificial | AG20: XVI CONGRESO INTERNACIONAL DE ELECTRÓNICA, CONTROL Y TELECOMUNICACIONES | AH20: 2023 | AI20: Ponencia | AJ20: =IFERROR(VLOOKUP(AI20,Listas!K:L,2,0),"") -> 0.2 | AK20: =IFERROR(VLOOKUP(AJ20,Listas!L:M,2,0),"") -> 10 | AL20: 45161 | AM20: 010-2023 | AN20: 45161 | AO20: Miguel Alberto Melgarejo | AP20: 45161 | AQ20: 45216 | AR20: 42 | AS20: 43 | AT20: Aprobado | AU20: Paulo Cesar Coronado Sanchez | AV20: 45161 | AW20: 45209 | AX20: 45 | AY20: 46 | AZ20: Aprobado | BA20: 45183 | BB20: =IFERROR(AVERAGE(AR20,AS20,AX20,AY20),"") -> 44 | BC20: =BB20*(100%-AJ20) -> 35.2 | BD20: =SUM(BC20,AK20) -> 45.2 | BG20: =IF(OR(H20="A",$H20="D",$H20="P",$H20="V"),L20,"")
A21: 20161495013 | B21: =VLOOKUP(A21,'Datos Personales'!A:M,2,FALSE) -> MORA JIMÉNEZ JEANET | C21: =VLOOKUP(A21,'ESTADOS ESTUDIANTES'!B:L,11,0) -> 51882949 | D21: =VLOOKUP(A21,'Datos Personales'!$A:$M,3,FALSE) -> 495 | E21: =VLOOKUP(Tabla4[[#This Row],[ENFASIS]],Listas!$R$2:$S$8,2,0) -> ENFASIS EN ING. SOFT | F21: =VLOOKUP(A21,'Datos Personales'!A:M,8,0) -> 0 | G21: =VLOOKUP(A21,'Datos Personales'!A:M,9,0) -> jeanetmj@gmail.com | H21: =VLOOKUP(A21,'Datos Personales'!A:M,5,FALSE) -> X | I21: =VLOOKUP(Tabla4[[#This Row],[CODIGO]],'ESTADOS ESTUDIANTES'!B:M,12,0) -> 2021-1 | J21: Investigación | S21: =IF(Tabla4[[#This Row],[FECHA DE ACEPTACION DEL GRUP. INV.]]="","",DATE(YEAR(Tabla4[[#This Row],[FECHA DE ACEPTACION DEL GRUP. INV.]])+2,MONTH(Tabla4[[#This Row],[FECHA DE ACEPTACION DEL GRUP. INV.]]),DAY(Tabla4[[#This Row],[FECHA DE ACEPTACION DEL GRUP. INV.]]))) | T21: =IF(Tabla4[[#This Row],[FECHA DE ACEPTACION DEL GRUP. INV.]]="","",IF(Tabla4[[#This Row],[FECHA DE VENCIMIENTO ANTE PROYECTO]]<TODAY(),"SÍ","NO")) | AJ21: =IFERROR(VLOOKUP(AI21,Listas!K:L,2,0),"") | AK21: =IFERROR(VLOOKUP(AJ21,Listas!L:M,2,0),"") | BB21: =IFERROR(ROUND(AVERAGE(AY21,AX21,AS21,AR21),0),"") | BC21: =BB21*(100%-AJ21) -> #VALUE! | BD21: =SUM(BC21,AK21) -> #VALUE! | BG21: =IF(OR(H21="A",$H21="D",$H21="P",$H21="V"),L21,"")
A22: 20161495016 | B22: =VLOOKUP(A22,'Datos Personales'!A:M,2,FALSE) -> PUPIALES ARÉVALO ANDRÉS | C22: =VLOOKUP(A22,'ESTADOS ESTUDIANTES'!B:L,11,0) -> 1018413339 | D22: =VLOOKUP(A22,'Datos Personales'!$A:$M,3,FALSE) -> 495 | E22: =VLOOKUP(Tabla4[[#This Row],[ENFASIS]],Listas!$R$2:$S$8,2,0) -> ENFASIS EN ING. SOFT | F22: =VLOOKUP(A22,'Datos Personales'!A:M,8,0) -> anpupialesa@udistrital.edu.co | G22: =VLOOKUP(A22,'Datos Personales'!A:M,9,0) -> apupiales@gmail.com | H22: =VLOOKUP(A22,'Datos Personales'!A:M,5,FALSE) -> E | I22: =VLOOKUP(Tabla4[[#This Row],[CODIGO]],'ESTADOS ESTUDIANTES'!B:M,12,0) -> 2023-1 | J22: Investigación | L22: Roberto Manuel Poveda | S22: =IF(Tabla4[[#This Row],[FECHA DE ACEPTACION DEL GRUP. INV.]]="","",DATE(YEAR(Tabla4[[#This Row],[FECHA DE ACEPTACION DEL GRUP. INV.]])+2,MONTH(Tabla4[[#This Row],[FECHA DE ACEPTACION DEL GRUP. INV.]]),DAY(Tabla4[[#This Row],[FECHA DE ACEPTACION DEL GRUP. INV.]]))) | T22: =IF(Tabla4[[#This Row],[FECHA DE ACEPTACION DEL GRUP. INV.]]="","",IF(Tabla4[[#This Row],[FECHA DE VENCIMIENTO ANTE PROYECTO]]<TODAY(),"SÍ","NO")) | AD22: 023 | AE22: 44867 | AF22: NSGA-II y Greedy 2-opt Paralelo (PNG2) implementado en CUDA C++ para la solución de problemas de asignación cuadrática multiobjetivo mQAP aplicables a la toma de decisiones en planeación estratégica hotelera | AJ22: =IFERROR(VLOOKUP(AI22,Listas!K:L,2,0),"") | AK22: =IFERROR(VLOOKUP(AJ22,Listas!L:M,2,0),"") | AO22: Jorge Enrique Rodriguez Rodriguez | AU22: Cesar Andrey Perdomo Charry | BB22: =IFERROR(AVERAGE(AR22,AS22,AX22,AY22),"") | BC22: =BB22*(100%-AJ22) -> #VALUE! | BD22: =SUM(BC22,AK22) -> #VALUE! | BE22: OK | BG22: =IF(OR(H22="A",$H22="D",$H22="P",$H22="V"),L22,"")
A23: 20161495021 | B23: =VLOOKUP(A23,'Datos Personales'!A:M,2,FALSE) -> RUBIANO VÁSQUEZ LUIS ENRIQUE | C23: =VLOOKUP(A23,'ESTADOS ESTUDIANTES'!B:L,11,0) -> 79156398 | D23: =VLOOKUP(A23,'Datos Personales'!$A:$M,3,FALSE) -> 495 | E23: =VLOOKUP(Tabla4[[#This Row],[ENFASIS]],Listas!$R$2:$S$8,2,0) -> ENFASIS EN ING. SOFT | F23: =VLOOKUP(A23,'Datos Personales'!A:M,8,0) -> lerubianov@correo.udistrital.edu.co | G23: =VLOOKUP(A23,'Datos Personales'!A:M,9,0) -> lrubianov@hotmail.com | H23: =VLOOKUP(A23,'Datos Personales'!A:M,5,FALSE) -> X | I23: =VLOOKUP(Tabla4[[#This Row],[CODIGO]],'ESTADOS ESTUDIANTES'!B:M,12,0) -> 2021-1 | J23: Investigación | S23: =IF(Tabla4[[#This Row],[FECHA DE ACEPTACION DEL GRUP. INV.]]="","",DATE(YEAR(Tabla4[[#This Row],[FECHA DE ACEPTACION DEL GRUP. INV.]])+2,MONTH(Tabla4[[#This Row],[FECHA DE ACEPTACION DEL GRUP. INV.]]),DAY(Tabla4[[#This Row],[FECHA DE ACEPTACION DEL GRUP. INV.]]))) | T23: =IF(Tabla4[[#This Row],[FECHA DE ACEPTACION DEL GRUP. INV.]]="","",IF(Tabla4[[#This Row],[FECHA DE VENCIMIENTO ANTE PROYECTO]]<TODAY(),"SÍ","NO")) | AJ23: =IFERROR(VLOOKUP(AI23,Listas!K:L,2,0),"") | AK23: =IFERROR(VLOOKUP(AJ23,Listas!L:M,2,0),"") | BB23: =IFERROR(ROUND(AVERAGE(AY23,AX23,AS23,AR23),0),"") | BC23: =BB23*(100%-AJ23) -> #VALUE! | BD23: =SUM(BC23,AK23) -> #VALUE! | BG23: =IF(OR(H23="A",$H23="D",$H23="P",$H23="V"),L23,"")
A24: 20162195003 | B24: =VLOOKUP(A24,'Datos Personales'!A:M,2,FALSE) -> BELTRÁN GARCIA JORGE ELIECER | C24: =VLOOKUP(A24,'ESTADOS ESTUDIANTES'!B:L,11,0) -> 11255923 | D24: =VLOOKUP(A24,'Datos Personales'!$A:$M,3,FALSE) -> 195 | E24: =VLOOKUP(Tabla4[[#This Row],[ENFASIS]],Listas!$R$2:$S$8,2,0) -> EN TELEINF. | F24: =VLOOKUP(A24,'Datos Personales'!A:M,8,0) -> jebeltrang@udistrital.edu.co | G24: =VLOOKUP(A24,'Datos Personales'!A:M,9,0) -> jotaebeltrangarcia@gmail.com | H24: =VLOOKUP(A24,'Datos Personales'!A:M,5,FALSE) -> E | I24: =VLOOKUP(Tabla4[[#This Row],[CODIGO]],'ESTADOS ESTUDIANTES'!B:M,12,0) -> 2023-3 | J24: Investigación | K24: DISEÑO DE UNA INTERFAZ DIGITAL INTERPRETADORA DE BRAILLE PARA FACILITAR LA COMUNICACIÓN EFECTIVA DOCENTE – ALUMNO- DOCENTE EN LA INSTITUCIÓN EDUCATIVA TECNOLÓGICO DE MADRID. | L24: Edmundo Vega | N24: 44881 | O24: 2022 | P24: Bionanotecnología | Q24: Edmundo Vega | S24: =IF(Tabla4[[#This Row],[FECHA DE ACEPTACION DEL GRUP. INV.]]="","",DATE(YEAR(Tabla4[[#This Row],[FECHA DE ACEPTACION DEL GRUP. INV.]])+2,MONTH(Tabla4[[#This Row],[FECHA DE ACEPTACION DEL GRUP. INV.]]),DAY(Tabla4[[#This Row],[FECHA DE ACEPTACION DEL GRUP. INV.]]))) | T24: =IF(Tabla4[[#This Row],[FECHA DE ACEPTACION DEL GRUP. INV.]]="","",IF(Tabla4[[#This Row],[FECHA DE VENCIMIENTO ANTE PROYECTO]]<TODAY(),"SÍ","NO")) | AA24: 44981 | AB24: 73 | AC24: B1 | AD24: 008/2023 | AE24: 45104 | AF24: Diseño de una Interfaz digital interpretadora de Braile para facilitar la comunicación efectiva docente - alumno- docente en la Institución educativa Tecnológico de Madrid | AG24: CITICI Congreso Internacional sobre tecnología e Innovación + Ciencia e Investigación | AH24: 2023 | AI24: Ponencia | AJ24: =IFERROR(VLOOKUP(AI24,Listas!K:L,2,0),"") -> 0.2 | AK24: =IFERROR(VLOOKUP(AJ24,Listas!L:M,2,0),"") -> 10 | AL24: 45104 | AM24: 008/2023 | AO24: Octavio Jose Salcedo Parra | AR24: 47 | AS24: 48 | AT24: Aprobado | AU24: Leonardo Plazas Nossa | AX24: 40 | AY24: 48 | AZ24: Aprobado | BA24: 45166 | BB24: =IFERROR(AVERAGE(AR24,AS24,AX24,AY24),"") -> 45.75 | BC24: =BB24*(100%-AJ24) -> 36.6 | BD24: =SUM(BC24,AK24) -> 46.6 | BG24: =IF(OR(H24="A",$H24="D",$H24="P",$H24="V"),L24,"")
A25: 20162495001 | B25: =VLOOKUP(A25,'Datos Personales'!A:M,2,FALSE) -> ARÉVALO SANDOVAL JEYSON STITH | C25: =VLOOKUP(A25,'ESTADOS ESTUDIANTES'!B:L,11,0) -> 1031131535 | D25: =VLOOKUP(A25,'Datos Personales'!$A:$M,3,FALSE) -> 495 | E25: =VLOOKUP(Tabla4[[#This Row],[ENFASIS]],Listas!$R$2:$S$8,2,0) -> ENFASIS EN ING. SOFT | F25: =VLOOKUP(A25,'Datos Personales'!A:M,8,0) -> jsarevalos@udistrital.edu.co | G25: =VLOOKUP(A25,'Datos Personales'!A:M,9,0) -> jeysonarevalo@hotmail.com | H25: =VLOOKUP(A25,'Datos Personales'!A:M,5,FALSE) -> E | I25: =VLOOKUP(Tabla4[[#This Row],[CODIGO]],'ESTADOS ESTUDIANTES'!B:M,12,0) -> 2023-3 | J25: Investigación | K25: GENERACIÓN DE DOCUMENTACIÓN UML MEDIANTE CADENAS DE TRASNFORMACIÓN DE MODELOS | L25: Hector Arturo Florez Hernandez | N25: 44741 | O25: 2022 | P25: ITI* | Q25: Hector Arturo Florez Hernandez | R25: 44796 | S25: =IF(Tabla4[[#This Row],[FECHA DE ACEPTACION DEL GRUP. INV.]]="","",DATE(YEAR(Tabla4[[#This Row],[FECHA DE ACEPTACION DEL GRUP. INV.]])+2,MONTH(Tabla4[[#This Row],[FECHA DE ACEPTACION DEL GRUP. INV.]]),DAY(Tabla4[[#This Row],[FECHA DE ACEPTACION DEL GRUP. INV.]]))) -> 45527 | T25: =IF(Tabla4[[#This Row],[FECHA DE ACEPTACION DEL GRUP. INV.]]="","",IF(Tabla4[[#This Row],[FECHA DE VENCIMIENTO ANTE PROYECTO]]<TODAY(),"SÍ","NO")) -> SÍ | AA25: 44802 | AB25: 86 | AC25: B1 | AD25: 23/2022 | AE25: 44867 | AF25: Implementation of the domain metamodel for the generation of UML documentation through model transformation chains | AG25: 5th International Conference on Applied Informatics (ICAI 2022) | AH25: 2022 | AI25: Ponencia | AJ25: =IFERROR(VLOOKUP(AI25,Listas!K:L,2,0),"") -> 0.2 | AK25: =IFERROR(VLOOKUP(AJ25,Listas!L:M,2,0),"") -> 10 | AO25: Jhon Herrera | AQ25: 45253 | AR25: 30 | AS25: 30 | AU25: Rocio Rodriguez | AX25: 44 | AY25: 44 | AZ25: Aprobado | BB25: =IFERROR(AVERAGE(AR25,AS25,AX25,AY25),"") -> 37 | BC25: =BB25*(100%-AJ25) -> 29.6 | BD25: =SUM(BC25,AK25) -> 39.6 | BG25: =IF(OR(H25="A",$H25="D",$H25="P",$H25="V"),L25,"")
A26: 20162495006 | B26: =VLOOKUP(A26,'Datos Personales'!A:M,2,FALSE) -> GARAY GONZALEZ LADY VIVIANA | C26: =VLOOKUP(A26,'ESTADOS ESTUDIANTES'!B:L,11,0) -> 1022964650 | D26: =VLOOKUP(A26,'Datos Personales'!$A:$M,3,FALSE) -> 495 | E26: =VLOOKUP(Tabla4[[#This Row],[ENFASIS]],Listas!$R$2:$S$8,2,0) -> ENFASIS EN ING. SOFT | F26: =VLOOKUP(A26,'Datos Personales'!A:M,8,0) -> lvgarayg@udistrital.edu.co | G26: =VLOOKUP(A26,'Datos Personales'!A:M,9,0) -> ladyviviana.garay@gmail.com | H26: =VLOOKUP(A26,'Datos Personales'!A:M,5,FALSE) -> E | I26: =VLOOKUP(Tabla4[[#This Row],[CODIGO]],'ESTADOS ESTUDIANTES'!B:M,12,0) -> 2023-3 | J26: Investigación | K26: GENERACIÓN SEMIAUTOMATICA DE APLCIACIONES WEB USANDO CADENAS DE TRASNFORMACIÓN DE MODELOS | L26: Hector Arturo Florez Hernandez | N26: 44741 | O26: 2022 | P26: ITI* | Q26: Hector Arturo Florez Hernandez | R26: 44796 | S26: =IF(Tabla4[[#This Row],[FECHA DE ACEPTACION DEL GRUP. INV.]]="","",DATE(YEAR(Tabla4[[#This Row],[FECHA DE ACEPTACION DEL GRUP. INV.]])+2,MONTH(Tabla4[[#This Row],[FECHA DE ACEPTACION DEL GRUP. INV.]]),DAY(Tabla4[[#This Row],[FECHA DE ACEPTACION DEL GRUP. INV.]]))) -> 45527 | T26: =IF(Tabla4[[#This Row],[FECHA DE ACEPTACION DEL GRUP. INV.]]="","",IF(Tabla4[[#This Row],[FECHA DE VENCIMIENTO ANTE PROYECTO]]<TODAY(),"SÍ","NO")) -> SÍ | AA26: 44802 | AB26: 104 | AC26: B1 | AD26: 24/2022 | AE26: 44881 | AF26: CONSTRUCTION OF DOMAIN METAMODEL USING EMF FOR SEMIAUTOMATIC GENERATION OF WEB APPS | AG26: 5th International Conference on Applied Informatics (ICAI 2022) | AH26: 2022 | AI26: Ponencia | AJ26: =IFERROR(VLOOKUP(AI26,Listas!K:L,2,0),"") -> 0.2 | AK26: =IFERROR(VLOOKUP(AJ26,Listas!L:M,2,0),"") -> 10 | AL26: 45056 | AM26: 006/2023 | AN26: 45056 | AO26: Julio Baron Velandia | AP26: 45061 | AQ26: 45121 | AR26: 25 | AS26: 22 | AT26: Aprobado | AU26: Rocio Rodriguez | AV26: 45061 | AW26: 45086 | AX26: 47 | AY26: 40 | AZ26: Aprobado | BA26: 45053 | BB26: =IFERROR(AVERAGE(AR26,AS26,AX26,AY26),"") -> 33.5 | BC26: =BB26*(100%-AJ26) -> 26.8 | BD26: =SUM(BC26,AK26) -> 36.8 | BF26: SI | BG26: =IF(OR(H26="A",$H26="D",$H26="P",$H26="V"),L26,"")
A27: 20162495017 | B27: =VLOOKUP(A27,'Datos Personales'!A:M,2,FALSE) -> SANCHEZ RODRIGUEZ DANIEL ESTEBAN | C27: =VLOOKUP(A27,'ESTADOS ESTUDIANTES'!B:L,11,0) -> 1032417886 | D27: =VLOOKUP(A27,'Datos Personales'!$A:$M,3,FALSE) -> 495 | E27: =VLOOKUP(Tabla4[[#This Row],[ENFASIS]],Listas!$R$2:$S$8,2,0) -> ENFASIS EN ING. SOFT | F27: =VLOOKUP(A27,'Datos Personales'!A:M,8,0) -> 0 | G27: =VLOOKUP(A27,'Datos Personales'!A:M,9,0) -> danielssj88@gmail.com | H27: =VLOOKUP(A27,'Datos Personales'!A:M,5,FALSE) -> E | I27: =VLOOKUP(Tabla4[[#This Row],[CODIGO]],'ESTADOS ESTUDIANTES'!B:M,12,0) -> 2022-3 | J27: Investigación | K27: Model Transformation Chain to Manage peripherals in mobile devices | L27: Hector Arturo Florez Hernandez | N27: 44825 | S27: =IF(Tabla4[[#This Row],[FECHA DE ACEPTACION DEL GRUP. INV.]]="","",DATE(YEAR(Tabla4[[#This Row],[FECHA DE ACEPTACION DEL GRUP. INV.]])+2,MONTH(Tabla4[[#This Row],[FECHA DE ACEPTACION DEL GRUP. INV.]]),DAY(Tabla4[[#This Row],[FECHA DE ACEPTACION DEL GRUP. INV.]]))) | T27: =IF(Tabla4[[#This Row],[FECHA DE ACEPTACION DEL GRUP. INV.]]="","",IF(Tabla4[[#This Row],[FECHA DE VENCIMIENTO ANTE PROYECTO]]<TODAY(),"SÍ","NO")) | AJ27: =IFERROR(VLOOKUP(AI27,Listas!K:L,2,0),"") | AK27: =IFERROR(VLOOKUP(AJ27,Listas!L:M,2,0),"") | BC27: =BB27*(100%-AJ27) -> #VALUE! | BD27: =SUM(BC27,AK27) -> #VALUE! | BG27: =IF(OR(H27="A",$H27="D",$H27="P",$H27="V"),L27,"")
A28: 20162495018 | B28: =VLOOKUP(A28,'Datos Personales'!A:M,2,FALSE) -> VALENCIA MARTINEZ CAMILO ALEJANDRO | C28: =VLOOKUP(A28,'ESTADOS ESTUDIANTES'!B:L,11,0) -> 1070950958 | D28: =VLOOKUP(A28,'Datos Personales'!$A:$M,3,FALSE) -> 495 | E28: =VLOOKUP(Tabla4[[#This Row],[ENFASIS]],Listas!$R$2:$S$8,2,0) -> ENFASIS EN ING. SOFT | F28: =VLOOKUP(A28,'Datos Personales'!A:M,8,0) -> cavalenciam@udistrital.edu.co | G28: =VLOOKUP(A28,'Datos Personales'!A:M,9,0) -> kmilov@gmail.com | H28: =VLOOKUP(A28,'Datos Personales'!A:M,5,FALSE) -> E | I28: =VLOOKUP(Tabla4[[#This Row],[CODIGO]],'ESTADOS ESTUDIANTES'!B:M,12,0) -> 2023-3 | J28: Investigación | K28: Modelo de sistema multi-agente para la clasificación de recursos vinculados basados en niveles de confianza y mediante especificaciones Linked Open Data | L28: Paulo Alonso Gaona Garcia | N28: 44979 | O28: 2023 | P28: GIIRA | Q28: Paulo Alonso Gaona Garcia | S28: =IF(Tabla4[[#This Row],[FECHA DE ACEPTACION DEL GRUP. INV.]]="","",DATE(YEAR(Tabla4[[#This Row],[FECHA DE ACEPTACION DEL GRUP. INV.]])+2,MONTH(Tabla4[[#This Row],[FECHA DE ACEPTACION DEL GRUP. INV.]]),DAY(Tabla4[[#This Row],[FECHA DE ACEPTACION DEL GRUP. INV.]]))) | T28: =IF(Tabla4[[#This Row],[FECHA DE ACEPTACION DEL GRUP. INV.]]="","",IF(Tabla4[[#This Row],[FECHA DE VENCIMIENTO ANTE PROYECTO]]<TODAY(),"SÍ","NO")) | AA28: 45057 | AB28: 152 | AC28: B2 | AD28: 06/2023 | AE28: 45056 | AF28: Ontological model based on web of trust to analyze the use of resources in learning environment | AG28: ITECKNE Vol 14 No 1 (2017). | AH28: 2017 | AI28: Revista C | AJ28: =IFERROR(VLOOKUP(AI28,Listas!K:L,2,0),"") -> 0.4 | AK28: =IFERROR(VLOOKUP(AJ28,Listas!L:M,2,0),"") -> 20 | AL28: 45056 | AM28: 06/2023 | AN28: 45056 | AO28: Alejandro Paolo Daza Corredor | AP28: 45061 | AQ28: 45083 | AR28: 50 | AS28: 50 | AT28: Aprobado | AU28: Carlos Enrique Montenegro Marin | AV28: 45061 | AW28: 45083 | AX28: 50 | AY28: 50 | AZ28: Aprobado | BA28: 45083 | BB28: =IFERROR(AVERAGE(AR28,AS28,AX28,AY28),"") -> 50 | BC28: =BB28*(100%-AJ28) -> 30 | BD28: =SUM(BC28,AK28) -> 50 | BF28: SI | BG28: =IF(OR(H28="A",$H28="D",$H28="P",$H28="V"),L28,"")
A29: 20171195001 | B29: =VLOOKUP(A29,'Datos Personales'!A:M,2,FALSE) -> JOSE AGUSTIN AREVALO SILVA | C29: =VLOOKUP(A29,'ESTADOS ESTUDIANTES'!B:L,11,0) -> 79956049 | D29: =VLOOKUP(A29,'Datos Personales'!$A:$M,3,FALSE) -> 195 | E29: =VLOOKUP(Tabla4[[#This Row],[ENFASIS]],Listas!$R$2:$S$8,2,0) -> EN TELEINF. | F29: =VLOOKUP(A29,'Datos Personales'!A:M,8,0) -> jaarevalos@udistrital.edu.co | G29: =VLOOKUP(A29,'Datos Personales'!A:M,9,0) -> agustin.arevalo@gmail.com | H29: =VLOOKUP(A29,'Datos Personales'!A:M,5,FALSE) -> E | I29: =VLOOKUP(Tabla4[[#This Row],[CODIGO]],'ESTADOS ESTUDIANTES'!B:M,12,0) -> 2024-1 | J29: Investigación | K29: DESARROLLO DE UN PROTOTIPO DE SISTEMA PARA EL APOYO EN LA MOVILIDAD AUTÓNOMA DE PERSONAS INVIDENTES EN EXTERIORES | L29: Carlos Enrique Montenegro Marin | M29: Nancy Yaneth Gelvez | N29: 45218 | O29: 2023 | P29: GIIRA | Q29: Carlos Enrique Montenegro Marin | R29: 45219 | S29: =IF(Tabla4[[#This Row],[FECHA DE ACEPTACION DEL GRUP. INV.]]="","",DATE(YEAR(Tabla4[[#This Row],[FECHA DE ACEPTACION DEL GRUP. INV.]])+2,MONTH(Tabla4[[#This Row],[FECHA DE ACEPTACION DEL GRUP. INV.]]),DAY(Tabla4[[#This Row],[FECHA DE ACEPTACION DEL GRUP. INV.]]))) -> 45950 | T29: =IF(Tabla4[[#This Row],[FECHA DE ACEPTACION DEL GRUP. INV.]]="","",IF(Tabla4[[#This Row],[FECHA DE VENCIMIENTO ANTE PROYECTO]]<TODAY(),"SÍ","NO")) -> SÍ | W29: 15-2023 | AA29: 45167 | AB29: 104 | AC29: B1 | AD29: 002-2024 | AE29: 45343 | AF29: DESARROLLO DE UN PROTOTIPO DE SISTEMA PARA EL APOYO EN LA MOVILIDAD AUTÓNOMA DE PERSONAS INVIDENTES EN EXTERIORES. | AG29: 1era Conferencia Internacional de Innovación e Investigación FAEDIS | AI29: Ponencia | AJ29: =IFERROR(VLOOKUP(AI29,Listas!K:L,2,0),"") -> 0.2 | AK29: =IFERROR(VLOOKUP(AJ29,Listas!L:M,2,0),"") -> 10 | AL29: 45260 | AM29: 02/2024 | AN29: 45343 | AO29: Luz Helena Camargo | AR29: 50 | AS29: 50 | AT29: Aprobado | AU29: Paulo Alonso Gaona Garcia | AX29: 50 | AY29: 50 | AZ29: Aprobado | BA29: 45364 | BB29: 50 | BC29: =BB29*(100%-AJ29) -> 40 | BD29: =SUM(BC29,AK29) -> 50 | BG29: =IF(OR(H29="A",$H29="D",$H29="P",$H29="V"),L29,"")
A30: 20171495012 | B30: =VLOOKUP(A30,'Datos Personales'!A:M,2,FALSE) -> GONZALEZ ESCOBAR LEONARDO | C30: =VLOOKUP(A30,'ESTADOS ESTUDIANTES'!B:L,11,0) -> 86083193 | D30: =VLOOKUP(A30,'Datos Personales'!$A:$M,3,FALSE) -> 495 | E30: =VLOOKUP(Tabla4[[#This Row],[ENFASIS]],Listas!$R$2:$S$8,2,0) -> ENFASIS EN ING. SOFT | F30: =VLOOKUP(A30,'Datos Personales'!A:M,8,0) -> lgonzaleze@correo.udistrital.edu.co | G30: =VLOOKUP(A30,'Datos Personales'!A:M,9,0) -> leonardo.gonzalez.escobar@gmail.com | H30: =VLOOKUP(A30,'Datos Personales'!A:M,5,FALSE) -> X | I30: =VLOOKUP(Tabla4[[#This Row],[CODIGO]],'ESTADOS ESTUDIANTES'!B:M,12,0) -> 2020-3 | J30: Investigación | S30: =IF(Tabla4[[#This Row],[FECHA DE ACEPTACION DEL GRUP. INV.]]="","",DATE(YEAR(Tabla4[[#This Row],[FECHA DE ACEPTACION DEL GRUP. INV.]])+2,MONTH(Tabla4[[#This Row],[FECHA DE ACEPTACION DEL GRUP. INV.]]),DAY(Tabla4[[#This Row],[FECHA DE ACEPTACION DEL GRUP. INV.]]))) | T30: =IF(Tabla4[[#This Row],[FECHA DE ACEPTACION DEL GRUP. INV.]]="","",IF(Tabla4[[#This Row],[FECHA DE VENCIMIENTO ANTE PROYECTO]]<TODAY(),"SÍ","NO")) | AJ30: =IFERROR(VLOOKUP(AI30,Listas!K:L,2,0),"") | AK30: =IFERROR(VLOOKUP(AJ30,Listas!L:M,2,0),"") | BB30: =IFERROR(ROUND(AVERAGE(AY30,AX30,AS30,AR30),0),"") | BC30: =BB30*(100%-AJ30) -> #VALUE! | BD30: =SUM(BC30,AK30) -> #VALUE! | BG30: =IF(OR(H30="A",$H30="D",$H30="P",$H30="V"),L30,"")
A31: 20171495023 | B31: =VLOOKUP(A31,'Datos Personales'!A:M,2,FALSE) -> VELASQUEZ ARTUNDUAGA INGRID JULIETH | C31: =VLOOKUP(A31,'ESTADOS ESTUDIANTES'!B:L,11,0) -> 1024501542 | D31: =VLOOKUP(A31,'Datos Personales'!$A:$M,3,FALSE) -> 495 | E31: =VLOOKUP(Tabla4[[#This Row],[ENFASIS]],Listas!$R$2:$S$8,2,0) -> ENFASIS EN ING. SOFT | F31: =VLOOKUP(A31,'Datos Personales'!A:M,8,0) -> ijvelasqueza@correo.udistrital.edu.co | G31: =VLOOKUP(A31,'Datos Personales'!A:M,9,0) -> Ingridjulieth20@gmail.com | H31: =VLOOKUP(A31,'Datos Personales'!A:M,5,FALSE) -> X | I31: =VLOOKUP(Tabla4[[#This Row],[CODIGO]],'ESTADOS ESTUDIANTES'!B:M,12,0) -> 2021-3 | J31: Investigación | S31: =IF(Tabla4[[#This Row],[FECHA DE ACEPTACION DEL GRUP. INV.]]="","",DATE(YEAR(Tabla4[[#This Row],[FECHA DE ACEPTACION DEL GRUP. INV.]])+2,MONTH(Tabla4[[#This Row],[FECHA DE ACEPTACION DEL GRUP. INV.]]),DAY(Tabla4[[#This Row],[FECHA DE ACEPTACION DEL GRUP. INV.]]))) | T31: =IF(Tabla4[[#This Row],[FECHA DE ACEPTACION DEL GRUP. INV.]]="","",IF(Tabla4[[#This Row],[FECHA DE VENCIMIENTO ANTE PROYECTO]]<TODAY(),"SÍ","NO")) | AA31: 44468 | AB31: 131.75 | AC31: B1 | AJ31: =IFERROR(VLOOKUP(AI31,Listas!K:L,2,0),"") | AK31: =IFERROR(VLOOKUP(AJ31,Listas!L:M,2,0),"") | BB31: =IFERROR(ROUND(AVERAGE(AY31,AX31,AS31,AR31),0),"") | BC31: =BB31*(100%-AJ31) -> #VALUE! | BD31: =SUM(BC31,AK31) -> #VALUE! | BG31: =IF(OR(H31="A",$H31="D",$H31="P",$H31="V"),L31,"")
A32: 20172195007 | B32: =VLOOKUP(A32,'Datos Personales'!A:M,2,FALSE) -> DE LEON ARTURO VERBEL | C32: =VLOOKUP(A32,'ESTADOS ESTUDIANTES'!B:L,11,0) -> 1143355214 | D32: =VLOOKUP(A32,'Datos Personales'!$A:$M,3,FALSE) -> 195 | E32: =VLOOKUP(Tabla4[[#This Row],[ENFASIS]],Listas!$R$2:$S$8,2,0) -> EN TELEINF. | F32: =VLOOKUP(A32,'Datos Personales'!A:M,8,0) -> averbeldl@correo.udistrital.edu.co | G32: =VLOOKUP(A32,'Datos Personales'!A:M,9,0) -> arturo.verbel@gmail.com | H32: =VLOOKUP(A32,'Datos Personales'!A:M,5,FALSE) -> E | I32: =VLOOKUP(Tabla4[[#This Row],[CODIGO]],'ESTADOS ESTUDIANTES'!B:M,12,0) -> 2022-1 | J32: Investigación | K32: ACTUALIZACION DE TODOS LOS CAMINOS MAS CORTOS EN GRAFOS DINAMICOS CON INSERCION DE ARCOS | L32: Sergio Rojas Galeano | Q32: Marco Aurelio Alzate | R32: 43579 | S32: =IF(Tabla4[[#This Row],[FECHA DE ACEPTACION DEL GRUP. INV.]]="","",DATE(YEAR(Tabla4[[#This Row],[FECHA DE ACEPTACION DEL GRUP. INV.]])+2,MONTH(Tabla4[[#This Row],[FECHA DE ACEPTACION DEL GRUP. INV.]]),DAY(Tabla4[[#This Row],[FECHA DE ACEPTACION DEL GRUP. INV.]]))) -> 44310 | T32: =IF(Tabla4[[#This Row],[FECHA DE ACEPTACION DEL GRUP. INV.]]="","",IF(Tabla4[[#This Row],[FECHA DE VENCIMIENTO ANTE PROYECTO]]<TODAY(),"SÍ","NO")) -> SÍ | AA32: 44103 | AB32: 91.3 | AC32: B1 | AD32: 12-2022 | AE32: 44706 | AJ32: =IFERROR(VLOOKUP(AI32,Listas!K:L,2,0),"") | AK32: =IFERROR(VLOOKUP(AJ32,Listas!L:M,2,0),"") | AL32: 44483 | AM32: 14-2020 | AN32: 44497 | AO32: MARCO AURELIO ALZATE | AP32: 44497 | AQ32: 44539 | AR32: 50 | AS32: 50 | AT32: Meritorio | AU32: LUIS CASTILLO | AV32: 44497 | AW32: 44532 | AX32: 50 | AY32: 50 | AZ32: Meritorio | BA32: 44610 | BB32: =IFERROR(ROUND(AVERAGE(AY32,AX32,AS32,AR32),0),"") -> 50 | BC32: =BB32*(100%-AJ32) -> #VALUE! | BD32: =SUM(BC32,AK32) -> #VALUE! | BG32: =IF(OR(H32="A",$H32="D",$H32="P",$H32="V"),L32,"")
A33: 20172395014 | B33: =VLOOKUP(A33,'Datos Personales'!A:M,2,FALSE) -> PATIÑO RIVERA HÉCTOR RICARDO | C33: =VLOOKUP(A33,'ESTADOS ESTUDIANTES'!B:L,11,0) -> 1015411098 | D33: =VLOOKUP(A33,'Datos Personales'!$A:$M,3,FALSE) -> 395 | E33: =VLOOKUP(Tabla4[[#This Row],[ENFASIS]],Listas!$R$2:$S$8,2,0) -> ENFASIS EN GEOMATICA | F33: =VLOOKUP(A33,'Datos Personales'!A:M,8,0) -> hrpatinor@udistrital.edu.co | G33: =VLOOKUP(A33,'Datos Personales'!A:M,9,0) -> hectorpatino24@gmail.com | H33: =VLOOKUP(A33,'Datos Personales'!A:M,5,FALSE) -> E | I33: =VLOOKUP(Tabla4[[#This Row],[CODIGO]],'ESTADOS ESTUDIANTES'!B:M,12,0) -> 2024-1 | J33: Investigación | K33: Diseño de un prototipo para clasificación automática de imágenes satelitales mediante algoritmos de machine learning | L33: Alvaro Enrique Ortiz Davila | N33: 45170 | O33: 2023 | P33: NIDE | Q33: Alvaro Enrique Ortiz Davila | R33: 45170 | S33: =IF(Tabla4[[#This Row],[FECHA DE ACEPTACION DEL GRUP. INV.]]="","",DATE(YEAR(Tabla4[[#This Row],[FECHA DE ACEPTACION DEL GRUP. INV.]])+2,MONTH(Tabla4[[#This Row],[FECHA DE ACEPTACION DEL GRUP. INV.]]),DAY(Tabla4[[#This Row],[FECHA DE ACEPTACION DEL GRUP. INV.]]))) -> 45901 | T33: =IF(Tabla4[[#This Row],[FECHA DE ACEPTACION DEL GRUP. INV.]]="","",IF(Tabla4[[#This Row],[FECHA DE VENCIMIENTO ANTE PROYECTO]]<TODAY(),"SÍ","NO")) -> SÍ | W33: 12-2023 | Y33: 43964 | Z33: 86.96 | AA33: 45323 | AB33: 141 | AC33: B2 | AF33: Development of a prototype system to support the autonomous mobility of blind people outdoors. | AH33: 2-11-2023 | AI33: Ponencia | AJ33: =IFERROR(VLOOKUP(AI33,Listas!K:L,2,0),"") -> 0.2 | AK33: =IFERROR(VLOOKUP(AJ33,Listas!L:M,2,0),"") -> 10 | AL33: 45322 | AM33: 002-2024 | AN33: 45343 | AO33: Ruben Javier Medina Daza | AP33: 45337 | AQ33: 45363 | AR33: 41 | AS33: 41 | AT33: Aprobado | AU33: William Barragan Zaque | AV33: 45337 | AW33: 45365 | AX33: 50 | AY33: 50 | AZ33: Aprobado | BA33: 45350 | BB33: =IFERROR(AVERAGE(AR33,AS33,AX33,AY33),"") -> 45.5 | BC33: =BB33*(100%-AJ33) -> 36.4 | BD33: =SUM(BC33,AK29) -> 46.4 | BG33: =IF(OR(H33="A",$H33="D",$H33="P",$H33="V"),L33,"")
A34: 20172495009 | B34: =VLOOKUP(A34,'ESTADOS ESTUDIANTES'!B:L,2,0) -> GONZALEZ GONZALEZ DIANA SOFIA | C34: =VLOOKUP(A34,'ESTADOS ESTUDIANTES'!B:L,11,0) -> 1015403717 | D34: =VLOOKUP(A34,'ESTADOS ESTUDIANTES'!B:L,3,0) -> 495 | E34: =VLOOKUP(Tabla4[[#This Row],[ENFASIS]],Listas!$R$2:$S$8,2,0) -> ENFASIS EN ING. SOFT | F34: =VLOOKUP(A34,'ESTADOS ESTUDIANTES'!B:L,8,0) -> dsgonzalezg@udistrital.edu.co | G34: =VLOOKUP(A34,'ESTADOS ESTUDIANTES'!B:L,9,0) -> dsofiagonzalezg@gmail.com | H34: =VLOOKUP(A34,'ESTADOS ESTUDIANTES'!B:L,5,0) -> E | I34: =VLOOKUP(Tabla4[[#This Row],[CODIGO]],'ESTADOS ESTUDIANTES'!B:M,12,0) -> 2024-1 | J34: Investigación | K34: MODELO DE ASEGURAMIENTO DE LA CALIDAD DE DATOS FORESTALES EN EL MARCO DE LOS OBJETIVOS DE DESARROLLO SOSTENIBLE | L34: Beitmantt Cardenas | N34: 43074 | O34: 2017 | P34: GICOGE | Q34: Victor Hugo Medina Garcia | R34: 45238 | S34: =IF(Tabla4[[#This Row],[FECHA DE ACEPTACION DEL GRUP. INV.]]="","",DATE(YEAR(Tabla4[[#This Row],[FECHA DE ACEPTACION DEL GRUP. INV.]])+2,MONTH(Tabla4[[#This Row],[FECHA DE ACEPTACION DEL GRUP. INV.]]),DAY(Tabla4[[#This Row],[FECHA DE ACEPTACION DEL GRUP. INV.]]))) -> 45969 | T34: =IF(Tabla4[[#This Row],[FECHA DE ACEPTACION DEL GRUP. INV.]]="","",IF(Tabla4[[#This Row],[FECHA DE VENCIMIENTO ANTE PROYECTO]]<TODAY(),"SÍ","NO")) -> SÍ | W34: 017-2023 | Y34: 44680 | Z34: 141 | AA34: 45323 | AB34: 141 | AC34: B2 | AD34: 017-2023 | AE34: 45245 | AF34: Gestión total de la calidad de datos (TDQM) aplicada a la evaluación de calidad de datos abiertos de superficie de bosque natural de Colombia | AG34: Iberian Journal of Information Systems and Technologies-RISTI | AH34: 2020 | AI34: Revista B | AJ34: =IFERROR(VLOOKUP(AI34,Listas!K:L,2,0),"") -> 0.6 | AK34: =IFERROR(VLOOKUP(AJ34,Listas!L:M,2,0),"") -> 30 | AL34: 45240 | AM34: 17-2024 | AN34: 45245 | AO34: Victor Hugo Medina Garcia | AP34: 45337 | AQ34: 45348 | AR34: 44 | AS34: 39 | AT34: Aprobado | AU34: Alvaro Espinel Ortega | AV34: 45337 | AW34: 45348 | AX34: 46 | AY34: 41 | AZ34: Aprobado | BA34: 26-2-24 | BB34: =IFERROR(AVERAGE(AR34,AS34,AX34,AY34),"") -> 41.333333 | BC34: =BB34*(100%-AJ34) -> 16.533333 | BD34: =SUM(BC34,AK34) -> 46.533333
A35: 20181195008 | B35: =VLOOKUP(A35,'Datos Personales'!A:M,2,FALSE) -> PEÑA ARISMENDI SANTIAGO ANDRES | C35: =VLOOKUP(A35,'ESTADOS ESTUDIANTES'!B:L,11,0) -> 1026284597 | D35: =VLOOKUP(A35,'Datos Personales'!$A:$M,3,FALSE) -> 195 | E35: =VLOOKUP(Tabla4[[#This Row],[ENFASIS]],Listas!$R$2:$S$8,2,0) -> EN TELEINF. | F35: =VLOOKUP(A35,'Datos Personales'!A:M,8,0) -> saapenaa@udistrital.edu.co | G35: =VLOOKUP(A35,'Datos Personales'!A:M,9,0) -> saapenaa@correo.udistrital.edu.co | H35: =VLOOKUP(A35,'Datos Personales'!A:M,5,FALSE) -> E | I35: =VLOOKUP(Tabla4[[#This Row],[CODIGO]],'ESTADOS ESTUDIANTES'!B:M,12,0) -> 2024-3 | J35: Investigación | K35: ALGORITMO PARA LA DETECCIÓN DE CRISIS EPILÉPTICAS APLICABLE A REDES DE IOT | L35: Octavio Jose Salcedo Parra | M35: Laura Victoria Guio | N35: 45364 | O35: 2024 | P35: INTERNET INTELIGENTE | Q35: Octavio Jose Salcedo Parra | R35: 45365 | S35: =IF(Tabla4[[#This Row],[FECHA DE ACEPTACION DEL GRUP. INV.]]="","",DATE(YEAR(Tabla4[[#This Row],[FECHA DE ACEPTACION DEL GRUP. INV.]])+2,MONTH(Tabla4[[#This Row],[FECHA DE ACEPTACION DEL GRUP. INV.]]),DAY(Tabla4[[#This Row],[FECHA DE ACEPTACION DEL GRUP. INV.]]))) -> 46095 | T35: =IF(Tabla4[[#This Row],[FECHA DE ACEPTACION DEL GRUP. INV.]]="","",IF(Tabla4[[#This Row],[FECHA DE VENCIMIENTO ANTE PROYECTO]]<TODAY(),"SÍ","NO")) -> SÍ | U35: NO | W35: 04/2024 | Y35: 43964 | Z35: 88.7 | AA35: 45323 | AB35: 133 | AC35: B1 | AD35: 08/2024 | AE35: 45434 | AF35: Desarrollo de un sistema de IoT con Machine Learning para la detección temprana de crisis epilépticas | AG35: SAFARIS - TECH International 2024 | AH35: 10/5/2024 | AI35: Ponencia | AJ35: =IFERROR(VLOOKUP(AI35,Listas!K:L,2,0),"") -> 0.2 | AK35: =IFERROR(VLOOKUP(AJ35,Listas!L:M,2,0),"") -> 10 | AL35: 45432 | AM35: 008/2024 | AN35: 45434 | AO35: Lilia Edith Aparicio Pico | AU35: Cesar Augusto Hernandez Suarez | BB35: =IFERROR(AVERAGE(AR35,AS35,AX35,AY35),"") | BC35: =BB35*(100%-AJ35) -> #VALUE! | BD35: =SUM(BC35,AK35) -> #VALUE! | BG35: =SI(O(G40="A";$G40="D";$G40="P";$G40="V");J40;"")
A36: 20181195010 | B36: =VLOOKUP(A36,'ESTADOS ESTUDIANTES'!B:L,2,0) -> ROMERO ORTEGA RAUL | C36: =VLOOKUP(A36,'ESTADOS ESTUDIANTES'!B:L,11,0) -> 80205440 | D36: =VLOOKUP(A36,'Datos Personales'!$A:$M,3,FALSE) -> 195 | E36: =VLOOKUP(Tabla4[[#This Row],[ENFASIS]],Listas!$R$2:$S$8,2,0) -> EN TELEINF. | F36: =VLOOKUP(A36,'Datos Personales'!A:M,8,0) -> rromeroo@udistrital.edu.co | G36: =VLOOKUP(A36,'Datos Personales'!A:M,9,0) -> rromeroo7519@gmail.com | H36: =VLOOKUP(A36,'Datos Personales'!A:M,5,FALSE) -> E | I36: =VLOOKUP(Tabla4[[#This Row],[CODIGO]],'ESTADOS ESTUDIANTES'!B:M,12,0) -> 2024-3 | J36: Investigación | K36: MODELO PARA CLASIFICACIÓN DE PRECIPITACIONES ESTRATIFORMES Y CONVECTIVAS EN ZONA ECUATORIAL USANDO DATOS DE RADARES METEOROLÓGICOS. | L36: Cesar Andrey Perdomo Charry | N36: 45434 | O36: 2024 | P36: LASER | Q36: Ernesto Gomez Vargas | R36: 45434 | S36: =IF(Tabla4[[#This Row],[FECHA DE ACEPTACION DEL GRUP. INV.]]="","",DATE(YEAR(Tabla4[[#This Row],[FECHA DE ACEPTACION DEL GRUP. INV.]])+2,MONTH(Tabla4[[#This Row],[FECHA DE ACEPTACION DEL GRUP. INV.]]),DAY(Tabla4[[#This Row],[FECHA DE ACEPTACION DEL GRUP. INV.]]))) -> 46164 | T36: =IF(Tabla4[[#This Row],[FECHA DE ACEPTACION DEL GRUP. INV.]]="","",IF(Tabla4[[#This Row],[FECHA DE VENCIMIENTO ANTE PROYECTO]]<TODAY(),"SÍ","NO")) -> SÍ | U36: NO | W36: 008-24 | Y36: 43809 | Z36: 85.22 | AA36: 45531 | AB36: 92 | AC36: B1 | AD36: 09-2024 | AE36: 45448 | AF36: Classification of Stratiform and Convective Precipitation in the Equatorial Zone Using Meteorological Radar Data | AG36: Revista de Ingeniería, Universidad Distrital Francisco José de Caldas CATEGORIA B | AH36: 30-1-2025 | AI36: Revista B | AJ36: =IFERROR(VLOOKUP(AI36,Listas!K:L,2,0),"") -> 0.6 | AK36: =IFERROR(VLOOKUP(AJ36,Listas!L:M,2,0),"") -> 30 | AL36: 45427 | AM36: 008/2024 | AN36: 45448 | AO36: Ernesto Gomez Vargas | AP36: 45499 | AQ36: 45524 | AR36: 44 | AS36: 40 | AT36: Aprobado | AU36: Javier Moncada | AV36: 45499 | AW36: 45524 | AX36: 50 | AY36: 50 | AZ36: Aprobado | BA36: 45524 | BB36: =IFERROR(AVERAGE(AR36,AS36,AX36,AY36),"") -> 46 | BC36: =BB36*(100%-AJ36) -> 18.4 | BD36: =SUM(BC36,AK36) -> 48.4 | BG36: =SI(O(G41="A";$G41="D";$G41="P";$G41="V");J41;"")
A37: 20181395006 | B37: =VLOOKUP(A37,'Datos Personales'!A:M,2,FALSE) -> ROBLES MONDRAGON DUVAN ALEXANDER | C37: =VLOOKUP(A37,'ESTADOS ESTUDIANTES'!B:L,11,0) -> 1010191260 | D37: =VLOOKUP(A37,'Datos Personales'!$A:$M,3,FALSE) -> 395 | E37: =VLOOKUP(Tabla4[[#This Row],[ENFASIS]],Listas!$R$2:$S$8,2,0) -> ENFASIS EN GEOMATICA | F37: =VLOOKUP(A37,'Datos Personales'!A:M,8,0) -> daroblesm@correo.udistrital.edu.co | G37: =VLOOKUP(A37,'Datos Personales'!A:M,9,0) -> dalexrobles@gmail.com | H37: =VLOOKUP(A37,'Datos Personales'!A:M,5,FALSE) -> E | I37: =VLOOKUP(Tabla4[[#This Row],[CODIGO]],'ESTADOS ESTUDIANTES'!B:M,12,0) -> 2022-3 | J37: Investigación | K37: EXTRACCION DE CONTEXTO GEOGRAFICO A PARTIR DE NLP PARA INFORMACION DE TRANSITO EN REDES SOCIALES | L37: Cesar Andrey Perdomo Charry | N37: 43672 | O37: 2019 | P37: LASER LAMIC | Q37: Ernesto Gomez Vargas | R37: 43672 | S37: =IF(Tabla4[[#This Row],[FECHA DE ACEPTACION DEL GRUP. INV.]]="","",DATE(YEAR(Tabla4[[#This Row],[FECHA DE ACEPTACION DEL GRUP. INV.]])+2,MONTH(Tabla4[[#This Row],[FECHA DE ACEPTACION DEL GRUP. INV.]]),DAY(Tabla4[[#This Row],[FECHA DE ACEPTACION DEL GRUP. INV.]]))) -> 44403 | T37: =IF(Tabla4[[#This Row],[FECHA DE ACEPTACION DEL GRUP. INV.]]="","",IF(Tabla4[[#This Row],[FECHA DE VENCIMIENTO ANTE PROYECTO]]<TODAY(),"SÍ","NO")) -> SÍ | W37: 13-2019 | AA37: 44468 | AB37: 88.75 | AC37: B1 | AD37: 10-2021 | AE37: 44573 | AI37: Revista B | AJ37: =IFERROR(VLOOKUP(AI37,Listas!K:L,2,0),"") -> 0.6 | AK37: =IFERROR(VLOOKUP(AJ37,Listas!L:M,2,0),"") -> 30 | AL37: 44512 | AM37: 13-2021 | AN37: 44512 | AO37: Jorge Mario Calvo | AP37: 44512 | AQ37: 44545 | AR37: 44 | AS37: 42 | AT37: Aprobado | AU37: Marco Aurelio Alzate | AV37: 44512 | AW37: 44573 | AX37: 47 | AY37: 48 | AZ37: MERITORIO | BA37: 44573 | BB37: =IFERROR(ROUND(AVERAGE(AY37,AX37,AS37,AR37),0),"") -> 45 | BC37: =BB37*(100%-AJ37) -> 18 | BD37: =SUM(BC37,AK37) -> 48 | BE37: SI | BG37: =IF(OR(H37="A",$H37="D",$H37="P",$H37="V"),L37,"")
A38: 20181495001 | B38: =VLOOKUP(A38,'Datos Personales'!A:M,2,FALSE) -> BARON JEREZ LADY MAYERLY | C38: =VLOOKUP(A38,'ESTADOS ESTUDIANTES'!B:L,11,0) -> 53153876 | D38: =VLOOKUP(A38,'Datos Personales'!$A:$M,3,FALSE) -> 495 | E38: =VLOOKUP(Tabla4[[#This Row],[ENFASIS]],Listas!$R$2:$S$8,2,0) -> ENFASIS EN ING. SOFT | F38: =VLOOKUP(A38,'Datos Personales'!A:M,8,0) -> lmbaronj@udistrital.edu.co | G38: =VLOOKUP(A38,'Datos Personales'!A:M,9,0) -> ladybaronj@gmail.com | H38: =VLOOKUP(A38,'Datos Personales'!A:M,5,FALSE) -> X | I38: =VLOOKUP(Tabla4[[#This Row],[CODIGO]],'ESTADOS ESTUDIANTES'!B:M,12,0) -> 2024-1 | J38: Investigación | S38: =IF(Tabla4[[#This Row],[FECHA DE ACEPTACION DEL GRUP. INV.]]="","",DATE(YEAR(Tabla4[[#This Row],[FECHA DE ACEPTACION DEL GRUP. INV.]])+2,MONTH(Tabla4[[#This Row],[FECHA DE ACEPTACION DEL GRUP. INV.]]),DAY(Tabla4[[#This Row],[FECHA DE ACEPTACION DEL GRUP. INV.]]))) | T38: =IF(Tabla4[[#This Row],[FECHA DE ACEPTACION DEL GRUP. INV.]]="","",IF(Tabla4[[#This Row],[FECHA DE VENCIMIENTO ANTE PROYECTO]]<TODAY(),"SÍ","NO")) | AA38: 44510 | AB38: 68.22 | AC38: A2 | AJ38: =IFERROR(VLOOKUP(AI38,Listas!K:L,2,0),"") | AK38: =IFERROR(VLOOKUP(AJ38,Listas!L:M,2,0),"") | BB38: =IFERROR(AVERAGE(AR38,AS38,AX38,AY38),"") | BC38: =BB38*(100%-AJ38) -> #VALUE! | BD38: =SUM(BC38,AK38) -> #VALUE! | BG38: =IF(OR(H38="A",$H38="D",$H38="P",$H38="V"),L38,"")
A39: 20181495008 | B39: =VLOOKUP(A39,'Datos Personales'!A:M,2,FALSE) -> CORREA ALBA KAREN MICHELLE | C39: =VLOOKUP(A39,'ESTADOS ESTUDIANTES'!B:L,11,0) -> 1026285169 | D39: =VLOOKUP(A39,'Datos Personales'!$A:$M,3,FALSE) -> 495 | E39: =VLOOKUP(Tabla4[[#This Row],[ENFASIS]],Listas!$R$2:$S$8,2,0) -> ENFASIS EN ING. SOFT | F39: =VLOOKUP(A39,'Datos Personales'!A:M,8,0) -> kmcorreaa@udistrital.edu.co | G39: =VLOOKUP(A39,'Datos Personales'!A:M,9,0) -> karencorrea93@hotmail.com | H39: =VLOOKUP(A39,'Datos Personales'!A:M,5,FALSE) -> X | I39: =VLOOKUP(Tabla4[[#This Row],[CODIGO]],'ESTADOS ESTUDIANTES'!B:M,12,0) -> 2020-3 | S39: =IF(Tabla4[[#This Row],[FECHA DE ACEPTACION DEL GRUP. INV.]]="","",DATE(YEAR(Tabla4[[#This Row],[FECHA DE ACEPTACION DEL GRUP. INV.]])+2,MONTH(Tabla4[[#This Row],[FECHA DE ACEPTACION DEL GRUP. INV.]]),DAY(Tabla4[[#This Row],[FECHA DE ACEPTACION DEL GRUP. INV.]]))) | T39: =IF(Tabla4[[#This Row],[FECHA DE ACEPTACION DEL GRUP. INV.]]="","",IF(Tabla4[[#This Row],[FECHA DE VENCIMIENTO ANTE PROYECTO]]<TODAY(),"SÍ","NO")) | AJ39: =IFERROR(VLOOKUP(AI39,Listas!K:L,2,0),"") | AK39: =IFERROR(VLOOKUP(AJ39,Listas!L:M,2,0),"") | BB39: =IFERROR(ROUND(AVERAGE(AY39,AX39,AS39,AR39),0),"") | BC39: =BB39*(100%-AJ39) -> #VALUE! | BD39: =SUM(BC39,AK39) -> #VALUE! | BG39: =IF(OR(H39="A",$H39="D",$H39="P",$H39="V"),L39,"")
A40: 20182195004 | B40: =VLOOKUP(A40,'Datos Personales'!A:M,2,FALSE) -> RAMÍREZ JEREZ LUIS EDUARDO | C40: =VLOOKUP(A40,'ESTADOS ESTUDIANTES'!B:L,11,0) -> 1014184238 | D40: =VLOOKUP(A40,'Datos Personales'!$A:$M,3,FALSE) -> 195 | E40: =VLOOKUP(Tabla4[[#This Row],[ENFASIS]],Listas!$R$2:$S$8,2,0) -> EN TELEINF. | F40: =VLOOKUP(A40,'Datos Personales'!A:M,8,0) -> leramirezj@udistrital.edu.co | G40: =VLOOKUP(A40,'Datos Personales'!A:M,9,0) -> leramirezj182@gmail.com | H40: =VLOOKUP(A40,'Datos Personales'!A:M,5,FALSE) -> X | I40: =VLOOKUP(Tabla4[[#This Row],[CODIGO]],'ESTADOS ESTUDIANTES'!B:M,12,0) -> 2024-1 | J40: Investigación | K40: DESARROLLO DE UN PROTOTIPO DE SMART CONTRACT BAJO ARQUITECTURA DE BLOCKCHAIN PARA LOS PROCESOS DE COMPRA DE EQUIPOS ROBUSTOS DE LA UNIVERSIDAD DISTRITAL FRANCISCO JOSE DE CALDAS | L40: Roberto Ferro Escobar | O40: 2019 | P40: LIDER | Q40: Roberto Ferro Escobar | R40: 43635 | S40: =IF(Tabla4[[#This Row],[FECHA DE ACEPTACION DEL GRUP. INV.]]="","",DATE(YEAR(Tabla4[[#This Row],[FECHA DE ACEPTACION DEL GRUP. INV.]])+2,MONTH(Tabla4[[#This Row],[FECHA DE ACEPTACION DEL GRUP. INV.]]),DAY(Tabla4[[#This Row],[FECHA DE ACEPTACION DEL GRUP. INV.]]))) -> 44366 | T40: =IF(Tabla4[[#This Row],[FECHA DE ACEPTACION DEL GRUP. INV.]]="","",IF(Tabla4[[#This Row],[FECHA DE VENCIMIENTO ANTE PROYECTO]]<TODAY(),"SÍ","NO")) -> SÍ | U40: NO | W40: 10-2019 | AA40: 44097 | AB40: 81.31 | AC40: B1 | AJ40: =IFERROR(VLOOKUP(AI40,Listas!K:L,2,0),"") | AK40: =IFERROR(VLOOKUP(AJ40,Listas!L:M,2,0),"") | BB40: =IFERROR(AVERAGE(AR40,AS40,AX40,AY40),"") | BC40: =BB40*(100%-AJ40) -> #VALUE! | BD40: =SUM(BC40,AK40) -> #VALUE! | BG40: =IF(OR(H40="A",$H40="D",$H40="P",$H40="V"),L40,"")
A41: 20182195007 | B41: =VLOOKUP(A41,'Datos Personales'!A:M,2,FALSE) -> MERIÑO SUAREZ IVET PATRICIA | C41: =VLOOKUP(A41,'ESTADOS ESTUDIANTES'!B:L,11,0) -> 45716000 | D41: =VLOOKUP(A41,'Datos Personales'!$A:$M,3,FALSE) -> 195 | E41: =VLOOKUP(Tabla4[[#This Row],[ENFASIS]],Listas!$R$2:$S$8,2,0) -> EN TELEINF. | F41: =VLOOKUP(A41,'Datos Personales'!A:M,8,0) -> ipmerinos@udistrital.edu.co | G41: =VLOOKUP(A41,'Datos Personales'!A:M,9,0) -> ivetpatricia@hotmail.com | H41: =VLOOKUP(A41,'Datos Personales'!A:M,5,FALSE) -> X | I41: =VLOOKUP(Tabla4[[#This Row],[CODIGO]],'ESTADOS ESTUDIANTES'!B:M,12,0) -> 2024-3 | J41: Investigación | K41: DISEÑO DE UN MODELO DE GOBIERNO DE TECNOLOGIAS DE LA INFORMACION (TI), PARA INSTITUCIONES DE EDUCACION SUPERIOR (IES). CASO DE ESTUDIO: UNIVERSIDAD DISTRITAL FRANCISCO JOSE DE CALDAS | L41: Roberto Ferro Escobar | N41: 43628 | O41: 2019 | P41: LIDER | Q41: Roberto Ferro Escobar | R41: 43628 | S41: =IF(Tabla4[[#This Row],[FECHA DE ACEPTACION DEL GRUP. INV.]]="","",DATE(YEAR(Tabla4[[#This Row],[FECHA DE ACEPTACION DEL GRUP. INV.]])+2,MONTH(Tabla4[[#This Row],[FECHA DE ACEPTACION DEL GRUP. INV.]]),DAY(Tabla4[[#This Row],[FECHA DE ACEPTACION DEL GRUP. INV.]]))) -> 44359 | T41: =IF(Tabla4[[#This Row],[FECHA DE ACEPTACION DEL GRUP. INV.]]="","",IF(Tabla4[[#This Row],[FECHA DE VENCIMIENTO ANTE PROYECTO]]<TODAY(),"SÍ","NO")) -> SÍ | U41: NO | W41: 09-2019 | AA41: 44097 | AB41: 90.65 | AC41: B1 | AJ41: =IFERROR(VLOOKUP(AI41,Listas!K:L,2,0),"") | AK41: =IFERROR(VLOOKUP(AJ41,Listas!L:M,2,0),"") | BB41: =IFERROR(AVERAGE(AR41,AS41,AX41,AY41),"") | BC41: =BB41*(100%-AJ41) -> #VALUE! | BD41: =SUM(BC41,AK41) -> #VALUE! | BG41: =IF(OR(H41="A",$H41="D",$H41="P",$H41="V"),L41,"")
A42: 20182395005 | B42: =VLOOKUP(A42,'Datos Personales'!A:M,2,FALSE) -> GALINDO AMBUILA JHON ALEXANDER | C42: =VLOOKUP(A42,'ESTADOS ESTUDIANTES'!B:L,11,0) -> 1010208668 | D42: =VLOOKUP(A42,'Datos Personales'!$A:$M,3,FALSE) -> 395 | E42: =VLOOKUP(Tabla4[[#This Row],[ENFASIS]],Listas!$R$2:$S$8,2,0) -> ENFASIS EN GEOMATICA | F42: =VLOOKUP(A42,'Datos Personales'!A:M,8,0) -> jagalindoa@udistrital.edu.co | G42: =VLOOKUP(A42,'Datos Personales'!A:M,9,0) -> jagalindoa@correo.udistrital.edu.co | H42: =VLOOKUP(A42,'Datos Personales'!A:M,5,FALSE) -> E | I42: =VLOOKUP(Tabla4[[#This Row],[CODIGO]],'ESTADOS ESTUDIANTES'!B:M,12,0) -> 2024-3 | J42: Investigación | K42: Propuesta metodologica Para La Recoleccion De Informacion Para El Catastro Multiproposito conforme al Modelo LADM-COL | L42: Alvaro Enrique Ortiz Davila | N42: 45456 | O42: 2024 | P42: NIDE | Q42: Alvaro Enrique Ortiz Davila | S42: =IF(Tabla4[[#This Row],[FECHA DE ACEPTACION DEL GRUP. INV.]]="","",DATE(YEAR(Tabla4[[#This Row],[FECHA DE ACEPTACION DEL GRUP. INV.]])+2,MONTH(Tabla4[[#This Row],[FECHA DE ACEPTACION DEL GRUP. INV.]]),DAY(Tabla4[[#This Row],[FECHA DE ACEPTACION DEL GRUP. INV.]]))) | T42: =IF(Tabla4[[#This Row],[FECHA DE ACEPTACION DEL GRUP. INV.]]="","",IF(Tabla4[[#This Row],[FECHA DE VENCIMIENTO ANTE PROYECTO]]<TODAY(),"SÍ","NO")) | U42: NO | AA42: 45586 | AB42: Instituto Colombo. | AC42: B1 | AD42: 015/2024 | AE42: 45595 | AF42: Geographic Information Management Applied to Land Administration in Colombia Through the Use of Free Software Tools | AG42: Applied Computer Sciences in Engineering 11th Workshop on Engineering Applications, WEA 2024, Barranquilla, Colombia, October 23–25, 2024, Proceedings, Part II ISBN 978-3-031-74598-0 | AH42: 2024 | AI42: capítulo de un libro | AJ42: =IFERROR(VLOOKUP(AI42,Listas!K:L,2,0),"") -> 0.6 | AK42: =IFERROR(VLOOKUP(AJ42,Listas!L:M,2,0),"") -> 30 | AL42: 45595 | AM42: 015/2024 | AN42: 45595 | AO42: Hector Javier Fuentes Lopez | AU42: Miriam Rivas | BB42: =IFERROR(AVERAGE(AR42,AS42,AX42,AY42),"") | BC42: =BB42*(100%-AJ42) -> #VALUE! | BD42: =SUM(BC42,AK42) -> #VALUE! | BG42: =IF(OR(H42="A",$H42="D",$H42="P",$H42="V"),L42,"")
A43: 20182395007 | B43: =VLOOKUP(A43,'Datos Personales'!A:M,2,FALSE) -> HURTADO VÁSQUEZ CRISTIAN CAMILO | C43: =VLOOKUP(A43,'ESTADOS ESTUDIANTES'!B:L,11,0) -> 1026269815 | D43: =VLOOKUP(A43,'Datos Personales'!$A:$M,3,FALSE) -> 395 | E43: =VLOOKUP(Tabla4[[#This Row],[ENFASIS]],Listas!$R$2:$S$8,2,0) -> ENFASIS EN GEOMATICA | F43: =VLOOKUP(A43,'Datos Personales'!A:M,8,0) -> cchurtadov@udistrital.edu.co | G43: =VLOOKUP(A43,'Datos Personales'!A:M,9,0) -> cchurtadov@udistrital.edu.co | H43: =VLOOKUP(A43,'Datos Personales'!A:M,5,FALSE) -> X | I43: =VLOOKUP(Tabla4[[#This Row],[CODIGO]],'ESTADOS ESTUDIANTES'!B:M,12,0) -> 2026-1 | J43: Investigación | K43: Modelado Predictivo de la Incidencia del Deterioro del Arbolado Urbano con Aprendizaje Automático y GIS: Implementación de Servicios Geográficos Web para una Zonificación de Manejo para la Ciudad de Cali - Colombia | L43: Max Alejandro Triana Góme | N43: 45581 | O43: 2024 | P43: PROPROBOS | Q43: Jaime Alberto Moreno Gutierrez | R43: 45580 | S43: =IF(Tabla4[[#This Row],[FECHA DE ACEPTACION DEL GRUP. INV.]]="","",DATE(YEAR(Tabla4[[#This Row],[FECHA DE ACEPTACION DEL GRUP. INV.]])+2,MONTH(Tabla4[[#This Row],[FECHA DE ACEPTACION DEL GRUP. INV.]]),DAY(Tabla4[[#This Row],[FECHA DE ACEPTACION DEL GRUP. INV.]]))) -> 46310 | T43: =IF(Tabla4[[#This Row],[FECHA DE ACEPTACION DEL GRUP. INV.]]="","",IF(Tabla4[[#This Row],[FECHA DE VENCIMIENTO ANTE PROYECTO]]<TODAY(),"SÍ","NO")) -> NO | U43: NO | X43: Tesis 2 | Y43: 43977 | Z43: 66.09 | AA43: 44299 | AB43: 66 | AC43: A2 | BB43: =IFERROR(AVERAGE(AR43,AS43,AX43,AY43),"") | BC43: =(BB43*0.8)/10 -> #VALUE! | BD43: =SUM(BC43,AK43) -> #VALUE! | BG43: =IF(OR(H43="A",$H43="D",$H43="P",$H43="V"),L43,"")
A44: 20182395011 | B44: =VLOOKUP(A44,'Datos Personales'!A:M,2,FALSE) -> MORENO GAMA JUAN MANUEL | C44: =VLOOKUP(A44,'ESTADOS ESTUDIANTES'!B:L,11,0) -> 1018484572 | D44: =VLOOKUP(A44,'Datos Personales'!$A:$M,3,FALSE) -> 395 | E44: =VLOOKUP(Tabla4[[#This Row],[ENFASIS]],Listas!$R$2:$S$8,2,0) -> ENFASIS EN GEOMATICA | F44: =VLOOKUP(A44,'Datos Personales'!A:M,8,0) -> juammorenog@udistrital.edu.co | G44: =VLOOKUP(A44,'Datos Personales'!A:M,9,0) -> juammorenog@udistrital.edu.co | H44: =VLOOKUP(A44,'Datos Personales'!A:M,5,FALSE) -> E | I44: =VLOOKUP(Tabla4[[#This Row],[CODIGO]],'ESTADOS ESTUDIANTES'!B:M,12,0) -> 2024-3 | J44: Investigación | K44: Análisis espacial de la fragmentación urbana basado en la destinación económica predominante por manzana en Bogotá D.C | L44: Luis Eduardo Castillo Mendez | N44: 45230 | O44: 2023 | P44: GFEM | Q44: Luis Eduardo Castillo Mendez | R44: 45240 | S44: =IF(Tabla4[[#This Row],[FECHA DE ACEPTACION DEL GRUP. INV.]]="","",DATE(YEAR(Tabla4[[#This Row],[FECHA DE ACEPTACION DEL GRUP. INV.]])+2,MONTH(Tabla4[[#This Row],[FECHA DE ACEPTACION DEL GRUP. INV.]]),DAY(Tabla4[[#This Row],[FECHA DE ACEPTACION DEL GRUP. INV.]]))) -> 45971 | T44: =IF(Tabla4[[#This Row],[FECHA DE ACEPTACION DEL GRUP. INV.]]="","",IF(Tabla4[[#This Row],[FECHA DE VENCIMIENTO ANTE PROYECTO]]<TODAY(),"SÍ","NO")) -> SÍ | U44: NO | W44: 017/2023 | AA44: 45323 | AB44: 126 | AC44: B1 | AD44: 014-2024 | AE44: 45581 | AF44: Fragmentación Urbana en Bogotá D.C: Análisis Espacial de los Retos en Ámbitos Sociales y Ambientales | AG44: II Congreso Internacional Sobre Retos y Desafíos Ambientales Locales. | AH44: 2024 | AI44: Ponencia | AJ44: =IFERROR(VLOOKUP(AI44,Listas!K:L,2,0),"") -> 0.2 | AK44: =IFERROR(VLOOKUP(AJ44,Listas!L:M,2,0),"") -> 10 | AL44: 45581 | AM44: 014/2024 | AN44: 45581 | AO44: Erika Sofia Upegui Cardona | AP44: 45582 | AQ44: 45609 | AR44: 43 | AS44: 44 | AT44: Aprobado | AU44: Yenny Espinosa | AV44: 45582 | AW44: 45609 | AX44: 40 | AY44: 44 | AZ44: Aprobado | BA44: 45609 | BB44: =IFERROR(AVERAGE(AR44,AS44,AX44,AY44),"") -> 42.75 | BC44: =BB44*(100%-AJ44) -> 34.2 | BD44: =SUM(BC44,AK44) -> 44.2 | BG44: =IF(OR(H44="A",$H44="D",$H44="P",$H44="V"),L44,"")
A45: 20182495004 | B45: =VLOOKUP(A45,'Datos Personales'!A:M,2,FALSE) -> BARRAGAN SARMIENTO ANDRÉS MAURICIO | C45: =VLOOKUP(A45,'ESTADOS ESTUDIANTES'!B:L,11,0) -> 1110537094 | D45: =VLOOKUP(A45,'Datos Personales'!$A:$M,3,FALSE) -> 495 | E45: =VLOOKUP(Tabla4[[#This Row],[ENFASIS]],Listas!$R$2:$S$8,2,0) -> ENFASIS EN ING. SOFT | F45: =VLOOKUP(A45,'Datos Personales'!A:M,8,0) -> ambarragans@udistrital.edu.co | G45: =VLOOKUP(A45,'Datos Personales'!A:M,9,0) -> barragan_amb@hotmail.com | H45: =VLOOKUP(A45,'Datos Personales'!A:M,5,FALSE) -> X | I45: =VLOOKUP(Tabla4[[#This Row],[CODIGO]],'ESTADOS ESTUDIANTES'!B:M,12,0) -> 2025-1 | J45: Investigación | K45: Evaluación de un Modelo Basado en la Arquitectura Transformer para Generar Test Unitarios en Java | L45: Sonia Ordoñez Salinas | N45: 45211 | O45: 2023 | P45: GESDATOS | Q45: Sonia Ordoñez Salinas | R45: 45229 | S45: =IF(Tabla4[[#This Row],[FECHA DE ACEPTACION DEL GRUP. INV.]]="","",DATE(YEAR(Tabla4[[#This Row],[FECHA DE ACEPTACION DEL GRUP. INV.]])+2,MONTH(Tabla4[[#This Row],[FECHA DE ACEPTACION DEL GRUP. INV.]]),DAY(Tabla4[[#This Row],[FECHA DE ACEPTACION DEL GRUP. INV.]]))) -> 45960 | T45: =IF(Tabla4[[#This Row],[FECHA DE ACEPTACION DEL GRUP. INV.]]="","",IF(Tabla4[[#This Row],[FECHA DE VENCIMIENTO ANTE PROYECTO]]<TODAY(),"SÍ","NO")) -> SÍ | U45: NO | W45: 016/2023 | AA45: 45531 | AB45: 128 | AC45: B1 | BB45: =IFERROR(AVERAGE(AR45,AS45,AX45,AY45),"") | BC45: =(BB45*0.8)/10 -> #VALUE! | BD45: =SUM(BC45,AK45) -> #VALUE! | BG45: =IF(OR(H45="A",$H45="D",$H45="P",$H45="V"),L45,"")
A46: 20182495011 | B46: =VLOOKUP(A46,'Datos Personales'!A:M,2,FALSE) -> PIÑEROS RAMIREZ JEISSON RODRIGO | C46: =VLOOKUP(A46,'ESTADOS ESTUDIANTES'!B:L,11,0) -> 1030678110 | D46: =VLOOKUP(A46,'Datos Personales'!$A:$M,3,FALSE) -> 495 | E46: =VLOOKUP(Tabla4[[#This Row],[ENFASIS]],Listas!$R$2:$S$8,2,0) -> ENFASIS EN ING. SOFT | F46: =VLOOKUP(A46,'Datos Personales'!A:M,8,0) -> jrpinerosr@udistrital.edu.co | G46: =VLOOKUP(A46,'Datos Personales'!A:M,9,0) -> jeisson005@hotmail.com | H46: =VLOOKUP(A46,'Datos Personales'!A:M,5,FALSE) -> E | I46: =VLOOKUP(Tabla4[[#This Row],[CODIGO]],'ESTADOS ESTUDIANTES'!B:M,12,0) -> 2025-1 | J46: Investigación | K46: METAMODELO SOFTWARE DE SIMULACION REMOTA INTERACTIVA EN AMBIENTE WEB | L46: Julio Baron Velandia | N46: 45308 | O46: 2024 | P46: INTECSE | Q46: Julio Baron Velandia | R46: 45403 | S46: =IF(Tabla4[[#This Row],[FECHA DE ACEPTACION DEL GRUP. INV.]]="","",DATE(YEAR(Tabla4[[#This Row],[FECHA DE ACEPTACION DEL GRUP. INV.]])+2,MONTH(Tabla4[[#This Row],[FECHA DE ACEPTACION DEL GRUP. INV.]]),DAY(Tabla4[[#This Row],[FECHA DE ACEPTACION DEL GRUP. INV.]]))) -> 46133 | T46: =IF(Tabla4[[#This Row],[FECHA DE ACEPTACION DEL GRUP. INV.]]="","",IF(Tabla4[[#This Row],[FECHA DE VENCIMIENTO ANTE PROYECTO]]<TODAY(),"SÍ","NO")) -> SÍ | U46: NO | W46: 21-3-2024 | AA46: 45139 | AB46: 122 | AC46: B1 | AD46: 016-2024 | AE46: 45608 | AF46: Caracterización de un Entorno de Simulación Visual Interactiva de Procesamiento Remoto Aplicado a Redes de Enrrutamiento | AG46: IX Semana Internacional de Ciencia, Tecnología e Innovación | AH46: 2024 | AI46: Ponencia | AJ46: =IFERROR(VLOOKUP(AI46,Listas!K:L,2,0),"") -> 0.2 | AK46: =IFERROR(VLOOKUP(AJ46,Listas!L:M,2,0),"") -> 10 | AL46: 45608 | AM46: 016-2024 | AN46: 45609 | AO46: Oswaldo Romero | AP46: 45688 | AQ46: 45714 | AR46: 50 | AS46: 50 | AT46: Aprobado | AU46: Sandro Javier Bolaños | AV46: 45688 | AW46: 45714 | AX46: 50 | AY46: 50 | AZ46: Aprobado | BA46: 45714 | BB46: =IFERROR(AVERAGE(AR46,AS46,AX46,AY46),"") -> 50 | BC46: =BB46*(100%-AJ46) -> 40 | BD46: =SUM(BC46,AK46) -> 50 | BE46: SI | BF46: SI | BG46: =IF(OR(H46="A",$H46="D",$H46="P",$H46="V"),L46,"")
A47: 20182495014 | B47: =VLOOKUP(A47,'Datos Personales'!A:M,2,FALSE) -> ROMERO PINTO JAWY ANDRÉS | C47: =VLOOKUP(A47,'ESTADOS ESTUDIANTES'!B:L,11,0) -> 1022955756 | D47: =VLOOKUP(A47,'Datos Personales'!$A:$M,3,FALSE) -> 495 | E47: =VLOOKUP(Tabla4[[#This Row],[ENFASIS]],Listas!$R$2:$S$8,2,0) -> ENFASIS EN ING. SOFT | F47: =VLOOKUP(A47,'Datos Personales'!A:M,8,0) -> jawaromerop@udistrital.edu.co | G47: =VLOOKUP(A47,'Datos Personales'!A:M,9,0) -> jawy.romero@gmail.com | H47: E | I47: =VLOOKUP(Tabla4[[#This Row],[CODIGO]],'ESTADOS ESTUDIANTES'!B:M,12,0) -> 2025-1 | J47: Investigación | K47: Metodología para validar la integridad de la información de las transacciones de los contratos inteligentes empleando cifrado homomórfico | L47: Elvis Eduardo Gaona Garcia | N47: 44609 | O47: 2022 | P47: GIIRA | Q47: Carlos Enrique Montenegro Marin | R47: 44609 | S47: =IF(Tabla4[[#This Row],[FECHA DE ACEPTACION DEL GRUP. INV.]]="","",DATE(YEAR(Tabla4[[#This Row],[FECHA DE ACEPTACION DEL GRUP. INV.]])+2,MONTH(Tabla4[[#This Row],[FECHA DE ACEPTACION DEL GRUP. INV.]]),DAY(Tabla4[[#This Row],[FECHA DE ACEPTACION DEL GRUP. INV.]]))) -> 45339 | T47: =IF(Tabla4[[#This Row],[FECHA DE ACEPTACION DEL GRUP. INV.]]="","",IF(Tabla4[[#This Row],[FECHA DE VENCIMIENTO ANTE PROYECTO]]<TODAY(),"SÍ","NO")) -> SÍ | U47: NO | W47: 2022 | AA47: 44981 | AB47: 82 | AC47: B1 | AD47: 015/2024 | AE47: 45595 | AF47: A Survey of Homomorphic cryptography, ZPK and zk-SNARK protocols for identity and privacy protection in Ethereum blockchain | AG47: Workshop on Engineering Applications (WEA 2022) | AH47: 2022 | AI47: Ponencia | AJ47: =IFERROR(VLOOKUP(AI47,Listas!K:L,2,0),"") -> 0.2 | AK47: =IFERROR(VLOOKUP(AJ47,Listas!L:M,2,0),"") -> 10 | AL47: 45595 | AM47: 015/2024 | AN47: 45595 | AO47: Carlos Enrique Montenegro Marin | AP47: 45595 | AQ47: 45635 | AR47: 40 | AS47: 40 | AT47: Aprobado | AU47: Roberto Albeiro Pava Diaz | AV47: 45595 | AW47: 45635 | AX47: 40 | AY47: 40 | AZ47: Aprobado | BA47: 45635 | BB47: =IFERROR(AVERAGE(AR47,AS47,AX47,AY47),"") -> 40 | BC47: =BB47*(100%-AJ47) -> 32 | BD47: =SUM(BC47,AK47) -> 42
A48: 20191195002 | B48: =VLOOKUP(A48,'Datos Personales'!A:M,2,FALSE) -> BELLO GONZALEZ IVAN DARIO | C48: =VLOOKUP(A48,'ESTADOS ESTUDIANTES'!B:L,11,0) -> 1031138497 | D48: =VLOOKUP(A48,'Datos Personales'!$A:$M,3,FALSE) -> 195 | E48: =VLOOKUP(Tabla4[[#This Row],[ENFASIS]],Listas!$R$2:$S$8,2,0) -> EN TELEINF. | F48: =VLOOKUP(A48,'Datos Personales'!A:M,8,0) -> idbellog@udistrital.edu.co | G48: =VLOOKUP(A48,'Datos Personales'!A:M,9,0) -> idbellog@gmail.com | H48: =VLOOKUP(A48,'Datos Personales'!A:M,5,FALSE) -> E | I48: =VLOOKUP(Tabla4[[#This Row],[CODIGO]],'ESTADOS ESTUDIANTES'!B:M,12,0) -> 2024-3 | J48: Investigación | K48: METODOLOGÍA PARA LA ELECCIÓN DE MODELOS DE LENGUAJE DE GRAN TAMAÑO (LLMS) EN APLICACIONES DE PREDICCIÓN METEREOLÓGICAS A TRAVÉS DE ALGORITMOS DE APRENDIZAJE AUTOMÁTICO SOBRE ENTORNOS DE COMPUTACIÓN EN LA NUBE Y CAPTURAS DE DATOS A TRAVÉS DE IOT | L48: Elvis Eduardo Gaona Garcia | M48: Paulo Alonso Gaona Garcia | N48: 45439 | O48: 2024 | P48: GIIRA | Q48: Carlos Enrique Montenegro Marin | R48: 45454 | S48: =IF(Tabla4[[#This Row],[FECHA DE ACEPTACION DEL GRUP. INV.]]="","",DATE(YEAR(Tabla4[[#This Row],[FECHA DE ACEPTACION DEL GRUP. INV.]])+2,MONTH(Tabla4[[#This Row],[FECHA DE ACEPTACION DEL GRUP. INV.]]),DAY(Tabla4[[#This Row],[FECHA DE ACEPTACION DEL GRUP. INV.]]))) -> 46184 | T48: =IF(Tabla4[[#This Row],[FECHA DE ACEPTACION DEL GRUP. INV.]]="","",IF(Tabla4[[#This Row],[FECHA DE VENCIMIENTO ANTE PROYECTO]]<TODAY(),"SÍ","NO")) -> SÍ | U48: No | W48: 010-2024 | AA48: 45531 | AB48: 127 | AC48: B1 | AD48: 015/2024 | AE48: 45595 | AF48: An Iterative Methodology for Evaluating Large Language Models in IoT Weather Monitoring Systems | AG48: Workshop on Engineering Applications 2024 Artificial Intelligence, Optimization and Simulation Oct. 23-25, 2024, Barranquilla - Colombia | AH48: 2024 | AI48: Ponencia | AJ48: 0.2 | AK48: =IFERROR(VLOOKUP(AJ48,Listas!L:M,2,0),"") -> 10 | AL48: 45594 | AM48: 015/2024 | AN48: 45595 | AO48: Carlos Enrique Montenegro Marin | BC48: =(BB48*0.8)/10 -> 0 | BD48: =SUM(BC48,AK48) -> 10 | BG48: =IF(OR(H48="A",$H48="D",$H48="P",$H48="V"),L48,"")
A49: 20191195005 | B49: =VLOOKUP(A49,'Datos Personales'!A:M,2,FALSE) -> LOPEZ GARCÍA ANDRES CAMILO | C49: =VLOOKUP(A49,'ESTADOS ESTUDIANTES'!B:L,11,0) -> 1022395511 | D49: =VLOOKUP(A49,'Datos Personales'!$A:$M,3,FALSE) -> 195 | E49: =VLOOKUP(Tabla4[[#This Row],[ENFASIS]],Listas!$R$2:$S$8,2,0) -> EN TELEINF. | F49: =VLOOKUP(A49,'Datos Personales'!A:M,8,0) -> anclopezg@udistrital.edu.co | G49: =VLOOKUP(A49,'Datos Personales'!A:M,9,0) -> anclopezg@correo.udistrital.edu.co | H49: =VLOOKUP(A49,'Datos Personales'!A:M,5,FALSE) -> E | I49: =VLOOKUP(Tabla4[[#This Row],[CODIGO]],'ESTADOS ESTUDIANTES'!B:M,12,0) -> 2023-1 | J49: Investigación | K49: Diseño e implementación de un algoritmo y plataforma para el análisis descriptivo y predictivo de la producción energética de la turbina HAWT-VG bioinspirada en Plumas dorsales de halcón peregrino | L49: Elvis Eduardo Gaona Garcia | M49: Alejandro Oyono Ondo (Uni. Rosario) | N49: 43635 | O49: 2019 | P49: GITUD | Q49: Roberto Ferro Escobar | R49: 44807 | S49: =IF(Tabla4[[#This Row],[FECHA DE ACEPTACION DEL GRUP. INV.]]="","",DATE(YEAR(Tabla4[[#This Row],[FECHA DE ACEPTACION DEL GRUP. INV.]])+2,MONTH(Tabla4[[#This Row],[FECHA DE ACEPTACION DEL GRUP. INV.]]),DAY(Tabla4[[#This Row],[FECHA DE ACEPTACION DEL GRUP. INV.]]))) -> 45538 | T49: =IF(Tabla4[[#This Row],[FECHA DE ACEPTACION DEL GRUP. INV.]]="","",IF(Tabla4[[#This Row],[FECHA DE VENCIMIENTO ANTE PROYECTO]]<TODAY(),"SÍ","NO")) -> SÍ | W49: 01-2020 | Y49: 43809 | Z49: 86.9 | AA49: 44981 | AB49: 156 | AC49: B2 | AD49: 001/2023 | AE49: 44927 | AF49: Generadores de vórtice activos y bio-inspirados para rotores eólicos en zonas rurales de Cundinamarca mediante CFD | AI49: Ponencia | AJ49: =IFERROR(VLOOKUP(AI49,Listas!K:L,2,0),"") -> 0.2 | AK49: =IFERROR(VLOOKUP(AJ49,Listas!L:M,2,0),"") -> 10 | AL49: 44924 | AN49: 44958 | AO49: Julian Orlando Camargo | AP49: 44958 | AQ49: 44981 | AR49: 50 | AS49: 50 | AT49: Meritorio | AU49: Julian Rodriguez | AV49: 44958 | AW49: 44981 | AX49: 50 | AY49: 50 | AZ49: Meritorio | BA49: 44981 | BB49: =IFERROR(AVERAGE(AR49,AS49,AX49,AY49),"") -> 50 | BC49: =BB49*(100%-AJ49) -> 40 | BD49: =SUM(BC49,AK49) -> 50 | BG49: =IF(OR(H49="A",$H49="D",$H49="P",$H49="V"),L49,"")
A50: 20191195007 | B50: =VLOOKUP(A50,'Datos Personales'!A:M,2,FALSE) -> RENGIFO GÜIZA WILMAR NEISER | C50: =VLOOKUP(A50,'ESTADOS ESTUDIANTES'!B:L,11,0) -> 80248462 | D50: =VLOOKUP(A50,'Datos Personales'!$A:$M,3,FALSE) -> 195 | E50: =VLOOKUP(Tabla4[[#This Row],[ENFASIS]],Listas!$R$2:$S$8,2,0) -> EN TELEINF. | F50: =VLOOKUP(A50,'Datos Personales'!A:M,8,0) -> wnrengifog@udistrital.edu.co | G50: =VLOOKUP(A50,'Datos Personales'!A:M,9,0) -> wilrengui@gmail.com | H50: E | I50: =VLOOKUP(Tabla4[[#This Row],[CODIGO]],'ESTADOS ESTUDIANTES'!B:M,12,0) -> 2025-1 | J50: Investigación | K50: Metodología para el análisis de vulnerabilidades aplicado a sistemas de navegación y telemetría presentes en RPA’s | L50: Elvis Eduardo Gaona Garcia | N50: 45594 | O50: 2024 | P50: GITUD | Q50: Elvis Eduardo Gaona Garcia | R50: 45594 | S50: =IF(Tabla4[[#This Row],[FECHA DE ACEPTACION DEL GRUP. INV.]]="","",DATE(YEAR(Tabla4[[#This Row],[FECHA DE ACEPTACION DEL GRUP. INV.]])+2,MONTH(Tabla4[[#This Row],[FECHA DE ACEPTACION DEL GRUP. INV.]]),DAY(Tabla4[[#This Row],[FECHA DE ACEPTACION DEL GRUP. INV.]]))) -> 46324 | T50: =IF(Tabla4[[#This Row],[FECHA DE ACEPTACION DEL GRUP. INV.]]="","",IF(Tabla4[[#This Row],[FECHA DE VENCIMIENTO ANTE PROYECTO]]<TODAY(),"SÍ","NO")) -> NO | U50: NO | W50: 015/2024 | Y50: 44097 | Z50: 91.59 | AA50: 45531 | AB50: 140 | AC50: B1 | AD50: 017/2024 | AE50: 45622 | AF50: A Risk assessment approach methodology to score vulnerabilities in airworthiness systems | AG50: Workshop in Engineering Applications 2024 | AH50: 2024 | AI50: Ponencia | AJ50: =IFERROR(VLOOKUP(AI50,Listas!K:L,2,0),"") -> 0.2 | AK50: =IFERROR(VLOOKUP(AJ50,Listas!L:M,2,0),"") -> 10 | AL50: 45622 | AM50: 017/2024 | AN50: 45622 | AO50: Cesar Andrey Perdomo Charry | AP50: 45624 | AQ50: 45635 | AR50: 50 | AS50: 50 | AT50: Aprobado | AU50: Paulo Alonso Gaona Garcia | AV50: 45624 | AW50: 45635 | AX50: 50 | AY50: 50 | AZ50: Aprobado | BA50: 45635 | BB50: =IFERROR(AVERAGE(AR50,AS50,AX50,AY50),"") -> 50 | BC50: =BB50*(100%-AJ50) -> 40 | BD50: =SUM(BC50,AK50) -> 50 | BG50: =IF(OR(H50="A",$H50="D",$H50="P",$H50="V"),L50,"")
A51: 20191395002 | B51: =VLOOKUP(A51,'Datos Personales'!A:M,2,FALSE) -> FERNÁNDEZ CAMPOS JAVIER ORLANDO | C51: =VLOOKUP(A51,'ESTADOS ESTUDIANTES'!B:L,11,0) -> 1077147477 | D51: =VLOOKUP(A51,'Datos Personales'!$A:$M,3,FALSE) -> 395 | E51: =VLOOKUP(Tabla4[[#This Row],[ENFASIS]],Listas!$R$2:$S$8,2,0) -> ENFASIS EN GEOMATICA | F51: =VLOOKUP(A51,'Datos Personales'!A:M,8,0) -> jofernandezc@correo.udistrital.edu.co | G51: =VLOOKUP(A51,'Datos Personales'!A:M,9,0) -> fernandezjavier480@gmail.com | H51: =VLOOKUP(A51,'Datos Personales'!A:M,5,FALSE) -> E | I51: =VLOOKUP(Tabla4[[#This Row],[CODIGO]],'ESTADOS ESTUDIANTES'!B:M,12,0) -> 2022-1 | J51: Investigación | K51: MODELO PARA LA DETERMINACION DE ISOGLOSAS Y CLASIFICACION DIALECTAL A PARTIR DEL TOMO II DE ATLAS LINGUISTICO ETNOGRAFICO DE COLOMBIA | L51: Luz Angela Rocha | M51: Johnatan Estiven Bonilla | N51: 43623 | O51: 2019 | P51: NIDE | Q51: Luz Angela Rocha Salamanca | R51: 43817 | S51: =IF(Tabla4[[#This Row],[FECHA DE ACEPTACION DEL GRUP. INV.]]="","",DATE(YEAR(Tabla4[[#This Row],[FECHA DE ACEPTACION DEL GRUP. INV.]])+2,MONTH(Tabla4[[#This Row],[FECHA DE ACEPTACION DEL GRUP. INV.]]),DAY(Tabla4[[#This Row],[FECHA DE ACEPTACION DEL GRUP. INV.]]))) -> 44548 | T51: =IF(Tabla4[[#This Row],[FECHA DE ACEPTACION DEL GRUP. INV.]]="","",IF(Tabla4[[#This Row],[FECHA DE VENCIMIENTO ANTE PROYECTO]]<TODAY(),"SÍ","NO")) -> SÍ | W51: 01-2020 | Z51: 66.09 | AA51: 43964 | AB51: 82.61 | AC51: B1 | AD51: 07-2022 | AE51: 44629 | AF51: cryptography, ZPK and zk-SNARK protocols for identity and privacy protection in Ethereum blockchain | AI51: Revista B | AJ51: =IFERROR(VLOOKUP(AI51,Listas!K:L,2,0),"") -> 0.6 | AK51: =IFERROR(VLOOKUP(AJ51,Listas!L:M,2,0),"") -> 30 | AL51: 44629 | AM51: 44743 | AN51: 44629 | AO51: Johan Andres Avendaño Arias | AP51: 44630 | AQ51: 44673 | AR51: 47 | AS51: 48 | AT51: LAUREADO | AU51: Julio Alexander Bernal Chávez | AV51: 44630 | AW51: 44673 | AX51: 50 | AY51: 50 | AZ51: LAUREADO | BA51: 44673 | BB51: =IFERROR(ROUND(AVERAGE(AY51,AX51,AZ51,AR51),0),"") -> 49 | BC51: =BB51*(100%-AJ51) -> 19.6 | BD51: =SUM(BC51,AK51) -> 49.6 | BG51: =IF(OR(H51="A",$H51="D",$H51="P",$H51="V"),L51,"")
A52: 20191395004 | B52: =VLOOKUP(A52,'Datos Personales'!A:M,2,FALSE) -> LARA ABELLO JENNIFFER | C52: =VLOOKUP(A52,'ESTADOS ESTUDIANTES'!B:L,11,0) -> 1016068098 | D52: =VLOOKUP(A52,'Datos Personales'!$A:$M,3,FALSE) -> 395 | E52: =VLOOKUP(Tabla4[[#This Row],[ENFASIS]],Listas!$R$2:$S$8,2,0) -> ENFASIS EN GEOMATICA | F52: =VLOOKUP(A52,'Datos Personales'!A:M,8,0) -> jlaraa@correo.udistrital.edu.co | G52: =VLOOKUP(A52,'Datos Personales'!A:M,9,0) -> jlaraa@correo.udistrital.edu.co | H52: =VLOOKUP(A52,'Datos Personales'!A:M,5,FALSE) -> X | I52: =VLOOKUP(Tabla4[[#This Row],[CODIGO]],'ESTADOS ESTUDIANTES'!B:M,12,0) -> 2019-1 | S52: =IF(Tabla4[[#This Row],[FECHA DE ACEPTACION DEL GRUP. INV.]]="","",DATE(YEAR(Tabla4[[#This Row],[FECHA DE ACEPTACION DEL GRUP. INV.]])+2,MONTH(Tabla4[[#This Row],[FECHA DE ACEPTACION DEL GRUP. INV.]]),DAY(Tabla4[[#This Row],[FECHA DE ACEPTACION DEL GRUP. INV.]]))) | T52: =IF(Tabla4[[#This Row],[FECHA DE ACEPTACION DEL GRUP. INV.]]="","",IF(Tabla4[[#This Row],[FECHA DE VENCIMIENTO ANTE PROYECTO]]<TODAY(),"SÍ","NO")) | AJ52: =IFERROR(VLOOKUP(AI52,Listas!K:L,2,0),"") | AK52: =IFERROR(VLOOKUP(AJ52,Listas!L:M,2,0),"") | BB52: =IFERROR(ROUND(AVERAGE(AY52,AX52,AS52,AR52),0),"") | BC52: =BB52*(100%-AJ52) -> #VALUE! | BD52: =SUM(BC52,AK52) -> #VALUE! | BG52: =IF(OR(H52="A",$H52="D",$H52="P",$H52="V"),L52,"")
A53: 20191395010 | B53: =VLOOKUP(A53,'Datos Personales'!A:M,2,FALSE) -> RAYO BERMUDEZ KAREN YULIETH | C53: =VLOOKUP(A53,'ESTADOS ESTUDIANTES'!B:L,11,0) -> 1023009167 | D53: =VLOOKUP(A53,'Datos Personales'!$A:$M,3,FALSE) -> 395 | E53: =VLOOKUP(Tabla4[[#This Row],[ENFASIS]],Listas!$R$2:$S$8,2,0) -> ENFASIS EN GEOMATICA | F53: =VLOOKUP(A53,'Datos Personales'!A:M,8,0) -> kyrayob@correo.udistrital.edu.co | G53: =VLOOKUP(A53,'Datos Personales'!A:M,9,0) -> karenrayo27@gmail.com | H53: =VLOOKUP(A53,'Datos Personales'!A:M,5,FALSE) -> E | I53: =VLOOKUP(Tabla4[[#This Row],[CODIGO]],'ESTADOS ESTUDIANTES'!B:M,12,0) -> 2022-3 | J53: Investigación | K53: ANÁLISIS DE PRECIPITACIONES CON MODELOS PREDICTIVOS A PARTIR DE LA INTERRELACIÓN DE SERIES DE TIEMPO Y GEOESTADÍSTICA PARA EL DEPARTAMENTO DE CUNDINAMARCA | L53: Carlos Eduardo Melo | N53: 43615 | O53: 2019 | P53: NIDE | Q53: Luz Angela Rocha Salamanca | R53: 43817 | S53: =IF(Tabla4[[#This Row],[FECHA DE ACEPTACION DEL GRUP. INV.]]="","",DATE(YEAR(Tabla4[[#This Row],[FECHA DE ACEPTACION DEL GRUP. INV.]])+2,MONTH(Tabla4[[#This Row],[FECHA DE ACEPTACION DEL GRUP. INV.]]),DAY(Tabla4[[#This Row],[FECHA DE ACEPTACION DEL GRUP. INV.]]))) -> 44548 | T53: =IF(Tabla4[[#This Row],[FECHA DE ACEPTACION DEL GRUP. INV.]]="","",IF(Tabla4[[#This Row],[FECHA DE VENCIMIENTO ANTE PROYECTO]]<TODAY(),"SÍ","NO")) -> SÍ | W53: 01-2020 | Y53: 43964 | Z53: 70.43 | AA53: 44802 | AB53: 114 | AC53: B1 | AD53: 02/2021 | AE53: 44242 | AI53: Revista B | AJ53: =IFERROR(VLOOKUP(AI53,Listas!K:L,2,0),"") -> 0.6 | AK53: =IFERROR(VLOOKUP(AJ53,Listas!L:M,2,0),"") -> 30 | AL53: 44734 | AM53: 14-2022 | AN53: 44734 | AO53: Hector Javier Fuentes Lopez | AP53: 44741 | AQ53: 44804 | AR53: 42 | AS53: 38 | AT53: Aprobado | AU53: Leonardo Plazas Nossa | AV53: 44741 | AW53: 44804 | AX53: 46 | AY53: 46 | AZ53: Aprobado | BA53: 44804 | BB53: =IFERROR(ROUND(AVERAGE(AY53,AX53,AS53,AR53),0),"") -> 43 | BC53: =BB53*(100%-AJ53) -> 17.2 | BD53: =SUM(BC53,AK53) -> 47.2 | BG53: =IF(OR(H53="A",$H53="D",$H53="P",$H53="V"),L53,"")
A54: 20191395011 | B54: =VLOOKUP(A54,'Datos Personales'!A:M,2,FALSE) -> SUAREZ JAIMES PAOLA ANDREA | C54: =VLOOKUP(A54,'ESTADOS ESTUDIANTES'!B:L,11,0) -> 1014267962 | D54: =VLOOKUP(A54,'Datos Personales'!$A:$M,3,FALSE) -> 395 | E54: =VLOOKUP(Tabla4[[#This Row],[ENFASIS]],Listas!$R$2:$S$8,2,0) -> ENFASIS EN GEOMATICA | F54: =VLOOKUP(A54,'Datos Personales'!A:M,8,0) -> pasuarezj@udistrital.edu.co | G54: =VLOOKUP(A54,'Datos Personales'!A:M,9,0) -> ingpaolasuarez@gmail.com | H54: =VLOOKUP(A54,'Datos Personales'!A:M,5,FALSE) -> E | I54: =VLOOKUP(Tabla4[[#This Row],[CODIGO]],'ESTADOS ESTUDIANTES'!B:M,12,0) -> 2025-3 | J54: Investigación | K54: Metodología para el monitoreo de la subsidencia del suelo en la ciudad de Bogotá D.C. con técnicas de interferometría y Persistent Scatterers | L54: Edilberto Suarez Torres | N54: 45442 | O54: 2024 | P54: NIDE | Q54: Luz Angela Rocha Salamanca | R54: 45540 | S54: =IF(Tabla4[[#This Row],[FECHA DE ACEPTACION DEL GRUP. INV.]]="","",DATE(YEAR(Tabla4[[#This Row],[FECHA DE ACEPTACION DEL GRUP. INV.]])+2,MONTH(Tabla4[[#This Row],[FECHA DE ACEPTACION DEL GRUP. INV.]]),DAY(Tabla4[[#This Row],[FECHA DE ACEPTACION DEL GRUP. INV.]]))) -> 46270 | T54: =IF(Tabla4[[#This Row],[FECHA DE ACEPTACION DEL GRUP. INV.]]="","",IF(Tabla4[[#This Row],[FECHA DE VENCIMIENTO ANTE PROYECTO]]<TODAY(),"SÍ","NO")) -> SÍ | U54: NO | W54: 13-2024 | Y54: 45768 | Z54: 63 | AA54: 45870 | AB54: 97 | AC54: B1 | AD54: 013-2025 | AE54: 45819 | AF54: Estimación y análisis de la subsidencia del suelo en la ciudad de Bogotá D.C. con técnicas de Interferometría y Persistent Scatterers | AG54: Congreso internacional en Ingeniería, tecnología e innovación- CIITI 2025 | AH54: 2025 | AI54: Ponencia | AJ54: =IFERROR(VLOOKUP(AI54,Listas!K:L,2,0),"") -> 0.2 | AK54: =IFERROR(VLOOKUP(AJ54,Listas!L:M,2,0),"") -> 10 | AL54: 45819 | AM54: 013-2025 | AN54: 45819 | AO54: Jose Luis Herrera Escorcia | AU54: William Barragan Zaque | BB54: =IFERROR(AVERAGE(AR54,AS54,AX54,AY54),"") | BC54: =BB54*(100%-AJ54) -> #VALUE! | BD54: =SUM(BC54,AK54) -> #VALUE! | BG54: =IF(OR(H54="A",$H54="D",$H54="P",$H54="V"),L54,"")
A55: 20191495002 | B55: =VLOOKUP(A55,'Datos Personales'!A:M,2,FALSE) -> BELTRAN ALFONSO RICARDO ANDRES | C55: =VLOOKUP(A55,'ESTADOS ESTUDIANTES'!B:L,11,0) -> 1012390507 | D55: =VLOOKUP(A55,'Datos Personales'!$A:$M,3,FALSE) -> 495 | E55: =VLOOKUP(Tabla4[[#This Row],[ENFASIS]],Listas!$R$2:$S$8,2,0) -> ENFASIS EN ING. SOFT | F55: =VLOOKUP(A55,'Datos Personales'!A:M,8,0) -> rabeltrana@correo.udistrital.edu.co | G55: =VLOOKUP(A55,'Datos Personales'!A:M,9,0) -> richardb9207@gmail.com | H55: =VLOOKUP(A55,'Datos Personales'!A:M,5,FALSE) -> X | I55: =VLOOKUP(Tabla4[[#This Row],[CODIGO]],'ESTADOS ESTUDIANTES'!B:M,12,0) -> 2019-3 | J55: Investigación | K55: ESQUEMA VISUAL PARA LA EXPLOTACION DE RECURSOS BASADO EN LINKED OPEN DATA Y ANALITICA VISUAL | L55: Paulo Alonso Gaona Garcia | N55: 43636 | O55: 2019 | P55: MULTIMEDIA INTERACTIVA | Q55: Paulo Alonso Gaona Garcia | S55: =IF(Tabla4[[#This Row],[FECHA DE ACEPTACION DEL GRUP. INV.]]="","",DATE(YEAR(Tabla4[[#This Row],[FECHA DE ACEPTACION DEL GRUP. INV.]])+2,MONTH(Tabla4[[#This Row],[FECHA DE ACEPTACION DEL GRUP. INV.]]),DAY(Tabla4[[#This Row],[FECHA DE ACEPTACION DEL GRUP. INV.]]))) | T55: =IF(Tabla4[[#This Row],[FECHA DE ACEPTACION DEL GRUP. INV.]]="","",IF(Tabla4[[#This Row],[FECHA DE VENCIMIENTO ANTE PROYECTO]]<TODAY(),"SÍ","NO")) | AJ55: =IFERROR(VLOOKUP(AI55,Listas!K:L,2,0),"") | AK55: =IFERROR(VLOOKUP(AJ55,Listas!L:M,2,0),"") | BB55: =IFERROR(ROUND(AVERAGE(AY55,AX55,AS55,AR55),0),"") | BC55: =BB55*(100%-AJ55) -> #VALUE! | BD55: =SUM(BC55,AK55) -> #VALUE! | BG55: =IF(OR(H55="A",$H55="D",$H55="P",$H55="V"),L55,"")
A56: 20191495003 | B56: =VLOOKUP(A56,'Datos Personales'!A:M,2,FALSE) -> CARVAJAL TORRES JOSE AUGUSTO | C56: =VLOOKUP(A56,'ESTADOS ESTUDIANTES'!B:L,11,0) -> 1026295788 | D56: =VLOOKUP(A56,'Datos Personales'!$A:$M,3,FALSE) -> 495 | E56: =VLOOKUP(Tabla4[[#This Row],[ENFASIS]],Listas!$R$2:$S$8,2,0) -> ENFASIS EN ING. SOFT | F56: =VLOOKUP(A56,'Datos Personales'!A:M,8,0) -> jacarvajalt@udistrital.edu.co | G56: =VLOOKUP(A56,'Datos Personales'!A:M,9,0) -> jacarvajalt@correo.udistrital.edu.co | H56: =VLOOKUP(A56,'Datos Personales'!A:M,5,FALSE) -> X | I56: =VLOOKUP(Tabla4[[#This Row],[CODIGO]],'ESTADOS ESTUDIANTES'!B:M,12,0) -> 2025-1 | J56: Investigación | K56: ESQUEMA DE CLASIFICACION DE RECURSOS HISTORICOS DE POSTCONFLICTO EN COLOMBIA BASADO EN SKOS EN AMBIENTES INMERSIVOS | L56: Nancy Yaneth Gelvez | N56: 43633 | O56: 2019 | P56: GIIRA | Q56: Carlos Enrique Montenegro Marin | R56: 43817 | S56: =IF(Tabla4[[#This Row],[FECHA DE ACEPTACION DEL GRUP. INV.]]="","",DATE(YEAR(Tabla4[[#This Row],[FECHA DE ACEPTACION DEL GRUP. INV.]])+2,MONTH(Tabla4[[#This Row],[FECHA DE ACEPTACION DEL GRUP. INV.]]),DAY(Tabla4[[#This Row],[FECHA DE ACEPTACION DEL GRUP. INV.]]))) -> 44548 | T56: =IF(Tabla4[[#This Row],[FECHA DE ACEPTACION DEL GRUP. INV.]]="","",IF(Tabla4[[#This Row],[FECHA DE VENCIMIENTO ANTE PROYECTO]]<TODAY(),"SÍ","NO")) -> SÍ | U56: NO | W56: 01-2020 | AA56: 45335 | AB56: 120 | AC56: B1 | AJ56: =IFERROR(VLOOKUP(AI56,Listas!K:L,2,0),"") | AK56: =IFERROR(VLOOKUP(AJ56,Listas!L:M,2,0),"") | BB56: =IFERROR(AVERAGE(AR56,AS56,AX56,AY56),"") | BC56: =BB56*(100%-AJ56) -> #VALUE! | BD56: =SUM(BC56,AK56) -> #VALUE! | BG56: =IF(OR(H56="A",$H56="D",$H56="P",$H56="V"),L56,"")
A57: 20191495004 | B57: =VLOOKUP(A57,'Datos Personales'!A:M,2,FALSE) -> CATAÑO HOYOS LUIS ADOLFO | C57: =VLOOKUP(A57,'ESTADOS ESTUDIANTES'!B:L,11,0) -> 1067876861 | D57: =VLOOKUP(A57,'Datos Personales'!$A:$M,3,FALSE) -> 495 | E57: =VLOOKUP(Tabla4[[#This Row],[ENFASIS]],Listas!$R$2:$S$8,2,0) -> ENFASIS EN ING. SOFT | F57: =VLOOKUP(A57,'Datos Personales'!A:M,8,0) -> lacatanoh@correo.udistrital.edu.co | G57: =VLOOKUP(A57,'Datos Personales'!A:M,9,0) -> luchoad17@gmail.com | H57: =VLOOKUP(A57,'Datos Personales'!A:M,5,FALSE) -> X | I57: =VLOOKUP(Tabla4[[#This Row],[CODIGO]],'ESTADOS ESTUDIANTES'!B:M,12,0) -> 2019-1 | S57: =IF(Tabla4[[#This Row],[FECHA DE ACEPTACION DEL GRUP. INV.]]="","",DATE(YEAR(Tabla4[[#This Row],[FECHA DE ACEPTACION DEL GRUP. INV.]])+2,MONTH(Tabla4[[#This Row],[FECHA DE ACEPTACION DEL GRUP. INV.]]),DAY(Tabla4[[#This Row],[FECHA DE ACEPTACION DEL GRUP. INV.]]))) | T57: =IF(Tabla4[[#This Row],[FECHA DE ACEPTACION DEL GRUP. INV.]]="","",IF(Tabla4[[#This Row],[FECHA DE VENCIMIENTO ANTE PROYECTO]]<TODAY(),"SÍ","NO")) | AJ57: =IFERROR(VLOOKUP(AI57,Listas!K:L,2,0),"") | AK57: =IFERROR(VLOOKUP(AJ57,Listas!L:M,2,0),"") | BB57: =IFERROR(ROUND(AVERAGE(AY57,AX57,AS57,AR57),0),"") | BC57: =BB57*(100%-AJ57) -> #VALUE! | BD57: =SUM(BC57,AK57) -> #VALUE! | BG57: =IF(OR(H57="A",$H57="D",$H57="P",$H57="V"),L57,"")
A58: 20191495006 | B58: =VLOOKUP(A58,'Datos Personales'!A:M,2,FALSE) -> COTTA GARCÍA JUAN GUILLERMO | C58: =VLOOKUP(A58,'ESTADOS ESTUDIANTES'!B:L,11,0) -> 1032470566 | D58: =VLOOKUP(A58,'Datos Personales'!$A:$M,3,FALSE) -> 495 | E58: =VLOOKUP(Tabla4[[#This Row],[ENFASIS]],Listas!$R$2:$S$8,2,0) -> ENFASIS EN ING. SOFT | F58: =VLOOKUP(A58,'Datos Personales'!A:M,8,0) -> jgcottag@udistrital.edu.co | G58: =VLOOKUP(A58,'Datos Personales'!A:M,9,0) -> jgcotta@hotmail.com | H58: =VLOOKUP(A58,'Datos Personales'!A:M,5,FALSE) -> E | I58: =VLOOKUP(Tabla4[[#This Row],[CODIGO]],'ESTADOS ESTUDIANTES'!B:M,12,0) -> 2025-3 | J58: Investigación | K58: Mejoramiento de la descripción de recursos educativos abiertos, a partir de técnicas basadas en inteligencia artificial, machine learning y minería de datos | L58: Jhon Francined Herrera Cubides | M58: Paulo Alonso Gaona Garcia | N58: 45784 | O58: 2019 | P58: GIIRA | Q58: Carlos Enrique Montenegro Marin | R58: 45784 | S58: =IF(Tabla4[[#This Row],[FECHA DE ACEPTACION DEL GRUP. INV.]]="","",DATE(YEAR(Tabla4[[#This Row],[FECHA DE ACEPTACION DEL GRUP. INV.]])+2,MONTH(Tabla4[[#This Row],[FECHA DE ACEPTACION DEL GRUP. INV.]]),DAY(Tabla4[[#This Row],[FECHA DE ACEPTACION DEL GRUP. INV.]]))) -> 46514 | T58: =IF(Tabla4[[#This Row],[FECHA DE ACEPTACION DEL GRUP. INV.]]="","",IF(Tabla4[[#This Row],[FECHA DE VENCIMIENTO ANTE PROYECTO]]<TODAY(),"SÍ","NO")) -> NO | U58: NO | W58: 011/2025 | AA58: 45531 | AB58: 140 | AC58: B1 | AD58: 013-2025 | AE58: 45819 | AF58: Estrategia para mejorar la descripción a Recursos Educativos Abiertos a partir de la integración de técnicas basadas en Inteligencia Artificial, Machine Learning y Minería de Datos | AG58: 5ta edición del Congreso Internacional en Ingeniería, tecnología e innovación - CIITI 2025 | AH58: 2025 | AI58: Ponencia | AJ58: =IFERROR(VLOOKUP(AI58,Listas!K:L,2,0),"") -> 0.2 | AK58: =IFERROR(VLOOKUP(AJ58,Listas!L:M,2,0),"") -> 10 | AL58: 45806 | AM58: 013-2025 | AN58: 45819 | AO58: Jorge Enrique Rodriguez Rodriguez | AP58: 45874 | AQ58: 45891 | AR58: 46 | AS58: 46 | AT58: Aprobado | AU58: Daniel Leal | AV58: 45874 | AW58: 45891 | AX58: 46 | AY58: 46 | AZ58: Aprobado | BA58: 45891 | BB58: =IFERROR(AVERAGE(AR58,AS58,AX58,AY58),"") -> 46 | BC58: =BB58*(100%-AJ58) -> 36.8 | BD58: =SUM(BC58,AK58) -> 46.8 | BG58: =IF(OR(H58="A",$H58="D",$H58="P",$H58="V"),L58,"")
A59: 20191495007 | B59: =VLOOKUP(A59,'Datos Personales'!A:M,2,FALSE) -> CUELLAR MAYORGA JULIAN ORLANDO | C59: =VLOOKUP(A59,'ESTADOS ESTUDIANTES'!B:L,11,0) -> 80817300 | D59: =VLOOKUP(A59,'Datos Personales'!$A:$M,3,FALSE) -> 495 | E59: =VLOOKUP(Tabla4[[#This Row],[ENFASIS]],Listas!$R$2:$S$8,2,0) -> ENFASIS EN ING. SOFT | F59: =VLOOKUP(A59,'Datos Personales'!A:M,8,0) -> jocuellarm@udistrital.edu.co | G59: =VLOOKUP(A59,'Datos Personales'!A:M,9,0) -> julianorlando@gmail.com | H59: =VLOOKUP(A59,'Datos Personales'!A:M,5,FALSE) -> X | I59: =VLOOKUP(Tabla4[[#This Row],[CODIGO]],'ESTADOS ESTUDIANTES'!B:M,12,0) -> 2025-1 | J59: Investigación | K59: SEGUIMIENTO DE ENFERMEDAD DE PARKINSON A TRAVES DE ANALISIS DE MARCHA USANDO DEEP LEARNING Y VISION ARTIFICIAL | L59: Octavio Jose Salcedo Parra | N59: 43626 | O59: 2019 | P59: INTERNET INTELIGENTE | Q59: Octavio Jose Salcedo Parra | R59: 43819 | S59: =IF(Tabla4[[#This Row],[FECHA DE ACEPTACION DEL GRUP. INV.]]="","",DATE(YEAR(Tabla4[[#This Row],[FECHA DE ACEPTACION DEL GRUP. INV.]])+2,MONTH(Tabla4[[#This Row],[FECHA DE ACEPTACION DEL GRUP. INV.]]),DAY(Tabla4[[#This Row],[FECHA DE ACEPTACION DEL GRUP. INV.]]))) -> 44550 | T59: =IF(Tabla4[[#This Row],[FECHA DE ACEPTACION DEL GRUP. INV.]]="","",IF(Tabla4[[#This Row],[FECHA DE VENCIMIENTO ANTE PROYECTO]]<TODAY(),"SÍ","NO")) -> SÍ | U59: NO | W59: 01-2020 | AA59: 43964 | AB59: 84.35 | AC59: B1 | AJ59: =IFERROR(VLOOKUP(AI59,Listas!K:L,2,0),"") | AK59: =IFERROR(VLOOKUP(AJ59,Listas!L:M,2,0),"") | BB59: =IFERROR(AVERAGE(AR59,AS59,AX59,AY59),"") | BC59: =BB59*(100%-AJ59) -> #VALUE! | BD59: =SUM(BC59,AK59) -> #VALUE! | BG59: =IF(OR(H59="A",$H59="D",$H59="P",$H59="V"),L59,"")
A60: 20191495008 | B60: =VLOOKUP(A60,'Datos Personales'!A:M,2,FALSE) -> DALLOS PARRA DAVID LEONARDO | C60: =VLOOKUP(A60,'ESTADOS ESTUDIANTES'!B:L,11,0) -> 1015460560 | D60: =VLOOKUP(A60,'Datos Personales'!$A:$M,3,FALSE) -> 495 | E60: =VLOOKUP(Tabla4[[#This Row],[ENFASIS]],Listas!$R$2:$S$8,2,0) -> ENFASIS EN ING. SOFT | F60: =VLOOKUP(A60,'Datos Personales'!A:M,8,0) -> dldallosp@udistrital.edu.co | G60: =VLOOKUP(A60,'Datos Personales'!A:M,9,0) -> leonardodallos@hotmail.com | H60: =VLOOKUP(A60,'Datos Personales'!A:M,5,FALSE) -> X | I60: =VLOOKUP(Tabla4[[#This Row],[CODIGO]],'ESTADOS ESTUDIANTES'!B:M,12,0) -> 2022-1 | J60: Investigación | K60: MODELO DE LA DINAMICA ESPACIO-TEMPORAL DE LOS ACCIDENTES DE TRANSITO DESDE UNA OPTICA DE SISTEMAS COMPLEJOS | L60: Miguel Alberto Melgarejo | N60: 43636 | O60: 2019 | P60: LAMIC | Q60: Andres Eduardo Gaona Barrera | R60: 44012 | S60: =IF(Tabla4[[#This Row],[FECHA DE ACEPTACION DEL GRUP. INV.]]="","",DATE(YEAR(Tabla4[[#This Row],[FECHA DE ACEPTACION DEL GRUP. INV.]])+2,MONTH(Tabla4[[#This Row],[FECHA DE ACEPTACION DEL GRUP. INV.]]),DAY(Tabla4[[#This Row],[FECHA DE ACEPTACION DEL GRUP. INV.]]))) -> 44742 | T60: =IF(Tabla4[[#This Row],[FECHA DE ACEPTACION DEL GRUP. INV.]]="","",IF(Tabla4[[#This Row],[FECHA DE VENCIMIENTO ANTE PROYECTO]]<TODAY(),"SÍ","NO")) -> SÍ | W60: 08-2020 | AJ60: =IFERROR(VLOOKUP(AI60,Listas!K:L,2,0),"") | AK60: =IFERROR(VLOOKUP(AJ60,Listas!L:M,2,0),"") | BB60: =IFERROR(ROUND(AVERAGE(AY60,AX60,AS60,AR60),0),"") | BC60: =BB60*(100%-AJ60) -> #VALUE! | BD60: =SUM(BC60,AK60) -> #VALUE! | BG60: =IF(OR(H60="A",$H60="D",$H60="P",$H60="V"),L60,"")
A61: 20191495010 | B61: =VLOOKUP(A61,'Datos Personales'!A:M,2,FALSE) -> DÍAZ MONJE KEVIN CAMILO | C61: =VLOOKUP(A61,'ESTADOS ESTUDIANTES'!B:L,11,0) -> 1022395664 | D61: =VLOOKUP(A61,'Datos Personales'!$A:$M,3,FALSE) -> 495 | E61: =VLOOKUP(Tabla4[[#This Row],[ENFASIS]],Listas!$R$2:$S$8,2,0) -> ENFASIS EN ING. SOFT | F61: =VLOOKUP(A61,'Datos Personales'!A:M,8,0) -> kcdiazm@udistrital.edu.co | G61: =VLOOKUP(A61,'Datos Personales'!A:M,9,0) -> kcdiazm@correo.udistrital.edu.co | H61: =VLOOKUP(A61,'Datos Personales'!A:M,5,FALSE) -> E | I61: =VLOOKUP(Tabla4[[#This Row],[CODIGO]],'ESTADOS ESTUDIANTES'!B:M,12,0) -> 2025-3 | J61: Investigación | K61: Modelo de clasificación de imágenes basado en multiview learning | L61: Nancy Yaneth Gelvez | N61: 45722 | O61: 2019 | P61: GIIRA | Q61: Carlos Enrique Montenegro Marin | R61: 45727 | S61: =IF(Tabla4[[#This Row],[FECHA DE ACEPTACION DEL GRUP. INV.]]="","",DATE(YEAR(Tabla4[[#This Row],[FECHA DE ACEPTACION DEL GRUP. INV.]])+2,MONTH(Tabla4[[#This Row],[FECHA DE ACEPTACION DEL GRUP. INV.]]),DAY(Tabla4[[#This Row],[FECHA DE ACEPTACION DEL GRUP. INV.]]))) -> 46457 | T61: =IF(Tabla4[[#This Row],[FECHA DE ACEPTACION DEL GRUP. INV.]]="","",IF(Tabla4[[#This Row],[FECHA DE VENCIMIENTO ANTE PROYECTO]]<TODAY(),"SÍ","NO")) -> NO | U61: NO | W61: 012-2025 | Y61: 43964 | Z61: 93.91 | AA61: 45323 | AB61: 110 | AC61: B1 | AD61: 013-2025 | AE61: 45819 | AF61: Modelo de clasificación de ímagenes basado en multiview learning | AG61: IV Congreso Internacional en Ingeniería, Tecnología e Innovación – CIITI 2025 | AH61: 2025 | AI61: Ponencia | AJ61: =IFERROR(VLOOKUP(AI61,Listas!K:L,2,0),"") -> 0.2 | AK61: =IFERROR(VLOOKUP(AJ61,Listas!L:M,2,0),"") -> 10 | AM61: 013-2025 | AN61: 45819 | AO61: Paulo Alonso Gaona Garcia | AU61: Gerardo Alcides Muñoz Quiñones | BB61: =IFERROR(AVERAGE(AR61,AS61,AX61,AY61),"") | BC61: =BB61*(100%-AJ61) -> #VALUE! | BD61: =SUM(BC61,AK61) -> #VALUE! | BG61: =IF(OR(H61="A",$H61="D",$H61="P",$H61="V"),L61,"")
A62: 20191495011 | B62: =VLOOKUP(A62,'Datos Personales'!A:M,2,FALSE) -> GARCIA BARAHONA YENY PAOLA | C62: =VLOOKUP(A62,'ESTADOS ESTUDIANTES'!B:L,11,0) -> 1121819760 | D62: =VLOOKUP(A62,'Datos Personales'!$A:$M,3,FALSE) -> 495 | E62: =VLOOKUP(Tabla4[[#This Row],[ENFASIS]],Listas!$R$2:$S$8,2,0) -> ENFASIS EN ING. SOFT | F62: =VLOOKUP(A62,'Datos Personales'!A:M,8,0) -> ypgarciab@correo.udistrital.edu.co | G62: =VLOOKUP(A62,'Datos Personales'!A:M,9,0) -> ingpaolagarcia@gmail.com | H62: =VLOOKUP(A62,'Datos Personales'!A:M,5,FALSE) -> X | I62: =VLOOKUP(Tabla4[[#This Row],[CODIGO]],'ESTADOS ESTUDIANTES'!B:M,12,0) -> 2019-1 | J62: Investigación | K62: MECANISMO DE INTELIGENCIA ARTIFICIAL PARA PREDECIR EL POSIBLE EMPAREJAMINTO EMPRESARIAL ENTRE LA OFERTA Y LA DEMANDA DEL SECTOR DE CALZADO PARA MIPYMES EN VILLAVICENCIO, META - COLOMBIA | L62: Paulo Cesar Coronado | N62: 43630 | O62: 2019 | P62: GITEM ++ | Q62: Lilia Edith Aparicio Pico | S62: =IF(Tabla4[[#This Row],[FECHA DE ACEPTACION DEL GRUP. INV.]]="","",DATE(YEAR(Tabla4[[#This Row],[FECHA DE ACEPTACION DEL GRUP. INV.]])+2,MONTH(Tabla4[[#This Row],[FECHA DE ACEPTACION DEL GRUP. INV.]]),DAY(Tabla4[[#This Row],[FECHA DE ACEPTACION DEL GRUP. INV.]]))) | T62: =IF(Tabla4[[#This Row],[FECHA DE ACEPTACION DEL GRUP. INV.]]="","",IF(Tabla4[[#This Row],[FECHA DE VENCIMIENTO ANTE PROYECTO]]<TODAY(),"SÍ","NO")) | AJ62: =IFERROR(VLOOKUP(AI62,Listas!K:L,2,0),"") | AK62: =IFERROR(VLOOKUP(AJ62,Listas!L:M,2,0),"") | BB62: =IFERROR(ROUND(AVERAGE(AY62,AX62,AS62,AR62),0),"") | BC62: =BB62*(100%-AJ62) -> #VALUE! | BD62: =SUM(BC62,AK62) -> #VALUE! | BG62: =IF(OR(H62="A",$H62="D",$H62="P",$H62="V"),L62,"")
A63: 20191495012 | B63: =VLOOKUP(A63,'Datos Personales'!A:M,2,FALSE) -> GUERRERO BERMÚDEZ CRISTIAN ANDRÉS | C63: =VLOOKUP(A63,'ESTADOS ESTUDIANTES'!B:L,11,0) -> 80818510 | D63: =VLOOKUP(A63,'Datos Personales'!$A:$M,3,FALSE) -> 495 | E63: =VLOOKUP(Tabla4[[#This Row],[ENFASIS]],Listas!$R$2:$S$8,2,0) -> ENFASIS EN ING. SOFT | F63: =VLOOKUP(A63,'Datos Personales'!A:M,8,0) -> caguerrerob@correo.udistrital.edu.co | G63: =VLOOKUP(A63,'Datos Personales'!A:M,9,0) -> cristianandresgb@hotmail.com | H63: =VLOOKUP(A63,'Datos Personales'!A:M,5,FALSE) -> X | I63: =VLOOKUP(Tabla4[[#This Row],[CODIGO]],'ESTADOS ESTUDIANTES'!B:M,12,0) -> 2019-1 | S63: =IF(Tabla4[[#This Row],[FECHA DE ACEPTACION DEL GRUP. INV.]]="","",DATE(YEAR(Tabla4[[#This Row],[FECHA DE ACEPTACION DEL GRUP. INV.]])+2,MONTH(Tabla4[[#This Row],[FECHA DE ACEPTACION DEL GRUP. INV.]]),DAY(Tabla4[[#This Row],[FECHA DE ACEPTACION DEL GRUP. INV.]]))) | T63: =IF(Tabla4[[#This Row],[FECHA DE ACEPTACION DEL GRUP. INV.]]="","",IF(Tabla4[[#This Row],[FECHA DE VENCIMIENTO ANTE PROYECTO]]<TODAY(),"SÍ","NO")) | AJ63: =IFERROR(VLOOKUP(AI63,Listas!K:L,2,0),"") | AK63: =IFERROR(VLOOKUP(AJ63,Listas!L:M,2,0),"") | BB63: =IFERROR(ROUND(AVERAGE(AY63,AX63,AS63,AR63),0),"") | BC63: =BB63*(100%-AJ63) -> #VALUE! | BD63: =SUM(BC63,AK63) -> #VALUE! | BG63: =IF(OR(H63="A",$H63="D",$H63="P",$H63="V"),L63,"")
A64: 20191495013 | B64: =VLOOKUP(A64,'Datos Personales'!A:M,2,FALSE) -> HERNÁNDEZ MONTEALEGRE DANIEL ALEXANDER | C64: =VLOOKUP(A64,'ESTADOS ESTUDIANTES'!B:L,11,0) -> 1014277134 | D64: =VLOOKUP(A64,'Datos Personales'!$A:$M,3,FALSE) -> 495 | E64: =VLOOKUP(Tabla4[[#This Row],[ENFASIS]],Listas!$R$2:$S$8,2,0) -> ENFASIS EN ING. SOFT | F64: =VLOOKUP(A64,'Datos Personales'!A:M,8,0) -> danahernandezm@udistrital.edu.co | G64: =VLOOKUP(A64,'Datos Personales'!A:M,9,0) -> dahm35@hotmail.com | H64: =VLOOKUP(A64,'Datos Personales'!A:M,5,FALSE) -> E | I64: =VLOOKUP(Tabla4[[#This Row],[CODIGO]],'ESTADOS ESTUDIANTES'!B:M,12,0) -> 2025-3 | J64: Investigación | K64: Modelo de asignación de recursos indivisibles con restricciones de exclusividad aplicando agentes autónomos mediante negociación distribuida | L64: Julio Baron Velandia | M64: Sebastian Camilo Vanegas Ayala | N64: 45796 | O64: 2019 | P64: INTECSE | Q64: Julio Baron Velandia | R64: 45800 | S64: =IF(Tabla4[[#This Row],[FECHA DE ACEPTACION DEL GRUP. INV.]]="","",DATE(YEAR(Tabla4[[#This Row],[FECHA DE ACEPTACION DEL GRUP. INV.]])+2,MONTH(Tabla4[[#This Row],[FECHA DE ACEPTACION DEL GRUP. INV.]]),DAY(Tabla4[[#This Row],[FECHA DE ACEPTACION DEL GRUP. INV.]]))) -> 46530 | T64: =IF(Tabla4[[#This Row],[FECHA DE ACEPTACION DEL GRUP. INV.]]="","",IF(Tabla4[[#This Row],[FECHA DE VENCIMIENTO ANTE PROYECTO]]<TODAY(),"SÍ","NO")) -> NO | U64: NO | W64: 012-2025 | AA64: 45323 | AB64: 151 | AC64: B2 | AD64: 020-2025 | AE64: 45945 | AF64: Agentes inteligentes para gestión de recursos en campañas multicanal de marketing digital | AG64: Congreso internacional Ingeniería tecnología e innovación CIITI 2025 | AH64: 2025 | AI64: Ponencia | AJ64: =IFERROR(VLOOKUP(AI64,Listas!K:L,2,0),"") -> 0.2 | AK64: =IFERROR(VLOOKUP(AJ64,Listas!L:M,2,0),"") -> 10 | AL64: 45929 | AM64: 020-2025 | AN64: 45945 | AO64: Oswaldo Romero | AU64: Jorge Enrique Rodriguez Rodriguez | BB64: =IFERROR(AVERAGE(AR64,AS64,AX64,AY64),"") | BC64: =BB64*(100%-AJ64) -> #VALUE! | BD64: =SUM(BC64,AK64) -> #VALUE! | BG64: =IF(OR(H64="A",$H64="D",$H64="P",$H64="V"),L64,"")
A65: 20191495014 | B65: =VLOOKUP(A65,'Datos Personales'!A:M,2,FALSE) -> HURTADO ROMERO JAIME ARTURO | C65: =VLOOKUP(A65,'ESTADOS ESTUDIANTES'!B:L,11,0) -> 1015439205 | D65: =VLOOKUP(A65,'Datos Personales'!$A:$M,3,FALSE) -> 495 | E65: =VLOOKUP(Tabla4[[#This Row],[ENFASIS]],Listas!$R$2:$S$8,2,0) -> ENFASIS EN ING. SOFT | F65: =VLOOKUP(A65,'Datos Personales'!A:M,8,0) -> jaahurtador@correo.udistrital.edu.co | G65: =VLOOKUP(A65,'Datos Personales'!A:M,9,0) -> jart1221@gmail.com | H65: =VLOOKUP(A65,'Datos Personales'!A:M,5,FALSE) -> X | I65: =VLOOKUP(Tabla4[[#This Row],[CODIGO]],'ESTADOS ESTUDIANTES'!B:M,12,0) -> 2019-1 | S65: =IF(Tabla4[[#This Row],[FECHA DE ACEPTACION DEL GRUP. INV.]]="","",DATE(YEAR(Tabla4[[#This Row],[FECHA DE ACEPTACION DEL GRUP. INV.]])+2,MONTH(Tabla4[[#This Row],[FECHA DE ACEPTACION DEL GRUP. INV.]]),DAY(Tabla4[[#This Row],[FECHA DE ACEPTACION DEL GRUP. INV.]]))) | T65: =IF(Tabla4[[#This Row],[FECHA DE ACEPTACION DEL GRUP. INV.]]="","",IF(Tabla4[[#This Row],[FECHA DE VENCIMIENTO ANTE PROYECTO]]<TODAY(),"SÍ","NO")) | AJ65: =IFERROR(VLOOKUP(AI65,Listas!K:L,2,0),"") | AK65: =IFERROR(VLOOKUP(AJ65,Listas!L:M,2,0),"") | BB65: =IFERROR(ROUND(AVERAGE(AY65,AX65,AS65,AR65),0),"") | BC65: =BB65*(100%-AJ65) -> #VALUE! | BD65: =SUM(BC65,AK65) -> #VALUE! | BG65: =IF(OR(H65="A",$H65="D",$H65="P",$H65="V"),L65,"")
A66: 20191495016 | B66: =VLOOKUP(A66,'Datos Personales'!A:M,2,FALSE) -> MARTÍNEZ CERVERA DANIEL ESTEBAN | C66: =VLOOKUP(A66,'ESTADOS ESTUDIANTES'!B:L,11,0) -> 1019112987 | D66: =VLOOKUP(A66,'Datos Personales'!$A:$M,3,FALSE) -> 495 | E66: =VLOOKUP(Tabla4[[#This Row],[ENFASIS]],Listas!$R$2:$S$8,2,0) -> ENFASIS EN ING. SOFT | F66: =VLOOKUP(A66,'Datos Personales'!A:M,8,0) -> demartinezc@correo.udistrital.edu.co | G66: =VLOOKUP(A66,'Datos Personales'!A:M,9,0) -> demartinezc@correo.udistrital.edu.co | H66: =VLOOKUP(A66,'Datos Personales'!A:M,5,FALSE) -> E | I66: =VLOOKUP(Tabla4[[#This Row],[CODIGO]],'ESTADOS ESTUDIANTES'!B:M,12,0) -> 2021-1 | J66: Investigación | K66: MODELO DE PRONOSTICO EN LA EDUCACION SUPERIOR EN PRUEBAS ESPECIFICAS DE INGENIERIA, LICENCIATURA, Y PENSAMIENTO CIENTIFICO MATEMATCICO EN SABER PRO APLICANDO MACHINE LEARNING | L66: Octavio Jose Salcedo | M66: Marco Aguilera Prado | N66: 43616 | O66: 2019 | P66: INTERNET INTELIGENTE | Q66: Octavio Jose Salcedo Parra | R66: 43800 | S66: =IF(Tabla4[[#This Row],[FECHA DE ACEPTACION DEL GRUP. INV.]]="","",DATE(YEAR(Tabla4[[#This Row],[FECHA DE ACEPTACION DEL GRUP. INV.]])+2,MONTH(Tabla4[[#This Row],[FECHA DE ACEPTACION DEL GRUP. INV.]]),DAY(Tabla4[[#This Row],[FECHA DE ACEPTACION DEL GRUP. INV.]]))) -> 44531 | T66: =IF(Tabla4[[#This Row],[FECHA DE ACEPTACION DEL GRUP. INV.]]="","",IF(Tabla4[[#This Row],[FECHA DE VENCIMIENTO ANTE PROYECTO]]<TODAY(),"SÍ","NO")) -> SÍ | W66: 01-2020 | AA66: 43964 | AB66: 72.17 | AC66: B1 | AF66: NSGA-II y Greedy 2-opt Paralelo (PNG2) implementado en CUDA C++ para la solución de problemas de asignación cuadrática multiobjetivo mQAP aplicables a la toma de decisiones en planeación estratégica hotelera | AJ66: =IFERROR(VLOOKUP(AI66,Listas!K:L,2,0),"") | AK66: =IFERROR(VLOOKUP(AJ66,Listas!L:M,2,0),"") | AL66: 44172 | AM66: 16-2020 | AO66: Leonardo Rodriguez Contreras | AP66: 44174 | AQ66: 44256 | AR66: 40 | AS66: 42 | AT66: Aprobado | AU66: Nelson Enrique Vera Parra | AV66: 44174 | AW66: 44256 | AX66: 41 | AY66: 41 | AZ66: Aprobado | BA66: 44256 | BB66: 41 | BC66: =BB66*(100%-AJ66) -> #VALUE! | BD66: =SUM(BC66,AK66) -> #VALUE! | BF66: OK | BG66: =IF(OR(H66="A",$H66="D",$H66="P",$H66="V"),L66,"")
A67: 20191495017 | B67: =VLOOKUP(A67,'Datos Personales'!A:M,2,FALSE) -> NOVOA PERALTA LEONARDO ANDRÉS | C67: =VLOOKUP(A67,'ESTADOS ESTUDIANTES'!B:L,11,0) -> 1026254497 | D67: =VLOOKUP(A67,'Datos Personales'!$A:$M,3,FALSE) -> 495 | E67: =VLOOKUP(Tabla4[[#This Row],[ENFASIS]],Listas!$R$2:$S$8,2,0) -> ENFASIS EN ING. SOFT | F67: =VLOOKUP(A67,'Datos Personales'!A:M,8,0) -> lanovoap@udistrital.edu.co | G67: =VLOOKUP(A67,'Datos Personales'!A:M,9,0) -> leonardo.novoa@grupohousemedia.com | H67: =VLOOKUP(A67,'Datos Personales'!A:M,5,FALSE) -> E | I67: =VLOOKUP(Tabla4[[#This Row],[CODIGO]],'ESTADOS ESTUDIANTES'!B:M,12,0) -> 2025-3 | J67: Investigación | K67: Análisis de minería de datos y desarrollo de software con inteligencia artificial enfocado a la detección de perfiles de aprobaciones de visas para estados unidos | L67: Victor Hugo Medina Garcia | N67: 45580 | O67: 2024 | P67: GICOGE | Q67: Victor Hugo Medina Garcia | R67: 45743 | S67: =IF(Tabla4[[#This Row],[FECHA DE ACEPTACION DEL GRUP. INV.]]="","",DATE(YEAR(Tabla4[[#This Row],[FECHA DE ACEPTACION DEL GRUP. INV.]])+2,MONTH(Tabla4[[#This Row],[FECHA DE ACEPTACION DEL GRUP. INV.]]),DAY(Tabla4[[#This Row],[FECHA DE ACEPTACION DEL GRUP. INV.]]))) -> 46473 | T67: =IF(Tabla4[[#This Row],[FECHA DE ACEPTACION DEL GRUP. INV.]]="","",IF(Tabla4[[#This Row],[FECHA DE VENCIMIENTO ANTE PROYECTO]]<TODAY(),"SÍ","NO")) -> NO | U67: NO | W67: 007-2025 | AA67: 43888 | AB67: 70.43 | AC67: B1 | AD67: 011-2025 | AE67: 45791 | AF67: Análisis de minería de datos y desarrollo de software con inteligencia artificial | AG67: Revista Prospectiva con ISSN en línea: 2216-1368 en el volumen 23 número 2 de Julio a diciembre. | AH67: 2025 | AI67: Revista B | AJ67: =IFERROR(VLOOKUP(AI67,Listas!K:L,2,0),"") -> 0.6 | AK67: =IFERROR(VLOOKUP(AJ67,Listas!L:M,2,0),"") -> 30 | AM67: 011-2025 | AN67: 45791 | AO67: Sandro Javier Bolaños | AQ67: 45824 | AR67: 50 | AS67: 50 | AT67: Aprobado | AU67: Jorge Enrique Rodriguez Rodriguez | AW67: 45824 | AX67: 50 | AY67: 50 | AZ67: Aprobado | BA67: 45824 | BB67: =IFERROR(AVERAGE(AR67,AS67,AX67,AY67),"") -> 50 | BC67: =BB67*(100%-AJ67) -> 20 | BD67: =SUM(BC67,AK67) -> 50 | BG67: =IF(OR(H67="A",$H67="D",$H67="P",$H67="V"),L67,"")
A68: 20191495018 | B68: =VLOOKUP(A68,'Datos Personales'!A:M,2,FALSE) -> OBREGON BARRERA CARLOS IVAN | C68: =VLOOKUP(A68,'ESTADOS ESTUDIANTES'!B:L,11,0) -> 1098675575 | D68: =VLOOKUP(A68,'Datos Personales'!$A:$M,3,FALSE) -> 495 | E68: =VLOOKUP(Tabla4[[#This Row],[ENFASIS]],Listas!$R$2:$S$8,2,0) -> ENFASIS EN ING. SOFT | F68: =VLOOKUP(A68,'Datos Personales'!A:M,8,0) -> ciobregonb@udistrital.edu.co | G68: =VLOOKUP(A68,'Datos Personales'!A:M,9,0) -> carlos.ivan.obregon@gmail.com | H68: =VLOOKUP(A68,'Datos Personales'!A:M,5,FALSE) -> X | I68: =VLOOKUP(Tabla4[[#This Row],[CODIGO]],'ESTADOS ESTUDIANTES'!B:M,12,0) -> 2022-3 | J68: Investigación | K68: MODELO DE PREDICCION DE VELOCIDAD DE TRAFICO BASADO EN APRENDIZAJE PROFUNDO UTILIZANDO COMPUTACION HETEROGENEA | L68: Nelson Enrique Vera Parra | N68: 43810 | O68: 2019 | P68: GICOGE | Q68: Jose Nelson Perez | R68: 43871 | S68: =IF(Tabla4[[#This Row],[FECHA DE ACEPTACION DEL GRUP. INV.]]="","",DATE(YEAR(Tabla4[[#This Row],[FECHA DE ACEPTACION DEL GRUP. INV.]])+2,MONTH(Tabla4[[#This Row],[FECHA DE ACEPTACION DEL GRUP. INV.]]),DAY(Tabla4[[#This Row],[FECHA DE ACEPTACION DEL GRUP. INV.]]))) -> 44602 | T68: =IF(Tabla4[[#This Row],[FECHA DE ACEPTACION DEL GRUP. INV.]]="","",IF(Tabla4[[#This Row],[FECHA DE VENCIMIENTO ANTE PROYECTO]]<TODAY(),"SÍ","NO")) -> SÍ | W68: 01-2020 | AA68: 44510 | AB68: 79 | AC68: B1 | AJ68: =IFERROR(VLOOKUP(AI68,Listas!K:L,2,0),"") | AK68: =IFERROR(VLOOKUP(AJ68,Listas!L:M,2,0),"") | BB68: =IFERROR(AVERAGE(AR68,AS68,AX68,AY68),"") | BC68: =BB68*(100%-AJ68) -> #VALUE! | BD68: =SUM(BC68,AK68) -> #VALUE! | BG68: =IF(OR(H68="A",$H68="D",$H68="P",$H68="V"),L68,"")
A69: 20191495020 | B69: =VLOOKUP(A69,'Datos Personales'!A:M,2,FALSE) -> PAEZ MARTINEZ YERSON ALEXANDER | C69: =VLOOKUP(A69,'ESTADOS ESTUDIANTES'!B:L,11,0) -> 1102715888 | D69: =VLOOKUP(A69,'Datos Personales'!$A:$M,3,FALSE) -> 495 | E69: =VLOOKUP(Tabla4[[#This Row],[ENFASIS]],Listas!$R$2:$S$8,2,0) -> ENFASIS EN ING. SOFT | F69: =VLOOKUP(A69,'Datos Personales'!A:M,8,0) -> yeapaezm@correo.udistrital.edu.co | G69: =VLOOKUP(A69,'Datos Personales'!A:M,9,0) -> yeralex19@gmail.com | H69: =VLOOKUP(A69,'Datos Personales'!A:M,5,FALSE) -> X | I69: =VLOOKUP(Tabla4[[#This Row],[CODIGO]],'ESTADOS ESTUDIANTES'!B:M,12,0) -> 2019-1 | S69: =IF(Tabla4[[#This Row],[FECHA DE ACEPTACION DEL GRUP. INV.]]="","",DATE(YEAR(Tabla4[[#This Row],[FECHA DE ACEPTACION DEL GRUP. INV.]])+2,MONTH(Tabla4[[#This Row],[FECHA DE ACEPTACION DEL GRUP. INV.]]),DAY(Tabla4[[#This Row],[FECHA DE ACEPTACION DEL GRUP. INV.]]))) | T69: =IF(Tabla4[[#This Row],[FECHA DE ACEPTACION DEL GRUP. INV.]]="","",IF(Tabla4[[#This Row],[FECHA DE VENCIMIENTO ANTE PROYECTO]]<TODAY(),"SÍ","NO")) | AJ69: =IFERROR(VLOOKUP(AI69,Listas!K:L,2,0),"") | AK69: =IFERROR(VLOOKUP(AJ69,Listas!L:M,2,0),"") | BB69: =IFERROR(ROUND(AVERAGE(AY69,AX69,AS69,AR69),0),"") | BC69: =(BB69*0.8)/10 -> #VALUE! | BD69: =SUM(BC69,AK69) -> #VALUE! | BG69: =IF(OR(H69="A",$H69="D",$H69="P",$H69="V"),L69,"")
