Workbook

Sheet LIQUIDACION
A1: LLAVE | B1: Ultima_Fecha | C1: Valor | D1: VIGENCIA | E1: CUENTA | F1: DESCRIPCION | G1: VALOR PROYECTO | H1: BENEFICIO | I1: % | K1: INGRESOS-EJECUCION A LA FECHA | L1: BENEF REAL | M1: BENEFI TOMADO | N1: A TOMAR | O1: IDEXUD | Q1: OP IDEXUD | R1: UNIVERSIDAD | S1: OP UD | T1: CDP | U1: RP | V1: USUARIO | W1: FECHA DE DILIGENCIAMIENTO | X1: OBSERVACIONES
A2: =_xlfn.CONCAT(E2,W2,L2) -> 291090640144222611712530,330077 | B2: =_xlfn.MAXIFS(W:W,E:E,E2) -> 45957 | C2: =_xlfn.MAXIFS(L:L,E:E,E2) -> 6.7887808e+08 | D2: 2021 | E2: 2910906401 | F2: ILUD | G2: 5623455339 | H2: 674814641 | I2: =+H2/G2 -> 0.12 | K2: 5097604417 | L2: =+K2*I2 -> 6.1171253e+08 | M2: 611712530 | N2: 63102111 | O2: =+N2 -> 63102111 | Q2: 52 | R2: 0 | S2: 0 | V2: LORELY | W2: 44222
A3: =_xlfn.CONCAT(E3,W3,L3) -> 24530104064423812318000 | B3: =_xlfn.MAXIFS(W:W,E:E,E3) -> 44238 | C3: =_xlfn.MAXIFS(L:L,E:E,E3) -> 12318000 | D3: 2020 | E3: 2453010406 | F3: CONV ESPECIFICO 001 DE 2019 UNIVERSIDAD FHNW | G3: 102650000 | H3: 12318000 | I3: =+H3/G3 -> 0.12 | K3: 102650000 | L3: =+K3*I3 -> 12318000 | M3: 8490000 | N3: =+L3-M3 -> 3828000 | O3: =ROUND((N3*40%),0) -> 1531200 | Q3: 455 | R3: =+N3-O3 -> 2296800 | S3: 456 | T3: 1891 | U3: 3180 | V3: MONICA MOYA | W3: 44238
A4: =_xlfn.CONCAT(E4,W4,L4) -> 245301999644238188205671,909939 | B4: =_xlfn.MAXIFS(W:W,E:E,E4) -> 44831 | C4: =_xlfn.MAXIFS(L:L,E:E,E4) -> 190206861 | D4: 2020 | E4: 2453019996 | F4: CONV 430 2016 IDIGER - FONDIGER | G4: 1829508300 | H4: 196018746 | I4: =+H4/G4 -> 0.10714286 | K4: 1756586275 | L4: =+K4*I4 -> 1.8820567e+08 | M4: 184341692 | N4: =+L4-M4 -> 3863979.9 | O4: =ROUND((N4*40%),0) -> 1545592 | Q4: 457 | R4: =+N4-O4 -> 2318387.9 | S4: 458 | T4: 1889 | U4: 3178 | V4: MONICA MOYA | W4: 44238
A5: =_xlfn.CONCAT(E5,W5,L5) -> 29109066024423839831418,9258679 | B5: =_xlfn.MAXIFS(W:W,E:E,E5) -> 44406 | C5: =_xlfn.MAXIFS(L:L,E:E,E5) -> 57170161 | D5: 2020 | E5: 2910906602 | F5: CTTO INTERV TECN 121 DE 2019 GOB NORTE SANTANDER | G5: 899333962 | H5: 74256933 | I5: =+H5/G5 -> 0.082568808 | K5: 482402738 | L5: =+K5*I5 -> 39831419 | M5: 22504801 | N5: =+L5-M5 -> 17326618 | O5: =ROUND((N5*40%),0) -> 6930647 | Q5: 459 | R5: =+N5-O5 -> 10395971 | S5: 460 | T5: 1885 | U5: 3174 | V5: MONICA MOYA | W5: 44238
A6: =_xlfn.CONCAT(E6,W6,L6) -> 291090629944251155982593 | B6: =_xlfn.MAXIFS(W:W,E:E,E6) -> 44251 | C6: =_xlfn.MAXIFS(L:L,E:E,E6) -> 155982593 | D6: 2021 | E6: 2910906299 | F6: CONT 148 DE 2016 FDL RAFAEL URIBE URIBE | G6: 1299854942 | H6: 155982593 | I6: =+H6/G6 -> 0.12 | K6: 1299854942 | L6: =+K6*I6 -> 155982593 | M6: 131629790 | N6: =+L6-M6 -> 24352803 | O6: =ROUND((N6*40%),0) -> 9741121 | Q6: 996 | R6: =+N6-O6 -> 14611682 | S6: 997 | T6: 283 | U6: 242 | V6: MONICA MOYA | W6: 44251
A7: =_xlfn.CONCAT(E7,W7,L7) -> 2910906646442522200000 | B7: =_xlfn.MAXIFS(W:W,E:E,E7) -> 44252 | C7: =_xlfn.MAXIFS(L:L,E:E,E7) -> 2200000 | D7: 2020 | E7: 2910906646 | F7: CTTO INTERADM 31-2019 CONCEJO MUNICIPAL DE CHIA | G7: 20000000 | H7: 2200000 | I7: =+H7/G7 -> 0.11 | K7: 20000000 | L7: =+K7*I7 -> 2200000 | M7: 1980000 | N7: =+L7-M7 -> 220000 | O7: =ROUND((N7*40%),0) -> 88000 | Q7: 461 | R7: =+N7-O7 -> 132000 | S7: 462 | T7: 1886 | U7: 3175 | V7: MONICA MOYA | W7: 44252
A8: =_xlfn.CONCAT(E8,W8,L8) -> 2910906651442528717773,44 | B8: =_xlfn.MAXIFS(W:W,E:E,E8) -> 44405 | C8: =_xlfn.MAXIFS(L:L,E:E,E8) -> 15872640 | D8: 2020 | E8: 2910906651 | F8: CTTO INTERVENTORIA 201-5-19 FONDO ROTATORIO POLICI | G8: 132272000 | H8: 15872640 | I8: =+H8/G8 -> 0.12 | K8: 72648112 | L8: =+K8*I8 -> 8717773.4 | M8: 5295370 | N8: =+L8-M8 -> 3422403.4 | O8: =ROUND((N8*40%),0) -> 1368961 | Q8: 463 | R8: =+N8-O8 -> 2053442.4 | S8: 464 | T8: 1890 | U8: 3179 | V8: MONICA MOYA | W8: 44252
A9: =_xlfn.CONCAT(E9,W9,L9) -> 2910906657442521359369,09 | B9: =_xlfn.MAXIFS(W:W,E:E,E9) -> 44252 | C9: =_xlfn.MAXIFS(L:L,E:E,E9) -> 1359369.1 | D9: 2020 | E9: 2910906657 | F9: CTTO INTERADM 001-2019 CONCEJO DE TUNJA | G9: 12000000 | H9: 1527381 | I9: =+H9/G9 -> 0.12728175 | K9: 10680000 | L9: =+K9*I9 -> 1359369.1 | M9: 0 | N9: =+L9-M9 -> 1359369.1 | O9: =ROUND((N9*40%),0) -> 543748 | Q9: 465 | R9: =+N9-O9 -> 815621.09 | S9: 466 | T9: 1887 | U9: 3176 | V9: MONICA MOYA | W9: 44252
A10: =_xlfn.CONCAT(E10,W10,L10) -> 2910906661442522083630 | B10: =_xlfn.MAXIFS(W:W,E:E,E10) -> 44252 | C10: =_xlfn.MAXIFS(L:L,E:E,E10) -> 2083630 | D10: 2020 | E10: 2910906661 | F10: CPS 03 de 2019 ASAMBLEA DEPARTAMENTAL DEL CESAR | G10: 12000000 | H10: 2083630 | I10: =+H10/G10 -> 0.17363583 | K10: 12000000 | L10: =+K10*I10 -> 2083630 | M10: 0 | N10: =+L10-M10 -> 2083630 | O10: =ROUND((N10*40%),0) -> 833452 | Q10: 467 | R10: =+N10-O10 -> 1250178 | S10: 468 | T10: 1888 | U10: 3177 | V10: MONICA MOYA | W10: 44252
A11: =_xlfn.CONCAT(E11,W11,L11) -> 29109011644425716310893 | B11: =_xlfn.MAXIFS(W:W,E:E,E11) -> 44434 | C11: =_xlfn.MAXIFS(L:L,E:E,E11) -> 16310893 | D11: 2021 | E11: 2910901164 | F11: CTTO INTERADM 061-5-19 FONDO ROTATORIO POLICIA | G11: 153000000 | H11: 16392857 | I11: =+H11/G11 -> 0.10714286 | K11: 152234999 | L11: =ROUND((+K11*I11),0) -> 16310893 | M11: 14037154 | N11: 2273739 | O11: =ROUND((N11*40%),0) -> 909496 | Q11: 1037 | R11: =+N11-O11 -> 1364243 | S11: 1038 | T11: 321 | U11: 314 | V11: MONICA MOYA | W11: 44257
A12: =_xlfn.CONCAT(E12,W12,L12) -> 291090596144257982934233 | B12: =_xlfn.MAXIFS(W:W,E:E,E12) -> 44498 | C12: =_xlfn.MAXIFS(L:L,E:E,E12) -> 1224203654 | D12: 2021 | E12: 2910905961 | F12: MODIFICATORIO 2 ANEXO FINANCIERO 1029 2010 | G12: 8349652066 | H12: 934245965 | I12: =+H12/G12 -> 0.11189041 | K12: 8784794540 | L12: =ROUND((+K12*I12),0) -> 982934233 | M12: 896365068 | N12: =+L12-M12 -> 86569165 | O12: =ROUND((N12*40%),0) -> 34627666 | Q12: 1039 | R12: =+N12-O12 -> 51941499 | S12: 1040 | T12: 323 | U12: 315 | V12: MONICA MOYA | W12: 44257
A13: =_xlfn.CONCAT(E13,W13,L13) -> 24530183014425760556114 | B13: =_xlfn.MAXIFS(W:W,E:E,E13) -> 45099 | C13: =_xlfn.MAXIFS(L:L,E:E,E13) -> 133063733 | D13: 2021 | E13: 2453018301 | F13: CONV. INTERAD.389 2019 FDL CIUDAD BOLIVAR | G13: =941984000+470992000 -> 1412976000 | H13: 151390286 | I13: =+H13/G13 -> 0.10714286 | K13: 565190400 | L13: =ROUND((+K13*I13),0) -> 60556114 | M13: 0 | N13: =+L13-M13 -> 60556114 | O13: =ROUND((N13*40%),0) -> 24222446 | Q13: 1041 | R13: =+N13-O13 -> 36333668 | S13: 1042 | T13: 324 | U13: 316 | V13: MONICA MOYA | W13: 44257
A14: =_xlfn.CONCAT(E14,W14,L14) -> 24530183024425980828827 | B14: =_xlfn.MAXIFS(W:W,E:E,E14) -> 44434 | C14: =_xlfn.MAXIFS(L:L,E:E,E14) -> 89809808 | D14: 2021 | E14: 2453018302 | F14: CONV.COOP.003 2020 CAR VALLES DEL SINU Y SAN JORGE | G14: 838224872 | H14: 89809808 | I14: =+H14/G14 -> 0.10714286 | K14: 754402385 | L14: =ROUND((+K14*I14),0) -> 80828827 | M14: 62866866 | N14: =+L14-M14 -> 17961961 | Q14: 1043 | S14: 1044 | T14: 325 | U14: 317 | V14: MONICA MOYA | W14: 44259 | X14: NO HAY SALDO EN LA CUENTA CONTABLE. NO REALIZARON EL INGRESO. SE ANULA
A15: =_xlfn.CONCAT(E15,W15,L15) -> 2910906153442571574445174 | B15: =_xlfn.MAXIFS(W:W,E:E,E15) -> 44404 | C15: =_xlfn.MAXIFS(L:L,E:E,E15) -> 1.6000309e+09 | D15: 2021 | E15: 2910906153 | F15: CONTRAT 1069 DE 2015 SENA | I15: 0.1071 | K15: 14694821628 | L15: 1574445174 | M15: 370028904 | N15: 200000000 | O15: =ROUND((N15*40%),0) -> 80000000 | Q15: 1080 | R15: =+N15-O15 -> 120000000 | S15: 1081 | T15: 326 | U15: 382 | V15: MONICA MOYA | W15: 44257 | X15: SEGÚN LO ESTABLECIDO CON DIANA CARO EL VR DEL BENEFICIO A TOMAR ES DE $200,000,000, EXISTEN UNAS MULTAS POR VALOR DE $441,785,257
A16: =_xlfn.CONCAT(E16,W16,L16) -> 291090616444263346814269 | B16: =_xlfn.MAXIFS(W:W,E:E,E16) -> 44617 | C16: =_xlfn.MAXIFS(L:L,E:E,E16) -> 356207712 | D16: 2021 | E16: 2910906164 | F16: CONTR 226 FDL KENNEDY | G16: 3324605309 | H16: 356207712 | I16: =+H16/G16 -> 0.10714286 | K16: 3236933176 | L16: =ROUND((+K16*I16),0) -> 346814269 | M16: 291049114 | N16: 43224000 | O16: =ROUND((N16*40%),0) -> 17289600 | Q16: 1215 | R16: =+N16-O16 -> 25934400 | S16: 1216 | T16: 339 | U16: 414 | V16: KATIA FLOREZ | W16: 44263 | X16: SE APROPIA EL SALDO QUE HAY EN LA CUENTA CONTABLE.
A17: =_xlfn.CONCAT(E17,W17,L17) -> 29109067074427962142857 | B17: =_xlfn.MAXIFS(W:W,E:E,E17) -> 44279 | C17: =_xlfn.MAXIFS(L:L,E:E,E17) -> 62142857 | D17: 2021 | E17: 2910906707 | F17: CTTO INTERAD SFP-CDCTI-027-2020 GOBER.CUNDINAMARCA | G17: 580000000 | H17: 62142857 | I17: =+H17/G17 -> 0.10714286 | K17: 580000000 | L17: =ROUND((+K17*I17),0) -> 62142857 | M17: 55928571 | N17: 6214286 | O17: =ROUND((N17*40%),0) -> 2485714 | Q17: 1471 | R17: =+N17-O17 -> 3728572 | S17: 1472 | T17: 364 | U17: 508 | V17: MONICA MOYA | W17: 44279
A18: =_xlfn.CONCAT(E18,W18,L18) -> 2910906713442792257285 | B18: =_xlfn.MAXIFS(W:W,E:E,E18) -> 44279 | C18: =_xlfn.MAXIFS(L:L,E:E,E18) -> 2257285 | D18: 2021 | E18: 2910906713 | F18: CTTO INTER No SFP-CDCTI-044-2020 | G18: 21068000 | H18: 2257285 | I18: =+H18/G18 -> 0.10714282 | K18: 21068000 | L18: =ROUND((+K18*I18),0) -> 2257285 | M18: 0 | N18: 2257285 | O18: =ROUND((N18*40%),0) -> 902914 | Q18: 1473 | R18: =+N18-O18 -> 1354371 | S18: 1474 | T18: 343 | U18: 442 | V18: MONICA MOYA | W18: 44279
A19: =_xlfn.CONCAT(E19,W19,L19) -> 29109063204427925617621 | B19: =_xlfn.MAXIFS(W:W,E:E,E19) -> 44279 | C19: =_xlfn.MAXIFS(L:L,E:E,E19) -> 25617621 | D19: 2021 | E19: 2910906320 | F19: CONTRATO 083 DE 2017 ICCU | G19: 282092787 | H19: 30224228 | I19: =+H19/G19 -> 0.10714286 | K19: 239097794 | L19: =ROUND((+K19*I19),0) -> 25617621 | M19: 25617621 | N19: =+H19-L19 -> 4606607 | O19: =ROUND((N19*40%),0) -> 1842643 | Q19: 1475 | R19: =+N19-O19 -> 2763964 | S19: 1476 | T19: 344 | U19: 443 | V19: MONICA MOYA | W19: 44279
A20: =_xlfn.CONCAT(E20,W20,L20) -> 2453010405442799642857 | B20: =_xlfn.MAXIFS(W:W,E:E,E20) -> 44279 | C20: =_xlfn.MAXIFS(L:L,E:E,E20) -> 9642857 | D20: 2021 | E20: 2453010405 | F20: CONV INTERADM 80 DE 2019 REG ADMIN Y PLAN ESP RAPE | G20: 100000000 | H20: 10714285 | I20: =+H20/G20 -> 0.10714285 | J20: =+I20/H20 -> 1e-08 | K20: 90000000 | L20: =ROUND((+K20*I20),0) -> 9642857 | M20: 9639000 | N20: =+L20-M20 -> 3857 | O20: =ROUND((N20*40%),0) -> 1543 | Q20: 1477 | R20: =+N20-O20 -> 2314 | S20: 1478 | T20: 346 | U20: 444 | V20: MONICA MOYA | W20: 44279
A21: =_xlfn.CONCAT(E21,W21,L21) -> 2910906718442791875000 | B21: =_xlfn.MAXIFS(W:W,E:E,E21) -> 44279 | C21: =_xlfn.MAXIFS(L:L,E:E,E21) -> 1875000 | D21: 2021 | E21: 2910906718 | F21: CTTO INTER 230 IDECUT 2020 - ASAB | G21: 17500000 | H21: 1875000 | I21: =+H21/G21 -> 0.10714286 | K21: 17500000 | L21: =ROUND((+K21*I21),0) -> 1875000 | M21: 0 | N21: 1875000 | O21: =ROUND((N21*40%),0) -> 750000 | Q21: 1479 | R21: =+N21-O21 -> 1125000 | S21: 1480 | T21: 347 | U21: 445 | V21: MONICA MOYA | W21: 44279
A22: =_xlfn.CONCAT(E22,W22,L22) -> 2910901163442799521601 | B22: =_xlfn.MAXIFS(W:W,E:E,E22) -> 44279 | C22: =_xlfn.MAXIFS(L:L,E:E,E22) -> 9521601 | D22: 2021 | E22: 2910901163 | F22: CTTO INTERADM 025-5-19 FONDO ROTATORIO POLICIA | G22: 99238720 | H22: 10632720 | I22: =+H22/G22 -> 0.10714286 | K22: 88868274 | L22: =ROUND((+K22*I22),0) -> 9521601 | M22: 9517792 | N22: =+L22-M22 -> 3809 | O22: =ROUND((N22*40%),0) -> 1524 | Q22: 1481 | R22: =+N22-O22 -> 2285 | S22: 1482 | T22: 348 | U22: 446 | V22: MONICA MOYA | W22: 44279
A23: =_xlfn.CONCAT(E23,W23,L23) -> 29109066514427913872699 | B23: =_xlfn.MAXIFS(W:W,E:E,E23) -> 44405 | C23: =_xlfn.MAXIFS(L:L,E:E,E23) -> 15872640 | D23: 2021 | E23: 2910906651 | F23: CTTO INTERVENTORIA 201-5-19 FONDO ROTATORIO POLICIA | G23: 132272000 | H23: 15872640 | I23: =+H23/G23 -> 0.12 | K23: 115605827 | L23: =ROUND((+K23*I23),0) -> 13872699 | M23: 8717773 | N23: 4798715 | O23: =ROUND((N23*40%),0) -> 1919486 | Q23: 1483 | R23: =+N23-O23 -> 2879229 | S23: 1484 | T23: 349 | U23: 447 | V23: MONICA MOYA | W23: 44279 | X23: EL VR A APROPIAR DE BENEFICIO SEGÚN LOS INGRESOS A MARZO 24-2021 CORRESPONDE A $ 5,154,926, PERO SOLO DE TOMA $4,798,715 SEGÚN EL SALDO EXISTENTE A LA FECHA EN LA CTA CONTABLE 2910906651.
A24: =_xlfn.CONCAT(E24,W24,L24) -> 2910906699442792220540 | B24: =_xlfn.MAXIFS(W:W,E:E,E24) -> 44279 | C24: =_xlfn.MAXIFS(L:L,E:E,E24) -> 2220540 | D24: 2021 | E24: 2910906699 | F24: CTTO INTERADM 45 ASAMBLEA DEPARTAMENTAL | G24: 20000000 | H24: 2317891 | I24: =+H24/G24 -> 0.11589455 | K24: 19160000 | L24: =ROUND((+K24*I24),0) -> 2220540 | M24: 2220540 | N24: =+H24-L24 -> 97351 | O24: =ROUND((N24*40%),0) -> 38940 | Q24: 1485 | R24: =+N24-O24 -> 58411 | S24: 1486 | T24: 350 | U24: 448 | V24: MONICA MOYA | W24: 44279 | X24: SE APROPIA EL SALDO PTE DEL BENEFICIO ESTABLECIDO EN EL PRESUPUESTO, DEBIDO A QUE EL PROYECTO ESTA LIQUIDADO Y GENERA UN EXCEDENTE.
A25: =_xlfn.CONCAT(E25,W25,L25) -> 24530183064427918542880 | B25: =_xlfn.MAXIFS(W:W,E:E,E25) -> 44281 | C25: =_xlfn.MAXIFS(L:L,E:E,E25) -> 23107179 | D25: 2021 | E25: 2453018306 | F25: CONV INTER 092 RAP-E-UD-GICALYT-2020 | G25: 236667000 | H25: 25357179 | I25: =+H25/G25 -> 0.10714286 | K25: 173066880 | L25: =ROUND((+K25*I25),0) -> 18542880 | M25: 0 | N25: =+L25-M25 -> 18542880 | O25: =ROUND((N25*40%),0) -> 7417152 | Q25: 1487 | R25: =+N25-O25 -> 11125728 | S25: 1488 | T25: 351 | U25: 449 | V25: MONICA MOYA | W25: 44279
A26: =_xlfn.CONCAT(E26,W26,L26) -> 2453018307442791933071 | B26: =_xlfn.MAXIFS(W:W,E:E,E26) -> 44279 | C26: =_xlfn.MAXIFS(L:L,E:E,E26) -> 1933071 | D26: 2021 | E26: 2453018307 | F26: CENTRO PENSAMIENTO Y DIALOGO POLITICO | G26: 18042000 | H26: 1933071 | I26: =+H26/G26 -> 0.10714283 | K26: 18042000 | L26: =ROUND((+K26*I26),0) -> 1933071 | M26: 0 | N26: =+L26-M26 -> 1933071 | O26: =ROUND((N26*40%),0) -> 773228 | Q26: 1489 | R26: =+N26-O26 -> 1159843 | S26: 1490 | T26: 353 | U26: 450 | V26: MONICA MOYA | W26: 44279
A27: =_xlfn.CONCAT(E27,W27,L27) -> 2910901169442795308344 | B27: =_xlfn.MAXIFS(W:W,E:E,E27) -> 44434 | C27: =_xlfn.MAXIFS(L:L,E:E,E27) -> 5308344 | D27: 2021 | E27: 2910901169 | F27: CTTO INTERADM 152-5-19 INTERV FONDO ROTATORIO POLICIA | G27: 49793510 | H27: 5335019 | I27: =+H27/G27 -> 0.10714286 | K27: 49544542 | L27: =ROUND((+K27*I27),0) -> 5308344 | M27: 989610 | N27: =+L27-M27 -> 4318734 | O27: =ROUND((N27*40%),0) -> 1727494 | Q27: 1491 | R27: =+N27-O27 -> 2591240 | S27: 1492 | T27: 354 | U27: 451 | V27: MONICA MOYA | W27: 44279
A28: =_xlfn.CONCAT(E28,W28,L28) -> 29109058784427919860040 | B28: =_xlfn.MAXIFS(W:W,E:E,E28) -> 44279 | C28: =_xlfn.MAXIFS(L:L,E:E,E28) -> 19860040 | D28: 2021 | E28: 2910905878 | F28: G-27 2013 SERVIVIENDA | G28: 438947360 | H28: 47030074 | I28: =+H28/G28 -> 0.10714286 | K28: 185360377 | L28: =ROUND((+K28*I28),0) -> 19860040 | M28: 0 | N28: =+L28-M28 -> 19860040 | O28: =ROUND((N28*40%),0) -> 7944016 | Q28: 1493 | R28: =+N28-O28 -> 11916024 | S28: 1494 | T28: 355 | U28: 452 | V28: MONICA MOYA | W28: 44279
A29: =_xlfn.CONCAT(E29,W29,L29) -> 291090626044279306737224 | B29: =_xlfn.MAXIFS(W:W,E:E,E29) -> 44459 | C29: =_xlfn.MAXIFS(L:L,E:E,E29) -> 306737224 | D29: 2021 | E29: 2910906260 | F29: EMPRESA DE SERVICIOS PÚBICOS DE CHÍA EMSECHIA E.S.P. | G29: 4300708566 | H29: 516085028 | I29: =+H29/G29 -> 0.12 | K29: 2556143530 | L29: =ROUND((+K29*I29),0) -> 306737224 | M29: 203289922 | N29: 50000000 | O29: =ROUND((N29*40%),0) -> 20000000 | Q29: 1495 | R29: =+N29-O29 -> 30000000 | S29: 1496 | T29: 356 | U29: 453 | V29: MONICA MOYA | W29: 44279 | X29: SEGÚN LO ACORDADO CON DIANA CARO SE APROPIA $50,000,000
A30: =_xlfn.CONCAT(E30,W30,L30) -> 24530183064428123107179 | B30: =_xlfn.MAXIFS(W:W,E:E,E30) -> 44281 | C30: =_xlfn.MAXIFS(L:L,E:E,E30) -> 23107179 | D30: 2021 | E30: 2453018306 | F30: CONV INTER 092 RAP-E-UD-GICALYT-2020 | G30: 236667000 | H30: 25357179 | I30: =+H30/G30 -> 0.10714286 | K30: 215667000 | L30: =ROUND((+K30*I30),0) -> 23107179 | M30: 18542880 | N30: =+L30-M30 -> 4564299 | O30: =ROUND((N30*40%),0) -> 1825720 | Q30: 1546 | R30: =+N30-O30 -> 2738579 | S30: 1547 | T30: 449 | U30: 714 | V30: MONICA MOYA | W30: 44281 | X30: POR ERROR SE REGISTRO UN REINTEGRO DE UN AVANCE COMO UN INGRESO, SE CORRIJE EN ABRIL . OJO PARA TENER ENCUENTA AL APROPIAR BENEFICIO DE INGRESOS POSTERIORES A ABRIL 2021. EL INGRESO REAL DEL PROYECTO CON CORTE 23 DE ABRIL ES $194,067,000. SE TOMO MAS BENEFICIO DEL QUE CORRESPONDIA.
A31: =_xlfn.CONCAT(E31,W31,L31) -> 29109067214429110155046 | B31: =_xlfn.MAXIFS(W:W,E:E,E31) -> 44406 | C31: =_xlfn.MAXIFS(L:L,E:E,E31) -> 10897200 | D31: 2021 | E31: 2910906721 | F31: CTTO INTER 118-ICFE-2020 - INST DE CASAS FISCALES | G31: 90810000 | H31: 10897200 | I31: =+H31/G31 -> 0.12 | K31: 84625384 | L31: =ROUND((+K31*I31),0) -> 10155046 | M31: 0 | N31: =+L31-M31 -> 10155046 | O31: =ROUND((N31*40%),0) -> 4062018 | Q31: 1596 | R31: =+N31-O31 -> 6093028 | S31: 1597 | T31: 502 | U31: 760 | V31: MONICA MOYA | W31: 44291
A32: =_xlfn.CONCAT(E32,W32,L32) -> 2910906724442914467407 | B32: =_xlfn.MAXIFS(W:W,E:E,E32) -> 44291 | C32: =_xlfn.MAXIFS(L:L,E:E,E32) -> 4467407 | D32: 2021 | E32: 2910906724 | F32: CTTO INTER 2385 IDIPROM - 2020 | G32: 41695800 | H32: 4467407 | I32: =+H32/G32 -> 0.10714285 | K32: 41695800 | L32: =ROUND((+K32*I32),0) -> 4467407 | M32: 0 | N32: =+L32-M32 -> 4467407 | O32: =ROUND((N32*40%),0) -> 1786963 | Q32: 1598 | R32: =+N32-O32 -> 2680444 | S32: 1599 | T32: 503 | U32: 761 | V32: MONICA MOYA | W32: 44291
A33: =_xlfn.CONCAT(E33,W33,L33) -> 2910908024442933479129 | B33: =_xlfn.MAXIFS(W:W,E:E,E33) -> 44293 | C33: =_xlfn.MAXIFS(L:L,E:E,E33) -> 3479129 | D33: 2021 | E33: 2910908024 | F33: PROG ACADÉMICO TRANSIT FAC MEDIO AMBIENTE 2020-3 | G33: 28967499 | H33: 3479129 | I33: =+H33/G33 -> 0.12010457 | K33: 28967499 | L33: =ROUND((+K33*I33),0) -> 3479129 | M33: 0 | N33: =+L33-M33 -> 3479129 | O33: 3479129 | Q33: 1766 | R33: 0 | S33: 0 | T33: 504 | U33: 768 | V33: MONICA MOYA | W33: 44293
A34: =_xlfn.CONCAT(E34,W34,L34) -> 291090631544294110362094 | B34: =_xlfn.MAXIFS(W:W,E:E,E34) -> 44375 | C34: =_xlfn.MAXIFS(L:L,E:E,E34) -> 122624549 | D34: 2021 | E34: 2910906315 | F34: CONT 232 DE 2016 FDL USME | G34: 1144495782 | H34: 122624549 | I34: =+H34/G34 -> 0.10714286 | K34: =840262114+189784089 -> 1030046203 | L34: =ROUND((+K34*I34),0) -> 110362094 | M34: 69140917 | N34: =+L34-M34 -> 41221177 | O34: =ROUND((N34*40%),0) -> 16488471 | Q34: 1935 | R34: =+N34-O34 -> 24732706 | S34: 1936 | T34: 508 | U34: 790 | V34: MONICA MOYA | W34: 44294
A35: =_xlfn.CONCAT(E35,W35,L35) -> 29109080084429412414836 | B35: =_xlfn.MAXIFS(W:W,E:E,E35) -> 44294 | C35: =_xlfn.MAXIFS(L:L,E:E,E35) -> 12414836 | D35: 2021 | E35: 2910908008 | F35: PROGRAMA ACADÉMICO DE GRADO FACULTAD TECNOLÓGICA | G35: 115871800 | H35: 12414836 | I35: =+H35/G35 -> 0.10714286 | K35: 115871800 | L35: =ROUND((+K35*I35),0) -> 12414836 | M35: 12127836 | N35: =+L35-M35 -> 287000 | O35: =ROUND((N35*100%),0) -> 287000 | Q35: 1937 | R35: 0 | S35: 0 | T35: 509 | U35: 791 | V35: MONICA MOYA | W35: 44294
A36: =_xlfn.CONCAT(E36,W36,L36) -> 2910908021442953644222 | B36: =_xlfn.MAXIFS(W:W,E:E,E36) -> 44295 | C36: =_xlfn.MAXIFS(L:L,E:E,E36) -> 3644222 | D36: 2021 | E36: 2910908021 | F36: PROGRAMA ACADÉMICO DE GRADO 2020-III FAC ING | G36: 30368519 | H36: 3644222 | I36: =+H36/G36 -> 0.11999999 | K36: 30368519 | L36: =ROUND((+K36*I36),0) -> 3644222 | M36: 0 | N36: =+L36-M36 -> 3644222 | O36: =ROUND((N36*100%),0) -> 3644222 | Q36: 1938 | R36: 0 | S36: 0 | T36: 514 | U36: 804 | V36: MONICA MOYA | W36: 44295
A37: =_xlfn.CONCAT(E37,W37,L37) -> 2910908023442957268322 | B37: =_xlfn.MAXIFS(W:W,E:E,E37) -> 44295 | C37: =_xlfn.MAXIFS(L:L,E:E,E37) -> 7268322 | D37: 2021 | E37: 2910908023 | F37: PROGRAMA ACADÉMICO DE GRADO FACULTAD TECNOLÓGICA | G37: 60569350 | H37: 7268322 | I37: =+H37/G37 -> 0.12 | K37: 60569350 | L37: =ROUND((+K37*I37),0) -> 7268322 | M37: 0 | N37: =+L37-M37 -> 7268322 | O37: =ROUND((N37*100%),0) -> 7268322 | Q37: 1939 | R37: 0 | S37: 0 | T37: 515 | U37: 823 | V37: MONICA MOYA | W37: 44295
A38: =_xlfn.CONCAT(E38,W38,L38) -> 2910906629443015857500 | B38: =_xlfn.MAXIFS(W:W,E:E,E38) -> 44770 | C38: =_xlfn.MAXIFS(L:L,E:E,E38) -> 6214482 | D38: 2021 | E38: 2910906629 | F38: DIPLOMADO EN INNOVACIÓN FORM Y EVAL DE PROYECTOS | G38: 54670000 | H38: 5857500 | I38: =+H38/G38 -> 0.10714286 | K38: 54670000 | L38: =+K38*I38 -> 5857500 | M38: 0 | N38: 5591250 | O38: =ROUND((N38*100%),0) -> 5591250 | Q38: 1973 | R38: 0 | S38: 0 | T38: 544 | U38: 871 | V38: MONICA MOYA | W38: 44301 | X38: SE APROPIA $5,591,250 SEGÚN CORREO ENVIADO POR CARLOS ESTE ES EL SALDO PRESUPUESTAL.
A39: =_xlfn.CONCAT(E39,W39,L39) -> 2910908005443012413200 | B39: =_xlfn.MAXIFS(W:W,E:E,E39) -> 44301 | C39: =_xlfn.MAXIFS(L:L,E:E,E39) -> 2413200 | D39: 2021 | E39: 2910908005 | F39: DIPLOMADO EN ECONOMIA CIRCULAR Y SOSTENIBILIDAD | G39: 20110000 | H39: 2413200 | I39: =+H39/G39 -> 0.12 | K39: 20110000 | L39: =+K39*I39 -> 2413200 | M39: 1733400 | N39: =+L39-M39 -> 679800 | O39: =ROUND((N39*100%),0) -> 679800 | Q39: 1974 | R39: 0 | S39: 0 | T39: 545 | U39: 872 | V39: MONICA MOYA | W39: 44301
A40: =_xlfn.CONCAT(E40,W40,L40) -> 29109067194430816379464 | B40: =_xlfn.MAXIFS(W:W,E:E,E40) -> 44529 | C40: =_xlfn.MAXIFS(L:L,E:E,E40) -> 71236607 | D40: 2021 | E40: 2910906719 | F40: CTTO INTER 085-00-D-CACOM1-DEDHU-2020 | G40: 664875000 | H40: 71236607 | I40: =+H40/G40 -> 0.10714286 | K40: 152875000 | L40: =ROUND((+K40*I40),0) -> 16379464 | M40: 0 | N40: =+L40-M40 -> 16379464 | O40: =ROUND((N40*40%),0) -> 6551786 | Q40: 2467 | R40: =+N40-O40 -> 9827678 | S40: 2468 | T40: 594 | U40: 958 | V40: MONICA MOYA | W40: 44308
A41: =_xlfn.CONCAT(E41,W41,L41) -> 24530183024430880828827 | B41: =_xlfn.MAXIFS(W:W,E:E,E41) -> 44434 | C41: =_xlfn.MAXIFS(L:L,E:E,E41) -> 89809808 | D41: 2021 | E41: 2453018302 | F41: CONV.COOP.003 2020 CAR VALLES DEL SINU Y SAN JORGE | G41: 838224872 | H41: 89809808 | I41: =+H41/G41 -> 0.10714286 | K41: 754402385 | L41: =ROUND((+K41*I41),0) -> 80828827 | M41: 62866866 | N41: =+L41-M41 -> 17961961 | O41: =ROUND((N41*40%),0) -> 7184784 | Q41: 2227 | R41: =+N41-O41 -> 10777177 | S41: 2228 | T41: 325 | U41: 317 | V41: MONICA MOYA | W41: 44308
A42: =_xlfn.CONCAT(E42,W42,L42) -> 24530183024430889199094 | B42: =_xlfn.MAXIFS(W:W,E:E,E42) -> 44434 | C42: =_xlfn.MAXIFS(L:L,E:E,E42) -> 89809808 | D42: 2021 | E42: 2453018302 | F42: CONV.COOP.003 2020 CAR VALLES DEL SINU Y SAN JORGE | G42: 838224872 | H42: 89809808 | I42: =+H42/G42 -> 0.10714286 | K42: 832524872 | L42: =ROUND((+K42*I42),0) -> 89199094 | M42: =62866866+17961961 -> 80828827 | N42: =+L42-M42 -> 8370267 | O42: =ROUND((N42*40%),0) -> 3348107 | Q42: 2469 | R42: =+N42-O42 -> 5022160 | S42: 2470 | T42: 595 | U42: 959 | V42: MONICA MOYA | W42: 44308
A43: =_xlfn.CONCAT(E43,W43,L43) -> 24530134064431264237720 | B43: =_xlfn.MAXIFS(W:W,E:E,E43) -> 44498 | C43: =_xlfn.MAXIFS(L:L,E:E,E43) -> 68202670 | D43: 2021 | E43: 2453013406 | F43: CONV 1594 DE 2016 CAR CUNDINAMARCA | G43: 628595167 | H43: 71375244 | I43: =+H43/G43 -> 0.11354724 | K43: 565735650 | L43: =ROUND((+K43*I43),0) -> 64237720 | M43: 0 | N43: =+L43-M43 -> 64237720 | O43: =ROUND((N43*40%),0) -> 25695088 | Q43: 2447 | R43: =+N43-O43 -> 38542632 | S43: 2448 | T43: 596 | U43: 964 | V43: MONICA MOYA | W43: 44312
A44: =_xlfn.CONCAT(E44,W44,L44) -> 24530183044431211640000 | B44: =_xlfn.MAXIFS(W:W,E:E,E44) -> 44312 | C44: =_xlfn.MAXIFS(L:L,E:E,E44) -> 11640000 | D44: 2021 | E44: 2453018304 | F44: CONV INTER 4130-2016 - SED-ICETEX 2020 | G44: 97000000 | H44: 11640000 | I44: =+H44/G44 -> 0.12 | K44: 97000000 | L44: =ROUND((+K44*I44),0) -> 11640000 | M44: 0 | N44: =+L44-M44 -> 11640000 | O44: =ROUND((N44*100%),0) -> 11640000 | Q44: 2449 | R44: =+N44-O44 -> 0 | S44: 0 | T44: 597 | U44: 965 | V44: MONICA MOYA | W44: 44312
A45: =_xlfn.CONCAT(E45,W45,L45) -> 2453018309443125357143 | B45: =_xlfn.MAXIFS(W:W,E:E,E45) -> 44463 | C45: =_xlfn.MAXIFS(L:L,E:E,E45) -> 10714286 | D45: 2021 | E45: 2453018309 | F45: CONV INTER 1004-2020 - IDPAC | G45: 100000000 | H45: 10714286 | I45: =+H45/G45 -> 0.10714286 | K45: 50000000 | L45: =ROUND((+K45*I45),0) -> 5357143 | M45: 0 | N45: =+L45-M45 -> 5357143 | O45: =ROUND((N45*100%),0) -> 5357143 | Q45: 2450 | R45: =+N45-O45 -> 0 | S45: 0 | T45: 598 | U45: 966 | V45: MONICA MOYA | W45: 44312
A46: =_xlfn.CONCAT(E46,W46,L46) -> 2910905961443121087367431 | B46: =_xlfn.MAXIFS(W:W,E:E,E46) -> 44498 | C46: =_xlfn.MAXIFS(L:L,E:E,E46) -> 1224203654 | D46: 2021 | E46: 2910905961 | F46: MODIFICATORIO 2 ANEXO FINANCIERO 1029 2010 | G46: 9849652066 | H46: 1114245965 | I46: =+H46/G46 -> 0.11312541 | K46: 9612052631 | L46: =ROUND((+K46*I46),0) -> 1087367431 | M46: 982934233 | N46: =+L46-M46 -> 104433198 | O46: =ROUND((N46*40%),0) -> 41773279 | Q46: 2451 | R46: =+N46-O46 -> 62659919 | S46: 2452 | T46: 599 | U46: 967 | V46: MONICA MOYA | W46: 44312
A47: =_xlfn.CONCAT(E47,W47,L47) -> 291090637044312246085114 | B47: =_xlfn.MAXIFS(W:W,E:E,E47) -> 45530 | C47: =_xlfn.MAXIFS(L:L,E:E,E47) -> 4.6723419e+08 | D47: 2018 | E47: 2910906370 | F47: CTTO INTERADM - INTERVENTORIA 2180684 - FONADE | G47: 3829020000 | H47: 410252143 | I47: =+H47/G47 -> 0.10714286 | K47: 2296794396 | L47: =ROUND((+K47*I47),0) -> 246085114 | M47: 158563039 | N47: 246085114 | O47: =ROUND((N47*40%),0) -> 98434046 | Q47: 2453 | R47: =+N47-O47 -> 147651068 | S47: 2454 | T47: 600 | U47: 968 | V47: MONICA MOYA | W47: 44312
A48: =_xlfn.CONCAT(E48,W48,L48) -> 291090671044312116734800 | B48: =_xlfn.MAXIFS(W:W,E:E,E48) -> 44656 | C48: =_xlfn.MAXIFS(L:L,E:E,E48) -> 134694000 | D48: 2021 | E48: 2910906710 | F48: CTTO INTER 289-2020 SUPERTRANSPORTE | G48: 1257144000 | H48: 134694000 | I48: =+H48/G48 -> 0.10714286 | K48: 1089524800 | L48: =ROUND((+K48*I48),0) -> 116734800 | M48: 58367400 | N48: 23634355 | O48: =ROUND((N48*40%),0) -> 9453742 | Q48: 2455 | R48: =+N48-O48 -> 14180613 | S48: 2456 | T48: 601 | U48: 969 | V48: MONICA MOYA | W48: 44312 | X48: SE APROPIA ESTE VALOR DE ACUERDO AL SALDO QUE HABIA EN ESTE MOMENTO EN LA CTA CONTABLE . QUEDA SALDO EN EL CDP Y RP PARA CUANDO INGRESE DINERO AL PROYECTO
A49: =_xlfn.CONCAT(E49,W49,L49) -> 29109067154431220142865 | B49: =_xlfn.MAXIFS(W:W,E:E,E49) -> 44312 | C49: =_xlfn.MAXIFS(L:L,E:E,E49) -> 20142865 | D49: 2021 | E49: 2910906715 | F49: CTTO INTER No 390 MUNICIPIO MADRID | G49: 200000000 | H49: 21428580 | I49: =+H49/G49 -> 0.1071429 | K49: 188000000 | L49: =ROUND((+K49*I49),0) -> 20142865 | M49: 8057146 | N49: =+L49-M49 -> 12085719 | O49: 12085719 | Q49: 2457 | R49: =+N49-O49 -> 0 | S49: 0 | T49: 602 | U49: 970 | V49: MONICA MOYA | W49: 44312
A50: =_xlfn.CONCAT(E50,W50,L50) -> 291090671744312245270004 | B50: =_xlfn.MAXIFS(W:W,E:E,E50) -> 44312 | C50: =_xlfn.MAXIFS(L:L,E:E,E50) -> 245270004 | D50: 2021 | E50: 2910906717 | F50: ANEXO CTTO CO1.PCCNTR.1923917 - SENA | G50: 2289186700 | H50: 245270004 | I50: =+H50/G50 -> 0.10714286 | K50: 2289186700 | L50: =ROUND((+K50*I50),0) -> 245270004 | M50: 171630690 | N50: =+L50-M50 -> 73639314 | O50: =ROUND((N50*40%),0) -> 29455726 | Q50: 2471 | R50: =+N50-O50 -> 44183588 | S50: 2472 | T50: 623 | U50: 989 | V50: MONICA MOYA | W50: 44312
A51: =_xlfn.CONCAT(E51,W51,L51) -> 29109067164431210289986 | B51: =_xlfn.MAXIFS(W:W,E:E,E51) -> 44312 | C51: =_xlfn.MAXIFS(L:L,E:E,E51) -> 10289986 | D51: 2021 | E51: 2910906716 | F51: CTTO 487 SERV.CAPACITACIONES PLAN INSTITUCION-INDIGER | G51: 96039870 | H51: 10289986 | I51: =+H51/G51 -> 0.10714286 | K51: 96039870 | L51: =ROUND((+K51*I51),0) -> 10289986 | M51: 0 | N51: =+L51-M51 -> 10289986 | O51: 10289986 | Q51: 2458 | R51: =+N51-O51 -> 0 | S51: 0 | T51: 603 | U51: 971 | V51: MONICA MOYA | W51: 44312
A52: =_xlfn.CONCAT(E52,W52,L52) -> 29109067234431242529828 | B52: =_xlfn.MAXIFS(W:W,E:E,E52) -> 45467 | C52: =_xlfn.MAXIFS(L:L,E:E,E52) -> 53971864 | D52: 2021 | E52: 2910906723 | F52: CTTO INTERAD 624 - 2020 MUNICIPIO FUNZA | G52: 503737398 | H52: 53971864 | I52: =+H52/G52 -> 0.10714286 | K52: 396945060 | L52: =ROUND((+K52*I52),0) -> 42529828 | M52: 0 | N52: =+L52-M52 -> 42529828 | O52: 42529828 | Q52: 2459 | R52: =+N52-O52 -> 0 | S52: 0 | T52: 604 | U52: 972 | V52: MONICA MOYA | W52: 44312
A53: =_xlfn.CONCAT(E53,W53,L53) -> 2910906725443122695179 | B53: =_xlfn.MAXIFS(W:W,E:E,E53) -> 44312 | C53: =_xlfn.MAXIFS(L:L,E:E,E53) -> 2695179 | D53: 2021 | E53: 2910906725 | F53: CTTO CO1.PCCNTR1953890 SH SAN ANDRES | G53: 86000000 | H53: 9214286 | I53: =+H53/G53 -> 0.10714286 | K53: 25155000 | L53: =ROUND((+K53*I53),0) -> 2695179 | M53: 0 | N53: =+L53-M53 -> 2695179 | O53: =ROUND((N53*40%),0) -> 1078072 | Q53: 2460 | R53: =+N53-O53 -> 1617107 | S53: 2461 | T53: 605 | U53: 973 | V53: MONICA MOYA | W53: 44312
A54: =_xlfn.CONCAT(E54,W54,L54) -> 2910906730443127709825 | B54: =_xlfn.MAXIFS(W:W,E:E,E54) -> 44441 | C54: =_xlfn.MAXIFS(L:L,E:E,E54) -> 19274820 | D54: 2021 | E54: 2910906730 | F54: CTTO GEF-CA-SNC 010 - 2020 | G54: 100000000 | H54: 10714286 | I54: =+H54/G54 -> 0.10714286 | K54: 71958362 | L54: =ROUND((+K54*I54),0) -> 7709825 | M54: 0 | N54: =+L54-M54 -> 7709825 | O54: 7709825 | Q54: 2462 | R54: =+N54-O54 -> 0 | S54: 0 | T54: 606 | U54: 974 | V54: MONICA MOYA | W54: 44312
A55: =_xlfn.CONCAT(E55,W55,L55) -> 29109066104431316037679 | B55: =_xlfn.MAXIFS(W:W,E:E,E55) -> 44313 | C55: =_xlfn.MAXIFS(L:L,E:E,E55) -> 16037679 | D55: 2021 | E55: 2910906610 | F55: CTTO INTERADM 541-2019 U ADMINIST SERV PUB - UAESP | G55: 149685000 | H55: 16037679 | I55: =+H55/G55 -> 0.10714286 | K55: 149685000 | L55: =ROUND((+K55*I55),0) -> 16037679 | M55: 6099841 | N55: =+L55-M55 -> 9937838 | O55: =ROUND((N55*40%),0) -> 3975135 | Q55: 2463 | R55: =+N55-O55 -> 5962703 | S55: 2464 | T55: 613 | U55: 983 | V55: MONICA MOYA | W55: 44313
A56: =_xlfn.CONCAT(E56,W56,L56) -> 291090670644314107830878 | B56: =_xlfn.MAXIFS(W:W,E:E,E56) -> 44372 | C56: =_xlfn.MAXIFS(L:L,E:E,E56) -> 119812087 | D56: 2021 | E56: 2910906706 | F56: CTTO INTERAD 434 ESAB 2020 | G56: 1118239980 | H56: 119812087 | I56: =+H56/G56 -> 0.10714345 | K56: 1006415982 | L56: =ROUND((+K56*I56),0) -> 107830878 | M56: 23962417 | N56: =+L56-M56 -> 83868461 | O56: =ROUND((N56*40%),0) -> 33547384 | Q56: 2465 | R56: =+N56-O56 -> 50321077 | S56: 2466 | T56: 614 | U56: 984 | V56: MONICA MOYA | W56: 44314
A57: =_xlfn.CONCAT(E57,W57,L57) -> 2910906401 | B57: =_xlfn.MAXIFS(W:W,E:E,E57) -> 45957 | C57: =_xlfn.MAXIFS(L:L,E:E,E57) -> 6.7887808e+08 | D57: 2021 | E57: 2910906401 | F57: ILUD | I57: 0.12 | N57: 180546920 | O57: 180546920 | Q57: 2412
A58: =_xlfn.CONCAT(E58,W58,L58) -> 29109080224432719593773 | B58: =_xlfn.MAXIFS(W:W,E:E,E58) -> 44327 | C58: =_xlfn.MAXIFS(L:L,E:E,E58) -> 19593773 | D58: 2021 | E58: 2910908022 | F58: ORDEN DE COMPRA 4500135787 COMPENSAR - ILUD | G58: 182875000 | H58: 19593773 | I58: =+H58/G58 -> 0.10714298 | K58: 182875000 | L58: =ROUND((+K58*I58),0) -> 19593773 | M58: 0 | N58: =+L58-M58 -> 19593773 | O58: =ROUND((N58*100%),0) -> 19593773 | Q58: 2809 | R58: 0 | S58: 0 | T58: 739 | U58: 1022 | V58: MONICA MOYA | W58: 44327 | X58: OBJETO ORDEN DE COMPRA COMPENSAR: EL SIGUIENTE CLAUSULADO GENERAL HACE PARTE INTEGRAL DE LAS ÓRDENES DE COMPRA EMITIDAS POR COMPENSAR CCF, EN ADELANTE “COMPENSAR” Y REGLAMENTA LA RELACIÓN COMERCIAL DE COMPENSAR Y SUS CONTRATISTAS Y/O PROVEEDORES EN ADELANTE “PROVEEDORES” OBJETO PROPUESTA IDEXUD: FORMACIÓN EN LENGUA EXTRANJERA INGLÉS PARA LOS SERVIDORES PÚBLICOS DE LA SECRETARÍA DISTRITAL DE EDUCACIÓN.
A59: =_xlfn.CONCAT(E59,W59,L59) -> 291090631044336759533756 | B59: =_xlfn.MAXIFS(W:W,E:E,E59) -> 44862 | C59: =_xlfn.MAXIFS(L:L,E:E,E59) -> 8.1619605e+08 | D59: 2021 | E59: 2910906310 | F59: CONT 213 DE 2017 ALCADIA BUCARAMANGA | G59: 7100279267 | H59: 816196045 | I59: =+H59/G59 -> 0.11495267 | K59: 6.6073608e+09 | L59: =ROUND((+K59*I59),0) -> 759533756 | M59: 205780620 | N59: 381314740 | O59: =ROUND((N59*40%),0) -> 152525896 | Q59: 2995 | R59: =+N59-O59 -> 228788844 | S59: 2996 | T59: 796 | U59: 1152 | V59: MONICA MOYA | W59: 44336 | X59: EL VR A APROPIAR DE BENEFICIO SEGÚN LOS INGRESOS A MAYO 20-2021 CORRESPONDE A $ 553,753,136 PERO SOLO SE TOMA $381,314,740 SEGÚN EL SALDO EXISTENTE A LA FECHA EN LA CTA CONTABLE 2910906310 RESTANDO LOS RP QUE ESTAN PENDIENTES DE PAGO POR VR DE $100,663,312.
A60: =_xlfn.CONCAT(E60,W60,L60) -> 2910905961443571134911773 | B60: =_xlfn.MAXIFS(W:W,E:E,E60) -> 44498 | C60: =_xlfn.MAXIFS(L:L,E:E,E60) -> 1224203654 | D60: 2021 | E60: 2910905961 | F60: MODIFICATORIO 2 ANEXO FINANCIERO 1029 2010 | G60: 9849652066 | H60: 1114245965 | I60: =+H60/G60 -> 0.11312541 | K60: 10032332573 | L60: =ROUND((+K60*I60),0) -> 1134911773 | M60: 1087367431 | N60: =+L60-M60 -> 47544342 | O60: =ROUND((N60*40%),0) -> 19017737 | Q60: 3918 | R60: =+N60-O60 -> 28526605 | S60: 3919 | T60: 955 | U60: 1533 | V60: MONICA MOYA | W60: 44357
A61: =_xlfn.CONCAT(E61,W61,L61) -> 291090670644372119812087 | B61: =_xlfn.MAXIFS(W:W,E:E,E61) -> 44372 | C61: =_xlfn.MAXIFS(L:L,E:E,E61) -> 119812087 | D61: 2021 | E61: 2910906706 | F61: CTTO INTERAD 434 ESAB 2020 | G61: 1118239980 | H61: 119812087 | I61: =+H61/G61 -> 0.10714345 | K61: 1118239962 | L61: =ROUND((+K61*I61),0)+2 -> 119812087 | M61: 107830878 | N61: =+L61-M61 -> 11981209 | O61: =ROUND((N61*40%),0) -> 4792484 | Q61: 3920 | R61: =+N61-O61 -> 7188725 | S61: 3921 | T61: 956 | U61: 1534 | V61: MONICA MOYA | W61: 44372
A62: =_xlfn.CONCAT(E62,W62,L62) -> 24530183014437290834172 | B62: =_xlfn.MAXIFS(W:W,E:E,E62) -> 45099 | C62: =_xlfn.MAXIFS(L:L,E:E,E62) -> 133063733 | D62: 2021 | E62: 2453018301 | F62: CONV. INTERAD.389 2019 FDL CIUDAD BOLIVAR | G62: =941984000+470992000 -> 1412976000 | H62: 151390286 | I62: =+H62/G62 -> 0.10714286 | K62: 847785600 | L62: =ROUND((+K62*I62),0) -> 90834172 | M62: 60556114 | N62: =+L62-M62 -> 30278058 | O62: =ROUND((N62*40%),0) -> 12111223 | Q62: 3922 | R62: =+N62-O62 -> 18166835 | S62: 3923 | T62: 957 | U62: 1535 | V62: MONICA MOYA | W62: 44372
A63: =_xlfn.CONCAT(E63,W63,L63) -> 2910904061443720 | B63: =_xlfn.MAXIFS(W:W,E:E,E63) -> 44372 | C63: =_xlfn.MAXIFS(L:L,E:E,E63) -> 0 | D63: 2021 | E63: 2910904061 | F63: CONTR 036-2012 UNIDAD REHAB Y MTO VIAL | G63: 102650000 | H63: 12318000 | I63: =+H63/G63 -> 0.12 | L63: =ROUND((+K63*I63),0) -> 0 | N63: 2628571 | O63: =ROUND((N63*40%),0) -> 1051428 | R63: =+N63-O63 -> 1577143 | V63: MONICA MOYA | W63: 44372 | X63: OJO REVISAR URGENTE SI NO SE HA PASADO ESTE BENEFICIO
A64: =_xlfn.CONCAT(E64,W64,L64) -> 29109061584437225769722 | B64: =_xlfn.MAXIFS(W:W,E:E,E64) -> 44372 | C64: =_xlfn.MAXIFS(L:L,E:E,E64) -> 25769722 | D64: 2021 | E64: 2910906158 | F64: CONT 225 DE 2015 FDL KENNEDY | G64: 3242508354 | H64: 347411515 | I64: =+H64/G64 -> 0.10714283 | K64: 240517472 | L64: =ROUND((+K64*I64),0) -> 25769722 | M64: 0 | N64: 8347305 | O64: =ROUND((N64*40%),0) -> 3338922 | Q64: 3924 | R64: =+N64-O64 -> 5008383 | S64: 3925 | T64: 958 | U64: 1536 | V64: MONICA MOYA | W64: 44372 | X64: SE TOMA EL SALDO QUE HAY SIIGO A LA FECHA.
A65: =_xlfn.CONCAT(E65,W65,L65) -> 29109067324437247440800 | B65: =_xlfn.MAXIFS(W:W,E:E,E65) -> 44797 | C65: =_xlfn.MAXIFS(L:L,E:E,E65) -> 158136000 | D65: 2021 | E65: 2910906732 | F65: CTTO 003-2021-AGENCIA NACIONAL SEG VIAL | G65: 1475936000 | H65: 158136000 | I65: =+H65/G65 -> 0.10714286 | K65: 442780800 | L65: =ROUND((+K65*I65),0) -> 47440800 | M65: 0 | N65: =+L65-M65 -> 47440800 | O65: =ROUND((N65*40%),0) -> 18976320 | Q65: 3926 | R65: =+N65-O65 -> 28464480 | S65: 3927 | T65: 959 | U65: 1537 | V65: MONICA MOYA | W65: 44372
A66: =_xlfn.CONCAT(E66,W66,L66) -> 291090631544375122624549 | B66: =_xlfn.MAXIFS(W:W,E:E,E66) -> 44375 | C66: =_xlfn.MAXIFS(L:L,E:E,E66) -> 122624549 | D66: 2021 | E66: 2910906315 | F66: CONT 232 DE 2016 FDL USME | G66: =+G34 -> 1144495782 | H66: 122624549 | I66: =+H66/G66 -> 0.10714286 | K66: 1144495782 | L66: =ROUND((+K66*I66),0) -> 122624549 | M66: 69140917 | N66: 12262455 | O66: =ROUND((N66*40%),0) -> 4904982 | Q66: 3967 | R66: =+N66-O66 -> 7357473 | S66: 3968 | T66: 960 | U66: 1538 | V66: MONICA MOYA | W66: 44375 | X66: SE TOMA EL SALDO INDICADO POR PRESUPUESTO SEGÚN CORREO DEL 28-06-2021
A67: =_xlfn.CONCAT(E67,W67,L67) -> 29109066244437828809640 | B67: =_xlfn.MAXIFS(W:W,E:E,E67) -> 44378 | C67: =_xlfn.MAXIFS(L:L,E:E,E67) -> 28809640 | D67: 2021 | E67: 2910906624 | F67: CTTO INTERADM 279 2019 MUNICIPIO DE MADRID | G67: 674223041 | H67: 72238183 | I67: =+H67/G67 -> 0.10714286 | J67: =IFERROR((+H67/(G67-H67)),0) -> 0.12 | K67: 268889978 | L67: =ROUND((+K67*I67),0)-1 -> 28809640 | M67: 6480857 | N67: =+L67-M67 -> 22328783 | O67: =ROUND((N67*40%),0) -> 8931513 | P67: R 014 00000000117 008 | Q67: 4020 | R67: =+N67-O67 -> 13397270 | S67: 4021 | T67: 991 | U67: 1567 | V67: MONICA MOYA | W67: 44378
A68: =_xlfn.CONCAT(E68,W68,L68) -> 29109080014438636823645 | B68: =_xlfn.MAXIFS(W:W,E:E,E68) -> 44603 | C68: =_xlfn.MAXIFS(L:L,E:E,E68) -> 45553609 | D68: 2021 | E68: 2910908001 | F68: DIPLOMADOS MULTIDICIPLINARIOS 2020 | G68: 306863645 | H68: 36823645 | I68: =+H68/G68 -> 0.12000002 | J68: =IFERROR((+H68/(G68-H68)),0) -> 0.13636367 | K68: 306863705 | L68: 36823645 | M68: 27678504 | N68: 9145140 | O68: =+N68 -> 9145140 | P68: R-14-105 | Q68: 4288 | R68: 0 | S68: 0 | T68: 1016 | U68: 1611 | V68: MONICA MOYA | W68: 44386
A69: =_xlfn.CONCAT(E69,W69,L69) -> 2910908029443861838571 | B69: =_xlfn.MAXIFS(W:W,E:E,E69) -> 44386 | C69: =_xlfn.MAXIFS(L:L,E:E,E69) -> 1838571 | D69: 2021 | E69: 2910908029 | F69: CURSO EN ADMINISTRACION DE TIERRAS 2021 | G69: 17160000 | H69: 1838571 | I69: =+H69/G69 -> 0.10714283 | J69: =IFERROR((+H69/(G69-H69)),0) -> 0.11999997 | K69: 17160000 | L69: =+K69*I69 -> 1838571 | M69: 0 | N69: =+L69-M69 -> 1838571 | O69: =+N69 -> 1838571 | P69: R-14-105 | Q69: 4289 | R69: 0 | S69: 0 | T69: 1017 | U69: 1612 | V69: MONICA MOYA | W69: 44386
A70: =_xlfn.CONCAT(E70,W70,L70) -> 2910908033443867849872 | B70: =_xlfn.MAXIFS(W:W,E:E,E70) -> 44386 | C70: =_xlfn.MAXIFS(L:L,E:E,E70) -> 7849872 | D70: 2021 | E70: 2910908033 | F70: PROG. ACAD. TRANSIT. RETORNO FAC TECNOLOGICA 2021 | G70: 65415600 | H70: 7849872 | I70: =+H70/G70 -> 0.12 | J70: =IFERROR((+H70/(G70-H70)),0) -> 0.13636364 | K70: 65415600 | L70: =+K70*I70 -> 7849872 | M70: 0 | N70: =+L70-M70 -> 7849872 | O70: =+N70 -> 7849872 | P70: R-14-105 | Q70: 4403 | R70: 0 | S70: 0 | T70: 1037 | U70: 1613 | V70: MONICA MOYA | W70: 44386
A71: =_xlfn.CONCAT(E71,W71,L71) -> 29109065544438958499346,2940902 | B71: =_xlfn.MAXIFS(W:W,E:E,E71) -> 44389 | C71: =_xlfn.MAXIFS(L:L,E:E,E71) -> 58499346 | D71: 2021 | E71: 2910906554 | F71: CPS 187 DE 2018 FDL TUNJUELITO | G71: 580000000 | H71: 62142857 | I71: =+H71/G71 -> 0.10714286 | J71: =IFERROR((+H71/(G71-H71)),0) -> 0.12 | K71: 545993900 | L71: =+K71*I71 -> 58499346 | M71: 54616708 | N71: 6609130 | O71: =ROUND((N71*40%),0) -> 2643652 | P71: R-14-105 | Q71: 4404 | R71: =+N71-O71 -> 3965478 | S71: 4405 | T71: 1038 | U71: 1614 | V71: MONICA MOYA | W71: 44389 | X71: SE TOMA EL SALDO QUE HAY A LA FECHA EN SIIGO,NO EXISTEN GIROS PENDIENTES ENTONCES SE TOMA EL SALDO PARA BENEFICIO. SE ANEXA ESTADO DE CUENTA
A72: =_xlfn.CONCAT(E72,W72,L72) -> 29109063594439328834285,184 | B72: =_xlfn.MAXIFS(W:W,E:E,E72) -> 44393 | C72: =_xlfn.MAXIFS(L:L,E:E,E72) -> 28834285 | D72: 2021 | E72: 2910906359 | F72: CONTR 880 DE 2017 DEP DEL GUAINIA | G72: 290000000 | H72: 31071428 | I72: =+H72/G72 -> 0.10714286 | J72: =IFERROR((+H72/(G72-H72)),0) -> 0.12 | K72: 269120000 | L72: =+K72*I72 -> 28834285 | M72: 28408011 | N72: =+H72-M72 -> 2663417 | O72: =+N72 -> 2663417 | P72: R-14-108 | Q72: 4566 | R72: =+N72-O72 -> 0 | S72: 0 | T72: 1045 | U72: 1631 | V72: MONICA MOYA | W72: 44393 | X72: SE TOMA EL SALDO TOTAL QUE QUEDA DEL BENEFICIO SEGÚN PRESUPUESTO. SE REVISÓ QUE HAY SALDO DISPONIBLE PARA APROPIAR EL SALDO TOTAL TANTO EN SIIGO COMO PRESUPUESTALMENTE, DESPUES DE GIRAR LOS RP QUE SE ENCUENTRAN PENDIENTES.
A73: =_xlfn.CONCAT(E73,W73,L73) -> 29109062784440332258610 | B73: =_xlfn.MAXIFS(W:W,E:E,E73) -> 44403 | C73: =_xlfn.MAXIFS(L:L,E:E,E73) -> 32258610 | D73: 2021 | E73: 2910906278 | F73: CONTRATO 79 DE 2017 FONCEP | G73: 455000000 | H73: 48750000 | I73: =+H73/G73 -> 0.10714286 | J73: =IFERROR((+H73/(G73-H73)),0) -> 0.12 | K73: 301080359 | L73: =ROUND((+K73*I73),0) -> 32258610 | M73: 0 | N73: 1506804 | O73: =ROUND((N73*40%),0) -> 602722 | P73: R-14-115 | Q73: 4687 | R73: =+N73-O73 -> 904082 | S73: 4688 | T73: 1098 | U73: 1673 | V73: MONICA MOYA | W73: 44403 | X73: SEGÚN ANALISIS DE CASOS DEPURADOS DEL AÑO 2017 SE REALIZO ESTADO DE CUENTA Y SE APROPIA EL SALDO QUE HAY EN LA CUENTA EN SIIGO.
A74: =_xlfn.CONCAT(E74,W74,L74) -> 29109067314440336868405 | B74: =_xlfn.MAXIFS(W:W,E:E,E74) -> 44797 | C74: =_xlfn.MAXIFS(L:L,E:E,E74) -> 118545925 | D74: 2021 | E74: 2910906731 | F74: CTTO 021-00-G-CACOM-4-DEDHU-2021 MINDEFENSA | G74: 739371600 | H74: 79218386 | I74: =+H74/G74 -> 0.10714286 | J74: =IFERROR((+H74/(G74-H74)),0) -> 0.12 | K74: 344105115 | L74: =ROUND((+K74*I74),0) -> 36868405 | M74: 0 | N74: =+L74-M74 -> 36868405 | O74: =ROUND((N74*40%),0) -> 14747362 | P74: R 014 00000000118 008 | Q74: 4708 | R74: =+N74-O74 -> 22121043 | S74: 4709 | T74: 263 | U74: 1676 | V74: MONICA MOYA | W74: 44403
A75: =_xlfn.CONCAT(E75,W75,L75) -> 29109067084440350650071 | B75: =_xlfn.MAXIFS(W:W,E:E,E75) -> 44403 | C75: =_xlfn.MAXIFS(L:L,E:E,E75) -> 50650071 | D75: 2021 | E75: 2910906708 | F75: CTTO INTER 015-2020 SERVICIO GEOLÓGICO COLOMBIANO | G75: 472734000 | H75: 50650071 | I75: =+H75/G75 -> 0.10714286 | J75: =IFERROR((+H75/(G75-H75)),0) -> 0.12 | K75: 472734000 | L75: =ROUND((+K75*I75),0) -> 50650071 | M75: 27857539 | N75: =+L75-M75 -> 22792532 | O75: =ROUND((N75*40%),0) -> 9117013 | P75: R 014 00000000118 006 | Q75: 4706 | R75: =+N75-O75 -> 13675519 | S75: 4707 | T75: 1103 | U75: 1675 | V75: MONICA MOYA | W75: 44403
A76: =_xlfn.CONCAT(E76,W76,L76) -> 291090640144404 | B76: =_xlfn.MAXIFS(W:W,E:E,E76) -> 45957 | C76: =_xlfn.MAXIFS(L:L,E:E,E76) -> 6.7887808e+08 | D76: 2021 | E76: 2910906401 | F76: ILUD | J76: =IFERROR((+H76/(G76-H76)),0) -> 0 | N76: 147959096 | O76: =+N76 -> 147959096 | P76: R 014 00000000118 010 | Q76: 4710 | R76: 0 | S76: 0 | T76: 1104 | U76: 1677 | V76: MONICA MOYA | W76: 44404
A77: =_xlfn.CONCAT(E77,W77,L77) -> 2910906153444041600030901,9961 | B77: =_xlfn.MAXIFS(W:W,E:E,E77) -> 44404 | C77: =_xlfn.MAXIFS(L:L,E:E,E77) -> 1.6000309e+09 | D77: 2021 | E77: 2910906153 | F77: CONTRAT 1069 DE 2015 SENA | I77: 0.1071 | J77: =IFERROR((+H77/(G77-H77)),0) -> 0 | K77: 14939597591 | L77: =+K77*I77 -> 1.6000309e+09 | M77: 570028904 | N77: 200000000 | O77: =ROUND((N77*40%),0) -> 80000000 | P77: R 014 00000000117 004 | Q77: 4712 | R77: =+N77-O77 -> 120000000 | S77: 4713 | T77: 1109 | U77: 1682 | V77: MONICA MOYA | W77: 44404 | X77: SEGÚN LO ESTABLECIDO CON DIANA CARO EL VR DEL BENEFICIO A TOMAR ES DE $200,000,000
A78: =_xlfn.CONCAT(E78,W78,L78) -> 29109067324440494881600 | B78: =_xlfn.MAXIFS(W:W,E:E,E78) -> 44797 | C78: =_xlfn.MAXIFS(L:L,E:E,E78) -> 158136000 | D78: 2021 | E78: 2910906732 | F78: CTTO 003-2021-AGENCIA NACIONAL SEG VIAL | G78: 1475936000 | H78: 158136000 | I78: =+H78/G78 -> 0.10714286 | J78: =IFERROR((+H78/(G78-H78)),0) -> 0.12 | K78: 885561600 | L78: =ROUND((+K78*I78),0) -> 94881600 | M78: 47440800 | N78: =+L78-M78 -> 47440800 | O78: =ROUND((N78*40%),0) -> 18976320 | P78: R 014 00000000120 006 | Q78: 4714 | R78: =+N78-O78 -> 28464480 | S78: 4715 | T78: 1110 | U78: 1683 | V78: MONICA MOYA | W78: 44404
A79: =_xlfn.CONCAT(E79,W79,L79) -> 2453018310444058948355 | B79: =_xlfn.MAXIFS(W:W,E:E,E79) -> 45099 | C79: =_xlfn.MAXIFS(L:L,E:E,E79) -> 30406868 | D79: 2021 | E79: 2453018310 | F79: CONV INTER 128-2021 MUNICIPIO EL COLEGIO | G79: 306603272 | H79: 32850351 | I79: =+H79/G79 -> 0.10714286 | J79: =IFERROR((+H79/(G79-H79)),0) -> 0.12 | K79: 83517981 | L79: =ROUND((+K79*I79),0) -> 8948355 | M79: 0 | N79: =+L79-M79 -> 8948355 | O79: =ROUND((N79*40%),0) -> 3579342 | P79: R 014 00000000123 002 | Q79: 4793 | R79: =+N79-O79 -> 5369013 | S79: 4794 | T79: 1116 | U79: 1688 | V79: MONICA MOYA | W79: 44405
A80: =_xlfn.CONCAT(E80,W80,L80) -> 29109066514440515872640 | B80: =_xlfn.MAXIFS(W:W,E:E,E80) -> 44405 | C80: =_xlfn.MAXIFS(L:L,E:E,E80) -> 15872640 | D80: 2021 | E80: 2910906651 | F80: CTTO INTERVENTORIA 201-5-19 FONDO ROTATORIO POLICIA | G80: 132272000 | H80: 15872640 | I80: =+H80/G80 -> 0.12 | J80: =IFERROR((+H80/(G80-H80)),0) -> 0.13636364 | K80: 132272000 | L80: =ROUND((+K80*I80),0) -> 15872640 | M80: 13516488 | N80: =+L80-M80 -> 2356152 | O80: =ROUND((N80*40%),0) -> 942461 | P80: R 014 00000000123 002 | Q80: 4749 | R80: =+N80-O80 -> 1413691 | S80: 4750 | T80: 349 | U80: 447 | V80: MONICA MOYA | W80: 44405 | X80: INGRESO EL 100% DEL PROYECTO, SE TOMA EL SALDO TOTAL QUE QUEDA POR APROPIAR DE BENEFICIO. SE TOMA CON EL RP 447 QUE YA HABIA SIDO SOLICITADO EL 9 DE MARZO DE 2021 POR VALOR DE $7,154,867.
A81: =_xlfn.CONCAT(E81,W81,L81) -> 29109066024440657170161 | B81: =_xlfn.MAXIFS(W:W,E:E,E81) -> 44406 | C81: =_xlfn.MAXIFS(L:L,E:E,E81) -> 57170161 | D81: 2021 | E81: 2910906602 | F81: CTTO INTERV TECN 121 DE 2019 GOB NORTE SANTANDER | G81: 899333962 | H81: 74256933 | I81: =+H81/G81 -> 0.082568808 | J81: =IFERROR((+H81/(G81-H81)),0) -> 0.09 | K81: 692394170 | L81: =ROUND((+K81*I81),0) -> 57170161 | M81: 39831419 | N81: =+L81-M81 -> 17338742 | O81: 6930647 | P81: R 014 00000000123 002 | Q81: 4795 | R81: =+N81-O81 -> 10408095 | S81: 4796 | T81: 1117 | U81: 1690 | V81: MONICA MOYA | W81: 44406
A82: =_xlfn.CONCAT(E82,W82,L82) -> 29109067214440610897200 | B82: =_xlfn.MAXIFS(W:W,E:E,E82) -> 44406 | C82: =_xlfn.MAXIFS(L:L,E:E,E82) -> 10897200 | D82: 2021 | E82: 2910906721 | F82: CTTO INTER 118-ICFE-2020 - INST DE CASAS FISCALES | G82: 90810000 | H82: 10897200 | I82: =+H82/G82 -> 0.12 | J82: =IFERROR((+H82/(G82-H82)),0) -> 0.13636364 | K82: 90810000 | L82: =+K82*I82 -> 10897200 | M82: 10155046 | N82: =+L82-M82 -> 742154 | O82: =ROUND((N82*40%),0) -> 296862 | P82: R 014 00000000123 002 | Q82: 4797 | R82: =+N82-O82 -> 445292 | S82: 4798 | T82: 1120 | U82: 1733 | V82: MONICA MOYA | W82: 44406
A83: =_xlfn.CONCAT(E83,W83,L83) -> 29109065894441019139263 | B83: =_xlfn.MAXIFS(W:W,E:E,E83) -> 44410 | C83: =_xlfn.MAXIFS(L:L,E:E,E83) -> 19139263 | D83: 2021 | E83: 2910906589 | F83: CTTO INTERADM 672 2019 ESC SUPERIOR DE ADMON PUBIL | G83: 178633122 | H83: 19139263 | I83: =+H83/G83 -> 0.10714286 | J83: =IFERROR((+H83/(G83-H83)),0) -> 0.12 | K83: 178633122 | L83: =ROUND((+K83*I83),0) -> 19139263 | M83: 5744608 | N83: =+L83-M83 -> 13394655 | O83: 1911097 | P83: R 014 00000000173 004 | Q83: 6347 | R83: 11483558 | S83: 6348 | T83: 1125 | U83: 1783 | V83: MONICA MOYA | W83: 44410 | X83: SE APROPIA PARA EL IDEXUD $1,911,097 POR QUE EN LA OP 3291 DEL 1-06-2020 YA SE HABIA APROPIADO $5,744,608 PARA UN TOTAL DE $7,655,705 CORRESPONDIENTE AL 40% DEL TOTAL DEL BENEFICIO.
A84: =_xlfn.CONCAT(E84,W84,L84) -> 24530134184441225966288 | B84: =_xlfn.MAXIFS(W:W,E:E,E84) -> 44412 | C84: =_xlfn.MAXIFS(L:L,E:E,E84) -> 25966288 | D84: 2021 | E84: 2453013418 | F84: CONV INTERADM 178-2019 CORP AUTONOMA ALTO MAGDALEN | G84: 403904382 | H84: 43277146 | I84: =+H84/G84 -> 0.10714701 | J84: =IFERROR((+H84/(G84-H84)),0) -> 0.12000521 | K84: 242342630 | L84: =ROUND((+K84*I84),0) -> 25966288 | M84: 12983144 | N84: 5226630 | O84: =ROUND((N84*40%),0) -> 2090652 | P84: R 014 00000000140 004 | Q84: 5335 | R84: =+N84-O84 -> 3135978 | S84: 5336 | T84: 1131 | U84: 1787 | V84: MONICA MOYA | W84: 44412 | X84: EL VALOR CORRESPONDIENTE A APROPIAR ES $12,983,144, PERO SE APROPIA EL SALDO QUE EXISTE EN LA CTA A LA FECHA EN SIIGO $5,226,630.
A85: =_xlfn.CONCAT(E85,W85,L85) -> 29109011644443416310893 | B85: =_xlfn.MAXIFS(W:W,E:E,E85) -> 44434 | C85: =_xlfn.MAXIFS(L:L,E:E,E85) -> 16310893 | D85: 2021 | E85: 2910901164 | F85: POLICIA NACIONAL | G85: 153000000 | H85: 16392857 | I85: =+H85/G85 -> 0.10714286 | J85: =IFERROR((+H85/(G85-H85)),0) -> 0.12 | K85: 152234999 | L85: =ROUND((+K85*I85),0) -> 16310893 | M85: 16310893 | N85: 81964 | O85: =ROUND((N85*40%),0) -> 32786 | P85: R 014 00000000140 004 | Q85: 5337 | R85: =+N85-O85 -> 49178 | S85: 5338 | T85: 1314 | U85: 2139 | V85: MONICA MOYA | W85: 44434
A86: =_xlfn.CONCAT(E86,W86,L86) -> 29109011674443420895000 | B86: =_xlfn.MAXIFS(W:W,E:E,E86) -> 44434 | C86: =_xlfn.MAXIFS(L:L,E:E,E86) -> 20895000 | D86: 2021 | E86: 2910901167 | F86: POLICIA NACIONAL | G86: 196000000 | H86: 21000000 | I86: =+H86/G86 -> 0.10714286 | J86: =IFERROR((+H86/(G86-H86)),0) -> 0.12 | K86: 195020000 | L86: =ROUND((+K86*I86),0) -> 20895000 | M86: 20895000 | N86: 105000 | O86: =ROUND((N86*40%),0) -> 42000 | P86: R 014 00000000140 004 | Q86: 5339 | R86: =+N86-O86 -> 63000 | S86: 5340 | T86: 1315 | U86: 2140 | V86: MONICA MOYA | W86: 44434
A87: =_xlfn.CONCAT(E87,W87,L87) -> 2910901169444345308344 | B87: =_xlfn.MAXIFS(W:W,E:E,E87) -> 44434 | C87: =_xlfn.MAXIFS(L:L,E:E,E87) -> 5308344 | D87: 2021 | E87: 2910901169 | F87: POLICIA NACIONAL | G87: 49793510 | H87: 5335019 | I87: =+H87/G87 -> 0.10714286 | J87: =IFERROR((+H87/(G87-H87)),0) -> 0.12 | K87: 49544542 | L87: =ROUND((+K87*I87),0) -> 5308344 | M87: 5308344 | N87: 26675 | O87: =ROUND((N87*40%),0) -> 10670 | P87: R 014 00000000140 004 | Q87: 5341 | R87: =+N87-O87 -> 16005 | S87: 5342 | T87: 1316 | U87: 2141 | V87: MONICA MOYA | W87: 44434 | X87: SEGÚN ANALISIS SE APROPIA EL 100% DEL SALDO PENDIENTE POR APROPROPIAR EN EL RP
A88: =_xlfn.CONCAT(E88,W88,L88) -> 2910906412444342400154 | B88: =_xlfn.MAXIFS(W:W,E:E,E88) -> 44434 | C88: =_xlfn.MAXIFS(L:L,E:E,E88) -> 2400154 | D88: 2021 | E88: 2910906412 | F88: INSTITUTO DISTRITAL DE LAS ARTES - IDARTES | G88: 25000000 | H88: 2678571 | I88: =+H88/G88 -> 0.10714284 | J88: =IFERROR((+H88/(G88-H88)),0) -> 0.11999998 | K88: 22401443 | L88: =ROUND((+K88*I88),0) -> 2400154 | M88: 2400154 | N88: 278417 | O88: =+N88 -> 278417 | P88: R 014 00000000156 010 | Q88: 5343 | R88: 0 | S88: 0 | T88: 1317 | U88: 2142 | V88: MONICA MOYA | W88: 44434 | X88: SE APROPIA EL 100% SEGÚN SALDO PRESUPUESTAL
A89: =_xlfn.CONCAT(E89,W89,L89) -> 2910906559444344864344 | B89: =_xlfn.MAXIFS(W:W,E:E,E89) -> 44434 | C89: =_xlfn.MAXIFS(L:L,E:E,E89) -> 4864344 | D89: 2021 | E89: 2910906559 | F89: CAJA DE VIVIENDA POPULAR | G89: 47096000 | H89: 5046000 | I89: =+H89/G89 -> 0.10714286 | J89: =IFERROR((+H89/(G89-H89)),0) -> 0.12 | K89: 45400544 | L89: =ROUND((+K89*I89),0) -> 4864344 | M89: 3960544 | N89: 1085456 | O89: =+N89 -> 1085456 | Q89: 5344 | R89: 0 | S89: 0 | T89: 1318 | U89: 2143 | V89: MONICA MOYA | W89: 44434
A90: =_xlfn.CONCAT(E90,W90,L90) -> 29109067194443443808036 | B90: =_xlfn.MAXIFS(W:W,E:E,E90) -> 44529 | C90: =_xlfn.MAXIFS(L:L,E:E,E90) -> 71236607 | D90: 2021 | E90: 2910906719 | F90: CTTO INTER 085-00-D-CACOM1-DEDHU-2020 | G90: 664875000 | H90: 71236607 | I90: =+H90/G90 -> 0.10714286 | J90: =IFERROR((+H90/(G90-H90)),0) -> 0.12 | K90: 408875000 | L90: =ROUND((+K90*I90),0) -> 43808036 | M90: 16379464 | N90: =+L90-M90 -> 27428572 | O90: =ROUND((N90*40%),0) -> 10971429 | P90: R 014 00000000140 004 | Q90: 5345 | R90: =+N90-O90 -> 16457143 | S90: 5346 | T90: 1319 | U90: 2144 | V90: MONICA MOYA | W90: 44434
A91: =_xlfn.CONCAT(E91,W91,L91) -> 24530183024443489809808 | B91: =_xlfn.MAXIFS(W:W,E:E,E91) -> 44434 | C91: =_xlfn.MAXIFS(L:L,E:E,E91) -> 89809808 | D91: 2021 | E91: 2453018302 | F91: CORPORACIÓN AUTÓNOMA DE LOS VALLES DEL SINU Y SAN JORGE-CVS | G91: 838224872 | H91: 89809808 | I91: =+H91/G91 -> 0.10714286 | J91: =IFERROR((+H91/(G91-H91)),0) -> 0.12 | K91: 838224872 | L91: =ROUND((+K91*I91),0) -> 89809808 | M91: 89199094 | N91: =+L91-M91 -> 610714 | O91: =ROUND((N91*40%),0) -> 244286 | P91: R 014 00000000156 010 | Q91: 5347 | R91: =+N91-O91 -> 366428 | S91: 5348 | T91: 1320 | U91: 2145 | V91: MONICA MOYA | W91: 44434 | X91: SE TOMA EL TOTAL DEL SALDO POR APROPIAR SEGÚN PRESUPUESTO. PROYECTO LIQUIDADO.
A92: =_xlfn.CONCAT(E92,W92,L92) -> 29109067054443444232143 | B92: =_xlfn.MAXIFS(W:W,E:E,E92) -> 44434 | C92: =_xlfn.MAXIFS(L:L,E:E,E92) -> 44232143 | D92: 2021 | E92: 2910906705 | F92: FONDO FINANCIERO DISTRITAL DE SALUD-SDS | G92: 412833333 | H92: 44232143 | I92: =+H92/G92 -> 0.10714286 | J92: =IFERROR((+H92/(G92-H92)),0) -> 0.12 | K92: 412833333 | L92: =ROUND((+K92*I92),0) -> 44232143 | M92: 33113839 | N92: =+L92-M92 -> 11118304 | O92: =ROUND((N92*40%),0) -> 4447322 | P92: R 014 00000000140 004 | Q92: 5349 | R92: =+N92-O92 -> 6670982 | S92: 5350 | T92: 1321 | U92: 2146 | V92: MONICA MOYA | W92: 44434
A93: =_xlfn.CONCAT(E93,W93,L93) -> 291090801544434421273 | B93: =_xlfn.MAXIFS(W:W,E:E,E93) -> 44434 | C93: =_xlfn.MAXIFS(L:L,E:E,E93) -> 421273 | D93: 2021 | E93: 2910908015 | F93: CURSOS LIBRES ARTE DANZARIO 2020-3 ASAB | G93: 20299702 | H93: 421273 | I93: =+H93/G93 -> 0.020752669 | J93: =IFERROR((+H93/(G93-H93)),0) -> 0.021192469 | K93: 20299702 | L93: =ROUND((+K93*I93),0) -> 421273 | M93: 0 | N93: =+L93-M93 -> 421273 | O93: =+N93 -> 421273 | P93: R 014 00000000140 004 | Q93: 5353 | R93: =+N93-O93 -> 0 | S93: 0 | T93: 1322 | U93: 2147 | V93: MONICA MOYA | W93: 44434 | X93: SE APROPIA EL 100% SEGÚN PESUPUESTO
A94: =_xlfn.CONCAT(E94,W94,L94) -> 2910908019444344740136 | B94: =_xlfn.MAXIFS(W:W,E:E,E94) -> 44434 | C94: =_xlfn.MAXIFS(L:L,E:E,E94) -> 4740136 | D94: 2021 | E94: 2910908019 | F94: PROGRAMA ACADÉMICO TRANSITORIO DE RETORNO 2020-3 | G94: 39501132 | H94: 4740136 | I94: =+H94/G94 -> 0.12 | J94: =IFERROR((+H94/(G94-H94)),0) -> 0.13636364 | K94: 39501132 | L94: =ROUND((+K94*I94),0) -> 4740136 | M94: 0 | N94: =+L94-M94 -> 4740136 | O94: =+N94 -> 4740136 | P94: R 014 00000000140 004 | Q94: 5354 | R94: =+N94-O94 -> 0 | S94: 0 | T94: 1323 | U94: 2148 | V94: MONICA MOYA | W94: 44434
A95: =_xlfn.CONCAT(E95,W95,L95) -> 291090150144434167160000 | B95: =_xlfn.MAXIFS(W:W,E:E,E95) -> 44434 | C95: =_xlfn.MAXIFS(L:L,E:E,E95) -> 167160000 | D95: 2021 | E95: 2910901501 | F95: CONT 180/2012 I D M | G95: 1500000000 | H95: =150287413+29712586 -> 179999999 | I95: =+H95/G95 -> 0.12 | J95: =IFERROR((+H95/(G95-H95)),0) -> 0.13636364 | K95: 1393000000 | L95: =+K95*0.12 -> 167160000 | M95: 72000000 | N95: =+L95-M95 -> 95160000 | O95: =ROUND((N95*40%),0) -> 38064000 | P95: R 014 00000000140 004 | Q95: 5355 | R95: =+N95-O95 -> 57096000 | S95: 5356 | T95: 1311 | U95: 2082 | V95: MONICA MOYA | W95: 44434
A96: =_xlfn.CONCAT(E96,W96,L96) -> 291090804544434887725 | B96: =_xlfn.MAXIFS(W:W,E:E,E96) -> 44434 | C96: =_xlfn.MAXIFS(L:L,E:E,E96) -> 887725 | D96: 2021 | E96: 2910908045 | F96: CURSO INTRODUCCION A LA PROGRAMACION PYTHON 2021 | G96: 8285436 | H96: 887725 | I96: =+H96/G96 -> 0.10714282 | J96: =IFERROR((+H96/(G96-H96)),0) -> 0.11999996 | K96: 8285436 | L96: =ROUND((+K96*I96),0) -> 887725 | M96: 0 | N96: =+L96-M96 -> 887725 | O96: =+N96 -> 887725 | P96: R 014 00000000156 010 | Q96: 5357 | R96: 0 | S96: 0 | T96: 1324 | U96: 2149 | V96: MONICA MOYA | W96: 44434
A97: =_xlfn.CONCAT(E97,W97,L97) -> 2910905873444348266000 | B97: =_xlfn.MAXIFS(W:W,E:E,E97) -> 44434 | C97: =_xlfn.MAXIFS(L:L,E:E,E97) -> 8266000 | D97: 2021 | E97: 2910905873 | F97: CONTRATO DE INTERVENTORIA 09 DE 2013 FUNDACION SERVICIO DE VIVIENDA POPULAR - SERVIVIENDA | G97: 70368755 | H97: 8266000 | I97: =+H97/G97 -> 0.11746691 | J97: =IFERROR((+H97/(G97-H97)),0) -> 0.13310199 | K97: 70368755 | L97: =ROUND((+K97*I97),0) -> 8266000 | M97: 51633 | N97: =+L97-M97 -> 8214367 | O97: =ROUND((N97*40%),0) -> 3285747 | P97: R 014 00000000156 010 | Q97: 5358 | R97: =+N97-O97 -> 4928620 | S97: 5359 | T97: 1332 | U97: 2130 | V97: MONICA MOYA | W97: 44434
A98: =_xlfn.CONCAT(E98,W98,L98) -> 29109067304444119274820 | B98: =_xlfn.MAXIFS(W:W,E:E,E98) -> 44441 | C98: =_xlfn.MAXIFS(L:L,E:E,E98) -> 19274820 | D98: 2021 | E98: 2910906730 | F98: CTTO GEF-CA-SNC 010 - 2020 | G98: 179895904 | H98: 19274820 | I98: =+H98/G98 -> 0.1071443 | J98: =IFERROR((+H98/(G98-H98)),0) -> 0.1200018 | K98: =71958362+107937542 -> 179895904 | L98: =ROUND((+K98*I98),0) -> 19274820 | M98: 7709825 | N98: =+L98-M98 -> 11564995 | O98: =ROUND((N98*40%),0) -> 4625998 | P98: R 014 00000000141 004 | Q98: 5515 | R98: =+N98-O98 -> 6938997 | S98: 5516 | T98: 1398 | U98: 2184 | V98: MONICA MOYA | W98: 44441
A99: =_xlfn.CONCAT(E99,W99,L99) -> 29109062754445921950254 | B99: =_xlfn.MAXIFS(W:W,E:E,E99) -> 44459 | C99: =_xlfn.MAXIFS(L:L,E:E,E99) -> 21950254 | D99: 2021 | E99: 2910906275 | F99: CONTR L16 171 DE 2016 F D L PUENTE ARANDA | G99: 204869041 | H99: 21950254 | I99: =+H99/G99 -> 0.10714286 | J99: =IFERROR((+H99/(G99-H99)),0) -> 0.12 | K99: 204869041 | L99: =+K99*I99 -> 21950254 | M99: 0 | N99: =+L99-M99 -> 21950254 | O99: =ROUND((N99*40%),0) -> 8780102 | P99: R 014 00000000156 010 | Q99: 5765 | R99: =+N99-O99 -> 13170152 | S99: 5766 | T99: 1624 | U99: 2505 | V99: MONICA MOYA | W99: 44459
A100: =_xlfn.CONCAT(E100,W100,L100) -> 291090626044459306737224 | B100: =_xlfn.MAXIFS(W:W,E:E,E100) -> 44459 | C100: =_xlfn.MAXIFS(L:L,E:E,E100) -> 306737224 | D100: 2021 | E100: 2910906260 | F100: EMPRESA DE SERVICIOS PÚBICOS DE CHÍA EMSECHIA E.S.P. | G100: 4300708566 | H100: 516085028 | I100: 0.12 | J100: =IFERROR((+H100/(G100-H100)),0) -> 0.13636364 | K100: 2556143530 | L100: 306737224 | M100: =203289922+50000000 -> 253289922 | N100: =+L100-M100 -> 53447302 | O100: =ROUND((N100*40%),0) -> 21378921 | P100: R 014 00000000156 010 | Q100: 5767 | R100: =+N100-O100 -> 32068381 | S100: 5768 | T100: 1625 | U100: 2594 | V100: MONICA MOYA | W100: 44459 | X100: SE APROPIA PROPORCIONAL A LOS INGRESOS.SALDO POR APROPIAR $53,447,302
...

Sheet Proyectos Extensión
E1: FORMATO LIQUIDACIÓN BENEFICIO INSTITUCIONAL | J1: Código: GRF-FR-041
E2: Macroproceso: Gestión de Recursos | J2: Versión: 01
E3: Proceso: Gestión de Recursos Financieros | J3: Fecha de Aprobación: 2025/07/02
B5: BENEFICIO INSTITUCIONAL DEL 01 DE ABRIL AL 30 DE JUNIO DEL 2026 | V5: 1 TRIMESTRE | Z5: 2 TRIMESTRE | AD5: 3 TRIMESTRE | AH5: 4 TRIMESTRE
A6: ITEM | B6: VIGENCIA | C6: ENTIDAD CONTRATANTE | D6: NOMBRE PROYECTO | E6: Tipo | F6: FECHA DE SUSCRIPCIÓN | G6: FECHA DE FINALIZACIÓN | H6: DURACION EN TRIMESTRES | I6: ESTADO | J6: OBSERVACIONES AL ESTADO | K6: ENTIDAD BANCARIA DEPOSITARIA DE LOS RECURSOS | L6: TIPO DE CUENTA | M6: N° CUENTA | N6: N° CENTRO DE COSTOS ASIGNADO | O6: CÓDIGO CONTABLE | P6: VALOR PROYECTO SEGÚN MINUTA | Q6: VALOR ADICIONES | R6: VALOR TOTAL PRESUPUESTO | S6: % DE B.I. AUTORIZADO - SEGÚN PRESUPUESTO | T6: BENEFICIO TOTAL PRESUPUESTADO | U6: TOTAL INGRESOS A LA FECHA | V6: VALOR RECAUDO DEL TRIMESTRE 1 | W6: BENEFICIO TOTAL A DISTRIBUIR EN EL TRIMESTRE LIQUIDADO | X6: IDEXUD 40% | Y6: UNIVERSIDAD 60% | Z6: VALOR RECAUDO DEL TRIMESTRE 2 | AA6: BENEFICIO TOTAL A DISTRIBUIR EN EL TRIMESTRE LIQUIDADO | AB6: IDEXUD 40% | AC6: UNIVERSIDAD 60% | AD6: VALOR RECAUDO DEL TRIMESTRE 3 | AE6: BENEFICIO TOTAL A DISTRIBUIR EN EL TRIMESTRE LIQUIDADO | AF6: IDEXUD 40% | AG6: UNIVERSIDAD 60% | AH6: VALOR RECAUDO DEL TRIMESTRE 4 | AI6: BENEFICIO TOTAL A DISTRIBUIR EN EL TRIMESTRE LIQUIDADO | AJ6: IDEXUD 40% | AK6: UNIVERSIDAD 60% | AL6: BENEFICIO TOTAL APROPIADO (ACUMULADO) A LA FECHA | AM6: VALOR TOTAL DE B.I. EN LA VIGENCIA | AN6: NOTAS PRIMER TRIMESTRE | AO6: NOTAS SEGUNDO TRIMESTRE
A7: 1 | B7: 2021 | C7: UNIVERSIDAD DISTRITAL FRANCISCO JOSÉ DE CALDAS - UD | D7: FAC-ASAB-8016-UNIVERSIDAD DISTRITAL FRANCISCO JOSÉ DE CALDAS - UD | E7: Curso Propio | F7: 44167 | G7: 44287 | H7: =+(G7-F7)/90 -> 1.3333333 | I7: Liquidado | J7: Sin Observaciones | K7: OCCIDENTE | L7: Cuenta de ahorros | M7: 230-85718-7 | N7: 580 16 | O7: 2910908016 | P7: =+_xlfn.XLOOKUP(O7,'[3]Benef Primera fecha '!$C:$C,'[3]Benef Primera fecha '!$E:$E,0) -> 25096800 | Q7: 0 | R7: =+(P7+Q7) -> 25096800 | S7: 0.028018089 | T7: =(R7/(1+S7))*S7 -> 684000 | U7: 25096800 | V7: 0 | W7: =+V7/(1+$S7)*$S7 -> 0 | X7: =+W7*40% -> 0 | Y7: =+W7*60% -> 0 | Z7: =_xlfn.XLOOKUP(O7,'[4]2DO TRIMESTRE'!$C:$C,'[4]2DO TRIMESTRE'!$I:$I,0,0) -> 0 | AA7: =+Z7/(1+$S7)*$S7 -> 0 | AB7: =+AA7*40% -> 0 | AC7: =+AA7*60% -> 0 | AD7: 0 | AE7: =+AD7/(1+$S7)*$S7 -> 0 | AF7: =+AE7*40% -> 0 | AG7: =+AE7*60% -> 0 | AH7: 0 | AI7: =+AH7/(1+$S7)*$S7 -> 0 | AJ7: =+AI7*40% -> 0 | AK7: =+AI7*60% -> 0 | AL7: 684000 | AM7: =W7+AA7+AE7+AI7 -> 0
A8: 2 | B8: 2021 | C8: DIEZX CONSULTORES SAS | D8: ACUERDO Y CONDICIO-2-DIEZX CONSULTORES SAS | E8: Contrato | F8: 44215 | G8: 44531 | H8: =+(G8-F8)/90 -> 3.5111111 | I8: En Ejecución | J8: Sin Observaciones | K8: OCCIDENTE | L8: Cuenta de ahorros | M8: 230-87986-8 | N8: 567 71 | O8: 2910906771 | P8: =+_xlfn.XLOOKUP(O8,'[3]Benef Primera fecha '!$C:$C,'[3]Benef Primera fecha '!$E:$E,0) -> 22500000 | Q8: 0 | R8: =+(P8+Q8) -> 22500000 | S8: 0.12 | T8: =(R8/(1+S8))*S8 -> 2410714.3 | U8: 22500000 | V8: 0 | W8: =+V8/(1+$S8)*$S8 -> 0 | X8: =+W8*40% -> 0 | Y8: =+W8*60% -> 0 | Z8: =_xlfn.XLOOKUP(O8,'[4]2DO TRIMESTRE'!$C:$C,'[4]2DO TRIMESTRE'!$I:$I,0,0) -> 0 | AA8: =+Z8/(1+$S8)*$S8 -> 0 | AB8: =+AA8*40% -> 0 | AC8: =+AA8*60% -> 0 | AD8: 0 | AE8: =+AD8/(1+$S8)*$S8 -> 0 | AF8: =+AE8*40% -> 0 | AG8: =+AE8*60% -> 0 | AH8: 0 | AI8: =+AH8/(1+$S8)*$S8 -> 0 | AJ8: =+AI8*40% -> 0 | AK8: =+AI8*60% -> 0 | AL8: 2410710 | AM8: =W8+AA8+AE8+AI8 -> 0
A9: 3 | B9: 2021 | C9: DIEZX CONSULTORES SAS | D9: S/N ACUERDO-DIEZX CONSULTORES SAS | E9: Contrato | F9: 44215 | G9: 44394 | H9: =+(G9-F9)/90 -> 1.9888889 | I9: Terminado | J9: Sin Observaciones | K9: OCCIDENTE | L9: Cuenta de ahorros | M9: 230-87986-8 | N9: 567 36 | O9: 2910906736 | P9: =+_xlfn.XLOOKUP(O9,'[3]Benef Primera fecha '!$C:$C,'[3]Benef Primera fecha '!$E:$E,0) -> 15250000 | Q9: 0 | R9: =+(P9+Q9) -> 15250000 | S9: 0.12 | T9: =(R9/(1+S9))*S9 -> 1633928.6 | U9: 15250000 | V9: 0 | W9: =+V9/(1+$S9)*$S9 -> 0 | X9: =+W9*40% -> 0 | Y9: =+W9*60% -> 0 | Z9: =_xlfn.XLOOKUP(O9,'[4]2DO TRIMESTRE'!$C:$C,'[4]2DO TRIMESTRE'!$I:$I,0,0) -> 0 | AA9: =+Z9/(1+$S9)*$S9 -> 0 | AB9: =+AA9*40% -> 0 | AC9: =+AA9*60% -> 0 | AD9: 0 | AE9: =+AD9/(1+$S9)*$S9 -> 0 | AF9: =+AE9*40% -> 0 | AG9: =+AE9*60% -> 0 | AH9: 0 | AI9: =+AH9/(1+$S9)*$S9 -> 0 | AJ9: =+AI9*40% -> 0 | AK9: =+AI9*60% -> 0 | AL9: 1633929 | AM9: =W9+AA9+AE9+AI9 -> 0
A10: 4 | B10: 2021 | C10: AGENCIA NACIONAL DE SEGURIDAD VIAL | D10: ANSV-003-AGENCIA NACIONAL DE SEGURIDAD VIAL | E10: Contrato | F10: 44238 | G10: 44424 | H10: =+(G10-F10)/90 -> 2.0666667 | I10: Cierre Financiero | J10: Sin Observaciones | K10: OCCIDENTE | L10: Cuenta de ahorros | M10: 230-85893- 8 | N10: 567 32 | O10: 2910906732 | P10: =+_xlfn.XLOOKUP(O10,'[3]Benef Primera fecha '!$C:$C,'[3]Benef Primera fecha '!$E:$E,0) -> 1475936000 | Q10: 0 | R10: =+(P10+Q10) -> 1475936000 | S10: 0.12 | T10: =(R10/(1+S10))*S10 -> 1.58136e+08 | U10: 1475936000 | V10: 0 | W10: =+V10/(1+$S10)*$S10 -> 0 | X10: =+W10*40% -> 0 | Y10: =+W10*60% -> 0 | Z10: =_xlfn.XLOOKUP(O10,'[4]2DO TRIMESTRE'!$C:$C,'[4]2DO TRIMESTRE'!$I:$I,0,0) -> 0 | AA10: =+Z10/(1+$S10)*$S10 -> 0 | AB10: =+AA10*40% -> 0 | AC10: =+AA10*60% -> 0 | AD10: 0 | AE10: =+AD10/(1+$S10)*$S10 -> 0 | AF10: =+AE10*40% -> 0 | AG10: =+AE10*60% -> 0 | AH10: 0 | AI10: =+AH10/(1+$S10)*$S10 -> 0 | AJ10: =+AI10*40% -> 0 | AK10: =+AI10*60% -> 0 | AL10: 158136000 | AM10: =W10+AA10+AE10+AI10 -> 0
A11: 5 | B11: 2021 | C11: UNIVERSIDAD DISTRITAL FRANCISCO JOSÉ DE CALDAS - UD | D11: FAC-MED-8024-UNIVERSIDAD DISTRITAL FRANCISCO JOSÉ DE CALDAS - UD | E11: Curso Propio | F11: 44238 | G11: 44293 | H11: =+(G11-F11)/90 -> 0.61111111 | I11: Liquidado | J11: Sin Observaciones | K11: OCCIDENTE | L11: Cuenta de ahorros | M11: 230-85718-7 | N11: 580 24 | O11: 2910908024 | P11: =+_xlfn.XLOOKUP(O11,'[3]Benef Primera fecha '!$C:$C,'[3]Benef Primera fecha '!$E:$E,0) -> 28967499 | Q11: 0 | R11: =+(P11+Q11) -> 28967499 | S11: 0.1365 | T11: =(R11/(1+S11))*S11 -> 3479158.5 | U11: 28967499 | V11: 0 | W11: =+V11/(1+$S11)*$S11 -> 0 | X11: =+W11*40% -> 0 | Y11: =+W11*60% -> 0 | Z11: =_xlfn.XLOOKUP(O11,'[4]2DO TRIMESTRE'!$C:$C,'[4]2DO TRIMESTRE'!$I:$I,0,0) -> 0 | AA11: =+Z11/(1+$S11)*$S11 -> 0 | AB11: =+AA11*40% -> 0 | AC11: =+AA11*60% -> 0 | AD11: 0 | AE11: =+AD11/(1+$S11)*$S11 -> 0 | AF11: =+AE11*40% -> 0 | AG11: =+AE11*60% -> 0 | AH11: 0 | AI11: =+AH11/(1+$S11)*$S11 -> 0 | AJ11: =+AI11*40% -> 0 | AK11: =+AI11*60% -> 0 | AL11: 3479129 | AM11: =W11+AA11+AE11+AI11 -> 0
A12: 6 | B12: 2021 | C12: MINISTERIO DE DEFENSA NACIONAL | D12: 021-00-G-CACOM-4-MINISTERIO DE DEFENSA NACIONAL | E12: Contrato | F12: 44249 | G12: 44700 | H12: =+(G12-F12)/90 -> 5.0111111 | I12: En Ejecución | J12: Sin Observaciones | K12: OCCIDENTE | L12: Cuenta de ahorros | M12: 230-85893- 8 | N12: 567 31 | O12: 2910906731 | P12: =+_xlfn.XLOOKUP(O12,'[3]Benef Primera fecha '!$C:$C,'[3]Benef Primera fecha '!$E:$E,0) -> 739371600 | Q12: 367057023 | R12: =+(P12+Q12) -> 1106428623 | S12: 0.12 | T12: =(R12/(1+S12))*S12 -> 118545925 | U12: 1106428623 | V12: 0 | W12: =+V12/(1+$S12)*$S12 -> 0 | X12: =+W12*40% -> 0 | Y12: =+W12*60% -> 0 | Z12: =_xlfn.XLOOKUP(O12,'[4]2DO TRIMESTRE'!$C:$C,'[4]2DO TRIMESTRE'!$I:$I,0,0) -> 0 | AA12: =+Z12/(1+$S12)*$S12 -> 0 | AB12: =+AA12*40% -> 0 | AC12: =+AA12*60% -> 0 | AD12: 0 | AE12: =+AD12/(1+$S12)*$S12 -> 0 | AF12: =+AE12*40% -> 0 | AG12: =+AE12*60% -> 0 | AH12: 0 | AI12: =+AH12/(1+$S12)*$S12 -> 0 | AJ12: =+AI12*40% -> 0 | AK12: =+AI12*60% -> 0 | AL12: 118545925 | AM12: =W12+AA12+AE12+AI12 -> 0
A13: 7 | B13: 2021 | C13: MUNICIPIO DE EL COLEGIO | D13: 128-MUNICIPIO DE EL COLEGIO | E13: Convenio Interadministrativo | F13: 44257 | G13: 44867 | H13: =+(G13-F13)/90 -> 6.7777778 | I13: Terminado | J13: Sin Observaciones | K13: OCCIDENTE | L13: Cuenta de ahorros | M13: 230-85893- 8 | N13: 83 10 | O13: 2453018310 | P13: =+_xlfn.XLOOKUP(O13,'[3]Benef Primera fecha '!$C:$C,'[3]Benef Primera fecha '!$E:$E,0) -> 306603272 | Q13: 0 | R13: =+(P13+Q13) -> 306603272 | S13: 0.12 | T13: =(R13/(1+S13))*S13 -> 32850351 | U13: 283797434 | V13: 0 | W13: =+V13/(1+$S13)*$S13 -> 0 | X13: =+W13*40% -> 0 | Y13: =+W13*60% -> 0 | Z13: =_xlfn.XLOOKUP(O13,'[4]2DO TRIMESTRE'!$C:$C,'[4]2DO TRIMESTRE'!$I:$I,0,0) -> 0 | AA13: =+Z13/(1+$S13)*$S13 -> 0 | AB13: =+AA13*40% -> 0 | AC13: =+AA13*60% -> 0 | AD13: 0 | AE13: =+AD13/(1+$S13)*$S13 -> 0 | AF13: =+AE13*40% -> 0 | AG13: =+AE13*60% -> 0 | AH13: 0 | AI13: =+AH13/(1+$S13)*$S13 -> 0 | AJ13: =+AI13*40% -> 0 | AK13: =+AI13*60% -> 0 | AL13: 30406868 | AM13: =W13+AA13+AE13+AI13 -> 0
A14: 8 | B14: 2021 | C14: INSTITUTO DEPARTAMENTAL DE CULTURA Y TURISMO DE CUNDINAMARCA | D14: 117-INSTITUTO DEPARTAMENTAL DE CULTURA Y TURISMO DE CUNDINAMARCA | E14: Contrato | F14: 44258 | G14: 44412 | H14: =+(G14-F14)/90 -> 1.7111111 | I14: Liquidado | J14: Sin Observaciones | K14: OCCIDENTE | L14: Cuenta de ahorros | M14: 230-85893- 8 | N14: 567 33 | O14: 2910906733 | P14: =+_xlfn.XLOOKUP(O14,'[3]Benef Primera fecha '!$C:$C,'[3]Benef Primera fecha '!$E:$E,0) -> 35000000 | Q14: 0 | R14: =+(P14+Q14) -> 35000000 | S14: 0.12 | T14: =(R14/(1+S14))*S14 -> 3750000 | U14: 35000000 | V14: 0 | W14: =+V14/(1+$S14)*$S14 -> 0 | X14: =+W14*40% -> 0 | Y14: =+W14*60% -> 0 | Z14: =_xlfn.XLOOKUP(O14,'[4]2DO TRIMESTRE'!$C:$C,'[4]2DO TRIMESTRE'!$I:$I,0,0) -> 0 | AA14: =+Z14/(1+$S14)*$S14 -> 0 | AB14: =+AA14*40% -> 0 | AC14: =+AA14*60% -> 0 | AD14: 0 | AE14: =+AD14/(1+$S14)*$S14 -> 0 | AF14: =+AE14*40% -> 0 | AG14: =+AE14*60% -> 0 | AH14: 0 | AI14: =+AH14/(1+$S14)*$S14 -> 0 | AJ14: =+AI14*40% -> 0 | AK14: =+AI14*60% -> 0 | AL14: 3750000 | AM14: =W14+AA14+AE14+AI14 -> 0
A15: 9 | B15: 2021 | C15: CORPORACIÓN AUTÓNOMA REGIONAL DE LOS VALLES DEL SINÚ Y DEL SAN JORGE - CVS | D15: 001-CORPORACIÓN AUTÓNOMA REGIONAL DE LOS VALLES DEL SINÚ Y DEL SAN JORGE - CVS | E15: Convenio Interadministrativo | F15: 44281 | G15: 44538 | H15: =+(G15-F15)/90 -> 2.8555556 | I15: Cierre Financiero | J15: Sin Observaciones | K15: OCCIDENTE | L15: Cuenta de ahorros | M15: 230-89456-0 | N15: 83 11 | O15: 2453018311 | P15: =+_xlfn.XLOOKUP(O15,'[3]Benef Primera fecha '!$C:$C,'[3]Benef Primera fecha '!$E:$E,0) -> 839500000 | Q15: 0 | R15: =+(P15+Q15) -> 839500000 | S15: 0.12 | T15: =(R15/(1+S15))*S15 -> 89946429 | U15: 693521814 | V15: 0 | W15: =+V15/(1+$S15)*$S15 -> 0 | X15: =+W15*40% -> 0 | Y15: =+W15*60% -> 0 | Z15: =_xlfn.XLOOKUP(O15,'[4]2DO TRIMESTRE'!$C:$C,'[4]2DO TRIMESTRE'!$I:$I,0,0) -> 0 | AA15: =+Z15/(1+$S15)*$S15 -> 0 | AB15: =+AA15*40% -> 0 | AC15: =+AA15*60% -> 0 | AD15: 0 | AE15: =+AD15/(1+$S15)*$S15 -> 0 | AF15: =+AE15*40% -> 0 | AG15: =+AE15*60% -> 0 | AH15: 0 | AI15: =+AH15/(1+$S15)*$S15 -> 0 | AJ15: =+AI15*40% -> 0 | AK15: =+AI15*60% -> 0 | AL15: 74305909 | AM15: =W15+AA15+AE15+AI15 -> 0
A16: 10 | B16: 2021 | C16: GOBERNACIÓN DE CUNDINAMARCA | D16: SFP-CDCTI-043-GOBERNACIÓN DE CUNDINAMARCA | E16: Contrato | F16: 44306 | G16: 44505 | H16: =+(G16-F16)/90 -> 2.2111111 | I16: Liquidado | J16: Sin Observaciones | K16: OCCIDENTE | L16: Cuenta de ahorros | M16: 230-85718-7 | N16: 567 34 | O16: 2910906734 | P16: =+_xlfn.XLOOKUP(O16,'[3]Benef Primera fecha '!$C:$C,'[3]Benef Primera fecha '!$E:$E,0) -> 39028000 | Q16: 0 | R16: =+(P16+Q16) -> 39028000 | S16: 0.12 | T16: =(R16/(1+S16))*S16 -> 4181571.4 | U16: 20814936 | V16: 0 | W16: =+V16/(1+$S16)*$S16 -> 0 | X16: =+W16*40% -> 0 | Y16: =+W16*60% -> 0 | Z16: =_xlfn.XLOOKUP(O16,'[4]2DO TRIMESTRE'!$C:$C,'[4]2DO TRIMESTRE'!$I:$I,0,0) -> 0 | AA16: =+Z16/(1+$S16)*$S16 -> 0 | AB16: =+AA16*40% -> 0 | AC16: =+AA16*60% -> 0 | AD16: 0 | AE16: =+AD16/(1+$S16)*$S16 -> 0 | AF16: =+AE16*40% -> 0 | AG16: =+AE16*60% -> 0 | AH16: 0 | AI16: =+AH16/(1+$S16)*$S16 -> 0 | AJ16: =+AI16*40% -> 0 | AK16: =+AI16*60% -> 0 | AL16: 2230171 | AM16: =W16+AA16+AE16+AI16 -> 0
A17: 11 | B17: 2021 | C17: INSTITUTO NACIONAL DE VIAS - INVIAS | D17: 891-2021-INSTITUTO NACIONAL DE VIAS - INVIAS | E17: Contrato | F17: 44315 | H17: =+(G17-F17)/90 -> -492.38889 | I17: Liquidado | J17: Sin Observaciones | K17: OCCIDENTE | L17: Cuenta de ahorros | M17: 230-85893- 8 | N17: 567 35 | O17: 2910906735 | P17: =+_xlfn.XLOOKUP(O17,'[3]Benef Primera fecha '!$C:$C,'[3]Benef Primera fecha '!$E:$E,0) -> 925000000 | Q17: 0 | R17: =+(P17+Q17) -> 925000000 | S17: 0.12 | T17: =(R17/(1+S17))*S17 -> 99107143 | U17: 1121496023 | V17: 0 | W17: =+V17/(1+$S17)*$S17 -> 0 | X17: =+W17*40% -> 0 | Y17: =+W17*60% -> 0 | Z17: =_xlfn.XLOOKUP(O17,'[4]2DO TRIMESTRE'!$C:$C,'[4]2DO TRIMESTRE'!$I:$I,0,0) -> 0 | AA17: =+Z17/(1+$S17)*$S17 -> 0 | AB17: =+AA17*40% -> 0 | AC17: =+AA17*60% -> 0 | AD17: 0 | AE17: =+AD17/(1+$S17)*$S17 -> 0 | AF17: =+AE17*40% -> 0 | AG17: =+AE17*60% -> 0 | AH17: 0 | AI17: =+AH17/(1+$S17)*$S17 -> 0 | AJ17: =+AI17*40% -> 0 | AK17: =+AI17*60% -> 0 | AL17: 99107143 | AM17: =W17+AA17+AE17+AI17 -> 0
A18: 12 | B18: 2021 | C18: CIDC-UNIVERSIDAD NACIONAL DE COLOMBIA | D18: 80740-542 S/N CONVENIO DE ASOCIACION-UNIVERSIDAD NACIONAL DE COLOMBIA | E18: Convenio Interadministrativo | F18: 44320 | G18: 45236 | H18: =+(G18-F18)/90 -> 10.177778 | I18: En Ejecución | J18: Sin Observaciones | K18: OCCIDENTE | L18: Cuenta de ahorros | M18: 230-85893- 8 | N18: 83 12 | O18: 2453018312 | P18: =_xlfn.XLOOKUP(O18,[5]Base!$C:$C,[5]Base!$E:$E,0,0) -> 0 | Q18: 0 | R18: =+(P18+Q18) -> 0 | S18: 0 | T18: =(R18/(1+S18))*S18 -> 0 | U18: 0 | V18: 0 | W18: =+V18/(1+$S18)*$S18 -> 0 | X18: =+W18*40% -> 0 | Y18: =+W18*60% -> 0 | Z18: =_xlfn.XLOOKUP(O18,'[4]2DO TRIMESTRE'!$C:$C,'[4]2DO TRIMESTRE'!$I:$I,0,0) -> 0 | AA18: =+Z18/(1+$S18)*$S18 -> 0 | AB18: =+AA18*40% -> 0 | AC18: =+AA18*60% -> 0 | AD18: 0 | AE18: =+AD18/(1+$S18)*$S18 -> 0 | AF18: =+AE18*40% -> 0 | AG18: =+AE18*60% -> 0 | AH18: 0 | AI18: =+AH18/(1+$S18)*$S18 -> 0 | AJ18: =+AI18*40% -> 0 | AK18: =+AI18*60% -> 0 | AL18: 0 | AM18: =W18+AA18+AE18+AI18 -> 0 | AN18: Proyecto sin beneficio institucional estipulado en el presupuesto | AO18: Proyecto sin beneficio institucional estipulado en el presupuesto
A19: 13 | B19: 2021 | C19: UNIVERSIDAD DISTRITAL FRANCISCO JOSÉ DE CALDAS - UD | D19: FAC-TECNO-8033-UNIVERSIDAD DISTRITAL FRANCISCO JOSÉ DE CALDAS - UD | E19: Curso Propio | F19: 44323 | G19: 44419 | H19: =+(G19-F19)/90 -> 1.0666667 | I19: Liquidado | J19: Sin Observaciones | K19: OCCIDENTE | L19: Cuenta de ahorros | M19: 230-85718-7 | N19: 580 33 | O19: 2910908033 | P19: =+_xlfn.XLOOKUP(O19,'[3]Benef Primera fecha '!$C:$C,'[3]Benef Primera fecha '!$E:$E,0) -> 65415600 | Q19: 0 | R19: =+(P19+Q19) -> 65415600 | S19: 0.12 | T19: 7849872 | U19: 65415600 | V19: 0 | W19: =+V19/(1+$S19)*$S19 -> 0 | X19: =+W19*40% -> 0 | Y19: =+W19*60% -> 0 | Z19: =_xlfn.XLOOKUP(O19,'[4]2DO TRIMESTRE'!$C:$C,'[4]2DO TRIMESTRE'!$I:$I,0,0) -> 0 | AA19: =+Z19/(1+$S19)*$S19 -> 0 | AB19: =+AA19*40% -> 0 | AC19: =+AA19*60% -> 0 | AD19: 0 | AE19: =+AD19/(1+$S19)*$S19 -> 0 | AF19: =+AE19*40% -> 0 | AG19: =+AE19*60% -> 0 | AH19: 0 | AI19: =+AH19/(1+$S19)*$S19 -> 0 | AJ19: =+AI19*40% -> 0 | AK19: =+AI19*60% -> 0 | AL19: 7849872 | AM19: =W19+AA19+AE19+AI19 -> 0
A20: 14 | B20: 2021 | C20: ORGANISMO INTERNACIONAL DE ENERGÍA ATOMICA | D20: 24500-ORGANISMO INTERNACIONAL DE ENERGÍA ATOMICA | E20: Contrato | F20: 44326 | G20: 44529 | H20: =+(G20-F20)/90 -> 2.2555556 | I20: En Ejecución | J20: Sin Observaciones | K20: OCCIDENTE | L20: Cuenta de ahorros | M20: 230-85893- 8 | N20: 567 45 | O20: 2910906745 | P20: 180187477 | Q20: 0 | R20: =+(P20+Q20) -> 180187477 | S20: 0 | T20: =(R20/(1+S20))*S20 -> 0 | U20: 0 | V20: 0 | W20: =+V20/(1+$S20)*$S20 -> 0 | X20: =+W20*40% -> 0 | Y20: =+W20*60% -> 0 | Z20: =_xlfn.XLOOKUP(O20,'[4]2DO TRIMESTRE'!$C:$C,'[4]2DO TRIMESTRE'!$I:$I,0,0) -> 0 | AA20: =+Z20/(1+$S20)*$S20 -> 0 | AB20: =+AA20*40% -> 0 | AC20: =+AA20*60% -> 0 | AD20: 0 | AE20: =+AD20/(1+$S20)*$S20 -> 0 | AF20: =+AE20*40% -> 0 | AG20: =+AE20*60% -> 0 | AH20: 0 | AI20: =+AH20/(1+$S20)*$S20 -> 0 | AJ20: =+AI20*40% -> 0 | AK20: =+AI20*60% -> 0 | AL20: 0 | AM20: =W20+AA20+AE20+AI20 -> 0 | AN20: Proyecto sin beneficio institucional estipulado en el presupuesto | AO20: Proyecto sin beneficio institucional estipulado en el presupuesto
A21: 15 | B21: 2021 | C21: COMISIÓN DE REGULACIÓN DE AGUA POTABLE Y SANEAMIENTO BÁSICO - CRA | D21: 97-COMISIÓN DE REGULACIÓN DE AGUA POTABLE Y SANEAMIENTO BÁSICO - CRA | E21: Contrato | F21: 44326 | G21: 44530 | H21: =+(G21-F21)/90 -> 2.2666667 | I21: Cierre Financiero | J21: Sin Observaciones | K21: OCCIDENTE | L21: Cuenta de ahorros | M21: 230-85893- 8 | N21: 567 37 | O21: 2910906737 | P21: =+_xlfn.XLOOKUP(O21,'[3]Benef Primera fecha '!$C:$C,'[3]Benef Primera fecha '!$E:$E,0) -> 50000000 | Q21: 0 | R21: =+(P21+Q21) -> 50000000 | S21: 0.12 | T21: =(R21/(1+S21))*S21 -> 5357142.9 | U21: 50000000 | V21: 0 | W21: =+V21/(1+$S21)*$S21 -> 0 | X21: =+W21*40% -> 0 | Y21: =+W21*60% -> 0 | Z21: =_xlfn.XLOOKUP(O21,'[4]2DO TRIMESTRE'!$C:$C,'[4]2DO TRIMESTRE'!$I:$I,0,0) -> 0 | AA21: =+Z21/(1+$S21)*$S21 -> 0 | AB21: =+AA21*40% -> 0 | AC21: =+AA21*60% -> 0 | AD21: 0 | AE21: =+AD21/(1+$S21)*$S21 -> 0 | AF21: =+AE21*40% -> 0 | AG21: =+AE21*60% -> 0 | AH21: 0 | AI21: =+AH21/(1+$S21)*$S21 -> 0 | AJ21: =+AI21*40% -> 0 | AK21: =+AI21*60% -> 0 | AL21: 5357143 | AM21: =W21+AA21+AE21+AI21 -> 0
A22: 16 | B22: 2021 | C22: MINISTERIO DE DEFENSA NACIONAL INSTITUTO DE CASAS FISCALES DEL EJÉRCITO | D22: 111-MINISTERIO DE DEFENSA NACIONAL INSTITUTO DE CASAS FISCALES DEL EJÉRCITO | E22: Contrato | F22: 44327 | G22: 44510 | H22: =+(G22-F22)/90 -> 2.0333333 | I22: Liquidado | J22: Sin Observaciones | K22: OCCIDENTE | L22: Cuenta de ahorros | M22: 230-85893- 8 | N22: 567 40 | O22: 2910906740 | P22: =+_xlfn.XLOOKUP(O22,'[3]Benef Primera fecha '!$C:$C,'[3]Benef Primera fecha '!$E:$E,0) -> 53704000 | Q22: 0 | R22: =+(P22+Q22) -> 53704000 | S22: 0.12 | T22: 6445000 | U22: 53704000 | V22: 0 | W22: =+V22/(1+$S22)*$S22 -> 0 | X22: =+W22*40% -> 0 | Y22: =+W22*60% -> 0 | Z22: 50638245 | AA22: =+Z22/(1+$S22)*$S22 -> 5425526.2 | AB22: =+AA22*40% -> 2170210.5 | AC22: =+AA22*60% -> 3255315.7 | AD22: 0 | AE22: =+AD22/(1+$S22)*$S22 -> 0 | AF22: =+AE22*40% -> 0 | AG22: =+AE22*60% -> 0 | AH22: 0 | AI22: =+AH22/(1+$S22)*$S22 -> 0 | AJ22: =+AI22*40% -> 0 | AK22: =+AI22*60% -> 0 | AL22: 6445000 | AM22: =W22+AA22+AE22+AI22 -> 5425526.2
A23: 17 | B23: 2021 | C23: UNIVERSIDAD DISTRITAL FRANCISCO JOSÉ DE CALDAS - UD | D23: FAC-ING-8029-UNIVERSIDAD DISTRITAL FRANCISCO JOSÉ DE CALDAS - UD | E23: Curso Propio | F23: 44327 | G23: 44428 | H23: =+(G23-F23)/90 -> 1.1222222 | I23: Liquidado | J23: Sin Observaciones | K23: OCCIDENTE | L23: Cuenta de ahorros | M23: 230-85718-7 | N23: 580 29 | O23: 2910908029 | P23: =+_xlfn.XLOOKUP(O23,'[3]Benef Primera fecha '!$C:$C,'[3]Benef Primera fecha '!$E:$E,0) -> 17160000 | Q23: 0 | R23: =+(P23+Q23) -> 17160000 | S23: 0.12 | T23: =(R23/(1+S23))*S23 -> 1838571.4 | U23: 17160000 | V23: 0 | W23: =+V23/(1+$S23)*$S23 -> 0 | X23: =+W23*40% -> 0 | Y23: =+W23*60% -> 0 | Z23: =_xlfn.XLOOKUP(O23,'[4]2DO TRIMESTRE'!$C:$C,'[4]2DO TRIMESTRE'!$I:$I,0,0) -> 0 | AA23: =+Z23/(1+$S23)*$S23 -> 0 | AB23: =+AA23*40% -> 0 | AC23: =+AA23*60% -> 0 | AD23: 0 | AE23: =+AD23/(1+$S23)*$S23 -> 0 | AF23: =+AE23*40% -> 0 | AG23: =+AE23*60% -> 0 | AH23: 0 | AI23: =+AH23/(1+$S23)*$S23 -> 0 | AJ23: =+AI23*40% -> 0 | AK23: =+AI23*60% -> 0 | AL23: 1838571 | AM23: =W23+AA23+AE23+AI23 -> 0
A24: 18 | B24: 2021 | C24: UNIVERSIDAD DISTRITAL FRANCISCO JOSÉ DE CALDAS - UD | D24: 16161-UNIVERSIDAD DISTRITAL FRANCISCO JOSÉ DE CALDAS - UD | E24: Curso Propio | F24: 44328 | G24: 44695 | H24: =+(G24-F24)/90 -> 4.0777778 | I24: Terminado | J24: Sin Observaciones | K24: OCCIDENTE | L24: Cuenta de ahorros | M24: 230-85718-7 | N24: 580 37 | O24: 2910908037 | P24: 36473350 | Q24: 0 | R24: =+(P24+Q24) -> 36473350 | S24: 0 | T24: =(R24/(1+S24))*S24 -> 0 | U24: 0 | V24: 0 | W24: =+V24/(1+$S24)*$S24 -> 0 | X24: =+W24*40% -> 0 | Y24: =+W24*60% -> 0 | Z24: =_xlfn.XLOOKUP(O24,'[4]2DO TRIMESTRE'!$C:$C,'[4]2DO TRIMESTRE'!$I:$I,0,0) -> 0 | AA24: =+Z24/(1+$S24)*$S24 -> 0 | AB24: =+AA24*40% -> 0 | AC24: =+AA24*60% -> 0 | AD24: 0 | AE24: =+AD24/(1+$S24)*$S24 -> 0 | AF24: =+AE24*40% -> 0 | AG24: =+AE24*60% -> 0 | AH24: 0 | AI24: =+AH24/(1+$S24)*$S24 -> 0 | AJ24: =+AI24*40% -> 0 | AK24: =+AI24*60% -> 0 | AL24: 0 | AM24: =W24+AA24+AE24+AI24 -> 0
A25: 19 | B25: 2021 | C25: INSTITUTO GEOGRAFICO AGUSTIN CODAZZI - IGAC | D25: 24715-INSTITUTO GEOGRAFICO AGUSTIN CODAZZI - IGAC | E25: Contrato | F25: 44329 | G25: 44560 | H25: =+(G25-F25)/90 -> 2.5666667 | I25: Liquidado | J25: Sin Observaciones | K25: OCCIDENTE | L25: Cuenta de ahorros | M25: 230-85893- 8 | N25: 567 39 | O25: 2910906739 | P25: =+_xlfn.XLOOKUP(O25,'[3]Benef Primera fecha '!$C:$C,'[3]Benef Primera fecha '!$E:$E,0) -> 225600000 | Q25: 0 | R25: =+(P25+Q25) -> 225600000 | S25: 0.12 | T25: =(R25/(1+S25))*S25 -> 24171429 | U25: 225600000 | V25: 0 | W25: =+V25/(1+$S25)*$S25 -> 0 | X25: =+W25*40% -> 0 | Y25: =+W25*60% -> 0 | Z25: =_xlfn.XLOOKUP(O25,'[4]2DO TRIMESTRE'!$C:$C,'[4]2DO TRIMESTRE'!$I:$I,0,0) -> 0 | AA25: =+Z25/(1+$S25)*$S25 -> 0 | AB25: =+AA25*40% -> 0 | AC25: =+AA25*60% -> 0 | AD25: 0 | AE25: =+AD25/(1+$S25)*$S25 -> 0 | AF25: =+AE25*40% -> 0 | AG25: =+AE25*60% -> 0 | AH25: 0 | AI25: =+AH25/(1+$S25)*$S25 -> 0 | AJ25: =+AI25*40% -> 0 | AK25: =+AI25*60% -> 0 | AL25: 24171429 | AM25: =W25+AA25+AE25+AI25 -> 0
A26: 20 | B26: 2021 | C26: FIDUPREVISORA S.A. | D26: 80740-023-FIDUPREVISORA S.A. | E26: Contrato | F26: 44330 | G26: 45059 | H26: =+(G26-F26)/90 -> 8.1 | I26: En Ejecución | J26: Sin Observaciones | K26: OCCIDENTE | L26: Cuenta de ahorros | M26: 230-85893- 8 | N26: 567 38 | O26: 2910906738 | P26: 298773815 | Q26: 0 | R26: =+(P26+Q26) -> 298773815 | S26: 0 | T26: =(R26/(1+S26))*S26 -> 0 | U26: 0 | V26: 0 | W26: =+V26/(1+$S26)*$S26 -> 0 | X26: =+W26*40% -> 0 | Y26: =+W26*60% -> 0 | Z26: =_xlfn.XLOOKUP(O26,'[4]2DO TRIMESTRE'!$C:$C,'[4]2DO TRIMESTRE'!$I:$I,0,0) -> 0 | AA26: =+Z26/(1+$S26)*$S26 -> 0 | AB26: =+AA26*40% -> 0 | AC26: =+AA26*60% -> 0 | AD26: 0 | AE26: =+AD26/(1+$S26)*$S26 -> 0 | AF26: =+AE26*40% -> 0 | AG26: =+AE26*60% -> 0 | AH26: 0 | AI26: =+AH26/(1+$S26)*$S26 -> 0 | AJ26: =+AI26*40% -> 0 | AK26: =+AI26*60% -> 0 | AL26: 0 | AM26: =W26+AA26+AE26+AI26 -> 0 | AN26: Proyecto sin beneficio institucional estipulado en el presupuesto | AO26: Proyecto sin beneficio institucional estipulado en el presupuesto
A27: 21 | B27: 2021 | C27: FIDUPREVISORA S.A. | D27: 80740-110-FIDUPREVISORA S.A. | E27: Contrato | F27: 44330 | G27: 44817 | H27: =+(G27-F27)/90 -> 5.4111111 | I27: En Ejecución | J27: Sin Observaciones | K27: OCCIDENTE | L27: Cuenta de ahorros | M27: 230-85893- 8 | N27: 567 41 | O27: 2910906741 | P27: 75266267 | Q27: 0 | R27: =+(P27+Q27) -> 75266267 | S27: 0 | T27: =(R27/(1+S27))*S27 -> 0 | U27: 0 | V27: 0 | W27: =+V27/(1+$S27)*$S27 -> 0 | X27: =+W27*40% -> 0 | Y27: =+W27*60% -> 0 | Z27: =_xlfn.XLOOKUP(O27,'[4]2DO TRIMESTRE'!$C:$C,'[4]2DO TRIMESTRE'!$I:$I,0,0) -> 0 | AA27: =+Z27/(1+$S27)*$S27 -> 0 | AB27: =+AA27*40% -> 0 | AC27: =+AA27*60% -> 0 | AD27: 0 | AE27: =+AD27/(1+$S27)*$S27 -> 0 | AF27: =+AE27*40% -> 0 | AG27: =+AE27*60% -> 0 | AH27: 0 | AI27: =+AH27/(1+$S27)*$S27 -> 0 | AJ27: =+AI27*40% -> 0 | AK27: =+AI27*60% -> 0 | AL27: 0 | AM27: =W27+AA27+AE27+AI27 -> 0 | AN27: Proyecto sin beneficio institucional estipulado en el presupuesto | AO27: Proyecto sin beneficio institucional estipulado en el presupuesto
A28: 22 | B28: 2021 | C28: UNIVERSIDAD DISTRITAL FRANCISCO JOSÉ DE CALDAS - UD | D28: FAC-CIE-8032-UNIVERSIDAD DISTRITAL FRANCISCO JOSÉ DE CALDAS - UD | E28: Curso Propio | F28: 44336 | G28: 44427 | H28: =+(G28-F28)/90 -> 1.0111111 | I28: Liquidado | J28: Sin Observaciones | K28: OCCIDENTE | L28: Cuenta de ahorros | M28: 230-85718-7 | N28: 580 32 | O28: 2910908032 | P28: =+_xlfn.XLOOKUP(O28,'[3]Benef Primera fecha '!$C:$C,'[3]Benef Primera fecha '!$E:$E,0) -> 32706980 | Q28: 0 | R28: =+(P28+Q28) -> 32706980 | S28: 0.12 | T28: 3924832 | U28: 32706980 | V28: 0 | W28: =+V28/(1+$S28)*$S28 -> 0 | X28: =+W28*40% -> 0 | Y28: =+W28*60% -> 0 | Z28: =_xlfn.XLOOKUP(O28,'[4]2DO TRIMESTRE'!$C:$C,'[4]2DO TRIMESTRE'!$I:$I,0,0) -> 0 | AA28: =+Z28/(1+$S28)*$S28 -> 0 | AB28: =+AA28*40% -> 0 | AC28: =+AA28*60% -> 0 | AD28: 0 | AE28: =+AD28/(1+$S28)*$S28 -> 0 | AF28: =+AE28*40% -> 0 | AG28: =+AE28*60% -> 0 | AH28: 0 | AI28: =+AH28/(1+$S28)*$S28 -> 0 | AJ28: =+AI28*40% -> 0 | AK28: =+AI28*60% -> 0 | AL28: 3924832 | AM28: =W28+AA28+AE28+AI28 -> 0
A29: 23 | B29: 2021 | C29: UNIVERSIDAD DE TWENTE | D29: 3-UNIVERSIDAD DE TWENTE | E29: Convenio Interadministrativo | F29: 44351 | G29: 44530 | H29: =+(G29-F29)/90 -> 1.9888889 | I29: En Ejecución | J29: Sin Observaciones | K29: OCCIDENTE | L29: Cuenta de ahorros | M29: 230-85893- 8 | N29: 83 14 | O29: 2453018314 | P29: 24028920 | Q29: 0 | R29: =+(P29+Q29) -> 24028920 | S29: 0 | T29: =(R29/(1+S29))*S29 -> 0 | U29: 0 | V29: 0 | W29: =+V29/(1+$S29)*$S29 -> 0 | X29: =+W29*40% -> 0 | Y29: =+W29*60% -> 0 | Z29: =_xlfn.XLOOKUP(O29,'[4]2DO TRIMESTRE'!$C:$C,'[4]2DO TRIMESTRE'!$I:$I,0,0) -> 0 | AA29: =+Z29/(1+$S29)*$S29 -> 0 | AB29: =+AA29*40% -> 0 | AC29: =+AA29*60% -> 0 | AD29: 0 | AE29: =+AD29/(1+$S29)*$S29 -> 0 | AF29: =+AE29*40% -> 0 | AG29: =+AE29*60% -> 0 | AH29: 0 | AI29: =+AH29/(1+$S29)*$S29 -> 0 | AJ29: =+AI29*40% -> 0 | AK29: =+AI29*60% -> 0 | AL29: 0 | AM29: =W29+AA29+AE29+AI29 -> 0 | AN29: Proyecto sin beneficio institucional estipulado en el presupuesto | AO29: Proyecto sin beneficio institucional estipulado en el presupuesto
A30: 24 | B30: 2021 | C30: GOBERNACIÓN DE LA GUAJIRA | D30: 010-2021-GOBERNACIÓN DE LA GUAJIRA | E30: Contrato | F30: 44351 | G30: 45317 | H30: =+(G30-F30)/90 -> 10.733333 | I30: En Ejecución | J30: Sin Observaciones | K30: OCCIDENTE | L30: Cuenta de ahorros | M30: 230-89464-4 | N30: 567 43 | O30: 2910906743 | P30: =+_xlfn.XLOOKUP(O30,'[3]Benef Primera fecha '!$C:$C,'[3]Benef Primera fecha '!$E:$E,0) -> 577046931 | Q30: 0 | R30: =+(P30+Q30) -> 577046931 | S30: 0.12 | T30: =(R30/(1+S30))*S30 -> 61826457 | U30: 5.2476971e+08 | V30: 0 | W30: =+V30/(1+$S30)*$S30 -> 0 | X30: =+W30*40% -> 0 | Y30: =+W30*60% -> 0 | Z30: =_xlfn.XLOOKUP(O30,'[4]2DO TRIMESTRE'!$C:$C,'[4]2DO TRIMESTRE'!$I:$I,0,0) -> 0 | AA30: =+Z30/(1+$S30)*$S30 -> 0 | AB30: =+AA30*40% -> 0 | AC30: =+AA30*60% -> 0 | AD30: 0 | AE30: =+AD30/(1+$S30)*$S30 -> 0 | AF30: =+AE30*40% -> 0 | AG30: =+AE30*60% -> 0 | AH30: 0 | AI30: =+AH30/(1+$S30)*$S30 -> 0 | AJ30: =+AI30*40% -> 0 | AK30: =+AI30*60% -> 0 | AL30: 5288324 | AM30: =W30+AA30+AE30+AI30 -> 0
A31: 25 | B31: 2021 | C31: REGIÓN ADMINISTRATIVA Y DE PLANEACION ESPECIAL — RAPE | D31: 55-REGIÓN ADMINISTRATIVA Y DE PLANEACION ESPECIAL — RAPE | E31: Convenio Interadministrativo | F31: 44355 | G31: 44561 | H31: =+(G31-F31)/90 -> 2.2888889 | I31: Liquidado | J31: Sin Observaciones | K31: OCCIDENTE | L31: Cuenta de ahorros | M31: 230-89467-7 | N31: 83 13 | O31: 2453018313 | P31: =+_xlfn.XLOOKUP(O31,'[3]Benef Primera fecha '!$C:$C,'[3]Benef Primera fecha '!$E:$E,0) -> 419170248 | Q31: 209552512 | R31: =+(P31+Q31) -> 628722760 | S31: 0.12 | T31: =(R31/(1+S31))*S31 -> 67363153 | U31: 543477013 | V31: 0 | W31: =+V31/(1+$S31)*$S31 -> 0 | X31: =+W31*40% -> 0 | Y31: =+W31*60% -> 0 | Z31: =_xlfn.XLOOKUP(O31,'[4]2DO TRIMESTRE'!$C:$C,'[4]2DO TRIMESTRE'!$I:$I,0,0) -> 0 | AA31: =+Z31/(1+$S31)*$S31 -> 0 | AB31: =+AA31*40% -> 0 | AC31: =+AA31*60% -> 0 | AD31: 0 | AE31: =+AD31/(1+$S31)*$S31 -> 0 | AF31: =+AE31*40% -> 0 | AG31: =+AE31*60% -> 0 | AH31: 0 | AI31: =+AH31/(1+$S31)*$S31 -> 0 | AJ31: =+AI31*40% -> 0 | AK31: =+AI31*60% -> 0 | AL31: 58229680 | AM31: =W31+AA31+AE31+AI31 -> 0
A32: 26 | B32: 2021 | C32: SERVICIO NACIONAL DE APRENDIZAJE - SENA | D32: CO1.PCCNTR.2564825-SERVICIO NACIONAL DE APRENDIZAJE - SENA | E32: Contrato | F32: 44356 | G32: 45464 | H32: =+(G32-F32)/90 -> 12.311111 | I32: En Ejecución | J32: Sin Observaciones | K32: OCCIDENTE | L32: Cuenta Corriente | M32: 230-89517-9 | N32: 567 42 | O32: 2910906742 | P32: =+_xlfn.XLOOKUP(O32,'[3]Benef Primera fecha '!$C:$C,'[3]Benef Primera fecha '!$E:$E,0) -> 7279682085 | Q32: 1980000000 | R32: =+(P32+Q32) -> 9259682085 | S32: 0.12 | T32: =(R32/(1+S32))*S32 -> 9.9210879e+08 | U32: 6813745669 | V32: 0 | W32: =+V32/(1+$S32)*$S32 -> 0 | X32: =+W32*40% -> 0 | Y32: =+W32*60% -> 0 | Z32: =_xlfn.XLOOKUP(O32,'[4]2DO TRIMESTRE'!$C:$C,'[4]2DO TRIMESTRE'!$I:$I,0,0) -> 0 | AA32: =+Z32/(1+$S32)*$S32 -> 0 | AB32: =+AA32*40% -> 0 | AC32: =+AA32*60% -> 0 | AD32: 0 | AE32: =+AD32/(1+$S32)*$S32 -> 0 | AF32: =+AE32*40% -> 0 | AG32: =+AE32*60% -> 0 | AH32: 0 | AI32: =+AH32/(1+$S32)*$S32 -> 0 | AJ32: =+AI32*40% -> 0 | AK32: =+AI32*60% -> 0 | AL32: 7.3004418e+08 | AM32: =W32+AA32+AE32+AI32 -> 0
A33: 27 | B33: 2021 | C33: FIDUPREVISORA S.A. | D33: 80740-194-FIDUPREVISORA S.A. | E33: Contrato | F33: 44362 | G33: 44848 | H33: =+(G33-F33)/90 -> 5.4 | I33: En Ejecución | J33: Sin Observaciones | K33: OCCIDENTE | L33: Cuenta de ahorros | M33: 230-85893- 8 | N33: 567 44 | O33: 2910906744 | P33: 63454623 | Q33: 0 | R33: =+(P33+Q33) -> 63454623 | S33: 0 | T33: =(R33/(1+S33))*S33 -> 0 | U33: 0 | V33: 0 | W33: =+V33/(1+$S33)*$S33 -> 0 | X33: =+W33*40% -> 0 | Y33: =+W33*60% -> 0 | Z33: =_xlfn.XLOOKUP(O33,'[4]2DO TRIMESTRE'!$C:$C,'[4]2DO TRIMESTRE'!$I:$I,0,0) -> 0 | AA33: =+Z33/(1+$S33)*$S33 -> 0 | AB33: =+AA33*40% -> 0 | AC33: =+AA33*60% -> 0 | AD33: 0 | AE33: =+AD33/(1+$S33)*$S33 -> 0 | AF33: =+AE33*40% -> 0 | AG33: =+AE33*60% -> 0 | AH33: 0 | AI33: =+AH33/(1+$S33)*$S33 -> 0 | AJ33: =+AI33*40% -> 0 | AK33: =+AI33*60% -> 0 | AL33: 0 | AM33: =W33+AA33+AE33+AI33 -> 0 | AN33: Proyecto sin beneficio institucional estipulado en el presupuesto | AO33: Proyecto sin beneficio institucional estipulado en el presupuesto
A34: 28 | B34: 2021 | C34: SECRETARÍA DE EDUCACION DEL DISTRITO - SED | D34: 2609142-SECRETARÍA DE EDUCACION DEL DISTRITO - SED | E34: Contrato | F34: 44379 | G34: 44592 | H34: =+(G34-F34)/90 -> 2.3666667 | I34: Liquidado | J34: Sin Observaciones | K34: OCCIDENTE | L34: Cuenta de ahorros | M34: 230-89470-1 | N34: 83 15 | O34: 2453018315 | P34: =+_xlfn.XLOOKUP(O34,'[3]Benef Primera fecha '!$C:$C,'[3]Benef Primera fecha '!$E:$E,0) -> 1518787008 | Q34: 0 | R34: =+(P34+Q34) -> 1518787008 | S34: 0.12 | T34: =(R34/(1+S34))*S34 -> 1.6272718e+08 | U34: 1248942571 | V34: 0 | W34: =+V34/(1+$S34)*$S34 -> 0 | X34: =+W34*40% -> 0 | Y34: =+W34*60% -> 0 | Z34: =_xlfn.XLOOKUP(O34,'[4]2DO TRIMESTRE'!$C:$C,'[4]2DO TRIMESTRE'!$I:$I,0,0) -> 0 | AA34: =+Z34/(1+$S34)*$S34 -> 0 | AB34: =+AA34*40% -> 0 | AC34: =+AA34*60% -> 0 | AD34: 0 | AE34: =+AD34/(1+$S34)*$S34 -> 0 | AF34: =+AE34*40% -> 0 | AG34: =+AE34*60% -> 0 | AH34: 0 | AI34: =+AH34/(1+$S34)*$S34 -> 0 | AJ34: =+AI34*40% -> 0 | AK34: =+AI34*60% -> 0 | AL34: 149761919 | AM34: =W34+AA34+AE34+AI34 -> 0
A35: 29 | B35: 2021 | C35: FDL BOSA | D35: 278-FDL BOSA | E35: Contrato | F35: 44379 | G35: 44537 | H35: =+(G35-F35)/90 -> 1.7555556 | I35: Liquidado | J35: Sin Observaciones | K35: OCCIDENTE | L35: Cuenta de ahorros | M35: 230-85893- 8 | N35: 567 46 | O35: 2910906746 | P35: =+_xlfn.XLOOKUP(O35,'[3]Benef Primera fecha '!$C:$C,'[3]Benef Primera fecha '!$E:$E,0) -> 450000000 | Q35: 0 | R35: =+(P35+Q35) -> 450000000 | S35: 0.12 | T35: =(R35/(1+S35))*S35 -> 48214286 | U35: 450000000 | V35: 0 | W35: =+V35/(1+$S35)*$S35 -> 0 | X35: =+W35*40% -> 0 | Y35: =+W35*60% -> 0 | Z35: =_xlfn.XLOOKUP(O35,'[4]2DO TRIMESTRE'!$C:$C,'[4]2DO TRIMESTRE'!$I:$I,0,0) -> 0 | AA35: =+Z35/(1+$S35)*$S35 -> 0 | AB35: =+AA35*40% -> 0 | AC35: =+AA35*60% -> 0 | AD35: 0 | AE35: =+AD35/(1+$S35)*$S35 -> 0 | AF35: =+AE35*40% -> 0 | AG35: =+AE35*60% -> 0 | AH35: 0 | AI35: =+AH35/(1+$S35)*$S35 -> 0 | AJ35: =+AI35*40% -> 0 | AK35: =+AI35*60% -> 0 | AL35: 48214286 | AM35: =W35+AA35+AE35+AI35 -> 0
A36: 30 | B36: 2021 | C36: UNIDAD ADMINISTRATIVA ESPECIAL DE CATASTRO DISTRITAL - UAECD | D36: 593-2021-UNIDAD ADMINISTRATIVA ESPECIAL DE CATASTRO DISTRITAL - UAECD | E36: Contrato | F36: 44384 | G36: 44794 | H36: =+(G36-F36)/90 -> 4.5555556 | I36: Liquidado | J36: Sin Observaciones | K36: OCCIDENTE | L36: Cuenta de ahorros | M36: 230-85893- 8 | N36: 567 49 | O36: 2910906749 | P36: =+_xlfn.XLOOKUP(O36,'[3]Benef Primera fecha '!$C:$C,'[3]Benef Primera fecha '!$E:$E,0) -> 87371000 | Q36: 43680000 | R36: =+(P36+Q36) -> 131051000 | S36: 0.12 | T36: =(R36/(1+S36))*S36 -> 14041179 | U36: 131051000 | V36: 0 | W36: =+V36/(1+$S36)*$S36 -> 0 | X36: =+W36*40% -> 0 | Y36: =+W36*60% -> 0 | Z36: =_xlfn.XLOOKUP(O36,'[4]2DO TRIMESTRE'!$C:$C,'[4]2DO TRIMESTRE'!$I:$I,0,0) -> 0 | AA36: =+Z36/(1+$S36)*$S36 -> 0 | AB36: =+AA36*40% -> 0 | AC36: =+AA36*60% -> 0 | AD36: 0 | AE36: =+AD36/(1+$S36)*$S36 -> 0 | AF36: =+AE36*40% -> 0 | AG36: =+AE36*60% -> 0 | AH36: 0 | AI36: =+AH36/(1+$S36)*$S36 -> 0 | AJ36: =+AI36*40% -> 0 | AK36: =+AI36*60% -> 0 | AL36: 14041179 | AM36: =W36+AA36+AE36+AI36 -> 0
A37: 31 | B37: 2021 | C37: UNIVERSIDAD DISTRITAL FRANCISCO JOSÉ DE CALDAS - UD | D37: FAC-MED-8040-UNIVERSIDAD DISTRITAL FRANCISCO JOSÉ DE CALDAS - UD | E37: Curso Propio | F37: 44400 | G37: 44522 | H37: =+(G37-F37)/90 -> 1.3555556 | I37: Liquidado | J37: Sin Observaciones | K37: OCCIDENTE | L37: Cuenta de ahorros | M37: 230-85718-7 | N37: 580 40 | O37: 2910908040 | P37: =+_xlfn.XLOOKUP(O37,'[3]Benef Primera fecha '!$C:$C,'[3]Benef Primera fecha '!$E:$E,0) -> 92700000 | Q37: 0 | R37: =+(P37+Q37) -> 92700000 | S37: 0.12 | T37: =(R37/(1+S37))*S37 -> 9932142.9 | U37: 92700000 | V37: 0 | W37: =+V37/(1+$S37)*$S37 -> 0 | X37: =+W37*40% -> 0 | Y37: =+W37*60% -> 0 | Z37: =_xlfn.XLOOKUP(O37,'[4]2DO TRIMESTRE'!$C:$C,'[4]2DO TRIMESTRE'!$I:$I,0,0) -> 0 | AA37: =+Z37/(1+$S37)*$S37 -> 0 | AB37: =+AA37*40% -> 0 | AC37: =+AA37*60% -> 0 | AD37: 0 | AE37: =+AD37/(1+$S37)*$S37 -> 0 | AF37: =+AE37*40% -> 0 | AG37: =+AE37*60% -> 0 | AH37: 0 | AI37: =+AH37/(1+$S37)*$S37 -> 0 | AJ37: =+AI37*40% -> 0 | AK37: =+AI37*60% -> 0 | AL37: 9932143 | AM37: =W37+AA37+AE37+AI37 -> 0
A38: 32 | B38: 2021 | C38: SERVICIO GEOLOGICO COLOMBIANO | D38: 27-SERVICIO GEOLOGICO COLOMBIANO | E38: Contrato | F38: 44403 | G38: 44681 | H38: =+(G38-F38)/90 -> 3.0888889 | I38: Liquidado | J38: Sin Observaciones | K38: OCCIDENTE | L38: Cuenta de ahorros | M38: 230-85893- 8 | N38: 567 52 | O38: 2910906752 | P38: =+_xlfn.XLOOKUP(O38,'[3]Benef Primera fecha '!$C:$C,'[3]Benef Primera fecha '!$E:$E,0) -> 858400000 | Q38: 0 | R38: =+(P38+Q38) -> 858400000 | S38: 0.12 | T38: =(R38/(1+S38))*S38 -> 91971429 | U38: 858400000 | V38: 0 | W38: =+V38/(1+$S38)*$S38 -> 0 | X38: =+W38*40% -> 0 | Y38: =+W38*60% -> 0 | Z38: =_xlfn.XLOOKUP(O38,'[4]2DO TRIMESTRE'!$C:$C,'[4]2DO TRIMESTRE'!$I:$I,0,0) -> 0 | AA38: =+Z38/(1+$S38)*$S38 -> 0 | AB38: =+AA38*40% -> 0 | AC38: =+AA38*60% -> 0 | AD38: 0 | AE38: =+AD38/(1+$S38)*$S38 -> 0 | AF38: =+AE38*40% -> 0 | AG38: =+AE38*60% -> 0 | AH38: 0 | AI38: =+AH38/(1+$S38)*$S38 -> 0 | AJ38: =+AI38*40% -> 0 | AK38: =+AI38*60% -> 0 | AL38: 91971429 | AM38: =W38+AA38+AE38+AI38 -> 0
A39: 33 | B39: 2021 | C39: MASCULTURAL CORPORACION | D39: CPSENELMARCO216921-1-MASCULTURAL CORPORACION | E39: Contrato | F39: 44403 | G39: 44540 | H39: =+(G39-F39)/90 -> 1.5222222 | I39: Cierre Financiero | J39: Sin Observaciones | K39: OCCIDENTE | L39: Cuenta de ahorros | M39: 230-85718-7 | N39: 567 48 | O39: 2910906748 | P39: =+_xlfn.XLOOKUP(O39,'[3]Benef Primera fecha '!$C:$C,'[3]Benef Primera fecha '!$E:$E,0) -> 116000000 | Q39: 0 | R39: =+(P39+Q39) -> 116000000 | S39: 0.12 | T39: =(R39/(1+S39))*S39 -> 12428571 | U39: 115759880 | V39: 0 | W39: =+V39/(1+$S39)*$S39 -> 0 | X39: =+W39*40% -> 0 | Y39: =+W39*60% -> 0 | Z39: =_xlfn.XLOOKUP(O39,'[4]2DO TRIMESTRE'!$C:$C,'[4]2DO TRIMESTRE'!$I:$I,0,0) -> 0 | AA39: =+Z39/(1+$S39)*$S39 -> 0 | AB39: =+AA39*40% -> 0 | AC39: =+AA39*60% -> 0 | AD39: 0 | AE39: =+AD39/(1+$S39)*$S39 -> 0 | AF39: =+AE39*40% -> 0 | AG39: =+AE39*60% -> 0 | AH39: 0 | AI39: =+AH39/(1+$S39)*$S39 -> 0 | AJ39: =+AI39*40% -> 0 | AK39: =+AI39*60% -> 0 | AL39: 12402844 | AM39: =W39+AA39+AE39+AI39 -> 0
A40: 34 | B40: 2021 | C40: CENTRO NACIONAL DE MEMORIA HISTORICA | D40: 419-CENTRO NACIONAL DE MEMORIA HISTORICA | E40: Contrato | F40: 44407 | G40: 44593 | H40: =+(G40-F40)/90 -> 2.0666667 | I40: Liquidado | J40: Sin Observaciones | K40: OCCIDENTE | L40: Cuenta de ahorros | M40: 230-85893- 8 | N40: 567 53 | O40: 2910906753 | P40: =+_xlfn.XLOOKUP(O40,'[3]Benef Primera fecha '!$C:$C,'[3]Benef Primera fecha '!$E:$E,0) -> 737502714 | Q40: 0 | R40: =+(P40+Q40) -> 737502714 | S40: 0.12 | T40: =(R40/(1+S40))*S40 -> 79018148 | U40: 737502714 | V40: 0 | W40: =+V40/(1+$S40)*$S40 -> 0 | X40: =+W40*40% -> 0 | Y40: =+W40*60% -> 0 | Z40: =_xlfn.XLOOKUP(O40,'[4]2DO TRIMESTRE'!$C:$C,'[4]2DO TRIMESTRE'!$I:$I,0,0) -> 0 | AA40: =+Z40/(1+$S40)*$S40 -> 0 | AB40: =+AA40*40% -> 0 | AC40: =+AA40*60% -> 0 | AD40: 0 | AE40: =+AD40/(1+$S40)*$S40 -> 0 | AF40: =+AE40*40% -> 0 | AG40: =+AE40*60% -> 0 | AH40: 0 | AI40: =+AH40/(1+$S40)*$S40 -> 0 | AJ40: =+AI40*40% -> 0 | AK40: =+AI40*60% -> 0 | AL40: 79018148 | AM40: =W40+AA40+AE40+AI40 -> 0
A41: 35 | B41: 2021 | C41: CAJA DE COMPENSACIÓN FAMILIAR - COMPENSAR | D41: 4500184175-CAJA DE COMPENSACIÓN FAMILIAR - COMPENSAR | E41: Contrato | F41: 44420 | G41: 44511 | H41: =+(G41-F41)/90 -> 1.0111111 | I41: Liquidado | J41: Sin Observaciones | K41: OCCIDENTE | L41: Cuenta de ahorros | M41: 230-85893- 8 | N41: 567 51 | O41: 2910906751 | P41: =+_xlfn.XLOOKUP(O41,'[3]Benef Primera fecha '!$C:$C,'[3]Benef Primera fecha '!$E:$E,0) -> 78690000 | Q41: 0 | R41: =+(P41+Q41) -> 78690000 | S41: 0.12 | T41: =(R41/(1+S41))*S41 -> 8431071.4 | U41: 78690000 | V41: 0 | W41: =+V41/(1+$S41)*$S41 -> 0 | X41: =+W41*40% -> 0 | Y41: =+W41*60% -> 0 | Z41: =_xlfn.XLOOKUP(O41,'[4]2DO TRIMESTRE'!$C:$C,'[4]2DO TRIMESTRE'!$I:$I,0,0) -> 0 | AA41: =+Z41/(1+$S41)*$S41 -> 0 | AB41: =+AA41*40% -> 0 | AC41: =+AA41*60% -> 0 | AD41: 0 | AE41: =+AD41/(1+$S41)*$S41 -> 0 | AF41: =+AE41*40% -> 0 | AG41: =+AE41*60% -> 0 | AH41: 0 | AI41: =+AH41/(1+$S41)*$S41 -> 0 | AJ41: =+AI41*40% -> 0 | AK41: =+AI41*60% -> 0 | AL41: 8431071 | AM41: =W41+AA41+AE41+AI41 -> 0
A42: 36 | B42: 2021 | C42: SECRETARÍA DISTRITAL DE MOVILIDAD | D42: 2248-SECRETARÍA DISTRITAL DE MOVILIDAD | E42: Contrato | F42: 44421 | G42: 44773 | H42: =+(G42-F42)/90 -> 3.9111111 | I42: Terminado | J42: Sin Observaciones | K42: OCCIDENTE | L42: Cuenta de ahorros | M42: 230-85893- 8 | N42: 567 50 | O42: 2910906750 | P42: =+_xlfn.XLOOKUP(O42,'[3]Benef Primera fecha '!$C:$C,'[3]Benef Primera fecha '!$E:$E,0) -> 2243183001 | Q42: 0 | R42: =+(P42+Q42) -> 2243183001 | S42: 0.12 | T42: =(R42/(1+S42))*S42 -> 2.4034104e+08 | U42: 2031147202 | V42: 0 | W42: =+V42/(1+$S42)*$S42 -> 0 | X42: =+W42*40% -> 0 | Y42: =+W42*60% -> 0 | Z42: =_xlfn.XLOOKUP(O42,'[4]2DO TRIMESTRE'!$C:$C,'[4]2DO TRIMESTRE'!$I:$I,0,0) -> 0 | AA42: =+Z42/(1+$S42)*$S42 -> 0 | AB42: =+AA42*40% -> 0 | AC42: =+AA42*60% -> 0 | AD42: 0 | AE42: =+AD42/(1+$S42)*$S42 -> 0 | AF42: =+AE42*40% -> 0 | AG42: =+AE42*60% -> 0 | AH42: 0 | AI42: =+AH42/(1+$S42)*$S42 -> 0 | AJ42: =+AI42*40% -> 0 | AK42: =+AI42*60% -> 0 | AL42: 217757261 | AM42: =W42+AA42+AE42+AI42 -> 0
A43: 37 | B43: 2021 | C43: SECRETARÍA DE EDUCACION DEL DISTRITO - SED | D43: CO1.PCCNTR.2750267-SECRETARÍA DE EDUCACION DEL DISTRITO - SED | E43: Convenio Interadministrativo | F43: 44425 | G43: 44615 | H43: =+(G43-F43)/90 -> 2.1111111 | I43: Liquidado | J43: Sin Observaciones | K43: OCCIDENTE | L43: Cuenta de ahorros | M43: 230-85893- 8 | N43: 83 16 | O43: 2453018316 | P43: =+_xlfn.XLOOKUP(O43,'[3]Benef Primera fecha '!$C:$C,'[3]Benef Primera fecha '!$E:$E,0) -> 950649339 | Q43: 0 | R43: =+(P43+Q43) -> 950649339 | S43: 0.12 | T43: 101855299 | U43: 950649339 | V43: 0 | W43: =+V43/(1+$S43)*$S43 -> 0 | X43: =+W43*40% -> 0 | Y43: =+W43*60% -> 0 | Z43: =_xlfn.XLOOKUP(O43,'[4]2DO TRIMESTRE'!$C:$C,'[4]2DO TRIMESTRE'!$I:$I,0,0) -> 0 | AA43: =+Z43/(1+$S43)*$S43 -> 0 | AB43: =+AA43*40% -> 0 | AC43: =+AA43*60% -> 0 | AD43: 0 | AE43: =+AD43/(1+$S43)*$S43 -> 0 | AF43: =+AE43*40% -> 0 | AG43: =+AE43*60% -> 0 | AH43: 0 | AI43: =+AH43/(1+$S43)*$S43 -> 0 | AJ43: =+AI43*40% -> 0 | AK43: =+AI43*60% -> 0 | AL43: 101855299 | AM43: =W43+AA43+AE43+AI43 -> 0
A44: 38 | B44: 2021 | C44: UNIVERSIDAD DISTRITAL FRANCISCO JOSÉ DE CALDAS - UD | D44: FAC-MED-8044-UNIVERSIDAD DISTRITAL FRANCISCO JOSÉ DE CALDAS - UD | E44: Curso Propio | F44: 44425 | G44: 44516 | H44: =+(G44-F44)/90 -> 1.0111111 | I44: Liquidado | J44: Sin Observaciones | K44: OCCIDENTE | L44: Cuenta de ahorros | M44: 230-85718-7 | N44: 580 44 | O44: 2910908044 | P44: =+_xlfn.XLOOKUP(O44,'[3]Benef Primera fecha '!$C:$C,'[3]Benef Primera fecha '!$E:$E,0) -> 29981358 | Q44: 0 | R44: =+(P44+Q44) -> 29981358 | S44: 0.12 | T44: 3597933 | U44: 29981358 | V44: 0 | W44: =+V44/(1+$S44)*$S44 -> 0 | X44: =+W44*40% -> 0 | Y44: =+W44*60% -> 0 | Z44: =_xlfn.XLOOKUP(O44,'[4]2DO TRIMESTRE'!$C:$C,'[4]2DO TRIMESTRE'!$I:$I,0,0) -> 0 | AA44: =+Z44/(1+$S44)*$S44 -> 0 | AB44: =+AA44*40% -> 0 | AC44: =+AA44*60% -> 0 | AD44: 0 | AE44: =+AD44/(1+$S44)*$S44 -> 0 | AF44: =+AE44*40% -> 0 | AG44: =+AE44*60% -> 0 | AH44: 0 | AI44: =+AH44/(1+$S44)*$S44 -> 0 | AJ44: =+AI44*40% -> 0 | AK44: =+AI44*60% -> 0 | AL44: 3597933 | AM44: =W44+AA44+AE44+AI44 -> 0
A45: 39 | B45: 2021 | C45: FDL SUBA | D45: FDLSCI-372-2021-FDL SUBA | E45: Convenio Interadministrativo | F45: 44426 | G45: 44635 | H45: =+(G45-F45)/90 -> 2.3222222 | I45: Cierre Financiero | J45: Sin Observaciones | K45: OCCIDENTE | L45: Cuenta de ahorros | M45: 230-85893- 8 | N45: 83 18 | O45: 2453018318 | P45: =+_xlfn.XLOOKUP(O45,'[3]Benef Primera fecha '!$C:$C,'[3]Benef Primera fecha '!$E:$E,0) -> 595495040 | Q45: 0 | R45: =+(P45+Q45) -> 595495040 | S45: 0.12 | T45: =(R45/(1+S45))*S45 -> 63803040 | U45: 485900000 | V45: 0 | W45: =+V45/(1+$S45)*$S45 -> 0 | X45: =+W45*40% -> 0 | Y45: =+W45*60% -> 0 | Z45: =_xlfn.XLOOKUP(O45,'[4]2DO TRIMESTRE'!$C:$C,'[4]2DO TRIMESTRE'!$I:$I,0,0) -> 0 | AA45: =+Z45/(1+$S45)*$S45 -> 0 | AB45: =+AA45*40% -> 0 | AC45: =+AA45*60% -> 0 | AD45: 0 | AE45: =+AD45/(1+$S45)*$S45 -> 0 | AF45: =+AE45*40% -> 0 | AG45: =+AE45*60% -> 0 | AH45: 0 | AI45: =+AH45/(1+$S45)*$S45 -> 0 | AJ45: =+AI45*40% -> 0 | AK45: =+AI45*60% -> 0 | AL45: 52060714 | AM45: =W45+AA45+AE45+AI45 -> 0
A46: 40 | B46: 2021 | C46: INSTITUTO DISTRITAL DE GESTIÓN DE RIESGOS Y CAMBIO CLIMATICO - IDIGER - FONDIGER | D46: IDIGER-199-2021-INSTITUTO DISTRITAL DE GESTIÓN DE RIESGOS Y CAMBIO CLIMATICO - IDIGER - FONDIGER | E46: Contrato | F46: 44427 | G46: 44563 | H46: =+(G46-F46)/90 -> 1.5111111 | I46: En Ejecución | J46: Sin Observaciones | K46: OCCIDENTE | L46: Cuenta de ahorros | M46: 230-85893- 8 | N46: 567 55 | O46: 2910906755 | P46: =+_xlfn.XLOOKUP(O46,'[3]Benef Primera fecha '!$C:$C,'[3]Benef Primera fecha '!$E:$E,0) -> 59999936 | Q46: 64 | R46: =+(P46+Q46) -> 60000000 | S46: 0.12000013 | T46: =(R46/(1+S46))*S46 -> 6428577.9 | U46: 59999936 | V46: 0 | W46: =+V46/(1+$S46)*$S46 -> 0 | X46: =+W46*40% -> 0 | Y46: =+W46*60% -> 0 | Z46: =_xlfn.XLOOKUP(O46,'[4]2DO TRIMESTRE'!$C:$C,'[4]2DO TRIMESTRE'!$I:$I,0,0) -> 0 | AA46: =+Z46/(1+$S46)*$S46 -> 0 | AB46: =+AA46*40% -> 0 | AC46: =+AA46*60% -> 0 | AD46: 0 | AE46: =+AD46/(1+$S46)*$S46 -> 0 | AF46: =+AE46*40% -> 0 | AG46: =+AE46*60% -> 0 | AH46: 0 | AI46: =+AH46/(1+$S46)*$S46 -> 0 | AJ46: =+AI46*40% -> 0 | AK46: =+AI46*60% -> 0 | AL46: 6428571 | AM46: =W46+AA46+AE46+AI46 -> 0
A47: 41 | B47: 2021 | C47: UNIDAD ADMINISTRATIVA ESPECIAL MIGRACIÓN COLOMBIA | D47: 105-UNIDAD ADMINISTRATIVA ESPECIAL MIGRACIÓN COLOMBIA | E47: Contrato | F47: 44428 | G47: 44561 | H47: =+(G47-F47)/90 -> 1.4777778 | I47: Cierre Financiero | J47: Sin Observaciones | K47: OCCIDENTE | L47: Cuenta de ahorros | M47: 230-85893- 8 | N47: 567 54 | O47: 2910906754 | P47: =+_xlfn.XLOOKUP(O47,'[3]Benef Primera fecha '!$C:$C,'[3]Benef Primera fecha '!$E:$E,0) -> 72667000 | Q47: 0 | R47: =+(P47+Q47) -> 72667000 | S47: 0.12 | T47: 7786821 | U47: 72667000 | V47: 0 | W47: =+V47/(1+$S47)*$S47 -> 0 | X47: =+W47*40% -> 0 | Y47: =+W47*60% -> 0 | Z47: =_xlfn.XLOOKUP(O47,'[4]2DO TRIMESTRE'!$C:$C,'[4]2DO TRIMESTRE'!$I:$I,0,0) -> 0 | AA47: =+Z47/(1+$S47)*$S47 -> 0 | AB47: =+AA47*40% -> 0 | AC47: =+AA47*60% -> 0 | AD47: 0 | AE47: =+AD47/(1+$S47)*$S47 -> 0 | AF47: =+AE47*40% -> 0 | AG47: =+AE47*60% -> 0 | AH47: 0 | AI47: =+AH47/(1+$S47)*$S47 -> 0 | AJ47: =+AI47*40% -> 0 | AK47: =+AI47*60% -> 0 | AL47: 7786821 | AM47: =W47+AA47+AE47+AI47 -> 0
A48: 42 | B48: 2021 | C48: INSTITUTO PARA LA INVESTIGACIÓN EDUCATIVA Y EL DESARROLLO PEDAGÓGICO - IDEP | D48: 79-INSTITUTO PARA LA INVESTIGACIÓN EDUCATIVA Y EL DESARROLLO PEDAGÓGICO - IDEP | E48: Convenio Interadministrativo | F48: 44431 | G48: 44553 | H48: =+(G48-F48)/90 -> 1.3555556 | I48: Cierre Financiero | J48: Sin Observaciones | K48: OCCIDENTE | L48: Cuenta de ahorros | M48: 230-85893- 8 | N48: 83 17 | O48: 2453018317 | P48: =+_xlfn.XLOOKUP(O48,'[3]Benef Primera fecha '!$C:$C,'[3]Benef Primera fecha '!$E:$E,0) -> 92000000 | Q48: 0 | R48: =+(P48+Q48) -> 92000000 | S48: 0.12 | T48: 9857160 | U48: 92000000 | V48: 0 | W48: =+V48/(1+$S48)*$S48 -> 0 | X48: =+W48*40% -> 0 | Y48: =+W48*60% -> 0 | Z48: =_xlfn.XLOOKUP(O48,'[4]2DO TRIMESTRE'!$C:$C,'[4]2DO TRIMESTRE'!$I:$I,0,0) -> 0 | AA48: =+Z48/(1+$S48)*$S48 -> 0 | AB48: =+AA48*40% -> 0 | AC48: =+AA48*60% -> 0 | AD48: 0 | AE48: =+AD48/(1+$S48)*$S48 -> 0 | AF48: =+AE48*40% -> 0 | AG48: =+AE48*60% -> 0 | AH48: 0 | AI48: =+AH48/(1+$S48)*$S48 -> 0 | AJ48: =+AI48*40% -> 0 | AK48: =+AI48*60% -> 0 | AL48: 9857160 | AM48: =W48+AA48+AE48+AI48 -> 0
A49: 43 | B49: 2021 | C49: CONCEJO MUNICIPAL DE VILLAVICENCIO | D49: 36-CONCEJO MUNICIPAL DE VILLAVICENCIO | E49: Contrato | F49: 44432 | G49: 44647 | H49: =+(G49-F49)/90 -> 2.3888889 | I49: Liquidado | J49: Sin Observaciones | K49: OCCIDENTE | L49: Cuenta de ahorros | M49: 230-85893- 8 | N49: 567 60 | O49: 2910906760 | P49: =+_xlfn.XLOOKUP(O49,'[3]Benef Primera fecha '!$C:$C,'[3]Benef Primera fecha '!$E:$E,0) -> 94999200 | Q49: 0 | R49: =+(P49+Q49) -> 94999200 | S49: 0.12 | T49: =(R49/(1+S49))*S49 -> 10178486 | U49: 94999200 | V49: 0 | W49: =+V49/(1+$S49)*$S49 -> 0 | X49: =+W49*40% -> 0 | Y49: =+W49*60% -> 0 | Z49: =_xlfn.XLOOKUP(O49,'[4]2DO TRIMESTRE'!$C:$C,'[4]2DO TRIMESTRE'!$I:$I,0,0) -> 0 | AA49: =+Z49/(1+$S49)*$S49 -> 0 | AB49: =+AA49*40% -> 0 | AC49: =+AA49*60% -> 0 | AD49: 0 | AE49: =+AD49/(1+$S49)*$S49 -> 0 | AF49: =+AE49*40% -> 0 | AG49: =+AE49*60% -> 0 | AH49: 0 | AI49: =+AH49/(1+$S49)*$S49 -> 0 | AJ49: =+AI49*40% -> 0 | AK49: =+AI49*60% -> 0 | AL49: 10178486 | AM49: =W49+AA49+AE49+AI49 -> 0
A50: 44 | B50: 2021 | C50: AVANCIENCIA - ASOCIACIÓN COLOMBIANA PARA EL AVANCE DE LA CIENCIA | D50: CDP2671 – 2021-AVANCIENCIA - ASOCIACIÓN COLOMBIANA PARA EL AVANCE DE LA CIENCIA | E50: Contrato | F50: 44433 | G50: 44676 | H50: =+(G50-F50)/90 -> 2.7 | I50: Cierre Financiero | J50: Sin Observaciones | K50: OCCIDENTE | L50: Cuenta de ahorros | M50: 230-85893- 8 | N50: 83 19 | O50: 2453018319 | P50: =+_xlfn.XLOOKUP(O50,'[3]Benef Primera fecha '!$C:$C,'[3]Benef Primera fecha '!$E:$E,0) -> 128800000 | Q50: 0 | R50: =+(P50+Q50) -> 128800000 | S50: 0.12 | T50: 13815914 | U50: 128800000 | V50: 0 | W50: =+V50/(1+$S50)*$S50 -> 0 | X50: =+W50*40% -> 0 | Y50: =+W50*60% -> 0 | Z50: =_xlfn.XLOOKUP(O50,'[4]2DO TRIMESTRE'!$C:$C,'[4]2DO TRIMESTRE'!$I:$I,0,0) -> 0 | AA50: =+Z50/(1+$S50)*$S50 -> 0 | AB50: =+AA50*40% -> 0 | AC50: =+AA50*60% -> 0 | AD50: 0 | AE50: =+AD50/(1+$S50)*$S50 -> 0 | AF50: =+AE50*40% -> 0 | AG50: =+AE50*60% -> 0 | AH50: 0 | AI50: =+AH50/(1+$S50)*$S50 -> 0 | AJ50: =+AI50*40% -> 0 | AK50: =+AI50*60% -> 0 | AL50: 13815914 | AM50: =W50+AA50+AE50+AI50 -> 0
A51: 45 | B51: 2021 | C51: ASAMBLEA DEPARTAMENTAL CASANARE | D51: 36-CONCEJO MUNICIPAL DE VILLAVICENCIO | E51: Contrato | F51: 44438 | G51: 44536 | H51: =+(G51-F51)/90 -> 1.0888889 | I51: Liquidado | J51: Sin Observaciones | K51: OCCIDENTE | L51: Cuenta de ahorros | M51: 230-85893- 8 | N51: 567 60 | O51: 2910906760 | P51: =+_xlfn.XLOOKUP(O51,'[3]Benef Primera fecha '!$C:$C,'[3]Benef Primera fecha '!$E:$E,0) -> 94999200 | Q51: 0 | R51: =+(P51+Q51) -> 94999200 | S51: 0.12 | T51: =(R51/(1+S51))*S51 -> 10178486 | U51: 94999200 | V51: 0 | W51: =+V51/(1+$S51)*$S51 -> 0 | X51: =+W51*40% -> 0 | Y51: =+W51*60% -> 0 | Z51: =_xlfn.XLOOKUP(O51,'[4]2DO TRIMESTRE'!$C:$C,'[4]2DO TRIMESTRE'!$I:$I,0,0) -> 0 | AA51: =+Z51/(1+$S51)*$S51 -> 0 | AB51: =+AA51*40% -> 0 | AC51: =+AA51*60% -> 0 | AD51: 0 | AE51: =+AD51/(1+$S51)*$S51 -> 0 | AF51: =+AE51*40% -> 0 | AG51: =+AE51*60% -> 0 | AH51: 0 | AI51: =+AH51/(1+$S51)*$S51 -> 0 | AJ51: =+AI51*40% -> 0 | AK51: =+AI51*60% -> 0 | AL51: 10178486 | AM51: =W51+AA51+AE51+AI51 -> 0
A52: 46 | B52: 2021 | C52: ASAMBLEA DEPARTAMENTAL SANTANDER | D52: CD-CI- 117- 2021-ASAMBLEA DEPARTAMENTAL SANTANDER | E52: Contrato | F52: 44441 | G52: 44531 | H52: =+(G52-F52)/90 -> 1 | I52: Liquidado | J52: Sin Observaciones | K52: OCCIDENTE | L52: Cuenta de ahorros | M52: 230-85893- 8 | N52: 567 59 | O52: 2910906759 | P52: =+_xlfn.XLOOKUP(O52,'[3]Benef Primera fecha '!$C:$C,'[3]Benef Primera fecha '!$E:$E,0) -> 70000000 | Q52: 0 | R52: =+(P52+Q52) -> 70000000 | S52: 0.12 | T52: =(R52/(1+S52))*S52 -> 7500000 | U52: 70000000 | V52: 0 | W52: =+V52/(1+$S52)*$S52 -> 0 | X52: =+W52*40% -> 0 | Y52: =+W52*60% -> 0 | Z52: =_xlfn.XLOOKUP(O52,'[4]2DO TRIMESTRE'!$C:$C,'[4]2DO TRIMESTRE'!$I:$I,0,0) -> 0 | AA52: =+Z52/(1+$S52)*$S52 -> 0 | AB52: =+AA52*40% -> 0 | AC52: =+AA52*60% -> 0 | AD52: 0 | AE52: =+AD52/(1+$S52)*$S52 -> 0 | AF52: =+AE52*40% -> 0 | AG52: =+AE52*60% -> 0 | AH52: 0 | AI52: =+AH52/(1+$S52)*$S52 -> 0 | AJ52: =+AI52*40% -> 0 | AK52: =+AI52*60% -> 0 | AL52: 7500000 | AM52: =W52+AA52+AE52+AI52 -> 0
A53: 47 | B53: 2021 | C53: UNIVERSIDAD DISTRITAL FRANCISCO JOSÉ DE CALDAS - UD | D53: FAC - ING - 8045-UNIVERSIDAD DISTRITAL FRANCISCO JOSÉ DE CALDAS - UD | E53: Curso Propio | F53: 44448 | G53: 44477 | H53: =+(G53-F53)/90 -> 0.32222222 | I53: Liquidado | J53: Sin Observaciones | K53: OCCIDENTE | L53: Cuenta de ahorros | M53: 230-85718-7 | N53: 580 45 | O53: 2910908045 | P53: =+_xlfn.XLOOKUP(O53,'[3]Benef Primera fecha '!$C:$C,'[3]Benef Primera fecha '!$E:$E,0) -> 8285436 | Q53: 0 | R53: =+(P53+Q53) -> 8285436 | S53: 0.12 | T53: =(R53/(1+S53))*S53 -> 887725.29 | U53: 8285436 | V53: 0 | W53: =+V53/(1+$S53)*$S53 -> 0 | X53: =+W53*40% -> 0 | Y53: =+W53*60% -> 0 | Z53: =_xlfn.XLOOKUP(O53,'[4]2DO TRIMESTRE'!$C:$C,'[4]2DO TRIMESTRE'!$I:$I,0,0) -> 0 | AA53: =+Z53/(1+$S53)*$S53 -> 0 | AB53: =+AA53*40% -> 0 | AC53: =+AA53*60% -> 0 | AD53: 0 | AE53: =+AD53/(1+$S53)*$S53 -> 0 | AF53: =+AE53*40% -> 0 | AG53: =+AE53*60% -> 0 | AH53: 0 | AI53: =+AH53/(1+$S53)*$S53 -> 0 | AJ53: =+AI53*40% -> 0 | AK53: =+AI53*60% -> 0 | AL53: 887725 | AM53: =W53+AA53+AE53+AI53 -> 0
A54: 48 | B54: 2021 | C54: INSTITUTO DE HIDROLOGIA, METEREOLOGIA Y ESTUDIOS AMBIENTALES - IDEAM | D54: 426-INSTITUTO DE HIDROLOGIA, METEREOLOGIA Y ESTUDIOS AMBIENTALES - IDEAM | E54: Contrato | F54: 44449 | G54: 44545 | H54: =+(G54-F54)/90 -> 1.0666667 | I54: Terminado | J54: Sin Observaciones | K54: OCCIDENTE | L54: Cuenta de ahorros | M54: 230-85893- 8 | N54: 567 63 | O54: 2910906763 | P54: =+_xlfn.XLOOKUP(O54,'[3]Benef Primera fecha '!$C:$C,'[3]Benef Primera fecha '!$E:$E,0) -> 100000000 | Q54: 0 | R54: =+(P54+Q54) -> 100000000 | S54: 0.12 | T54: =(R54/(1+S54))*S54 -> 10714286 | U54: 100000000 | V54: 0 | W54: =+V54/(1+$S54)*$S54 -> 0 | X54: =+W54*40% -> 0 | Y54: =+W54*60% -> 0 | Z54: =_xlfn.XLOOKUP(O54,'[4]2DO TRIMESTRE'!$C:$C,'[4]2DO TRIMESTRE'!$I:$I,0,0) -> 0 | AA54: =+Z54/(1+$S54)*$S54 -> 0 | AB54: =+AA54*40% -> 0 | AC54: =+AA54*60% -> 0 | AD54: 0 | AE54: =+AD54/(1+$S54)*$S54 -> 0 | AF54: =+AE54*40% -> 0 | AG54: =+AE54*60% -> 0 | AH54: 0 | AI54: =+AH54/(1+$S54)*$S54 -> 0 | AJ54: =+AI54*40% -> 0 | AK54: =+AI54*60% -> 0 | AL54: 10714286 | AM54: =W54+AA54+AE54+AI54 -> 0
A55: 49 | B55: 2021 | C55: FDL RAFAEL URIBE URIBE | D55: CIA-253-2021-FDL RAFAEL URIBE URIBE | E55: Contrato | F55: 44449 | G55: 44883 | H55: =+(G55-F55)/90 -> 4.8222222 | I55: Liquidado | J55: Sin Observaciones | K55: OCCIDENTE | L55: Cuenta de ahorros | M55: 230-85893- 8 | N55: 567 58 | O55: 2910906758 | P55: =+_xlfn.XLOOKUP(O55,'[3]Benef Primera fecha '!$C:$C,'[3]Benef Primera fecha '!$E:$E,0) -> 660783000 | Q55: 0 | R55: =+(P55+Q55) -> 660783000 | S55: 0.12000007 | T55: =(R55/(1+S55))*S55 -> 70798215 | U55: 660783000 | V55: 0 | W55: =+V55/(1+$S55)*$S55 -> 0 | X55: =+W55*40% -> 0 | Y55: =+W55*60% -> 0 | Z55: =_xlfn.XLOOKUP(O55,'[4]2DO TRIMESTRE'!$C:$C,'[4]2DO TRIMESTRE'!$I:$I,0,0) -> 0 | AA55: =+Z55/(1+$S55)*$S55 -> 0 | AB55: =+AA55*40% -> 0 | AC55: =+AA55*60% -> 0 | AD55: 0 | AE55: =+AD55/(1+$S55)*$S55 -> 0 | AF55: =+AE55*40% -> 0 | AG55: =+AE55*60% -> 0 | AH55: 0 | AI55: =+AH55/(1+$S55)*$S55 -> 0 | AJ55: =+AI55*40% -> 0 | AK55: =+AI55*60% -> 0 | AL55: 70798215 | AM55: =W55+AA55+AE55+AI55 -> 0
A56: 50 | B56: 2021 | C56: UNIDAD ADMINISTRATIVA ESPECIAL DE SERVICIOS PÚBLICOS - UAESP | D56: UAESP-544-2021-UNIDAD ADMINISTRATIVA ESPECIAL DE SERVICIOS PÚBLICOS - UAESP | E56: Convenio Interadministrativo | F56: 44449 | G56: 44633 | H56: =+(G56-F56)/90 -> 2.0444444 | I56: Liquidado | J56: Sin Observaciones | K56: OCCIDENTE | L56: Cuenta de ahorros | M56: 230-85893- 8 | N56: 83 21 | O56: 2453018321 | P56: =+_xlfn.XLOOKUP(O56,'[3]Benef Primera fecha '!$C:$C,'[3]Benef Primera fecha '!$E:$E,0) -> 439581220 | Q56: 0 | R56: =+(P56+Q56) -> 439581220 | S56: 0.12 | T56: =(R56/(1+S56))*S56 -> 47097988 | U56: 391529566 | V56: 0 | W56: =+V56/(1+$S56)*$S56 -> 0 | X56: =+W56*40% -> 0 | Y56: =+W56*60% -> 0 | Z56: =_xlfn.XLOOKUP(O56,'[4]2DO TRIMESTRE'!$C:$C,'[4]2DO TRIMESTRE'!$I:$I,0,0) -> 0 | AA56: =+Z56/(1+$S56)*$S56 -> 0 | AB56: =+AA56*40% -> 0 | AC56: =+AA56*60% -> 0 | AD56: 0 | AE56: =+AD56/(1+$S56)*$S56 -> 0 | AF56: =+AE56*40% -> 0 | AG56: =+AE56*60% -> 0 | AH56: 0 | AI56: =+AH56/(1+$S56)*$S56 -> 0 | AJ56: =+AI56*40% -> 0 | AK56: =+AI56*60% -> 0 | AL56: 40539368 | AM56: =W56+AA56+AE56+AI56 -> 0
A57: 51 | B57: 2021 | C57: ASAMBLEA DEPARTAMENTAL DE BOYACA | D57: 36-CONCEJO MUNICIPAL DE VILLAVICENCIO | E57: Contrato | F57: 44453 | G57: 44587 | H57: =+(G57-F57)/90 -> 1.4888889 | I57: Liquidado | J57: Sin Observaciones | K57: OCCIDENTE | L57: Cuenta de ahorros | M57: 230-85893- 8 | N57: 567 60 | O57: 2910906760 | P57: =+_xlfn.XLOOKUP(O57,'[3]Benef Primera fecha '!$C:$C,'[3]Benef Primera fecha '!$E:$E,0) -> 94999200 | Q57: 0 | R57: =+(P57+Q57) -> 94999200 | S57: 0.12 | T57: =(R57/(1+S57))*S57 -> 10178486 | U57: 94999200 | V57: 0 | W57: =+V57/(1+$S57)*$S57 -> 0 | X57: =+W57*40% -> 0 | Y57: =+W57*60% -> 0 | Z57: =_xlfn.XLOOKUP(O57,'[4]2DO TRIMESTRE'!$C:$C,'[4]2DO TRIMESTRE'!$I:$I,0,0) -> 0 | AA57: =+Z57/(1+$S57)*$S57 -> 0 | AB57: =+AA57*40% -> 0 | AC57: =+AA57*60% -> 0 | AD57: 0 | AE57: =+AD57/(1+$S57)*$S57 -> 0 | AF57: =+AE57*40% -> 0 | AG57: =+AE57*60% -> 0 | AH57: 0 | AI57: =+AH57/(1+$S57)*$S57 -> 0 | AJ57: =+AI57*40% -> 0 | AK57: =+AI57*60% -> 0 | AL57: 10178486 | AM57: =W57+AA57+AE57+AI57 -> 0
A58: 52 | B58: 2021 | C58: UNIVERSIDAD DISTRITAL FRANCISCO JOSÉ DE CALDAS - UD | D58: FAC-TECNO-8048-UNIVERSIDAD DISTRITAL FRANCISCO JOSÉ DE CALDAS - UD | E58: Curso Propio | F58: 44453 | G58: 44574 | H58: =+(G58-F58)/90 -> 1.3444444 | I58: Liquidado | J58: Sin Observaciones | K58: OCCIDENTE | L58: Cuenta de ahorros | M58: 230-85718-7 | N58: 580 48 | O58: 2910908048 | P58: 11685000 | Q58: 0 | R58: =+(P58+Q58) -> 11685000 | S58: 0 | T58: =(R58/(1+S58))*S58 -> 0 | U58: 0 | V58: 0 | W58: =+V58/(1+$S58)*$S58 -> 0 | X58: =+W58*40% -> 0 | Y58: =+W58*60% -> 0 | Z58: =_xlfn.XLOOKUP(O58,'[4]2DO TRIMESTRE'!$C:$C,'[4]2DO TRIMESTRE'!$I:$I,0,0) -> 0 | AA58: =+Z58/(1+$S58)*$S58 -> 0 | AB58: =+AA58*40% -> 0 | AC58: =+AA58*60% -> 0 | AD58: 0 | AE58: =+AD58/(1+$S58)*$S58 -> 0 | AF58: =+AE58*40% -> 0 | AG58: =+AE58*60% -> 0 | AH58: 0 | AI58: =+AH58/(1+$S58)*$S58 -> 0 | AJ58: =+AI58*40% -> 0 | AK58: =+AI58*60% -> 0 | AL58: 0 | AM58: =W58+AA58+AE58+AI58 -> 0
A59: 53 | B59: 2021 | C59: UNIDAD ADMINISTRATIVA ESPECIAL DE SERVICIOS PÚBLICOS - UAESP | D59: UAESP-501-UNIDAD ADMINISTRATIVA ESPECIAL DE SERVICIOS PÚBLICOS - UAESP | E59: Contrato | F59: 44454 | G59: 45150 | H59: =+(G59-F59)/90 -> 7.7333333 | I59: En Ejecución | J59: Sin Observaciones | K59: OCCIDENTE | L59: Cuenta de ahorros | M59: 230-85893- 8 | N59: 567 56 | O59: 2910906756 | P59: =+_xlfn.XLOOKUP(O59,'[3]Benef Primera fecha '!$C:$C,'[3]Benef Primera fecha '!$E:$E,0) -> 2243355967 | Q59: 601517120 | R59: =+(P59+Q59) -> 2844873087 | S59: 0.12 | T59: =(R59/(1+S59))*S59 -> 3.0480783e+08 | U59: 1874978920 | V59: 0 | W59: =+V59/(1+$S59)*$S59 -> 0 | X59: =+W59*40% -> 0 | Y59: =+W59*60% -> 0 | Z59: =_xlfn.XLOOKUP(O59,'[4]2DO TRIMESTRE'!$C:$C,'[4]2DO TRIMESTRE'!$I:$I,0,0) -> 0 | AA59: =+Z59/(1+$S59)*$S59 -> 0 | AB59: =+AA59*40% -> 0 | AC59: =+AA59*60% -> 0 | AD59: 0 | AE59: =+AD59/(1+$S59)*$S59 -> 0 | AF59: =+AE59*40% -> 0 | AG59: =+AE59*60% -> 0 | AH59: 0 | AI59: =+AH59/(1+$S59)*$S59 -> 0 | AJ59: =+AI59*40% -> 0 | AK59: =+AI59*60% -> 0 | AL59: 2.008906e+08 | AM59: =W59+AA59+AE59+AI59 -> 0
A60: 54 | B60: 2021 | C60: SECRETARÍA DE EDUCACION DEL DISTRITO - SED | D60: 2862289-SECRETARÍA DE EDUCACION DEL DISTRITO - SED | E60: Convenio Interadministrativo | F60: 44459 | G60: 44557 | H60: =+(G60-F60)/90 -> 1.0888889 | I60: Terminado | J60: Sin Observaciones | K60: OCCIDENTE | L60: Cuenta de ahorros | M60: 230-89524-5 | N60: 83 20 | O60: 2453018320 | P60: 440000000 | Q60: 0 | R60: =+(P60+Q60) -> 440000000 | S60: 0 | T60: =(R60/(1+S60))*S60 -> 0 | U60: 0 | V60: 0 | W60: =+V60/(1+$S60)*$S60 -> 0 | X60: =+W60*40% -> 0 | Y60: =+W60*60% -> 0 | Z60: =_xlfn.XLOOKUP(O60,'[4]2DO TRIMESTRE'!$C:$C,'[4]2DO TRIMESTRE'!$I:$I,0,0) -> 0 | AA60: =+Z60/(1+$S60)*$S60 -> 0 | AB60: =+AA60*40% -> 0 | AC60: =+AA60*60% -> 0 | AD60: 0 | AE60: =+AD60/(1+$S60)*$S60 -> 0 | AF60: =+AE60*40% -> 0 | AG60: =+AE60*60% -> 0 | AH60: 0 | AI60: =+AH60/(1+$S60)*$S60 -> 0 | AJ60: =+AI60*40% -> 0 | AK60: =+AI60*60% -> 0 | AL60: 0 | AM60: =W60+AA60+AE60+AI60 -> 0 | AN60: Proyecto sin beneficio institucional estipulado en el presupuesto | AO60: Proyecto sin beneficio institucional estipulado en el presupuesto
A61: 55 | B61: 2022 | C61: UNIVERSIDAD DISTRITAL FRANCISCO JOSÉ DE CALDAS - UD | D61: FAC-ASAB-8062-UNIVERSIDAD DISTRITAL FRANCISCO JOSÉ DE CALDAS - UD | E61: Curso Propio | F61: 44460 | G61: 45519 | H61: =+(G61-F61)/90 -> 11.766667 | I61: Liquidado | J61: Sin Observaciones | K61: OCCIDENTE | L61: Cuenta de ahorros | M61: 230-85718-7 | N61: 580 62 | O61: 2910908062 | P61: =+_xlfn.XLOOKUP(O61,'[3]Benef Primera fecha '!$C:$C,'[3]Benef Primera fecha '!$E:$E,0) -> 118762000 | Q61: 0 | R61: =+(P61+Q61) -> 118762000 | S61: 0.12 | T61: =(R61/(1+S61))*S61 -> 12724500 | U61: 118762000 | V61: 0 | W61: =+V61/(1+$S61)*$S61 -> 0 | X61: =+W61*40% -> 0 | Y61: =+W61*60% -> 0 | Z61: =_xlfn.XLOOKUP(O61,'[4]2DO TRIMESTRE'!$C:$C,'[4]2DO TRIMESTRE'!$I:$I,0,0) -> 0 | AA61: =+Z61/(1+$S61)*$S61 -> 0 | AB61: =+AA61*40% -> 0 | AC61: =+AA61*60% -> 0 | AD61: 0 | AE61: =+AD61/(1+$S61)*$S61 -> 0 | AF61: =+AE61*40% -> 0 | AG61: =+AE61*60% -> 0 | AH61: 0 | AI61: =+AH61/(1+$S61)*$S61 -> 0 | AJ61: =+AI61*40% -> 0 | AK61: =+AI61*60% -> 0 | AL61: 12724500 | AM61: =W61+AA61+AE61+AI61 -> 0
A62: 56 | B62: 2021 | C62: AJG PODAS Y JARDINES SAS | D62: 01-PODAS Y JARDINES SAS | E62: Contrato | F62: 44461 | G62: 44521 | H62: =+(G62-F62)/90 -> 0.66666667 | I62: En Ejecución | J62: Sin Observaciones | K62: OCCIDENTE | L62: Cuenta de ahorros | M62: 230-85893- 8 | N62: 567 62 | O62: 2910906762 | P62: =+_xlfn.XLOOKUP(O62,'[3]Benef Primera fecha '!$C:$C,'[3]Benef Primera fecha '!$E:$E,0) -> 20000000 | Q62: 0 | R62: =+(P62+Q62) -> 20000000 | S62: 0.12 | T62: 2143000 | U62: 20000000 | V62: 0 | W62: =+V62/(1+$S62)*$S62 -> 0 | X62: =+W62*40% -> 0 | Y62: =+W62*60% -> 0 | Z62: =_xlfn.XLOOKUP(O62,'[4]2DO TRIMESTRE'!$C:$C,'[4]2DO TRIMESTRE'!$I:$I,0,0) -> 0 | AA62: =+Z62/(1+$S62)*$S62 -> 0 | AB62: =+AA62*40% -> 0 | AC62: =+AA62*60% -> 0 | AD62: 0 | AE62: =+AD62/(1+$S62)*$S62 -> 0 | AF62: =+AE62*40% -> 0 | AG62: =+AE62*60% -> 0 | AH62: 0 | AI62: =+AH62/(1+$S62)*$S62 -> 0 | AJ62: =+AI62*40% -> 0 | AK62: =+AI62*60% -> 0 | AL62: 2143000 | AM62: =W62+AA62+AE62+AI62 -> 0
A63: 57 | B63: 2021 | C63: FDL USAQUÉN | D63: FDLUSA-CI-365-2021-FDL USAQUÉN | E63: Contrato | F63: 44461 | G63: 44724 | H63: =+(G63-F63)/90 -> 2.9222222 | I63: Liquidado | J63: Sin Observaciones | K63: OCCIDENTE | L63: Cuenta de ahorros | M63: 230-85893- 8 | N63: 567 64 | O63: 2910906764 | P63: =+_xlfn.XLOOKUP(O63,'[3]Benef Primera fecha '!$C:$C,'[3]Benef Primera fecha '!$E:$E,0) -> 114000000 | Q63: 0 | R63: =+(P63+Q63) -> 114000000 | S63: 0.12 | T63: =(R63/(1+S63))*S63 -> 12214286 | U63: 114000000 | V63: 0 | W63: =+V63/(1+$S63)*$S63 -> 0 | X63: =+W63*40% -> 0 | Y63: =+W63*60% -> 0 | Z63: =_xlfn.XLOOKUP(O63,'[4]2DO TRIMESTRE'!$C:$C,'[4]2DO TRIMESTRE'!$I:$I,0,0) -> 0 | AA63: =+Z63/(1+$S63)*$S63 -> 0 | AB63: =+AA63*40% -> 0 | AC63: =+AA63*60% -> 0 | AD63: 0 | AE63: =+AD63/(1+$S63)*$S63 -> 0 | AF63: =+AE63*40% -> 0 | AG63: =+AE63*60% -> 0 | AH63: 0 | AI63: =+AH63/(1+$S63)*$S63 -> 0 | AJ63: =+AI63*40% -> 0 | AK63: =+AI63*60% -> 0 | AL63: 9762857 | AM63: =W63+AA63+AE63+AI63 -> 0
A64: 58 | B64: 2021 | C64: MINISTERIO DEL INTERIOR Y JUSTICIA | D64: No. 1610 DE 2021-MINISTERIO DEL INTERIOR Y JUSTICIA | E64: Contrato | F64: 44462 | G64: 44560 | H64: =+(G64-F64)/90 -> 1.0888889 | I64: Liquidado | J64: Sin Observaciones | K64: OCCIDENTE | L64: Cuenta de ahorros | M64: 230-85893- 8 | N64: 567 65 | O64: 2910906765 | P64: =+_xlfn.XLOOKUP(O64,'[3]Benef Primera fecha '!$C:$C,'[3]Benef Primera fecha '!$E:$E,0) -> 81450000 | Q64: 0 | R64: =+(P64+Q64) -> 81450000 | S64: 0.12 | T64: =(R64/(1+S64))*S64 -> 8726785.7 | U64: 81450000 | V64: 0 | W64: =+V64/(1+$S64)*$S64 -> 0 | X64: =+W64*40% -> 0 | Y64: =+W64*60% -> 0 | Z64: =_xlfn.XLOOKUP(O64,'[4]2DO TRIMESTRE'!$C:$C,'[4]2DO TRIMESTRE'!$I:$I,0,0) -> 0 | AA64: =+Z64/(1+$S64)*$S64 -> 0 | AB64: =+AA64*40% -> 0 | AC64: =+AA64*60% -> 0 | AD64: 0 | AE64: =+AD64/(1+$S64)*$S64 -> 0 | AF64: =+AE64*40% -> 0 | AG64: =+AE64*60% -> 0 | AH64: 0 | AI64: =+AH64/(1+$S64)*$S64 -> 0 | AJ64: =+AI64*40% -> 0 | AK64: =+AI64*60% -> 0 | AL64: 8726786 | AM64: =W64+AA64+AE64+AI64 -> 0
A65: 59 | B65: 2021 | C65: SECRETARÍA DISTRITAL DEL HÁBITAT | D65: 842-SECRETARÍA DISTRITAL DEL HÁBITAT | E65: Contrato | F65: 44463 | G65: 44561 | H65: =+(G65-F65)/90 -> 1.0888889 | I65: Liquidado | J65: Sin Observaciones | K65: OCCIDENTE | L65: Cuenta de ahorros | M65: 230-85893- 8 | N65: 567 66 | O65: 2910906766 | P65: =+_xlfn.XLOOKUP(O65,'[3]Benef Primera fecha '!$C:$C,'[3]Benef Primera fecha '!$E:$E,0) -> 39600000 | Q65: 0 | R65: =+(P65+Q65) -> 39600000 | S65: 0.12 | T65: =(R65/(1+S65))*S65 -> 4242857.1 | U65: 39600000 | V65: 0 | W65: =+V65/(1+$S65)*$S65 -> 0 | X65: =+W65*40% -> 0 | Y65: =+W65*60% -> 0 | Z65: =_xlfn.XLOOKUP(O65,'[4]2DO TRIMESTRE'!$C:$C,'[4]2DO TRIMESTRE'!$I:$I,0,0) -> 0 | AA65: =+Z65/(1+$S65)*$S65 -> 0 | AB65: =+AA65*40% -> 0 | AC65: =+AA65*60% -> 0 | AD65: 0 | AE65: =+AD65/(1+$S65)*$S65 -> 0 | AF65: =+AE65*40% -> 0 | AG65: =+AE65*60% -> 0 | AH65: 0 | AI65: =+AH65/(1+$S65)*$S65 -> 0 | AJ65: =+AI65*40% -> 0 | AK65: =+AI65*60% -> 0 | AL65: 4242857 | AM65: =W65+AA65+AE65+AI65 -> 0
A66: 60 | B66: 2021 | C66: MINISTERIO DE DEFENSA NACIONAL | D66: 102-00-D-CACOM-1-DED-MINISTERIO DE DEFENSA NACIONAL | E66: Contrato | F66: 44467 | G66: 44772 | H66: =+(G66-F66)/90 -> 3.3888889 | I66: Liquidado | J66: Sin Observaciones | K66: OCCIDENTE | L66: Cuenta de ahorros | M66: 230-85893- 8 | N66: 567 69 | O66: 2910906769 | P66: =+_xlfn.XLOOKUP(O66,'[3]Benef Primera fecha '!$C:$C,'[3]Benef Primera fecha '!$E:$E,0) -> 483310000 | Q66: 0 | R66: =+(P66+Q66) -> 483310000 | S66: 0.12 | T66: =(R66/(1+S66))*S66 -> 51783214 | U66: 481988167 | V66: 0 | W66: =+V66/(1+$S66)*$S66 -> 0 | X66: =+W66*40% -> 0 | Y66: =+W66*60% -> 0 | Z66: =_xlfn.XLOOKUP(O66,'[4]2DO TRIMESTRE'!$C:$C,'[4]2DO TRIMESTRE'!$I:$I,0,0) -> 0 | AA66: =+Z66/(1+$S66)*$S66 -> 0 | AB66: =+AA66*40% -> 0 | AC66: =+AA66*60% -> 0 | AD66: 0 | AE66: =+AD66/(1+$S66)*$S66 -> 0 | AF66: =+AE66*40% -> 0 | AG66: =+AE66*60% -> 0 | AH66: 0 | AI66: =+AH66/(1+$S66)*$S66 -> 0 | AJ66: =+AI66*40% -> 0 | AK66: =+AI66*60% -> 0 | AL66: 51633460 | AM66: =W66+AA66+AE66+AI66 -> 0
A67: 61 | B67: 2021 | C67: INSTITUTO DEPARTAMENTAL DE CULTURA Y TURISMO DE CUNDINAMARCA | D67: 473-INSTITUTO DEPARTAMENTAL DE CULTURA Y TURISMO DE CUNDINAMARCA | E67: Contrato | F67: 44469 | G67: 44561 | H67: =+(G67-F67)/90 -> 1.0222222 | I67: Cierre Financiero | J67: Sin Observaciones | K67: OCCIDENTE | L67: Cuenta de ahorros | M67: 230-85893- 8 | N67: 567 61 | O67: 2910906761 | P67: =+_xlfn.XLOOKUP(O67,'[3]Benef Primera fecha '!$C:$C,'[3]Benef Primera fecha '!$E:$E,0) -> 21000000 | Q67: 0 | R67: =+(P67+Q67) -> 21000000 | S67: 0.12 | T67: =(R67/(1+S67))*S67 -> 2250000 | U67: 21000000 | V67: 0 | W67: =+V67/(1+$S67)*$S67 -> 0 | X67: =+W67*40% -> 0 | Y67: =+W67*60% -> 0 | Z67: =_xlfn.XLOOKUP(O67,'[4]2DO TRIMESTRE'!$C:$C,'[4]2DO TRIMESTRE'!$I:$I,0,0) -> 0 | AA67: =+Z67/(1+$S67)*$S67 -> 0 | AB67: =+AA67*40% -> 0 | AC67: =+AA67*60% -> 0 | AD67: 0 | AE67: =+AD67/(1+$S67)*$S67 -> 0 | AF67: =+AE67*40% -> 0 | AG67: =+AE67*60% -> 0 | AH67: 0 | AI67: =+AH67/(1+$S67)*$S67 -> 0 | AJ67: =+AI67*40% -> 0 | AK67: =+AI67*60% -> 0 | AL67: 2250000 | AM67: =W67+AA67+AE67+AI67 -> 0
A68: 62 | B68: 2021 | C68: UNIVERSIDAD DISTRITAL FRANCISCO JOSÉ DE CALDAS - UD | D68: FAC-ASAB-8043-UNIVERSIDAD DISTRITAL FRANCISCO JOSÉ DE CALDAS - UD | E68: Curso Propio | F68: 44470 | G68: 44651 | H68: =+(G68-F68)/90 -> 2.0111111 | I68: Liquidado | J68: Sin Observaciones | K68: OCCIDENTE | L68: Cuenta de ahorros | M68: 230-85718-7 | N68: 580 43 | O68: 2910908043 | P68: =+_xlfn.XLOOKUP(O68,'[3]Benef Primera fecha '!$C:$C,'[3]Benef Primera fecha '!$E:$E,0) -> 10909669 | Q68: 0 | R68: =+(P68+Q68) -> 10909669 | S68: 0.12 | T68: =(R68/(1+S68))*S68 -> 1168893.1 | U68: 10909669 | V68: 0 | W68: =+V68/(1+$S68)*$S68 -> 0 | X68: =+W68*40% -> 0 | Y68: =+W68*60% -> 0 | Z68: =_xlfn.XLOOKUP(O68,'[4]2DO TRIMESTRE'!$C:$C,'[4]2DO TRIMESTRE'!$I:$I,0,0) -> 0 | AA68: =+Z68/(1+$S68)*$S68 -> 0 | AB68: =+AA68*40% -> 0 | AC68: =+AA68*60% -> 0 | AD68: 0 | AE68: =+AD68/(1+$S68)*$S68 -> 0 | AF68: =+AE68*40% -> 0 | AG68: =+AE68*60% -> 0 | AH68: 0 | AI68: =+AH68/(1+$S68)*$S68 -> 0 | AJ68: =+AI68*40% -> 0 | AK68: =+AI68*60% -> 0 | AL68: 1105339 | AM68: =W68+AA68+AE68+AI68 -> 0
A69: 63 | B69: 2021 | C69: MINISTERIO DE DEFENSA NACIONAL INSTITUTO DE CASAS FISCALES DEL EJÉRCITO | D69: 185-MINISTERIO DE DEFENSA NACIONAL INSTITUTO DE CASAS FISCALES DEL EJÉRCITO | E69: Contrato | F69: 44470 | G69: 44505 | H69: =+(G69-F69)/90 -> 0.38888889 | I69: En Ejecución | J69: Sin Observaciones | K69: OCCIDENTE | L69: Cuenta de ahorros | M69: 230-85893- 8 | N69: 567 70 | O69: 2910906770 | P69: =+_xlfn.XLOOKUP(O69,'[3]Benef Primera fecha '!$C:$C,'[3]Benef Primera fecha '!$E:$E,0) -> 248617170 | Q69: 28000000 | R69: =+(P69+Q69) -> 276617170 | S69: 0.12 | T69: =(R69/(1+S69))*S69 -> 29637554 | U69: 210827357 | V69: 0 | W69: =+V69/(1+$S69)*$S69 -> 0 | X69: =+W69*40% -> 0 | Y69: =+W69*60% -> 0 | Z69: =_xlfn.XLOOKUP(O69,'[4]2DO TRIMESTRE'!$C:$C,'[4]2DO TRIMESTRE'!$I:$I,0,0) -> 0 | AA69: =+Z69/(1+$S69)*$S69 -> 0 | AB69: =+AA69*40% -> 0 | AC69: =+AA69*60% -> 0 | AD69: 0 | AE69: =+AD69/(1+$S69)*$S69 -> 0 | AF69: =+AE69*40% -> 0 | AG69: =+AE69*60% -> 0 | AH69: 0 | AI69: =+AH69/(1+$S69)*$S69 -> 0 | AJ69: =+AI69*40% -> 0 | AK69: =+AI69*60% -> 0 | AL69: 22588645 | AM69: =W69+AA69+AE69+AI69 -> 0
A70: 64 | B70: 2021 | C70: ALCALDÍA MUNICIPAL DE CAJICÁ | D70: 8-ALCALDÍA MUNICIPAL DE CAJICÁ | E70: Contrato | F70: 44474 | G70: 44683 | H70: =+(G70-F70)/90 -> 2.3222222 | I70: Liquidado | J70: Sin Observaciones | K70: OCCIDENTE | L70: Cuenta de ahorros | M70: 230-85893- 8 | N70: 567 68 | O70: 2910906768 | P70: =+_xlfn.XLOOKUP(O70,'[3]Benef Primera fecha '!$C:$C,'[3]Benef Primera fecha '!$E:$E,0) -> 205490000 | Q70: 0 | R70: =+(P70+Q70) -> 205490000 | S70: 0.12 | T70: =(R70/(1+S70))*S70 -> 22016786 | U70: 195221000 | V70: 0 | W70: =+V70/(1+$S70)*$S70 -> 0 | X70: =+W70*40% -> 0 | Y70: =+W70*60% -> 0 | Z70: =_xlfn.XLOOKUP(O70,'[4]2DO TRIMESTRE'!$C:$C,'[4]2DO TRIMESTRE'!$I:$I,0,0) -> 0 | AA70: =+Z70/(1+$S70)*$S70 -> 0 | AB70: =+AA70*40% -> 0 | AC70: =+AA70*60% -> 0 | AD70: 0 | AE70: =+AD70/(1+$S70)*$S70 -> 0 | AF70: =+AE70*40% -> 0 | AG70: =+AE70*60% -> 0 | AH70: 0 | AI70: =+AH70/(1+$S70)*$S70 -> 0 | AJ70: =+AI70*40% -> 0 | AK70: =+AI70*60% -> 0 | AL70: 20916536 | AM70: =W70+AA70+AE70+AI70 -> 0
A71: 65 | B71: 2021 | C71: POLICIA NACIONAL | D71: 80-7-10089-21-POLICIA NACIONAL | E71: Contrato | F71: 44484 | G71: 44530 | H71: =+(G71-F71)/90 -> 0.51111111 | I71: Liquidado | J71: Sin Observaciones | K71: OCCIDENTE | L71: Cuenta de ahorros | M71: 230-85893- 8 | N71: 567 67 | O71: 2910906767 | P71: =+_xlfn.XLOOKUP(O71,'[3]Benef Primera fecha '!$C:$C,'[3]Benef Primera fecha '!$E:$E,0) -> 400000000 | Q71: 50000000 | R71: =+(P71+Q71) -> 450000000 | S71: 0.12 | T71: 48250000 | U71: 450000000 | V71: 0 | W71: =+V71/(1+$S71)*$S71 -> 0 | X71: =+W71*40% -> 0 | Y71: =+W71*60% -> 0 | Z71: =_xlfn.XLOOKUP(O71,'[4]2DO TRIMESTRE'!$C:$C,'[4]2DO TRIMESTRE'!$I:$I,0,0) -> 0 | AA71: =+Z71/(1+$S71)*$S71 -> 0 | AB71: =+AA71*40% -> 0 | AC71: =+AA71*60% -> 0 | AD71: 0 | AE71: =+AD71/(1+$S71)*$S71 -> 0 | AF71: =+AE71*40% -> 0 | AG71: =+AE71*60% -> 0 | AH71: 0 | AI71: =+AH71/(1+$S71)*$S71 -> 0 | AJ71: =+AI71*40% -> 0 | AK71: =+AI71*60% -> 0 | AL71: 48250000 | AM71: =W71+AA71+AE71+AI71 -> 0
A72: 66 | B72: 2021 | C72: REGIÓN ADMINISTRATIVA Y DE PLANEACION ESPECIAL — RAPE | D72: 71-REGIÓN ADMINISTRATIVA Y DE PLANEACION ESPECIAL — RAPE | E72: Convenio Interadministrativo | F72: 44488 | H72: =+(G72-F72)/90 -> -494.31111 | I72: Cierre Financiero | J72: Sin Observaciones | K72: OCCIDENTE | L72: Cuenta de ahorros | M72: 230-85893- 8 | N72: 83 22 | O72: 2453018322 | P72: =+_xlfn.XLOOKUP(O72,'[3]Benef Primera fecha '!$C:$C,'[3]Benef Primera fecha '!$E:$E,0) -> 80000000 | Q72: 0 | R72: =+(P72+Q72) -> 80000000 | S72: 0.12 | T72: =(R72/(1+S72))*S72 -> 8571428.6 | U72: 80000000 | V72: 0 | W72: =+V72/(1+$S72)*$S72 -> 0 | X72: =+W72*40% -> 0 | Y72: =+W72*60% -> 0 | Z72: =_xlfn.XLOOKUP(O72,'[4]2DO TRIMESTRE'!$C:$C,'[4]2DO TRIMESTRE'!$I:$I,0,0) -> 0 | AA72: =+Z72/(1+$S72)*$S72 -> 0 | AB72: =+AA72*40% -> 0 | AC72: =+AA72*60% -> 0 | AD72: 0 | AE72: =+AD72/(1+$S72)*$S72 -> 0 | AF72: =+AE72*40% -> 0 | AG72: =+AE72*60% -> 0 | AH72: 0 | AI72: =+AH72/(1+$S72)*$S72 -> 0 | AJ72: =+AI72*40% -> 0 | AK72: =+AI72*60% -> 0 | AL72: 8571428 | AM72: =W72+AA72+AE72+AI72 -> 0
A73: 67 | B73: 2021 | C73: UNIVERSIDAD DISTRITAL FRANCISCO JOSÉ DE CALDAS - UD | D73: FAC-TECNO-8049-UNIVERSIDAD DISTRITAL FRANCISCO JOSÉ DE CALDAS - UD | E73: Curso Propio | F73: 44489 | G73: 44491 | H73: =+(G73-F73)/90 -> 0.022222222 | I73: En Ejecución | J73: Sin Observaciones | K73: OCCIDENTE | L73: Cuenta de ahorros | M73: 230-85718-7 | N73: 580 49 | O73: 2910908049 | P73: 7014816 | Q73: 0 | R73: =+(P73+Q73) -> 7014816 | S73: 0.12 | T73: =(R73/(1+S73))*S73 -> 751587.43 | U73: 0 | V73: 0 | W73: =+V73/(1+$S73)*$S73 -> 0 | X73: =+W73*40% -> 0 | Y73: =+W73*60% -> 0 | Z73: =_xlfn.XLOOKUP(O73,'[4]2DO TRIMESTRE'!$C:$C,'[4]2DO TRIMESTRE'!$I:$I,0,0) -> 0 | AA73: =+Z73/(1+$S73)*$S73 -> 0 | AB73: =+AA73*40% -> 0 | AC73: =+AA73*60% -> 0 | AD73: 0 | AE73: =+AD73/(1+$S73)*$S73 -> 0 | AF73: =+AE73*40% -> 0 | AG73: =+AE73*60% -> 0 | AH73: 0 | AI73: =+AH73/(1+$S73)*$S73 -> 0 | AJ73: =+AI73*40% -> 0 | AK73: =+AI73*60% -> 0 | AL73: 0 | AM73: =W73+AA73+AE73+AI73 -> 0
A74: 68 | B74: 2021 | C74: MUNICIPIO DE CHÍA | D74: 025-2021-MUNICIPIO DE CHÍA | E74: Contrato | F74: 44490 | G74: 44561 | H74: =+(G74-F74)/90 -> 0.78888889 | I74: Terminado | J74: Sin Observaciones | K74: OCCIDENTE | L74: Cuenta de ahorros | M74: 230-85893- 8 | N74: 83 23 | O74: 2453018323 | P74: =+_xlfn.XLOOKUP(O74,'[3]Benef Primera fecha '!$C:$C,'[3]Benef Primera fecha '!$E:$E,0) -> 430696700 | Q74: 0 | R74: =+(P74+Q74) -> 430696700 | S74: 0.12 | T74: =(R74/(1+S74))*S74 -> 46146075 | U74: 430696700 | V74: 0 | W74: =+V74/(1+$S74)*$S74 -> 0 | X74: =+W74*40% -> 0 | Y74: =+W74*60% -> 0 | Z74: =_xlfn.XLOOKUP(O74,'[4]2DO TRIMESTRE'!$C:$C,'[4]2DO TRIMESTRE'!$I:$I,0,0) -> 0 | AA74: =+Z74/(1+$S74)*$S74 -> 0 | AB74: =+AA74*40% -> 0 | AC74: =+AA74*60% -> 0 | AD74: 0 | AE74: =+AD74/(1+$S74)*$S74 -> 0 | AF74: =+AE74*40% -> 0 | AG74: =+AE74*60% -> 0 | AH74: 0 | AI74: =+AH74/(1+$S74)*$S74 -> 0 | AJ74: =+AI74*40% -> 0 | AK74: =+AI74*60% -> 0 | AL74: 35431790 | AM74: =W74+AA74+AE74+AI74 -> 0
A75: 69 | B75: 2021 | C75: ALCALDÍA MUNICIPAL DE JUNÍN | D75: CD-CI-2021000007-ALCALDÍA MUNICIPAL DE JUNÍN | E75: Contrato | F75: 44497 | G75: 44598 | H75: =+(G75-F75)/90 -> 1.1222222 | I75: Liquidado | J75: Sin Observaciones | K75: OCCIDENTE | L75: Cuenta de ahorros | M75: 230-85893- 8 | N75: 83 29 | O75: 2453018329 | P75: =+_xlfn.XLOOKUP(O75,'[3]Benef Primera fecha '!$C:$C,'[3]Benef Primera fecha '!$E:$E,0) -> 23000000 | Q75: 0 | R75: =+(P75+Q75) -> 23000000 | S75: 0.12000002 | T75: =(R75/(1+S75))*S75 -> 2464286 | U75: 9619080 | V75: 0 | W75: =+V75/(1+$S75)*$S75 -> 0 | X75: =+W75*40% -> 0 | Y75: =+W75*60% -> 0 | Z75: =_xlfn.XLOOKUP(O75,'[4]2DO TRIMESTRE'!$C:$C,'[4]2DO TRIMESTRE'!$I:$I,0,0) -> 0 | AA75: =+Z75/(1+$S75)*$S75 -> 0 | AB75: =+AA75*40% -> 0 | AC75: =+AA75*60% -> 0 | AD75: 0 | AE75: =+AD75/(1+$S75)*$S75 -> 0 | AF75: =+AE75*40% -> 0 | AG75: =+AE75*60% -> 0 | AH75: 0 | AI75: =+AH75/(1+$S75)*$S75 -> 0 | AJ75: =+AI75*40% -> 0 | AK75: =+AI75*60% -> 0 | AL75: 2464286 | AM75: =W75+AA75+AE75+AI75 -> 0
A76: 70 | B76: 2021 | C76: SECRETARÍA DE EDUCACION DEL DISTRITO - SED | D76: 2996174-SECRETARÍA DE EDUCACION DEL DISTRITO - SED | E76: Convenio Interadministrativo | F76: 44505 | G76: 44711 | H76: =+(G76-F76)/90 -> 2.2888889 | I76: Cierre Financiero | J76: Sin Observaciones | K76: OCCIDENTE | L76: Cuenta de ahorros | M76: 230-85893- 8 | N76: 83 26 | O76: 2453018326 | P76: =+_xlfn.XLOOKUP(O76,'[3]Benef Primera fecha '!$C:$C,'[3]Benef Primera fecha '!$E:$E,0) -> 420254100 | Q76: 0 | R76: =+(P76+Q76) -> 420254100 | S76: 0.12 | T76: =(R76/(1+S76))*S76 -> 45027225 | U76: 420254100 | V76: 0 | W76: =+V76/(1+$S76)*$S76 -> 0 | X76: =+W76*40% -> 0 | Y76: =+W76*60% -> 0 | Z76: =_xlfn.XLOOKUP(O76,'[4]2DO TRIMESTRE'!$C:$C,'[4]2DO TRIMESTRE'!$I:$I,0,0) -> 0 | AA76: =+Z76/(1+$S76)*$S76 -> 0 | AB76: =+AA76*40% -> 0 | AC76: =+AA76*60% -> 0 | AD76: 0 | AE76: =+AD76/(1+$S76)*$S76 -> 0 | AF76: =+AE76*40% -> 0 | AG76: =+AE76*60% -> 0 | AH76: 0 | AI76: =+AH76/(1+$S76)*$S76 -> 0 | AJ76: =+AI76*40% -> 0 | AK76: =+AI76*60% -> 0 | AL76: 45027225 | AM76: =W76+AA76+AE76+AI76 -> 0
A77: 71 | B77: 2021 | C77: MINISTERIO DE DEFENSA NACIONAL INSTITUTO DE CASAS FISCALES DEL EJÉRCITO | D77: 190-ICFE-2021-MINISTERIO DE DEFENSA NACIONAL INSTITUTO DE CASAS FISCALES DEL EJÉRCITO | E77: Contrato | F77: 44508 | G77: 44758 | H77: =+(G77-F77)/90 -> 2.7777778 | I77: Terminado | J77: Sin Observaciones | K77: OCCIDENTE | L77: Cuenta de ahorros | M77: 230-85893- 8 | N77: 567 72 | O77: 2910906772 | P77: =+_xlfn.XLOOKUP(O77,'[3]Benef Primera fecha '!$C:$C,'[3]Benef Primera fecha '!$E:$E,0) -> 186462878 | Q77: 0 | R77: =+(P77+Q77) -> 186462878 | S77: 0.12 | T77: =(R77/(1+S77))*S77 -> 19978166 | U77: 154080490 | V77: 0 | W77: =+V77/(1+$S77)*$S77 -> 0 | X77: =+W77*40% -> 0 | Y77: =+W77*60% -> 0 | Z77: =_xlfn.XLOOKUP(O77,'[4]2DO TRIMESTRE'!$C:$C,'[4]2DO TRIMESTRE'!$I:$I,0,0) -> 0 | AA77: =+Z77/(1+$S77)*$S77 -> 0 | AB77: =+AA77*40% -> 0 | AC77: =+AA77*60% -> 0 | AD77: 0 | AE77: =+AD77/(1+$S77)*$S77 -> 0 | AF77: =+AE77*40% -> 0 | AG77: =+AE77*60% -> 0 | AH77: 0 | AI77: =+AH77/(1+$S77)*$S77 -> 0 | AJ77: =+AI77*40% -> 0 | AK77: =+AI77*60% -> 0 | AL77: 16508624 | AM77: =W77+AA77+AE77+AI77 -> 0
A78: 72 | B78: 2021 | C78: FDL TUNJUELITO | D78: 203-FDL TUNJUELITO | E78: Contrato | F78: 44508 | G78: 44697 | H78: =+(G78-F78)/90 -> 2.1 | I78: En Ejecución | J78: Sin Observaciones | K78: OCCIDENTE | L78: Cuenta de ahorros | M78: 230-85893- 8 | N78: 567 75 | O78: 2910906775 | P78: =+_xlfn.XLOOKUP(O78,'[3]Benef Primera fecha '!$C:$C,'[3]Benef Primera fecha '!$E:$E,0) -> 423000000 | Q78: 0 | R78: =+(P78+Q78) -> 423000000 | S78: 0.12 | T78: =(R78/(1+S78))*S78 -> 45321429 | U78: 423000000 | V78: 0 | W78: =+V78/(1+$S78)*$S78 -> 0 | X78: =+W78*40% -> 0 | Y78: =+W78*60% -> 0 | Z78: =_xlfn.XLOOKUP(O78,'[4]2DO TRIMESTRE'!$C:$C,'[4]2DO TRIMESTRE'!$I:$I,0,0) -> 0 | AA78: =+Z78/(1+$S78)*$S78 -> 0 | AB78: =+AA78*40% -> 0 | AC78: =+AA78*60% -> 0 | AD78: 0 | AE78: =+AD78/(1+$S78)*$S78 -> 0 | AF78: =+AE78*40% -> 0 | AG78: =+AE78*60% -> 0 | AH78: 0 | AI78: =+AH78/(1+$S78)*$S78 -> 0 | AJ78: =+AI78*40% -> 0 | AK78: =+AI78*60% -> 0 | AL78: 45321429 | AM78: =W78+AA78+AE78+AI78 -> 0
A79: 73 | B79: 2021 | C79: CORPORACIÓN AUTÓNOMA REGIONAL DE BOYACÁ - CORPOBOYACÁ | D79: 019-CORPORACIÓN AUTÓNOMA REGIONAL DE BOYACÁ - CORPOBOYACÁ | E79: Contrato | F79: 44511 | G79: 44828 | H79: =+(G79-F79)/90 -> 3.5222222 | I79: Liquidado | J79: Sin Observaciones | K79: OCCIDENTE | L79: Cuenta de ahorros | M79: 230-89548-4 | N79: 83 25 | O79: 2453018325 | P79: =+_xlfn.XLOOKUP(O79,'[3]Benef Primera fecha '!$C:$C,'[3]Benef Primera fecha '!$E:$E,0) -> 744689120 | Q79: 0 | R79: =+(P79+Q79) -> 744689120 | S79: 0.12 | T79: =(R79/(1+S79))*S79 -> 79788120 | U79: 736984380 | V79: 0 | W79: =+V79/(1+$S79)*$S79 -> 0 | X79: =+W79*40% -> 0 | Y79: =+W79*60% -> 0 | Z79: =_xlfn.XLOOKUP(O79,'[4]2DO TRIMESTRE'!$C:$C,'[4]2DO TRIMESTRE'!$I:$I,0,0) -> 0 | AA79: =+Z79/(1+$S79)*$S79 -> 0 | AB79: =+AA79*40% -> 0 | AC79: =+AA79*60% -> 0 | AD79: 0 | AE79: =+AD79/(1+$S79)*$S79 -> 0 | AF79: =+AE79*40% -> 0 | AG79: =+AE79*60% -> 0 | AH79: 0 | AI79: =+AH79/(1+$S79)*$S79 -> 0 | AJ79: =+AI79*40% -> 0 | AK79: =+AI79*60% -> 0 | AL79: 78962612 | AM79: =W79+AA79+AE79+AI79 -> 0
A80: 74 | B80: 2021 | C80: CORPORACIÓN AUTÓNOMA REGIONAL DE LOS VALLES DEL SINÚ Y DEL SAN JORGE - CVS | D80: 8-CORPORACIÓN AUTÓNOMA REGIONAL DE LOS VALLES DEL SINÚ Y DEL SAN JORGE - CVS | E80: Convenio Interadministrativo | F80: 44512 | G80: 44763 | H80: =+(G80-F80)/90 -> 2.7888889 | I80: Liquidado | J80: Sin Observaciones | K80: OCCIDENTE | L80: Cuenta de ahorros | M80: 230-89553-4 | N80: 83 28 | O80: 2453018328 | P80: =+_xlfn.XLOOKUP(O80,'[3]Benef Primera fecha '!$C:$C,'[3]Benef Primera fecha '!$E:$E,0) -> 1199922000 | Q80: 0 | R80: =+(P80+Q80) -> 1199922000 | S80: 0.12 | T80: =(R80/(1+S80))*S80 -> 1.2856307e+08 | U80: 1090248013 | V80: 0 | W80: =+V80/(1+$S80)*$S80 -> 0 | X80: =+W80*40% -> 0 | Y80: =+W80*60% -> 0 | Z80: =_xlfn.XLOOKUP(O80,'[4]2DO TRIMESTRE'!$C:$C,'[4]2DO TRIMESTRE'!$I:$I,0,0) -> 0 | AA80: =+Z80/(1+$S80)*$S80 -> 0 | AB80: =+AA80*40% -> 0 | AC80: =+AA80*60% -> 0 | AD80: 0 | AE80: =+AD80/(1+$S80)*$S80 -> 0 | AF80: =+AE80*40% -> 0 | AG80: =+AE80*60% -> 0 | AH80: 0 | AI80: =+AH80/(1+$S80)*$S80 -> 0 | AJ80: =+AI80*40% -> 0 | AK80: =+AI80*60% -> 0 | AL80: 116812287 | AM80: =W80+AA80+AE80+AI80 -> 0
A81: 75 | B81: 2021 | C81: FDL FONTIBÓN | D81: 23-FDL FONTIBÓN | E81: Convenio Interadministrativo | F81: 44512 | G81: 44851 | H81: =+(G81-F81)/90 -> 3.7666667 | I81: En Ejecución | J81: Sin Observaciones | K81: OCCIDENTE | L81: Cuenta de ahorros | M81: 230-85893- 8 | N81: 83 34 | O81: 2453018334 | P81: 384000000 | Q81: 0 | R81: =+(P81+Q81) -> 384000000 | S81: 0 | T81: =(R81/(1+S81))*S81 -> 0 | U81: 0 | V81: 0 | W81: =+V81/(1+$S81)*$S81 -> 0 | X81: =+W81*40% -> 0 | Y81: =+W81*60% -> 0 | Z81: =_xlfn.XLOOKUP(O81,'[4]2DO TRIMESTRE'!$C:$C,'[4]2DO TRIMESTRE'!$I:$I,0,0) -> 0 | AA81: =+Z81/(1+$S81)*$S81 -> 0 | AB81: =+AA81*40% -> 0 | AC81: =+AA81*60% -> 0 | AD81: 0 | AE81: =+AD81/(1+$S81)*$S81 -> 0 | AF81: =+AE81*40% -> 0 | AG81: =+AE81*60% -> 0 | AH81: 0 | AI81: =+AH81/(1+$S81)*$S81 -> 0 | AJ81: =+AI81*40% -> 0 | AK81: =+AI81*60% -> 0 | AL81: 0 | AM81: =W81+AA81+AE81+AI81 -> 0 | AN81: Proyecto sin beneficio institucional estipulado en el presupuesto | AO81: Proyecto sin beneficio institucional estipulado en el presupuesto
A82: 76 | B82: 2021 | C82: CORPORACIÓN AUTÓNOMA REGIONAL DE CUNDINAMARCA - CAR | D82: 2596-CORPORACIÓN AUTÓNOMA REGIONAL DE CUNDINAMARCA - CAR | E82: Convenio Interadministrativo | F82: 44512 | G82: 44914 | H82: =+(G82-F82)/90 -> 4.4666667 | I82: Terminado | J82: Sin Observaciones | K82: OCCIDENTE | L82: Cuenta de ahorros | M82: 230-89558-3 | N82: 83 30 | O82: 2453018330 | P82: =+_xlfn.XLOOKUP(O82,'[3]Benef Primera fecha '!$C:$C,'[3]Benef Primera fecha '!$E:$E,0) -> 2419332150 | Q82: 0 | R82: =+(P82+Q82) -> 2419332150 | S82: 0.12 | T82: =(R82/(1+S82))*S82 -> 259214159 | U82: 2419332150 | V82: 0 | W82: =+V82/(1+$S82)*$S82 -> 0 | X82: =+W82*40% -> 0 | Y82: =+W82*60% -> 0 | Z82: =_xlfn.XLOOKUP(O82,'[4]2DO TRIMESTRE'!$C:$C,'[4]2DO TRIMESTRE'!$I:$I,0,0) -> 0 | AA82: =+Z82/(1+$S82)*$S82 -> 0 | AB82: =+AA82*40% -> 0 | AC82: =+AA82*60% -> 0 | AD82: 0 | AE82: =+AD82/(1+$S82)*$S82 -> 0 | AF82: =+AE82*40% -> 0 | AG82: =+AE82*60% -> 0 | AH82: 0 | AI82: =+AH82/(1+$S82)*$S82 -> 0 | AJ82: =+AI82*40% -> 0 | AK82: =+AI82*60% -> 0 | AL82: 259214159 | AM82: =W82+AA82+AE82+AI82 -> 0
A83: 77 | B83: 2021 | C83: SECRETARÍA DISTRITAL DE CULTURA, RECREACIÓN Y DEPORTE | D83: 477-2021-SECRETARÍA DISTRITAL DE CULTURA, RECREACIÓN Y DEPORTE-SCRD | E83: Convenio Interadministrativo | F83: 44512 | G83: 44561 | H83: =+(G83-F83)/90 -> 0.54444444 | I83: Terminado | J83: Sin Observaciones | K83: OCCIDENTE | L83: Cuenta de ahorros | M83: 230-89545-0 | N83: 83 24 | O83: 2453018324 | P83: =+_xlfn.XLOOKUP(O83,'[3]Benef Primera fecha '!$C:$C,'[3]Benef Primera fecha '!$E:$E,0) -> 3388773098 | Q83: 0 | R83: =+(P83+Q83) -> 3388773098 | S83: 0.12 | T83: =(R83/(1+S83))*S83 -> 3.6308283e+08 | U83: 3388773098 | V83: 0 | W83: =+V83/(1+$S83)*$S83 -> 0 | X83: =+W83*40% -> 0 | Y83: =+W83*60% -> 0 | Z83: =_xlfn.XLOOKUP(O83,'[4]2DO TRIMESTRE'!$C:$C,'[4]2DO TRIMESTRE'!$I:$I,0,0) -> 0 | AA83: =+Z83/(1+$S83)*$S83 -> 0 | AB83: =+AA83*40% -> 0 | AC83: =+AA83*60% -> 0 | AD83: 0 | AE83: =+AD83/(1+$S83)*$S83 -> 0 | AF83: =+AE83*40% -> 0 | AG83: =+AE83*60% -> 0 | AH83: 0 | AI83: =+AH83/(1+$S83)*$S83 -> 0 | AJ83: =+AI83*40% -> 0 | AK83: =+AI83*60% -> 0 | AL83: 363082832 | AM83: =W83+AA83+AE83+AI83 -> 0
A84: 78 | B84: 2021 | C84: CORPORACION PARA EL DESARROLLO SOSTENIBLE DEL SUR DE LA AMAZONIA CORPOAMAZONIA | D84: 520-CORPORACION PARA EL DESARROLLO SOSTENIBLE DEL SUR DE LA AMAZONIA CORPOAMAZONIA | E84: Convenio Interadministrativo | F84: 44512 | G84: 45239 | H84: =+(G84-F84)/90 -> 8.0777778 | I84: En Ejecución | J84: Sin Observaciones | K84: OCCIDENTE | L84: Cuenta de ahorros | M84: 230-85893- 8 | N84: 83 27 | O84: 2453018327 | P84: =+_xlfn.XLOOKUP(O84,'[3]Benef Primera fecha '!$C:$C,'[3]Benef Primera fecha '!$E:$E,0) -> 570067542 | Q84: 0 | R84: =+(P84+Q84) -> 570067542 | S84: 0.12 | T84: =(R84/(1+S84))*S84 -> 61078665 | U84: 570067542 | V84: 0 | W84: =+V84/(1+$S84)*$S84 -> 0 | X84: =+W84*40% -> 0 | Y84: =+W84*60% -> 0 | Z84: =_xlfn.XLOOKUP(O84,'[4]2DO TRIMESTRE'!$C:$C,'[4]2DO TRIMESTRE'!$I:$I,0,0) -> 0 | AA84: =+Z84/(1+$S84)*$S84 -> 0 | AB84: =+AA84*40% -> 0 | AC84: =+AA84*60% -> 0 | AD84: 0 | AE84: =+AD84/(1+$S84)*$S84 -> 0 | AF84: =+AE84*40% -> 0 | AG84: =+AE84*60% -> 0 | AH84: 0 | AI84: =+AH84/(1+$S84)*$S84 -> 0 | AJ84: =+AI84*40% -> 0 | AK84: =+AI84*60% -> 0 | AL84: 61078665 | AM84: =W84+AA84+AE84+AI84 -> 0
A85: 79 | B85: 2021 | C85: FDL CIUDAD BOLIVAR | D85: 610-FDL CIUDAD BOLIVAR | E85: Convenio Interadministrativo | F85: 44512 | G85: 45266 | H85: =+(G85-F85)/90 -> 8.3777778 | I85: En Ejecución | J85: Sin Observaciones | K85: OCCIDENTE | L85: Cuenta de ahorros | M85: 230-85893- 8 | N85: 83 32 | O85: 2453018332 | P85: =+_xlfn.XLOOKUP(O85,'[3]Benef Primera fecha '!$C:$C,'[3]Benef Primera fecha '!$E:$E,0) -> 1703681000 | Q85: -154999930 | R85: =+(P85+Q85) -> 1548681070 | S85: 0.12 | T85: =(R85/(1+S85))*S85 -> 165930115 | U85: 992816670 | V85: 0 | W85: =+V85/(1+$S85)*$S85 -> 0 | X85: =+W85*40% -> 0 | Y85: =+W85*60% -> 0 | Z85: =_xlfn.XLOOKUP(O85,'[4]2DO TRIMESTRE'!$C:$C,'[4]2DO TRIMESTRE'!$I:$I,0,0) -> 0 | AA85: =+Z85/(1+$S85)*$S85 -> 0 | AB85: =+AA85*40% -> 0 | AC85: =+AA85*60% -> 0 | AD85: 0 | AE85: =+AD85/(1+$S85)*$S85 -> 0 | AF85: =+AE85*40% -> 0 | AG85: =+AE85*60% -> 0 | AH85: 0 | AI85: =+AH85/(1+$S85)*$S85 -> 0 | AJ85: =+AI85*40% -> 0 | AK85: =+AI85*60% -> 0 | AL85: 106373215 | AM85: =W85+AA85+AE85+AI85 -> 0
A86: 80 | B86: 2021 | C86: SECRETARÍA DISTRITAL DE LA MUJER | D86: 907-2021-LA SECRETARÍA DISTRITAL DE LA MUJER | E86: Contrato | F86: 44512 | G86: 44766 | H86: =+(G86-F86)/90 -> 2.8222222 | I86: Liquidado | J86: Sin Observaciones | K86: OCCIDENTE | L86: Cuenta de ahorros | M86: 230-85893- 8 | N86: 567 76 | O86: 2910906776 | P86: =+_xlfn.XLOOKUP(O86,'[3]Benef Primera fecha '!$C:$C,'[3]Benef Primera fecha '!$E:$E,0) -> 150000000 | Q86: 0 | R86: =+(P86+Q86) -> 150000000 | S86: 0.12 | T86: =(R86/(1+S86))*S86 -> 16071429 | U86: 135000000 | V86: 0 | W86: =+V86/(1+$S86)*$S86 -> 0 | X86: =+W86*40% -> 0 | Y86: =+W86*60% -> 0 | Z86: =_xlfn.XLOOKUP(O86,'[4]2DO TRIMESTRE'!$C:$C,'[4]2DO TRIMESTRE'!$I:$I,0,0) -> 0 | AA86: =+Z86/(1+$S86)*$S86 -> 0 | AB86: =+AA86*40% -> 0 | AC86: =+AA86*60% -> 0 | AD86: 0 | AE86: =+AD86/(1+$S86)*$S86 -> 0 | AF86: =+AE86*40% -> 0 | AG86: =+AE86*60% -> 0 | AH86: 0 | AI86: =+AH86/(1+$S86)*$S86 -> 0 | AJ86: =+AI86*40% -> 0 | AK86: =+AI86*60% -> 0 | AL86: 14490000 | AM86: =W86+AA86+AE86+AI86 -> 0
A87: 81 | B87: 2021 | C87: FDL RAFAEL URIBE URIBE | D87: CIA-305-2021-FDL RAFAEL URIBE URIBE | E87: Contrato | F87: 44512 | G87: 44849 | H87: =+(G87-F87)/90 -> 3.7444444 | I87: Liquidado | J87: Sin Observaciones | K87: OCCIDENTE | L87: Cuenta de ahorros | M87: 230-85893- 8 | N87: 567 77 | O87: 2910906777 | P87: =+_xlfn.XLOOKUP(O87,'[3]Benef Primera fecha '!$C:$C,'[3]Benef Primera fecha '!$E:$E,0) -> 1162897960 | Q87: 0 | R87: =+(P87+Q87) -> 1162897960 | S87: 0.12 | T87: =(R87/(1+S87))*S87 -> 1.2459621e+08 | U87: 1134011560 | V87: 0 | W87: =+V87/(1+$S87)*$S87 -> 0 | X87: =+W87*40% -> 0 | Y87: =+W87*60% -> 0 | Z87: =_xlfn.XLOOKUP(O87,'[4]2DO TRIMESTRE'!$C:$C,'[4]2DO TRIMESTRE'!$I:$I,0,0) -> 0 | AA87: =+Z87/(1+$S87)*$S87 -> 0 | AB87: =+AA87*40% -> 0 | AC87: =+AA87*60% -> 0 | AD87: 0 | AE87: =+AD87/(1+$S87)*$S87 -> 0 | AF87: =+AE87*40% -> 0 | AG87: =+AE87*60% -> 0 | AH87: 0 | AI87: =+AH87/(1+$S87)*$S87 -> 0 | AJ87: =+AI87*40% -> 0 | AK87: =+AI87*60% -> 0 | AL87: 121501239 | AM87: =W87+AA87+AE87+AI87 -> 0
A88: 82 | B88: 2021 | C88: FDL CIUDAD BOLIVAR | D88: CIA-591-2021-FDL CIUDAD BOLIVAR | E88: Convenio Interadministrativo | F88: 44512 | G88: 45250 | H88: =+(G88-F88)/90 -> 8.2 | I88: En Ejecución | J88: Sin Observaciones | K88: OCCIDENTE | L88: Cuenta de ahorros | M88: 230-85893- 8 | N88: 83 31 | O88: 2453018331 | P88: =+_xlfn.XLOOKUP(O88,'[3]Benef Primera fecha '!$C:$C,'[3]Benef Primera fecha '!$E:$E,0) -> 1079098616 | Q88: 0 | R88: =+(P88+Q88) -> 1079098616 | S88: 0.12 | T88: =(R88/(1+S88))*S88 -> 1.1561771e+08 | U88: 1079098616 | V88: 0 | W88: =+V88/(1+$S88)*$S88 -> 0 | X88: =+W88*40% -> 0 | Y88: =+W88*60% -> 0 | Z88: 585489219 | AA88: =+Z88/(1+$S88)*$S88 -> 62730988 | AB88: =+AA88*40% -> 25092395 | AC88: =+AA88*60% -> 37638593 | AD88: 0 | AE88: =+AD88/(1+$S88)*$S88 -> 0 | AF88: =+AE88*40% -> 0 | AG88: =+AE88*60% -> 0 | AH88: 0 | AI88: =+AH88/(1+$S88)*$S88 -> 0 | AJ88: =+AI88*40% -> 0 | AK88: =+AI88*60% -> 0 | AL88: 1.1561771e+08 | AM88: =W88+AA88+AE88+AI88 -> 62730988
A89: 83 | B89: 2021 | C89: MINISTERIO DE DEFENSA NACIONAL INSTITUTO DE CASAS FISCALES DEL EJÉRCITO | D89: N°192-ICFE-2021-MINISTERIO DE DEFENSA NACIONAL INSTITUTO DE CASAS FISCALES DEL EJÉRCITO | E89: Contrato | F89: 44525 | G89: 44789 | H89: =+(G89-F89)/90 -> 2.9333333 | I89: Terminado | J89: Sin Observaciones | K89: OCCIDENTE | L89: Cuenta de ahorros | M89: 230-85893- 8 | N89: 567 73 | O89: 2910906773 | P89: =+_xlfn.XLOOKUP(O89,'[3]Benef Primera fecha '!$C:$C,'[3]Benef Primera fecha '!$E:$E,0) -> 248617174 | Q89: 0 | R89: =+(P89+Q89) -> 248617174 | S89: 0.12 | T89: =(R89/(1+S89))*S89 -> 26637554 | U89: 141514384 | V89: 0 | W89: =+V89/(1+$S89)*$S89 -> 0 | X89: =+W89*40% -> 0 | Y89: =+W89*60% -> 0 | Z89: =_xlfn.XLOOKUP(O89,'[4]2DO TRIMESTRE'!$C:$C,'[4]2DO TRIMESTRE'!$I:$I,0,0) -> 0 | AA89: =+Z89/(1+$S89)*$S89 -> 0 | AB89: =+AA89*40% -> 0 | AC89: =+AA89*60% -> 0 | AD89: 0 | AE89: =+AD89/(1+$S89)*$S89 -> 0 | AF89: =+AE89*40% -> 0 | AG89: =+AE89*60% -> 0 | AH89: 0 | AI89: =+AH89/(1+$S89)*$S89 -> 0 | AJ89: =+AI89*40% -> 0 | AK89: =+AI89*60% -> 0 | AL89: 15162255 | AM89: =W89+AA89+AE89+AI89 -> 0
A90: 84 | B90: 2022 | C90: ENEL EMGESA S.A ESP | D90: ZOCS 4500448697-ENEL EMGESA S.A ESP | E90: Contrato | F90: 44588 | G90: 44925 | H90: =+(G90-F90)/90 -> 3.7444444 | I90: Liquidado | J90: Sin Observaciones | K90: OCCIDENTE | L90: Cuenta de ahorros | M90: 230-85893- 8 | N90: 567 81 | O90: 2910906781 | P90: =+_xlfn.XLOOKUP(O90,'[3]Benef Primera fecha '!$C:$C,'[3]Benef Primera fecha '!$E:$E,0) -> 98000000 | Q90: 0 | R90: =+(P90+Q90) -> 98000000 | S90: 0.12 | T90: =(R90/(1+S90))*S90 -> 10500000 | U90: 98000000 | V90: 0 | W90: =+V90/(1+$S90)*$S90 -> 0 | X90: =+W90*40% -> 0 | Y90: =+W90*60% -> 0 | Z90: =_xlfn.XLOOKUP(O90,'[4]2DO TRIMESTRE'!$C:$C,'[4]2DO TRIMESTRE'!$I:$I,0,0) -> 0 | AA90: =+Z90/(1+$S90)*$S90 -> 0 | AB90: =+AA90*40% -> 0 | AC90: =+AA90*60% -> 0 | AD90: 0 | AE90: =+AD90/(1+$S90)*$S90 -> 0 | AF90: =+AE90*40% -> 0 | AG90: =+AE90*60% -> 0 | AH90: 0 | AI90: =+AH90/(1+$S90)*$S90 -> 0 | AJ90: =+AI90*40% -> 0 | AK90: =+AI90*60% -> 0 | AL90: 10500000 | AM90: =W90+AA90+AE90+AI90 -> 0
A91: 85 | B91: 2022 | C91: MINISTERIO DE DEFENSA NACIONAL | D91: 001-00-G-CACOM-4- DE-MINISTERIO DE DEFENSA NACIONAL | E91: Contrato | F91: 44589 | G91: 44865 | H91: =+(G91-F91)/90 -> 3.0666667 | I91: Liquidado | J91: Sin Observaciones | K91: OCCIDENTE | L91: Cuenta de ahorros | M91: 230-85893- 8 | N91: 567 84 | O91: 2910906784 | P91: =+_xlfn.XLOOKUP(O91,'[3]Benef Primera fecha '!$C:$C,'[3]Benef Primera fecha '!$E:$E,0) -> 434569106 | Q91: 80975609 | R91: =+(P91+Q91) -> 515544715 | S91: 0.12 | T91: =(R91/(1+S91))*S91 -> 55236934 | U91: 515544715 | V91: 0 | W91: =+V91/(1+$S91)*$S91 -> 0 | X91: =+W91*40% -> 0 | Y91: =+W91*60% -> 0 | Z91: =_xlfn.XLOOKUP(O91,'[4]2DO TRIMESTRE'!$C:$C,'[4]2DO TRIMESTRE'!$I:$I,0,0) -> 0 | AA91: =+Z91/(1+$S91)*$S91 -> 0 | AB91: =+AA91*40% -> 0 | AC91: =+AA91*60% -> 0 | AD91: 0 | AE91: =+AD91/(1+$S91)*$S91 -> 0 | AF91: =+AE91*40% -> 0 | AG91: =+AE91*60% -> 0 | AH91: 0 | AI91: =+AH91/(1+$S91)*$S91 -> 0 | AJ91: =+AI91*40% -> 0 | AK91: =+AI91*60% -> 0 | AL91: 55236934 | AM91: =W91+AA91+AE91+AI91 -> 0
A92: 86 | B92: 2022 | C92: CONCEJO MUNICIPAL DE YOPAL | D92: 035-CONCEJO MUNICIPAL DE YOPAL | E92: Contrato | F92: 44589 | G92: 44653 | H92: =+(G92-F92)/90 -> 0.71111111 | I92: Liquidado | J92: Sin Observaciones | K92: OCCIDENTE | L92: Cuenta de ahorros | M92: 230-85893- 8 | N92: 567 78 | O92: 2910906778 | P92: =+_xlfn.XLOOKUP(O92,'[3]Benef Primera fecha '!$C:$C,'[3]Benef Primera fecha '!$E:$E,0) -> 20000000 | Q92: 0 | R92: =+(P92+Q92) -> 20000000 | S92: 0.12 | T92: =(R92/(1+S92))*S92 -> 2142857.1 | U92: 20000000 | V92: 0 | W92: =+V92/(1+$S92)*$S92 -> 0 | X92: =+W92*40% -> 0 | Y92: =+W92*60% -> 0 | Z92: =_xlfn.XLOOKUP(O92,'[4]2DO TRIMESTRE'!$C:$C,'[4]2DO TRIMESTRE'!$I:$I,0,0) -> 0 | AA92: =+Z92/(1+$S92)*$S92 -> 0 | AB92: =+AA92*40% -> 0 | AC92: =+AA92*60% -> 0 | AD92: 0 | AE92: =+AD92/(1+$S92)*$S92 -> 0 | AF92: =+AE92*40% -> 0 | AG92: =+AE92*60% -> 0 | AH92: 0 | AI92: =+AH92/(1+$S92)*$S92 -> 0 | AJ92: =+AI92*40% -> 0 | AK92: =+AI92*60% -> 0 | AL92: 2142857 | AM92: =W92+AA92+AE92+AI92 -> 0
A93: 87 | B93: 2022 | C93: INSTITUTO COLOMBIANO DE CRÉDITO EDUCATIVO Y ESTUDIOS TÈNICOS EN EL EXTERIOR - ICETEX | D93: 475-INSTITUTO COLOMBIANO DE CRÉDITO EDUCATIVO Y ESTUDIOS TÈNICOS EN EL EXTERIOR - ICETEX | E93: Contrato | F93: 44589 | G93: 45684 | H93: =+(G93-F93)/90 -> 12.166667 | I93: En Ejecución | J93: Sin Observaciones | K93: OCCIDENTE | L93: Cuenta de ahorros | M93: 230-89731-6 | N93: 567 94 | O93: 2910906794 | P93: 588925908 | Q93: 1003999 | R93: =+(P93+Q93) -> 589929907 | S93: 0 | T93: =(R93/(1+S93))*S93 -> 0 | U93: 0 | V93: 0 | W93: =+V93/(1+$S93)*$S93 -> 0 | X93: =+W93*40% -> 0 | Y93: =+W93*60% -> 0 | Z93: =_xlfn.XLOOKUP(O93,'[4]2DO TRIMESTRE'!$C:$C,'[4]2DO TRIMESTRE'!$I:$I,0,0) -> 0 | AA93: =+Z93/(1+$S93)*$S93 -> 0 | AB93: =+AA93*40% -> 0 | AC93: =+AA93*60% -> 0 | AD93: 0 | AE93: =+AD93/(1+$S93)*$S93 -> 0 | AF93: =+AE93*40% -> 0 | AG93: =+AE93*60% -> 0 | AH93: 0 | AI93: =+AH93/(1+$S93)*$S93 -> 0 | AJ93: =+AI93*40% -> 0 | AK93: =+AI93*60% -> 0 | AL93: 0 | AM93: =W93+AA93+AE93+AI93 -> 0 | AN93: Proyecto sin beneficio institucional estipulado en el presupuesto | AO93: Proyecto sin beneficio institucional estipulado en el presupuesto
A94: 88 | B94: 2022 | C94: CONCEJO MUNICIPAL DE MOSQUERA | D94: 18-CONCEJO MUNICIPAL DE MOSQUERA | E94: Contrato | F94: 44589 | G94: 44647 | H94: =+(G94-F94)/90 -> 0.64444444 | I94: Liquidado | J94: Sin Observaciones | K94: OCCIDENTE | L94: Cuenta de ahorros | M94: 230-85893- 8 | N94: 567 79 | O94: 2910906779 | P94: =+_xlfn.XLOOKUP(O94,'[3]Benef Primera fecha '!$C:$C,'[3]Benef Primera fecha '!$E:$E,0) -> 39000000 | Q94: 0 | R94: =+(P94+Q94) -> 39000000 | S94: 0.12 | T94: =(R94/(1+S94))*S94 -> 4178571.4 | U94: 39000000 | V94: 0 | W94: =+V94/(1+$S94)*$S94 -> 0 | X94: =+W94*40% -> 0 | Y94: =+W94*60% -> 0 | Z94: =_xlfn.XLOOKUP(O94,'[4]2DO TRIMESTRE'!$C:$C,'[4]2DO TRIMESTRE'!$I:$I,0,0) -> 0 | AA94: =+Z94/(1+$S94)*$S94 -> 0 | AB94: =+AA94*40% -> 0 | AC94: =+AA94*60% -> 0 | AD94: 0 | AE94: =+AD94/(1+$S94)*$S94 -> 0 | AF94: =+AE94*40% -> 0 | AG94: =+AE94*60% -> 0 | AH94: 0 | AI94: =+AH94/(1+$S94)*$S94 -> 0 | AJ94: =+AI94*40% -> 0 | AK94: =+AI94*60% -> 0 | AL94: 4178571 | AM94: =W94+AA94+AE94+AI94 -> 0
A95: 89 | B95: 2022 | C95: FIDUPREVISORA S.A. | D95: 80740-011-FIDUPREVISORA S.A. | E95: Contrato | F95: 44589 | G95: 44997 | H95: =+(G95-F95)/90 -> 4.5333333 | I95: En Ejecución | J95: Sin Observaciones | K95: OCCIDENTE | L95: Cuenta de ahorros | M95: 230-85893- 8 | N95: 567 83 | O95: 2910906783 | P95: 170613762 | Q95: 0 | R95: =+(P95+Q95) -> 170613762 | S95: 0 | T95: =(R95/(1+S95))*S95 -> 0 | U95: 0 | V95: 0 | W95: =+V95/(1+$S95)*$S95 -> 0 | X95: =+W95*40% -> 0 | Y95: =+W95*60% -> 0 | Z95: =_xlfn.XLOOKUP(O95,'[4]2DO TRIMESTRE'!$C:$C,'[4]2DO TRIMESTRE'!$I:$I,0,0) -> 0 | AA95: =+Z95/(1+$S95)*$S95 -> 0 | AB95: =+AA95*40% -> 0 | AC95: =+AA95*60% -> 0 | AD95: 0 | AE95: =+AD95/(1+$S95)*$S95 -> 0 | AF95: =+AE95*40% -> 0 | AG95: =+AE95*60% -> 0 | AH95: 0 | AI95: =+AH95/(1+$S95)*$S95 -> 0 | AJ95: =+AI95*40% -> 0 | AK95: =+AI95*60% -> 0 | AL95: 0 | AM95: =W95+AA95+AE95+AI95 -> 0 | AN95: Proyecto sin beneficio institucional estipulado en el presupuesto | AO95: Proyecto sin beneficio institucional estipulado en el presupuesto
A96: 90 | B96: 2022 | C96: SERVICIO NACIONAL DE APRENDIZAJE - SENA | D96: CO1.PCCNTR.3451677-SERVICIO NACIONAL DE APRENDIZAJE - SENA | E96: Contrato | F96: 44589 | G96: 45684 | H96: =+(G96-F96)/90 -> 12.166667 | I96: En Ejecución | J96: Sin Observaciones | K96: OCCIDENTE | L96: Cuenta Corriente | M96: 230-89517-9 | N96: 75 02 | O96: 2453017502 | P96: =+_xlfn.XLOOKUP(O96,'[3]Benef Primera fecha '!$C:$C,'[3]Benef Primera fecha '!$E:$E,0) -> 5408592000 | Q96: 0 | R96: =+(P96+Q96) -> 5408592000 | S96: 0.12 | T96: =(R96/(1+S96))*S96 -> 579492000 | U96: 3245155200 | V96: 0 | W96: =+V96/(1+$S96)*$S96 -> 0 | X96: =+W96*40% -> 0 | Y96: =+W96*60% -> 0 | Z96: =_xlfn.XLOOKUP(O96,'[4]2DO TRIMESTRE'!$C:$C,'[4]2DO TRIMESTRE'!$I:$I,0,0) -> 0 | AA96: =+Z96/(1+$S96)*$S96 -> 0 | AB96: =+AA96*40% -> 0 | AC96: =+AA96*60% -> 0 | AD96: 0 | AE96: =+AD96/(1+$S96)*$S96 -> 0 | AF96: =+AE96*40% -> 0 | AG96: =+AE96*60% -> 0 | AH96: 0 | AI96: =+AH96/(1+$S96)*$S96 -> 0 | AJ96: =+AI96*40% -> 0 | AK96: =+AI96*60% -> 0 | AL96: 358776831 | AM96: =W96+AA96+AE96+AI96 -> 0
A97: 91 | B97: 2022 | C97: CONCEJO MUNICIPAL DE CHÍA | D97: CO1.PCCNTR.3540718-CONCEJO MUNICIPAL DE CHÍA | E97: Contrato | F97: 44589 | G97: 44681 | H97: =+(G97-F97)/90 -> 1.0222222 | I97: Liquidado | J97: Sin Observaciones | K97: OCCIDENTE | L97: Cuenta de ahorros | M97: 230-85893- 8 | N97: 567 82 | O97: 2910906782 | P97: 20000000 | Q97: 0 | R97: =+(P97+Q97) -> 20000000 | S97: 0.12 | T97: =(R97/(1+S97))*S97 -> 2142857.1 | U97: 20000000 | V97: 0 | W97: =+V97/(1+$S97)*$S97 -> 0 | X97: =+W97*40% -> 0 | Y97: =+W97*60% -> 0 | Z97: =_xlfn.XLOOKUP(O97,'[4]2DO TRIMESTRE'!$C:$C,'[4]2DO TRIMESTRE'!$I:$I,0,0) -> 0 | AA97: =+Z97/(1+$S97)*$S97 -> 0 | AB97: =+AA97*40% -> 0 | AC97: =+AA97*60% -> 0 | AD97: 0 | AE97: =+AD97/(1+$S97)*$S97 -> 0 | AF97: =+AE97*40% -> 0 | AG97: =+AE97*60% -> 0 | AH97: 0 | AI97: =+AH97/(1+$S97)*$S97 -> 0 | AJ97: =+AI97*40% -> 0 | AK97: =+AI97*60% -> 0 | AL97: 2142857 | AM97: =W97+AA97+AE97+AI97 -> 0
A98: 92 | B98: 2022 | C98: CONCEJO MUNICIPAL DE FUNZA | D98: CPS-036-CONCEJO MUNICIPAL DE FUNZA | E98: Contrato | F98: 44589 | G98: 44647 | H98: =+(G98-F98)/90 -> 0.64444444 | I98: Liquidado | J98: Sin Observaciones | K98: OCCIDENTE | L98: Cuenta de ahorros | M98: 230-85893- 8 | N98: 567 80 | O98: 2910906780 | P98: =+_xlfn.XLOOKUP(O98,'[3]Benef Primera fecha '!$C:$C,'[3]Benef Primera fecha '!$E:$E,0) -> 39000000 | Q98: 0 | R98: =+(P98+Q98) -> 39000000 | S98: 0.12 | T98: =(R98/(1+S98))*S98 -> 4178571.4 | U98: 39000000 | V98: 0 | W98: =+V98/(1+$S98)*$S98 -> 0 | X98: =+W98*40% -> 0 | Y98: =+W98*60% -> 0 | Z98: =_xlfn.XLOOKUP(O98,'[4]2DO TRIMESTRE'!$C:$C,'[4]2DO TRIMESTRE'!$I:$I,0,0) -> 0 | AA98: =+Z98/(1+$S98)*$S98 -> 0 | AB98: =+AA98*40% -> 0 | AC98: =+AA98*60% -> 0 | AD98: 0 | AE98: =+AD98/(1+$S98)*$S98 -> 0 | AF98: =+AE98*40% -> 0 | AG98: =+AE98*60% -> 0 | AH98: 0 | AI98: =+AH98/(1+$S98)*$S98 -> 0 | AJ98: =+AI98*40% -> 0 | AK98: =+AI98*60% -> 0 | AL98: 4178571 | AM98: =W98+AA98+AE98+AI98 -> 0
A99: 93 | B99: 2022 | C99: UNIVERSIDAD DISTRITAL FRANCISCO JOSÉ DE CALDAS - UD | D99: FAC-TECNO-8050-UNIVERSIDAD DISTRITAL FRANCISCO JOSÉ DE CALDAS - UD | E99: Curso Propio | F99: 44600 | G99: 44688 | H99: =+(G99-F99)/90 -> 0.97777778 | I99: Liquidado | J99: Sin Observaciones | K99: OCCIDENTE | L99: Cuenta de ahorros | M99: 230-85718-7 | N99: 580 50 | O99: 2910908050 | P99: 40884750 | Q99: 10902599 | R99: =+(P99+Q99) -> 51787349 | S99: 0.13636364 | T99: =(R99/(1+S99))*S99 -> 6214482 | U99: 0 | V99: 0 | W99: =+V99/(1+$S99)*$S99 -> 0 | X99: =+W99*40% -> 0 | Y99: =+W99*60% -> 0 | Z99: =_xlfn.XLOOKUP(O99,'[4]2DO TRIMESTRE'!$C:$C,'[4]2DO TRIMESTRE'!$I:$I,0,0) -> 0 | AA99: =+Z99/(1+$S99)*$S99 -> 0 | AB99: =+AA99*40% -> 0 | AC99: =+AA99*60% -> 0 | AD99: 0 | AE99: =+AD99/(1+$S99)*$S99 -> 0 | AF99: =+AE99*40% -> 0 | AG99: =+AE99*60% -> 0 | AH99: 0 | AI99: =+AH99/(1+$S99)*$S99 -> 0 | AJ99: =+AI99*40% -> 0 | AK99: =+AI99*60% -> 0 | AL99: 0 | AM99: =W99+AA99+AE99+AI99 -> 0
A100: 94 | B100: 2022 | C100: UNIVERSIDAD DISTRITAL FRANCISCO JOSÉ DE CALDAS - UD | D100: FAC-MED-8051-UNIVERSIDAD DISTRITAL FRANCISCO JOSÉ DE CALDAS - UD | E100: Curso Propio | F100: 44608 | H100: =+(G100-F100)/90 -> -495.64444 | I100: Liquidado | J100: Sin Observaciones | K100: OCCIDENTE | L100: Cuenta de ahorros | M100: 230-85718-7 | N100: 580 51 | O100: 2910908051 | P100: 102300000 | Q100: 46544000 | R100: =+(P100+Q100) -> 148844000 | S100: 0.13636364 | T100: =(R100/(1+S100))*S100 -> 17861280 | U100: 0 | V100: 0 | W100: =+V100/(1+$S100)*$S100 -> 0 | X100: =+W100*40% -> 0 | Y100: =+W100*60% -> 0 | Z100: =_xlfn.XLOOKUP(O100,'[4]2DO TRIMESTRE'!$C:$C,'[4]2DO TRIMESTRE'!$I:$I,0,0) -> 0 | AA100: =+Z100/(1+$S100)*$S100 -> 0 | AB100: =+AA100*40% -> 0 | AC100: =+AA100*60% -> 0 | AD100: 0 | AE100: =+AD100/(1+$S100)*$S100 -> 0 | AF100: =+AE100*40% -> 0 | AG100: =+AE100*60% -> 0 | AH100: 0 | AI100: =+AH100/(1+$S100)*$S100 -> 0 | AJ100: =+AI100*40% -> 0 | AK100: =+AI100*60% -> 0 | AL100: 0 | AM100: =W100+AA100+AE100+AI100 -> 0
A101: 95 | B101: 2022 | C101: UNIVERSIDAD DISTRITAL FRANCISCO JOSÉ DE CALDAS - UD | D101: FAC-TECNO-8053-UNIVERSIDAD DISTRITAL FRANCISCO JOSÉ DE CALDAS - UD | E101: Curso Propio | F101: 44610 | G101: 44974 | H101: =+(G101-F101)/90 -> 4.0444444 | I101: Liquidado | J101: Sin Observaciones | K101: OCCIDENTE | L101: Cuenta de ahorros | M101: 230-85718-7 | N101: 580 53 | O101: 2910908053 | P101: =+_xlfn.XLOOKUP(O101,'[3]Benef Primera fecha '!$C:$C,'[3]Benef Primera fecha '!$E:$E,0) -> 191412500 | Q101: 139861000 | R101: =+(P101+Q101) -> 331273500 | S101: 0.12 | T101: 39752820 | U101: 331273500 | V101: 0 | W101: =+V101/(1+$S101)*$S101 -> 0 | X101: =+W101*40% -> 0 | Y101: =+W101*60% -> 0 | Z101: =_xlfn.XLOOKUP(O101,'[4]2DO TRIMESTRE'!$C:$C,'[4]2DO TRIMESTRE'!$I:$I,0,0) -> 0 | AA101: =+Z101/(1+$S101)*$S101 -> 0 | AB101: =+AA101*40% -> 0 | AC101: =+AA101*60% -> 0 | AD101: 0 | AE101: =+AD101/(1+$S101)*$S101 -> 0 | AF101: =+AE101*40% -> 0 | AG101: =+AE101*60% -> 0 | AH101: 0 | AI101: =+AH101/(1+$S101)*$S101 -> 0 | AJ101: =+AI101*40% -> 0 | AK101: =+AI101*60% -> 0 | AL101: 39752820 | AM101: =W101+AA101+AE101+AI101 -> 0
...

Sheet ILUD
E1: FORMATO LIQUIDACIÓN BENEFICIO INSTITUCIONAL | J1: Código: GRF-FR-041
E2: Macroproceso: Gestión de Recursos | J2: Versión: 01
E3: Proceso: Gestión de Recursos Financieros | J3: Fecha de Aprobación: 2025/07/02
A5: BENEFICIO INSTITUCIONAL DEL 01 DE ABRIL AL 30 DE JUNIO DEL 2026 | R5: 1 TRIMESTRE | V5: 2 TRIMESTRE | Z5: 3 TRIMESTRE | AD5: 4 TRIMESTRE
A6: ITEM | B6: VIGENCIA | C6: ENTIDAD CONTRATANTE | D6: NOMBRE PROYECTO | E6: DURACION EN TRIMESTRES | F6: ESTADO | G6: ENTIDAD BANCARIA DEPOSITARIA DE LOS RECURSOS | H6: TIPO DE CUENTA | I6: N° CUENTA | J6: N° CENTRO DE COSTOS ASIGNADO | K6: CÓDIGO CONTABLE | L6: VALOR PRESUPUESTO MATRICULAS | M6: VALOR ADICIONES | N6: VALOR TOTAL PRESUPUESTO MATRICULAS | O6: % DE B.I. AUTORIZADO - SEGÚN PRESUPUESTO | P6: BENEFICIO TOTAL PRESUPUESTADO | Q6: TOTAL INGRESOS A LA FECHA | R6: VALOR RECAUDO DEL TRIMESTRE 1 | S6: BENEFICIO TOTAL A DISTRIBUIR EN EL TRIMESTRE LIQUIDADO | T6: IDEXUD 40% | U6: UNIVERSIDAD 60% | V6: VALOR RECAUDO DEL TRIMESTRE 2 | W6: BENEFICIO TOTAL A DISTRIBUIR EN EL TRIMESTRE LIQUIDADO | X6: IDEXUD 40% | Y6: UNIVERSIDAD 60% | Z6: VALOR RECAUDO DEL TRIMESTRE 3 | AA6: BENEFICIO TOTAL A DISTRIBUIR EN EL TRIMESTRE LIQUIDADO | AB6: IDEXUD 40% | AC6: UNIVERSIDAD 60% | AD6: VALOR RECAUDO DEL TRIMESTRE 4 | AE6: BENEFICIO TOTAL A DISTRIBUIR EN EL TRIMESTRE LIQUIDADO | AF6: IDEXUD 40% | AG6: UNIVERSIDAD 60% | AH6: BENEFICIO TOTAL APROPIADO (ACUMULADO) A LA FECHA | AI6: VALOR TOTAL DE B.I. EN LA VIGENCIA | AJ6: NOTAS PRIMER TRIMESTRE
A7: 1 | B7: 2 | C7: UNIVERSIDAD DISTRITAL | D7: ILUD -2025 | E7: 4 | F7: Terminado | G7: OCCIDENTE | H7: Cuenta de ahorros | I7: 230-86428-2 | J7: 564 01 | K7: 2910906401 | L7: 6086762486 | M7: 0 | N7: =+(L7+M7) -> 6086762486 | O7: 0.12 | P7: 730411498 | Q7: 5150315931 | R7: 952797582 | S7: =(+R7*O7) -> 1.1433571e+08 | T7: =+S7*40% -> 45734284 | U7: =+S7*60% -> 68601426 | V7: 0 | W7: =+V7*O7 -> 0 | X7: =+W7*40% -> 0 | Y7: =+W7*60% -> 0 | Z7: 0 | AA7: =+Z7*$O7 -> 0 | AB7: =+AA7*40% -> 0 | AC7: =+AA7*60% -> 0 | AD7: 0 | AE7: =+AD7*$O7 -> 0 | AF7: =+AE7*40% -> 0 | AG7: =+AE7*60% -> 0 | AH7: 6.1803791e+08 | AI7: =S7+W7+AA7+AE7 -> 1.1433571e+08 | AJ7: Corresponde al trim 4 del 2025
A8: 2 | B8: 2025 | C8: UNIVERSIDAD DISTRITAL | D8: ILUD -2026 | E8: 4 | F8: En ejecucion | G8: OCCIDENTE | H8: Cuenta de ahorros | I8: 230-86428-2 | J8: 564 01 | K8: 2910906401 | L8: 5912107000 | M8: 0 | N8: =+(L8+M8) -> 5912107000 | O8: 0.12 | P8: 709452840 | Q8: 1090888710 | R8: 0 | S8: =(+R8*O8) -> 0 | T8: =+S8*40% -> 0 | U8: =+S8*60% -> 0 | V8: 1090888710 | W8: =+V8*O8 -> 1.3090665e+08 | X8: =+W8*40% -> 52362658 | Y8: =+W8*60% -> 78543987 | Z8: 0 | AA8: =+Z8*$O8 -> 0 | AB8: =+AA8*40% -> 0 | AC8: =+AA8*60% -> 0 | AD8: 0 | AE8: =+AD8*$O8 -> 0 | AF8: =+AE8*40% -> 0 | AG8: =+AE8*60% -> 0 | AH8: =S8+W8+AA8+AE8 -> 1.3090665e+08 | AI8: =S8+W8+AA8+AE8 -> 1.3090665e+08 | AJ8: Corresponde al trim 1 del 2026
B9: TOTALES | R9: =SUM(R7) -> 952797582 | S9: =SUM(S7) -> 1.1433571e+08 | T9: =SUM(T7) -> 45734284 | U9: =SUM(U7) -> 68601426 | V9: =SUM(V7:V8) -> 1090888710 | W9: =SUM(W7:W8) -> 1.3090665e+08 | X9: =SUM(X7:X8) -> 52362658 | Y9: =SUM(Y7:Y8) -> 78543987 | AA9: =SUM(AA7:AA7) -> 0 | AB9: =+AA9*40% -> 0 | AC9: =+AA9*60% -> 0 | AD9: =SUM(AD7) -> 0 | AE9: =SUM(AE7:AE7) -> 0 | AF9: =SUM(AF7:AF7) -> 0 | AG9: =SUM(AG7:AG7) -> 0 | AI9: =SUM(AI7:AI8) -> 2.4524236e+08

Sheet Conversión
A1: Estado Convenio / Contrato | B1: Observación al estado | C1: Estado | D1: Tipo de Cuenta
A2: Suscrito | B2: Suspendido | C2: Aprobado recaudo | D2: Cuenta de ahorros
A3: En Ejecución | B3: Litigio | C3: En Ejecución | D3: Cuenta Corriente
A4: Terminado | B4: Sin Observaciones | C4: Terminado
A5: Liquidado | C5: Liquidado
A6: Cierre Financiero | C6: Cierre Financiero
