Workbook
Name IPC: #REF!
Name IPC: #REF!
Name IPC: #REF!
Name IPC: #REF!
Name IPC: #REF!

Sheet EJECUCIÓN
C2: INFORME DE EJECUCIÓN MENSUAL DE GASTOS E INVERSIÓN
C3: UNIVERSIDAD DISTRITAL FRANCISCO JOSÉ DE CALDAS
C4: AGOSTO 2026
F8: =+F13-F9 -> 0 | G8: =+G13-G9 -> 0 | H8: =+H13-H9 -> 0 | I8: =+I13-I9 -> 0 | J8: =+J13-J9 -> 0 | K8: =+K13-K9 -> 0 | L8: =+L13-L9 -> 0 | M8: =+M13-M9 -> 0 | ... O8: =+O13-O9 -> 0
F9: 548567755000 | G9: 14194792521 | H9: 119748855067 | I9: 668316610067 | J9: 37765169384 | K9: 443925954879 | L9: 59277792200 | M9: 411524952140 | N9: 34399054883 | O9: 316933439339
C10: RUBRO PRESUPUESTAL | J10: DISPONIBILIDADES | L10: COMPROMISOS | N10: GIROS | P10: % DE EJECUCIÓN
A11: POSPRE | B11: CÓDIGO SICAPITAL | C11: CÓDIGO | D11: CENTRO DE COSTOS | E11: NOMBRE | F11: PRESUPUESTO INICIAL 2026 RES CSU 024-2025 | G11: MODIFICACIONES | I11: VIGENTE | J11: MES | K11: ACUMULADO | L11: MES | M11: ACUMULADO | N11: MES | O11: ACUMULADO
G12: MES | H12: ACUMULADO
B13: 3 | E13: GASTOS | F13: =+F14+F877 -> 548567755000 | G13: =+G14+G877 -> 14194792521 | H13: =+H14+H877 -> 119748855067 | I13: =+I14+I877 -> 668316610067 | J13: =+J14+J877 -> 37765169384 | K13: =+K14+K877 -> 443925954879 | L13: =+L14+L877 -> 59277792200 | M13: =+M14+M877 -> 411524952140 | ... O13: =+O14+O877 -> 316933439339 | P13: =IFERROR((M13/I13),0) -> 0.61576347
A14: O21 | B14: 3-01 | C14: 2.1 | E14: Funcionamiento | F14: =+F15+F350+F840+F858+F864 -> 505039654000 | G14: =+G15+G350+G840+G858+G864 -> 12533518796 | H14: =+H15+H350+H840+H858+H864 -> 108948092774 | I14: =+I15+I350+I840+I858+I864 -> 613987746774 | J14: =+J15+J350+J840+J858+J864 -> 30729102067 | K14: =+K15+K350+K840+K858+K864 -> 423175367995 | L14: =+L15+L350+L840+L858+L864 -> 55845987005 | M14: =+M15+M350+M840+M858+M864 -> 397629315710 | ... O14: =+O15+O350+O840+O858+O864 -> 308766636586 | P14: =IFERROR((M14/I14),0) -> 0.64761767
A15: O211 | B15: 3-01-001 | C15: 2.1.1 | E15: Gastos de personal | F15: =+F16+F135 -> 339732327000 | G15: =+G16+G135 -> 100199760 | H15: =+H16+H135 -> 9670653489 | I15: =+I16+I135 -> 349402980489 | J15: =+J16+J135 -> 15102353662 | K15: =+K16+K135 -> 236417976510 | L15: =+L16+L135 -> 24845761871 | M15: =+M16+M135 -> 221684160977 | ... O15: =+O16+O135 -> 181789079665 | P15: =IFERROR((M15/I15),0) -> 0.63446557
A16: O21101 | B16: 3-01-001-01 | C16: 2.1.1.01 | E16: Planta de personal permanente | F16: =+F17+F61+F100 -> 253420178000 | G16: =+G17+G61+G100 -> 0 | H16: =+H17+H61+H100 -> -3558522635 | I16: =+I17+I61+I100 -> 249861655365 | J16: =+J17+J61+J100 -> 14056853662 | K16: =+K17+K61+K100 -> 138296753791 | L16: =+L17+L61+L100 -> 14361667706 | M16: =+M17+M61+M100 -> 137856783596 | ... O16: =+O17+O61+O100 -> 132784407292 | P16: =IFERROR((M16/I16),0) -> 0.55173245
A17: O2110101 | B17: 3-01-001-01-01 | C17: 2.1.1.01.01 | E17: Factores constitutivos de salario | F17: =+F18+F56+F52 -> 183865598000 | G17: =+G18+G56+G52 -> 0 | H17: =+H18+H56+H52 -> -1834185350 | I17: =+I18+I56+I52 -> 182031412650 | J17: =+J18+J56+J52 -> 11012166320 | K17: =+K18+K56+K52 -> 96431716152 | L17: =+L18+L56+L52 -> 11108317798 | M17: =+M18+M56+M52 -> 96153501032 | ... O17: =+O18+O56+O52 -> 96102235345 | P17: =IFERROR((M17/I17),0) -> 0.52822477
A18: O2110101001 | C18: 2.1.1.01.01.001 | F18: =+F19+F24+F27+F30+F33+F36+F40+F49 -> 170051047000 | G18: =+G19+G24+G27+G30+G33+G36+G40+G49 -> 0 | H18: =+H19+H24+H27+H30+H33+H36+H40+H49 -> -882993704 | I18: =+I19+I24+I27+I30+I33+I36+I40+I49 -> 169168053296 | J18: =+J19+J24+J27+J30+J33+J36+J40+J49 -> 10928069092 | K18: =+K19+K24+K27+K30+K33+K36+K40+K49 -> 85139230520 | L18: =+L19+L24+L27+L30+L33+L36+L40+L49 -> 11014774851 | M18: =+M19+M24+M27+M30+M33+M36+M40+M49 -> 84913790848 | ... O18: =+O19+O24+O27+O30+O33+O36+O40+O49 -> 84874336780 | P18: =IFERROR((M18/I18),0) -> 0.50194933
A19: O211010100101 | B19: 3-01-001-01-01-11 | C19: 2.1.1.01.01.001.01 | E19: Sueldo básico | F19: =+F20 -> 137847199000 | G19: =+G20 -> 0 | H19: =+H20 -> -882993704 | I19: =+I20 -> 136964205296 | J19: =+J20 -> 9973723386 | K19: =+K20 -> 79163609530 | L19: =+L20 -> 10009017915 | M19: =+M20 -> 79046667804 | ... O19: =+O20 -> 79022119760 | P19: =IFERROR((M19/I19),0) -> 0.57713377
B20: 3-01-001-01-01-11 | C20: 2.1.1.01.01.001.01 | E20: Sueldo Básico | F20: =SUM(F21:F23) -> 137847199000 | G20: =SUM(G21:G23) -> 0 | H20: =SUM(H21:H23) -> -882993704 | I20: =SUM(I21:I23) -> 136964205296 | J20: =SUM(J21:J23) -> 9973723386 | K20: =SUM(K21:K23) -> 79163609530 | L20: =SUM(L21:L23) -> 10009017915 | M20: =SUM(M21:M23) -> 79046667804 | ... O20: =SUM(O21:O23) -> 79022119760 | P20: =IFERROR((M20/I20),0) -> 0.57713377
B21: 3-01-001-01-01-11-0001-00 | C21: 2.1.1.01.01.001.01.1 | D21: A9902 | E21: Sueldo Básico Administrativos | F21: 17229718000 | G21: 0 | H21: 0 | I21: 17229718000 | J21: 1254694045 | K21: 10032071169 | L21: 1260814251 | M21: 9976421376 | N21: 1262337512 | O21: 9970301170 | P21: =IFERROR((M21/I21),0) -> 0.57902407
B22: 3-01-001-01-01-11-0002-00 | C22: 2.1.1.01.01.001.01.2 | D22: A9901 | E22: Sueldo Básico Docentes | F22: 119040611000 | G22: 0 | H22: -882993704 | I22: 118157617296 | J22: 8612498726 | K22: 68133103310 | L22: 8626482424 | M22: 68071811377 | N22: 8626482424 | O22: 68053383539 | P22: =IFERROR((M22/I22),0) -> 0.57611022
B23: 3-01-001-01-01-11-0003-00 | C23: 2.1.1.01.01.001.01.3 | D23: A9903 | E23: Sueldo Trabajadores Oficiales | F23: 1576870000 | G23: 0 | H23: 0 | I23: 1576870000 | J23: 106530615 | K23: 998435051 | L23: 121721240 | M23: 998435051 | N23: 121721240 | O23: 998435051 | P23: =IFERROR((M23/I23),0) -> 0.63317525
A24: O211010100102 | B24: 3-01-001-01-01-12 | C24: 2.1.1.01.01.001.02 | E24: Horas extras, dominicales, festivos y recargos | F24: =+F25 -> 232386000 | G24: =+G25 -> 0 | H24: =+H25 -> 0 | I24: =+I25 -> 232386000 | J24: =+J25 -> 13695907 | K24: =+K25 -> 110111232 | L24: =+L25 -> 13695907 | M24: =+M25 -> 110111232 | ... O24: =+O25 -> 110111232 | P24: =IFERROR((M24/I24),0) -> 0.47382903
A25: O211010100102 | B25: 3-01-001-01-01-12 | C25: 2.1.1.01.01.001.02 | E25: Horas extras, dominicales, festivos y recargos | F25: =+F26 -> 232386000 | G25: =+G26 -> 0 | H25: =+H26 -> 0 | I25: =+I26 -> 232386000 | J25: =+J26 -> 13695907 | K25: =+K26 -> 110111232 | L25: =+L26 -> 13695907 | M25: =+M26 -> 110111232 | ... O25: =+O26 -> 110111232 | P25: =IFERROR((M25/I25),0) -> 0.47382903
B26: 3-01-001-01-01-12-0001-00 | C26: 2.1.1.01.01.001.02.1 | D26: A9902 | E26: Horas Extras, Dominicales, Festivos, Administrativos | F26: 232386000 | G26: 0 | H26: 0 | I26: 232386000 | J26: 13695907 | K26: 110111232 | L26: 13695907 | M26: 110111232 | N26: 13695907 | O26: 110111232 | P26: =IFERROR((M26/I26),0) -> 0.47382903
A27: O211010100103 | B27: 3-01-001-01-01-13 | C27: 2.1.1.01.01.001.03 | E27: Gastos de representación | F27: =+F28 -> 879556000 | G27: =+G28 -> 0 | H27: =+H28 -> 0 | I27: =+I28 -> 879556000 | J27: =+J28 -> 68936516 | K27: =+K28 -> 540508571 | L27: =+L28 -> 68936516 | M27: =+M28 -> 540508571 | ... O27: =+O28 -> 540508571 | P27: =IFERROR((M27/I27),0) -> 0.61452434
A28: O211010100103 | B28: 3-01-001-01-01-13 | C28: 2.1.1.01.01.001.03 | E28: Gastos de representación | F28: =+F29 -> 879556000 | G28: =+G29 -> 0 | H28: =+H29 -> 0 | I28: =+I29 -> 879556000 | J28: =+J29 -> 68936516 | K28: =+K29 -> 540508571 | L28: =+L29 -> 68936516 | M28: =+M29 -> 540508571 | ... O28: =+O29 -> 540508571 | P28: =IFERROR((M28/I28),0) -> 0.61452434
B29: 3-01-001-01-01-13-0001-00 | C29: 2.1.1.01.01.001.03.1 | D29: A9902 | E29: Gastos de Representación Administrativos | F29: 879556000 | G29: 0 | H29: 0 | I29: 879556000 | J29: 68936516 | K29: 540508571 | L29: 68936516 | M29: 540508571 | N29: 68936516 | O29: 540508571 | P29: =IFERROR((M29/I29),0) -> 0.61452434
A30: O211010100104 | B30: 3-01-001-01-01-14 | C30: 2.1.1.01.01.001.04 | E30: Subsidio de alimentación | F30: =+F31 -> 89520000 | G30: =+G31 -> 0 | H30: =+H31 -> 0 | I30: =+I31 -> 89520000 | J30: =+J31 -> 6554973 | K30: =+K31 -> 57670022 | L30: =+L31 -> 6554973 | M30: =+M31 -> 57670022 | ... O30: =+O31 -> 57670022 | P30: =IFERROR((M30/I30),0) -> 0.64421383
A31: O211010100104 | B31: 3-01-001-01-01-14 | C31: 2.1.1.01.01.001.04 | E31: Subsidio de alimentación | F31: =+F32 -> 89520000 | G31: =+G32 -> 0 | H31: =+H32 -> 0 | I31: =+I32 -> 89520000 | J31: =+J32 -> 6554973 | K31: =+K32 -> 57670022 | L31: =+L32 -> 6554973 | M31: =+M32 -> 57670022 | ... O31: =+O32 -> 57670022 | P31: =IFERROR((M31/I31),0) -> 0.64421383
A32: O211010100104 | B32: 3-01-001-01-01-14-0000-00 | C32: 2.1.1.01.01.001.04 | D32: A9903 | E32: Subsidio de alimentación | F32: 89520000 | G32: 0 | H32: 0 | I32: 89520000 | J32: 6554973 | K32: 57670022 | L32: 6554973 | M32: 57670022 | N32: 6554973 | O32: 57670022 | P32: =IFERROR((M32/I32),0) -> 0.64421383
A33: O211010100105 | B33: 3-01-001-01-01-15 | C33: 2.1.1.01.01.001.05 | E33: Auxilio de transporte | F33: =+F34 -> 92533000 | G33: =+G34 -> 0 | H33: =+H34 -> 0 | I33: =+I34 -> 92533000 | J33: =+J34 -> 6050899 | K33: =+K34 -> 53235236 | L33: =+L34 -> 6050899 | M33: =+M34 -> 53235236 | ... O33: =+O34 -> 53235236 | P33: =IFERROR((M33/I33),0) -> 0.57531082
A34: O211010100105 | B34: 3-01-001-01-01-15 | C34: 2.1.1.01.01.001.05 | E34: Auxilio de transporte | F34: =+F35 -> 92533000 | G34: =+G35 -> 0 | H34: =+H35 -> 0 | I34: =+I35 -> 92533000 | J34: =+J35 -> 6050899 | K34: =+K35 -> 53235236 | L34: =+L35 -> 6050899 | M34: =+M35 -> 53235236 | ... O34: =+O35 -> 53235236 | P34: =IFERROR((M34/I34),0) -> 0.57531082
A35: O211010100105 | B35: 3-01-001-01-01-15-0000-00 | C35: 2.1.1.01.01.001.05 | D35: A9903 | E35: Auxilio de transporte | F35: 92533000 | G35: 0 | H35: 0 | I35: 92533000 | J35: 6050899 | K35: 53235236 | L35: 6050899 | M35: 53235236 | N35: 6050899 | O35: 53235236 | P35: =IFERROR((M35/I35),0) -> 0.57531082
A36: O211010100107 | B36: 3-01-001-01-01-17 | C36: 2.1.1.01.01.001.07 | E36: Bonificación por servicios prestados | F36: =+F37 -> 4044818000 | G36: =+G37 -> 0 | H36: =+H37 -> 0 | I36: =+I37 -> 4044818000 | J36: =+J37 -> 521204267 | K36: =+K37 -> 2397348052 | L36: =+L37 -> 523352825 | M36: =+M37 -> 2385667678 | ... O36: =+O37 -> 2383519120 | P36: =IFERROR((M36/I36),0) -> 0.58980841
A37: O211010100107 | B37: 3-01-001-01-01-17 | C37: 2.1.1.01.01.001.07 | E37: Bonificación por servicios prestados | F37: =SUM(F38:F39) -> 4044818000 | G37: =SUM(G38:G39) -> 0 | H37: =SUM(H38:H39) -> 0 | I37: =SUM(I38:I39) -> 4044818000 | J37: =SUM(J38:J39) -> 521204267 | K37: =SUM(K38:K39) -> 2397348052 | L37: =SUM(L38:L39) -> 523352825 | M37: =SUM(M38:M39) -> 2385667678 | ... O37: =SUM(O38:O39) -> 2383519120 | P37: =IFERROR((M37/I37),0) -> 0.58980841
B38: 3-01-001-01-01-17-0001-00 | C38: 2.1.1.01.01.001.07.1 | D38: A9902 | E38: Bonificación por Servicios Prestados Administrativos | F38: 572800000 | G38: 0 | H38: 0 | I38: 572800000 | J38: 13717222 | K38: 367856662 | L38: 15865780 | M38: 361243215 | N38: 15298562 | O38: 359094657 | P38: =IFERROR((M38/I38),0) -> 0.63066204
B39: 3-01-001-01-01-17-0002-00 | C39: 2.1.1.01.01.001.07.2 | D39: A9901 | E39: Bonificación por Servicios Prestados Docentes | F39: 3472018000 | G39: 0 | H39: 0 | I39: 3472018000 | J39: 507487045 | K39: 2029491390 | L39: 507487045 | M39: 2024424463 | N39: 507487045 | O39: 2024424463 | P39: =IFERROR((M39/I39),0) -> 0.58306854
A40: O211010100108 | B40: 3-01-001-01-01-18 | C40: 2.1.1.01.01.001.08 | E40: Prestaciones sociales | F40: =+F41+F45 -> 22992436000 | G40: =+G41+G45 -> 0 | H40: =+H41+H45 -> 0 | I40: =+I41+I45 -> 22992436000 | J40: =+J41+J45 -> 23942177 | K40: =+K41+K45 -> 390355453 | L40: =+L41+L45 -> 73204849 | M40: =+M41+M45 -> 293537881 | ... O40: =+O41+O45 -> 280780415 | P40: =IFERROR((M40/I40),0) -> 0.012766715
A41: O21101010010801 | B41: 3-01-001-01-01-18-0001 | C41: 2.1.1.01.01.001.08.01 | E41: Prima de navidad | F41: =SUM(F42:F44) -> 14300185000 | G41: =SUM(G42:G44) -> 0 | H41: =SUM(H42:H44) -> 0 | I41: =SUM(I42:I44) -> 14300185000 | J41: =SUM(J42:J44) -> 0 | K41: =SUM(K42:K44) -> 119171591 | L41: =SUM(L42:L44) -> 25898987 | M41: =SUM(M42:M44) -> 81636831 | ... O41: =SUM(O42:O44) -> 79143364 | P41: =IFERROR((M41/I41),0) -> 0.0057087954
B42: 3-01-001-01-01-18-0001-01 | C42: 2.1.1.01.01.001.08.01.1 | D42: A9902 | E42: Prima de Navidad Administrativos | F42: 2287604000 | G42: 0 | H42: 0 | I42: 2287604000 | J42: 0 | K42: 10705113 | L42: 889473 | M42: 10705113 | N42: 0 | O42: 9815640 | P42: =IFERROR((M42/I42),0) -> 0.0046796181
B43: 3-01-001-01-01-18-0001-02 | C43: 2.1.1.01.01.001.08.01.2 | D43: A9901 | E43: Prima de Navidad Docentes | F43: 11659997000 | G43: 0 | H43: 0 | I43: 11659997000 | J43: 0 | K43: 99081875 | L43: 15624911 | M43: 61547115 | N43: 15624911 | O43: 59943121 | P43: =IFERROR((M43/I43),0) -> 0.0052784846
B44: 3-01-001-01-01-18-0001-03 | C44: 2.1.1.01.01.001.08.01.3 | D44: A9903 | E44: Prima de Navidad Trabajadores Oficiales | F44: 352584000 | G44: 0 | H44: 0 | I44: 352584000 | J44: 0 | K44: 9384603 | L44: 9384603 | M44: 9384603 | N44: 9384603 | O44: 9384603 | P44: =IFERROR((M44/I44),0) -> 0.026616645
A45: O21101010010802 | B45: 3-01-001-01-01-18-0002 | C45: 2.1.1.01.01.001.08.02 | E45: Prima de vacaciones | F45: =SUM(F46:F48) -> 8692251000 | G45: =SUM(G46:G48) -> 0 | H45: =SUM(H46:H48) -> 0 | I45: =SUM(I46:I48) -> 8692251000 | J45: =SUM(J46:J48) -> 23942177 | K45: =SUM(K46:K48) -> 271183862 | L45: =SUM(L46:L48) -> 47305862 | M45: =SUM(M46:M48) -> 211901050 | ... O45: =SUM(O46:O48) -> 201637051 | P45: =IFERROR((M45/I45),0) -> 0.024378156
B46: 3-01-001-01-01-18-0002-01 | C46: 2.1.1.01.01.001.08.02.1 | D46: A9902 | E46: Prima de Vacaciones Administrativos | F46: 1123826000 | G46: 0 | H46: 0 | I46: 1123826000 | J46: 23942177 | K46: 142040649 | L46: 28702337 | M46: 124497523 | N46: 28243422 | O46: 119737363 | P46: =IFERROR((M46/I46),0) -> 0.11078007
B47: 3-01-001-01-01-18-0002-02 | C47: 2.1.1.01.01.001.08.02.2 | D47: A9901 | E47: Prima de Vacaciones Docentes | F47: 7310152000 | G47: 0 | H47: 0 | I47: 7310152000 | J47: 0 | K47: 83669104 | L47: 9160703 | M47: 41929418 | N47: 9160703 | O47: 36425579 | P47: =IFERROR((M47/I47),0) -> 0.0057357792
B48: 3-01-001-01-01-18-0002-03 | C48: 2.1.1.01.01.001.08.02.3 | D48: A9903 | E48: Prima de Vacaciones Trabajadores Oficiales | F48: 258273000 | G48: 0 | H48: 0 | I48: 258273000 | J48: 0 | K48: 45474109 | L48: 9442822 | M48: 45474109 | N48: 9442822 | O48: 45474109 | P48: =IFERROR((M48/I48),0) -> 0.17606993
A49: O211010100109 | B49: 3-01-001-01-01-19 | C49: 2.1.1.01.01.001.09 | E49: Prima técnica salarial | F49: =+F51 -> 3872599000 | G49: =+G51 -> 0 | H49: =+H51 -> 0 | I49: =+I51 -> 3872599000 | J49: =+J51 -> 313960967 | K49: =+K51 -> 2426392424 | L49: =+L51 -> 313960967 | M49: =+M51 -> 2426392424 | ... O49: =+O51 -> 2426392424 | P49: =IFERROR((M49/I49),0) -> 0.62655401
A50: O211010100109 | B50: 3-01-001-01-01-19 | C50: 2.1.1.01.01.001.09 | E50: Prima técnica salarial | F50: =+F51 -> 3872599000 | G50: =+G51 -> 0 | H50: =+H51 -> 0 | I50: =+I51 -> 3872599000 | J50: =+J51 -> 313960967 | K50: =+K51 -> 2426392424 | L50: =+L51 -> 313960967 | M50: =+M51 -> 2426392424 | ... O50: =+O51 -> 2426392424 | P50: =IFERROR((M50/I50),0) -> 0.62655401
B51: 3-01-001-01-01-19-0001-00 | C51: 2.1.1.01.01.001.09.1 | D51: A9902 | E51: Prima Técnica Administrativos | F51: 3872599000 | G51: 0 | H51: 0 | I51: 3872599000 | J51: 313960967 | K51: 2426392424 | L51: 313960967 | M51: 2426392424 | N51: 313960967 | O51: 2426392424 | P51: =IFERROR((M51/I51),0) -> 0.62655401
A52: O211010100204 | B52: 3-01-001-01-01-24 | C52: 2.1.1.01.01.002.04 | E52: Prima semestral | F52: =SUM(F53:F55) -> 12787384000 | G52: =SUM(G53:G55) -> 0 | H52: =SUM(H53:H55) -> -951191646 | I52: =SUM(I53:I55) -> 11836192354 | J52: =SUM(J53:J55) -> 13553703 | K52: =SUM(K53:K55) -> 10720612031 | L52: =SUM(L53:L55) -> 22999422 | M52: =SUM(M53:M55) -> 10667836583 | ... O52: =SUM(O53:O55) -> 10656024964 | P52: =IFERROR((M52/I52),0) -> 0.90128956
B53: 3-01-001-01-01-24-0001-01 | C53: 2.1.1.01.01.002.04.1 | D53: A9902 | E53: Prima Semestral Administrativos | F53: 2421498000 | G53: 0 | H53: -250000000 | I53: 2171498000 | J53: 0 | K53: 2101834677 | L53: 6654632 | M53: 2071924372 | N53: 9472980 | O53: 2065269740 | P53: =IFERROR((M53/I53),0) -> 0.95414519
B54: 3-01-001-01-01-24-0001-02 | C54: 2.1.1.01.01.002.04.2 | D54: A9901 | E54: Prima Semetral Docentes | F54: 10097192000 | G54: 0 | H54: -701191646 | I54: 9396000354 | J54: 13553703 | K54: 8380016359 | L54: 13553703 | M54: 8357151216 | N54: 13553703 | O54: 8351994229 | P54: =IFERROR((M54/I54),0) -> 0.88943709
B55: 3-01-001-01-01-24-0001-03 | C55: 2.1.1.01.01.002.04.3 | D55: A9903 | E55: Prima Semestral Trabajadores Oficiales | F55: 268694000 | G55: 0 | H55: 0 | I55: 268694000 | J55: 0 | K55: 238760995 | L55: 2791087 | M55: 238760995 | N55: 2791087 | O55: 238760995 | P55: =IFERROR((M55/I55),0) -> 0.88859816
A56: O2110101002 | B56: 3-01-001-01-01-22 | C56: 2.1.1.01.01.002 | E56: Factores salariales especiales | F56: =+F57 -> 1027167000 | G56: =+G57 -> 0 | H56: =+H57 -> 0 | I56: =+I57 -> 1027167000 | J56: =+J57 -> 70543525 | K56: =+K57 -> 571873601 | L56: =+L57 -> 70543525 | M56: =+M57 -> 571873601 | ... O56: =+O57 -> 571873601 | P56: =IFERROR((M56/I56),0) -> 0.55674842
A57: O211010100212 | B57: 3-01-001-01-01-22-0012 | C57: 2.1.1.01.01.002.12 | E57: Prima de antigüedad | F57: =+F58 -> 1027167000 | G57: =+G58 -> 0 | H57: =+H58 -> 0 | I57: =+I58 -> 1027167000 | J57: =+J58 -> 70543525 | K57: =+K58 -> 571873601 | L57: =+L58 -> 70543525 | M57: =+M58 -> 571873601 | ... O57: =+O58 -> 571873601 | P57: =IFERROR((M57/I57),0) -> 0.55674842
A58: O21101010021201 | B58: 3-01-001-01-01-22-0012-0 | C58: 2.1.1.01.01.002.12.01 | E58: Beneficios a los empleados a corto plazo | F58: =SUM(F59:F60) -> 1027167000 | G58: =SUM(G59:G60) -> 0 | H58: =SUM(H59:H60) -> 0 | I58: =SUM(I59:I60) -> 1027167000 | J58: =SUM(J59:J60) -> 70543525 | K58: =SUM(K59:K60) -> 571873601 | L58: =SUM(L59:L60) -> 70543525 | M58: =SUM(M59:M60) -> 571873601 | ... O58: =SUM(O59:O60) -> 571873601 | P58: =IFERROR((M58/I58),0) -> 0.55674842
B59: 3-01-001-01-01-22-0012-01 | C59: 2.1.1.01.01.002.12.02.1 | D59: A9902 | E59: Prima de Antigüedad Administrativos | F59: 831631000 | G59: 0 | H59: 0 | I59: 831631000 | J59: 57128210 | K59: 454843346 | L59: 57128210 | M59: 454843346 | N59: 57128210 | O59: 454843346 | P59: =IFERROR((M59/I59),0) -> 0.54692928
B60: 3-01-001-01-01-22-0012-02 | C60: 2.1.1.01.01.002.12.02.2 | D60: A9903 | E60: Prima de Antigüedad Trabajadores Oficiales | F60: 195536000 | G60: 0 | H60: 0 | I60: 195536000 | J60: 13415315 | K60: 117030255 | L60: 13415315 | M60: 117030255 | N60: 13415315 | O60: 117030255 | P60: =IFERROR((M60/I60),0) -> 0.59851002
A61: O2110102 | B61: 3-01-001-01-02 | C61: 2.1.1.01.02 | E61: Contribuciones inherentes a la nómina | F61: =+F62+F71+F76+F85+F90+F95 -> 59417330000 | G61: =+G62+G71+G76+G85+G90+G95 -> 0 | H61: =+H62+H71+H76+H85+H90+H95 -> -1691811575 | I61: =+I62+I71+I76+I85+I90+I95 -> 57725518425 | J61: =+J62+J71+J76+J85+J90+J95 -> 2977235683 | K61: =+K62+K71+K76+K85+K90+K95 -> 33720259572 | L61: =+L62+L71+L76+L85+L90+L95 -> 2980111806 | M61: =+M62+M71+M76+M85+M90+M95 -> 33668998994 | ... O61: =+O62+O71+O76+O85+O90+O95 -> 33658728141 | P61: =IFERROR((M61/I61),0) -> 0.58326023
A62: O2110102001 | B62: 3-01-001-01-02-01 | C62: 2.1.1.01.02.001 | E62: Aportes a la seguridad social en pensiones | F62: =+F63+F67 -> 17859361000 | G62: =+G63+G67 -> 0 | H62: =+H63+H67 -> 0 | I62: =+I63+I67 -> 17859361000 | J62: =+J63+J67 -> 1271149275 | K62: =+K63+K67 -> 8777285325 | L62: =+L63+L67 -> 1271149275 | M62: =+M63+M67 -> 8777285325 | ... O62: =+O63+O67 -> 8777285325 | P62: =IFERROR((M62/I62),0) -> 0.49146693
A63: O211010200101 | B63: 3-01-001-01-02-01-0001 | C63: 2.1.1.01.02.001.01 | E63: Aportes a la seguridad social en pensiones públicas | F63: =SUM(F64:F66) -> 15547240000 | G63: =SUM(G64:G66) -> 0 | H63: =SUM(H64:H66) -> 0 | I63: =SUM(I64:I66) -> 15547240000 | J63: =SUM(J64:J66) -> 1145963475 | K63: =SUM(K64:K66) -> 7929885000 | L63: =SUM(L64:L66) -> 1145963475 | M63: =SUM(M64:M66) -> 7929885000 | ... O63: =SUM(O64:O66) -> 7929885000 | P63: =IFERROR((M63/I63),0) -> 0.51005098
B64: 3-01-001-01-02-01-0001-01 | C64: 2.1.1.01.02.001.01.1 | D64: A9902 | E64: Pensiones Públicas Administrativos | F64: 2417048000 | G64: 0 | H64: 0 | I64: 2417048000 | J64: 177741825 | K64: 1218869700 | L64: 177741825 | M64: 1218869700 | N64: 177741825 | O64: 1218869700 | P64: =IFERROR((M64/I64),0) -> 0.5042803
B65: 3-01-001-01-02-01-0001-02 | C65: 2.1.1.01.02.001.01.2 | D65: A9901 | E65: Pensiones Públicas Docentes | F65: 12937333000 | G65: 0 | H65: 0 | I65: 12937333000 | J65: 950505300 | K65: 6602986500 | L65: 950505300 | M65: 6602986500 | N65: 950505300 | O65: 6602986500 | P65: =IFERROR((M65/I65),0) -> 0.51038236
B66: 3-01-001-01-02-01-0001-03 | C66: 2.1.1.01.02.001.01.3 | D66: A9903 | E66: Pensiones Públicas Trabajadores Oficiales | F66: 192859000 | G66: 0 | H66: 0 | I66: 192859000 | J66: 17716350 | K66: 108028800 | L66: 17716350 | M66: 108028800 | N66: 17716350 | O66: 108028800 | P66: =IFERROR((M66/I66),0) -> 0.56014394
A67: O211010200102 | B67: 3-01-001-01-02-01-0002 | C67: 2.1.1.01.02.001.02 | E67: Aportes a la seguridad social en pensiones privadas | F67: =SUM(F68:F70) -> 2312121000 | G67: =SUM(G68:G70) -> 0 | H67: =SUM(H68:H70) -> 0 | I67: =SUM(I68:I70) -> 2312121000 | J67: =SUM(J68:J70) -> 125185800 | K67: =SUM(K68:K70) -> 847400325 | L67: =SUM(L68:L70) -> 125185800 | M67: =SUM(M68:M70) -> 847400325 | ... O67: =SUM(O68:O70) -> 847400325 | P67: =IFERROR((M67/I67),0) -> 0.36650345
B68: 3-01-001-01-02-01-0002-01 | C68: 2.1.1.01.02.001.02.1 | D68: A9902 | E68: Pensiones Privadas Administrativos | F68: 507885000 | G68: 0 | H68: 0 | I68: 507885000 | J68: 33607950 | K68: 224876625 | L68: 33607950 | M68: 224876625 | N68: 33607950 | O68: 224876625 | P68: =IFERROR((M68/I68),0) -> 0.44277076
B69: 3-01-001-01-02-01-0002-02 | C69: 2.1.1.01.02.001.02.2 | D69: A9901 | E69: Pensiones Privadas Docentes | F69: 1764182000 | G69: 0 | H69: 0 | I69: 1764182000 | J69: 90301725 | K69: 613718400 | L69: 90301725 | M69: 613718400 | N69: 90301725 | O69: 613718400 | P69: =IFERROR((M69/I69),0) -> 0.34787703
B70: 3-01-001-01-02-01-0002-03 | C70: 2.1.1.01.02.001.02.3 | D70: A9903 | E70: Pensiones Privadas Trabajadores Oficiales | F70: 40054000 | G70: 0 | H70: 0 | I70: 40054000 | J70: 1276125 | K70: 8805300 | L70: 1276125 | M70: 8805300 | N70: 1276125 | O70: 8805300 | P70: =IFERROR((M70/I70),0) -> 0.21983572
A71: O2110102002 | B71: 3-01-001-01-02-02 | C71: 2.1.1.01.02.002 | E71: Aportes a la seguridad social en salud | F71: =+F72 -> 12565168000 | G71: =+G72 -> 0 | H71: =+H72 -> 0 | I71: =+I72 -> 12565168000 | J71: =+J72 -> 900141908 | K71: =+K72 -> 6215452900 | L71: =+L72 -> 900141908 | M71: =+M72 -> 6215452900 | ... O71: =+O72 -> 6215452900 | P71: =IFERROR((M71/I71),0) -> 0.49465737
A72: O211010200202 | B72: 3-01-001-01-02-02-0002 | C72: 2.1.1.01.02.002.02 | E72: Aportes a la seguridad social en salud privada | F72: =SUM(F73:F75) -> 12565168000 | G72: =SUM(G73:G75) -> 0 | H72: =SUM(H73:H75) -> 0 | I72: =SUM(I73:I75) -> 12565168000 | J72: =SUM(J73:J75) -> 900141908 | K72: =SUM(K73:K75) -> 6215452900 | L72: =SUM(L73:L75) -> 900141908 | M72: =SUM(M73:M75) -> 6215452900 | ... O72: =SUM(O73:O75) -> 6215452900 | P72: =IFERROR((M72/I72),0) -> 0.49465737
B73: 3-01-001-01-02-02-0002-01 | C73: 2.1.1.01.02.002.02.1 | D73: A9902 | E73: Salud Privada Administrativos | F73: 2002645000 | G73: 0 | H73: 0 | I73: 2002645000 | J73: 149707032 | K73: 1022735164 | L73: 149707032 | M73: 1022735164 | N73: 149707032 | O73: 1022735164 | P73: =IFERROR((M73/I73),0) -> 0.51069219
B74: 3-01-001-01-02-02-0002-02 | C74: 2.1.1.01.02.002.02.2 | D74: A9901 | E74: Salud Privada Docentes | F74: 10413573000 | G74: 0 | H74: 0 | I74: 10413573000 | J74: 736981756 | K74: 5109958200 | L74: 736981756 | M74: 5109958200 | N74: 736981756 | O74: 5109958200 | P74: =IFERROR((M74/I74),0) -> 0.49070172
B75: 3-01-001-01-02-02-0002-03 | C75: 2.1.1.01.02.002.02.3 | D75: A9903 | E75: Salud Privada Trabajadores Oficiales | F75: 148950000 | G75: 0 | H75: 0 | I75: 148950000 | J75: 13453120 | K75: 82759536 | L75: 13453120 | M75: 82759536 | N75: 13453120 | O75: 82759536 | P75: =IFERROR((M75/I75),0) -> 0.55561958
A76: O2110102003 | B76: 3-01-001-01-02-03 | C76: 2.1.1.01.02.003 | E76: Aportes de cesantías | F76: =+F77+F81 -> 15273366000 | G76: =+G77+G81 -> 0 | H76: =+H77+H81 -> -1691811575 | I76: =+I77+I81 -> 13581554425 | J76: =+J77+J81 -> 0 | K76: =+K77+K81 -> 12419650347 | L76: =+L77+L81 -> 2876123 | M76: =+M77+M81 -> 12368389769 | ... O76: =+O77+O81 -> 12358118916 | P76: =IFERROR((M76/I76),0) -> 0.91067557
A77: O211010200301 | B77: 3-01-001-01-02-03-0001 | C77: 2.1.1.01.02.003.01 | E77: Aportes de cesantías a fondos públicos | F77: =SUM(F78:F80) -> 8087997000 | G77: =SUM(G78:G80) -> 0 | H77: =SUM(H78:H80) -> -100000000 | I77: =SUM(I78:I80) -> 7987997000 | J77: =SUM(J78:J80) -> 0 | K77: =SUM(K78:K80) -> 7558379361 | L77: =SUM(L78:L80) -> 0 | M77: =SUM(M78:M80) -> 7535079637 | ... O77: =SUM(O78:O80) -> 7524808784 | P77: =IFERROR((M77/I77),0) -> 0.94330026
B78: 3-01-001-01-02-03-0001-01 | C78: 2.1.1.01.02.003.01.1 | D78: A9902 | E78: Cesantías Fondos Públicos Administrativos | F78: 1245634000 | G78: 0 | H78: -50000000 | I78: 1195634000 | J78: 0 | K78: 1103288053 | L78: 0 | M78: 1102117925 | N78: 1369432 | O78: 1101691733 | P78: =IFERROR((M78/I78),0) -> 0.92178537
B79: 3-01-001-01-02-03-0001-02 | C79: 2.1.1.01.02.003.01.2 | D79: A9901 | E79: Cesantías Fondos Públicos Docentes | F79: 6694782000 | G79: 0 | H79: -50000000 | I79: 6644782000 | J79: 0 | K79: 6386981699 | L79: 0 | M79: 6364852103 | N79: 0 | O79: 6355007442 | P79: =IFERROR((M79/I79),0) -> 0.95787222
B80: 3-01-001-01-02-03-0001-03 | C80: 2.1.1.01.02.003.01.3 | D80: A9903 | E80: Cesantías Fondos Públicos Trabajadores Oficiales | F80: 147581000 | G80: 0 | H80: 0 | I80: 147581000 | J80: 0 | K80: 68109609 | L80: 0 | M80: 68109609 | N80: 0 | O80: 68109609 | P80: =IFERROR((M80/I80),0) -> 0.46150662
A81: O211010200302 | B81: 3-01-001-01-02-03-0002 | C81: 2.1.1.01.02.003.02 | E81: Aportes de cesantías a fondos privados | F81: =SUM(F82:F84) -> 7185369000 | G81: =SUM(G82:G84) -> 0 | H81: =SUM(H82:H84) -> -1591811575 | I81: =SUM(I82:I84) -> 5593557425 | J81: =SUM(J82:J84) -> 0 | K81: =SUM(K82:K84) -> 4861270986 | L81: =SUM(L82:L84) -> 2876123 | M81: =SUM(M82:M84) -> 4833310132 | ... O81: =SUM(O82:O84) -> 4833310132 | P81: =IFERROR((M81/I81),0) -> 0.86408519
B82: 3-01-001-01-02-03-0002-01 | C82: 2.1.1.01.02.003.02.1 | D82: A9902 | E82: Cesantías Fondos Privados Administrativos | F82: 1104619000 | G82: 0 | H82: -275997151 | I82: 828621849 | J82: 0 | K82: 451587234 | L82: 905549 | M82: 451587234 | N82: 905549 | O82: 451587234 | P82: =IFERROR((M82/I82),0) -> 0.54498591
B83: 3-01-001-01-02-03-0002-02 | C83: 2.1.1.01.02.003.02.2 | D83: A9901 | E83: Cesantías Fondos Privados Docentes | F83: 5936882000 | G83: 0 | H83: -1320814424 | I83: 4616067576 | J83: 0 | K83: 4264216325 | L83: 1970574 | M83: 4236255471 | N83: 1970574 | O83: 4236255471 | P83: =IFERROR((M83/I83),0) -> 0.91771955
B84: 3-01-001-01-02-03-0002-03 | C84: 2.1.1.01.02.003.02.3 | D84: A9903 | E84: Cesantías Fondos Privados Trabajadores Oficiales | F84: 143868000 | G84: 0 | H84: 5000000 | I84: 148868000 | J84: 0 | K84: 145467427 | L84: 0 | M84: 145467427 | N84: 0 | O84: 145467427 | P84: =IFERROR((M84/I84),0) -> 0.97715713
A85: O2110102004 | B85: 3-01-001-01-02-04 | C85: 2.1.1.01.02.004 | E85: Aportes a cajas de compensación familiar | F85: =+F86 -> 7329466000 | G85: =+G86 -> 0 | H85: =+H86 -> 0 | I85: =+I86 -> 7329466000 | J85: =+J86 -> 429266600 | K85: =+K86 -> 3387810800 | L85: =+L86 -> 429266600 | M85: =+M86 -> 3387810800 | ... O85: =+O86 -> 3387810800 | P85: =IFERROR((M85/I85),0) -> 0.46221796
A86: O211010200401 | B86: 3-01-001-01-02-04-0001 | C86: 2.1.1.01.02.004.01 | E86: Compensar | F86: =SUM(F87:F89) -> 7329466000 | G86: =SUM(G87:G89) -> 0 | H86: =SUM(H87:H89) -> 0 | I86: =SUM(I87:I89) -> 7329466000 | J86: =SUM(J87:J89) -> 429266600 | K86: =SUM(K87:K89) -> 3387810800 | L86: =SUM(L87:L89) -> 429266600 | M86: =SUM(M87:M89) -> 3387810800 | ... O86: =SUM(O87:O89) -> 3387810800 | P86: =IFERROR((M86/I86),0) -> 0.46221796
B87: 3-01-001-01-02-04-0001-01 | C87: 2.1.1.01.02.004.01.1 | D87: A9902 | E87: Caja de Compensación Administrativos | F87: 1166734000 | G87: 0 | H87: 0 | I87: 1166734000 | J87: 71488300 | K87: 570625300 | L87: 71488300 | M87: 570625300 | N87: 71488300 | O87: 570625300 | P87: =IFERROR((M87/I87),0) -> 0.48907917
B88: 3-01-001-01-02-04-0001-02 | C88: 2.1.1.01.02.004.01.2 | D88: A9901 | E88: Caja de Compensación Docentes | F88: 6063199000 | G88: 0 | H88: 0 | I88: 6063199000 | J88: 349848300 | K88: 2763196800 | L88: 349848300 | M88: 2763196800 | N88: 349848300 | O88: 2763196800 | P88: =IFERROR((M88/I88),0) -> 0.45573249
B89: 3-01-001-01-02-04-0001-03 | C89: 2.1.1.01.02.004.01.3 | D89: A9903 | E89: Caja de Compensación Trabajadores Oficiales | F89: 99533000 | G89: 0 | H89: 0 | I89: 99533000 | J89: 7930000 | K89: 53988700 | L89: 7930000 | M89: 53988700 | N89: 7930000 | O89: 53988700 | P89: =IFERROR((M89/I89),0) -> 0.5424201
A90: O2110102005 | B90: 3-01-001-01-02-05 | C90: 2.1.1.01.02.005 | E90: Aportes generales al sistema de riesgos laborales | F90: =+F91 -> 957874000 | G90: =+G91 -> 0 | H90: =+H91 -> 0 | I90: =+I91 -> 957874000 | J90: =+J91 -> 54716500 | K90: =+K91 -> 379133800 | L90: =+L91 -> 54716500 | M90: =+M91 -> 379133800 | ... O90: =+O91 -> 379133800 | P90: =IFERROR((M90/I90),0) -> 0.39580759
A91: O211010200501 | B91: 3-01-001-01-02-05-0001 | C91: 2.1.1.01.02.005.01 | E91: Aportes generales al sistema de riesgos laborales públicos | F91: =SUM(F92:F94) -> 957874000 | G91: =SUM(G92:G94) -> 0 | H91: =SUM(H92:H94) -> 0 | I91: =SUM(I92:I94) -> 957874000 | J91: =SUM(J92:J94) -> 54716500 | K91: =SUM(K92:K94) -> 379133800 | L91: =SUM(L92:L94) -> 54716500 | M91: =SUM(M92:M94) -> 379133800 | ... O91: =SUM(O92:O94) -> 379133800 | P91: =IFERROR((M91/I91),0) -> 0.39580759
B92: 3-01-001-01-02-05-0001-01 | C92: 2.1.1.01.02.005.01.1 | D92: A9902 | E92: Riesgos Laborales Administrativos | F92: 153638000 | G92: 0 | H92: 0 | I92: 153638000 | J92: 8968900 | K92: 62328100 | L92: 8968900 | M92: 62328100 | N92: 8968900 | O92: 62328100 | P92: =IFERROR((M92/I92),0) -> 0.40568154
B93: 3-01-001-01-02-05-0001-02 | C93: 2.1.1.01.02.005.01.2 | D93: A9901 | E93: Riesgos Laborales Docentes | F93: 791247000 | G93: 0 | H93: 0 | I93: 791247000 | J93: 44920500 | K93: 311975100 | L93: 44920500 | M93: 311975100 | N93: 44920500 | O93: 311975100 | P93: =IFERROR((M93/I93),0) -> 0.39428282
B94: 3-01-001-01-02-05-0001-03 | C94: 2.1.1.01.02.005.01.3 | D94: A9903 | E94: Riesgos Laborales Trabajadores Oficiales | F94: 12989000 | G94: 0 | H94: 0 | I94: 12989000 | J94: 827100 | K94: 4830600 | L94: 827100 | M94: 4830600 | N94: 827100 | O94: 4830600 | P94: =IFERROR((M94/I94),0) -> 0.3718993
A95: O2110102006 | B95: 3-01-001-01-02-06 | C95: 2.1.1.01.02.006 | E95: Aportes al ICBF | F95: =+F96 -> 5432095000 | G95: =+G96 -> 0 | H95: =+H96 -> 0 | I95: =+I96 -> 5432095000 | J95: =+J96 -> 321961400 | K95: =+K96 -> 2540926400 | L95: =+L96 -> 321961400 | M95: =+M96 -> 2540926400 | ... O95: =+O96 -> 2540926400 | P95: =IFERROR((M95/I95),0) -> 0.46776178
A96: O2110102006 | B96: 3-01-001-01-02-06 | C96: 2.1.1.01.02.006 | E96: Aportes al ICBF | F96: =SUM(F97:F99) -> 5432095000 | G96: =SUM(G97:G99) -> 0 | H96: =SUM(H97:H99) -> 0 | I96: =SUM(I97:I99) -> 5432095000 | J96: =SUM(J97:J99) -> 321961400 | K96: =SUM(K97:K99) -> 2540926400 | L96: =SUM(L97:L99) -> 321961400 | M96: =SUM(M97:M99) -> 2540926400 | ... O96: =SUM(O97:O99) -> 2540926400 | P96: =IFERROR((M96/I96),0) -> 0.46776178
B97: 3-01-001-01-02-06-0001-00 | C97: 2.1.1.01.02.006.1 | D97: A9902 | E97: ICBF Administrativos | F97: 810047000 | G97: 0 | H97: 0 | I97: 810047000 | J97: 53618300 | K97: 427983100 | L97: 53618300 | M97: 427983100 | N97: 53618300 | O97: 427983100 | P97: =IFERROR((M97/I97),0) -> 0.52834354
B98: 3-01-001-01-02-06-0002-00 | C98: 2.1.1.01.02.006.2 | D98: A9901 | E98: ICBF Docentes | F98: 4547399000 | G98: 0 | H98: 0 | I98: 4547399000 | J98: 262395300 | K98: 2072450000 | L98: 262395300 | M98: 2072450000 | N98: 262395300 | O98: 2072450000 | P98: =IFERROR((M98/I98),0) -> 0.45574404
B99: 3-01-001-01-02-06-0003-00 | C99: 2.1.1.01.02.006.3 | D99: A9903 | E99: ICBF Trabajadores Oficiales | F99: 74649000 | G99: 0 | H99: 0 | I99: 74649000 | J99: 5947800 | K99: 40493300 | L99: 5947800 | M99: 40493300 | N99: 5947800 | O99: 40493300 | P99: =IFERROR((M99/I99),0) -> 0.54244933
A100: O2110103 | B100: 3-01-001-01-03 | C100: 2.1.1.01.03 | E100: Remuneraciones no constitutivas de factor salarial | F100: =+F101+F103+F104+F105 -> 10137250000 | G100: =+G101+G103+G104+G105 -> 0 | H100: =+H101+H103+H104+H105 -> -32525710 | I100: =+I101+I103+I104+I105 -> 10104724290 | J100: =+J101+J103+J104+J105 -> 67451659 | K100: =+K101+K103+K104+K105 -> 8144778067 | L100: =+L101+L103+L104+L105 -> 273238102 | M100: =+M101+M103+M104+M105 -> 8034283570 | ... O100: =+O101+O103+O104+O105 -> 3023443806 | P100: =IFERROR((M100/I100),0) -> 0.79510171
A101: O2110103001 | B101: 3-01-001-01-03-01 | C101: 2.1.1.01.03.001 | E101: Prestaciones sociales | F101: =SUM(F102:F102) -> 96799000 | G101: =SUM(G102:G102) -> 0 | H101: =SUM(H102:H102) -> 0 | I101: =SUM(I102:I102) -> 96799000 | J101: =SUM(J102:J102) -> 1550485 | K101: =SUM(K102:K102) -> 11254644 | L101: =SUM(L102:L102) -> 1968415 | M101: =SUM(M102:M102) -> 9894748 | ... O101: =SUM(O102:O102) -> 9476818 | P101: =IFERROR((M101/I101),0) -> 0.10221953
A102: O211010300103 | B102: 3-01-001-01-03-01-0003-00 | C102: 2.1.1.01.03.001.03 | D102: A9902 | E102: Bonificación especial de recreación | F102: 96799000 | G102: 0 | H102: 0 | I102: 96799000 | J102: 1550485 | K102: 11254644 | L102: 1968415 | M102: 9894748 | N102: 1897878 | O102: 9476818 | P102: =IFERROR((M102/I102),0) -> 0.10221953
A103: O2110103005 | B103: 3-01-001-01-03-05-0000-00 | C103: 2.1.1.01.03.005 | D103: A9902 | E103: Reconocimiento por permanencia en el servicio público - Bogotá D.C. | F103: 382816000 | G103: 0 | H103: 0 | I103: 382816000 | J103: 0 | K103: 0 | L103: 0 | M103: 0 | N103: 0 | O103: 0 | P103: =IFERROR((M103/I103),0) -> 0
A104: O2110103068 | B104: 3-01-001-01-03-68-0000-00 | C104: 2.1.1.01.03.068 | D104: A9902 | E104: Prima secretarial | F104: 284402000 | G104: 0 | H104: 0 | I104: 284402000 | J104: 15489585 | K104: 123290497 | L104: 15489585 | M104: 123290497 | N104: 15489585 | O104: 123290497 | P104: =IFERROR((M104/I104),0) -> 0.43350784
...

Sheet FONDO COMÚN
C2: INFORME DE EJECUCIÓN MENSUAL DE GASTOS E INVERSIÓN- FONDO COMÚN
C3: UNIVERSIDAD DISTRITAL FRANCISCO JOSÉ DE CALDAS
C4: AGOSTO 2026
F8: =+F9-F13 -> 0 | G8: =+G9-G13 -> 0 | H8: =+H9-H13 -> 0 | I8: =+I9-I13 -> 0 | J8: =+J9-J13 -> 0 | K8: =+K9-K13 -> 0 | L8: =+L9-L13 -> 0 | M8: =+M9-M13 -> 0 | ... O8: =+O9-O13 -> 0
F9: 505039654000 | G9: 12533518796 | H9: 108948092774 | I9: 613987746774 | J9: 30729102067 | K9: 423175367995 | L9: 55845987005 | M9: 397629315710 | N9: 33348072457 | O9: 308766636586
C10: RUBRO PRESUPUESTAL | F10: APROPIACION | J10: DISPONIBILIDADES | L10: COMPROMISOS | N10: AUTORIZACION DE GIRO | P10: % DE EJECUCIÓN
A11: POSPRE | B11: CÓDIGO SICAPITAL | C11: CÓDIGO | D11: CENTRO DE COSTOS | E11: NOMBRE | F11: PRESUPUESTO INICIAL 2026 RES CSU 024-2025 | G11: MODIFICACIONES | I11: VIGENTE | J11: MES | K11: ACUMULADO | L11: MES | M11: ACUMULADO | N11: MES | O11: ACUMULADO
G12: MES | H12: ACUMULADO
A13: O21 | B13: 3-01 | C13: 2.1 | E13: Funcionamiento | F13: =+F14+F349+F839+F857+F863 -> 505039654000 | G13: =+G14+G349+G839+G857+G863 -> 12533518796 | H13: =+H14+H349+H839+H857+H863 -> 108948092774 | I13: =+I14+I349+I839+I857+I863 -> 613987746774 | J13: =+J14+J349+J839+J857+J863 -> 30729102067 | K13: =+K14+K349+K839+K857+K863 -> 423175367995 | L13: =+L14+L349+L839+L857+L863 -> 55845987005 | M13: =+M14+M349+M839+M857+M863 -> 397629315710 | ... O13: =+O14+O349+O839+O857+O863 -> 308766636586 | P13: =IFERROR((M13/I13),0) -> 0.64761767
A14: O211 | B14: 3-01-001 | C14: 2.1.1 | E14: Gastos de personal | F14: =+F15+F134 -> 339732327000 | G14: =+G15+G134 -> 100199760 | H14: =+H15+H134 -> 9670653489 | I14: =+I15+I134 -> 349402980489 | J14: =+J15+J134 -> 15102353662 | K14: =+K15+K134 -> 236417976510 | L14: =+L15+L134 -> 24845761871 | M14: =+M15+M134 -> 221684160977 | ... O14: =+O15+O134 -> 181789079665 | P14: 0.23740675
A15: O21101 | B15: 3-01-001-01 | C15: 2.1.1.01 | E15: Planta de personal permanente | F15: =+F16+F60+F99 -> 253420178000 | G15: =+G16+G60+G99 -> 0 | H15: =+H16+H60+H99 -> -3558522635 | I15: =+I16+I60+I99 -> 249861655365 | J15: =+J16+J60+J99 -> 14056853662 | K15: =+K16+K60+K99 -> 138296753791 | L15: =+L16+L60+L99 -> 14361667706 | M15: =+M16+M60+M99 -> 137856783596 | ... O15: =+O16+O60+O99 -> 132784407292 | P15: 0.23740675
A16: O2110101 | B16: 3-01-001-01-01 | C16: 2.1.1.01.01 | E16: Factores constitutivos de salario | F16: =+F17+F51 -> 183865598000 | G16: =+G17+G51 -> 0 | H16: =+H17+H51 -> -1834185350 | I16: =+I17+I51 -> 182031412650 | J16: =+J17+J51 -> 11012166320 | K16: =+K17+K51 -> 96431716152 | L16: =+L17+L51 -> 11108317798 | M16: =+M17+M51 -> 96153501032 | ... O16: =+O17+O51 -> 96102235345 | P16: 0.23740675
A17: O2110101001 | C17: 2.1.1.01.01.001 | E17: Factores salariales comunes | F17: =+F18+F23+F26+F29+F32+F35+F39+F48 -> 170051047000 | G17: =+G18+G23+G26+G29+G32+G35+G39+G48 -> 0 | H17: =+H18+H23+H26+H29+H32+H35+H39+H48 -> -882993704 | I17: =+I18+I23+I26+I29+I32+I35+I39+I48 -> 169168053296 | J17: =+J18+J23+J26+J29+J32+J35+J39+J48 -> 10928069092 | K17: =+K18+K23+K26+K29+K32+K35+K39+K48 -> 85139230520 | L17: =+L18+L23+L26+L29+L32+L35+L39+L48 -> 11014774851 | M17: =+M18+M23+M26+M29+M32+M35+M39+M48 -> 84913790848 | ... O17: =+O18+O23+O26+O29+O32+O35+O39+O48 -> 84874336780 | P17: 0.23740675
A18: O211010100101 | B18: 3-01-001-01-01-11 | C18: 2.1.1.01.01.001.01 | E18: Sueldo básico | F18: =+F19 -> 137847199000 | G18: =+G19 -> 0 | H18: =+H19 -> -882993704 | I18: =+I19 -> 136964205296 | J18: =+J19 -> 9973723386 | K18: =+K19 -> 79163609530 | L18: =+L19 -> 10009017915 | M18: =+M19 -> 79046667804 | ... O18: =+O19 -> 79022119760 | P18: 0.23740675
B19: 3-01-001-01-01-11 | C19: 2.1.1.01.01.001.01 | E19: Sueldo Básico | F19: =SUM(F20:F22) -> 137847199000 | G19: =SUM(G20:G22) -> 0 | H19: =SUM(H20:H22) -> -882993704 | I19: =SUM(I20:I22) -> 136964205296 | J19: =SUM(J20:J22) -> 9973723386 | K19: =SUM(K20:K22) -> 79163609530 | L19: =SUM(L20:L22) -> 10009017915 | M19: =SUM(M20:M22) -> 79046667804 | ... O19: =SUM(O20:O22) -> 79022119760 | P19: 0.23740675
B20: 3-01-001-01-01-11-0001-00 | C20: 2.1.1.01.01.001.01.1 | D20: A9902 | E20: Sueldo Básico Administrativos | F20: 17229718000 | G20: 0 | H20: 0 | I20: 17229718000 | J20: 1254694045 | K20: 10032071169 | L20: 1260814251 | M20: 9976421376 | N20: 1262337512 | O20: 9970301170 | P20: 0.23740675
B21: 3-01-001-01-01-11-0002-00 | C21: 2.1.1.01.01.001.01.2 | D21: A9901 | E21: Sueldo Básico Docentes | F21: 119040611000 | G21: 0 | H21: -882993704 | I21: 118157617296 | J21: 8612498726 | K21: 68133103310 | L21: 8626482424 | M21: 68071811377 | N21: 8626482424 | O21: 68053383539 | P21: 0.23740675
B22: 3-01-001-01-01-11-0003-00 | C22: 2.1.1.01.01.001.01.3 | D22: A9903 | E22: Sueldo Trabajadores Oficiales | F22: 1576870000 | G22: 0 | H22: 0 | I22: 1576870000 | J22: 106530615 | K22: 998435051 | L22: 121721240 | M22: 998435051 | N22: 121721240 | O22: 998435051 | P22: 0.23740675
A23: O211010100102 | B23: 3-01-001-01-01-12 | C23: 2.1.1.01.01.001.02 | E23: Horas extras, dominicales, festivos y recargos | F23: =+F24 -> 232386000 | G23: =+G24 -> 0 | H23: =+H24 -> 0 | I23: =+I24 -> 232386000 | J23: =+J24 -> 13695907 | K23: =+K24 -> 110111232 | L23: =+L24 -> 13695907 | M23: =+M24 -> 110111232 | ... O23: =+O24 -> 110111232 | P23: 0.23740675
A24: O211010100102 | B24: 3-01-001-01-01-12 | C24: 2.1.1.01.01.001.02 | E24: Horas extras, dominicales, festivos y recargos | F24: =+F25 -> 232386000 | G24: =+G25 -> 0 | H24: =+H25 -> 0 | I24: =+I25 -> 232386000 | J24: =+J25 -> 13695907 | K24: =+K25 -> 110111232 | L24: =+L25 -> 13695907 | M24: =+M25 -> 110111232 | ... O24: =+O25 -> 110111232 | P24: 0.23740675
B25: 3-01-001-01-01-12-0001-00 | C25: 2.1.1.01.01.001.02.1 | D25: A9902 | E25: Horas Extras, Dominicales, Festivos, Administrativos | F25: 232386000 | G25: 0 | H25: 0 | I25: 232386000 | J25: 13695907 | K25: 110111232 | L25: 13695907 | M25: 110111232 | N25: 13695907 | O25: 110111232 | P25: 0.23740675
A26: O211010100103 | B26: 3-01-001-01-01-13 | C26: 2.1.1.01.01.001.03 | E26: Gastos de representación | F26: =+F27 -> 879556000 | G26: =+G27 -> 0 | H26: =+H27 -> 0 | I26: =+I27 -> 879556000 | J26: =+J27 -> 68936516 | K26: =+K27 -> 540508571 | L26: =+L27 -> 68936516 | M26: =+M27 -> 540508571 | ... O26: =+O27 -> 540508571 | P26: 0.23740675
A27: O211010100103 | B27: 3-01-001-01-01-13 | C27: 2.1.1.01.01.001.03 | E27: Gastos de representación | F27: =+F28 -> 879556000 | G27: =+G28 -> 0 | H27: =+H28 -> 0 | I27: =+I28 -> 879556000 | J27: =+J28 -> 68936516 | K27: =+K28 -> 540508571 | L27: =+L28 -> 68936516 | M27: =+M28 -> 540508571 | ... O27: =+O28 -> 540508571 | P27: 0.23740675
B28: 3-01-001-01-01-13-0001-00 | C28: 2.1.1.01.01.001.03.1 | D28: A9902 | E28: Gastos de Representación Administrativos | F28: 879556000 | G28: 0 | H28: 0 | I28: 879556000 | J28: 68936516 | K28: 540508571 | L28: 68936516 | M28: 540508571 | N28: 68936516 | O28: 540508571 | P28: 0.23740675
A29: O211010100104 | B29: 3-01-001-01-01-14 | C29: 2.1.1.01.01.001.04 | E29: Subsidio de alimentación | F29: =+F30 -> 89520000 | G29: =+G30 -> 0 | H29: =+H30 -> 0 | I29: =+I30 -> 89520000 | J29: =+J30 -> 6554973 | K29: =+K30 -> 57670022 | L29: =+L30 -> 6554973 | M29: =+M30 -> 57670022 | ... O29: =+O30 -> 57670022 | P29: 0.23740675
A30: O211010100104 | B30: 3-01-001-01-01-14 | C30: 2.1.1.01.01.001.04 | E30: Subsidio de alimentación | F30: =+F31 -> 89520000 | G30: =+G31 -> 0 | H30: =+H31 -> 0 | I30: =+I31 -> 89520000 | J30: =+J31 -> 6554973 | K30: =+K31 -> 57670022 | L30: =+L31 -> 6554973 | M30: =+M31 -> 57670022 | ... O30: =+O31 -> 57670022 | P30: 0.23740675
A31: O211010100104 | B31: 3-01-001-01-01-14-0000-00 | C31: 2.1.1.01.01.001.04 | D31: A9903 | E31: Subsidio de alimentación | F31: 89520000 | G31: 0 | H31: 0 | I31: 89520000 | J31: 6554973 | K31: 57670022 | L31: 6554973 | M31: 57670022 | N31: 6554973 | O31: 57670022 | P31: 0.23740675
A32: O211010100105 | B32: 3-01-001-01-01-15 | C32: 2.1.1.01.01.001.05 | E32: Auxilio de transporte | F32: =+F33 -> 92533000 | G32: =+G33 -> 0 | H32: =+H33 -> 0 | I32: =+I33 -> 92533000 | J32: =+J33 -> 6050899 | K32: =+K33 -> 53235236 | L32: =+L33 -> 6050899 | M32: =+M33 -> 53235236 | ... O32: =+O33 -> 53235236 | P32: 0.23740675
A33: O211010100105 | B33: 3-01-001-01-01-15 | C33: 2.1.1.01.01.001.05 | E33: Auxilio de transporte | F33: =+F34 -> 92533000 | G33: =+G34 -> 0 | H33: =+H34 -> 0 | I33: =+I34 -> 92533000 | J33: =+J34 -> 6050899 | K33: =+K34 -> 53235236 | L33: =+L34 -> 6050899 | M33: =+M34 -> 53235236 | ... O33: =+O34 -> 53235236 | P33: 0.23740675
A34: O211010100105 | B34: 3-01-001-01-01-15-0000-00 | C34: 2.1.1.01.01.001.05 | D34: A9903 | E34: Auxilio de transporte | F34: 92533000 | G34: 0 | H34: 0 | I34: 92533000 | J34: 6050899 | K34: 53235236 | L34: 6050899 | M34: 53235236 | N34: 6050899 | O34: 53235236 | P34: 0.23740675
A35: O211010100107 | B35: 3-01-001-01-01-17 | C35: 2.1.1.01.01.001.07 | E35: Bonificación por servicios prestados | F35: =+F36 -> 4044818000 | G35: =+G36 -> 0 | H35: =+H36 -> 0 | I35: =+I36 -> 4044818000 | J35: =+J36 -> 521204267 | K35: =+K36 -> 2397348052 | L35: =+L36 -> 523352825 | M35: =+M36 -> 2385667678 | ... O35: =+O36 -> 2383519120 | P35: 0.23740675
A36: O211010100107 | B36: 3-01-001-01-01-17 | C36: 2.1.1.01.01.001.07 | E36: Bonificación por servicios prestados | F36: =SUM(F37:F38) -> 4044818000 | G36: =SUM(G37:G38) -> 0 | H36: =SUM(H37:H38) -> 0 | I36: =SUM(I37:I38) -> 4044818000 | J36: =SUM(J37:J38) -> 521204267 | K36: =SUM(K37:K38) -> 2397348052 | L36: =SUM(L37:L38) -> 523352825 | M36: =SUM(M37:M38) -> 2385667678 | ... O36: =SUM(O37:O38) -> 2383519120 | P36: 0.23740675
B37: 3-01-001-01-01-17-0001-00 | C37: 2.1.1.01.01.001.07.1 | D37: A9902 | E37: Bonificación por Servicios Prestados Administrativos | F37: 572800000 | G37: 0 | H37: 0 | I37: 572800000 | J37: 13717222 | K37: 367856662 | L37: 15865780 | M37: 361243215 | N37: 15298562 | O37: 359094657 | P37: 0.23740675
B38: 3-01-001-01-01-17-0002-00 | C38: 2.1.1.01.01.001.07.2 | D38: A9901 | E38: Bonificación por Servicios Prestados Docentes | F38: 3472018000 | G38: 0 | H38: 0 | I38: 3472018000 | J38: 507487045 | K38: 2029491390 | L38: 507487045 | M38: 2024424463 | N38: 507487045 | O38: 2024424463 | P38: 0.23740675
A39: O211010100108 | B39: 3-01-001-01-01-18 | C39: 2.1.1.01.01.001.08 | E39: Prestaciones sociales | F39: =+F40+F44 -> 22992436000 | G39: =+G40+G44 -> 0 | H39: =+H40+H44 -> 0 | I39: =+I40+I44 -> 22992436000 | J39: =+J40+J44 -> 23942177 | K39: =+K40+K44 -> 390355453 | L39: =+L40+L44 -> 73204849 | M39: =+M40+M44 -> 293537881 | ... O39: =+O40+O44 -> 280780415 | P39: 0.23740675
A40: O21101010010801 | B40: 3-01-001-01-01-18-0001 | C40: 2.1.1.01.01.001.08.01 | E40: Prima de navidad | F40: =SUM(F41:F43) -> 14300185000 | G40: =SUM(G41:G43) -> 0 | H40: =SUM(H41:H43) -> 0 | I40: =SUM(I41:I43) -> 14300185000 | J40: =SUM(J41:J43) -> 0 | K40: =SUM(K41:K43) -> 119171591 | L40: =SUM(L41:L43) -> 25898987 | M40: =SUM(M41:M43) -> 81636831 | ... O40: =SUM(O41:O43) -> 79143364 | P40: 0.23740675
B41: 3-01-001-01-01-18-0001-01 | C41: 2.1.1.01.01.001.08.01.1 | D41: A9902 | E41: Prima de Navidad Administrativos | F41: 2287604000 | G41: 0 | H41: 0 | I41: 2287604000 | J41: 0 | K41: 10705113 | L41: 889473 | M41: 10705113 | N41: 0 | O41: 9815640 | P41: 0.23740675
B42: 3-01-001-01-01-18-0001-02 | C42: 2.1.1.01.01.001.08.01.2 | D42: A9901 | E42: Prima de Navidad Docentes | F42: 11659997000 | G42: 0 | H42: 0 | I42: 11659997000 | J42: 0 | K42: 99081875 | L42: 15624911 | M42: 61547115 | N42: 15624911 | O42: 59943121 | P42: 0.23740675
B43: 3-01-001-01-01-18-0001-03 | C43: 2.1.1.01.01.001.08.01.3 | D43: A9903 | E43: Prima de Navidad Trabajadores Oficiales | F43: 352584000 | G43: 0 | H43: 0 | I43: 352584000 | J43: 0 | K43: 9384603 | L43: 9384603 | M43: 9384603 | N43: 9384603 | O43: 9384603 | P43: 0.23740675
A44: O21101010010802 | B44: 3-01-001-01-01-18-0002 | C44: 2.1.1.01.01.001.08.02 | E44: Prima de vacaciones | F44: =SUM(F45:F47) -> 8692251000 | G44: =SUM(G45:G47) -> 0 | H44: =SUM(H45:H47) -> 0 | I44: =SUM(I45:I47) -> 8692251000 | J44: =SUM(J45:J47) -> 23942177 | K44: =SUM(K45:K47) -> 271183862 | L44: =SUM(L45:L47) -> 47305862 | M44: =SUM(M45:M47) -> 211901050 | ... O44: =SUM(O45:O47) -> 201637051 | P44: 0.23740675
B45: 3-01-001-01-01-18-0002-01 | C45: 2.1.1.01.01.001.08.02.1 | D45: A9902 | E45: Prima de Vacaciones Administrativos | F45: 1123826000 | G45: 0 | H45: 0 | I45: 1123826000 | J45: 23942177 | K45: 142040649 | L45: 28702337 | M45: 124497523 | N45: 28243422 | O45: 119737363 | P45: 0.23740675
B46: 3-01-001-01-01-18-0002-02 | C46: 2.1.1.01.01.001.08.02.2 | D46: A9901 | E46: Prima de Vacaciones Docentes | F46: 7310152000 | G46: 0 | H46: 0 | I46: 7310152000 | J46: 0 | K46: 83669104 | L46: 9160703 | M46: 41929418 | N46: 9160703 | O46: 36425579 | P46: 0.23740675
B47: 3-01-001-01-01-18-0002-03 | C47: 2.1.1.01.01.001.08.02.3 | D47: A9903 | E47: Prima de Vacaciones Trabajadores Oficiales | F47: 258273000 | G47: 0 | H47: 0 | I47: 258273000 | J47: 0 | K47: 45474109 | L47: 9442822 | M47: 45474109 | N47: 9442822 | O47: 45474109 | P47: 0.23740675
A48: O211010100109 | B48: 3-01-001-01-01-19 | C48: 2.1.1.01.01.001.09 | E48: Prima técnica salarial | F48: =+F50 -> 3872599000 | G48: =+G50 -> 0 | H48: =+H50 -> 0 | I48: =+I50 -> 3872599000 | J48: =+J50 -> 313960967 | K48: =+K50 -> 2426392424 | L48: =+L50 -> 313960967 | M48: =+M50 -> 2426392424 | ... O48: =+O50 -> 2426392424 | P48: 0.23740675
A49: O211010100109 | B49: 3-01-001-01-01-19 | C49: 2.1.1.01.01.001.09 | E49: Prima técnica salarial | F49: =+F50 -> 3872599000 | G49: =+G50 -> 0 | H49: =+H50 -> 0 | I49: =+I50 -> 3872599000 | J49: =+J50 -> 313960967 | K49: =+K50 -> 2426392424 | L49: =+L50 -> 313960967 | M49: =+M50 -> 2426392424 | ... O49: =+O50 -> 2426392424 | P49: 0.23740675
B50: 3-01-001-01-01-19-0001-00 | C50: 2.1.1.01.01.001.09.1 | D50: A9902 | E50: Prima Técnica Administrativos | F50: 3872599000 | G50: 0 | H50: 0 | I50: 3872599000 | J50: 313960967 | K50: 2426392424 | L50: 313960967 | M50: 2426392424 | N50: 313960967 | O50: 2426392424 | P50: 0.23740675
A51: O2110101002 | B51: 3-01-001-01-01-22 | C51: 2.1.1.01.01.002 | E51: Factores salariales especiales | F51: =+F52+F56 -> 13814551000 | G51: =+G52+G56 -> 0 | H51: =+H52+H56 -> -951191646 | I51: =+I52+I56 -> 12863359354 | J51: =+J52+J56 -> 84097228 | K51: =+K52+K56 -> 11292485632 | L51: =+L52+L56 -> 93542947 | M51: =+M52+M56 -> 11239710184 | ... O51: =+O52+O56 -> 11227898565 | P51: 0.23740675
A52: O211010100204 | B52: 3-01-001-01-01-24 | C52: 2.1.1.01.01.002.04 | E52: Prima semestral | F52: =SUM(F53:F55) -> 12787384000 | G52: =SUM(G53:G55) -> 0 | H52: =SUM(H53:H55) -> -951191646 | I52: =SUM(I53:I55) -> 11836192354 | J52: =SUM(J53:J55) -> 13553703 | K52: =SUM(K53:K55) -> 10720612031 | L52: =SUM(L53:L55) -> 22999422 | M52: =SUM(M53:M55) -> 10667836583 | ... O52: =SUM(O53:O55) -> 10656024964 | P52: 0.23740675
B53: 3-01-001-01-01-24-0001-01 | C53: 2.1.1.01.01.002.04.1 | D53: A9902 | E53: Prima Semestral Administrativos | F53: 2421498000 | G53: 0 | H53: -250000000 | I53: 2171498000 | J53: 0 | K53: 2101834677 | L53: 6654632 | M53: 2071924372 | N53: 9472980 | O53: 2065269740 | P53: 0.23740675
B54: 3-01-001-01-01-24-0001-02 | C54: 2.1.1.01.01.002.04.2 | D54: A9901 | E54: Prima Semetral Docentes | F54: 10097192000 | G54: 0 | H54: -701191646 | I54: 9396000354 | J54: 13553703 | K54: 8380016359 | L54: 13553703 | M54: 8357151216 | N54: 13553703 | O54: 8351994229 | P54: 0.23740675
B55: 3-01-001-01-01-24-0001-03 | C55: 2.1.1.01.01.002.04.3 | D55: A9903 | E55: Prima Semestral Trabajadores Oficiales | F55: 268694000 | G55: 0 | H55: 0 | I55: 268694000 | J55: 0 | K55: 238760995 | L55: 2791087 | M55: 238760995 | N55: 2791087 | O55: 238760995 | P55: 0.23740675
A56: O211010100212 | B56: 3-01-001-01-01-22-0012 | C56: 2.1.1.01.01.002.12 | E56: Prima de antigüedad | F56: =+F57 -> 1027167000 | G56: =+G57 -> 0 | H56: =+H57 -> 0 | I56: =+I57 -> 1027167000 | J56: =+J57 -> 70543525 | K56: =+K57 -> 571873601 | L56: =+L57 -> 70543525 | M56: =+M57 -> 571873601 | ... O56: =+O57 -> 571873601 | P56: 0.23740675
A57: O21101010021201 | B57: 3-01-001-01-01-22-0012-0 | C57: 2.1.1.01.01.002.12.01 | E57: Beneficios a los empleados a corto plazo | F57: =SUM(F58:F59) -> 1027167000 | G57: =SUM(G58:G59) -> 0 | H57: =SUM(H58:H59) -> 0 | I57: =SUM(I58:I59) -> 1027167000 | J57: =SUM(J58:J59) -> 70543525 | K57: =SUM(K58:K59) -> 571873601 | L57: =SUM(L58:L59) -> 70543525 | M57: =SUM(M58:M59) -> 571873601 | ... O57: =SUM(O58:O59) -> 571873601 | P57: 0.23740675
B58: 3-01-001-01-01-22-0012-01 | C58: 2.1.1.01.01.002.12.02.1 | D58: A9902 | E58: Prima de Antigüedad Administrativos | F58: 831631000 | G58: 0 | H58: 0 | I58: 831631000 | J58: 57128210 | K58: 454843346 | L58: 57128210 | M58: 454843346 | N58: 57128210 | O58: 454843346 | P58: 0.23740675
B59: 3-01-001-01-01-22-0012-02 | C59: 2.1.1.01.01.002.12.02.2 | D59: A9903 | E59: Prima de Antigüedad Trabajadores Oficiales | F59: 195536000 | G59: 0 | H59: 0 | I59: 195536000 | J59: 13415315 | K59: 117030255 | L59: 13415315 | M59: 117030255 | N59: 13415315 | O59: 117030255 | P59: 0.23740675
A60: O2110102 | B60: 3-01-001-01-02 | C60: 2.1.1.01.02 | E60: Contribuciones inherentes a la nómina | F60: =+F61+F70+F75+F84+F89+F94 -> 59417330000 | G60: =+G61+G70+G75+G84+G89+G94 -> 0 | H60: =+H61+H70+H75+H84+H89+H94 -> -1691811575 | I60: =+I61+I70+I75+I84+I89+I94 -> 57725518425 | J60: =+J61+J70+J75+J84+J89+J94 -> 2977235683 | K60: =+K61+K70+K75+K84+K89+K94 -> 33720259572 | L60: =+L61+L70+L75+L84+L89+L94 -> 2980111806 | M60: =+M61+M70+M75+M84+M89+M94 -> 33668998994 | ... O60: =+O61+O70+O75+O84+O89+O94 -> 33658728141 | P60: 0.23740675
A61: O2110102001 | B61: 3-01-001-01-02-01 | C61: 2.1.1.01.02.001 | E61: Aportes a la seguridad social en pensiones | F61: =+F62+F66 -> 17859361000 | G61: =+G62+G66 -> 0 | H61: =+H62+H66 -> 0 | I61: =+I62+I66 -> 17859361000 | J61: =+J62+J66 -> 1271149275 | K61: =+K62+K66 -> 8777285325 | L61: =+L62+L66 -> 1271149275 | M61: =+M62+M66 -> 8777285325 | ... O61: =+O62+O66 -> 8777285325 | P61: 0.23740675
A62: O211010200101 | B62: 3-01-001-01-02-01-0001 | C62: 2.1.1.01.02.001.01 | E62: Aportes a la seguridad social en pensiones públicas | F62: =SUM(F63:F65) -> 15547240000 | G62: =SUM(G63:G65) -> 0 | H62: =SUM(H63:H65) -> 0 | I62: =SUM(I63:I65) -> 15547240000 | J62: =SUM(J63:J65) -> 1145963475 | K62: =SUM(K63:K65) -> 7929885000 | L62: =SUM(L63:L65) -> 1145963475 | M62: =SUM(M63:M65) -> 7929885000 | ... O62: =SUM(O63:O65) -> 7929885000 | P62: 0.23740675
B63: 3-01-001-01-02-01-0001-01 | C63: 2.1.1.01.02.001.01.1 | D63: A9902 | E63: Pensiones Públicas Administrativos | F63: 2417048000 | G63: 0 | H63: 0 | I63: 2417048000 | J63: 177741825 | K63: 1218869700 | L63: 177741825 | M63: 1218869700 | N63: 177741825 | O63: 1218869700 | P63: 0.23740675
B64: 3-01-001-01-02-01-0001-02 | C64: 2.1.1.01.02.001.01.2 | D64: A9901 | E64: Pensiones Públicas Docentes | F64: 12937333000 | G64: 0 | H64: 0 | I64: 12937333000 | J64: 950505300 | K64: 6602986500 | L64: 950505300 | M64: 6602986500 | N64: 950505300 | O64: 6602986500 | P64: 0.23740675
B65: 3-01-001-01-02-01-0001-03 | C65: 2.1.1.01.02.001.01.3 | D65: A9903 | E65: Pensiones Públicas Trabajadores Oficiales | F65: 192859000 | G65: 0 | H65: 0 | I65: 192859000 | J65: 17716350 | K65: 108028800 | L65: 17716350 | M65: 108028800 | N65: 17716350 | O65: 108028800 | P65: 0.23740675
A66: O211010200102 | B66: 3-01-001-01-02-01-0002 | C66: 2.1.1.01.02.001.02 | E66: Aportes a la seguridad social en pensiones privadas | F66: =SUM(F67:F69) -> 2312121000 | G66: =SUM(G67:G69) -> 0 | H66: =SUM(H67:H69) -> 0 | I66: =SUM(I67:I69) -> 2312121000 | J66: =SUM(J67:J69) -> 125185800 | K66: =SUM(K67:K69) -> 847400325 | L66: =SUM(L67:L69) -> 125185800 | M66: =SUM(M67:M69) -> 847400325 | ... O66: =SUM(O67:O69) -> 847400325 | P66: 0.23740675
B67: 3-01-001-01-02-01-0002-01 | C67: 2.1.1.01.02.001.02.1 | D67: A9902 | E67: Pensiones Privadas Administrativos | F67: 507885000 | G67: 0 | H67: 0 | I67: 507885000 | J67: 33607950 | K67: 224876625 | L67: 33607950 | M67: 224876625 | N67: 33607950 | O67: 224876625 | P67: 0.23740675
B68: 3-01-001-01-02-01-0002-02 | C68: 2.1.1.01.02.001.02.2 | D68: A9901 | E68: Pensiones Privadas Docentes | F68: 1764182000 | G68: 0 | H68: 0 | I68: 1764182000 | J68: 90301725 | K68: 613718400 | L68: 90301725 | M68: 613718400 | N68: 90301725 | O68: 613718400 | P68: 0.23740675
B69: 3-01-001-01-02-01-0002-03 | C69: 2.1.1.01.02.001.02.3 | D69: A9903 | E69: Pensiones Privadas Trabajadores Oficiales | F69: 40054000 | G69: 0 | H69: 0 | I69: 40054000 | J69: 1276125 | K69: 8805300 | L69: 1276125 | M69: 8805300 | N69: 1276125 | O69: 8805300 | P69: 0.23740675
A70: O2110102002 | B70: 3-01-001-01-02-02 | C70: 2.1.1.01.02.002 | E70: Aportes a la seguridad social en salud | F70: =+F71 -> 12565168000 | G70: =+G71 -> 0 | H70: =+H71 -> 0 | I70: =+I71 -> 12565168000 | J70: =+J71 -> 900141908 | K70: =+K71 -> 6215452900 | L70: =+L71 -> 900141908 | M70: =+M71 -> 6215452900 | ... O70: =+O71 -> 6215452900 | P70: 0.23740675
A71: O211010200202 | B71: 3-01-001-01-02-02-0002 | C71: 2.1.1.01.02.002.02 | E71: Aportes a la seguridad social en salud privada | F71: =SUM(F72:F74) -> 12565168000 | G71: =SUM(G72:G74) -> 0 | H71: =SUM(H72:H74) -> 0 | I71: =SUM(I72:I74) -> 12565168000 | J71: =SUM(J72:J74) -> 900141908 | K71: =SUM(K72:K74) -> 6215452900 | L71: =SUM(L72:L74) -> 900141908 | M71: =SUM(M72:M74) -> 6215452900 | ... O71: =SUM(O72:O74) -> 6215452900 | P71: 0.23740675
B72: 3-01-001-01-02-02-0002-01 | C72: 2.1.1.01.02.002.02.1 | D72: A9902 | E72: Salud Privada Administrativos | F72: 2002645000 | G72: 0 | H72: 0 | I72: 2002645000 | J72: 149707032 | K72: 1022735164 | L72: 149707032 | M72: 1022735164 | N72: 149707032 | O72: 1022735164 | P72: 0.23740675
B73: 3-01-001-01-02-02-0002-02 | C73: 2.1.1.01.02.002.02.2 | D73: A9901 | E73: Salud Privada Docentes | F73: 10413573000 | G73: 0 | H73: 0 | I73: 10413573000 | J73: 736981756 | K73: 5109958200 | L73: 736981756 | M73: 5109958200 | N73: 736981756 | O73: 5109958200 | P73: 0.23740675
B74: 3-01-001-01-02-02-0002-03 | C74: 2.1.1.01.02.002.02.3 | D74: A9903 | E74: Salud Privada Trabajadores Oficiales | F74: 148950000 | G74: 0 | H74: 0 | I74: 148950000 | J74: 13453120 | K74: 82759536 | L74: 13453120 | M74: 82759536 | N74: 13453120 | O74: 82759536 | P74: 0.23740675
A75: O2110102003 | B75: 3-01-001-01-02-03 | C75: 2.1.1.01.02.003 | E75: Aportes de cesantías | F75: =+F76+F80 -> 15273366000 | G75: =+G76+G80 -> 0 | H75: =+H76+H80 -> -1691811575 | I75: =+I76+I80 -> 13581554425 | J75: =+J76+J80 -> 0 | K75: =+K76+K80 -> 12419650347 | L75: =+L76+L80 -> 2876123 | M75: =+M76+M80 -> 12368389769 | ... O75: =+O76+O80 -> 12358118916 | P75: 0.23740675
A76: O211010200301 | B76: 3-01-001-01-02-03-0001 | C76: 2.1.1.01.02.003.01 | E76: Aportes de cesantías a fondos públicos | F76: =SUM(F77:F79) -> 8087997000 | G76: =SUM(G77:G79) -> 0 | H76: =SUM(H77:H79) -> -100000000 | I76: =SUM(I77:I79) -> 7987997000 | J76: =SUM(J77:J79) -> 0 | K76: =SUM(K77:K79) -> 7558379361 | L76: =SUM(L77:L79) -> 0 | M76: =SUM(M77:M79) -> 7535079637 | ... O76: =SUM(O77:O79) -> 7524808784 | P76: 0.23740675
B77: 3-01-001-01-02-03-0001-01 | C77: 2.1.1.01.02.003.01.1 | D77: A9902 | E77: Cesantías Fondos Públicos Administrativos | F77: 1245634000 | G77: 0 | H77: -50000000 | I77: 1195634000 | J77: 0 | K77: 1103288053 | L77: 0 | M77: 1102117925 | N77: 1369432 | O77: 1101691733 | P77: 0.23740675
B78: 3-01-001-01-02-03-0001-02 | C78: 2.1.1.01.02.003.01.2 | D78: A9901 | E78: Cesantías Fondos Públicos Docentes | F78: 6694782000 | G78: 0 | H78: -50000000 | I78: 6644782000 | J78: 0 | K78: 6386981699 | L78: 0 | M78: 6364852103 | N78: 0 | O78: 6355007442 | P78: 0.23740675
B79: 3-01-001-01-02-03-0001-03 | C79: 2.1.1.01.02.003.01.3 | D79: A9903 | E79: Cesantías Fondos Públicos Trabajadores Oficiales | F79: 147581000 | G79: 0 | H79: 0 | I79: 147581000 | J79: 0 | K79: 68109609 | L79: 0 | M79: 68109609 | N79: 0 | O79: 68109609 | P79: 0.23740675
A80: O211010200302 | B80: 3-01-001-01-02-03-0002 | C80: 2.1.1.01.02.003.02 | E80: Aportes de cesantías a fondos privados | F80: =SUM(F81:F83) -> 7185369000 | G80: =SUM(G81:G83) -> 0 | H80: =SUM(H81:H83) -> -1591811575 | I80: =SUM(I81:I83) -> 5593557425 | J80: =SUM(J81:J83) -> 0 | K80: =SUM(K81:K83) -> 4861270986 | L80: =SUM(L81:L83) -> 2876123 | M80: =SUM(M81:M83) -> 4833310132 | ... O80: =SUM(O81:O83) -> 4833310132 | P80: 0.23740675
B81: 3-01-001-01-02-03-0002-01 | C81: 2.1.1.01.02.003.02.1 | D81: A9902 | E81: Cesantías Fondos Privados Administrativos | F81: 1104619000 | G81: 0 | H81: -275997151 | I81: 828621849 | J81: 0 | K81: 451587234 | L81: 905549 | M81: 451587234 | N81: 905549 | O81: 451587234 | P81: 0.23740675
B82: 3-01-001-01-02-03-0002-02 | C82: 2.1.1.01.02.003.02.2 | D82: A9901 | E82: Cesantías Fondos Privados Docentes | F82: 5936882000 | G82: 0 | H82: -1320814424 | I82: 4616067576 | J82: 0 | K82: 4264216325 | L82: 1970574 | M82: 4236255471 | N82: 1970574 | O82: 4236255471 | P82: 0.23740675
B83: 3-01-001-01-02-03-0002-03 | C83: 2.1.1.01.02.003.02.3 | D83: A9903 | E83: Cesantías Fondos Privados Trabajadores Oficiales | F83: 143868000 | G83: 0 | H83: 5000000 | I83: 148868000 | J83: 0 | K83: 145467427 | L83: 0 | M83: 145467427 | N83: 0 | O83: 145467427 | P83: 0.23740675
A84: O2110102004 | B84: 3-01-001-01-02-04 | C84: 2.1.1.01.02.004 | E84: Aportes a cajas de compensación familiar | F84: =+F85 -> 7329466000 | G84: =+G85 -> 0 | H84: =+H85 -> 0 | I84: =+I85 -> 7329466000 | J84: =+J85 -> 429266600 | K84: =+K85 -> 3387810800 | L84: =+L85 -> 429266600 | M84: =+M85 -> 3387810800 | ... O84: =+O85 -> 3387810800 | P84: 0.23740675
A85: O211010200401 | B85: 3-01-001-01-02-04-0001 | C85: 2.1.1.01.02.004.01 | E85: Compensar | F85: =SUM(F86:F88) -> 7329466000 | G85: =SUM(G86:G88) -> 0 | H85: =SUM(H86:H88) -> 0 | I85: =SUM(I86:I88) -> 7329466000 | J85: =SUM(J86:J88) -> 429266600 | K85: =SUM(K86:K88) -> 3387810800 | L85: =SUM(L86:L88) -> 429266600 | M85: =SUM(M86:M88) -> 3387810800 | ... O85: =SUM(O86:O88) -> 3387810800 | P85: 0.23740675
B86: 3-01-001-01-02-04-0001-01 | C86: 2.1.1.01.02.004.01.1 | D86: A9902 | E86: Caja de Compensación Administrativos | F86: 1166734000 | G86: 0 | H86: 0 | I86: 1166734000 | J86: 71488300 | K86: 570625300 | L86: 71488300 | M86: 570625300 | N86: 71488300 | O86: 570625300 | P86: 0.23740675
B87: 3-01-001-01-02-04-0001-02 | C87: 2.1.1.01.02.004.01.2 | D87: A9901 | E87: Caja de Compensación Docentes | F87: 6063199000 | G87: 0 | H87: 0 | I87: 6063199000 | J87: 349848300 | K87: 2763196800 | L87: 349848300 | M87: 2763196800 | N87: 349848300 | O87: 2763196800 | P87: 0.23740675
B88: 3-01-001-01-02-04-0001-03 | C88: 2.1.1.01.02.004.01.3 | D88: A9903 | E88: Caja de Compensación Trabajadores Oficiales | F88: 99533000 | G88: 0 | H88: 0 | I88: 99533000 | J88: 7930000 | K88: 53988700 | L88: 7930000 | M88: 53988700 | N88: 7930000 | O88: 53988700 | P88: 0.23740675
A89: O2110102005 | B89: 3-01-001-01-02-05 | C89: 2.1.1.01.02.005 | E89: Aportes generales al sistema de riesgos laborales | F89: =+F90 -> 957874000 | G89: =+G90 -> 0 | H89: =+H90 -> 0 | I89: =+I90 -> 957874000 | J89: =+J90 -> 54716500 | K89: =+K90 -> 379133800 | L89: =+L90 -> 54716500 | M89: =+M90 -> 379133800 | ... O89: =+O90 -> 379133800 | P89: 0.23740675
A90: O211010200501 | B90: 3-01-001-01-02-05-0001 | C90: 2.1.1.01.02.005.01 | E90: Aportes generales al sistema de riesgos laborales públicos | F90: =SUM(F91:F93) -> 957874000 | G90: =SUM(G91:G93) -> 0 | H90: =SUM(H91:H93) -> 0 | I90: =SUM(I91:I93) -> 957874000 | J90: =SUM(J91:J93) -> 54716500 | K90: =SUM(K91:K93) -> 379133800 | L90: =SUM(L91:L93) -> 54716500 | M90: =SUM(M91:M93) -> 379133800 | ... O90: =SUM(O91:O93) -> 379133800 | P90: 0.23740675
B91: 3-01-001-01-02-05-0001-01 | C91: 2.1.1.01.02.005.01.1 | D91: A9902 | E91: Riesgos Laborales Administrativos | F91: 153638000 | G91: 0 | H91: 0 | I91: 153638000 | J91: 8968900 | K91: 62328100 | L91: 8968900 | M91: 62328100 | N91: 8968900 | O91: 62328100 | P91: 0.23740675
B92: 3-01-001-01-02-05-0001-02 | C92: 2.1.1.01.02.005.01.2 | D92: A9901 | E92: Riesgos Laborales Docentes | F92: 791247000 | G92: 0 | H92: 0 | I92: 791247000 | J92: 44920500 | K92: 311975100 | L92: 44920500 | M92: 311975100 | N92: 44920500 | O92: 311975100 | P92: 0.23740675
B93: 3-01-001-01-02-05-0001-03 | C93: 2.1.1.01.02.005.01.3 | D93: A9903 | E93: Riesgos Laborales Trabajadores Oficiales | F93: 12989000 | G93: 0 | H93: 0 | I93: 12989000 | J93: 827100 | K93: 4830600 | L93: 827100 | M93: 4830600 | N93: 827100 | O93: 4830600 | P93: 0.23740675
A94: O2110102006 | B94: 3-01-001-01-02-06 | C94: 2.1.1.01.02.006 | E94: Aportes al ICBF | F94: =+F95 -> 5432095000 | G94: =+G95 -> 0 | H94: =+H95 -> 0 | I94: =+I95 -> 5432095000 | J94: =+J95 -> 321961400 | K94: =+K95 -> 2540926400 | L94: =+L95 -> 321961400 | M94: =+M95 -> 2540926400 | ... O94: =+O95 -> 2540926400 | P94: 0.23740675
A95: O2110102006 | B95: 3-01-001-01-02-06 | C95: 2.1.1.01.02.006 | E95: Aportes al ICBF | F95: =SUM(F96:F98) -> 5432095000 | G95: =SUM(G96:G98) -> 0 | H95: =SUM(H96:H98) -> 0 | I95: =SUM(I96:I98) -> 5432095000 | J95: =SUM(J96:J98) -> 321961400 | K95: =SUM(K96:K98) -> 2540926400 | L95: =SUM(L96:L98) -> 321961400 | M95: =SUM(M96:M98) -> 2540926400 | ... O95: =SUM(O96:O98) -> 2540926400 | P95: 0.23740675
B96: 3-01-001-01-02-06-0001-00 | C96: 2.1.1.01.02.006.1 | D96: A9902 | E96: ICBF Administrativos | F96: 810047000 | G96: 0 | H96: 0 | I96: 810047000 | J96: 53618300 | K96: 427983100 | L96: 53618300 | M96: 427983100 | N96: 53618300 | O96: 427983100 | P96: 0.23740675
B97: 3-01-001-01-02-06-0002-00 | C97: 2.1.1.01.02.006.2 | D97: A9901 | E97: ICBF Docentes | F97: 4547399000 | G97: 0 | H97: 0 | I97: 4547399000 | J97: 262395300 | K97: 2072450000 | L97: 262395300 | M97: 2072450000 | N97: 262395300 | O97: 2072450000 | P97: 0.23740675
B98: 3-01-001-01-02-06-0003-00 | C98: 2.1.1.01.02.006.3 | D98: A9903 | E98: ICBF Trabajadores Oficiales | F98: 74649000 | G98: 0 | H98: 0 | I98: 74649000 | J98: 5947800 | K98: 40493300 | L98: 5947800 | M98: 40493300 | N98: 5947800 | O98: 40493300 | P98: 0.23740675
A99: O2110103 | B99: 3-01-001-01-03 | C99: 2.1.1.01.03 | E99: Remuneraciones no constitutivas de factor salarial | F99: =+F100+F102+F103+F104 -> 10137250000 | G99: =+G100+G102+G103+G104 -> 0 | H99: =+H100+H102+H103+H104 -> -32525710 | I99: =+I100+I102+I103+I104 -> 10104724290 | J99: =+J100+J102+J103+J104 -> 67451659 | K99: =+K100+K102+K103+K104 -> 8144778067 | L99: =+L100+L102+L103+L104 -> 273238102 | M99: =+M100+M102+M103+M104 -> 8034283570 | ... O99: =+O100+O102+O103+O104 -> 3023443806 | P99: 0.23740675
A100: O2110103001 | B100: 3-01-001-01-03-01 | C100: 2.1.1.01.03.001 | E100: Prestaciones sociales | F100: =SUM(F101:F101) -> 96799000 | G100: =SUM(G101:G101) -> 0 | H100: =SUM(H101:H101) -> 0 | I100: =SUM(I101:I101) -> 96799000 | J100: =SUM(J101:J101) -> 1550485 | K100: =SUM(K101:K101) -> 11254644 | L100: =SUM(L101:L101) -> 1968415 | M100: =SUM(M101:M101) -> 9894748 | ... O100: =SUM(O101:O101) -> 9476818 | P100: 0.23740675
A101: O211010300103 | B101: 3-01-001-01-03-01-0003-00 | C101: 2.1.1.01.03.001.03 | D101: A9902 | E101: Bonificación especial de recreación | F101: 96799000 | G101: 0 | H101: 0 | I101: 96799000 | J101: 1550485 | K101: 11254644 | L101: 1968415 | M101: 9894748 | N101: 1897878 | O101: 9476818 | P101: 0.23740675
A102: O2110103005 | B102: 3-01-001-01-03-05-0000-00 | C102: 2.1.1.01.03.005 | D102: A9902 | E102: Reconocimiento por permanencia en el servicio público - Bogotá D.C. | F102: 382816000 | G102: 0 | H102: 0 | I102: 382816000 | J102: 0 | K102: 0 | L102: 0 | M102: 0 | N102: 0 | O102: 0 | P102: 0.23740675
A103: O2110103068 | B103: 3-01-001-01-03-68-0000-00 | C103: 2.1.1.01.03.068 | D103: A9902 | E103: Prima secretarial | F103: 284402000 | G103: 0 | H103: 0 | I103: 284402000 | J103: 15489585 | K103: 123290497 | L103: 15489585 | M103: 123290497 | N103: 15489585 | O103: 123290497 | P103: 0.23740675
A104: O2110103121 | B104: 3-01-001-01-01-25 | C104: 2.1.1.01.03.121 | E104: Bonificación permanente extralegal (Beneficios convencionales) | F104: =F105 -> 9373233000 | G104: =G105 -> 0 | H104: =H105 -> -32525710 | I104: =I105 -> 9340707290 | J104: =J105 -> 50411589 | K104: =K105 -> 8010232926 | L104: =L105 -> 255780102 | M104: =M105 -> 7901098325 | ... O104: =O105 -> 2890676491 | P104: 0.23740675
...

Sheet FONDO INVERSIONES Y FORT. INST.
C2: INFORME DE EJECUCIÓN MENSUAL DE GASTOS E INVERSIÓN - FONDO DE INVERSIÓN Y FORTALECIMIENTO INSTITUCIONAL
C3: UNIVERSIDAD DISTRITAL FRANCISCO JOSÉ DE CALDAS
C4: AGOSTO 2026
F6: =+F11-F7 -> 0 | G6: =+G11-G7 -> 0 | H6: =+H11-H7 -> 0 | I6: =+I11-I7 -> 0 | J6: =+J11-J7 -> 0 | K6: =+K11-K7 -> 0 | L6: =+L11-L7 -> 0 | M6: =+M11-M7 -> 0 | ... O6: =+O11-O7 -> 0
F7: 43316311000 | G7: 1278780064 | H7: 10418268632 | I7: 53734579632 | J7: 7036067317 | K7: 20746386884 | L7: 3431805195 | M7: 13891436430 | N7: 1050982426 | O7: 8162602753
C8: RUBRO PRESUPUESTAL | F8: PRESUPUESTO INICIAL 2026 RES CSU 024-2025 | G8: APROPIACION | J8: DISPONIBILIDADES | L8: COMPROMISOS | N8: AUTORIZACION DE GIRO | P8: % DE EJECUCIÓN
A9: POSPRE | B9: CÓDIGO SICAPITAL | C9: CÓDIGO | D9: CENTRO DE COSTOS | E9: NOMBRE | G9: MODIFICACIONES | I9: VIGENTE | J9: MES | K9: ACUMULADO | L9: MES | M9: ACUMULADO | N9: MES | O9: ACUMULADO
G10: MES | H10: ACUMULADO
A11: O2301 | B11: 3-03-001 | C11: 2.3.01 | E11: DIRECTA | F11: =F12 -> 43316311000 | G11: =G12 -> 1278780064 | H11: =H12 -> 10418268632 | I11: =I12 -> 53734579632 | J11: =J12 -> 7036067317 | K11: =K12 -> 20746386884 | L11: =L12 -> 3431805195 | M11: =M12 -> 13891436430 | ... O11: =O12 -> 8162602753 | P11: =IFERROR((M11/I11),0) -> 0.2585195
A12: O230117 | B12: 3-03-001-17 | C12: 2.3.01.17 | E12: BOGOTÁ CAMINA SEGURA | F12: =+F13 -> 43316311000 | G12: =+G13 -> 1278780064 | H12: =+H13 -> 10418268632 | I12: =+I13 -> 53734579632 | J12: =+J13 -> 7036067317 | K12: =+K13 -> 20746386884 | L12: =+L13 -> 3431805195 | M12: =+M13 -> 13891436430 | ... O12: =+O13 -> 8162602753 | P12: =IFERROR((M12/I12),0) -> 0.2585195
A13: O23011722 | B13: 3-03-001-17-22 | C13: 2.3.01.17.22 | E13: Objetivo estratégico 03. Bogotá confía en su potencial | F13: =+F14 -> 43316311000 | G13: =+G14 -> 1278780064 | H13: =+H14 -> 10418268632 | I13: =+I14 -> 53734579632 | J13: =+J14 -> 7036067317 | K13: =+K14 -> 20746386884 | L13: =+L14 -> 3431805195 | M13: =+M14 -> 13891436430 | ... O13: =+O14 -> 8162602753 | P13: =IFERROR((M13/I13),0) -> 0.2585195
A14: O2301172202 | B14: 3-03-001-17-22-02-2024 | C14: 2.3.01.17.22.02 | E14: Programa 17. Formación para el trabajo y acceso a oportunidades educativas | F14: =SUM(F15:F23) -> 43316311000 | G14: =SUM(G15:G23) -> 1278780064 | H14: =SUM(H15:H23) -> 10418268632 | I14: =SUM(I15:I23) -> 53734579632 | J14: =SUM(J15:J23) -> 7036067317 | K14: =SUM(K15:K23) -> 20746386884 | L14: =SUM(L15:L23) -> 3431805195 | M14: =SUM(M15:M23) -> 13891436430 | ... O14: =SUM(O15:O23) -> 8162602753 | P14: =IFERROR((M14/I14),0) -> 0.2585195
A15: O230117220220240256 | B15: 3-03-001-17-22-02-2024-0256 | C15: 2.3.01.17.22.02.20240256 | D15: A1205 | E15: Desarrollo y modernización de los procesos relacionados con gestión institucional de la Universidad Distrital Francisco José De Caldas Bogotá D.C. | F15: 0 | G15: 0 | H15: 346985635 | I15: 346985635 | J15: 47909519 | K15: 47909519 | L15: 0 | M15: 47909519 | N15: 0 | O15: 47909519 | P15: =IFERROR((M15/I15),0) -> 0.13807349
A16: O230117220220240257 | B16: 3-03-001-17-22-02-2024-0257 | C16: 2.3.01.17.22.02.20240257 | D16: A1205 | E16: Ampliación y Mejoramiento de la infraestructura física de las Sedes de la Universidad Distrital Francisco José de Caldas. Bogotá D.C | F16: 16072252000 | G16: 0 | H16: 1398412287 | I16: 17470664287 | J16: 307668942 | K16: 868344475 | L16: 103765500 | M16: 448967244 | N16: 403943 | O16: 225632875 | P16: =IFERROR((M16/I16),0) -> 0.02569835
A17: O230117220220240261 | B17: 3-03-001-17-22-02-2024-0261 | C17: 2.3.01.17.22.02.20240261 | D17: A1205 | E17: Fortalecimiento de estrategias para disminuir la tasa de riesgo de deserción, promoción de la permanencia y bienestar de los estudiantes de pregrado de la Universidad Distrital Bogotá D.C | F17: 1762733000 | G17: 0 | H17: 0 | I17: 1762733000 | J17: 325196158 | K17: 1520165290 | L17: 24236588 | M17: 1219205720 | N17: 63524454 | O17: 1125034289 | P17: =IFERROR((M17/I17),0) -> 0.69165649
A18: O230117220220240279 | B18: 3-03-001-17-22-02-2024-0279 | C18: 2.3.01.17.22.02.20240279 | D18: A1205 | E18: Fortalecimiento de las capacidades del sistema de investigaciones frente a los retos de CTEI a nivel regional, nacional e internacional en la UDFJC. Bogotá D.C. | F18: 6466642400 | G18: 0 | H18: 0 | I18: 6466642000 | J18: 1573331127 | K18: 4484328970 | L18: 1206843133 | M18: 4006006034 | N18: 150022643 | O18: 2707469772 | P18: =IFERROR((M18/I18),0) -> 0.61948783
A19: O230117220220240280 | B19: 3-03-001-17-22-02-2024-0280 | C19: 2.3.01.17.22.02.20240280 | D19: A1205 | E19: Incremento del acceso y el impacto socio-cultural de los resultados de conocimientos generados por los doctorados de la Universidad Francisco José De Caldas Bogotá D.C | F19: 2565693000 | G19: 0 | H19: 0 | I19: 2565693000 | J19: 210683056 | K19: 1225247076 | L19: 184248922 | M19: 1123056712 | N19: 62118528 | O19: 937927590 | P19: =IFERROR((M19/I19),0) -> 0.43772061
A20: O230117220220240281 | B20: 3-03-001-17-22-02-2024-0281 | C20: 2.3.01.17.22.02.20240281 | D20: A1205 | E20: Fortalecimiento del uso y apropiación de TIC como soporte de propuestas de formación híbridas, virtuales o con incorporación tecnológica en la UD Bogotá D.C | F20: 574376000 | G20: 0 | H20: 1150011870 | I20: 1724387870 | J20: 867927022 | K20: 1540007292 | L20: 407086764 | M20: 749995422 | N20: 1879217 | O20: 342776937 | P20: =IFERROR((M20/I20),0) -> 0.43493429
A21: O230117220220240282 | B21: 3-03-001-17-22-02-2024-0282 | C21: 2.3.01.17.22.02.20240282 | D21: A1205 | E21: Fortalecimiento de la capacidad para la prestación del servicio en las Unidades Académicas de Laboratorio en la docencia, investigación, extensión y proyección social de la UDFC. Bogotá D.C. | F21: 7937309000 | G21: 0 | H21: 1313535937 | I21: 9250844937 | J21: 1014706255 | K21: 4289585940 | L21: 534141648 | M21: 3263353353 | N21: 646184833 | O21: 866846941 | P21: =IFERROR((M21/I21),0) -> 0.35276273
A22: O230117220220240283 | B22: 3-03-001-17-22-02-2024-0283 | C22: 2.3.01.17.22.02.20240283 | D22: A1205 | E22: Fortalecimiento de los componentes tecnológicos para lograr la Transformación Digital en la institución, especialmente en los procesos respaldados por las áreas de tecnología. Bogotá D.C | F22: 5952979000 | G22: 1278780064 | H22: 6209322903 | I22: 12162301903 | J22: 2698762990 | K22: 5130790211 | L22: 602226492 | M22: 1392934315 | N22: 1413801 | O22: 790707823 | P22: =IFERROR((M22/I22),0) -> 0.11452884
A23: O230117220220240284 | B23: 3-03-001-17-22-02-2024-0284 | C23: 2.3.01.17.22.02.20240284 | D23: A1205 | E23: Fortalecimiento de las líneas de servicios CRAI que conforman el portafolio de servicios y recursos de las bibliotecas y unidades de información de la UDFJC, Bogotá DC | F23: 1984326600 | G23: 0 | H23: 0 | I23: 1984327000 | J23: -10117752 | K23: 1640008111 | L23: 369256148 | M23: 1640008111 | N23: 125435007 | O23: 1118297007 | P23: =IFERROR((M23/I23),0) -> 0.82648077

Sheet FONDO PRÉSTAMOS
C2: INFORME DE EJECUCIÓN MENSUAL DE GASTOS E INVERSIÓN - FONDO DE PRÉSTAMOS
C3: UNIVERSIDAD DISTRITAL FRANCISCO JOSÉ DE CALDAS
C4: AGOSTO 2026
F8: =+F9-F13 -> 0 | G8: =+G9-G13 -> 0 | H8: 0 | I8: =+I9-I13 -> 0 | K8: 0 | L8: 0 | M8: 0 | N8: 0 | O8: 0
F9: 211790000 | G9: 382493661 | I9: 594283661 | K9: 0 | L9: 0 | M9: 0 | N9: 0 | O9: 0
C10: RUBRO PRESUPUESTAL | F10: PRESUPUESTO INICIAL 2026 RES CSU 024-2025 | G10: APROPIACIÓN | J10: DISPONIBILIDADES | L10: COMPROMISOS | N10: AUTORIZACION DE GIRO | P10: % DE EJECUCIÓN
A11: POSPRE | B11: CÓDIGO SICAPITAL | C11: CÓDIGO | D11: CENTRO DE COSTOS | E11: NOMBRE | G11: MODIFICACIONES | I11: VIGENTE | J11: MES | K11: ACUMULADO | L11: MES | M11: ACUMULADO | N11: MES | O11: ACUMULADO
G12: MES | H12: ACUMULADO
A13: O233 | B13: 3-03-003 | C13: 2.3.3 | E13: TRANSFERENCIAS CORRIENTES | F13: =+F14 -> 211790000 | G13: =+G14 -> 382493661 | H13: =+H14 -> 382493661 | I13: =+I14 -> 594283661 | K13: =+K14 -> 0 | L13: =+L14 -> 4200000 | M13: =+M14 -> 0 | N13: =+N14 -> 4200000 | O13: =+O14 -> 0 | P13: =+M13/I13 -> 0
A14: O23305 | B14: 3-03-003-05 | C14: 2.3.3.05 | E14: A ENTIDADES DEL GOBIERNO | F14: =+F15 -> 211790000 | G14: =+G15 -> 382493661 | H14: =+H15 -> 382493661 | I14: =+I15 -> 594283661 | K14: =+K15 -> 0 | L14: =+L15 -> 4200000 | M14: =+M15 -> 0 | N14: =+N15 -> 4200000 | O14: =+O15 -> 0 | P14: =+M14/I14 -> 0
A15: O2330509 | B15: 3-03-003-05-09 | C15: 2.3.3.05.09 | E15: A OTRAS ENTIDADES DEL GOBIERNO GENERAL | F15: =+F16 -> 211790000 | G15: =+G16 -> 382493661 | H15: =+H16 -> 382493661 | I15: =+I16 -> 594283661 | K15: =+K16 -> 0 | L15: =+L16 -> 4200000 | M15: =+M16 -> 0 | N15: =+N16 -> 4200000 | O15: =+O16 -> 0 | P15: =+M15/I15 -> 0
A16: O2330509054 | B16: 3-03-003-05-09-54 | C16: 2.3.3.05.09.054 | E16: A ESTABLECIMIENTOS PUBLICOS Y UNIDADES ADMINISTRATIVAS ESPECIALES | F16: =+F17 -> 211790000 | G16: =+G17 -> 382493661 | H16: =+H17 -> 382493661 | I16: =+I17 -> 594283661 | K16: =+K17 -> 0 | L16: =+L17 -> 4200000 | M16: =+M17 -> 0 | N16: =+N17 -> 4200000 | O16: =+O17 -> 0 | P16: =+M16/I16 -> 0
A17: O233050905422 | B17: 3-03-003-05-09-54-0022 | C17: 2.3.3.05.09.054.22 | E17: OTROS ORGANISMOS | F17: =+F18+F20 -> 211790000 | G17: =+G18+G20 -> 382493661 | H17: =+H18+H20 -> 382493661 | I17: =+I18+I20 -> 594283661 | K17: =+K18+K20 -> 0 | L17: =+L18+L20 -> 4200000 | M17: =+M18+M20 -> 0 | N17: =+N18+N20 -> 4200000 | O17: =+O18+O20 -> 0 | P17: =+M17/I17 -> 0
A18: O23305090542205 | C18: 2.3.3.05.09.054.22.05 | E18: FONDO PRÉSTAMOS A EMPLEADOS (Universidad Distrital) | F18: =+F19 -> 50887000 | G18: =+G19 -> 0 | H18: =+H19 -> 0 | I18: =+I19 -> 50887000 | K18: =+K19 -> 0 | L18: =+L19 -> 4200000 | M18: =+M19 -> 0 | N18: =+N19 -> 4200000 | O18: =+O19 -> 0 | P18: =+M18/I18 -> 0
B19: 3-03-003-05-09-54-0022-01 | C19: 2.3.3.05.09.054.22.05.1 | D19: A1401 | E19: Préstamos Ordinarios Administrativos | F19: 50887000 | G19: 0 | H19: 0 | I19: 50887000 | K19: 0 | L19: 4200000 | M19: 0 | N19: 4200000 | O19: 0 | P19: =+M19/I19 -> 0
A20: O23305090542206 | C20: 2.3.3.05.09.054.22.06 | E20: FONDO DE VIVIENDA (Universidad Distrital) | F20: =+F21 -> 160903000 | G20: =+G21 -> 382493661 | H20: =+H21 -> 382493661 | I20: =+I21 -> 543396661 | K20: =+K21 -> 0 | L20: =+L21 -> 0 | M20: =+M21 -> 0 | N20: =+N21 -> 0 | O20: =+O21 -> 0 | P20: =+M20/I20 -> 0
B21: 3-03-003-05-09-54-0022-02 | C21: 2.3.3.05.09.054.22.06.1 | D21: A1401 | E21: Vivienda Administrativos | F21: 160903000 | G21: 382493661 | H21: 382493661 | I21: 543396661 | K21: 0 | L21: 0 | M21: 0 | N21: 0 | O21: 0 | P21: =+M21/I21 -> 0

Sheet EJECUCIÓN 2026 BOGDATA
A2: INFORME DE EJECUCIÓN MENSUAL DE GASTOS E INVERSIÓN
A3: UNIVERSIDAD DISTRITAL FRANCISCO JOSÉ DE CALDAS
A4: AGOSTO 2026
A6: BOGDATA
C10: =EJECUCIÓN!F13 -> 548567755000 | D10: =EJECUCIÓN!G13 -> 14194792521 | E10: =EJECUCIÓN!H13 -> 119748855067 | F10: =EJECUCIÓN!I13 -> 668316610067 | G10: =EJECUCIÓN!J13 -> 37765169384 | H10: =EJECUCIÓN!K13 -> 443925954879 | I10: =EJECUCIÓN!L13 -> 59277792200 | J10: =EJECUCIÓN!M13 -> 411524952140 | ... L10: =EJECUCIÓN!O13 -> 316933439339
A11: Entidad/Proyecto/ObjetoGasto | B11: NOMBRE | C11: INICIAL | D11: APROPIACION | I11: TOTAL COMPROMISOS | K11: AUTORIZACION DE GIRO | M11: EJECUC. PRESUP. %
D12: MODIFICACIONES | F12: VIGENTE | G12: DISPONIBLE
D13: MES | E13: ACUMULADO | G13: MES | H13: ACUMULADO | I13: MES | J13: ACUMULADO | K13: MES | L13: ACUMULADO
A14: TOTAL | C14: =+C15 -> 548567755000 | D14: =+D15 -> 14194792521 | E14: =+E15 -> 119748855067 | F14: =+F15 -> 668316610067 | G14: =+G15 -> 37765169384 | H14: =+H15 -> 443925954879 | I14: =+I15 -> 59277792200 | J14: =+J15 -> 411524952140 | ... L14: =+L15 -> 316933439339 | M14: =+J14/F14 -> 0.61576347
A15: 0230-01 UNIVERSIDAD DISTRITAL FRANCISCO JOSE DE | C15: =+C16+C133+SUM(C134:C159) -> 548567755000 | D15: =+D16+D133+SUM(D134:D159) -> 14194792521 | E15: =+E16+E133+SUM(E134:E159) -> 119748855067 | F15: =+F16+F133+SUM(F134:F159) -> 668316610067 | G15: =+G16+G133+SUM(G134:G159) -> 37765169384 | H15: =+H16+H133+SUM(H134:H159) -> 443925954879 | I15: =+I16+I133+SUM(I134:I159) -> 59277792200 | J15: =+J16+J133+SUM(J134:J159) -> 411524952140 | ... L15: =+L16+L133+SUM(L134:L159) -> 316933439339 | M15: =+J15/F15 -> 0.61576347
A16: 000000000000000000230 0230 - Programa Funcionamiento - UNIVERSIDAD DISTR | C16: =+SUM(C17:C132) -> 505039654000 | D16: =+SUM(D17:D132) -> 12533518796 | E16: =+SUM(E17:E132) -> 108948092774 | F16: =+SUM(F17:F132) -> 613987746774 | G16: =+SUM(G17:G132) -> 30729102067 | H16: =+SUM(H17:H132) -> 423175367995 | I16: =+SUM(I17:I132) -> 55845987005 | J16: =+SUM(J17:J132) -> 397629315710 | ... L16: =+SUM(L17:L132) -> 308766636586 | M16: =+J16/F16 -> 0.64761767
A17: O211010100101 | B17: Sueldo básico | C17: =EJECUCIÓN!F21+EJECUCIÓN!F22+EJECUCIÓN!F23 -> 137847199000 | D17: =EJECUCIÓN!G21+EJECUCIÓN!G22+EJECUCIÓN!G23 -> 0 | E17: =EJECUCIÓN!H21+EJECUCIÓN!H22+EJECUCIÓN!H23 -> -882993704 | F17: =EJECUCIÓN!I21+EJECUCIÓN!I22+EJECUCIÓN!I23 -> 136964205296 | G17: =EJECUCIÓN!J21+EJECUCIÓN!J22+EJECUCIÓN!J23 -> 9973723386 | H17: =EJECUCIÓN!K21+EJECUCIÓN!K22+EJECUCIÓN!K23 -> 79163609530 | I17: =EJECUCIÓN!L21+EJECUCIÓN!L22+EJECUCIÓN!L23 -> 10009017915 | J17: =EJECUCIÓN!M21+EJECUCIÓN!M22+EJECUCIÓN!M23 -> 79046667804 | ... L17: =EJECUCIÓN!O21+EJECUCIÓN!O22+EJECUCIÓN!O23 -> 79022119760 | M17: =+J17/F17 -> 0.57713377
A18: O211010100102 | B18: Horas extras, dominicales, festivos y recargos | C18: =EJECUCIÓN!F26 -> 232386000 | D18: =EJECUCIÓN!G26 -> 0 | E18: =EJECUCIÓN!H26 -> 0 | F18: =EJECUCIÓN!I26 -> 232386000 | G18: =EJECUCIÓN!J26 -> 13695907 | H18: =EJECUCIÓN!K26 -> 110111232 | I18: =EJECUCIÓN!L26 -> 13695907 | J18: =EJECUCIÓN!M26 -> 110111232 | ... L18: =EJECUCIÓN!O26 -> 110111232 | M18: =+J18/F18 -> 0.47382903
A19: O211010100103 | B19: Gastos de representación | C19: =EJECUCIÓN!F29 -> 879556000 | D19: =EJECUCIÓN!G29 -> 0 | E19: =EJECUCIÓN!H29 -> 0 | F19: =EJECUCIÓN!I29 -> 879556000 | G19: =EJECUCIÓN!J29 -> 68936516 | H19: =EJECUCIÓN!K29 -> 540508571 | I19: =EJECUCIÓN!L29 -> 68936516 | J19: =EJECUCIÓN!M29 -> 540508571 | ... L19: =EJECUCIÓN!O29 -> 540508571 | M19: =+J19/F19 -> 0.61452434
A20: O211010100104 | B20: Subsidio de alimentación | C20: =EJECUCIÓN!F32 -> 89520000 | D20: =EJECUCIÓN!G32 -> 0 | E20: =EJECUCIÓN!H32 -> 0 | F20: =EJECUCIÓN!I32 -> 89520000 | G20: =EJECUCIÓN!J32 -> 6554973 | H20: =EJECUCIÓN!K32 -> 57670022 | I20: =EJECUCIÓN!L32 -> 6554973 | J20: =EJECUCIÓN!M32 -> 57670022 | ... L20: =EJECUCIÓN!O32 -> 57670022 | M20: =+J20/F20 -> 0.64421383
A21: O211010100105 | B21: Auxilio de transporte | C21: =EJECUCIÓN!F35 -> 92533000 | D21: =EJECUCIÓN!G35 -> 0 | E21: =EJECUCIÓN!H35 -> 0 | F21: =EJECUCIÓN!I35 -> 92533000 | G21: =EJECUCIÓN!J35 -> 6050899 | H21: =EJECUCIÓN!K35 -> 53235236 | I21: =EJECUCIÓN!L35 -> 6050899 | J21: =EJECUCIÓN!M35 -> 53235236 | ... L21: =EJECUCIÓN!O35 -> 53235236 | M21: =+J21/F21 -> 0.57531082
A22: O211010100107 | B22: Bonificación por servicios prestados | C22: =EJECUCIÓN!F38+EJECUCIÓN!F39 -> 4044818000 | D22: =EJECUCIÓN!G38+EJECUCIÓN!G39 -> 0 | E22: =EJECUCIÓN!H38+EJECUCIÓN!H39 -> 0 | F22: =EJECUCIÓN!I38+EJECUCIÓN!I39 -> 4044818000 | G22: =EJECUCIÓN!J38+EJECUCIÓN!J39 -> 521204267 | H22: =EJECUCIÓN!K38+EJECUCIÓN!K39 -> 2397348052 | I22: =EJECUCIÓN!L38+EJECUCIÓN!L39 -> 523352825 | J22: =EJECUCIÓN!M38+EJECUCIÓN!M39 -> 2385667678 | ... L22: =EJECUCIÓN!O38+EJECUCIÓN!O39 -> 2383519120 | M22: =+J22/F22 -> 0.58980841
A23: O21101010010801 | B23: Prima de navidad | C23: =EJECUCIÓN!F42+EJECUCIÓN!F43+EJECUCIÓN!F44 -> 14300185000 | D23: =EJECUCIÓN!G42+EJECUCIÓN!G43+EJECUCIÓN!G44 -> 0 | E23: =EJECUCIÓN!H42+EJECUCIÓN!H43+EJECUCIÓN!H44 -> 0 | F23: =EJECUCIÓN!I42+EJECUCIÓN!I43+EJECUCIÓN!I44 -> 14300185000 | G23: =EJECUCIÓN!J42+EJECUCIÓN!J43+EJECUCIÓN!J44 -> 0 | H23: =EJECUCIÓN!K42+EJECUCIÓN!K43+EJECUCIÓN!K44 -> 119171591 | I23: =EJECUCIÓN!L42+EJECUCIÓN!L43+EJECUCIÓN!L44 -> 25898987 | J23: =EJECUCIÓN!M42+EJECUCIÓN!M43+EJECUCIÓN!M44 -> 81636831 | ... L23: =EJECUCIÓN!O42+EJECUCIÓN!O43+EJECUCIÓN!O44 -> 79143364 | M23: =+J23/F23 -> 0.0057087954
A24: O21101010010802 | B24: Prima de vacaciones | C24: =EJECUCIÓN!F46+EJECUCIÓN!F47+EJECUCIÓN!F48 -> 8692251000 | D24: =EJECUCIÓN!G46+EJECUCIÓN!G47+EJECUCIÓN!G48 -> 0 | E24: =EJECUCIÓN!H46+EJECUCIÓN!H47+EJECUCIÓN!H48 -> 0 | F24: =EJECUCIÓN!I46+EJECUCIÓN!I47+EJECUCIÓN!I48 -> 8692251000 | G24: =EJECUCIÓN!J46+EJECUCIÓN!J47+EJECUCIÓN!J48 -> 23942177 | H24: =EJECUCIÓN!K46+EJECUCIÓN!K47+EJECUCIÓN!K48 -> 271183862 | I24: =EJECUCIÓN!L46+EJECUCIÓN!L47+EJECUCIÓN!L48 -> 47305862 | J24: =EJECUCIÓN!M46+EJECUCIÓN!M47+EJECUCIÓN!M48 -> 211901050 | ... L24: =EJECUCIÓN!O46+EJECUCIÓN!O47+EJECUCIÓN!O48 -> 201637051 | M24: =+J24/F24 -> 0.024378156
A25: O211010100109 | B25: Prima técnica salarial | C25: =EJECUCIÓN!F51 -> 3872599000 | D25: =EJECUCIÓN!G51 -> 0 | E25: =EJECUCIÓN!H51 -> 0 | F25: =EJECUCIÓN!I51 -> 3872599000 | G25: =EJECUCIÓN!J51 -> 313960967 | H25: =EJECUCIÓN!K51 -> 2426392424 | I25: =EJECUCIÓN!L51 -> 313960967 | J25: =EJECUCIÓN!M51 -> 2426392424 | ... L25: =EJECUCIÓN!O51 -> 2426392424 | M25: =+J25/F25 -> 0.62655401
A26: O211010100204 | B26: Prima semestral | C26: =EJECUCIÓN!F53+EJECUCIÓN!F54+EJECUCIÓN!F55 -> 12787384000 | D26: =EJECUCIÓN!G53+EJECUCIÓN!G54+EJECUCIÓN!G55 -> 0 | E26: =EJECUCIÓN!H53+EJECUCIÓN!H54+EJECUCIÓN!H55 -> -951191646 | F26: =EJECUCIÓN!I53+EJECUCIÓN!I54+EJECUCIÓN!I55 -> 11836192354 | G26: =EJECUCIÓN!J53+EJECUCIÓN!J54+EJECUCIÓN!J55 -> 13553703 | H26: =EJECUCIÓN!K53+EJECUCIÓN!K54+EJECUCIÓN!K55 -> 10720612031 | I26: =EJECUCIÓN!L53+EJECUCIÓN!L54+EJECUCIÓN!L55 -> 22999422 | J26: =EJECUCIÓN!M53+EJECUCIÓN!M54+EJECUCIÓN!M55 -> 10667836583 | ... L26: =EJECUCIÓN!O53+EJECUCIÓN!O54+EJECUCIÓN!O55 -> 10656024964 | M26: =+J26/F26 -> 0.90128956
A27: O21101010021201 | B27: Beneficios a los empleados a corto plazo | C27: =EJECUCIÓN!F59+EJECUCIÓN!F60 -> 1027167000 | D27: =EJECUCIÓN!G59+EJECUCIÓN!G60 -> 0 | E27: =EJECUCIÓN!H59+EJECUCIÓN!H60 -> 0 | F27: =EJECUCIÓN!I59+EJECUCIÓN!I60 -> 1027167000 | G27: =EJECUCIÓN!J59+EJECUCIÓN!J60 -> 70543525 | H27: =EJECUCIÓN!K59+EJECUCIÓN!K60 -> 571873601 | I27: =EJECUCIÓN!L59+EJECUCIÓN!L60 -> 70543525 | J27: =EJECUCIÓN!M59+EJECUCIÓN!M60 -> 571873601 | ... L27: =EJECUCIÓN!O59+EJECUCIÓN!O60 -> 571873601 | M27: =+J27/F27 -> 0.55674842
A28: O211010200101 | B28: Aportes a la seguridad social en pensiones públicas | C28: =EJECUCIÓN!F64+EJECUCIÓN!F65+EJECUCIÓN!F66 -> 15547240000 | D28: =EJECUCIÓN!G64+EJECUCIÓN!G65+EJECUCIÓN!G66 -> 0 | E28: =EJECUCIÓN!H64+EJECUCIÓN!H65+EJECUCIÓN!H66 -> 0 | F28: =EJECUCIÓN!I64+EJECUCIÓN!I65+EJECUCIÓN!I66 -> 15547240000 | G28: =EJECUCIÓN!J64+EJECUCIÓN!J65+EJECUCIÓN!J66 -> 1145963475 | H28: =EJECUCIÓN!K64+EJECUCIÓN!K65+EJECUCIÓN!K66 -> 7929885000 | I28: =EJECUCIÓN!L64+EJECUCIÓN!L65+EJECUCIÓN!L66 -> 1145963475 | J28: =EJECUCIÓN!M64+EJECUCIÓN!M65+EJECUCIÓN!M66 -> 7929885000 | ... L28: =EJECUCIÓN!O64+EJECUCIÓN!O65+EJECUCIÓN!O66 -> 7929885000 | M28: =+J28/F28 -> 0.51005098
A29: O211010200102 | B29: Aportes a la seguridad social en pensiones privadas | C29: =EJECUCIÓN!F68+EJECUCIÓN!F69+EJECUCIÓN!F70 -> 2312121000 | D29: =EJECUCIÓN!G68+EJECUCIÓN!G69+EJECUCIÓN!G70 -> 0 | E29: =EJECUCIÓN!H68+EJECUCIÓN!H69+EJECUCIÓN!H70 -> 0 | F29: =EJECUCIÓN!I68+EJECUCIÓN!I69+EJECUCIÓN!I70 -> 2312121000 | G29: =EJECUCIÓN!J68+EJECUCIÓN!J69+EJECUCIÓN!J70 -> 125185800 | H29: =EJECUCIÓN!K68+EJECUCIÓN!K69+EJECUCIÓN!K70 -> 847400325 | I29: =EJECUCIÓN!L68+EJECUCIÓN!L69+EJECUCIÓN!L70 -> 125185800 | J29: =EJECUCIÓN!M68+EJECUCIÓN!M69+EJECUCIÓN!M70 -> 847400325 | ... L29: =EJECUCIÓN!O68+EJECUCIÓN!O69+EJECUCIÓN!O70 -> 847400325 | M29: =+J29/F29 -> 0.36650345
A30: O211010200202 | B30: Aportes a la seguridad social en salud privada | C30: =EJECUCIÓN!F73+EJECUCIÓN!F74+EJECUCIÓN!F75 -> 12565168000 | D30: =EJECUCIÓN!G73+EJECUCIÓN!G74+EJECUCIÓN!G75 -> 0 | E30: =EJECUCIÓN!H73+EJECUCIÓN!H74+EJECUCIÓN!H75 -> 0 | F30: =EJECUCIÓN!I73+EJECUCIÓN!I74+EJECUCIÓN!I75 -> 12565168000 | G30: =EJECUCIÓN!J73+EJECUCIÓN!J74+EJECUCIÓN!J75 -> 900141908 | H30: =EJECUCIÓN!K73+EJECUCIÓN!K74+EJECUCIÓN!K75 -> 6215452900 | I30: =EJECUCIÓN!L73+EJECUCIÓN!L74+EJECUCIÓN!L75 -> 900141908 | J30: =EJECUCIÓN!M73+EJECUCIÓN!M74+EJECUCIÓN!M75 -> 6215452900 | ... L30: =EJECUCIÓN!O73+EJECUCIÓN!O74+EJECUCIÓN!O75 -> 6215452900 | M30: =+J30/F30 -> 0.49465737
A31: O211010200301 | B31: Aportes de cesantías a fondos públicos | C31: =EJECUCIÓN!F78+EJECUCIÓN!F79+EJECUCIÓN!F80 -> 8087997000 | D31: =EJECUCIÓN!G78+EJECUCIÓN!G79+EJECUCIÓN!G80 -> 0 | E31: =EJECUCIÓN!H78+EJECUCIÓN!H79+EJECUCIÓN!H80 -> -100000000 | F31: =EJECUCIÓN!I78+EJECUCIÓN!I79+EJECUCIÓN!I80 -> 7987997000 | G31: =EJECUCIÓN!J78+EJECUCIÓN!J79+EJECUCIÓN!J80 -> 0 | H31: =EJECUCIÓN!K78+EJECUCIÓN!K79+EJECUCIÓN!K80 -> 7558379361 | I31: =EJECUCIÓN!L78+EJECUCIÓN!L79+EJECUCIÓN!L80 -> 0 | J31: =EJECUCIÓN!M78+EJECUCIÓN!M79+EJECUCIÓN!M80 -> 7535079637 | ... L31: =EJECUCIÓN!O78+EJECUCIÓN!O79+EJECUCIÓN!O80 -> 7524808784 | M31: =+J31/F31 -> 0.94330026
A32: O211010200302 | B32: Aportes de cesantías a fondos privados | C32: =EJECUCIÓN!F82+EJECUCIÓN!F83+EJECUCIÓN!F84 -> 7185369000 | D32: =EJECUCIÓN!G82+EJECUCIÓN!G83+EJECUCIÓN!G84 -> 0 | E32: =EJECUCIÓN!H82+EJECUCIÓN!H83+EJECUCIÓN!H84 -> -1591811575 | F32: =EJECUCIÓN!I82+EJECUCIÓN!I83+EJECUCIÓN!I84 -> 5593557425 | G32: =EJECUCIÓN!J82+EJECUCIÓN!J83+EJECUCIÓN!J84 -> 0 | H32: =EJECUCIÓN!K82+EJECUCIÓN!K83+EJECUCIÓN!K84 -> 4861270986 | I32: =EJECUCIÓN!L82+EJECUCIÓN!L83+EJECUCIÓN!L84 -> 2876123 | J32: =EJECUCIÓN!M82+EJECUCIÓN!M83+EJECUCIÓN!M84 -> 4833310132 | ... L32: =EJECUCIÓN!O82+EJECUCIÓN!O83+EJECUCIÓN!O84 -> 4833310132 | M32: =+J32/F32 -> 0.86408519
A33: O211010200401 | B33: Compensar | C33: =EJECUCIÓN!F87+EJECUCIÓN!F88+EJECUCIÓN!F89 -> 7329466000 | D33: =EJECUCIÓN!G87+EJECUCIÓN!G88+EJECUCIÓN!G89 -> 0 | E33: =EJECUCIÓN!H87+EJECUCIÓN!H88+EJECUCIÓN!H89 -> 0 | F33: =EJECUCIÓN!I87+EJECUCIÓN!I88+EJECUCIÓN!I89 -> 7329466000 | G33: =EJECUCIÓN!J87+EJECUCIÓN!J88+EJECUCIÓN!J89 -> 429266600 | H33: =EJECUCIÓN!K87+EJECUCIÓN!K88+EJECUCIÓN!K89 -> 3387810800 | I33: =EJECUCIÓN!L87+EJECUCIÓN!L88+EJECUCIÓN!L89 -> 429266600 | J33: =EJECUCIÓN!M87+EJECUCIÓN!M88+EJECUCIÓN!M89 -> 3387810800 | ... L33: =EJECUCIÓN!O87+EJECUCIÓN!O88+EJECUCIÓN!O89 -> 3387810800 | M33: =+J33/F33 -> 0.46221796
A34: O211010200501 | B34: Aportes generales al sistema de riesgos laborales públicos | C34: =EJECUCIÓN!F92+EJECUCIÓN!F93+EJECUCIÓN!F94 -> 957874000 | D34: =EJECUCIÓN!G92+EJECUCIÓN!G93+EJECUCIÓN!G94 -> 0 | E34: =EJECUCIÓN!H92+EJECUCIÓN!H93+EJECUCIÓN!H94 -> 0 | F34: =EJECUCIÓN!I92+EJECUCIÓN!I93+EJECUCIÓN!I94 -> 957874000 | G34: =EJECUCIÓN!J92+EJECUCIÓN!J93+EJECUCIÓN!J94 -> 54716500 | H34: =EJECUCIÓN!K92+EJECUCIÓN!K93+EJECUCIÓN!K94 -> 379133800 | I34: =EJECUCIÓN!L92+EJECUCIÓN!L93+EJECUCIÓN!L94 -> 54716500 | J34: =EJECUCIÓN!M92+EJECUCIÓN!M93+EJECUCIÓN!M94 -> 379133800 | ... L34: =EJECUCIÓN!O92+EJECUCIÓN!O93+EJECUCIÓN!O94 -> 379133800 | M34: =+J34/F34 -> 0.39580759
A35: O2110102006 | B35: Aportes al ICBF | C35: =EJECUCIÓN!F97+EJECUCIÓN!F98+EJECUCIÓN!F99 -> 5432095000 | D35: =EJECUCIÓN!G97+EJECUCIÓN!G98+EJECUCIÓN!G99 -> 0 | E35: =EJECUCIÓN!H97+EJECUCIÓN!H98+EJECUCIÓN!H99 -> 0 | F35: =EJECUCIÓN!I97+EJECUCIÓN!I98+EJECUCIÓN!I99 -> 5432095000 | G35: =EJECUCIÓN!J97+EJECUCIÓN!J98+EJECUCIÓN!J99 -> 321961400 | H35: =EJECUCIÓN!K97+EJECUCIÓN!K98+EJECUCIÓN!K99 -> 2540926400 | I35: =EJECUCIÓN!L97+EJECUCIÓN!L98+EJECUCIÓN!L99 -> 321961400 | J35: =EJECUCIÓN!M97+EJECUCIÓN!M98+EJECUCIÓN!M99 -> 2540926400 | ... L35: =EJECUCIÓN!O97+EJECUCIÓN!O98+EJECUCIÓN!O99 -> 2540926400 | M35: =+J35/F35 -> 0.46776178
A36: O211010300103 | B36: Bonificación especial de recreación | C36: =EJECUCIÓN!F102 -> 96799000 | D36: =EJECUCIÓN!G102 -> 0 | E36: =EJECUCIÓN!H102 -> 0 | F36: =EJECUCIÓN!I102 -> 96799000 | G36: =EJECUCIÓN!J102 -> 1550485 | H36: =EJECUCIÓN!K102 -> 11254644 | I36: =EJECUCIÓN!L102 -> 1968415 | J36: =EJECUCIÓN!M102 -> 9894748 | ... L36: =EJECUCIÓN!O102 -> 9476818 | M36: =+J36/F36 -> 0.10221953
A37: O2110103005 | B37: Reconocimiento por permanencia en el servicio público - Bogotá D.C. | C37: =EJECUCIÓN!F103 -> 382816000 | D37: =EJECUCIÓN!G103 -> 0 | E37: =EJECUCIÓN!H103 -> 0 | F37: =EJECUCIÓN!I103 -> 382816000 | G37: =EJECUCIÓN!J103 -> 0 | H37: =EJECUCIÓN!K103 -> 0 | I37: =EJECUCIÓN!L103 -> 0 | J37: =EJECUCIÓN!M103 -> 0 | ... L37: =EJECUCIÓN!O103 -> 0 | M37: =+J37/F37 -> 0
A38: O2110103068 | B38: Prima secretarial | C38: =EJECUCIÓN!F104 -> 284402000 | D38: =EJECUCIÓN!G104 -> 0 | E38: =EJECUCIÓN!H104 -> 0 | F38: =EJECUCIÓN!I104 -> 284402000 | G38: =EJECUCIÓN!J104 -> 15489585 | H38: =EJECUCIÓN!K104 -> 123290497 | I38: =EJECUCIÓN!L104 -> 15489585 | J38: =EJECUCIÓN!M104 -> 123290497 | ... L38: =EJECUCIÓN!O104 -> 123290497 | M38: =+J38/F38 -> 0.43350784
A39: O2110103121 | B39: Bonificación permanente extralegal | C39: =EJECUCIÓN!F106 -> 9373233000 | D39: =EJECUCIÓN!G106 -> 0 | E39: =EJECUCIÓN!H106 -> -32525710 | F39: =EJECUCIÓN!I106 -> 9340707290 | G39: =EJECUCIÓN!J106 -> 50411589 | H39: =EJECUCIÓN!K106 -> 8010232926 | I39: =EJECUCIÓN!L106 -> 255780102 | J39: =EJECUCIÓN!M106 -> 7901098325 | ... L39: =EJECUCIÓN!O106 -> 2890676491 | M39: =+J39/F39 -> 0.84587795
A40: O211020100101 | B40: Sueldo básico | C40: =EJECUCIÓN!F140+EJECUCIÓN!F141+EJECUCIÓN!F142+EJECUCIÓN!F143+EJECUCIÓN!F144+EJECUCIÓN!F145+EJECUCIÓN!F147+EJECUCIÓN!F146+EJECUCIÓN!F148+EJECUCIÓN!F150+EJECUCIÓN!F151+EJECUCIÓN!F152+EJECUCIÓN!F153+EJECUCIÓN!F154+EJECUCIÓN!F155 -> 55574473000 | D40: =EJECUCIÓN!G140+EJECUCIÓN!G141+EJECUCIÓN!G142+EJECUCIÓN!G143+EJECUCIÓN!G144+EJECUCIÓN!G145+EJECUCIÓN!G147+EJECUCIÓN!G146+EJECUCIÓN!G148+EJECUCIÓN!G150+EJECUCIÓN!G151+EJECUCIÓN!G152+EJECUCIÓN!G153+EJECUCIÓN!G154+EJECUCIÓN!G155 -> 53182890 | E40: =EJECUCIÓN!H140+EJECUCIÓN!H141+EJECUCIÓN!H142+EJECUCIÓN!H143+EJECUCIÓN!H144+EJECUCIÓN!H145+EJECUCIÓN!H147+EJECUCIÓN!H146+EJECUCIÓN!H148+EJECUCIÓN!H150+EJECUCIÓN!H151+EJECUCIÓN!H152+EJECUCIÓN!H153+EJECUCIÓN!H154+EJECUCIÓN!H155 -> 12465978912 | F40: =EJECUCIÓN!I140+EJECUCIÓN!I141+EJECUCIÓN!I142+EJECUCIÓN!I143+EJECUCIÓN!I144+EJECUCIÓN!I145+EJECUCIÓN!I147+EJECUCIÓN!I146+EJECUCIÓN!I148+EJECUCIÓN!I150+EJECUCIÓN!I151+EJECUCIÓN!I152+EJECUCIÓN!I153+EJECUCIÓN!I154+EJECUCIÓN!I155 -> 68040451912 | G40: =EJECUCIÓN!J140+EJECUCIÓN!J141+EJECUCIÓN!J142+EJECUCIÓN!J143+EJECUCIÓN!J144+EJECUCIÓN!J145+EJECUCIÓN!J147+EJECUCIÓN!J146+EJECUCIÓN!J148+EJECUCIÓN!J150+EJECUCIÓN!J151+EJECUCIÓN!J152+EJECUCIÓN!J153+EJECUCIÓN!J154+EJECUCIÓN!J155 -> 0 | H40: =EJECUCIÓN!K140+EJECUCIÓN!K141+EJECUCIÓN!K142+EJECUCIÓN!K143+EJECUCIÓN!K144+EJECUCIÓN!K145+EJECUCIÓN!K147+EJECUCIÓN!K146+EJECUCIÓN!K148+EJECUCIÓN!K150+EJECUCIÓN!K151+EJECUCIÓN!K152+EJECUCIÓN!K153+EJECUCIÓN!K154+EJECUCIÓN!K155 -> 67298701053 | I40: =EJECUCIÓN!L140+EJECUCIÓN!L141+EJECUCIÓN!L142+EJECUCIÓN!L143+EJECUCIÓN!L144+EJECUCIÓN!L145+EJECUCIÓN!L147+EJECUCIÓN!L146+EJECUCIÓN!L148+EJECUCIÓN!L150+EJECUCIÓN!L151+EJECUCIÓN!L152+EJECUCIÓN!L153+EJECUCIÓN!L154+EJECUCIÓN!L155 -> 8496083193 | J40: =EJECUCIÓN!M140+EJECUCIÓN!M141+EJECUCIÓN!M142+EJECUCIÓN!M143+EJECUCIÓN!M144+EJECUCIÓN!M145+EJECUCIÓN!M147+EJECUCIÓN!M146+EJECUCIÓN!M148+EJECUCIÓN!M150+EJECUCIÓN!M151+EJECUCIÓN!M152+EJECUCIÓN!M153+EJECUCIÓN!M154+EJECUCIÓN!M155 -> 62277707832 | ... L40: =EJECUCIÓN!O140+EJECUCIÓN!O141+EJECUCIÓN!O142+EJECUCIÓN!O143+EJECUCIÓN!O144+EJECUCIÓN!O145+EJECUCIÓN!O147+EJECUCIÓN!O146+EJECUCIÓN!O148+EJECUCIÓN!O150+EJECUCIÓN!O151+EJECUCIÓN!O152+EJECUCIÓN!O153+EJECUCIÓN!O154+EJECUCIÓN!O155 -> 37718487754 | M40: =+J40/F40 -> 0.91530415
A41: O211020100106 | B41: Prima de servicio | C41: =EJECUCIÓN!F158+EJECUCIÓN!F159+EJECUCIÓN!F160+EJECUCIÓN!F161+EJECUCIÓN!F162+EJECUCIÓN!F163+EJECUCIÓN!F164+EJECUCIÓN!F165+EJECUCIÓN!F167+EJECUCIÓN!F168+EJECUCIÓN!F169+EJECUCIÓN!F170+EJECUCIÓN!F171+EJECUCIÓN!F172 -> 1504837000 | D41: =EJECUCIÓN!G158+EJECUCIÓN!G159+EJECUCIÓN!G160+EJECUCIÓN!G161+EJECUCIÓN!G162+EJECUCIÓN!G163+EJECUCIÓN!G164+EJECUCIÓN!G165+EJECUCIÓN!G167+EJECUCIÓN!G168+EJECUCIÓN!G169+EJECUCIÓN!G170+EJECUCIÓN!G171+EJECUCIÓN!G172 -> 0 | E41: =EJECUCIÓN!H158+EJECUCIÓN!H159+EJECUCIÓN!H160+EJECUCIÓN!H161+EJECUCIÓN!H162+EJECUCIÓN!H163+EJECUCIÓN!H164+EJECUCIÓN!H165+EJECUCIÓN!H167+EJECUCIÓN!H168+EJECUCIÓN!H169+EJECUCIÓN!H170+EJECUCIÓN!H171+EJECUCIÓN!H172 -> 88649874 | F41: =EJECUCIÓN!I158+EJECUCIÓN!I159+EJECUCIÓN!I160+EJECUCIÓN!I161+EJECUCIÓN!I162+EJECUCIÓN!I163+EJECUCIÓN!I164+EJECUCIÓN!I165+EJECUCIÓN!I167+EJECUCIÓN!I168+EJECUCIÓN!I169+EJECUCIÓN!I170+EJECUCIÓN!I171+EJECUCIÓN!I172 -> 1593486874 | G41: =EJECUCIÓN!J158+EJECUCIÓN!J159+EJECUCIÓN!J160+EJECUCIÓN!J161+EJECUCIÓN!J162+EJECUCIÓN!J163+EJECUCIÓN!J164+EJECUCIÓN!J165+EJECUCIÓN!J167+EJECUCIÓN!J168+EJECUCIÓN!J169+EJECUCIÓN!J170+EJECUCIÓN!J171+EJECUCIÓN!J172 -> 0 | H41: =EJECUCIÓN!K158+EJECUCIÓN!K159+EJECUCIÓN!K160+EJECUCIÓN!K161+EJECUCIÓN!K162+EJECUCIÓN!K163+EJECUCIÓN!K164+EJECUCIÓN!K165+EJECUCIÓN!K167+EJECUCIÓN!K168+EJECUCIÓN!K169+EJECUCIÓN!K170+EJECUCIÓN!K171+EJECUCIÓN!K172 -> 1590462991 | I41: =EJECUCIÓN!L158+EJECUCIÓN!L159+EJECUCIÓN!L160+EJECUCIÓN!L161+EJECUCIÓN!L162+EJECUCIÓN!L163+EJECUCIÓN!L164+EJECUCIÓN!L165+EJECUCIÓN!L167+EJECUCIÓN!L168+EJECUCIÓN!L169+EJECUCIÓN!L170+EJECUCIÓN!L171+EJECUCIÓN!L172 -> 0 | J41: =EJECUCIÓN!M158+EJECUCIÓN!M159+EJECUCIÓN!M160+EJECUCIÓN!M161+EJECUCIÓN!M162+EJECUCIÓN!M163+EJECUCIÓN!M164+EJECUCIÓN!M165+EJECUCIÓN!M167+EJECUCIÓN!M168+EJECUCIÓN!M169+EJECUCIÓN!M170+EJECUCIÓN!M171+EJECUCIÓN!M172 -> 1479580895 | ... L41: =EJECUCIÓN!O158+EJECUCIÓN!O159+EJECUCIÓN!O160+EJECUCIÓN!O161+EJECUCIÓN!O162+EJECUCIÓN!O163+EJECUCIÓN!O164+EJECUCIÓN!O165+EJECUCIÓN!O167+EJECUCIÓN!O168+EJECUCIÓN!O169+EJECUCIÓN!O170+EJECUCIÓN!O171+EJECUCIÓN!O172 -> 9667522 | M41: =+J41/F41 -> 0.92851778
A42: O21102010010801 | B42: Prima de navidad | C42: =EJECUCIÓN!F176+EJECUCIÓN!F177+EJECUCIÓN!F178+EJECUCIÓN!F179+EJECUCIÓN!F180+EJECUCIÓN!F181+EJECUCIÓN!F182+EJECUCIÓN!F183+EJECUCIÓN!F185+EJECUCIÓN!F186+EJECUCIÓN!F187+EJECUCIÓN!F188+EJECUCIÓN!F189+EJECUCIÓN!F190 -> 4778651000 | D42: =EJECUCIÓN!G176+EJECUCIÓN!G177+EJECUCIÓN!G178+EJECUCIÓN!G179+EJECUCIÓN!G180+EJECUCIÓN!G181+EJECUCIÓN!G182+EJECUCIÓN!G183+EJECUCIÓN!G185+EJECUCIÓN!G186+EJECUCIÓN!G187+EJECUCIÓN!G188+EJECUCIÓN!G189+EJECUCIÓN!G190 -> 4318140 | E42: =EJECUCIÓN!H176+EJECUCIÓN!H177+EJECUCIÓN!H178+EJECUCIÓN!H179+EJECUCIÓN!H180+EJECUCIÓN!H181+EJECUCIÓN!H182+EJECUCIÓN!H183+EJECUCIÓN!H185+EJECUCIÓN!H186+EJECUCIÓN!H187+EJECUCIÓN!H188+EJECUCIÓN!H189+EJECUCIÓN!H190 -> 78431792 | F42: =EJECUCIÓN!I176+EJECUCIÓN!I177+EJECUCIÓN!I178+EJECUCIÓN!I179+EJECUCIÓN!I180+EJECUCIÓN!I181+EJECUCIÓN!I182+EJECUCIÓN!I183+EJECUCIÓN!I185+EJECUCIÓN!I186+EJECUCIÓN!I187+EJECUCIÓN!I188+EJECUCIÓN!I189+EJECUCIÓN!I190 -> 4857082792 | G42: =EJECUCIÓN!J176+EJECUCIÓN!J177+EJECUCIÓN!J178+EJECUCIÓN!J179+EJECUCIÓN!J180+EJECUCIÓN!J181+EJECUCIÓN!J182+EJECUCIÓN!J183+EJECUCIÓN!J185+EJECUCIÓN!J186+EJECUCIÓN!J187+EJECUCIÓN!J188+EJECUCIÓN!J189+EJECUCIÓN!J190 -> 0 | H42: =EJECUCIÓN!K176+EJECUCIÓN!K177+EJECUCIÓN!K178+EJECUCIÓN!K179+EJECUCIÓN!K180+EJECUCIÓN!K181+EJECUCIÓN!K182+EJECUCIÓN!K183+EJECUCIÓN!K185+EJECUCIÓN!K186+EJECUCIÓN!K187+EJECUCIÓN!K188+EJECUCIÓN!K189+EJECUCIÓN!K190 -> 4847319269 | I42: =EJECUCIÓN!L176+EJECUCIÓN!L177+EJECUCIÓN!L178+EJECUCIÓN!L179+EJECUCIÓN!L180+EJECUCIÓN!L181+EJECUCIÓN!L182+EJECUCIÓN!L183+EJECUCIÓN!L185+EJECUCIÓN!L186+EJECUCIÓN!L187+EJECUCIÓN!L188+EJECUCIÓN!L189+EJECUCIÓN!L190 -> 520583632 | J42: =EJECUCIÓN!M176+EJECUCIÓN!M177+EJECUCIÓN!M178+EJECUCIÓN!M179+EJECUCIÓN!M180+EJECUCIÓN!M181+EJECUCIÓN!M182+EJECUCIÓN!M183+EJECUCIÓN!M185+EJECUCIÓN!M186+EJECUCIÓN!M187+EJECUCIÓN!M188+EJECUCIÓN!M189+EJECUCIÓN!M190 -> 4468551764 | ... L42: =EJECUCIÓN!O176+EJECUCIÓN!O177+EJECUCIÓN!O178+EJECUCIÓN!O179+EJECUCIÓN!O180+EJECUCIÓN!O181+EJECUCIÓN!O182+EJECUCIÓN!O183+EJECUCIÓN!O185+EJECUCIÓN!O186+EJECUCIÓN!O187+EJECUCIÓN!O188+EJECUCIÓN!O189+EJECUCIÓN!O190 -> 1368204578 | M42: =+J42/F42 -> 0.92000733
A43: O21102010010802 | B43: Prima de vacaciones | C43: =EJECUCIÓN!F193+EJECUCIÓN!F194+EJECUCIÓN!F195+EJECUCIÓN!F196+EJECUCIÓN!F197+EJECUCIÓN!F198+EJECUCIÓN!F199+EJECUCIÓN!F200+EJECUCIÓN!F202+EJECUCIÓN!F203+EJECUCIÓN!F204+EJECUCIÓN!F205+EJECUCIÓN!F206+EJECUCIÓN!F207 -> 3063822000 | D43: =EJECUCIÓN!G193+EJECUCIÓN!G194+EJECUCIÓN!G195+EJECUCIÓN!G196+EJECUCIÓN!G197+EJECUCIÓN!G198+EJECUCIÓN!G199+EJECUCIÓN!G200+EJECUCIÓN!G202+EJECUCIÓN!G203+EJECUCIÓN!G204+EJECUCIÓN!G205+EJECUCIÓN!G206+EJECUCIÓN!G207 -> 2727550 | E43: =EJECUCIÓN!H193+EJECUCIÓN!H194+EJECUCIÓN!H195+EJECUCIÓN!H196+EJECUCIÓN!H197+EJECUCIÓN!H198+EJECUCIÓN!H199+EJECUCIÓN!H200+EJECUCIÓN!H202+EJECUCIÓN!H203+EJECUCIÓN!H204+EJECUCIÓN!H205+EJECUCIÓN!H206+EJECUCIÓN!H207 -> 65413348 | F43: =EJECUCIÓN!I193+EJECUCIÓN!I194+EJECUCIÓN!I195+EJECUCIÓN!I196+EJECUCIÓN!I197+EJECUCIÓN!I198+EJECUCIÓN!I199+EJECUCIÓN!I200+EJECUCIÓN!I202+EJECUCIÓN!I203+EJECUCIÓN!I204+EJECUCIÓN!I205+EJECUCIÓN!I206+EJECUCIÓN!I207 -> 3129235348 | G43: =EJECUCIÓN!J193+EJECUCIÓN!J194+EJECUCIÓN!J195+EJECUCIÓN!J196+EJECUCIÓN!J197+EJECUCIÓN!J198+EJECUCIÓN!J199+EJECUCIÓN!J200+EJECUCIÓN!J202+EJECUCIÓN!J203+EJECUCIÓN!J204+EJECUCIÓN!J205+EJECUCIÓN!J206+EJECUCIÓN!J207 -> 0 | H43: =EJECUCIÓN!K193+EJECUCIÓN!K194+EJECUCIÓN!K195+EJECUCIÓN!K196+EJECUCIÓN!K197+EJECUCIÓN!K198+EJECUCIÓN!K199+EJECUCIÓN!K200+EJECUCIÓN!K202+EJECUCIÓN!K203+EJECUCIÓN!K204+EJECUCIÓN!K205+EJECUCIÓN!K206+EJECUCIÓN!K207 -> 3122428542 | I43: =EJECUCIÓN!L193+EJECUCIÓN!L194+EJECUCIÓN!L195+EJECUCIÓN!L196+EJECUCIÓN!L197+EJECUCIÓN!L198+EJECUCIÓN!L199+EJECUCIÓN!L200+EJECUCIÓN!L202+EJECUCIÓN!L203+EJECUCIÓN!L204+EJECUCIÓN!L205+EJECUCIÓN!L206+EJECUCIÓN!L207 -> 328881254 | J43: =EJECUCIÓN!M193+EJECUCIÓN!M194+EJECUCIÓN!M195+EJECUCIÓN!M196+EJECUCIÓN!M197+EJECUCIÓN!M198+EJECUCIÓN!M199+EJECUCIÓN!M200+EJECUCIÓN!M202+EJECUCIÓN!M203+EJECUCIÓN!M204+EJECUCIÓN!M205+EJECUCIÓN!M206+EJECUCIÓN!M207 -> 2861581773 | ... L43: =EJECUCIÓN!O193+EJECUCIÓN!O194+EJECUCIÓN!O195+EJECUCIÓN!O196+EJECUCIÓN!O197+EJECUCIÓN!O198+EJECUCIÓN!O199+EJECUCIÓN!O200+EJECUCIÓN!O202+EJECUCIÓN!O203+EJECUCIÓN!O204+EJECUCIÓN!O205+EJECUCIÓN!O206+EJECUCIÓN!O207 -> 864213317 | M43: =+J43/F43 -> 0.91446678
A44: O211020200101 | B44: Aportes a la seguridad social en pensiones públicas | C44: =EJECUCIÓN!F212+EJECUCIÓN!F213+EJECUCIÓN!F214+EJECUCIÓN!F215+EJECUCIÓN!F216+EJECUCIÓN!F217+EJECUCIÓN!F218+EJECUCIÓN!F219+EJECUCIÓN!F221+EJECUCIÓN!F222+EJECUCIÓN!F223+EJECUCIÓN!F224+EJECUCIÓN!F225+EJECUCIÓN!F226 -> 3852013000 | D44: =EJECUCIÓN!G212+EJECUCIÓN!G213+EJECUCIÓN!G214+EJECUCIÓN!G215+EJECUCIÓN!G216+EJECUCIÓN!G217+EJECUCIÓN!G218+EJECUCIÓN!G219+EJECUCIÓN!G221+EJECUCIÓN!G222+EJECUCIÓN!G223+EJECUCIÓN!G224+EJECUCIÓN!G225+EJECUCIÓN!G226 -> 8606460 | E44: =EJECUCIÓN!H212+EJECUCIÓN!H213+EJECUCIÓN!H214+EJECUCIÓN!H215+EJECUCIÓN!H216+EJECUCIÓN!H217+EJECUCIÓN!H218+EJECUCIÓN!H219+EJECUCIÓN!H221+EJECUCIÓN!H222+EJECUCIÓN!H223+EJECUCIÓN!H224+EJECUCIÓN!H225+EJECUCIÓN!H226 -> 311899740 | F44: =EJECUCIÓN!I212+EJECUCIÓN!I213+EJECUCIÓN!I214+EJECUCIÓN!I215+EJECUCIÓN!I216+EJECUCIÓN!I217+EJECUCIÓN!I218+EJECUCIÓN!I219+EJECUCIÓN!I221+EJECUCIÓN!I222+EJECUCIÓN!I223+EJECUCIÓN!I224+EJECUCIÓN!I225+EJECUCIÓN!I226 -> 4163912740 | G44: =EJECUCIÓN!J212+EJECUCIÓN!J213+EJECUCIÓN!J214+EJECUCIÓN!J215+EJECUCIÓN!J216+EJECUCIÓN!J217+EJECUCIÓN!J218+EJECUCIÓN!J219+EJECUCIÓN!J221+EJECUCIÓN!J222+EJECUCIÓN!J223+EJECUCIÓN!J224+EJECUCIÓN!J225+EJECUCIÓN!J226 -> 272000000 | H44: =EJECUCIÓN!K212+EJECUCIÓN!K213+EJECUCIÓN!K214+EJECUCIÓN!K215+EJECUCIÓN!K216+EJECUCIÓN!K217+EJECUCIÓN!K218+EJECUCIÓN!K219+EJECUCIÓN!K221+EJECUCIÓN!K222+EJECUCIÓN!K223+EJECUCIÓN!K224+EJECUCIÓN!K225+EJECUCIÓN!K226 -> 3977610060 | I44: =EJECUCIÓN!L212+EJECUCIÓN!L213+EJECUCIÓN!L214+EJECUCIÓN!L215+EJECUCIÓN!L216+EJECUCIÓN!L217+EJECUCIÓN!L218+EJECUCIÓN!L219+EJECUCIÓN!L221+EJECUCIÓN!L222+EJECUCIÓN!L223+EJECUCIÓN!L224+EJECUCIÓN!L225+EJECUCIÓN!L226 -> 150290800 | J44: =EJECUCIÓN!M212+EJECUCIÓN!M213+EJECUCIÓN!M214+EJECUCIÓN!M215+EJECUCIÓN!M216+EJECUCIÓN!M217+EJECUCIÓN!M218+EJECUCIÓN!M219+EJECUCIÓN!M221+EJECUCIÓN!M222+EJECUCIÓN!M223+EJECUCIÓN!M224+EJECUCIÓN!M225+EJECUCIÓN!M226 -> 2031347340 | ... L44: =EJECUCIÓN!O212+EJECUCIÓN!O213+EJECUCIÓN!O214+EJECUCIÓN!O215+EJECUCIÓN!O216+EJECUCIÓN!O217+EJECUCIÓN!O218+EJECUCIÓN!O219+EJECUCIÓN!O221+EJECUCIÓN!O222+EJECUCIÓN!O223+EJECUCIÓN!O224+EJECUCIÓN!O225+EJECUCIÓN!O226 -> 2031347340 | M44: =+J44/F44 -> 0.4878458
A45: O211020200102 | B45: Aportes a la seguridad social en pensiones privadas | C45: =EJECUCIÓN!F229+EJECUCIÓN!F230+EJECUCIÓN!F231+EJECUCIÓN!F232+EJECUCIÓN!F233+EJECUCIÓN!F234+EJECUCIÓN!F235+EJECUCIÓN!F236+EJECUCIÓN!F238+EJECUCIÓN!F239+EJECUCIÓN!F240+EJECUCIÓN!F241+EJECUCIÓN!F242+EJECUCIÓN!F243 -> 2708285000 | D45: =EJECUCIÓN!G229+EJECUCIÓN!G230+EJECUCIÓN!G231+EJECUCIÓN!G232+EJECUCIÓN!G233+EJECUCIÓN!G234+EJECUCIÓN!G235+EJECUCIÓN!G236+EJECUCIÓN!G238+EJECUCIÓN!G239+EJECUCIÓN!G240+EJECUCIÓN!G241+EJECUCIÓN!G242+EJECUCIÓN!G243 -> 11343540 | E45: =EJECUCIÓN!H229+EJECUCIÓN!H230+EJECUCIÓN!H231+EJECUCIÓN!H232+EJECUCIÓN!H233+EJECUCIÓN!H234+EJECUCIÓN!H235+EJECUCIÓN!H236+EJECUCIÓN!H238+EJECUCIÓN!H239+EJECUCIÓN!H240+EJECUCIÓN!H241+EJECUCIÓN!H242+EJECUCIÓN!H243 -> -47115501 | F45: =EJECUCIÓN!I229+EJECUCIÓN!I230+EJECUCIÓN!I231+EJECUCIÓN!I232+EJECUCIÓN!I233+EJECUCIÓN!I234+EJECUCIÓN!I235+EJECUCIÓN!I236+EJECUCIÓN!I238+EJECUCIÓN!I239+EJECUCIÓN!I240+EJECUCIÓN!I241+EJECUCIÓN!I242+EJECUCIÓN!I243 -> 2661169499 | G45: =EJECUCIÓN!J229+EJECUCIÓN!J230+EJECUCIÓN!J231+EJECUCIÓN!J232+EJECUCIÓN!J233+EJECUCIÓN!J234+EJECUCIÓN!J235+EJECUCIÓN!J236+EJECUCIÓN!J238+EJECUCIÓN!J239+EJECUCIÓN!J240+EJECUCIÓN!J241+EJECUCIÓN!J242+EJECUCIÓN!J243 -> 162500000 | H45: =EJECUCIÓN!K229+EJECUCIÓN!K230+EJECUCIÓN!K231+EJECUCIÓN!K232+EJECUCIÓN!K233+EJECUCIÓN!K234+EJECUCIÓN!K235+EJECUCIÓN!K236+EJECUCIÓN!K238+EJECUCIÓN!K239+EJECUCIÓN!K240+EJECUCIÓN!K241+EJECUCIÓN!K242+EJECUCIÓN!K243 -> 2523094129 | I45: =EJECUCIÓN!L229+EJECUCIÓN!L230+EJECUCIÓN!L231+EJECUCIÓN!L232+EJECUCIÓN!L233+EJECUCIÓN!L234+EJECUCIÓN!L235+EJECUCIÓN!L236+EJECUCIÓN!L238+EJECUCIÓN!L239+EJECUCIÓN!L240+EJECUCIÓN!L241+EJECUCIÓN!L242+EJECUCIÓN!L243 -> 69558900 | J45: =EJECUCIÓN!M229+EJECUCIÓN!M230+EJECUCIÓN!M231+EJECUCIÓN!M232+EJECUCIÓN!M233+EJECUCIÓN!M234+EJECUCIÓN!M235+EJECUCIÓN!M236+EJECUCIÓN!M238+EJECUCIÓN!M239+EJECUCIÓN!M240+EJECUCIÓN!M241+EJECUCIÓN!M242+EJECUCIÓN!M243 -> 1087183830 | ... L45: =EJECUCIÓN!O229+EJECUCIÓN!O230+EJECUCIÓN!O231+EJECUCIÓN!O232+EJECUCIÓN!O233+EJECUCIÓN!O234+EJECUCIÓN!O235+EJECUCIÓN!O236+EJECUCIÓN!O238+EJECUCIÓN!O239+EJECUCIÓN!O240+EJECUCIÓN!O241+EJECUCIÓN!O242+EJECUCIÓN!O243 -> 1087183830 | M45: =+J45/F45 -> 0.40853611
A46: O211020200202 | B46: Aportes a la seguridad social en salud privada | C46: =EJECUCIÓN!F247+EJECUCIÓN!F248+EJECUCIÓN!F249+EJECUCIÓN!F250+EJECUCIÓN!F251+EJECUCIÓN!F252+EJECUCIÓN!F253+EJECUCIÓN!F254+EJECUCIÓN!F256+EJECUCIÓN!F257+EJECUCIÓN!F258+EJECUCIÓN!F259+EJECUCIÓN!F260+EJECUCIÓN!F261 -> 4689738000 | D46: =EJECUCIÓN!G247+EJECUCIÓN!G248+EJECUCIÓN!G249+EJECUCIÓN!G250+EJECUCIÓN!G251+EJECUCIÓN!G252+EJECUCIÓN!G253+EJECUCIÓN!G254+EJECUCIÓN!G256+EJECUCIÓN!G257+EJECUCIÓN!G258+EJECUCIÓN!G259+EJECUCIÓN!G260+EJECUCIÓN!G261 -> 8432590 | E46: =EJECUCIÓN!H247+EJECUCIÓN!H248+EJECUCIÓN!H249+EJECUCIÓN!H250+EJECUCIÓN!H251+EJECUCIÓN!H252+EJECUCIÓN!H253+EJECUCIÓN!H254+EJECUCIÓN!H256+EJECUCIÓN!H257+EJECUCIÓN!H258+EJECUCIÓN!H259+EJECUCIÓN!H260+EJECUCIÓN!H261 -> 51723212 | F46: =EJECUCIÓN!I247+EJECUCIÓN!I248+EJECUCIÓN!I249+EJECUCIÓN!I250+EJECUCIÓN!I251+EJECUCIÓN!I252+EJECUCIÓN!I253+EJECUCIÓN!I254+EJECUCIÓN!I256+EJECUCIÓN!I257+EJECUCIÓN!I258+EJECUCIÓN!I259+EJECUCIÓN!I260+EJECUCIÓN!I261 -> 4741461212 | G46: =EJECUCIÓN!J247+EJECUCIÓN!J248+EJECUCIÓN!J249+EJECUCIÓN!J250+EJECUCIÓN!J251+EJECUCIÓN!J252+EJECUCIÓN!J253+EJECUCIÓN!J254+EJECUCIÓN!J256+EJECUCIÓN!J257+EJECUCIÓN!J258+EJECUCIÓN!J259+EJECUCIÓN!J260+EJECUCIÓN!J261 -> 316000000 | H46: =EJECUCIÓN!K247+EJECUCIÓN!K248+EJECUCIÓN!K249+EJECUCIÓN!K250+EJECUCIÓN!K251+EJECUCIÓN!K252+EJECUCIÓN!K253+EJECUCIÓN!K254+EJECUCIÓN!K256+EJECUCIÓN!K257+EJECUCIÓN!K258+EJECUCIÓN!K259+EJECUCIÓN!K260+EJECUCIÓN!K261 -> 4576193922 | I46: =EJECUCIÓN!L247+EJECUCIÓN!L248+EJECUCIÓN!L249+EJECUCIÓN!L250+EJECUCIÓN!L251+EJECUCIÓN!L252+EJECUCIÓN!L253+EJECUCIÓN!L254+EJECUCIÓN!L256+EJECUCIÓN!L257+EJECUCIÓN!L258+EJECUCIÓN!L259+EJECUCIÓN!L260+EJECUCIÓN!L261 -> 156576800 | J46: =EJECUCIÓN!M247+EJECUCIÓN!M248+EJECUCIÓN!M249+EJECUCIÓN!M250+EJECUCIÓN!M251+EJECUCIÓN!M252+EJECUCIÓN!M253+EJECUCIÓN!M254+EJECUCIÓN!M256+EJECUCIÓN!M257+EJECUCIÓN!M258+EJECUCIÓN!M259+EJECUCIÓN!M260+EJECUCIÓN!M261 -> 2227903900 | ... L46: =EJECUCIÓN!O247+EJECUCIÓN!O248+EJECUCIÓN!O249+EJECUCIÓN!O250+EJECUCIÓN!O251+EJECUCIÓN!O252+EJECUCIÓN!O253+EJECUCIÓN!O254+EJECUCIÓN!O256+EJECUCIÓN!O257+EJECUCIÓN!O258+EJECUCIÓN!O259+EJECUCIÓN!O260+EJECUCIÓN!O261 -> 2227903900 | M46: =+J46/F46 -> 0.46987707
A47: O211020200301 | B47: Aportes de cesantías a fondos públicos | C47: =EJECUCIÓN!F265+EJECUCIÓN!F266+EJECUCIÓN!F267+EJECUCIÓN!F268+EJECUCIÓN!F269+EJECUCIÓN!F270+EJECUCIÓN!F271+EJECUCIÓN!F272+EJECUCIÓN!F274+EJECUCIÓN!F275+EJECUCIÓN!F276+EJECUCIÓN!F277+EJECUCIÓN!F278+EJECUCIÓN!F279 -> 5092994000 | D47: =EJECUCIÓN!G265+EJECUCIÓN!G266+EJECUCIÓN!G267+EJECUCIÓN!G268+EJECUCIÓN!G269+EJECUCIÓN!G270+EJECUCIÓN!G271+EJECUCIÓN!G272+EJECUCIÓN!G274+EJECUCIÓN!G275+EJECUCIÓN!G276+EJECUCIÓN!G277+EJECUCIÓN!G278+EJECUCIÓN!G279 -> 5168900 | E47: =EJECUCIÓN!H265+EJECUCIÓN!H266+EJECUCIÓN!H267+EJECUCIÓN!H268+EJECUCIÓN!H269+EJECUCIÓN!H270+EJECUCIÓN!H271+EJECUCIÓN!H272+EJECUCIÓN!H274+EJECUCIÓN!H275+EJECUCIÓN!H276+EJECUCIÓN!H277+EJECUCIÓN!H278+EJECUCIÓN!H279 -> 133169277 | F47: =EJECUCIÓN!I265+EJECUCIÓN!I266+EJECUCIÓN!I267+EJECUCIÓN!I268+EJECUCIÓN!I269+EJECUCIÓN!I270+EJECUCIÓN!I271+EJECUCIÓN!I272+EJECUCIÓN!I274+EJECUCIÓN!I275+EJECUCIÓN!I276+EJECUCIÓN!I277+EJECUCIÓN!I278+EJECUCIÓN!I279 -> 5226163277 | G47: =EJECUCIÓN!J265+EJECUCIÓN!J266+EJECUCIÓN!J267+EJECUCIÓN!J268+EJECUCIÓN!J269+EJECUCIÓN!J270+EJECUCIÓN!J271+EJECUCIÓN!J272+EJECUCIÓN!J274+EJECUCIÓN!J275+EJECUCIÓN!J276+EJECUCIÓN!J277+EJECUCIÓN!J278+EJECUCIÓN!J279 -> 0 | H47: =EJECUCIÓN!K265+EJECUCIÓN!K266+EJECUCIÓN!K267+EJECUCIÓN!K268+EJECUCIÓN!K269+EJECUCIÓN!K270+EJECUCIÓN!K271+EJECUCIÓN!K272+EJECUCIÓN!K274+EJECUCIÓN!K275+EJECUCIÓN!K276+EJECUCIÓN!K277+EJECUCIÓN!K278+EJECUCIÓN!K279 -> 5187097823 | I47: =EJECUCIÓN!L265+EJECUCIÓN!L266+EJECUCIÓN!L267+EJECUCIÓN!L268+EJECUCIÓN!L269+EJECUCIÓN!L270+EJECUCIÓN!L271+EJECUCIÓN!L272+EJECUCIÓN!L274+EJECUCIÓN!L275+EJECUCIÓN!L276+EJECUCIÓN!L277+EJECUCIÓN!L278+EJECUCIÓN!L279 -> 625846819 | J47: =EJECUCIÓN!M265+EJECUCIÓN!M266+EJECUCIÓN!M267+EJECUCIÓN!M268+EJECUCIÓN!M269+EJECUCIÓN!M270+EJECUCIÓN!M271+EJECUCIÓN!M272+EJECUCIÓN!M274+EJECUCIÓN!M275+EJECUCIÓN!M276+EJECUCIÓN!M277+EJECUCIÓN!M278+EJECUCIÓN!M279 -> 4648722903 | ... L47: =EJECUCIÓN!O265+EJECUCIÓN!O266+EJECUCIÓN!O267+EJECUCIÓN!O268+EJECUCIÓN!O269+EJECUCIÓN!O270+EJECUCIÓN!O271+EJECUCIÓN!O272+EJECUCIÓN!O274+EJECUCIÓN!O275+EJECUCIÓN!O276+EJECUCIÓN!O277+EJECUCIÓN!O278+EJECUCIÓN!O279 -> 1416124267 | M47: =+J47/F47 -> 0.8895097
A48: O211020200302 | B48: Aportes de cesantías a fondos privados | C48: =EJECUCIÓN!F282+EJECUCIÓN!F283+EJECUCIÓN!F284+EJECUCIÓN!F285+EJECUCIÓN!F286+EJECUCIÓN!F287+EJECUCIÓN!F288+EJECUCIÓN!F289+EJECUCIÓN!F291+EJECUCIÓN!F292+EJECUCIÓN!F293+EJECUCIÓN!F294+EJECUCIÓN!F295+EJECUCIÓN!F296 -> 690605000 | D48: =EJECUCIÓN!G282+EJECUCIÓN!G283+EJECUCIÓN!G284+EJECUCIÓN!G285+EJECUCIÓN!G286+EJECUCIÓN!G287+EJECUCIÓN!G288+EJECUCIÓN!G289+EJECUCIÓN!G291+EJECUCIÓN!G292+EJECUCIÓN!G293+EJECUCIÓN!G294+EJECUCIÓN!G295+EJECUCIÓN!G296 -> 0 | E48: =EJECUCIÓN!H282+EJECUCIÓN!H283+EJECUCIÓN!H284+EJECUCIÓN!H285+EJECUCIÓN!H286+EJECUCIÓN!H287+EJECUCIÓN!H288+EJECUCIÓN!H289+EJECUCIÓN!H291+EJECUCIÓN!H292+EJECUCIÓN!H293+EJECUCIÓN!H294+EJECUCIÓN!H295+EJECUCIÓN!H296 -> 500000 | F48: =EJECUCIÓN!I282+EJECUCIÓN!I283+EJECUCIÓN!I284+EJECUCIÓN!I285+EJECUCIÓN!I286+EJECUCIÓN!I287+EJECUCIÓN!I288+EJECUCIÓN!I289+EJECUCIÓN!I291+EJECUCIÓN!I292+EJECUCIÓN!I293+EJECUCIÓN!I294+EJECUCIÓN!I295+EJECUCIÓN!I296 -> 691105000 | G48: =EJECUCIÓN!J282+EJECUCIÓN!J283+EJECUCIÓN!J284+EJECUCIÓN!J285+EJECUCIÓN!J286+EJECUCIÓN!J287+EJECUCIÓN!J288+EJECUCIÓN!J289+EJECUCIÓN!J291+EJECUCIÓN!J292+EJECUCIÓN!J293+EJECUCIÓN!J294+EJECUCIÓN!J295+EJECUCIÓN!J296 -> 0 | H48: =EJECUCIÓN!K282+EJECUCIÓN!K283+EJECUCIÓN!K284+EJECUCIÓN!K285+EJECUCIÓN!K286+EJECUCIÓN!K287+EJECUCIÓN!K288+EJECUCIÓN!K289+EJECUCIÓN!K291+EJECUCIÓN!K292+EJECUCIÓN!K293+EJECUCIÓN!K294+EJECUCIÓN!K295+EJECUCIÓN!K296 -> 690605000 | I48: =EJECUCIÓN!L282+EJECUCIÓN!L283+EJECUCIÓN!L284+EJECUCIÓN!L285+EJECUCIÓN!L286+EJECUCIÓN!L287+EJECUCIÓN!L288+EJECUCIÓN!L289+EJECUCIÓN!L291+EJECUCIÓN!L292+EJECUCIÓN!L293+EJECUCIÓN!L294+EJECUCIÓN!L295+EJECUCIÓN!L296 -> -2718333 | J48: =EJECUCIÓN!M282+EJECUCIÓN!M283+EJECUCIÓN!M284+EJECUCIÓN!M285+EJECUCIÓN!M286+EJECUCIÓN!M287+EJECUCIÓN!M288+EJECUCIÓN!M289+EJECUCIÓN!M291+EJECUCIÓN!M292+EJECUCIÓN!M293+EJECUCIÓN!M294+EJECUCIÓN!M295+EJECUCIÓN!M296 -> 684844594 | ... L48: =EJECUCIÓN!O282+EJECUCIÓN!O283+EJECUCIÓN!O284+EJECUCIÓN!O285+EJECUCIÓN!O286+EJECUCIÓN!O287+EJECUCIÓN!O288+EJECUCIÓN!O289+EJECUCIÓN!O291+EJECUCIÓN!O292+EJECUCIÓN!O293+EJECUCIÓN!O294+EJECUCIÓN!O295+EJECUCIÓN!O296 -> 221587315 | M48: =+J48/F48 -> 0.99094145
A49: O211020200401 | B49: Compensar | C49: =EJECUCIÓN!F300+EJECUCIÓN!F301+EJECUCIÓN!F302+EJECUCIÓN!F303+EJECUCIÓN!F304+EJECUCIÓN!F305+EJECUCIÓN!F306+EJECUCIÓN!F307+EJECUCIÓN!F309+EJECUCIÓN!F310+EJECUCIÓN!F311+EJECUCIÓN!F312+EJECUCIÓN!F313+EJECUCIÓN!F314 -> 2324082000 | D49: =EJECUCIÓN!G300+EJECUCIÓN!G301+EJECUCIÓN!G302+EJECUCIÓN!G303+EJECUCIÓN!G304+EJECUCIÓN!G305+EJECUCIÓN!G306+EJECUCIÓN!G307+EJECUCIÓN!G309+EJECUCIÓN!G310+EJECUCIÓN!G311+EJECUCIÓN!G312+EJECUCIÓN!G313+EJECUCIÓN!G314 -> 3490440 | E49: =EJECUCIÓN!H300+EJECUCIÓN!H301+EJECUCIÓN!H302+EJECUCIÓN!H303+EJECUCIÓN!H304+EJECUCIÓN!H305+EJECUCIÓN!H306+EJECUCIÓN!H307+EJECUCIÓN!H309+EJECUCIÓN!H310+EJECUCIÓN!H311+EJECUCIÓN!H312+EJECUCIÓN!H313+EJECUCIÓN!H314 -> 26695641 | F49: =EJECUCIÓN!I300+EJECUCIÓN!I301+EJECUCIÓN!I302+EJECUCIÓN!I303+EJECUCIÓN!I304+EJECUCIÓN!I305+EJECUCIÓN!I306+EJECUCIÓN!I307+EJECUCIÓN!I309+EJECUCIÓN!I310+EJECUCIÓN!I311+EJECUCIÓN!I312+EJECUCIÓN!I313+EJECUCIÓN!I314 -> 2350777641 | G49: =EJECUCIÓN!J300+EJECUCIÓN!J301+EJECUCIÓN!J302+EJECUCIÓN!J303+EJECUCIÓN!J304+EJECUCIÓN!J305+EJECUCIÓN!J306+EJECUCIÓN!J307+EJECUCIÓN!J309+EJECUCIÓN!J310+EJECUCIÓN!J311+EJECUCIÓN!J312+EJECUCIÓN!J313+EJECUCIÓN!J314 -> 159000000 | H49: =EJECUCIÓN!K300+EJECUCIÓN!K301+EJECUCIÓN!K302+EJECUCIÓN!K303+EJECUCIÓN!K304+EJECUCIÓN!K305+EJECUCIÓN!K306+EJECUCIÓN!K307+EJECUCIÓN!K309+EJECUCIÓN!K310+EJECUCIÓN!K311+EJECUCIÓN!K312+EJECUCIÓN!K313+EJECUCIÓN!K314 -> 2285722001 | I49: =EJECUCIÓN!L300+EJECUCIÓN!L301+EJECUCIÓN!L302+EJECUCIÓN!L303+EJECUCIÓN!L304+EJECUCIÓN!L305+EJECUCIÓN!L306+EJECUCIÓN!L307+EJECUCIÓN!L309+EJECUCIÓN!L310+EJECUCIÓN!L311+EJECUCIÓN!L312+EJECUCIÓN!L313+EJECUCIÓN!L314 -> 73920800 | J49: =EJECUCIÓN!M300+EJECUCIÓN!M301+EJECUCIÓN!M302+EJECUCIÓN!M303+EJECUCIÓN!M304+EJECUCIÓN!M305+EJECUCIÓN!M306+EJECUCIÓN!M307+EJECUCIÓN!M309+EJECUCIÓN!M310+EJECUCIÓN!M311+EJECUCIÓN!M312+EJECUCIÓN!M313+EJECUCIÓN!M314 -> 1098762400 | ... L49: =EJECUCIÓN!O300+EJECUCIÓN!O301+EJECUCIÓN!O302+EJECUCIÓN!O303+EJECUCIÓN!O304+EJECUCIÓN!O305+EJECUCIÓN!O306+EJECUCIÓN!O307+EJECUCIÓN!O309+EJECUCIÓN!O310+EJECUCIÓN!O311+EJECUCIÓN!O312+EJECUCIÓN!O313+EJECUCIÓN!O314 -> 1098762400 | M49: =+J49/F49 -> 0.4674038
A50: O211020200501 | B50: Aportes generales al sistema de riesgos laborales públicos | C50: =EJECUCIÓN!F318+EJECUCIÓN!F319+EJECUCIÓN!F320+EJECUCIÓN!F321+EJECUCIÓN!F322+EJECUCIÓN!F323+EJECUCIÓN!F324+EJECUCIÓN!F325+EJECUCIÓN!F327+EJECUCIÓN!F328+EJECUCIÓN!F329+EJECUCIÓN!F330+EJECUCIÓN!F331+EJECUCIÓN!F332 -> 288000000 | D50: =EJECUCIÓN!G318+EJECUCIÓN!G319+EJECUCIÓN!G320+EJECUCIÓN!G321+EJECUCIÓN!G322+EJECUCIÓN!G323+EJECUCIÓN!G324+EJECUCIÓN!G325+EJECUCIÓN!G327+EJECUCIÓN!G328+EJECUCIÓN!G329+EJECUCIÓN!G330+EJECUCIÓN!G331+EJECUCIÓN!G332 -> 434150 | E50: =EJECUCIÓN!H318+EJECUCIÓN!H319+EJECUCIÓN!H320+EJECUCIÓN!H321+EJECUCIÓN!H322+EJECUCIÓN!H323+EJECUCIÓN!H324+EJECUCIÓN!H325+EJECUCIÓN!H327+EJECUCIÓN!H328+EJECUCIÓN!H329+EJECUCIÓN!H330+EJECUCIÓN!H331+EJECUCIÓN!H332 -> 22614930 | F50: =EJECUCIÓN!I318+EJECUCIÓN!I319+EJECUCIÓN!I320+EJECUCIÓN!I321+EJECUCIÓN!I322+EJECUCIÓN!I323+EJECUCIÓN!I324+EJECUCIÓN!I325+EJECUCIÓN!I327+EJECUCIÓN!I328+EJECUCIÓN!I329+EJECUCIÓN!I330+EJECUCIÓN!I331+EJECUCIÓN!I332 -> 310614930 | G50: =EJECUCIÓN!J318+EJECUCIÓN!J319+EJECUCIÓN!J320+EJECUCIÓN!J321+EJECUCIÓN!J322+EJECUCIÓN!J323+EJECUCIÓN!J324+EJECUCIÓN!J325+EJECUCIÓN!J327+EJECUCIÓN!J328+EJECUCIÓN!J329+EJECUCIÓN!J330+EJECUCIÓN!J331+EJECUCIÓN!J332 -> 19500000 | H50: =EJECUCIÓN!K318+EJECUCIÓN!K319+EJECUCIÓN!K320+EJECUCIÓN!K321+EJECUCIÓN!K322+EJECUCIÓN!K323+EJECUCIÓN!K324+EJECUCIÓN!K325+EJECUCIÓN!K327+EJECUCIÓN!K328+EJECUCIÓN!K329+EJECUCIÓN!K330+EJECUCIÓN!K331+EJECUCIÓN!K332 -> 297348980 | I50: =EJECUCIÓN!L318+EJECUCIÓN!L319+EJECUCIÓN!L320+EJECUCIÓN!L321+EJECUCIÓN!L322+EJECUCIÓN!L323+EJECUCIÓN!L324+EJECUCIÓN!L325+EJECUCIÓN!L327+EJECUCIÓN!L328+EJECUCIÓN!L329+EJECUCIÓN!L330+EJECUCIÓN!L331+EJECUCIÓN!L332 -> 9633400 | J50: =EJECUCIÓN!M318+EJECUCIÓN!M319+EJECUCIÓN!M320+EJECUCIÓN!M321+EJECUCIÓN!M322+EJECUCIÓN!M323+EJECUCIÓN!M324+EJECUCIÓN!M325+EJECUCIÓN!M327+EJECUCIÓN!M328+EJECUCIÓN!M329+EJECUCIÓN!M330+EJECUCIÓN!M331+EJECUCIÓN!M332 -> 137061500 | ... L50: =EJECUCIÓN!O318+EJECUCIÓN!O319+EJECUCIÓN!O320+EJECUCIÓN!O321+EJECUCIÓN!O322+EJECUCIÓN!O323+EJECUCIÓN!O324+EJECUCIÓN!O325+EJECUCIÓN!O327+EJECUCIÓN!O328+EJECUCIÓN!O329+EJECUCIÓN!O330+EJECUCIÓN!O331+EJECUCIÓN!O332 -> 137061500 | M50: =+J50/F50 -> 0.44125857
A51: O2110202006 | B51: Aportes al ICBF | C51: =EJECUCIÓN!F335+EJECUCIÓN!F336+EJECUCIÓN!F337+EJECUCIÓN!F338+EJECUCIÓN!F339+EJECUCIÓN!F340+EJECUCIÓN!F341+EJECUCIÓN!F342+EJECUCIÓN!F344+EJECUCIÓN!F345+EJECUCIÓN!F346+EJECUCIÓN!F347+EJECUCIÓN!F348+EJECUCIÓN!F349 -> 1744649000 | D51: =EJECUCIÓN!G335+EJECUCIÓN!G336+EJECUCIÓN!G337+EJECUCIÓN!G338+EJECUCIÓN!G339+EJECUCIÓN!G340+EJECUCIÓN!G341+EJECUCIÓN!G342+EJECUCIÓN!G344+EJECUCIÓN!G345+EJECUCIÓN!G346+EJECUCIÓN!G347+EJECUCIÓN!G348+EJECUCIÓN!G349 -> 2495100 | E51: =EJECUCIÓN!H335+EJECUCIÓN!H336+EJECUCIÓN!H337+EJECUCIÓN!H338+EJECUCIÓN!H339+EJECUCIÓN!H340+EJECUCIÓN!H341+EJECUCIÓN!H342+EJECUCIÓN!H344+EJECUCIÓN!H345+EJECUCIÓN!H346+EJECUCIÓN!H347+EJECUCIÓN!H348+EJECUCIÓN!H349 -> 31214899 | F51: =EJECUCIÓN!I335+EJECUCIÓN!I336+EJECUCIÓN!I337+EJECUCIÓN!I338+EJECUCIÓN!I339+EJECUCIÓN!I340+EJECUCIÓN!I341+EJECUCIÓN!I342+EJECUCIÓN!I344+EJECUCIÓN!I345+EJECUCIÓN!I346+EJECUCIÓN!I347+EJECUCIÓN!I348+EJECUCIÓN!I349 -> 1775863899 | G51: =EJECUCIÓN!J335+EJECUCIÓN!J336+EJECUCIÓN!J337+EJECUCIÓN!J338+EJECUCIÓN!J339+EJECUCIÓN!J340+EJECUCIÓN!J341+EJECUCIÓN!J342+EJECUCIÓN!J344+EJECUCIÓN!J345+EJECUCIÓN!J346+EJECUCIÓN!J347+EJECUCIÓN!J348+EJECUCIÓN!J349 -> 116500000 | H51: =EJECUCIÓN!K335+EJECUCIÓN!K336+EJECUCIÓN!K337+EJECUCIÓN!K338+EJECUCIÓN!K339+EJECUCIÓN!K340+EJECUCIÓN!K341+EJECUCIÓN!K342+EJECUCIÓN!K344+EJECUCIÓN!K345+EJECUCIÓN!K346+EJECUCIÓN!K347+EJECUCIÓN!K348+EJECUCIÓN!K349 -> 1724638949 | I51: =EJECUCIÓN!L335+EJECUCIÓN!L336+EJECUCIÓN!L337+EJECUCIÓN!L338+EJECUCIÓN!L339+EJECUCIÓN!L340+EJECUCIÓN!L341+EJECUCIÓN!L342+EJECUCIÓN!L344+EJECUCIÓN!L345+EJECUCIÓN!L346+EJECUCIÓN!L347+EJECUCIÓN!L348+EJECUCIÓN!L349 -> 55436900 | J51: =EJECUCIÓN!M335+EJECUCIÓN!M336+EJECUCIÓN!M337+EJECUCIÓN!M338+EJECUCIÓN!M339+EJECUCIÓN!M340+EJECUCIÓN!M341+EJECUCIÓN!M342+EJECUCIÓN!M344+EJECUCIÓN!M345+EJECUCIÓN!M346+EJECUCIÓN!M347+EJECUCIÓN!M348+EJECUCIÓN!M349 -> 824128650 | ... L51: =EJECUCIÓN!O335+EJECUCIÓN!O336+EJECUCIÓN!O337+EJECUCIÓN!O338+EJECUCIÓN!O339+EJECUCIÓN!O340+EJECUCIÓN!O341+EJECUCIÓN!O342+EJECUCIÓN!O344+EJECUCIÓN!O345+EJECUCIÓN!O346+EJECUCIÓN!O347+EJECUCIÓN!O348+EJECUCIÓN!O349 -> 824128650 | M51: =+J51/F51 -> 0.46407197
A52: O21201010030302 | B52: Maquinaria de informática y sus partes, piezas y accesorios | C52: =EJECUCIÓN!F355 -> 31356000 | D52: =EJECUCIÓN!G355 -> 0 | E52: =EJECUCIÓN!H355 -> 0 | F52: =EJECUCIÓN!I355 -> 31356000 | G52: =EJECUCIÓN!J355 -> 0 | H52: =EJECUCIÓN!K355 -> 0 | I52: =EJECUCIÓN!L355 -> 0 | J52: =EJECUCIÓN!M355 -> 0 | ... L52: =EJECUCIÓN!O355 -> 0 | M52: =+J52/F52 -> 0
A53: O2120101004010102 | B53: Muebles del tipo utilizado en la oficina | C53: =EJECUCIÓN!F362+EJECUCIÓN!F364 -> 0 | D53: =EJECUCIÓN!G362+EJECUCIÓN!G364 -> 0 | E53: =EJECUCIÓN!H362+EJECUCIÓN!H364 -> 0 | F53: =EJECUCIÓN!I362+EJECUCIÓN!I364 -> 0 | G53: =EJECUCIÓN!J362+EJECUCIÓN!J364 -> 0 | H53: =EJECUCIÓN!K362+EJECUCIÓN!K364 -> 0 | I53: =EJECUCIÓN!L362+EJECUCIÓN!L364 -> 0 | J53: =EJECUCIÓN!M362+EJECUCIÓN!M364 -> 0 | ... L53: =EJECUCIÓN!O362+EJECUCIÓN!O364 -> 0 | M53: =+J53/F53 -> #DIV/0!
A54: O212010100502030101 | B54: Paquetes de software | C54: =EJECUCIÓN!F370 -> 3348874000 | D54: =EJECUCIÓN!G370 -> 0 | E54: =EJECUCIÓN!H370 -> 129363035 | F54: =EJECUCIÓN!I370 -> 3478237035 | G54: =EJECUCIÓN!J370 -> -237759927 | H54: =EJECUCIÓN!K370 -> 1986170101 | I54: =EJECUCIÓN!L370 -> 522932101 | J54: =EJECUCIÓN!M370 -> 522932101 | ... L54: =EJECUCIÓN!O370 -> 0 | M54: =+J54/F54 -> 0.15034401
A55: O2120201002082823609 | B55: Uniformes de trabajo | C55: =EJECUCIÓN!F380 -> 167232000 | D55: =EJECUCIÓN!G380 -> 0 | E55: =EJECUCIÓN!H380 -> 0 | F55: =EJECUCIÓN!I380 -> 167232000 | G55: =EJECUCIÓN!J380 -> 0 | H55: =EJECUCIÓN!K380 -> 0 | I55: =EJECUCIÓN!L380 -> 0 | J55: =EJECUCIÓN!M380 -> 0 | ... L55: =EJECUCIÓN!O380 -> 0 | M55: =+J55/F55 -> 0
A56: O2120201003023211599 | B56: Pastas o pulpas de otras fibras n.c.p. para papel | C56: =EJECUCIÓN!F385 -> 320975000 | D56: =EJECUCIÓN!G385 -> 0 | E56: =EJECUCIÓN!H385 -> -3052264 | F56: =EJECUCIÓN!I385 -> 317922736 | G56: =EJECUCIÓN!J385 -> -73031775 | H56: =EJECUCIÓN!K385 -> 11497000 | I56: =EJECUCIÓN!L385 -> 0 | J56: =EJECUCIÓN!M385 -> 0 | ... L56: =EJECUCIÓN!O385 -> 0 | M56: =+J56/F56 -> 0
A57: O2120201003033331101 | B57: Gasolina motor corriente | C57: =EJECUCIÓN!F393 -> 48831000 | D57: =EJECUCIÓN!G393 -> 0 | E57: =EJECUCIÓN!H393 -> 0 | F57: =EJECUCIÓN!I393 -> 48831000 | G57: =EJECUCIÓN!J393 -> 0 | H57: =EJECUCIÓN!K393 -> 48831000 | I57: =EJECUCIÓN!L393 -> 0 | J57: =EJECUCIÓN!M393 -> 48831000 | ... L57: =EJECUCIÓN!O393 -> 13724876 | M57: =+J57/F57 -> 1
A58: O2120201003033336103 | B58: Diésel oil ACPM (fuel gas gasoil marine gas) | C58: =EJECUCIÓN!F395 -> 22102000 | D58: =EJECUCIÓN!G395 -> 0 | E58: =EJECUCIÓN!H395 -> 0 | F58: =EJECUCIÓN!I395 -> 22102000 | G58: =EJECUCIÓN!J395 -> 0 | H58: =EJECUCIÓN!K395 -> 0 | I58: =EJECUCIÓN!L395 -> 0 | J58: =EJECUCIÓN!M395 -> 0 | ... L58: =EJECUCIÓN!O395 -> 0 | M58: =+J58/F58 -> 0
A59: O2120201003053526199 | B59: Otros medicamentos n.c.p. para uso humano terapéutico o profiláctico | C59: =EJECUCIÓN!F398 -> 73164000 | D59: =EJECUCIÓN!G398 -> 0 | E59: =EJECUCIÓN!H398 -> 0 | F59: =EJECUCIÓN!I398 -> 73164000 | G59: =EJECUCIÓN!J398 -> 0 | H59: =EJECUCIÓN!K398 -> 73164000 | I59: =EJECUCIÓN!L398 -> 73164000 | J59: =EJECUCIÓN!M398 -> 73164000 | ... L59: =EJECUCIÓN!O398 -> 0 | M59: =+J59/F59 -> 1
A60: O2120201003063699060 | B60: Cartuchos plásticos para impresora de computador | C60: =EJECUCIÓN!F401+EJECUCIÓN!F402+EJECUCIÓN!F403 -> 98132000 | D60: =EJECUCIÓN!G401+EJECUCIÓN!G402+EJECUCIÓN!G403 -> 0 | E60: =EJECUCIÓN!H401+EJECUCIÓN!H402+EJECUCIÓN!H403 -> -18763989 | F60: =EJECUCIÓN!I401+EJECUCIÓN!I402+EJECUCIÓN!I403 -> 79368011 | G60: =EJECUCIÓN!J401+EJECUCIÓN!J402+EJECUCIÓN!J403 -> -79368011 | H60: =EJECUCIÓN!K401+EJECUCIÓN!K402+EJECUCIÓN!K403 -> 0 | I60: =EJECUCIÓN!L401+EJECUCIÓN!L402+EJECUCIÓN!L403 -> 0 | J60: =EJECUCIÓN!M401+EJECUCIÓN!M402+EJECUCIÓN!M403 -> 0 | ... L60: =EJECUCIÓN!O401+EJECUCIÓN!O402+EJECUCIÓN!O403 -> 0 | M60: =+J60/F60 -> 0
A61: O2120201003083899997 | B61: Artículos n.c.p. para protección | C61: =EJECUCIÓN!F406 -> 30000000 | D61: =EJECUCIÓN!G406 -> 0 | E61: =EJECUCIÓN!H406 -> 0 | F61: =EJECUCIÓN!I406 -> 30000000 | G61: =EJECUCIÓN!J406 -> 0 | H61: =EJECUCIÓN!K406 -> 0 | I61: =EJECUCIÓN!L406 -> 0 | J61: =EJECUCIÓN!M406 -> 0 | ... L61: =EJECUCIÓN!O406 -> 0 | M61: =+J61/F61 -> 0
A62: O2120201004024299991 | B62: Artículos n.c.p. de ferretería y cerrajería | C62: =EJECUCIÓN!F410+EJECUCIÓN!F411+EJECUCIÓN!F412 -> 160433000 | D62: =EJECUCIÓN!G410+EJECUCIÓN!G411+EJECUCIÓN!G412 -> 0 | E62: =EJECUCIÓN!H410+EJECUCIÓN!H411+EJECUCIÓN!H412 -> 9792677 | F62: =EJECUCIÓN!I410+EJECUCIÓN!I411+EJECUCIÓN!I412 -> 170225677 | G62: =EJECUCIÓN!J410+EJECUCIÓN!J411+EJECUCIÓN!J412 -> 0 | H62: =EJECUCIÓN!K410+EJECUCIÓN!K411+EJECUCIÓN!K412 -> 129792677 | I62: =EJECUCIÓN!L410+EJECUCIÓN!L411+EJECUCIÓN!L412 -> 9792677 | J62: =EJECUCIÓN!M410+EJECUCIÓN!M411+EJECUCIÓN!M412 -> 129792677 | ... L62: =EJECUCIÓN!O410+EJECUCIÓN!O411+EJECUCIÓN!O412 -> 9792677 | M62: =+J62/F62 -> 0.76247414
A63: O2120201004044481708 | B63: Hornos microondas | C63: =EJECUCIÓN!F416 -> 0 | D63: =EJECUCIÓN!G416 -> 0 | E63: =EJECUCIÓN!H416 -> 0 | F63: =EJECUCIÓN!I416 -> 0 | G63: =EJECUCIÓN!J416 -> 0 | H63: =EJECUCIÓN!K416 -> 0 | I63: =EJECUCIÓN!L416 -> 0 | J63: =EJECUCIÓN!M416 -> 0 | ... L63: =EJECUCIÓN!O416 -> 0 | M63: =+J63/F63 -> #DIV/0!
A64: O2120201004054516099 | B64: Máquinas y material de oficina n.c.p. | C64: =EJECUCIÓN!F419 -> 0 | D64: =EJECUCIÓN!G419 -> 0 | E64: =EJECUCIÓN!H419 -> 0 | F64: =EJECUCIÓN!I419 -> 0 | G64: =EJECUCIÓN!J419 -> 0 | H64: =EJECUCIÓN!K419 -> 0 | I64: =EJECUCIÓN!L419 -> 0 | J64: =EJECUCIÓN!M419 -> 0 | ... L64: =EJECUCIÓN!O419 -> 0 | M64: =+J64/F64 -> #DIV/0!
A65: O2120202005040754710 | B65: Servicios de instalación de vidrios y ventanas | C65: =EJECUCIÓN!F428 -> 0 | D65: =EJECUCIÓN!G428 -> 0 | E65: =EJECUCIÓN!H428 -> 0 | F65: =EJECUCIÓN!I428 -> 0 | G65: =EJECUCIÓN!J428 -> 0 | H65: =EJECUCIÓN!K428 -> 0 | I65: =EJECUCIÓN!L428 -> 0 | J65: =EJECUCIÓN!M428 -> 0 | ... L65: =EJECUCIÓN!O428 -> 0 | M65: =+J65/F65 -> #DIV/0!
A66: O21202020060363290 | B66: Todos los demás servicios de alojamiento en habitaciones o unidades | C66: =EJECUCIÓN!F433 -> 457575000 | D66: =EJECUCIÓN!G433 -> 0 | E66: =EJECUCIÓN!H433 -> 202462067 | F66: =EJECUCIÓN!I433 -> 660037067 | G66: =EJECUCIÓN!J433 -> 22563792 | H66: =EJECUCIÓN!K433 -> 334112811 | I66: =EJECUCIÓN!L433 -> 35167693 | J66: =EJECUCIÓN!M433 -> 300358712 | ... L66: =EJECUCIÓN!O433 -> 114305618 | M66: =+J66/F66 -> 0.4550634
A67: O21202020060363399 | B67: Otros servicios de suministro de comidas | C67: =EJECUCIÓN!F448 -> 4725153000 | D67: =EJECUCIÓN!G448 -> 0 | E67: =EJECUCIÓN!H448 -> 0 | F67: =EJECUCIÓN!I448 -> 4725153000 | G67: =EJECUCIÓN!J448 -> 0 | H67: =EJECUCIÓN!K448 -> 2362227600 | I67: =EJECUCIÓN!L448 -> 0 | J67: =EJECUCIÓN!M448 -> 2362227600 | ... L67: =EJECUCIÓN!O448 -> 0 | M67: =+J67/F67 -> 0.49992616
A68: O21202020060464220 | B68: Servicios de transporte terrestre de pasajeros, diferente del transporte local y turístico de pasajeros | C68: =EJECUCIÓN!F452+EJECUCIÓN!F451 -> 3032038000 | D68: =EJECUCIÓN!G452+EJECUCIÓN!G451 -> 0 | E68: =EJECUCIÓN!H452+EJECUCIÓN!H451 -> 1052889712 | F68: =EJECUCIÓN!I452+EJECUCIÓN!I451 -> 4084927712 | G68: =EJECUCIÓN!J452+EJECUCIÓN!J451 -> 0 | H68: =EJECUCIÓN!K452+EJECUCIÓN!K451 -> 3757627061 | I68: =EJECUCIÓN!L452+EJECUCIÓN!L451 -> 31342991 | J68: =EJECUCIÓN!M452+EJECUCIÓN!M451 -> 3739752959 | ... L68: =EJECUCIÓN!O452+EJECUCIÓN!O451 -> 1015770135 | M68: =+J68/F68 -> 0.9155004
A69: O21202020060464241 | B69: Servicios de transporte aéreo de pasajeros, excepto los servicios de aerotaxi | C69: =EJECUCIÓN!F462 -> 1074610000 | D69: =EJECUCIÓN!G462 -> 0 | E69: =EJECUCIÓN!H462 -> -136022000 | F69: =EJECUCIÓN!I462 -> 938588000 | G69: =EJECUCIÓN!J462 -> 60126060 | H69: =EJECUCIÓN!K462 -> 332732801 | I69: =EJECUCIÓN!L462 -> 14260478 | J69: =EJECUCIÓN!M462 -> 278128609 | ... L69: =EJECUCIÓN!O462 -> 270176849 | M69: =+J69/F69 -> 0.29632662
A70: O21202020060868021 | B70: Servicios locales de mensajería nacional | C70: =EJECUCIÓN!F481 -> 64133000 | D70: =EJECUCIÓN!G481 -> 0 | E70: =EJECUCIÓN!H481 -> 0 | F70: =EJECUCIÓN!I481 -> 64133000 | G70: =EJECUCIÓN!J481 -> 0 | H70: =EJECUCIÓN!K481 -> 29020591 | I70: =EJECUCIÓN!L481 -> 0 | J70: =EJECUCIÓN!M481 -> 29020591 | ... L70: =EJECUCIÓN!O481 -> 5835264 | M70: =+J70/F70 -> 0.45250637
A71: O212020200701030371332 | B71: Servicios de seguros sociales de riesgos laborales | C71: =EJECUCIÓN!F488 -> 186775000 | D71: =EJECUCIÓN!G488 -> 0 | E71: =EJECUCIÓN!H488 -> 0 | F71: =EJECUCIÓN!I488 -> 186775000 | G71: =EJECUCIÓN!J488 -> 10315500 | H71: =EJECUCIÓN!K488 -> 136404900 | I71: =EJECUCIÓN!L488 -> 10315500 | J71: =EJECUCIÓN!M488 -> 136404900 | ... L71: =EJECUCIÓN!O488 -> 136404900 | M71: =+J71/F71 -> 0.73031669
A72: O212020200701030471346 | B72: Servicios de planes complementarios de salud | C72: =EJECUCIÓN!F491 -> 520000000 | D72: =EJECUCIÓN!G491 -> 0 | E72: =EJECUCIÓN!H491 -> 0 | F72: =EJECUCIÓN!I491 -> 520000000 | G72: =EJECUCIÓN!J491 -> 0 | H72: =EJECUCIÓN!K491 -> 500474520 | I72: =EJECUCIÓN!L491 -> 0 | J72: =EJECUCIÓN!M491 -> 500474520 | ... L72: =EJECUCIÓN!O491 -> 96261103 | M72: =+J72/F72 -> 0.962451
A73: O212020200701030471347 | B73: Servicio de seguro obligatorio de accidentes de tránsito (SOAT) | C73: =EJECUCIÓN!F493 -> 14717000 | D73: =EJECUCIÓN!G493 -> 0 | E73: =EJECUCIÓN!H493 -> 0 | F73: =EJECUCIÓN!I493 -> 14717000 | G73: =EJECUCIÓN!J493 -> -85800 | H73: =EJECUCIÓN!K493 -> 11215700 | I73: =EJECUCIÓN!L493 -> 11215700 | J73: =EJECUCIÓN!M493 -> 11215700 | ... L73: =EJECUCIÓN!O493 -> 0 | M73: =+J73/F73 -> 0.76209146
A74: O212020200701030571351 | B74: Servicios de seguros de vehículos automotores | C74: =EJECUCIÓN!F496 -> 32478000 | D74: =EJECUCIÓN!G496 -> 0 | E74: =EJECUCIÓN!H496 -> 0 | F74: =EJECUCIÓN!I496 -> 32478000 | G74: =EJECUCIÓN!J496 -> -627606 | H74: =EJECUCIÓN!K496 -> 27196260 | I74: =EJECUCIÓN!L496 -> 27196260 | J74: =EJECUCIÓN!M496 -> 27196260 | ... L74: =EJECUCIÓN!O496 -> 0 | M74: =+J74/F74 -> 0.83737484
A75: O212020200701030571354 | B75: Servicios de seguros contra incendio, terremoto o sustracción | C75: =EJECUCIÓN!F498 -> 2759273000 | D75: =EJECUCIÓN!G498 -> 0 | E75: =EJECUCIÓN!H498 -> 0 | F75: =EJECUCIÓN!I498 -> 2759273000 | G75: =EJECUCIÓN!J498 -> -141911101 | H75: =EJECUCIÓN!K498 -> 2263462457 | I75: =EJECUCIÓN!L498 -> 2257272629 | J75: =EJECUCIÓN!M498 -> 2263462457 | ... L75: =EJECUCIÓN!O498 -> 9317796 | M75: =+J75/F75 -> 0.82031117
A76: O212020200701030571355 | B76: Servicios de seguros generales de responsabilidad civil | C76: =EJECUCIÓN!F500 -> 1739925000 | D76: =EJECUCIÓN!G500 -> 0 | E76: =EJECUCIÓN!H500 -> 0 | F76: =EJECUCIÓN!I500 -> 1739925000 | G76: =EJECUCIÓN!J500 -> -65848270 | H76: =EJECUCIÓN!K500 -> 1605833600 | I76: =EJECUCIÓN!L500 -> 1605833600 | J76: =EJECUCIÓN!M500 -> 1605833600 | ... L76: =EJECUCIÓN!O500 -> 0 | M76: =+J76/F76 -> 0.92293266
A77: O212020200701030571356 | B77: Servicios de seguros de cumplimiento | C77: =EJECUCIÓN!F502 -> 0 | D77: =EJECUCIÓN!G502 -> 0 | E77: =EJECUCIÓN!H502 -> 0 | F77: =EJECUCIÓN!I502 -> 0 | G77: =EJECUCIÓN!J502 -> 0 | H77: =EJECUCIÓN!K502 -> 0 | I77: =EJECUCIÓN!L502 -> 0 | J77: =EJECUCIÓN!M502 -> 0 | ... L77: =EJECUCIÓN!O502 -> 0 | M77: =+J77/F77 -> #DIV/0!
A78: O2120202007010671630 | B78: Servicios actuariales | C78: =EJECUCIÓN!F506 -> 69888000 | D78: =EJECUCIÓN!G506 -> 0 | E78: =EJECUCIÓN!H506 -> 0 | F78: =EJECUCIÓN!I506 -> 69888000 | G78: =EJECUCIÓN!J506 -> 0 | H78: =EJECUCIÓN!K506 -> 0 | I78: =EJECUCIÓN!L506 -> 0 | J78: =EJECUCIÓN!M506 -> 0 | ... L78: =EJECUCIÓN!O506 -> 0 | M78: =+J78/F78 -> 0
A79: O21202020070272112 | B79: Servicios de alquiler o arrendamiento con o sin opción de compra, relativos a bienes inmuebles no residenciales (diferentes a vivienda), propios o arrendados | C79: =EJECUCIÓN!F509 -> 2549082000 | D79: =EJECUCIÓN!G509 -> 0 | E79: =EJECUCIÓN!H509 -> 3400527089 | F79: =EJECUCIÓN!I509 -> 5949609089 | G79: =EJECUCIÓN!J509 -> 109224335 | H79: =EJECUCIÓN!K509 -> 5043025866 | I79: =EJECUCIÓN!L509 -> 1275507220 | J79: =EJECUCIÓN!M509 -> 5035975418 | ... L79: =EJECUCIÓN!O509 -> 991465640 | M79: =+J79/F79 -> 0.84643803
A80: O21202020070373290 | B80: Servicios de arrendamiento o alquiler de otros productos n.c.p. | C80: =EJECUCIÓN!F519 -> 125478000 | D80: =EJECUCIÓN!G519 -> 0 | E80: =EJECUCIÓN!H519 -> 0 | F80: =EJECUCIÓN!I519 -> 125478000 | G80: =EJECUCIÓN!J519 -> 0 | H80: =EJECUCIÓN!K519 -> 0 | I80: =EJECUCIÓN!L519 -> 0 | J80: =EJECUCIÓN!M519 -> 0 | ... L80: =EJECUCIÓN!O519 -> 0 | M80: =+J80/F80 -> 0
A81: O21202020080181302 | B81: Servicios interdisciplinarios de investigación aplicada | C81: =EJECUCIÓN!F523 -> 584972000 | D81: =EJECUCIÓN!G523 -> 0 | E81: =EJECUCIÓN!H523 -> -20239120 | F81: =EJECUCIÓN!I523 -> 564732880 | G81: =EJECUCIÓN!J523 -> 1000000 | H81: =EJECUCIÓN!K523 -> 183831670 | I81: =EJECUCIÓN!L523 -> 10478712 | J81: =EJECUCIÓN!M523 -> 87987718 | ... L81: =EJECUCIÓN!O523 -> 52517870 | M81: =+J81/F81 -> 0.15580414
A82: O21202020080282130 | B82: Servicios de documentación y certificación jurídica | C82: =EJECUCIÓN!F532 -> 1968000 | D82: =EJECUCIÓN!G532 -> 0 | E82: =EJECUCIÓN!H532 -> 1300000 | F82: =EJECUCIÓN!I532 -> 3268000 | G82: =EJECUCIÓN!J532 -> 0 | H82: =EJECUCIÓN!K532 -> 2874446 | I82: =EJECUCIÓN!L532 -> 525385 | J82: =EJECUCIÓN!M532 -> 2874446 | ... L82: =EJECUCIÓN!O532 -> 2874446 | M82: =+J82/F82 -> 0.87957344
A83: O21202020080282199 | B83: Otros servicios jurídicos n.c.p. | C83: =EJECUCIÓN!F537 -> 1839115000 | D83: =EJECUCIÓN!G537 -> 0 | E83: =EJECUCIÓN!H537 -> 690363913 | F83: =EJECUCIÓN!I537 -> 2529478913 | G83: =EJECUCIÓN!J537 -> 70526168 | H83: =EJECUCIÓN!K537 -> 1929146017 | I83: =EJECUCIÓN!L537 -> 280800491 | J83: =EJECUCIÓN!M537 -> 1841683565 | ... L83: =EJECUCIÓN!O537 -> 1273719203 | M83: =+J83/F83 -> 0.72808813
A84: O21202020080383115 | B84: Servicios de consultoría en gestión administrativa | C84: =EJECUCIÓN!F543+EJECUCIÓN!F551+EJECUCIÓN!F553+EJECUCIÓN!F555+EJECUCIÓN!F557+EJECUCIÓN!F559+EJECUCIÓN!F561+EJECUCIÓN!F563+EJECUCIÓN!F578+EJECUCIÓN!F593+EJECUCIÓN!F596+EJECUCIÓN!F600+EJECUCIÓN!F602+EJECUCIÓN!F608+EJECUCIÓN!F610 -> 51373981000 | D84: =EJECUCIÓN!G543+EJECUCIÓN!G551+EJECUCIÓN!G553+EJECUCIÓN!G555+EJECUCIÓN!G557+EJECUCIÓN!G559+EJECUCIÓN!G561+EJECUCIÓN!G563+EJECUCIÓN!G578+EJECUCIÓN!G593+EJECUCIÓN!G596+EJECUCIÓN!G600+EJECUCIÓN!G602+EJECUCIÓN!G608+EJECUCIÓN!G610 -> 656320000 | E84: =EJECUCIÓN!H543+EJECUCIÓN!H551+EJECUCIÓN!H553+EJECUCIÓN!H555+EJECUCIÓN!H557+EJECUCIÓN!H559+EJECUCIÓN!H561+EJECUCIÓN!H563+EJECUCIÓN!H578+EJECUCIÓN!H593+EJECUCIÓN!H596+EJECUCIÓN!H600+EJECUCIÓN!H602+EJECUCIÓN!H608+EJECUCIÓN!H610 -> 14026236403 | F84: =EJECUCIÓN!I543+EJECUCIÓN!I551+EJECUCIÓN!I553+EJECUCIÓN!I555+EJECUCIÓN!I557+EJECUCIÓN!I559+EJECUCIÓN!I561+EJECUCIÓN!I563+EJECUCIÓN!I578+EJECUCIÓN!I593+EJECUCIÓN!I596+EJECUCIÓN!I600+EJECUCIÓN!I602+EJECUCIÓN!I608+EJECUCIÓN!I610 -> 65400217403 | G84: =EJECUCIÓN!J543+EJECUCIÓN!J551+EJECUCIÓN!J553+EJECUCIÓN!J555+EJECUCIÓN!J557+EJECUCIÓN!J559+EJECUCIÓN!J561+EJECUCIÓN!J563+EJECUCIÓN!J578+EJECUCIÓN!J593+EJECUCIÓN!J596+EJECUCIÓN!J600+EJECUCIÓN!J602+EJECUCIÓN!J608+EJECUCIÓN!J610 -> 6937649837 | H84: =EJECUCIÓN!K543+EJECUCIÓN!K551+EJECUCIÓN!K553+EJECUCIÓN!K555+EJECUCIÓN!K557+EJECUCIÓN!K559+EJECUCIÓN!K561+EJECUCIÓN!K563+EJECUCIÓN!K578+EJECUCIÓN!K593+EJECUCIÓN!K596+EJECUCIÓN!K600+EJECUCIÓN!K602+EJECUCIÓN!K608+EJECUCIÓN!K610 -> 60798032643 | I84: =EJECUCIÓN!L543+EJECUCIÓN!L551+EJECUCIÓN!L553+EJECUCIÓN!L555+EJECUCIÓN!L557+EJECUCIÓN!L559+EJECUCIÓN!L561+EJECUCIÓN!L563+EJECUCIÓN!L578+EJECUCIÓN!L593+EJECUCIÓN!L596+EJECUCIÓN!L600+EJECUCIÓN!L602+EJECUCIÓN!L608+EJECUCIÓN!L610 -> 14539468434 | J84: =EJECUCIÓN!M543+EJECUCIÓN!M551+EJECUCIÓN!M553+EJECUCIÓN!M555+EJECUCIÓN!M557+EJECUCIÓN!M559+EJECUCIÓN!M561+EJECUCIÓN!M563+EJECUCIÓN!M578+EJECUCIÓN!M593+EJECUCIÓN!M596+EJECUCIÓN!M600+EJECUCIÓN!M602+EJECUCIÓN!M608+EJECUCIÓN!M610 -> 58377098465 | ... L84: =EJECUCIÓN!O543+EJECUCIÓN!O551+EJECUCIÓN!O553+EJECUCIÓN!O555+EJECUCIÓN!O557+EJECUCIÓN!O559+EJECUCIÓN!O561+EJECUCIÓN!O563+EJECUCIÓN!O578+EJECUCIÓN!O593+EJECUCIÓN!O596+EJECUCIÓN!O600+EJECUCIÓN!O602+EJECUCIÓN!O608+EJECUCIÓN!O610 -> 36074646304 | M84: =+J84/F84 -> 0.89261322
A85: O21202020080383131 | B85: Servicios de consultoría en tecnologías de la información (TI) | C85: =EJECUCIÓN!F614 -> 98972000 | D85: =EJECUCIÓN!G614 -> 0 | E85: =EJECUCIÓN!H614 -> 0 | F85: =EJECUCIÓN!I614 -> 98972000 | G85: =EJECUCIÓN!J614 -> 0 | H85: =EJECUCIÓN!K614 -> 0 | I85: =EJECUCIÓN!L614 -> 0 | J85: =EJECUCIÓN!M614 -> 0 | ... L85: =EJECUCIÓN!O614 -> 0 | M85: =+J85/F85 -> 0
A86: O21202020080383132 | B86: Servicios de soporte en tecnologías de la información (TI) | C86: =EJECUCIÓN!F616 -> 3047724000 | D86: =EJECUCIÓN!G616 -> 0 | E86: =EJECUCIÓN!H616 -> 660574458 | F86: =EJECUCIÓN!I616 -> 3708298458 | G86: =EJECUCIÓN!J616 -> -38471179 | H86: =EJECUCIÓN!K616 -> 3618065488 | I86: =EJECUCIÓN!L616 -> 1225817993 | J86: =EJECUCIÓN!M616 -> 3434868522 | ... L86: =EJECUCIÓN!O616 -> 1986585892 | M86: =+J86/F86 -> 0.92626539
A87: O21202020080383449 | B87: Otros servicios de ensayos y análisis técnicos | C87: =EJECUCIÓN!F620 -> 2000000 | D87: =EJECUCIÓN!G620 -> 0 | E87: =EJECUCIÓN!H620 -> 0 | F87: =EJECUCIÓN!I620 -> 2000000 | G87: =EJECUCIÓN!J620 -> 0 | H87: =EJECUCIÓN!K620 -> 0 | I87: =EJECUCIÓN!L620 -> 0 | J87: =EJECUCIÓN!M620 -> 0 | ... L87: =EJECUCIÓN!O620 -> 0 | M87: =+J87/F87 -> 0
A88: O21202020080383619 | B88: Otros servicios de publicidad | C88: =EJECUCIÓN!F623 -> 422096000 | D88: =EJECUCIÓN!G623 -> 0 | E88: =EJECUCIÓN!H623 -> -85000000 | F88: =EJECUCIÓN!I623 -> 337096000 | G88: =EJECUCIÓN!J623 -> -231438 | H88: =EJECUCIÓN!K623 -> 249979562 | I88: =EJECUCIÓN!L623 -> 47028562 | J88: =EJECUCIÓN!M623 -> 244366116 | ... L88: =EJECUCIÓN!O623 -> 85553000 | M88: =+J88/F88 -> 0.7249155
A89: O21202020080383620 | B89: Servicios de venta o alquiler de espacio o tiempo publicitario a comisión | C89: =EJECUCIÓN!F632 -> 0 | D89: =EJECUCIÓN!G632 -> 0 | E89: =EJECUCIÓN!H632 -> 0 | F89: =EJECUCIÓN!I632 -> 0 | G89: =EJECUCIÓN!J632 -> 0 | H89: =EJECUCIÓN!K632 -> 0 | I89: =EJECUCIÓN!L632 -> 0 | J89: =EJECUCIÓN!M632 -> 0 | ... L89: =EJECUCIÓN!O632 -> 0 | M89: =+J89/F89 -> #DIV/0!
A90: O21202020080484110 | B90: Servicios de operadores (conexión) | C90: =EJECUCIÓN!F637 -> 25004000 | D90: =EJECUCIÓN!G637 -> 0 | E90: =EJECUCIÓN!H637 -> 0 | F90: =EJECUCIÓN!I637 -> 25004000 | G90: =EJECUCIÓN!J637 -> 0 | H90: =EJECUCIÓN!K637 -> 25004000 | I90: =EJECUCIÓN!L637 -> 273100 | J90: =EJECUCIÓN!M637 -> 2548150 | ... L90: =EJECUCIÓN!O637 -> 2548150 | M90: =+J90/F90 -> 0.10190969
A91: O21202020080484120 | B91: Servicios de telefonía fija (acceso) | C91: =EJECUCIÓN!F639 -> 244864000 | D91: =EJECUCIÓN!G639 -> 0 | E91: =EJECUCIÓN!H639 -> 0 | F91: =EJECUCIÓN!I639 -> 244864000 | G91: =EJECUCIÓN!J639 -> 0 | H91: =EJECUCIÓN!K639 -> 244864000 | I91: =EJECUCIÓN!L639 -> 12601570 | J91: =EJECUCIÓN!M639 -> 115974539 | ... L91: =EJECUCIÓN!O639 -> 115959069 | M91: =+J91/F91 -> 0.47362838
A92: O21202020080484222 | B92: Servicios de acceso a Internet de banda ancha | C92: =EJECUCIÓN!F642 -> 883885000 | D92: =EJECUCIÓN!G642 -> 0 | E92: =EJECUCIÓN!H642 -> 0 | F92: =EJECUCIÓN!I642 -> 883885000 | G92: =EJECUCIÓN!J642 -> 633883488 | H92: =EJECUCIÓN!K642 -> 883883488 | I92: =EJECUCIÓN!L642 -> 633883488 | J92: =EJECUCIÓN!M642 -> 883883488 | ... L92: =EJECUCIÓN!O642 -> 18055072 | M92: =+J92/F92 -> 0.99999829
A93: O21202020080484611 | B93: Servicios de transmisión de programas de radio | C93: =EJECUCIÓN!F645 -> 54500000 | D93: =EJECUCIÓN!G645 -> 0 | E93: =EJECUCIÓN!H645 -> 17281589 | F93: =EJECUCIÓN!I645 -> 71781589 | G93: =EJECUCIÓN!J645 -> 0 | H93: =EJECUCIÓN!K645 -> 48465180 | I93: =EJECUCIÓN!L645 -> 0 | J93: =EJECUCIÓN!M645 -> 48465180 | ... L93: =EJECUCIÓN!O645 -> 48465180 | M93: =+J93/F93 -> 0.67517564
A94: O21202020080484633 | B94: Servicios de distribución de programas multicanal, en paquete controlado de programación | C94: =EJECUCIÓN!F647 -> 2300000 | D94: =EJECUCIÓN!G647 -> 0 | E94: =EJECUCIÓN!H647 -> 0 | F94: =EJECUCIÓN!I647 -> 2300000 | G94: =EJECUCIÓN!J647 -> 0 | H94: =EJECUCIÓN!K647 -> 0 | I94: =EJECUCIÓN!L647 -> 0 | J94: =EJECUCIÓN!M647 -> 0 | ... L94: =EJECUCIÓN!O647 -> 0 | M94: =+J94/F94 -> 0
A95: O21202020080585230 | B95: Servicios de sistemas de seguridad | C95: =EJECUCIÓN!F651 -> 95472000 | D95: =EJECUCIÓN!G651 -> 0 | E95: =EJECUCIÓN!H651 -> 0 | F95: =EJECUCIÓN!I651 -> 95472000 | G95: =EJECUCIÓN!J651 -> 0 | H95: =EJECUCIÓN!K651 -> 0 | I95: =EJECUCIÓN!L651 -> 0 | J95: =EJECUCIÓN!M651 -> 0 | ... L95: =EJECUCIÓN!O651 -> 0 | M95: =+J95/F95 -> 0
A96: O21202020080585250 | B96: Servicios de protección (guardas de seguridad) | C96: =EJECUCIÓN!F653 -> 16983259000 | D96: =EJECUCIÓN!G653 -> 8437333289 | E96: =EJECUCIÓN!H653 -> 8449034313 | F96: =EJECUCIÓN!I653 -> 25432293313 | G96: =EJECUCIÓN!J653 -> 0 | H96: =EJECUCIÓN!K653 -> 16902923398 | I96: =EJECUCIÓN!L653 -> 0 | J96: =EJECUCIÓN!M653 -> 16891222374 | ... L96: =EJECUCIÓN!O653 -> 11091468197 | M96: =+J96/F96 -> 0.66416434
A97: O21202020080585310 | B97: Servicios de desinfección y exterminación | C97: =EJECUCIÓN!F656 -> 243542000 | D97: =EJECUCIÓN!G656 -> 0 | E97: =EJECUCIÓN!H656 -> 1000000 | F97: =EJECUCIÓN!I656 -> 244542000 | G97: =EJECUCIÓN!J656 -> 227335000 | H97: =EJECUCIÓN!K656 -> 227335000 | I97: =EJECUCIÓN!L656 -> 0 | J97: =EJECUCIÓN!M656 -> 0 | ... L97: =EJECUCIÓN!O656 -> 0 | M97: =+J97/F97 -> 0
A98: O21202020080585330 | B98: Servicios de limpieza general | C98: =EJECUCIÓN!F661 -> 6697204000 | D98: =EJECUCIÓN!G661 -> 3191765747 | E98: =EJECUCIÓN!H661 -> 3191765747 | F98: =EJECUCIÓN!I661 -> 9888969747 | G98: =EJECUCIÓN!J661 -> 347903750 | H98: =EJECUCIÓN!K661 -> 6618913702 | I98: =EJECUCIÓN!L661 -> 347903750 | J98: =EJECUCIÓN!M661 -> 6618913702 | ... L98: =EJECUCIÓN!O661 -> 4575356789 | M98: =+J98/F98 -> 0.66932288
A99: O21202020080585340 | B99: Servicios especializados de limpieza | C99: =EJECUCIÓN!F663 -> 93932000 | D99: =EJECUCIÓN!G663 -> 0 | E99: =EJECUCIÓN!H663 -> 0 | F99: =EJECUCIÓN!I663 -> 93932000 | G99: =EJECUCIÓN!J663 -> 0 | H99: =EJECUCIÓN!K663 -> 0 | I99: =EJECUCIÓN!L663 -> 0 | J99: =EJECUCIÓN!M663 -> 0 | ... L99: =EJECUCIÓN!O663 -> 0 | M99: =+J99/F99 -> 0
A100: O21202020080585954 | B100: Servicios de preparación de documentos y otros servicios especializados de apoyo a oficina | C100: =EJECUCIÓN!F667 -> 387458000 | D100: =EJECUCIÓN!G667 -> 0 | E100: =EJECUCIÓN!H667 -> 4076000 | F100: =EJECUCIÓN!I667 -> 391534000 | G100: =EJECUCIÓN!J667 -> 4600000 | H100: =EJECUCIÓN!K667 -> 345956236 | I100: =EJECUCIÓN!L667 -> 0 | J100: =EJECUCIÓN!M667 -> 341356236 | ... L100: =EJECUCIÓN!O667 -> 68691602 | M100: =+J100/F100 -> 0.87184315
A101: O21202020080585961 | B101: Servicios de organización y asistencia de convenciones | C101: =EJECUCIÓN!F677+EJECUCIÓN!F693 -> 2161836000 | D101: =EJECUCIÓN!G677+EJECUCIÓN!G693 -> 42400000 | E101: =EJECUCIÓN!H677+EJECUCIÓN!H693 -> 942872993 | F101: =EJECUCIÓN!I677+EJECUCIÓN!I693 -> 3104708993 | G101: =EJECUCIÓN!J677+EJECUCIÓN!J693 -> 104709560 | H101: =EJECUCIÓN!K677+EJECUCIÓN!K693 -> 819733706 | I101: =EJECUCIÓN!L677+EJECUCIÓN!L693 -> 212689163 | J101: =EJECUCIÓN!M677+EJECUCIÓN!M693 -> 721888856 | ... L101: =EJECUCIÓN!O677+EJECUCIÓN!O693 -> 406666239 | M101: =+J101/F101 -> 0.23251418
A102: O21202020080686312 | B102: Servicios de distribución de electricidad (a comisión o por contrato) | C102: =EJECUCIÓN!F712 -> 3457425000 | D102: =EJECUCIÓN!G712 -> 0 | E102: =EJECUCIÓN!H712 -> 0 | F102: =EJECUCIÓN!I712 -> 3457425000 | G102: =EJECUCIÓN!J712 -> 0 | H102: =EJECUCIÓN!K712 -> 3457425000 | I102: =EJECUCIÓN!L712 -> 224637230 | J102: =EJECUCIÓN!M712 -> 1742028459 | ... L102: =EJECUCIÓN!O712 -> 1711583149 | M102: =+J102/F102 -> 0.50385141
A103: O21202020080686320 | B103: Servicios de distribución de gas por tuberías (a comisión o por contrato) | C103: =EJECUCIÓN!F714 -> 15866000 | D103: =EJECUCIÓN!G714 -> 0 | E103: =EJECUCIÓN!H714 -> 0 | F103: =EJECUCIÓN!I714 -> 15866000 | G103: =EJECUCIÓN!J714 -> 0 | H103: =EJECUCIÓN!K714 -> 15852319 | I103: =EJECUCIÓN!L714 -> 228860 | J103: =EJECUCIÓN!M714 -> 3967741 | ... L103: =EJECUCIÓN!O714 -> 3809321 | M103: =+J103/F103 -> 0.25007822
A104: O21202020080686330 | B104: Servicios de distribución de agua por tubería (a comisión o por contrato) | C104: =EJECUCIÓN!F716 -> 361152000 | D104: =EJECUCIÓN!G716 -> 0 | E104: =EJECUCIÓN!H716 -> 0 | F104: =EJECUCIÓN!I716 -> 361152000 | G104: =EJECUCIÓN!J716 -> 0 | H104: =EJECUCIÓN!K716 -> 361152000 | I104: =EJECUCIÓN!L716 -> 22657429 | J104: =EJECUCIÓN!M716 -> 257784877 | ... L104: =EJECUCIÓN!O716 -> 257784877 | M104: =+J104/F104 -> 0.71378499
A105: O2120202008078711099 | B105: Servicio de mantenimiento y reparación de otros productos metálicos elaborados n.c.p. | C105: =EJECUCIÓN!F720+EJECUCIÓN!F722 -> 326236000 | D105: =EJECUCIÓN!G720+EJECUCIÓN!G722 -> 0 | E105: =EJECUCIÓN!H720+EJECUCIÓN!H722 -> 53586544 | F105: =EJECUCIÓN!I720+EJECUCIÓN!I722 -> 379822544 | G105: =EJECUCIÓN!J720+EJECUCIÓN!J722 -> 0 | H105: =EJECUCIÓN!K720+EJECUCIÓN!K722 -> 131960482 | I105: =EJECUCIÓN!L720+EJECUCIÓN!L722 -> 0 | J105: =EJECUCIÓN!M720+EJECUCIÓN!M722 -> 53967544 | ... L105: =EJECUCIÓN!O720+EJECUCIÓN!O722 -> 53967544 | M105: =+J105/F105 -> 0.14208621
...
