Workbook
Name _Hlk137488061: Ponderacion!$A$1
Name _Toc474160443: anterior!$A$15
Name _Toc474160444: anterior!$A$20
Name _Toc9345829: anterior!$A$16
Name _Toc9345832: anterior!$A$21
Name _Toc9345835: anterior!$A$26
Name _Toc9345838: anterior!$B$31
Name _Toc9345841: anterior!$H$11
Name _Toc9345844: anterior!$H$16
Name _Toc9345847: anterior!$H$21
Name _Toc9345850: anterior!$H$26
Name _Toc9345853: anterior!$H$31
Name _Toc9345856: anterior!$B$38
Name _Toc9348702: anterior!$A$10
Name _Toc9348705: anterior!$A$25
Name _Toc9348706: anterior!$A$30
Name _Toc9348707: anterior!$H$10
Name _Toc9348708: anterior!$H$15
Name _Toc9348709: anterior!$H$20
Name _Toc9348710: anterior!$H$25
Name _Toc9348711: anterior!$H$30
Name _Toc9348712: anterior!$B$36

Sheet FACTORES
A1: Haga clic para escribir el texto de la pregunta | B1: Valor del factor | C1: Recuento | E1: Puntuación | G1: Prueba puntuación | H1: =SUM(C2:C13) -> 0 | I1: =SUM(I2:I145) -> 1482
A2: PROYECTO EDUCATIVO DEL PROGRAMA E IDENTIDAD INSTITUCIONAL. | B2: 1 | C2: 5 | D2: 5 | E2: 12 | G2: =IF(C2>=1,E2,0) -> 12 | H2: =G2*C2 -> 60 | I2: =SUM(H2:H13) -> 179 | J2: =I2/$I$1 -> 0.12078273
A3: PROYECTO EDUCATIVO DEL PROGRAMA E IDENTIDAD INSTITUCIONAL. | B3: 2 | C3: 4 | D3: 4 | E3: 11 | G3: =IF(C3>=1,E3,0) -> 11 | H3: =G3*C3 -> 44
A4: PROYECTO EDUCATIVO DEL PROGRAMA E IDENTIDAD INSTITUCIONAL. | B4: 3 | C4: 1 | D4: 1 | E4: 10 | G4: =IF(C4>=1,E4,0) -> 10 | H4: =G4*C4 -> 10
A5: PROYECTO EDUCATIVO DEL PROGRAMA E IDENTIDAD INSTITUCIONAL. | B5: 4 | C5: 3 | D5: 3 | E5: 9 | G5: =IF(C5>=1,E5,0) -> 9 | H5: =G5*C5 -> 27
A6: PROYECTO EDUCATIVO DEL PROGRAMA E IDENTIDAD INSTITUCIONAL. | B6: 5 | C6: 2 | D6: 2 | E6: 8 | G6: =IF(C6>=1,E6,0) -> 8 | H6: =G6*C6 -> 16
A7: PROYECTO EDUCATIVO DEL PROGRAMA E IDENTIDAD INSTITUCIONAL. | B7: 6 | C7: 2 | D7: 2 | E7: 7 | G7: =IF(C7>=1,E7,0) -> 7 | H7: =G7*C7 -> 14
A8: PROYECTO EDUCATIVO DEL PROGRAMA E IDENTIDAD INSTITUCIONAL. | B8: 7 | C8: 0 | D8: 0 | E8: 6 | G8: =IF(C8>=1,E8,0) -> 6 | H8: =G8*C8 -> 0
A9: PROYECTO EDUCATIVO DEL PROGRAMA E IDENTIDAD INSTITUCIONAL. | B9: 8 | C9: 1 | D9: 1 | E9: 5 | G9: =IF(C9>=1,E9,0) -> 5 | H9: =G9*C9 -> 5
A10: PROYECTO EDUCATIVO DEL PROGRAMA E IDENTIDAD INSTITUCIONAL. | B10: 9 | C10: 0 | D10: 0 | E10: 4 | G10: =IF(C10>=1,E10,0) -> 4 | H10: =G10*C10 -> 0
A11: PROYECTO EDUCATIVO DEL PROGRAMA E IDENTIDAD INSTITUCIONAL. | B11: 10 | C11: 1 | D11: 1 | E11: 3 | G11: =IF(C11>=1,E11,0) -> 3 | H11: =G11*C11 -> 3
A12: PROYECTO EDUCATIVO DEL PROGRAMA E IDENTIDAD INSTITUCIONAL. | B12: 11 | C12: 0 | D12: 0 | E12: 2 | G12: =IF(C12>=1,E12,0) -> 2 | H12: =G12*C12 -> 0
A13: PROYECTO EDUCATIVO DEL PROGRAMA E IDENTIDAD INSTITUCIONAL. | B13: 12 | C13: 0 | D13: 0 | E13: 1 | G13: =IF(C13>=1,E13,0) -> 1 | H13: =G13*C13 -> 0
A14: ESTUDIANTES | B14: 1 | C14: 8 | D14: 8 | E14: 12 | G14: =IF(C14>=1,E14,0) -> 12 | H14: =G14*C14 -> 96 | I14: =SUM(H14:H25) -> 184 | J14: =I14/$I$1 -> 0.12415655
A15: ESTUDIANTES | B15: 2 | C15: 1 | D15: 1 | E15: 11 | G15: =IF(C15>=1,E15,0) -> 11 | H15: =G15*C15 -> 11
A16: ESTUDIANTES | B16: 3 | C16: 4 | D16: 4 | E16: 10 | G16: =IF(C16>=1,E16,0) -> 10 | H16: =G16*C16 -> 40
A17: ESTUDIANTES | B17: 4 | C17: 0 | D17: 0 | E17: 9 | G17: =IF(C17>=1,E17,0) -> 9 | H17: =G17*C17 -> 0
A18: ESTUDIANTES | B18: 5 | C18: 2 | D18: 2 | E18: 8 | G18: =IF(C18>=1,E18,0) -> 8 | H18: =G18*C18 -> 16
A19: ESTUDIANTES | B19: 6 | C19: 1 | D19: 1 | E19: 7 | G19: =IF(C19>=1,E19,0) -> 7 | H19: =G19*C19 -> 7
A20: ESTUDIANTES | B20: 7 | C20: 1 | D20: 1 | E20: 6 | G20: =IF(C20>=1,E20,0) -> 6 | H20: =G20*C20 -> 6
A21: ESTUDIANTES | B21: 8 | C21: 1 | D21: 1 | E21: 5 | G21: =IF(C21>=1,E21,0) -> 5 | H21: =G21*C21 -> 5
A22: ESTUDIANTES | B22: 9 | C22: 0 | D22: 0 | E22: 4 | G22: =IF(C22>=1,E22,0) -> 4 | H22: =G22*C22 -> 0
A23: ESTUDIANTES | B23: 10 | C23: 1 | D23: 1 | E23: 3 | G23: =IF(C23>=1,E23,0) -> 3 | H23: =G23*C23 -> 3
A24: ESTUDIANTES | B24: 11 | C24: 0 | D24: 0 | E24: 2 | G24: =IF(C24>=1,E24,0) -> 2 | H24: =G24*C24 -> 0
A25: ESTUDIANTES | B25: 12 | C25: 0 | D25: 0 | E25: 1 | G25: =IF(C25>=1,E25,0) -> 1 | H25: =G25*C25 -> 0
A26: PROFESORES | B26: 1 | C26: 1 | D26: 1 | E26: 12 | G26: =IF(C26>=1,E26,0) -> 12 | H26: =G26*C26 -> 12 | I26: =SUM(H26:H37) -> 173 | J26: =I26/$I$1 -> 0.11673414
A27: PROFESORES | B27: 2 | C27: 7 | D27: 7 | E27: 11 | G27: =IF(C27>=1,E27,0) -> 11 | H27: =G27*C27 -> 77
A28: PROFESORES | B28: 3 | C28: 4 | D28: 4 | E28: 10 | G28: =IF(C28>=1,E28,0) -> 10 | H28: =G28*C28 -> 40
A29: PROFESORES | B29: 4 | C29: 2 | D29: 2 | E29: 9 | G29: =IF(C29>=1,E29,0) -> 9 | H29: =G29*C29 -> 18
A30: PROFESORES | B30: 5 | C30: 0 | D30: 0 | E30: 8 | G30: =IF(C30>=1,E30,0) -> 8 | H30: =G30*C30 -> 0
A31: PROFESORES | B31: 6 | C31: 1 | D31: 1 | E31: 7 | G31: =IF(C31>=1,E31,0) -> 7 | H31: =G31*C31 -> 7
A32: PROFESORES | B32: 7 | C32: 1 | D32: 1 | E32: 6 | G32: =IF(C32>=1,E32,0) -> 6 | H32: =G32*C32 -> 6
A33: PROFESORES | B33: 8 | C33: 1 | D33: 1 | E33: 5 | G33: =IF(C33>=1,E33,0) -> 5 | H33: =G33*C33 -> 5
A34: PROFESORES | B34: 9 | C34: 2 | D34: 2 | E34: 4 | G34: =IF(C34>=1,E34,0) -> 4 | H34: =G34*C34 -> 8
A35: PROFESORES | B35: 10 | C35: 0 | D35: 0 | E35: 3 | G35: =IF(C35>=1,E35,0) -> 3 | H35: =G35*C35 -> 0
A36: PROFESORES | B36: 11 | C36: 0 | D36: 0 | E36: 2 | G36: =IF(C36>=1,E36,0) -> 2 | H36: =G36*C36 -> 0
A37: PROFESORES | B37: 12 | C37: 0 | D37: 0 | E37: 1 | G37: =IF(C37>=1,E37,0) -> 1 | H37: =G37*C37 -> 0
A38: ASPECTOS ACADÉMICOS Y RESULTADOS DE APRENDIZAJE | B38: 1 | C38: 2 | D38: 2 | E38: 12 | G38: =IF(C38>=1,E38,0) -> 12 | H38: =G38*C38 -> 24 | I38: =SUM(H38:H49) -> 160 | J38: =I38/$I$1 -> 0.10796221
A39: ASPECTOS ACADÉMICOS Y RESULTADOS DE APRENDIZAJE | B39: 2 | C39: 3 | D39: 3 | E39: 11 | G39: =IF(C39>=1,E39,0) -> 11 | H39: =G39*C39 -> 33
A40: ASPECTOS ACADÉMICOS Y RESULTADOS DE APRENDIZAJE | B40: 3 | C40: 3 | D40: 3 | E40: 10 | G40: =IF(C40>=1,E40,0) -> 10 | H40: =G40*C40 -> 30
A41: ASPECTOS ACADÉMICOS Y RESULTADOS DE APRENDIZAJE | B41: 4 | C41: 3 | D41: 3 | E41: 9 | G41: =IF(C41>=1,E41,0) -> 9 | H41: =G41*C41 -> 27
A42: ASPECTOS ACADÉMICOS Y RESULTADOS DE APRENDIZAJE | B42: 5 | C42: 4 | D42: 4 | E42: 8 | G42: =IF(C42>=1,E42,0) -> 8 | H42: =G42*C42 -> 32
A43: ASPECTOS ACADÉMICOS Y RESULTADOS DE APRENDIZAJE | B43: 6 | C43: 0 | D43: 0 | E43: 7 | G43: =IF(C43>=1,E43,0) -> 7 | H43: =G43*C43 -> 0
A44: ASPECTOS ACADÉMICOS Y RESULTADOS DE APRENDIZAJE | B44: 7 | C44: 1 | D44: 1 | E44: 6 | G44: =IF(C44>=1,E44,0) -> 6 | H44: =G44*C44 -> 6
A45: ASPECTOS ACADÉMICOS Y RESULTADOS DE APRENDIZAJE | B45: 8 | C45: 0 | D45: 0 | E45: 5 | G45: =IF(C45>=1,E45,0) -> 5 | H45: =G45*C45 -> 0
A46: ASPECTOS ACADÉMICOS Y RESULTADOS DE APRENDIZAJE | B46: 9 | C46: 0 | D46: 0 | E46: 4 | G46: =IF(C46>=1,E46,0) -> 4 | H46: =G46*C46 -> 0
A47: ASPECTOS ACADÉMICOS Y RESULTADOS DE APRENDIZAJE | B47: 10 | C47: 2 | D47: 2 | E47: 3 | G47: =IF(C47>=1,E47,0) -> 3 | H47: =G47*C47 -> 6
A48: ASPECTOS ACADÉMICOS Y RESULTADOS DE APRENDIZAJE | B48: 11 | C48: 1 | D48: 1 | E48: 2 | G48: =IF(C48>=1,E48,0) -> 2 | H48: =G48*C48 -> 2
A49: ASPECTOS ACADÉMICOS Y RESULTADOS DE APRENDIZAJE | B49: 12 | C49: 0 | D49: 0 | E49: 1 | G49: =IF(C49>=1,E49,0) -> 1 | H49: =G49*C49 -> 0
A50: PERMANENCIA Y GRADUACIÓN | B50: 1 | C50: 0 | D50: 0 | E50: 12 | G50: =IF(C50>=1,E50,0) -> 12 | H50: =G50*C50 -> 0 | I50: =SUM(H50:H61) -> 100 | J50: =I50/$I$1 -> 0.067476383
A51: PERMANENCIA Y GRADUACIÓN | B51: 2 | C51: 0 | D51: 0 | E51: 11 | G51: =IF(C51>=1,E51,0) -> 11 | H51: =G51*C51 -> 0
A52: PERMANENCIA Y GRADUACIÓN | B52: 3 | C52: 1 | D52: 1 | E52: 10 | G52: =IF(C52>=1,E52,0) -> 10 | H52: =G52*C52 -> 10
A53: PERMANENCIA Y GRADUACIÓN | B53: 4 | C53: 1 | D53: 1 | E53: 9 | G53: =IF(C53>=1,E53,0) -> 9 | H53: =G53*C53 -> 9
A54: PERMANENCIA Y GRADUACIÓN | B54: 5 | C54: 0 | D54: 0 | E54: 8 | G54: =IF(C54>=1,E54,0) -> 8 | H54: =G54*C54 -> 0
A55: PERMANENCIA Y GRADUACIÓN | B55: 6 | C55: 4 | D55: 4 | E55: 7 | G55: =IF(C55>=1,E55,0) -> 7 | H55: =G55*C55 -> 28
A56: PERMANENCIA Y GRADUACIÓN | B56: 7 | C56: 3 | D56: 3 | E56: 6 | G56: =IF(C56>=1,E56,0) -> 6 | H56: =G56*C56 -> 18
A57: PERMANENCIA Y GRADUACIÓN | B57: 8 | C57: 3 | D57: 3 | E57: 5 | G57: =IF(C57>=1,E57,0) -> 5 | H57: =G57*C57 -> 15
A58: PERMANENCIA Y GRADUACIÓN | B58: 9 | C58: 4 | D58: 4 | E58: 4 | G58: =IF(C58>=1,E58,0) -> 4 | H58: =G58*C58 -> 16
A59: PERMANENCIA Y GRADUACIÓN | B59: 10 | C59: 0 | D59: 0 | E59: 3 | G59: =IF(C59>=1,E59,0) -> 3 | H59: =G59*C59 -> 0
A60: PERMANENCIA Y GRADUACIÓN | B60: 11 | C60: 1 | D60: 1 | E60: 2 | G60: =IF(C60>=1,E60,0) -> 2 | H60: =G60*C60 -> 2
A61: PERMANENCIA Y GRADUACIÓN | B61: 12 | C61: 2 | D61: 2 | E61: 1 | G61: =IF(C61>=1,E61,0) -> 1 | H61: =G61*C61 -> 2
A62: INTERACCIÓN CON EL ENTORNO NACIONAL E INTERNACIONAL | B62: 1 | C62: 0 | D62: 0 | E62: 12 | G62: =IF(C62>=1,E62,0) -> 12 | H62: =G62*C62 -> 0 | I62: =SUM(H62:H73) -> 108 | J62: =I62/$I$1 -> 0.072874494
A63: INTERACCIÓN CON EL ENTORNO NACIONAL E INTERNACIONAL | B63: 2 | C63: 0 | D63: 0 | E63: 11 | G63: =IF(C63>=1,E63,0) -> 11 | H63: =G63*C63 -> 0
A64: INTERACCIÓN CON EL ENTORNO NACIONAL E INTERNACIONAL | B64: 3 | C64: 1 | D64: 1 | E64: 10 | G64: =IF(C64>=1,E64,0) -> 10 | H64: =G64*C64 -> 10
A65: INTERACCIÓN CON EL ENTORNO NACIONAL E INTERNACIONAL | B65: 4 | C65: 1 | D65: 1 | E65: 9 | G65: =IF(C65>=1,E65,0) -> 9 | H65: =G65*C65 -> 9
A66: INTERACCIÓN CON EL ENTORNO NACIONAL E INTERNACIONAL | B66: 5 | C66: 3 | D66: 3 | E66: 8 | G66: =IF(C66>=1,E66,0) -> 8 | H66: =G66*C66 -> 24
A67: INTERACCIÓN CON EL ENTORNO NACIONAL E INTERNACIONAL | B67: 6 | C67: 1 | D67: 1 | E67: 7 | G67: =IF(C67>=1,E67,0) -> 7 | H67: =G67*C67 -> 7
A68: INTERACCIÓN CON EL ENTORNO NACIONAL E INTERNACIONAL | B68: 7 | C68: 4 | D68: 4 | E68: 6 | G68: =IF(C68>=1,E68,0) -> 6 | H68: =G68*C68 -> 24
A69: INTERACCIÓN CON EL ENTORNO NACIONAL E INTERNACIONAL | B69: 8 | C69: 2 | D69: 2 | E69: 5 | G69: =IF(C69>=1,E69,0) -> 5 | H69: =G69*C69 -> 10
A70: INTERACCIÓN CON EL ENTORNO NACIONAL E INTERNACIONAL | B70: 9 | C70: 4 | D70: 4 | E70: 4 | G70: =IF(C70>=1,E70,0) -> 4 | H70: =G70*C70 -> 16
A71: INTERACCIÓN CON EL ENTORNO NACIONAL E INTERNACIONAL | B71: 10 | C71: 2 | D71: 2 | E71: 3 | G71: =IF(C71>=1,E71,0) -> 3 | H71: =G71*C71 -> 6
A72: INTERACCIÓN CON EL ENTORNO NACIONAL E INTERNACIONAL | B72: 11 | C72: 1 | D72: 1 | E72: 2 | G72: =IF(C72>=1,E72,0) -> 2 | H72: =G72*C72 -> 2
A73: INTERACCIÓN CON EL ENTORNO NACIONAL E INTERNACIONAL | B73: 12 | C73: 0 | D73: 0 | E73: 1 | G73: =IF(C73>=1,E73,0) -> 1 | H73: =G73*C73 -> 0
A74: APORTES DE LA INVESTIGACIÓN, LA INNOVACIÓN, EL DESARROLLO TECNOLÓGICO Y LA CREACIÓN, ASOCIADOS AL PROGRAMA ACADÉMICO | B74: 1 | C74: 3 | D74: 3 | E74: 12 | G74: =IF(C74>=1,E74,0) -> 12 | H74: =G74*C74 -> 36 | I74: =SUM(H74:H85) -> 157 | J74: =I74/$I$1 -> 0.10593792
A75: APORTES DE LA INVESTIGACIÓN, LA INNOVACIÓN, EL DESARROLLO TECNOLÓGICO Y LA CREACIÓN, ASOCIADOS AL PROGRAMA ACADÉMICO | B75: 2 | C75: 1 | D75: 1 | E75: 11 | G75: =IF(C75>=1,E75,0) -> 11 | H75: =G75*C75 -> 11
A76: APORTES DE LA INVESTIGACIÓN, LA INNOVACIÓN, EL DESARROLLO TECNOLÓGICO Y LA CREACIÓN, ASOCIADOS AL PROGRAMA ACADÉMICO | B76: 3 | C76: 1 | D76: 1 | E76: 10 | G76: =IF(C76>=1,E76,0) -> 10 | H76: =G76*C76 -> 10
A77: APORTES DE LA INVESTIGACIÓN, LA INNOVACIÓN, EL DESARROLLO TECNOLÓGICO Y LA CREACIÓN, ASOCIADOS AL PROGRAMA ACADÉMICO | B77: 4 | C77: 4 | D77: 4 | E77: 9 | G77: =IF(C77>=1,E77,0) -> 9 | H77: =G77*C77 -> 36
A78: APORTES DE LA INVESTIGACIÓN, LA INNOVACIÓN, EL DESARROLLO TECNOLÓGICO Y LA CREACIÓN, ASOCIADOS AL PROGRAMA ACADÉMICO | B78: 5 | C78: 4 | D78: 4 | E78: 8 | G78: =IF(C78>=1,E78,0) -> 8 | H78: =G78*C78 -> 32
A79: APORTES DE LA INVESTIGACIÓN, LA INNOVACIÓN, EL DESARROLLO TECNOLÓGICO Y LA CREACIÓN, ASOCIADOS AL PROGRAMA ACADÉMICO | B79: 6 | C79: 2 | D79: 2 | E79: 7 | G79: =IF(C79>=1,E79,0) -> 7 | H79: =G79*C79 -> 14
A80: APORTES DE LA INVESTIGACIÓN, LA INNOVACIÓN, EL DESARROLLO TECNOLÓGICO Y LA CREACIÓN, ASOCIADOS AL PROGRAMA ACADÉMICO | B80: 7 | C80: 1 | D80: 1 | E80: 6 | G80: =IF(C80>=1,E80,0) -> 6 | H80: =G80*C80 -> 6
A81: APORTES DE LA INVESTIGACIÓN, LA INNOVACIÓN, EL DESARROLLO TECNOLÓGICO Y LA CREACIÓN, ASOCIADOS AL PROGRAMA ACADÉMICO | B81: 8 | C81: 1 | D81: 1 | E81: 5 | G81: =IF(C81>=1,E81,0) -> 5 | H81: =G81*C81 -> 5
A82: APORTES DE LA INVESTIGACIÓN, LA INNOVACIÓN, EL DESARROLLO TECNOLÓGICO Y LA CREACIÓN, ASOCIADOS AL PROGRAMA ACADÉMICO | B82: 9 | C82: 1 | D82: 1 | E82: 4 | G82: =IF(C82>=1,E82,0) -> 4 | H82: =G82*C82 -> 4
A83: APORTES DE LA INVESTIGACIÓN, LA INNOVACIÓN, EL DESARROLLO TECNOLÓGICO Y LA CREACIÓN, ASOCIADOS AL PROGRAMA ACADÉMICO | B83: 10 | C83: 1 | D83: 1 | E83: 3 | G83: =IF(C83>=1,E83,0) -> 3 | H83: =G83*C83 -> 3
A84: APORTES DE LA INVESTIGACIÓN, LA INNOVACIÓN, EL DESARROLLO TECNOLÓGICO Y LA CREACIÓN, ASOCIADOS AL PROGRAMA ACADÉMICO | B84: 11 | C84: 0 | D84: 0 | E84: 2 | G84: =IF(C84>=1,E84,0) -> 2 | H84: =G84*C84 -> 0
A85: APORTES DE LA INVESTIGACIÓN, LA INNOVACIÓN, EL DESARROLLO TECNOLÓGICO Y LA CREACIÓN, ASOCIADOS AL PROGRAMA ACADÉMICO | B85: 12 | C85: 0 | D85: 0 | E85: 1 | G85: =IF(C85>=1,E85,0) -> 1 | H85: =G85*C85 -> 0
A86: BIENESTAR DE LA COMUNIDAD ACADÉMICA DEL PROGRAMA | B86: 1 | C86: 0 | D86: 0 | E86: 12 | G86: =IF(C86>=1,E86,0) -> 12 | H86: =G86*C86 -> 0 | I86: =SUM(H86:H97) -> 71 | J86: =I86/$I$1 -> 0.047908232
A87: BIENESTAR DE LA COMUNIDAD ACADÉMICA DEL PROGRAMA | B87: 2 | C87: 0 | D87: 0 | E87: 11 | G87: =IF(C87>=1,E87,0) -> 11 | H87: =G87*C87 -> 0
A88: BIENESTAR DE LA COMUNIDAD ACADÉMICA DEL PROGRAMA | B88: 3 | C88: 0 | D88: 0 | E88: 10 | G88: =IF(C88>=1,E88,0) -> 10 | H88: =G88*C88 -> 0
A89: BIENESTAR DE LA COMUNIDAD ACADÉMICA DEL PROGRAMA | B89: 4 | C89: 1 | D89: 1 | E89: 9 | G89: =IF(C89>=1,E89,0) -> 9 | H89: =G89*C89 -> 9
A90: BIENESTAR DE LA COMUNIDAD ACADÉMICA DEL PROGRAMA | B90: 5 | C90: 0 | D90: 0 | E90: 8 | G90: =IF(C90>=1,E90,0) -> 8 | H90: =G90*C90 -> 0
A91: BIENESTAR DE LA COMUNIDAD ACADÉMICA DEL PROGRAMA | B91: 6 | C91: 1 | D91: 1 | E91: 7 | G91: =IF(C91>=1,E91,0) -> 7 | H91: =G91*C91 -> 7
A92: BIENESTAR DE LA COMUNIDAD ACADÉMICA DEL PROGRAMA | B92: 7 | C92: 1 | D92: 1 | E92: 6 | G92: =IF(C92>=1,E92,0) -> 6 | H92: =G92*C92 -> 6
A93: BIENESTAR DE LA COMUNIDAD ACADÉMICA DEL PROGRAMA | B93: 8 | C93: 5 | D93: 5 | E93: 5 | G93: =IF(C93>=1,E93,0) -> 5 | H93: =G93*C93 -> 25
A94: BIENESTAR DE LA COMUNIDAD ACADÉMICA DEL PROGRAMA | B94: 9 | C94: 2 | D94: 2 | E94: 4 | G94: =IF(C94>=1,E94,0) -> 4 | H94: =G94*C94 -> 8
A95: BIENESTAR DE LA COMUNIDAD ACADÉMICA DEL PROGRAMA | B95: 10 | C95: 2 | D95: 2 | E95: 3 | G95: =IF(C95>=1,E95,0) -> 3 | H95: =G95*C95 -> 6
A96: BIENESTAR DE LA COMUNIDAD ACADÉMICA DEL PROGRAMA | B96: 11 | C96: 3 | D96: 3 | E96: 2 | G96: =IF(C96>=1,E96,0) -> 2 | H96: =G96*C96 -> 6
A97: BIENESTAR DE LA COMUNIDAD ACADÉMICA DEL PROGRAMA | B97: 12 | C97: 4 | D97: 4 | E97: 1 | G97: =IF(C97>=1,E97,0) -> 1 | H97: =G97*C97 -> 4
A98: MEDIOS EDUCATIVOS Y AMBIENTES DE APRENDIZAJE | B98: 1 | C98: 0 | D98: 0 | E98: 12 | G98: =IF(C98>=1,E98,0) -> 12 | H98: =G98*C98 -> 0 | I98: =SUM(H98:H109) -> 95 | J98: =I98/$I$1 -> 0.064102564
A99: MEDIOS EDUCATIVOS Y AMBIENTES DE APRENDIZAJE | B99: 2 | C99: 1 | D99: 1 | E99: 11 | G99: =IF(C99>=1,E99,0) -> 11 | H99: =G99*C99 -> 11
A100: MEDIOS EDUCATIVOS Y AMBIENTES DE APRENDIZAJE | B100: 3 | C100: 0 | D100: 0 | E100: 10 | G100: =IF(C100>=1,E100,0) -> 10 | H100: =G100*C100 -> 0
...

Sheet PEP
A1: Haga clic para escribir el texto de la pregunta | B1: Valor del factor | C1: Recuento | E1: Puntuación | G1: Prueba puntuación | H1: =SUM(C2:C5) -> 0 | I1: =SUM(I2:I5) -> 39
A2: Proyecto educativo del Programa. | B2: 1 | C2: 8 | E2: 2 | G2: =IF(C2>=1,E2,0) -> 2 | H2: =G2*C2 -> 16 | I2: =SUM(H2:H3) -> 21 | J2: =I2/$I$1 -> 0.53846154
A3: Proyecto educativo del Programa. | B3: 2 | C3: 5 | E3: 1 | G3: =IF(C3>=1,E3,0) -> 1 | H3: =G3*C3 -> 5
A4: Relevancia académica y pertinencia social del programa académico | B4: 1 | C4: 5 | E4: 2 | G4: =IF(C4>=1,E4,0) -> 2 | H4: =G4*C4 -> 10 | I4: =SUM(H4:H5) -> 18 | J4: =I4/$I$1 -> 0.46153846
A5: Relevancia académica y pertinencia social del programa académico | B5: 2 | C5: 8 | E5: 1 | G5: =IF(C5>=1,E5,0) -> 1 | H5: =G5*C5 -> 8

Sheet EST
A1: Haga clic para escribir el texto de la pregunta | B1: Valor del factor | C1: Recuento | E1: Puntuación | G1: Prueba puntuación | H1: =SUM(C2:C6) -> 0 | I1: =SUM(I2:I26) -> 172
A2: Participación en actividades de formación integral | B2: 1 | C2: 5 | E2: 5 | G2: =IF(C2>=1,E2,0) -> 5 | H2: =G2*C2 -> 25 | I2: =SUM(H2:H6) -> 57 | J2: =I2/$I$1 -> 0.33139535
A3: Participación en actividades de formación integral | B3: 2 | C3: 4 | E3: 4 | G3: =IF(C3>=1,E3,0) -> 4 | H3: =G3*C3 -> 16
A4: Participación en actividades de formación integral | B4: 3 | C4: 3 | E4: 3 | G4: =IF(C4>=1,E4,0) -> 3 | H4: =G4*C4 -> 9
A5: Participación en actividades de formación integral | B5: 4 | C5: 2 | E5: 2 | G5: =IF(C5>=1,E5,0) -> 2 | H5: =G5*C5 -> 4
A6: Participación en actividades de formación integral | B6: 5 | C6: 3 | E6: 1 | G6: =IF(C6>=1,E6,0) -> 1 | H6: =G6*C6 -> 3
A7: Orientación y seguimiento a estudiantes | B7: 1 | C7: 3 | E7: 3 | G7: =IF(C7>=1,E7,0) -> 3 | H7: =G7*C7 -> 9 | I7: =SUM(H7:H10) -> 31 | J7: =I7/$I$1 -> 0.18023256
A8: Orientación y seguimiento a estudiantes | B8: 2 | C8: 3 | E8: 2 | G8: =IF(C8>=1,E8,0) -> 2 | H8: =G8*C8 -> 6
A9: Orientación y seguimiento a estudiantes | B9: 3 | C9: 8 | E9: 1 | G9: =IF(C9>=1,E9,0) -> 1 | H9: =G9*C9 -> 8
A10: Orientación y seguimiento a estudiantes | B10: 4 | C10: 2 | E10: 4 | G10: =IF(C10>=1,E10,0) -> 4 | H10: =G10*C10 -> 8
A11: Orientación y seguimiento a estudiantes | B11: 5 | C11: 1 | E11: 3 | G11: =IF(C11>=1,E11,0) -> 3 | H11: =G11*C11 -> 3
A12: Capacidad de trabajo autónomo | B12: 1 | C12: 0 | E12: 2 | G12: =IF(C12>=1,E12,0) -> 2 | H12: =G12*C12 -> 0 | I12: =SUM(H12:H15) -> 33 | J12: =I12/$I$1 -> 0.19186047
A13: Capacidad de trabajo autónomo | B13: 2 | C13: 4 | E13: 1 | G13: =IF(C13>=1,E13,0) -> 1 | H13: =G13*C13 -> 4
A14: Capacidad de trabajo autónomo | B14: 3 | C14: 5 | E14: 4 | G14: =IF(C14>=1,E14,0) -> 4 | H14: =G14*C14 -> 20
A15: Capacidad de trabajo autónomo | B15: 4 | C15: 3 | E15: 3 | G15: =IF(C15>=1,E15,0) -> 3 | H15: =G15*C15 -> 9
A16: Capacidad de trabajo autónomo | B16: 5 | C16: 5 | E16: 2 | G16: =IF(C16>=1,E16,0) -> 2 | H16: =G16*C16 -> 10
A17: Reglamento estudiantil y política académica | B17: 1 | C17: 7 | E17: 1 | G17: =IF(C17>=1,E17,0) -> 1 | H17: =G17*C17 -> 7 | I17: =SUM(H17:H20) -> 23 | J17: =I17/$I$1 -> 0.13372093
A18: Reglamento estudiantil y política académica | B18: 2 | C18: 2 | E18: 4 | G18: =IF(C18>=1,E18,0) -> 4 | H18: =G18*C18 -> 8
A19: Reglamento estudiantil y política académica | B19: 3 | C19: 0 | E19: 3 | G19: =IF(C19>=1,E19,0) -> 3 | H19: =G19*C19 -> 0
A20: Reglamento estudiantil y política académica | B20: 4 | C20: 4 | E20: 2 | G20: =IF(C20>=1,E20,0) -> 2 | H20: =G20*C20 -> 8
A21: Reglamento estudiantil y política académica | B21: 5 | C21: 4 | E21: 1 | G21: =IF(C21>=1,E21,0) -> 1 | H21: =G21*C21 -> 4
A22: Estímulos y apoyos para estudiantes | B22: 1 | C22: 2 | E22: 4 | G22: =IF(C22>=1,E22,0) -> 4 | H22: =G22*C22 -> 8 | I22: =SUM(H22:H25) -> 28 | J22: =I22/$I$1 -> 0.1627907
A23: Estímulos y apoyos para estudiantes | B23: 2 | C23: 4 | E23: 3 | G23: =IF(C23>=1,E23,0) -> 3 | H23: =G23*C23 -> 12
A24: Estímulos y apoyos para estudiantes | B24: 3 | C24: 1 | E24: 2 | G24: =IF(C24>=1,E24,0) -> 2 | H24: =G24*C24 -> 2
A25: Estímulos y apoyos para estudiantes | B25: 4 | C25: 6 | E25: 1 | G25: =IF(C25>=1,E25,0) -> 1 | H25: =G25*C25 -> 6
A26: Estímulos y apoyos para estudiantes | B26: 5 | C26: 4 | E26: 4 | G26: =IF(C26>=1,E26,0) -> 4 | H26: =G26*C26 -> 16

Sheet DOC
A1: Haga clic para escribir el texto de la pregunta | B1: Valor del factor | C1: Recuento | E1: Puntuación | G1: Prueba puntuación | H1: =SUM(C2:C9) -> 0 | I1: =SUM(I2:I65) -> 648
A2: Selección, vinculación y permanencia | B2: 1 | C2: 6 | E2: 8 | G2: =IF(C2>=1,E2,0) -> 8 | H2: =G2*C2 -> 48 | I2: =SUM(H2:H9) -> 111 | J2: =I2/$I$1 -> 0.1712963
A3: Selección, vinculación y permanencia | B3: 2 | C3: 4 | E3: 7 | G3: =IF(C3>=1,E3,0) -> 7 | H3: =G3*C3 -> 28
A4: Selección, vinculación y permanencia | B4: 3 | C4: 1 | E4: 6 | G4: =IF(C4>=1,E4,0) -> 6 | H4: =G4*C4 -> 6
A5: Selección, vinculación y permanencia | B5: 4 | C5: 3 | E5: 5 | G5: =IF(C5>=1,E5,0) -> 5 | H5: =G5*C5 -> 15
A6: Selección, vinculación y permanencia | B6: 5 | C6: 3 | E6: 4 | G6: =IF(C6>=1,E6,0) -> 4 | H6: =G6*C6 -> 12
A7: Selección, vinculación y permanencia | B7: 6 | C7: 0 | E7: 3 | G7: =IF(C7>=1,E7,0) -> 3 | H7: =G7*C7 -> 0
A8: Selección, vinculación y permanencia | B8: 7 | C8: 1 | E8: 2 | G8: =IF(C8>=1,E8,0) -> 2 | H8: =G8*C8 -> 2
A9: Selección, vinculación y permanencia | B9: 8 | C9: 0 | E9: 1 | G9: =IF(C9>=1,E9,0) -> 1 | H9: =G9*C9 -> 0
A10: Estatuto profesoral | B10: 1 | C10: 4 | E10: 8 | G10: =IF(C10>=1,E10,0) -> 8 | H10: =G10*C10 -> 32 | I10: =SUM(H10:H17) -> 89 | J10: =I10/$I$1 -> 0.13734568
A11: Estatuto profesoral | B11: 2 | C11: 3 | E11: 7 | G11: =IF(C11>=1,E11,0) -> 7 | H11: =G11*C11 -> 21
A12: Estatuto profesoral | B12: 3 | C12: 3 | E12: 6 | G12: =IF(C12>=1,E12,0) -> 6 | H12: =G12*C12 -> 18
A13: Estatuto profesoral | B13: 4 | C13: 0 | E13: 5 | G13: =IF(C13>=1,E13,0) -> 5 | H13: =G13*C13 -> 0
A14: Estatuto profesoral | B14: 5 | C14: 2 | E14: 4 | G14: =IF(C14>=1,E14,0) -> 4 | H14: =G14*C14 -> 8
A15: Estatuto profesoral | B15: 6 | C15: 2 | E15: 3 | G15: =IF(C15>=1,E15,0) -> 3 | H15: =G15*C15 -> 6
A16: Estatuto profesoral | B16: 7 | C16: 0 | E16: 2 | G16: =IF(C16>=1,E16,0) -> 2 | H16: =G16*C16 -> 0
A17: Estatuto profesoral | B17: 8 | C17: 4 | E17: 1 | G17: =IF(C17>=1,E17,0) -> 1 | H17: =G17*C17 -> 4
A18: Número, dedicación, nivel de formación y experiencia | B18: 1 | C18: 3 | E18: 8 | G18: =IF(C18>=1,E18,0) -> 8 | H18: =G18*C18 -> 24 | I18: =SUM(H18:H25) -> 102 | J18: =I18/$I$1 -> 0.15740741
A19: Número, dedicación, nivel de formación y experiencia | B19: 2 | C19: 5 | E19: 7 | G19: =IF(C19>=1,E19,0) -> 7 | H19: =G19*C19 -> 35
A20: Número, dedicación, nivel de formación y experiencia | B20: 3 | C20: 1 | E20: 6 | G20: =IF(C20>=1,E20,0) -> 6 | H20: =G20*C20 -> 6
A21: Número, dedicación, nivel de formación y experiencia | B21: 4 | C21: 5 | E21: 5 | G21: =IF(C21>=1,E21,0) -> 5 | H21: =G21*C21 -> 25
A22: Número, dedicación, nivel de formación y experiencia | B22: 5 | C22: 2 | E22: 4 | G22: =IF(C22>=1,E22,0) -> 4 | H22: =G22*C22 -> 8
A23: Número, dedicación, nivel de formación y experiencia | B23: 6 | C23: 1 | E23: 3 | G23: =IF(C23>=1,E23,0) -> 3 | H23: =G23*C23 -> 3
A24: Número, dedicación, nivel de formación y experiencia | B24: 7 | C24: 0 | E24: 2 | G24: =IF(C24>=1,E24,0) -> 2 | H24: =G24*C24 -> 0
A25: Número, dedicación, nivel de formación y experiencia | B25: 8 | C25: 1 | E25: 1 | G25: =IF(C25>=1,E25,0) -> 1 | H25: =G25*C25 -> 1
A26: Desarrollo profesoral | B26: 1 | C26: 3 | E26: 8 | G26: =IF(C26>=1,E26,0) -> 8 | H26: =G26*C26 -> 24 | I26: =SUM(H26:H33) -> 99 | J26: =I26/$I$1 -> 0.15277778
A27: Desarrollo profesoral | B27: 2 | C27: 2 | E27: 7 | G27: =IF(C27>=1,E27,0) -> 7 | H27: =G27*C27 -> 14
A28: Desarrollo profesoral | B28: 3 | C28: 6 | E28: 6 | G28: =IF(C28>=1,E28,0) -> 6 | H28: =G28*C28 -> 36
A29: Desarrollo profesoral | B29: 4 | C29: 2 | E29: 5 | G29: =IF(C29>=1,E29,0) -> 5 | H29: =G29*C29 -> 10
A30: Desarrollo profesoral | B30: 5 | C30: 1 | E30: 4 | G30: =IF(C30>=1,E30,0) -> 4 | H30: =G30*C30 -> 4
A31: Desarrollo profesoral | B31: 6 | C31: 3 | E31: 3 | G31: =IF(C31>=1,E31,0) -> 3 | H31: =G31*C31 -> 9
A32: Desarrollo profesoral | B32: 7 | C32: 1 | E32: 2 | G32: =IF(C32>=1,E32,0) -> 2 | H32: =G32*C32 -> 2
A33: Desarrollo profesoral | B33: 8 | C33: 0 | E33: 1 | G33: =IF(C33>=1,E33,0) -> 1 | H33: =G33*C33 -> 0
A34: Estímulos a la trayectoria profesoral | B34: 1 | C34: 0 | E34: 8 | G34: =IF(C34>=1,E34,0) -> 8 | H34: =G34*C34 -> 0 | I34: =SUM(H34:H41) -> 67 | J34: =I34/$I$1 -> 0.10339506
A35: Estímulos a la trayectoria profesoral | B35: 2 | C35: 1 | E35: 7 | G35: =IF(C35>=1,E35,0) -> 7 | H35: =G35*C35 -> 7
A36: Estímulos a la trayectoria profesoral | B36: 3 | C36: 1 | E36: 6 | G36: =IF(C36>=1,E36,0) -> 6 | H36: =G36*C36 -> 6
A37: Estímulos a la trayectoria profesoral | B37: 4 | C37: 4 | E37: 5 | G37: =IF(C37>=1,E37,0) -> 5 | H37: =G37*C37 -> 20
A38: Estímulos a la trayectoria profesoral | B38: 5 | C38: 3 | E38: 4 | G38: =IF(C38>=1,E38,0) -> 4 | H38: =G38*C38 -> 12
A39: Estímulos a la trayectoria profesoral | B39: 6 | C39: 4 | E39: 3 | G39: =IF(C39>=1,E39,0) -> 3 | H39: =G39*C39 -> 12
A40: Estímulos a la trayectoria profesoral | B40: 7 | C40: 5 | E40: 2 | G40: =IF(C40>=1,E40,0) -> 2 | H40: =G40*C40 -> 10
A41: Estímulos a la trayectoria profesoral | B41: 8 | C41: 0 | E41: 1 | G41: =IF(C41>=1,E41,0) -> 1 | H41: =G41*C41 -> 0
A42: Producción, pertinencia, utilización e impacto del material docente | B42: 1 | C42: 2 | E42: 8 | G42: =IF(C42>=1,E42,0) -> 8 | H42: =G42*C42 -> 16 | I42: =SUM(H42:H49) -> 76 | J42: =I42/$I$1 -> 0.11728395
A43: Producción, pertinencia, utilización e impacto del material docente | B43: 2 | C43: 1 | E43: 7 | G43: =IF(C43>=1,E43,0) -> 7 | H43: =G43*C43 -> 7
A44: Producción, pertinencia, utilización e impacto del material docente | B44: 3 | C44: 2 | E44: 6 | G44: =IF(C44>=1,E44,0) -> 6 | H44: =G44*C44 -> 12
A45: Producción, pertinencia, utilización e impacto del material docente | B45: 4 | C45: 2 | E45: 5 | G45: =IF(C45>=1,E45,0) -> 5 | H45: =G45*C45 -> 10
A46: Producción, pertinencia, utilización e impacto del material docente | B46: 5 | C46: 3 | E46: 4 | G46: =IF(C46>=1,E46,0) -> 4 | H46: =G46*C46 -> 12
A47: Producción, pertinencia, utilización e impacto del material docente | B47: 6 | C47: 3 | E47: 3 | G47: =IF(C47>=1,E47,0) -> 3 | H47: =G47*C47 -> 9
A48: Producción, pertinencia, utilización e impacto del material docente | B48: 7 | C48: 5 | E48: 2 | G48: =IF(C48>=1,E48,0) -> 2 | H48: =G48*C48 -> 10
A49: Producción, pertinencia, utilización e impacto del material docente | B49: 8 | C49: 0 | E49: 1 | G49: =IF(C49>=1,E49,0) -> 1 | H49: =G49*C49 -> 0
A50: Remuneración por méritos | B50: 1 | C50: 0 | E50: 8 | G50: =IF(C50>=1,E50,0) -> 8 | H50: =G50*C50 -> 0 | I50: =SUM(H50:H57) -> 61 | J50: =I50/$I$1 -> 0.094135802
A51: Remuneración por méritos | B51: 2 | C51: 1 | E51: 7 | G51: =IF(C51>=1,E51,0) -> 7 | H51: =G51*C51 -> 7
A52: Remuneración por méritos | B52: 3 | C52: 3 | E52: 6 | G52: =IF(C52>=1,E52,0) -> 6 | H52: =G52*C52 -> 18
A53: Remuneración por méritos | B53: 4 | C53: 2 | E53: 5 | G53: =IF(C53>=1,E53,0) -> 5 | H53: =G53*C53 -> 10
A54: Remuneración por méritos | B54: 5 | C54: 2 | E54: 4 | G54: =IF(C54>=1,E54,0) -> 4 | H54: =G54*C54 -> 8
A55: Remuneración por méritos | B55: 6 | C55: 1 | E55: 3 | G55: =IF(C55>=1,E55,0) -> 3 | H55: =G55*C55 -> 3
A56: Remuneración por méritos | B56: 7 | C56: 6 | E56: 2 | G56: =IF(C56>=1,E56,0) -> 2 | H56: =G56*C56 -> 12
A57: Remuneración por méritos | B57: 8 | C57: 3 | E57: 1 | G57: =IF(C57>=1,E57,0) -> 1 | H57: =G57*C57 -> 3
A58: Evaluación de profesores | B58: 1 | C58: 0 | E58: 8 | G58: =IF(C58>=1,E58,0) -> 8 | H58: =G58*C58 -> 0 | I58: =SUM(H58:H65) -> 43 | J58: =I58/$I$1 -> 0.066358025
A59: Evaluación de profesores | B59: 2 | C59: 1 | E59: 7 | G59: =IF(C59>=1,E59,0) -> 7 | H59: =G59*C59 -> 7
A60: Evaluación de profesores | B60: 3 | C60: 1 | E60: 6 | G60: =IF(C60>=1,E60,0) -> 6 | H60: =G60*C60 -> 6
A61: Evaluación de profesores | B61: 4 | C61: 0 | E61: 5 | G61: =IF(C61>=1,E61,0) -> 5 | H61: =G61*C61 -> 0
A62: Evaluación de profesores | B62: 5 | C62: 2 | E62: 4 | G62: =IF(C62>=1,E62,0) -> 4 | H62: =G62*C62 -> 8
A63: Evaluación de profesores | B63: 6 | C63: 4 | E63: 3 | G63: =IF(C63>=1,E63,0) -> 3 | H63: =G63*C63 -> 12
A64: Evaluación de profesores | B64: 7 | C64: 0 | E64: 2 | G64: =IF(C64>=1,E64,0) -> 2 | H64: =G64*C64 -> 0
A65: Evaluación de profesores | B65: 8 | C65: 10 | E65: 1 | G65: =IF(C65>=1,E65,0) -> 1 | H65: =G65*C65 -> 10

Sheet FAC 5
A1: Haga clic para escribir el texto de la pregunta | B1: Valor del factor | C1: Recuento | E1: Puntuación | G1: Prueba puntuación | H1: =SUM(C2:C10) -> 0 | I1: =SUM(I2:I82) -> 810
A2: Integralidad de los aspectos curriculares | B2: 1 | C2: 9 | E2: 9 | G2: 9 | H2: =G2*C2 -> 81 | I2: =SUM(H2:H10) -> 139 | J2: =I2/$I$1 -> 0.17160494
A3: Integralidad de los aspectos curriculares | B3: 2 | C3: 2 | E3: 8 | G3: 8 | H3: =G3*C3 -> 16
A4: Integralidad de los aspectos curriculares | B4: 3 | C4: 4 | E4: 7 | G4: 7 | H4: =G4*C4 -> 28
A5: Integralidad de los aspectos curriculares | B5: 4 | C5: 2 | E5: 6 | G5: 6 | H5: =G5*C5 -> 12
A6: Integralidad de los aspectos curriculares | B6: 5 | C6: 0 | E6: 5 | G6: 5 | H6: =G6*C6 -> 0
A7: Integralidad de los aspectos curriculares | B7: 6 | C7: 0 | E7: 4 | G7: 4 | H7: =G7*C7 -> 0
A8: Integralidad de los aspectos curriculares | B8: 7 | C8: 0 | E8: 3 | G8: 3 | H8: =G8*C8 -> 0
A9: Integralidad de los aspectos curriculares | B9: 8 | C9: 1 | E9: 2 | G9: 2 | H9: =G9*C9 -> 2
A10: Integralidad de los aspectos curriculares | B10: 9 | C10: 0 | E10: 1 | G10: 1 | H10: =G10*C10 -> 0
A11: Flexibilidad de los aspectos curriculares | B11: 1 | C11: 2 | E11: 9 | G11: 9 | H11: =G11*C11 -> 18 | I11: =SUM(H11:H19) -> 119 | J11: =I11/$I$1 -> 0.14691358
A12: Flexibilidad de los aspectos curriculares | B12: 2 | C12: 5 | E12: 8 | G12: 8 | H12: =G12*C12 -> 40
A13: Flexibilidad de los aspectos curriculares | B13: 3 | C13: 1 | E13: 7 | G13: 7 | H13: =G13*C13 -> 7
A14: Flexibilidad de los aspectos curriculares | B14: 4 | C14: 6 | E14: 6 | G14: 6 | H14: =G14*C14 -> 36
A15: Flexibilidad de los aspectos curriculares | B15: 5 | C15: 2 | E15: 5 | G15: 5 | H15: =G15*C15 -> 10
A16: Flexibilidad de los aspectos curriculares | B16: 6 | C16: 2 | E16: 4 | G16: 4 | H16: =G16*C16 -> 8
A17: Flexibilidad de los aspectos curriculares | B17: 7 | C17: 0 | E17: 3 | G17: 3 | H17: =G17*C17 -> 0
A18: Flexibilidad de los aspectos curriculares | B18: 8 | C18: 0 | E18: 2 | G18: 2 | H18: =G18*C18 -> 0
A19: Flexibilidad de los aspectos curriculares | B19: 9 | C19: 0 | E19: 1 | G19: 1 | H19: =G19*C19 -> 0
A20: Interdisciplinariedad | B20: 1 | C20: 1 | E20: 9 | G20: 9 | H20: =G20*C20 -> 9 | I20: =SUM(H20:H28) -> 104 | J20: =I20/$I$1 -> 0.12839506
A21: Interdisciplinariedad | B21: 2 | C21: 3 | E21: 8 | G21: 8 | H21: =G21*C21 -> 24
A22: Interdisciplinariedad | B22: 3 | C22: 3 | E22: 7 | G22: 7 | H22: =G22*C22 -> 21
A23: Interdisciplinariedad | B23: 4 | C23: 3 | E23: 6 | G23: 6 | H23: =G23*C23 -> 18
A24: Interdisciplinariedad | B24: 5 | C24: 4 | E24: 5 | G24: 5 | H24: =G24*C24 -> 20
A25: Interdisciplinariedad | B25: 6 | C25: 1 | E25: 4 | G25: 4 | H25: =G25*C25 -> 4
A26: Interdisciplinariedad | B26: 7 | C26: 2 | E26: 3 | G26: 3 | H26: =G26*C26 -> 6
A27: Interdisciplinariedad | B27: 8 | C27: 1 | E27: 2 | G27: 2 | H27: =G27*C27 -> 2
A28: Interdisciplinariedad | B28: 9 | C28: 0 | E28: 1 | G28: 1 | H28: =G28*C28 -> 0
A29: Estrategias pedagógicas | B29: 1 | C29: 0 | E29: 9 | G29: 9 | H29: =G29*C29 -> 0 | I29: =SUM(H29:H37) -> 92 | J29: =I29/$I$1 -> 0.11358025
A30: Estrategias pedagógicas | B30: 2 | C30: 2 | E30: 8 | G30: 8 | H30: =G30*C30 -> 16
A31: Estrategias pedagógicas | B31: 3 | C31: 1 | E31: 7 | G31: 7 | H31: =G31*C31 -> 7
A32: Estrategias pedagógicas | B32: 4 | C32: 3 | E32: 6 | G32: 6 | H32: =G32*C32 -> 18
A33: Estrategias pedagógicas | B33: 5 | C33: 5 | E33: 5 | G33: 5 | H33: =G33*C33 -> 25
A34: Estrategias pedagógicas | B34: 6 | C34: 5 | E34: 4 | G34: 4 | H34: =G34*C34 -> 20
A35: Estrategias pedagógicas | B35: 7 | C35: 2 | E35: 3 | G35: 3 | H35: =G35*C35 -> 6
A36: Estrategias pedagógicas | B36: 8 | C36: 0 | E36: 2 | G36: 2 | H36: =G36*C36 -> 0
A37: Estrategias pedagógicas | B37: 9 | C37: 0 | E37: 1 | G37: 1 | H37: =G37*C37 -> 0
A38: Sistema de evaluación de estudiantes | B38: 1 | C38: 0 | E38: 9 | G38: 9 | H38: =G38*C38 -> 0 | I38: =SUM(H38:H46) -> 61 | J38: =I38/$I$1 -> 0.075308642
A39: Sistema de evaluación de estudiantes | B39: 2 | C39: 0 | E39: 8 | G39: 8 | H39: =G39*C39 -> 0
A40: Sistema de evaluación de estudiantes | B40: 3 | C40: 0 | E40: 7 | G40: 7 | H40: =G40*C40 -> 0
A41: Sistema de evaluación de estudiantes | B41: 4 | C41: 0 | E41: 6 | G41: 6 | H41: =G41*C41 -> 0
A42: Sistema de evaluación de estudiantes | B42: 5 | C42: 5 | E42: 5 | G42: 5 | H42: =G42*C42 -> 25
A43: Sistema de evaluación de estudiantes | B43: 6 | C43: 5 | E43: 4 | G43: 4 | H43: =G43*C43 -> 20
A44: Sistema de evaluación de estudiantes | B44: 7 | C44: 2 | E44: 3 | G44: 3 | H44: =G44*C44 -> 6
A45: Sistema de evaluación de estudiantes | B45: 8 | C45: 4 | E45: 2 | G45: 2 | H45: =G45*C45 -> 8
A46: Sistema de evaluación de estudiantes | B46: 9 | C46: 2 | E46: 1 | G46: 1 | H46: =G46*C46 -> 2
A47: Resultados de aprendizaje | B47: 1 | C47: 3 | E47: 9 | G47: 9 | H47: =G47*C47 -> 27 | I47: =SUM(H47:H55) -> 104 | J47: =I47/$I$1 -> 0.12839506
A48: Resultados de aprendizaje | B48: 2 | C48: 3 | E48: 8 | G48: 8 | H48: =G48*C48 -> 24
A49: Resultados de aprendizaje | B49: 3 | C49: 3 | E49: 7 | G49: 7 | H49: =G49*C49 -> 21
A50: Resultados de aprendizaje | B50: 4 | C50: 1 | E50: 6 | G50: 6 | H50: =G50*C50 -> 6
A51: Resultados de aprendizaje | B51: 5 | C51: 1 | E51: 5 | G51: 5 | H51: =G51*C51 -> 5
A52: Resultados de aprendizaje | B52: 6 | C52: 3 | E52: 4 | G52: 4 | H52: =G52*C52 -> 12
A53: Resultados de aprendizaje | B53: 7 | C53: 2 | E53: 3 | G53: 3 | H53: =G53*C53 -> 6
A54: Resultados de aprendizaje | B54: 8 | C54: 1 | E54: 2 | G54: 2 | H54: =G54*C54 -> 2
A55: Resultados de aprendizaje | B55: 9 | C55: 1 | E55: 1 | G55: 1 | H55: =G55*C55 -> 1
A56: Competencias | B56: 1 | C56: 1 | E56: 9 | G56: 9 | H56: =G56*C56 -> 9 | I56: =SUM(H56:H64) -> 89 | J56: =I56/$I$1 -> 0.10987654
A57: Competencias | B57: 2 | C57: 1 | E57: 8 | G57: 8 | H57: =G57*C57 -> 8
A58: Competencias | B58: 3 | C58: 6 | E58: 7 | G58: 7 | H58: =G58*C58 -> 42
A59: Competencias | B59: 4 | C59: 1 | E59: 6 | G59: 6 | H59: =G59*C59 -> 6
A60: Competencias | B60: 5 | C60: 0 | E60: 5 | G60: 5 | H60: =G60*C60 -> 0
A61: Competencias | B61: 6 | C61: 0 | E61: 4 | G61: 4 | H61: =G61*C61 -> 0
A62: Competencias | B62: 7 | C62: 7 | E62: 3 | G62: 3 | H62: =G62*C62 -> 21
A63: Competencias | B63: 8 | C63: 1 | E63: 2 | G63: 2 | H63: =G63*C63 -> 2
A64: Competencias | B64: 9 | C64: 1 | E64: 1 | G64: 1 | H64: =G64*C64 -> 1
A65: Evaluación y autorregulación del programa académico | B65: 1 | C65: 2 | E65: 9 | G65: 9 | H65: =G65*C65 -> 18 | I65: =SUM(H65:H73) -> 55 | J65: =I65/$I$1 -> 0.067901235
A66: Evaluación y autorregulación del programa académico | B66: 2 | C66: 0 | E66: 8 | G66: 8 | H66: =G66*C66 -> 0
A67: Evaluación y autorregulación del programa académico | B67: 3 | C67: 0 | E67: 7 | G67: 7 | H67: =G67*C67 -> 0
A68: Evaluación y autorregulación del programa académico | B68: 4 | C68: 2 | E68: 6 | G68: 6 | H68: =G68*C68 -> 12
A69: Evaluación y autorregulación del programa académico | B69: 5 | C69: 0 | E69: 5 | G69: 5 | H69: =G69*C69 -> 0
A70: Evaluación y autorregulación del programa académico | B70: 6 | C70: 0 | E70: 4 | G70: 4 | H70: =G70*C70 -> 0
A71: Evaluación y autorregulación del programa académico | B71: 7 | C71: 2 | E71: 3 | G71: 3 | H71: =G71*C71 -> 6
A72: Evaluación y autorregulación del programa académico | B72: 8 | C72: 7 | E72: 2 | G72: 2 | H72: =G72*C72 -> 14
A73: Evaluación y autorregulación del programa académico | B73: 9 | C73: 5 | E73: 1 | G73: 1 | H73: =G73*C73 -> 5
A74: Vinculación e interacción social | B74: 1 | C74: 0 | E74: 9 | G74: 9 | H74: =G74*C74 -> 0 | I74: =SUM(H74:H82) -> 47 | J74: =I74/$I$1 -> 0.058024691
A75: Vinculación e interacción social | B75: 2 | C75: 2 | E75: 8 | G75: 8 | H75: =G75*C75 -> 16
A76: Vinculación e interacción social | B76: 3 | C76: 0 | E76: 7 | G76: 7 | H76: =G76*C76 -> 0
A77: Vinculación e interacción social | B77: 4 | C77: 0 | E77: 6 | G77: 6 | H77: =G77*C77 -> 0
A78: Vinculación e interacción social | B78: 5 | C78: 1 | E78: 5 | G78: 5 | H78: =G78*C78 -> 5
A79: Vinculación e interacción social | B79: 6 | C79: 2 | E79: 4 | G79: 4 | H79: =G79*C79 -> 8
A80: Vinculación e interacción social | B80: 7 | C80: 1 | E80: 3 | G80: 3 | H80: =G80*C80 -> 3
A81: Vinculación e interacción social | B81: 8 | C81: 3 | E81: 2 | G81: 2 | H81: =G81*C81 -> 6
A82: Vinculación e interacción social | B82: 9 | C82: 9 | E82: 1 | G82: 1 | H82: =G82*C82 -> 9

Sheet FAC 6
A1: Haga clic para escribir el texto de la pregunta | B1: Valor del factor | C1: Recuento | E1: Puntuación | G1: Prueba puntuación | H1: =SUM(C2:C5) -> 0 | I1: =SUM(I2:I26) -> 180
A2: Políticas, estrategias y estructura para la permanencia y la graduación | B2: 1 | C2: 5 | E2: 4 | G2: 4 | H2: =G2*C2 -> 20 | I2: =SUM(H2:H5) -> 47 | J2: =I2/$I$1 -> 0.26111111
A3: Políticas, estrategias y estructura para la permanencia y la graduación | B3: 2 | C3: 6 | E3: 3 | G3: 3 | H3: =G3*C3 -> 18
A4: Políticas, estrategias y estructura para la permanencia y la graduación | B4: 3 | C4: 2 | E4: 2 | G4: 2 | H4: =G4*C4 -> 4
A5: Políticas, estrategias y estructura para la permanencia y la graduación | B5: 4 | C5: 5 | E5: 1 | G5: 1 | H5: =G5*C5 -> 5
A6: Caracterización de estudiantes y sistema de alertas tempranas | B6: 1 | C6: 6 | E6: 4 | G6: 4 | H6: =G6*C6 -> 24 | I6: =SUM(H6:H9) -> 50 | J6: =I6/$I$1 -> 0.27777778
A7: Caracterización de estudiantes y sistema de alertas tempranas | B7: 2 | C7: 2 | E7: 3 | G7: 3 | H7: =G7*C7 -> 6
A8: Caracterización de estudiantes y sistema de alertas tempranas | B8: 3 | C8: 10 | E8: 2 | G8: 2 | H8: =G8*C8 -> 20
A9: Caracterización de estudiantes y sistema de alertas tempranas | B9: 4 | C9: 0 | E9: 1 | G9: 1 | H9: =G9*C9 -> 0
A10: Ajustes a los aspectos curriculares | B10: 1 | C10: 2 | E10: 4 | G10: 4 | H10: =G10*C10 -> 8 | I10: =SUM(H10:H13) -> 38 | J10: =I10/$I$1 -> 0.21111111
A11: Ajustes a los aspectos curriculares | B11: 2 | C11: 6 | E11: 3 | G11: 3 | H11: =G11*C11 -> 18
A12: Ajustes a los aspectos curriculares | B12: 3 | C12: 2 | E12: 2 | G12: 2 | H12: =G12*C12 -> 4
A13: Ajustes a los aspectos curriculares | B13: 4 | C13: 8 | E13: 1 | G13: 1 | H13: =G13*C13 -> 8
A14: Mecanismos de selección | B14: 1 | C14: 5 | E14: 4 | G14: 4 | H14: =G14*C14 -> 20 | I14: =SUM(H14:H17) -> 45 | J14: =I14/$I$1 -> 0.25
A15: Mecanismos de selección | B15: 2 | C15: 4 | E15: 3 | G15: 3 | H15: =G15*C15 -> 12
A16: Mecanismos de selección | B16: 3 | C16: 4 | E16: 2 | G16: 2 | H16: =G16*C16 -> 8
A17: Mecanismos de selección | B17: 4 | C17: 5 | E17: 1 | G17: 1 | H17: =G17*C17 -> 5

Sheet FAC 7
A1: Haga clic para escribir el texto de la pregunta | B1: Valor del factor | C1: Recuento | E1: Puntuación | G1: Prueba puntuación | H1: =SUM(C2:C4) -> 0 | I1: =SUM(I2:I26) -> 138
A2: Inserción del programa en contextos académicos nacionales e internacionales | B2: 1 | C2: 5 | E2: 3 | G2: 3 | H2: =G2*C2 -> 15 | I2: =SUM(H2:H5) -> 48 | J2: =I2/$I$1 -> 0.34782609
A3: Inserción del programa en contextos académicos nacionales e internacionales | B3: 2 | C3: 6 | E3: 2 | G3: 2 | H3: =G3*C3 -> 12
A4: Inserción del programa en contextos académicos nacionales e internacionales | B4: 3 | C4: 6 | E4: 1 | G4: 1 | H4: =G4*C4 -> 6
A5: Relaciones externas de profesores y estudiantes | B5: 1 | C5: 5 | E5: 3 | G5: 3 | H5: =G5*C5 -> 15 | I5: =SUM(H5:H8) -> 56 | J5: =I5/$I$1 -> 0.4057971
A6: Relaciones externas de profesores y estudiantes | B6: 2 | C6: 8 | E6: 2 | G6: 2 | H6: =G6*C6 -> 16
A7: Relaciones externas de profesores y estudiantes | B7: 3 | C7: 4 | E7: 1 | G7: 1 | H7: =G7*C7 -> 4
A8: Habilidades comunicativas en una segunda lengua | B8: 1 | C8: 7 | E8: 3 | G8: 3 | H8: =G8*C8 -> 21 | I8: =SUM(H8:H11) -> 34 | J8: =I8/$I$1 -> 0.24637681
A9: Habilidades comunicativas en una segunda lengua | B9: 2 | C9: 3 | E9: 2 | G9: 2 | H9: =G9*C9 -> 6
A10: Habilidades comunicativas en una segunda lengua | B10: 3 | C10: 7 | E10: 1 | G10: 1 | H10: =G10*C10 -> 7

Sheet FAC 8
A1: Haga clic para escribir el texto de la pregunta | B1: Valor del factor | C1: Recuento | E1: Puntuación | G1: Prueba puntuación | H1: =SUM(C2:C3) -> 0 | I1: =SUM(I2:I5) -> 45
A2: Formación para la investigación, desarrollo tecnológico, la innovación y la creación | B2: 1 | C2: 9 | E2: 2 | G2: =IF(C2>=1,E2,0) -> 2 | H2: =G2*C2 -> 18 | I2: =SUM(H2:H3) -> 24 | J2: =I2/$I$1 -> 0.53333333
A3: Formación para la investigación, desarrollo tecnológico, la innovación y la creación | B3: 2 | C3: 6 | E3: 1 | G3: =IF(C3>=1,E3,0) -> 1 | H3: =G3*C3 -> 6
A4: Compromiso con la investigación, desarrollo tecnológico, la innovación y la creación | B4: 1 | C4: 6 | E4: 2 | G4: =IF(C4>=1,E4,0) -> 2 | H4: =G4*C4 -> 12 | I4: =SUM(H4:H5) -> 21 | J4: =I4/$I$1 -> 0.46666667
A5: Compromiso con la investigación, desarrollo tecnológico, la innovación y la creación | B5: 2 | C5: 9 | E5: 1 | G5: =IF(C5>=1,E5,0) -> 1 | H5: =G5*C5 -> 9

Sheet FAC 9
A1: Haga clic para escribir el texto de la pregunta | B1: Valor del factor | C1: Recuento | E1: Puntuación | G1: Prueba puntuación | H1: =SUM(C2:C3) -> 0 | I1: =SUM(I2:I5) -> 42
A2: Programas y servicios | B2: 1 | C2: 9 | E2: 2 | G2: =IF(C2>=1,E2,0) -> 2 | H2: =G2*C2 -> 18 | I2: =SUM(H2:H3) -> 23 | J2: =I2/$I$1 -> 0.54761905
A3: Programas y servicios | B3: 2 | C3: 5 | E3: 1 | G3: =IF(C3>=1,E3,0) -> 1 | H3: =G3*C3 -> 5
A4: Participación y seguimiento | B4: 1 | C4: 5 | E4: 2 | G4: =IF(C4>=1,E4,0) -> 2 | H4: =G4*C4 -> 10 | I4: =SUM(H4:H5) -> 19 | J4: =I4/$I$1 -> 0.45238095
A5: Participación y seguimiento | B5: 2 | C5: 9 | E5: 1 | G5: =IF(C5>=1,E5,0) -> 1 | H5: =G5*C5 -> 9

Sheet FAC 10
A1: Haga clic para escribir el texto de la pregunta | B1: Valor del factor | C1: Recuento | E1: Puntuación | G1: Prueba puntuación | H1: =SUM(C2:C4) -> 0 | I1: =SUM(I2:I26) -> 138
A2: Estrategias y recursos de apoyo a profesores | B2: 1 | C2: 8 | E2: 3 | G2: 3 | H2: =G2*C2 -> 24 | I2: =SUM(H2:H5) -> 55 | J2: =I2/$I$1 -> 0.39855072
A3: Estrategias y recursos de apoyo a profesores | B3: 2 | C3: 6 | E3: 2 | G3: 2 | H3: =G3*C3 -> 12
A4: Estrategias y recursos de apoyo a profesores | B4: 3 | C4: 4 | E4: 1 | G4: 1 | H4: =G4*C4 -> 4
A5: Estrategias y recursos de apoyo a estudiantes | B5: 1 | C5: 5 | E5: 3 | G5: 3 | H5: =G5*C5 -> 15 | I5: =SUM(H5:H8) -> 49 | J5: =I5/$I$1 -> 0.35507246
A6: Estrategias y recursos de apoyo a estudiantes | B6: 2 | C6: 6 | E6: 2 | G6: 2 | H6: =G6*C6 -> 12
A7: Estrategias y recursos de apoyo a estudiantes | B7: 3 | C7: 7 | E7: 1 | G7: 1 | H7: =G7*C7 -> 7
A8: Recursos bibliográficos y de información | B8: 1 | C8: 5 | E8: 3 | G8: 3 | H8: =G8*C8 -> 15 | I8: =SUM(H8:H11) -> 34 | J8: =I8/$I$1 -> 0.24637681
A9: Recursos bibliográficos y de información | B9: 2 | C9: 6 | E9: 2 | G9: 2 | H9: =G9*C9 -> 12
A10: Recursos bibliográficos y de información | B10: 3 | C10: 7 | E10: 1 | G10: 1 | H10: =G10*C10 -> 7

Sheet FAC 11
A1: Haga clic para escribir el texto de la pregunta | B1: Valor del factor | C1: Recuento | E1: Puntuación | G1: Prueba puntuación | H1: =SUM(C2:C7) -> 0 | I1: =SUM(I2:I79) -> 378
A2: Organización y administración | B2: 1 | C2: 6 | E2: 6 | G2: 6 | H2: =G2*C2 -> 36 | I2: =SUM(H2:H7) -> 87 | J2: =I2/$I$1 -> 0.23015873
A3: Organización y administración | B3: 2 | C3: 6 | E3: 5 | G3: 5 | H3: =G3*C3 -> 30
A4: Organización y administración | B4: 3 | C4: 4 | E4: 4 | G4: 4 | H4: =G4*C4 -> 16
A5: Organización y administración | B5: 4 | C5: 1 | E5: 3 | G5: 3 | H5: =G5*C5 -> 3
A6: Organización y administración | B6: 5 | C6: 1 | E6: 2 | G6: 2 | H6: =G6*C6 -> 2
A7: Organización y administración | B7: 6 | C7: 0 | E7: 1 | G7: 1 | H7: =G7*C7 -> 0
A8: Dirección y gestión | B8: 1 | C8: 3 | E8: 6 | G8: 6 | H8: =G8*C8 -> 18 | I8: =SUM(H8:H13) -> 80 | J8: =I8/$I$1 -> 0.21164021
A9: Dirección y gestión | B9: 2 | C9: 6 | E9: 5 | G9: 5 | H9: =G9*C9 -> 30
A10: Dirección y gestión | B10: 3 | C10: 5 | E10: 4 | G10: 4 | H10: =G10*C10 -> 20
A11: Dirección y gestión | B11: 4 | C11: 4 | E11: 3 | G11: 3 | H11: =G11*C11 -> 12
A12: Dirección y gestión | B12: 5 | C12: 0 | E12: 2 | G12: 2 | H12: =G12*C12 -> 0
A13: Dirección y gestión | B13: 6 | C13: 0 | E13: 1 | G13: 1 | H13: =G13*C13 -> 0
A14: Sistemas de comunicación e información | B14: 1 | C14: 0 | E14: 6 | G14: 6 | H14: =G14*C14 -> 0 | I14: =SUM(H14:H19) -> 50 | J14: =I14/$I$1 -> 0.13227513
A15: Sistemas de comunicación e información | B15: 2 | C15: 0 | E15: 5 | G15: 5 | H15: =G15*C15 -> 0
A16: Sistemas de comunicación e información | B16: 3 | C16: 4 | E16: 4 | G16: 4 | H16: =G16*C16 -> 16
A17: Sistemas de comunicación e información | B17: 4 | C17: 6 | E17: 3 | G17: 3 | H17: =G17*C17 -> 18
A18: Sistemas de comunicación e información | B18: 5 | C18: 8 | E18: 2 | G18: 2 | H18: =G18*C18 -> 16
A19: Sistemas de comunicación e información | B19: 6 | C19: 0 | E19: 1 | G19: 1 | H19: =G19*C19 -> 0
A20: Estudiantes y capacidad institucional | B20: 1 | C20: 1 | E20: 6 | G20: 6 | H20: =G20*C20 -> 6 | I20: =SUM(H20:H25) -> 45 | J20: =I20/$I$1 -> 0.11904762
A21: Estudiantes y capacidad institucional | B21: 2 | C21: 0 | E21: 5 | G21: 5 | H21: =G21*C21 -> 0
A22: Estudiantes y capacidad institucional | B22: 3 | C22: 3 | E22: 4 | G22: 4 | H22: =G22*C22 -> 12
A23: Estudiantes y capacidad institucional | B23: 4 | C23: 4 | E23: 3 | G23: 3 | H23: =G23*C23 -> 12
A24: Estudiantes y capacidad institucional | B24: 5 | C24: 5 | E24: 2 | G24: 2 | H24: =G24*C24 -> 10
A25: Estudiantes y capacidad institucional | B25: 6 | C25: 5 | E25: 1 | G25: 1 | H25: =G25*C25 -> 5
A26: Financiación del programa académico | B26: 1 | C26: 3 | E26: 6 | G26: 6 | H26: =G26*C26 -> 18 | I26: =SUM(H26:H31) -> 49 | J26: =I26/$I$1 -> 0.12962963
A27: Financiación del programa académico | B27: 2 | C27: 3 | E27: 5 | G27: 5 | H27: =G27*C27 -> 15
A28: Financiación del programa académico | B28: 3 | C28: 0 | E28: 4 | G28: 4 | H28: =G28*C28 -> 0
A29: Financiación del programa académico | B29: 4 | C29: 1 | E29: 3 | G29: 3 | H29: =G29*C29 -> 3
A30: Financiación del programa académico | B30: 5 | C30: 2 | E30: 2 | G30: 2 | H30: =G30*C30 -> 4
A31: Financiación del programa académico | B31: 6 | C31: 9 | E31: 1 | G31: 1 | H31: =G31*C31 -> 9
A32: Aseguramiento de la alta calidad y mejora continua | B32: 1 | C32: 5 | E32: 6 | G32: 6 | H32: =G32*C32 -> 30 | I32: =SUM(H32:H37) -> 67 | J32: =I32/$I$1 -> 0.17724868
A33: Aseguramiento de la alta calidad y mejora continua | B33: 2 | C33: 3 | E33: 5 | G33: 5 | H33: =G33*C33 -> 15
A34: Aseguramiento de la alta calidad y mejora continua | B34: 3 | C34: 2 | E34: 4 | G34: 4 | H34: =G34*C34 -> 8
A35: Aseguramiento de la alta calidad y mejora continua | B35: 4 | C35: 2 | E35: 3 | G35: 3 | H35: =G35*C35 -> 6
A36: Aseguramiento de la alta calidad y mejora continua | B36: 5 | C36: 2 | E36: 2 | G36: 2 | H36: =G36*C36 -> 4
A37: Aseguramiento de la alta calidad y mejora continua | B37: 6 | C37: 4 | E37: 1 | G37: 1 | H37: =G37*C37 -> 4

Sheet FAC 12
A1: Haga clic para escribir el texto de la pregunta | B1: Valor del factor | C1: Recuento | E1: Puntuación | G1: Prueba puntuación | H1: =SUM(C2:C3) -> 0 | I1: =SUM(I2:I5) -> 42
A2: Recursos de infraestructura física y tecnológica | B2: 1 | C2: 8 | E2: 2 | G2: =IF(C2>=1,E2,0) -> 2 | H2: =G2*C2 -> 16 | I2: =SUM(H2:H3) -> 22 | J2: =I2/$I$1 -> 0.52380952
A3: Recursos de infraestructura física y tecnológica | B3: 2 | C3: 6 | E3: 1 | G3: =IF(C3>=1,E3,0) -> 1 | H3: =G3*C3 -> 6
A4: Recursos informáticos y de comunicación | B4: 1 | C4: 6 | E4: 2 | G4: =IF(C4>=1,E4,0) -> 2 | H4: =G4*C4 -> 12 | I4: =SUM(H4:H5) -> 20 | J4: =I4/$I$1 -> 0.47619048
A5: Recursos informáticos y de comunicación | B5: 2 | C5: 8 | E5: 1 | G5: =IF(C5>=1,E5,0) -> 1 | H5: =G5*C5 -> 8

Sheet Graficos
B2: FACTOR | C2: PONDERACIÓN
B3: PROYECTO EDUCATIVO DEL PROGRAMA E IDENTIDAD INSTITUCIONAL. | C3: =FACTORES!J2 -> 0.12078273
B4: ESTUDIANTES | C4: =FACTORES!J14 -> 0.12415655
B5: PROFESORES | C5: =FACTORES!J26 -> 0.11673414
B6: EGRESADOS | C6: =FACTORES!J38 -> 0.10796221
B7: ASPECTOS ACADÉMICOS Y RESULTADOS DE APRENDIZAJE | C7: =FACTORES!J50 -> 0.067476383
B8: PERMANENCIA Y GRADUACIÓN | C8: =FACTORES!J62 -> 0.072874494
B9: INTERACCIÓN CON EL ENTORNO NACIONAL E INTERNACIONAL | C9: =FACTORES!J74 -> 0.10593792
B10: APORTES DE LA INVESTIGACIÓN, LA INNOVACIÓN, EL DESARROLLO TECNOLÓGICO Y LA CREACIÓN, ASOCIADOS AL PROGRAMA ACADÉMICO | C10: =FACTORES!J86 -> 0.047908232
B11: BIENESTAR DE LA COMUNIDAD ACADÉMICA DEL PROGRAMA | C11: =FACTORES!J98 -> 0.064102564
B12: MEDIOS EDUCATIVOS Y AMBIENTES DE APRENDIZAJE | C12: =FACTORES!J110 -> 0.068825911
B13: ORGANIZACIÓN, ADMINISTRACIÓN Y FINANCIACIÓN DEL PROGRAMA ACADÉMICO | C13: =FACTORES!J122 -> 0.066801619
B14: RECURSOS FÍSICOS Y TECNOLÓGICOS | C14: =FACTORES!J134 -> 0.036437247
B17: FACTOR 1 | C17: PONDERACIÓN
A18: 1 | B18: Proyecto educativo del Programa. | C18: =PEP!J2 -> 0.53846154
A19: 2 | B19: Relevancia académica y pertinencia social del programa académico | C19: =PEP!J4 -> 0.46153846
B22: FACTOR 2 | C22: PONDERACIÓN
A23: 3 | B23: Participación en actividades de formación integral | C23: =EST!J2 -> 0.33139535
A24: 4 | B24: Orientación y seguimiento a estudiantes | C24: =EST!J7 -> 0.18023256
A25: 5 | B25: Capacidad de trabajo autónomo | C25: =EST!J12 -> 0.19186047
A26: 6 | B26: Reglamento estudiantil y política académica | C26: =EST!J17 -> 0.13372093
A27: 7 | B27: Estímulos y apoyos para estudiantes | C27: =EST!J22 -> 0.1627907
B30: FACTOR 3 | C30: PONDERACIÓN
A31: 8 | B31: Selección, vinculación y permanencia | C31: =DOC!J2 -> 0.1712963
A32: 9 | B32: Estatuto profesoral | C32: =DOC!J10 -> 0.13734568
A33: 10 | B33: Número, dedicación, nivel de formación y experiencia | C33: =DOC!J18 -> 0.15740741
A34: 11 | B34: Desarrollo profesoral | C34: =DOC!J26 -> 0.15277778
A35: 12 | B35: Estímulos a la trayectoria profesoral | C35: =DOC!J34 -> 0.10339506
A36: 13 | B36: Producción, pertinencia, utilización e impacto del material docente | C36: =DOC!J42 -> 0.11728395
A37: 14 | B37: Remuneración por méritos | C37: =DOC!J50 -> 0.094135802
A38: 15 | B38: Evaluación de profesores | C38: =DOC!J58 -> 0.066358025
B41: FACTOR 5 | C41: PONDERACIÓN
A42: 16 | B42: Integralidad de los aspectos curriculares | C42: ='FAC 5'!J2 -> 0.17160494
A43: 17 | B43: Flexibilidad de los aspectos curriculares | C43: ='FAC 5'!J11 -> 0.14691358
A44: 18 | B44: Interdisciplinariedad | C44: ='FAC 5'!J20 -> 0.12839506
A45: 19 | B45: Estrategias pedagógicas | C45: ='FAC 5'!J29 -> 0.11358025
A46: 20 | B46: Sistema de evaluación de estudiantes | C46: ='FAC 5'!J38 -> 0.075308642
A47: 21 | B47: Resultados de aprendizaje | C47: ='FAC 5'!J47 -> 0.12839506
A48: 22 | B48: Competencias | C48: ='FAC 5'!J56 -> 0.10987654
A49: 23 | B49: Evaluación y autorregulación del programa académico | C49: ='FAC 5'!J65 -> 0.067901235
A50: 24 | B50: Vinculación e interacción social | C50: ='FAC 5'!J74 -> 0.058024691
B53: FACTOR 6 | C53: PONDERACIÓN
A54: 25 | B54: Políticas, estrategias y estructura para la permanencia y la graduación | C54: ='FAC 6'!J2 -> 0.26111111
A55: 26 | B55: Caracterización de estudiantes y sistema de alertas tempranas | C55: ='FAC 6'!J6 -> 0.27777778
A56: 27 | B56: Ajustes a los aspectos curriculares | C56: ='FAC 6'!J10 -> 0.21111111
A57: 28 | B57: Mecanismos de selección | C57: ='FAC 6'!J14 -> 0.25
B60: FACTOR 7 | C60: PONDERACIÓN
A61: 29 | B61: Inserción del programa en contextos académicos nacionales e internacionales | C61: ='FAC 7'!J2 -> 0.34782609
A62: 30 | B62: Relaciones externas de profesores y estudiantes | C62: ='FAC 7'!J5 -> 0.4057971
A63: 31 | B63: Habilidades comunicativas en una segunda lengua | C63: ='FAC 7'!J8 -> 0.24637681
B65: FACTOR 8 | C65: PONDERACIÓN
A66: 32 | B66: Formación para la investigación, desarrollo tecnológico, la innovación y la creación | C66: ='FAC 8'!J2 -> 0.53333333
A67: 33 | B67: Compromiso con la investigación, desarrollo tecnológico, la innovación y la creación | C67: ='FAC 8'!J4 -> 0.46666667
B70: FACTOR 9 | C70: PONDERACIÓN
A71: 34 | B71: Programas y servicios | C71: ='FAC 9'!J2 -> 0.54761905
A72: 35 | B72: Participación y seguimiento | C72: ='FAC 9'!J4 -> 0.45238095
B75: FACTOR 10 | C75: PONDERACIÓN
A76: 36 | B76: Estrategias y recursos de apoyo a profesores | C76: ='FAC 10'!J2 -> 0.39855072
A77: 37 | B77: Estrategias y recursos de apoyo a estudiantes | C77: ='FAC 10'!J5 -> 0.35507246
A78: 38 | B78: Recursos bibliográficos y de información | C78: ='FAC 10'!J8 -> 0.24637681
B81: FACTOR 11 | C81: PONDERACIÓN
A82: 39 | B82: Organización y administración | C82: ='FAC 11'!J2 -> 0.23015873
A83: 40 | B83: Dirección y gestión | C83: ='FAC 11'!J8 -> 0.21164021
A84: 41 | B84: Sistemas de comunicación e información | C84: ='FAC 11'!J14 -> 0.13227513
A85: 42 | B85: Estudiantes y capacidad institucional | C85: ='FAC 11'!J20 -> 0.11904762
A86: 43 | B86: Financiación del programa académico | C86: ='FAC 11'!J26 -> 0.12962963
A87: 44 | B87: Aseguramiento de la alta calidad y mejora continua | C87: ='FAC 11'!J32 -> 0.17724868
B89: FACTOR 12 | C89: PONDERACIÓN
A90: 45 | B90: Recursos de infraestructura física y tecnológica | C90: ='FAC 12'!J2 -> 0.52380952
A91: 46 | B91: Recursos informáticos y de comunicación | C91: ='FAC 12'!J4 -> 0.47619048

Sheet Ponderacion
A1: # Factor | B1: Factor | C1: Ponderación | D1: Características | E1: Ponderación
A2: 1 | B2: PROYECTO EDUCATIVO DEL PROGRAMA E IDENTIDAD INSTITUCIONAL. | C2: =Graficos!C3 -> 0.12078273 | D2: Proyecto educativo del Programa. | E2: =Graficos!C18 -> 0.53846154
D3: Relevancia académica y pertinencia social del programa académico | E3: =Graficos!C19 -> 0.46153846
A4: 2 | B4: ESTUDIANTES | C4: =Graficos!C4 -> 0.12415655 | D4: Participación en actividades de formación integral | E4: =Graficos!C23 -> 0.33139535
D5: Orientación y seguimiento a estudiantes | E5: =Graficos!C24 -> 0.18023256
D6: Capacidad de trabajo autónomo | E6: =Graficos!C25 -> 0.19186047
D7: Reglamento estudiantil y política académica | E7: =Graficos!C26 -> 0.13372093
D8: Estímulos y apoyos para estudiantes | E8: =Graficos!C27 -> 0.1627907
A9: 3 | B9: PROFESORES | C9: =Graficos!C5 -> 0.11673414 | D9: Selección, vinculación y permanencia | E9: =Graficos!C31 -> 0.1712963
D10: Estatuto profesoral | E10: =Graficos!C32 -> 0.13734568
D11: Número, dedicación, nivel de formación y experiencia | E11: =Graficos!C33 -> 0.15740741
D12: Desarrollo profesoral | E12: =Graficos!C34 -> 0.15277778
D13: Estímulos a la trayectoria profesoral | E13: =Graficos!C35 -> 0.10339506
D14: Producción, pertinencia, utilización e impacto del material docente | E14: =Graficos!C36 -> 0.11728395
D15: Remuneración por méritos | E15: =Graficos!C37 -> 0.094135802
D16: Evaluación de profesores | E16: =Graficos!C38 -> 0.066358025
A17: 4 | B17: EGRESADOS | C17: =Graficos!C6 -> 0.10796221 | D17: Seguimiento a los egresados | E17: 0.54761905
D18: Impacto de los egresados en el medio social y académico | E18: 0.45238095
A19: 5 | B19: ASPECTOS ACADÉMICOS Y RESULTADOS DE APRENDIZAJE | C19: =Graficos!C7 -> 0.067476383 | D19: Integralidad de los aspectos curriculares | E19: =Graficos!C42 -> 0.17160494
D20: Flexibilidad de los aspectos curriculares | E20: =Graficos!C43 -> 0.14691358
D21: Interdisciplinariedad | E21: =Graficos!C44 -> 0.12839506
D22: Estrategias pedagógicas | E22: =Graficos!C45 -> 0.11358025
D23: Sistema de evaluación de estudiantes | E23: =Graficos!C46 -> 0.075308642
D24: Resultados de aprendizaje | E24: =Graficos!C47 -> 0.12839506
D25: Competencias | E25: =Graficos!C48 -> 0.10987654
D26: Evaluación y autorregulación del programa académico | E26: =Graficos!C49 -> 0.067901235
D27: Vinculación e interacción social | E27: =Graficos!C50 -> 0.058024691
A28: 6 | B28: PERMANENCIA Y GRADUACIÓN | C28: =Graficos!C8 -> 0.072874494 | D28: Políticas, estrategias y estructura para la permanencia y la graduación | E28: =Graficos!C54 -> 0.26111111
D29: Caracterización de estudiantes y sistema de alertas tempranas | E29: =Graficos!C55 -> 0.27777778
D30: Ajustes a los aspectos curriculares | E30: =Graficos!C56 -> 0.21111111
D31: Mecanismos de selección | E31: =Graficos!C57 -> 0.25
A32: 7 | B32: INTERACCIÓN CON EL ENTORNO NACIONAL E INTERNACIONAL | C32: =Graficos!C9 -> 0.10593792 | D32: Inserción del programa en contextos académicos nacionales e internacionales | E32: =Graficos!C61 -> 0.34782609
D33: Relaciones externas de profesores y estudiantes | E33: =Graficos!C62 -> 0.4057971
D34: Habilidades comunicativas en una segunda lengua | E34: =Graficos!C63 -> 0.24637681
A35: 8 | B35: APORTES DE LA INVESTIGACIÓN, LA INNOVACIÓN, EL DESARROLLO TECNOLÓGICO Y LA CREACIÓN, ASOCIADOS AL PROGRAMA ACADÉMICO | C35: =Graficos!C10 -> 0.047908232 | D35: Formación para la investigación, desarrollo tecnológico, la innovación y la creación | E35: =Graficos!C66 -> 0.53333333
D37: Compromiso con la investigación, desarrollo tecnológico, la innovación y la creación | E37: =Graficos!C67 -> 0.46666667
A38: 9 | B38: BIENESTAR DE LA COMUNIDAD ACADÉMICA DEL PROGRAMA | C38: =Graficos!C11 -> 0.064102564 | D38: Programas y servicios | E38: =Graficos!C71 -> 0.54761905
D39: Participación y seguimiento | E39: =Graficos!C72 -> 0.45238095
A40: 10 | B40: MEDIOS EDUCATIVOS Y AMBIENTES DE APRENDIZAJE | C40: =Graficos!C12 -> 0.068825911 | D40: Estrategias y recursos de apoyo a profesores | E40: =Graficos!C76 -> 0.39855072
A41: 10 | D41: Estrategias y recursos de apoyo a estudiantes | E41: =Graficos!C77 -> 0.35507246
D42: Recursos bibliográficos y de información | E42: =Graficos!C78 -> 0.24637681
A43: 11 | B43: ORGANIZACIÓN, ADMINISTRACIÓN Y FINANCIACIÓN DEL PROGRAMA ACADÉMICO | C43: =Graficos!C13 -> 0.066801619 | D43: Organización y administración | E43: =Graficos!C82 -> 0.23015873
D44: Dirección y gestión | E44: =Graficos!C83 -> 0.21164021
D45: Sistemas de comunicación e información | E45: =Graficos!C84 -> 0.13227513
D46: Estudiantes y capacidad institucional | E46: =Graficos!C85 -> 0.11904762
D47: Financiación del programa académico | E47: =Graficos!C86 -> 0.12962963
D48: Aseguramiento de la alta calidad y mejora continua | E48: =Graficos!C87 -> 0.17724868
A49: 12 | B49: RECURSOS FÍSICOS Y TECNOLÓGICOS | C49: =Graficos!C14 -> 0.036437247 | D49: Recursos de infraestructura física y tecnológica | E49: =Graficos!C90 -> 0.52380952
D50: Recursos informáticos y de comunicación | E50: =Graficos!C91 -> 0.47619048

Sheet Hoja2
A1: FACTOR | B1: Valoración interpretativa | C1: NOTA | D1: PONDERACIÓN | G1: # Factor | H1: Factor | I1: Ponderación | J1: Valoración interpretativa | K1: NOTA | M1: PROYECTO EDUCATIVO DEL PROGRAMA E IDENTIDAD INSTITUCIONAL.
A2: Factor 1. Misión y visión de la Universidad. | B2: Se cumple en alto grado | C2: 4.4 | D2: 0.147 | E2: 0.7 | G2: 1 | H2: PROYECTO EDUCATIVO DEL PROGRAMA E IDENTIDAD INSTITUCIONAL. | I2: 0.12078273 | M2: Grado de cumplimiento | O2: Calificación numérica | Q2: Ponderación del factor
M4: Anterior 2020 | N4: Actual 2025 | O4: Anterior 2020 | P4: Actual 2025
M5: Se cumple en alto grado | N5: Se cumple en alto grado | O5: 4.4 | P5: 4 | Q5: 0.12078273
M6: Fortalezas | O6: Oportunidades de mejora
A9: Factor 2. Estudiantes. | B9: Se cumple en alto grado | C9: 4 | D9: 0.137 | E9: 0.5 | G9: 2 | H9: ESTUDIANTES | I9: 0.12415655 | M9: ESTUDIANTES
M10: Grado de cumplimiento | O10: Calificación numérica | Q10: Ponderación del factor
M12: Anterior 2020 | N12: Actual 2025 | O12: Anterior 2020 | P12: Actual 2025
M13: Se cumple en alto grado | N13: Se cumple en alto grado | O13: 4 | P13: 4.6 | Q13: 0.12415655
M14: Fortalezas | O14: Oportunidades de mejora
A17: Factor 3. Profesores. | B17: Se cumple en alto grado | C17: 4.2 | D17: 0.126 | E17: 0.5 | G17: 3 | H17: PROFESORES | I17: 0.11673414 | M17: PROFESORES
M18: Grado de cumplimiento | O18: Calificación numérica | Q18: Ponderación del factor
M20: Anterior 2020 | N20: Actual 2025 | O20: Anterior 2020 | P20: Actual 2025
M21: Se cumple en alto grado | N21: Se cumple en alto grado | O21: 4.2 | P21: 4.7 | Q21: 0.11673414
M22: Fortalezas | O22: Oportunidades de mejora
A25: Factor 9. Graduados y Análisis de Impacto del Programa. | B25: Se cumple en alto grado | C25: 4.1 | D25: 0.067 | E25: 0.3 | G25: 4 | H25: EGRESADOS | I25: 0.10796221 | M25: EGRESADOS
M26: Grado de cumplimiento | O26: Calificación numérica | Q26: Ponderación del factor
M28: Anterior 2020 | N28: Actual 2025 | O28: Anterior 2020 | P28: Actual 2025
M29: Se cumple en alto grado | N29: Se cumple en alto grado | O29: 4 | P29: 4.8 | Q29: 0.10796221
M30: Fortalezas | O30: Oportunidades de mejora
A33: Factor 4. Procesos Académicos y Lineamientos Curriculares. | B33: Se cumple en alto grado | C33: 4 | D33: 0.11 | E33: 0.4 | G33: 5 | H33: ASPECTOS ACADÉMICOS Y RESULTADOS DE APRENDIZAJE | I33: 0.067476383 | M33: ASPECTOS ACADÉMICOS Y RESULTADOS DE APRENDIZAJE
M34: Grado de cumplimiento | O34: Calificación numérica | Q34: Ponderación del factor
M36: Anterior 2020 | N36: Actual 2025 | O36: Anterior 2020 | P36: Actual 2025
M37: Se cumple en alto grado | N37: Se cumple en alto grado | O37: 4.2 | P37: 4.3 | Q37: 0.067476383
M38: Fortalezas | O38: Oportunidades de mejora
A41: Factor 5. Investigación, generación de conocimiento y producción artística. | B41: Se cumple en alto grado | C41: 4.2 | D41: 0.114 | E41: 0.5 | G41: 6 | H41: PERMANENCIA Y GRADUACIÓN | I41: 0.072874494 | M41: PERMANENCIA Y GRADUACIÓN
M42: Grado de cumplimiento | O42: Calificación numérica | Q42: Ponderación del factor
M44: Anterior 2020 | N44: Actual 2025 | O44: Anterior 2020 | P44: Actual 2025
M45: Se cumple en alto grado | N45: Se cumple en alto grado | O45: 4 | P45: 5 | Q45: 0.072874494
M46: Fortalezas | O46: Oportunidades de mejora
A49: Factor 6. Articulación con el entorno y capacidad para generar procesos de innovación. | B49: Se cumple en alto grado | C49: 4 | D49: 0.093 | E49: 0.4 | G49: 7 | H49: INTERACCIÓN CON EL ENTORNO NACIONAL E INTERNACIONAL | I49: 0.10593792 | M49: INTERACCIÓN CON EL ENTORNO NACIONAL E INTERNACIONAL
M50: Grado de cumplimiento | O50: Calificación numérica | Q50: Ponderación del factor
M52: Anterior 2020 | N52: Actual 2025 | O52: Anterior 2020 | P52: Actual 2025
M53: Se cumple en alto grado | N53: Se cumple en alto grado | O53: 4 | P53: 4.5 | Q53: 0.10593792
M54: Fortalezas | O54: Oportunidades de mejora
A57: Factor 7. Internacionalización, Alianzas Estratégicas e Inserción en Redes Científicas Globales. | B57: Se cumple aceptablemente | C57: 3.4 | D57: 0.085 | E57: 0.3 | G57: 8 | H57: APORTES DE LA INVESTIGACIÓN, LA INNOVACIÓN, EL DESARROLLO TECNOLÓGICO Y LA CREACIÓN, ASOCIADOS AL PROGRAMA ACADÉMICO | I57: 0.047908232 | M57: APORTES DE LA INVESTIGACIÓN, LA INNOVACIÓN, EL DESARROLLO TECNOLÓGICO Y LA CREACIÓN, ASOCIADOS AL PROGRAMA ACADÉMICO
M58: Grado de cumplimiento | O58: Calificación numérica | Q58: Ponderación del factor
M60: Anterior 2020 | N60: Actual 2025 | O60: Anterior 2020 | P60: Actual 2025
M61: Se cumple aceptablemente | N61: Se cumple en alto grado | O61: 3.4 | P61: 4.5 | Q61: 0.047908232
M62: Fortalezas | O62: Oportunidades de mejora
A65: Factor 9. Graduados y Análisis de Impacto del Programa. | B65: Se cumple en alto grado | C65: 4.1 | D65: 0.067 | E65: 0.3 | G65: 9 | H65: BIENESTAR DE LA COMUNIDAD ACADÉMICA DEL PROGRAMA | I65: 0.064102564 | M65: BIENESTAR DE LA COMUNIDAD ACADÉMICA DEL PROGRAMA
M66: Grado de cumplimiento | O66: Calificación numérica | Q66: Ponderación del factor
M68: Anterior 2020 | N68: Actual 2025 | O68: Anterior 2020 | P68: Actual 2025
M69: Se cumple en alto grado | N69: Se cumple en alto grado | O69: 4.1 | P69: 4.8 | Q69: 0.064102564
M70: Fortalezas | O70: Oportunidades de mejora
A73: Factor 8. Bienestar y Ambiente Institucional. | B73: Se cumple en alto grado | C73: 4 | D73: 0.05 | E73: 0.2 | G73: 10 | H73: MEDIOS EDUCATIVOS Y AMBIENTES DE APRENDIZAJE | I73: 0.068825911 | M73: MEDIOS EDUCATIVOS Y AMBIENTES DE APRENDIZAJE
M74: Grado de cumplimiento | O74: Calificación numérica | Q74: Ponderación del factor
M76: Anterior 2020 | N76: Actual 2025 | O76: Anterior 2020 | P76: Actual 2025
M77: Se cumple en alto grado | N77: Se cumple en alto grado | O77: 4 | P77: 5 | Q77: 0.068825911
M78: Fortalezas | O78: Oportunidades de mejora
A81: Factor 10. Recursos Físicos y Gestión Administrativa y Financiera. | B81: Se cumple en alto grado | C81: 3.9 | D81: 0.071 | E81: 0.3 | G81: 11 | H81: ORGANIZACIÓN, ADMINISTRACIÓN Y FINANCIACIÓN DEL PROGRAMA ACADÉMICO | I81: 0.066801619 | M81: ORGANIZACIÓN, ADMINISTRACIÓN Y FINANCIACIÓN DEL PROGRAMA ACADÉMICO
M82: Grado de cumplimiento | O82: Calificación numérica | Q82: Ponderación del factor
M84: Anterior 2020 | N84: Actual 2025 | O84: Anterior 2020 | P84: Actual 2025
M85: Se cumple en alto grado | N85: Se cumple en alto grado | O85: 3.9 | P85: 5 | Q85: 0.066801619
M86: Fortalezas | O86: Oportunidades de mejora
A89: Factor 10. Recursos Físicos y Gestión Administrativa y Financiera. | B89: Se cumple en alto grado | C89: 3.9 | D89: 0.071 | E89: 0.3 | G89: 12 | H89: RECURSOS FÍSICOS Y TECNOLÓGICOS | I89: 0.036437247 | M89: RECURSOS FÍSICOS Y TECNOLÓGICOS
M90: Grado de cumplimiento | O90: Calificación numérica | Q90: Ponderación del factor
M92: Anterior 2020 | N92: Actual 2025 | O92: Anterior 2020 | P92: Actual 2025
M93: Se cumple en alto grado | N93: Se cumple en alto grado | O93: 3.9 | P93: 5 | Q93: 0.036437247
M94: Fortalezas | O94: Oportunidades de mejora

Sheet anterior
C3: Grado de cumplimiento | E3: Valoración Cualitativa | G3: Cuantitativa
C4: Se cumple plenamente | D4: 45 - 50 | E4: Existen y tienen coherencia total con los indicadores | F4: Se cumple plenamente | G4: 5
C5: Se cumple en alto grado | D5: 38 – 44 | E5: Existen y tienen coherencia parcial con los indicadores | F5: Se cumple en alto grado | G5: 4
C6: Se cumple aceptablemente | D6: 30- 37 | E6: Existen y no tienen coherencia con los indicadores | F6: Se cumple aceptablemente | G6: 3
C7: Es insuficiente | D7: 20 - 29 | E7: Está en elaboración - Dependiendo el estado | F7: Se cumple insatisfactoriamente | G7: 2
C8: Es deficiente | D8: 0 - 19 | E8: No existe | F8: No se cumple | G8: 1
A10: FACTOR 1. MISIÓN Y VISIÓN DE LA UNIVERSIDAD | H10: FACTOR 6. ARTICULACIÓN CON EL ENTORNO Y CAPACIDAD PARA GENERAR PROCESOS DE INNOVACIÓN.
A12: Ponderación | B12: Grado de cumplimiento (1-5) | C12: Evaluación -ponderación | D12: Logro Ideal | E12: Relación con el logro ideal | F12: Valoración interpretativa | H12: Ponderación | I12: Grado de cumplimiento (1-5) | J12: Evaluación -ponderación | K12: Logro Ideal | L12: Relación con el logro ideal | M12: Valoración interpretativa
A13: 0.147 | B13: 4.4 | C13: 0.7 | D13: 0.8 | E13: 0.9 | F13: Se cumple en alto grado | H13: 0.09 | I13: 4 | J13: 0.4 | K13: 0.5 | L13: 0.8 | M13: Se cumple en alto grado
A15: FACTOR 2. ESTUDIANTES | H15: FACTOR 7. INTERNACIONALIZACIÓN, ALIANZAS ESTRATÉGICAS E INSERCIÓN EN REDES CIENTÍFICAS GLOBALES
A17: Ponderación | B17: Grado de cumplimiento (1-5) | C17: Evaluación -ponderación | D17: Logro Ideal | E17: Relación con el logro ideal | F17: Valoración interpretativa | H17: Ponderación | I17: Grado de cumplimiento (1-5) | J17: Evaluación -ponderación | K17: Logro Ideal | L17: Relación con el logro ideal | M17: Valoración interpretativa
A18: 0.14 | B18: 4 | C18: 0.5 | D18: 0.7 | E18: 0.8 | F18: Se cumple en alto grado | H18: 0.09 | I18: 3.4 | J18: 0.3 | K18: 0.5 | L18: 0.6 | M18: Cumple Aceptablemente
A20: FACTOR 3. PROFESORES | H20: FACTOR 8. BIENESTAR Y AMBIENTE INSTITUCIONAL
A22: Ponderación | B22: Grado de cumplimiento (1-5) | C22: Evaluación -ponderación | D22: Logro Ideal | E22: Relación con el logro ideal | F22: Valoración interpretativa | H22: Ponderación | I22: Grado de cumplimiento (1-5) | J22: Evaluación -ponderación | K22: Logro Ideal | L22: Relación con el logro ideal | M22: Valoración interpretativa
A23: 0.13 | B23: 4.2 | C23: 0.6 | D23: 0.7 | E23: 0.9 | F23: Se cumple en alto grado | H23: 0.05 | I23: 4 | J23: 0.2 | K23: 0.3 | L23: 0.8 | M23: Se cumple en alto grado
A25: FACTOR 4. PROCESOS ACADÉMICOS Y LINEAMIENTOS CURRICULARES. | H25: FACTOR 9. GRADUADOS Y ANÁLISIS DE IMPACTO
A27: Ponderación | B27: Grado de cumplimiento (1-5) | C27: Evaluación -ponderación | D27: Logro Ideal | E27: Relación con el logro ideal | F27: Valoración interpretativa | H27: Ponderación | I27: Grado de cumplimiento (1-5) | J27: Evaluación -ponderación | K27: Logro Ideal | L27: Relación con el logro ideal | M27: Valoración interpretativa
A28: 0.11 | B28: 4 | C28: 0.4 | D28: 0.6 | E28: 0.8 | F28: Se cumple en alto grado | H28: 0.07 | I28: 4.1 | J28: 0.3 | K28: 0.35 | L28: 0.8 | M28: Se cumple en alto grado
A30: FACTOR 5. INVESTIGACIÓN, GENERACIÓN DE CONOCIMIENTO Y PRODUCCIÓN ARTÍSTICA | H30: FACTOR 10. RECURSOS FÍSICOS Y GESTIÓN ADMINISTRATIVA Y FINANCIERA
A32: Ponderación | B32: Grado de cumplimiento (1-5) | C32: Evaluación -ponderación | D32: Logro Ideal | E32: Relación con el logro ideal | F32: Valoración interpretativa | H32: Ponderación | I32: Grado de cumplimiento (1-5) | J32: Evaluación -ponderación | K32: Logro Ideal | L32: Relación con el logro ideal | M32: Valoración interpretativa
A33: 0.11 | B33: 4.2 | C33: 0.5 | D33: 0.6 | E33: 0.8 | F33: Se cumple en alto grado | H33: 0.07 | I33: 3.9 | J33: 0.3 | K33: 0.4 | L33: 0.8 | M33: Se cumple en alto grado
B36: RESULTADOS FINALES DE AUTOEVALUACIÓN
B39: FACTOR | C39: Valoración interpretativa | D39: NOTA | E39: PONDERACIÓN
B40: Factor 1. Misión y visión de la Universidad. | C40: Se cumple en alto grado | D40: 4.4 | E40: 0.147 | F40: 0.7
B41: Factor 2. Estudiantes. | C41: Se cumple en alto grado | D41: 4 | E41: 0.137 | F41: 0.5
B42: Factor 3. Profesores. | C42: Se cumple en alto grado | D42: 4.2 | E42: 0.126 | F42: 0.5
B43: Factor 4. Procesos Académicos y Lineamientos Curriculares. | C43: Se cumple en alto grado | D43: 4 | E43: 0.11 | F43: 0.4
B44: Factor 5. Investigación, generación de conocimiento y producción artística. | C44: Se cumple en alto grado | D44: 4.2 | E44: 0.114 | F44: 0.5
B45: Factor 6. Articulación con el entorno y capacidad para generar procesos de innovación. | C45: Se cumple en alto grado | D45: 4 | E45: 0.093 | F45: 0.4
B46: Factor 7. Internacionalización, Alianzas Estratégicas e Inserción en Redes Científicas Globales. | C46: Se cumple aceptablemente | D46: 3.4 | E46: 0.085 | F46: 0.3
B47: Factor 8. Bienestar y Ambiente Institucional. | C47: Se cumple en alto grado | D47: 4 | E47: 0.05 | F47: 0.2
B48: Factor 9. Graduados y Análisis de Impacto del Programa. | C48: Se cumple en alto grado | D48: 4.1 | E48: 0.067 | F48: 0.3
B49: Factor 10. Recursos Físicos y Gestión Administrativa y Financiera. | C49: Se cumple en alto grado | D49: 3.9 | E49: 0.071 | F49: 0.3
B50: TOTAL | C50: Se cumple en alto grado | D50: 1 | F50: 4.1

Sheet Hoja5
A2: ° | B2: FACTOR | C2: POONDERACIÓN | D2: CARCATERISTICA | E2: POONDERACIÓN | F2: ASPECTO | G2: Grado de cumplimiento (1-5) | H2: POONDERACIÓN | I2: PROMEDIO CALIFICACIÓN | J2: PROMEDIO CALIFICACIÓN
A3: 1 | B3: FACTOR 1. PROYECTO EDUCATIVO DEL PROGRAMA E IDENTIDAD INSTITUCIONAL | C3: 0.12078273 | D3: Proyecto educativo del programa | E3: 0.53846154 | F3: Demostrar coherencia del Proyecto Educativo del Programa (PEP) o el que haga sus veces, con los lineamientos y políticas institucionales, así como en la definición de objetivos de formación y resultados de aprendizaje y la manera cómo el PEP ha ido mejorando, como resultado de los procesos de aseguramiento de la calidad, la consolidación de la identidad institucional y la relación que mantiene con la comunidad y sus grupos de interés. | G3: 4 | H3: =+AVERAGE(G3) -> 4 | I3: =AVERAGE(G3:G6) -> 4 | J3: =IF(I3>=4.5,"Se cumple plenamente",IF(I3>=4,"Se cumple en alto grado",IF(I3>=3.5,"Se cumple aceptablemente",IF(I3>=2.5,"Se cumple insatisfactoriamente",IF(I3>=1,"No se cumple",""))))) -> Se cumple en alto grado | K3: Falta aprobación para socializar | T3: Gradación no numérica | U3: Gradación numérica | V3: Grado de cumplimiento
D4: Relevancia académica y pertinencia social del programa académico. | E4: 0.46153846 | F4: Análisis sobre las tendencias, necesidades y líneas de desarrollo de la disciplina o profesión, en el contexto regional, nacional e internacional. | G4: 4 | H4: =AVERAGE(G4:G6) -> 4 | K4: PEP
F5: Estudio de la pertinencia social del programa desde la perspectiva de la comunidad académica y de sus grupos de interés con el fin de identificar necesidades y requerimientos del entorno local, regional o nacional en términos productivos y de competitividad, tecnológicos, culturales, científicos y de talento humano. | G5: 5 | K5: PEP | T5: 1 | U5: 1 | V5: No se cumple
F6: Evidencia de las transformaciones sociales pertinentes para el contexto y el territorio en el que se ofrece el programa académico, y del entorno tanto nacional como internacional. | G6: 3 | K6: PEP/convenio doble titulación | T6: 2.5 | U6: 2 | V6: Se cumple insatisfactoriamente
A7: 2 | B7: FACTOR 2. ESTUDIANTES | C7: 0.12415655 | D7: Participación en actividades de formación integral | E7: 0.33139535 | F7: Apreciación de los estudiantes en relación con su participación en las actividades de investigación, desarrollo tecnológico, creación artística, culturales, deportivas y de extensión, que contribuyen a su formación integral, junto con las acciones emprendidas como resultado de dichas apreciaciones. | G7: 4 | H7: =AVERAGE(G7:G10) -> 4 | I7: =+AVERAGE(G7:G16) -> 4.6 | J7: =IF(I3>=4.5,"Se cumple plenamente",IF(I3>=4,"Se cumple en alto grado",IF(I3>=3.5,"Se cumple aceptablemente",IF(I3>=2.5,"Se cumple insatisfactoriamente",IF(I3>=1,"No se cumple",""))))) -> Se cumple en alto grado | K7: Encuesta | L7: Docentes 12 | M7: Egresados 1 | N7: Egresados 2 | O7: Estudiantes 3 | P7: Estudiantes 8 | Q7: Estudiantes 9 | T7: 3.5 | U7: 3 | V7: Se cumple aceptablemente
F8: Resultados del análisis de la participación y principales logros de los estudiantes en actividades de investigación, desarrollo tecnológico, innovación, creación artística, culturales y deportivas. | G8: 4 | K8: Encuesta | L8: Estudiantes 9 | T8: 4 | U8: 4 | V8: Se cumple en alto grado
F9: Resultados del análisis de la participación y principales logros de los estudiantes en proyectos de desarrollo empresarial, relacionamiento nacional e internacional. | G9: 4 | K9: Encuesta | L9: Estudiantes 9 | T9: 4.5 | U9: 5 | V9: Se cumple plenamente
F10: Resultados del análisis de la participación y principales logros de los estudiantes en otras acciones de formación complementaria, que promuevan la comprensión de la realidad social, la empatía, la ética, habilidades blandas, así como el relacionamiento con otras culturas y lenguas, de acuerdo con el nivel de formación y la modalidad del programa. | G10: 4 | K10: Encuesta | L10: Estudiantes 9
D11: Orientación y seguimiento a estudiantes | E11: 0.18023256 | F11: Evidencia de los efectos en la formación de los estudiantes, a partir de los procesos de orientación y seguimiento de los estudiantes, teniendo como referencia sus características de ingreso. | G11: 5 | H11: =+AVERAGE(G3) -> 4 | K11: Listas se asistencia a reuniones e inducciones, investigación
D12: Capacidad de trabajo autónomo | E12: 0.19186047 | F12: Evidencia de los resultados de las estrategias de seguimiento y evaluación de los resultados de aprendizaje en el desarrollo de capacidades para el del trabajo autónomo del estudiante. | G12: 5 | H12: =+AVERAGE(G3) -> 4 | K12: Listas se asistencia a reuniones e inducciones, investigación | L12: Egresados 2 | M12: Estudiantes 3
D13: Reglamento estudiantil y política académica | E13: 0.13372093 | F13: Apreciación de estudiantes y profesores del programa sobre la pertinencia, vigencia y aplicación del reglamento estudiantil y las políticas académicas y, sobre las estrategias de divulgación de dicha reglamentación, junto con las acciones emprendidas como resultado de dichas apreciaciones. | G13: 5 | H13: =+AVERAGE(G13:G14) -> 5 | L13: Docentes 1 | M13: Docentes 9 | N13: Egresados 2 | O13: Estudiantes 4
F14: Evidencia de los mecanismos para la aplicación, actualización y divulgación del reglamento estudiantil. | G14: 5 | L14: Docentes 1 | M14: Estudiantes 4
D15: Estímulos y apoyos para estudiantes | E15: 0.1627907 | F15: Evidencia de los beneficios generados por el otorgamiento de estímulos académicos y apoyos socioeconómicos a los estudiantes. | G15: 5 | H15: =+AVERAGE(G15:G16) -> 5 | L15: Docentes 2 | M15: Estudiantes 3
F16: Apreciación de los estudiantes del programa frente a la aplicación de los estímulos académicos y apoyos socioeconómicos, y el cumplimiento institucional de estas medidas, junto con las acciones emprendidas como resultado de dichas apreciaciones. | G16: 5 | L16: Estudiantes 3 | M16: Estudiantes 5
A17: 3 | B17: FACTOR 3. PROFESORES | C17: 0.11673414 | D17: Selección, vinculación y permanencia | E17: 0.1712963 | F17: Evidencia de la aplicación de los procesos de selección, vinculación y permanencia de los profesores, en coherencia con el nivel de formación, modalidad del programa académico y lugar de desarrollo. | G17: 5 | H17: =+AVERAGE(G17:G18) -> 5 | I17: =+AVERAGE(G17:G34) -> 4.6666667 | J17: =IF(I3>=4.5,"Se cumple plenamente",IF(I3>=4,"Se cumple en alto grado",IF(I3>=3.5,"Se cumple aceptablemente",IF(I3>=2.5,"Se cumple insatisfactoriamente",IF(I3>=1,"No se cumple",""))))) -> Se cumple en alto grado
F18: Apreciación de los profesores sobre la aplicación, pertinencia y vigencia de las políticas, normas y criterios académicos establecidos por la institución para su selección, vinculación y permanencia, junto con las acciones emprendidas como resultado de dichas apreciaciones. | G18: 5
D19: Estatuto profesoral | E19: 0.13734568 | F19: Evidencia que demuestren los resultados de la aplicación del estatuto profesoral, o el que haga sus veces, sobre la trayectoria profesoral, la inclusión, el reconocimiento de méritos y el ascenso en el escalafón, de acuerdo con el nivel de formación y la modalidad del programa. | G19: 5 | H19: =+AVERAGE(G19:G21) -> 5 | L19: Docentes 4 | M19: Docentes 5
F20: Resultados en el mejoramiento de la calidad del programa, a partir de la aplicación de un estatuto que promueve la trayectoria profesoral, la inclusión, el reconocimiento de los méritos y el ascenso en el escalafón. | G20: 5 | L20: Docentes 3 | M20: Docentes 4
F21: Apreciación de los profesores sobre la aplicación y pertinencia del estatuto profesoral y de las políticas que establecen distinciones, estímulos que promueven la trayectoria profesoral, junto con las acciones emprendidas como resultado de dichas apreciaciones. | G21: 5 | L21: Docentes 3 | M21: Docentes 5 | N21: Docentes 6
D22: Número, dedicación, nivel de formación y experiencia | E22: 0.15740741 | F22: Evidencia de la coherencia entre el número, dedicación, nivel de formación y experiencia de los profesores de tiempo completo, con el número de estudiantes, nivel de formación y modalidad del programa académico. | G22: 5 | H22: =+AVERAGE(G22:G24) -> 5
F23: Evidencia de la existencia de un núcleo básico de profesores de tiempo completo, preferiblemente con contratación a término indefinido, y su relación con la formación de la comunidad académica del programa y el cumplimiento con alta calidad de las funciones esenciales del programa. | G23: 5
F24: Evidencia de la vinculación de una planta profesoral pertinente con el área disciplinar del programa con título de maestría y/o doctorado con experiencia o formación pedagógica, investigativa y profesional certificada y experiencia en investigación, que garantice el logro de los resultados de aprendizaje de los estudiantes y el cumplimiento de las funciones asignadas en condiciones de calidad, atendiendo a estándares internacionales, en coherencia con el nivel de formación y modalidad del programa. | G24: 5
D25: Desarrollo profesoral | E25: 0.15277778 | F25: Análisis de los resultados de la aplicación de políticas y estrategias institucionales en materia de desarrollo integral del profesorado, que incluya la capacitación y la actualización en los aspectos académicos, profesionales y pedagógicos relacionados con la naturaleza, nivel de formación y modalidad del programa. | G25: 5 | H25: =+AVERAGE(G25:G27) -> 4.3333333 | L25: Docentes 4 | M25: Docentes 5
F26: Evidencia de cómo el desarrollo profesoral atiende a la diversidad de los estudiantes, a las modalidades de la docencia y a los requerimientos de internacionalización y de inter y multiculturalidad de profesores y estudiantes. | G26: 4 | K26: Movilidad docente entrante y de estudiantes | L26: Docentes 4
F27: Apreciación de directivos y profesores del programa sobre los resultados que han tenido las acciones orientadas al desarrollo integral de los profesores, en el mejoramiento de las competencias pedagógicas, científicas y sociales para el sostenimiento de las funciones misionales, junto con las acciones emprendidas como resultado de dichas apreciaciones. | G27: 4 | L27: Docentes 3 | M27: Docentes 5
D28: Estímulos a la trayectoria profesoral | E28: 0.10339506 | F28: Evidencia de los efectos generados en el desempeño de las labores de docencia, investigación y extensión con el otorgamiento de estímulos a los profesores. | G28: 5 | H28: =+AVERAGE(G28:G29) -> 5 | K28: Reglamento, excelencia académica | L28: Docentes 4 | M28: Docentes 5
F29: Apreciación de directivos y profesores del programa, sobre el efecto que ha tenido el régimen de estímulos al profesorado en el ejercicio cualificado de la docencia, la investigación, la innovación, la creación artística y cultural, la extensión o proyección social, en los aportes al desarrollo técnico y tecnológico y la cooperación internacional, junto con las acciones emprendidas como resultado de dichas apreciaciones. | G29: 5 | K29: CvLac | L29: Docentes 3 | M29: Docentes 5 | N29: Docentes 6 | O29: Docentes 10
D30: Producción, pertinencia, utilización e impacto de material docente | E30: 0.11728395 | F30: Evidencia de la efectividad de los criterios de evaluación del material producido por los profesores en la calidad de los aprendizajes de los estudiantes, de acuerdo con el nivel de formación y modalidad del programa académico. | G30: 3 | H30: =+AVERAGE(G30:G31) -> 3 | K30: Hay material, pero no evaluacion del material | L30: Docentes 4 | M30: Docentes 5
F31: Presentación de los resultados de evaluación de los materiales académicos producidos por los profesores para el desarrollo de las diversas actividades académicas, que soportan los ambientes de aprendizaje, de acuerdo con el nivel de formación y modalidad. | G31: 3 | K31: Hay material, pero no evaluacion del material | L31: Docentes 4
D32: Remuneración por méritos | E32: 0.094135802 | F32: La remuneración que reciben los profesores está de acuerdo con sus méritos académicos y profesionales, el aporte en el desarrollo de los componentes formativos, pedagógicos y de evaluación, la interacción y relevancia social, el nivel de formación y la modalidad del programa académico. | G32: 5 | H32: =+AVERAGE(G32) -> 5 | L32: Docentes 3 | M32: Docentes 5
D33: Evaluación de profesores | E33: 0.066358025 | F33: Apreciación de los profesores, directivos y estudiantes sobre los criterios y mecanismos para la evaluación de los profesores; su transparencia, equidad y eficacia y; su coherencia con la naturaleza de la institución, el nivel de formación y la modalidad del programa, junto con las acciones emprendidas como resultado de dichas apreciaciones. | G33: 5 | H33: =+AVERAGE(G33:G34) -> 5 | L33: Docentes 9
F34: Demostración del mejoramiento continuo del programa, a partir de las evaluaciones permanentes realizadas a los profesores, en coherencia con el nivel de formación y modalidad. | G34: 5 | L34: Docentes 4
A35: 4 | B35: FACTOR 4. EGRESADOS | C35: 0.10796221 | D35: Seguimiento de los egresados | E35: 0.54761905 | F35: Resultado de los estudios sistémicos aplicados sobre el desarrollo profesional y laboral de los egresados, el alcance de las competencias adquiridas, la correspondencia entre el desempeño de los egresados y el perfil de egreso o resultados de aprendizaje del programa. | G35: 5 | H35: =+AVERAGE(G35:G36) -> 5 | I35: =+AVERAGE(G35:G38) -> 4.75 | J35: =IF(I3>=4.5,"Se cumple plenamente",IF(I3>=4,"Se cumple en alto grado",IF(I3>=3.5,"Se cumple aceptablemente",IF(I3>=2.5,"Se cumple insatisfactoriamente",IF(I3>=1,"No se cumple",""))))) -> Se cumple en alto grado | L35: Egresados 2
F36: Apreciación de los egresados en relación con el perfil de formación, las competencias adquiridas y las posibilidades que les ha ofrecido su formación para su desarrollo profesional y laboral, junto con las acciones emprendidas como resultado de dichas apreciaciones. | G36: 5 | L36: Docentes 8 | M36: Docentes 9 | N36: Egresados 1 | O36: Egresados 2
D37: Impacto de los egresados en el medio social y académico | E37: 0.45238095 | F37: Evidencia del impacto de los egresados en el medio social y académico, científico y cultural, como un mecanismo para establecer los aportes del programa a la solución de problemas de la sociedad y/o la creación e innovación de conocimiento. | G37: 5 | H37: =+AVERAGE(G37:G38) -> 4.5 | L37: Egresados 2
F38: Apreciación de empleadores sobre el desempeño destacado de los egresados y su aporte en la solución de los problemas académicos, ambientales, tecnológicos, sociales y culturales, junto con las acciones emprendidas como resultado de dichas apreciaciones. | G38: 4 | L38: Docentes 8 | M38: Docentes 9
A39: 5 | B39: FACTOR 5. ASPECTOS ACADÉMICOS Y RESULTADOS DE APRENDIZAJE | C39: 0.067476383 | D39: Integralidad de los aspectos curriculares | E39: 0.17160494 | F39: Resultados de la aplicación de ejercicios continuos de evaluación de la integralidad del currículo que conduzcan a la realización de ajustes y mejoras que impactan a la formación en valores, actitudes, aptitudes, conocimientos, métodos, capacidades y habilidades, de acuerdo con el estado del arte y con el ejercicio de la disciplina, profesión, ocupación u oficio, y que busca la formación integral del estudiante en coherencia con la misión institucional y los objetivos propios del programa académico. | G39: 5 | H39: =+AVERAGE(G39:G40) -> 5 | I39: =+AVERAGE(G39:G57) -> 4.3333333 | J39: =IF(I3>=4.5,"Se cumple plenamente",IF(I3>=4,"Se cumple en alto grado",IF(I3>=3.5,"Se cumple aceptablemente",IF(I3>=2.5,"Se cumple insatisfactoriamente",IF(I3>=1,"No se cumple",""))))) -> Se cumple en alto grado | K39: Actualizacion de syllabus
F40: Evaluación de las estrategias y acciones del programa para el mejoramiento de las competencias definidas por el programa. | G40: 5 | K40: Consejo curricular, reuniones de profesores
D41: Flexibilidad de los aspectos curriculares | E41: 0.14691358 | F41: Evidencia de procesos de flexibilización como, doble titulación; articulación pregrado-posgrado; reconocimiento de créditos, homologación y oferta de cursos electivos en distintas modalidades y lugares de desarrollo entre otros, que permiten al estudiante interactuar con otros programas a nivel institucional, nacional e internacional. | G41: 4 | H41: =+AVERAGE(G41:G42) -> 4 | K41: Reglamento postgrados, doble titulación | L41: Docentes 10 | M41: Egresados 2
F42: Apreciación de estudiantes, profesores y egresados sobre las rutas de formación alternativas y adoptadas por los estudiantes a partir de sus necesidades e intereses, derivadas de las estrategias de flexibilidad curricular definidas por la institución, junto con las acciones emprendidas como resultado de dichas apreciaciones. | G42: 4 | K42: movilidad curricular, pasantias | L42: Docentes 2 | M42: Docentes 7 | N42: Docentes 10 | O42: Egresados 1 | P42: Egresados 2 | Q42: Estudiantes 6 | R42: Estudiantes 7
D43: Interdisciplinariedad | E43: 0.12839506 | F43: Evidencia de la implementación de las estrategias que promueven y estimulan la interdisciplinariedad curricular del programa, y el resultado de su aplicación en las diferentes rutas formativas seguidas por los estudiantes. | G43: 5 | H43: =+AVERAGE(G43:G44) -> 5 | K43: movilidad curricular | L43: Egresados 2 | M43: Estudiantes 3
F44: Apreciación de los estudiantes y profesores frente a los mecanismos y criterios dispuestos por la institución para la interdisciplinariedad curricular del programa, los resultados de su análisis y la evidencia de los logros en el mejoramiento en la calidad del programa. | G44: 5 | K44: Encuesta | L44: Docentes 2 | M44: Docentes 8 | N44: Egresados 2 | O44: Estudiantes 6 | P44: Estudiantes 7
D45: Estrategias pedagógicas | E45: 0.11358025 | F45: Apreciación de profesores y estudiantes sobre la coherencia de las estrategias pedagógicas utilizadas que facilitan el logro de los resultados de aprendizaje esperados, incluyendo los escenarios de práctica para los programas que lo requieren, valorando la calidad, la pertinencia, el acompañamiento y el cumplimiento de la normatividad específica para su desarrollo, junto con las acciones emprendidas como resultado de dichas apreciaciones. | G45: 3 | H45: =+AVERAGE(G45:G47) -> 3.5 | K45: Transición a RA | L45: Egresados 1 | M45: Egresados 2
F46: Evidencia de la evaluación y el mejoramiento de las estrategias y prácticas pedagógicas, a partir de los aportes de la investigación pedagógica y de los procesos de actualización de los profesores. | G46: 4 | K46: Capacitaciones / encuestas | L46: Egresados 2 | M46: Estudiantes 3
F47: En el caso de programas académicos del área de la salud, presentar análisis de la incidencia de las actividades desarrolladas en el marco de los convenios de docencia servicio con los distintos escenarios de práctica (con énfasis en el escenario principal, cuando aplique) en los procesos de formación. Los análisis se deben realizar entre las partes que participan en el convenio. | G47: - | K47: No aplica
D48: Sistema de evaluación de estudiantes | E48: 0.075308642 | F48: Apreciación de profesores y estudiantes sobre los sistemas de evaluación de los resultados de aprendizaje que desarrolla o implementa el programa, junto con las acciones emprendidas como resultado de dichas apreciaciones. | G48: 3 | H48: =+AVERAGE(G48:G50) -> 3.6666667 | K48: Transición a RA | L48: Docentes 9
F49: Evidencia de los resultados obtenidos a partir de la implementación de los sistemas de evaluación de estudiantes basado en políticas y normas claras, universales y transparentes. | G49: 5
F50: Evidencia de sistemas de evaluación que integran la innovación para generar transformaciones profundas en el aprendizaje, y que acogen dinámicas en referencia a cambios en el conocimiento. | G50: 3 | K50: alcance de la evaluación a estudiantes
D51: Resultados de aprendizaje | E51: 0.12839506 | F51: Evidencia de la aplicación de una política institucional que establezca parámetros para la formulación, evaluación y mejora continua de los resultados de aprendizaje establecidos en el programa, en alineación con el perfil de formación y acorde con el nivel y la modalidad de formación. | G51: 5 | H51: =+AVERAGE(G51:G52) -> 4
F52: Evidencia del proceso de mejoramiento continuo relacionado con la evaluación entre los resultados de aprendizaje esperados y los alcanzados por los estudiantes, el sistema de evaluación de estudiantes y las acciones de ajuste de los aspectos curriculares y las metodologías de enseñanza - aprendizaje derivadas de dicha evaluación. | G52: 3 | K52: Transición a RA
D53: Competencias | E53: 0.10987654 | F53: Evidencia del resultado de la aplicación de estrategias para el desarrollo de las competencias previstas acordes con el perfil de formación del programa. | G53: 5 | H53: =+AVERAGE(G53) -> 5 | K53: Syllabus / estructura de la maestría | L53: Egresados 2 | M53: Estudiantes 3
D54: Evaluación y autorregulación del programa académico | E54: 0.067901235 | F54: Evidencia del cumplimiento de planes de mejoramiento y de innovación producto del proceso de autoevaluación del programa. | G54: 5 | H54: =+AVERAGE(G54:G55) -> 4.5
F55: Apreciación de los profesores y estudiantes sobre la calidad y pertinencia del proceso de evaluación y autorregulación del programa, junto con las acciones emprendidas como resultado de dichas apreciaciones. | G55: 4 | L55: Docentes 9
D56: Vinculación e interacción social | E56: 0.058024691 | F56: Evidencia de la participación de los profesores y estudiantes en la proyección social del programa. | G56: 5 | H56: =+AVERAGE(G56:G57) -> 5 | K56: Investigación, estensión, pasantías, trabajos de grado
F57: Evidencia del efecto de las estrategias y acciones de proyección social como un mecanismo para establecer los aportes del programa a la solución de problemas de la sociedad y a las mejoras de los aspectos curriculares. | G57: 5 | K57: Investigación, estensión, pasantías, trabajos de grado, publicaciones
A58: 6 | B58: FACTOR 6. PERMANENCIA Y GRADUACIÓN | C58: 0.072874494 | D58: Políticas, estrategias y estructura para la permanencia y la graduación | E58: 0.26111111 | F58: Análisis del efecto de las políticas, estrategias y acciones orientadas al mejoramiento de la permanencia y la graduación en el programa, que incluyan el comportamiento en los últimos seis años o en la vigencia de la acreditación si se trata de una renovación, de la tasa de deserción interanual, tasa de deserción por cohorte y la tasa de graduación acumulada del programa. | G58: 5 | H58: =+AVERAGE(G58) -> 5 | I58: =+AVERAGE(G58:G64) -> 5 | J58: =IF(I3>=4.5,"Se cumple plenamente",IF(I3>=4,"Se cumple en alto grado",IF(I3>=3.5,"Se cumple aceptablemente",IF(I3>=2.5,"Se cumple insatisfactoriamente",IF(I3>=1,"No se cumple",""))))) -> Se cumple en alto grado | K58: ruta investigación
D59: Caracterización de estudiantes y sistema de alertas tempranas | E59: 0.27777778 | F59: Evidencia de la existencia e implementación de un sistema de alertas tempranas que permita reconocer las particularidades de los estudiantes según su contexto sociocultural y la puesta en marcha de acciones que faciliten su proceso formativo, de acuerdo, al menos, con las normas nacionales vigentes en materia de inclusión y diversidad. | G59: 5 | H59: =+AVERAGE(G59:G61) -> 5 | K59: informes académicos semestrales
F60: Apreciación de estudiantes y profesores sobre la contribución de las estrategias del sistema de alertas tempranas en su permanencia y graduación, junto con las acciones emprendidas como resultado de dichas apreciaciones. | G60: 5 | K60: informes académicos semestrales | L60: Egresados 1 | M60: Estudiantes 5
F61: Presentación del análisis de los resultados derivados del sistema de alertas tempranas y su impacto en el currículo, para mejorar el desempeño académico de los estudiantes, su permanencia y graduación. | G61: 5 | K61: Cuadro de tasa de graduacióin
D62: Ajustes a los aspectos curriculares | E62: 0.21111111 | F62: Evidencia de la evaluación y el mejoramiento de los aspectos curriculares derivados de los análisis del desempeño académico de los estudiantes, la permanencia y la graduación. | G62: 5 | H62: =+AVERAGE(G62) -> 5 | K62: Inclusión de énfasis y nuevo plan de estudios | L62: Egresados 2
D63: Mecanismos de selección | E63: 0.25 | F63: Evidencia y análisis de la evolución de la matrícula total de estudiantes del programa y de la relación entre aspirantes inscritos, admitidos y matriculados en cada periodo, a fin de establecer la tasa de selectividad y/o absorción del programa. | G63: 5 | H63: =+AVERAGE(G63:G64) -> 5 | K63: Cuadro maestro
F64: Análisis de la correlación entre los mecanismos de selección, de desempeño académico, permanencia y graduación que resulte en ajustes a los procesos de selección del programa. | G64: 5 | K64: proceso de selección
A65: 7 | B65: FACTOR 7. INTERACCIÓN CON EL ENTORNO NACIONAL E INTERNACIONAL | C65: 0.10593792 | D65: Inserción del programa en contextos académicos nacionales e internacionales | E65: 0.34782609 | F65: Evidencia del efecto de la aplicación de políticas y estrategias de cooperación con comunidades, nacionales e internacionales, en el desarrollo de labores formativas, académicas, docentes, científicas, culturales, deportivas y de extensión, así como en aspectos curriculares y en la revisión de tendencias y referentes nacionales e internacionales que contribuyan al mejoramiento continuo del programa. | G65: 4 | H65: =+AVERAGE(G65) -> 4 | I65: =+AVERAGE(G65:G68) -> 4.5 | J65: =IF(I3>=4.5,"Se cumple plenamente",IF(I3>=4,"Se cumple en alto grado",IF(I3>=3.5,"Se cumple aceptablemente",IF(I3>=2.5,"Se cumple insatisfactoriamente",IF(I3>=1,"No se cumple",""))))) -> Se cumple en alto grado | K65: Urelinter | L65: Docentes 1 | M65: Egresados 3 | N65: Estudiantes 3
D66: Relaciones externas de profesores y estudiantes | E66: 0.4057971 | F66: Evidencia y análisis de los resultados de la cooperación académica y científica del programa, mediante convenios, proyectos conjuntos, intercambios de profesores, estudiantes y la participación en redes científicas, culturales y de extensión. | G66: 4 | L66: Docentes 10 | M66: Egresados 3 | N66: Estudiantes 3
F67: Apreciación de profesores, estudiantes y egresados sobre los resultados de la cooperación académica y científica derivados de la aplicación de políticas y estrategias que favorezcan la interacción de profesores y estudiantes con sus homólogos, a nivel nacional e internacional, junto con las acciones emprendidas como resultado de dichas apreciaciones. | G67: 5 | L67: Docentes 7 | M67: Docentes 8 | N67: Docentes 9 | O67: Docentes 10 | P67: Egresados 1 | Q67: Egresados 2 | R67: Egresados 3 | S67: Estudiantes 3
D68: Habilidades comunicativas en una segunda lengua | E68: 0.24637681 | F68: Evidencia de la incidencia de las estrategias empleadas para el desarrollo de las competencias comunicativas en una segunda lengua y las interacciones de profesores y estudiantes con otras comunidades no hispanohablantes de acuerdo con el nivel de formación y modalidad del programa. | G68: 5 | H68: =+AVERAGE(G68) -> 5 | K68: ILUD, publicaciones | L68: Docentes 10
A69: 8 | B69: FACTOR 8. APORTES DE LA INVESTIGACIÓN, LA INNOVACIÓN, EL DESARROLLO TECNOLÓGICO Y LA CREACIÓN, ASOCIADOS AL PROGRAMA ACADÉMICO | C69: 0.047908232 | D69: Formación para la investigación, desarrollo tecnológico, la innovación y la creación | E69: 0.53333333 | F69: Evidencia de las estrategias implementadas para el desarrollo de las competencias investigativas, de innovación o creación artística y cultural de los estudiantes, en coherencia con la naturaleza, nivel de formación y la modalidad de oferta del programa. | G69: 5 | H69: =+AVERAGE(G66:G67) -> 4.5 | I69: =+AVERAGE(G69:G72) -> 5 | J69: =IF(I3>=4.5,"Se cumple plenamente",IF(I3>=4,"Se cumple en alto grado",IF(I3>=3.5,"Se cumple aceptablemente",IF(I3>=2.5,"Se cumple insatisfactoriamente",IF(I3>=1,"No se cumple",""))))) -> Se cumple en alto grado | K69: Seminario de investigación, tutorías, asignaturas de tesis | L69: Docentes 4 | M69: Egresados 3 | N69: Estudiantes 3 | O69: Estudiantes 8
F70: Apreciación de los estudiantes acerca de la formación para la investigación, el desarrollo de un pensamiento crítico, creativo e innovador, así como el desarrollo tecnológico, la innovación y la creación promovida en el programa, junto con las acciones emprendidas como resultado de dichas apreciaciones. | G70: 5 | L70: Docentes 8 | M70: Docentes 9 | N70: Egresados 1 | O70: Egresados 3 | P70: Estudiantes 3 | Q70: Estudiantes 8 | R70: Estudiantes 9
D71: Compromiso con la investigación, desarrollo tecnológico, la innovación y la creación | E71: 0.46666667 | F71: Evidencia de la existencia de un reglamento de propiedad intelectual, de grupos de investigación categorizados y de profesores investigadores reconocidos en las convocatorias de medición de Minciencias, acorde con el Proyecto Educativo del Programa, el nivel de formación y la modalidad del programa. | G71: 5 | H71: =+AVERAGE(G68:G69) -> 5 | K71: OTRI | L71: Docentes 4
F72: Evidencia de resultados de investigación, desarrollo tecnológico, innovación o creación de los profesores del programa, que contribuyan al fortalecimiento de los aspectos curriculares, la formación de los estudiantes y a la generación de nuevo conocimiento o a la solución de problemas de la sociedad, en coherencia con el Proyecto Educativo del Programa, el nivel de formación y la modalidad del programa. | G72: 5 | K72: Grupos investigación | L72: Docentes 5 | M72: Estudiantes 3 | N72: Estudiantes 8 | O72: Estudiantes 9
A73: 9 | B73: FACTOR 9. BIENESTAR DE LA COMUNIDAD ACADÉMICA DEL PROGRAMA | C73: 0.064102564 | D73: Programas y servicios | E73: 0.54761905 | F73: Análisis sistemáticos de la participación de estudiantes y profesores en las actividades de bienestar en cada uno de los escenarios de práctica. | G73: 5 | H73: =+AVERAGE(G70:G71) -> 5 | I73: =+AVERAGE(G73:G76) -> 4.75 | J73: =IF(I3>=4.5,"Se cumple plenamente",IF(I3>=4,"Se cumple en alto grado",IF(I3>=3.5,"Se cumple aceptablemente",IF(I3>=2.5,"Se cumple insatisfactoriamente",IF(I3>=1,"No se cumple",""))))) -> Se cumple en alto grado
F74: Apreciación de los estudiantes, profesores y personal administrativo sobre la incidencia de la implementación de políticas, programas y servicios de bienestar, en coherencia con las condiciones y necesidades de la comunidad en cada uno de los lugares y escenarios de práctica donde desarrolla sus labores, en correspondencia con el nivel de formación y la modalidad del programa, junto con las acciones emprendidas como resultado de dichas apreciaciones. | G74: 5 | L74: Estudiantes 5
D75: Participación y seguimiento | E75: 0.45238095 | F75: Análisis sistemáticos de la participación de la comunidad del programa en los planes y las actividades de bienestar, de acuerdo con las particularidades de la población estudiantil, académica y administrativa. | G75: 5 | H75: =+AVERAGE(G72:G73) -> 5
F76: Evaluación de la calidad y pertinencia de la infraestructura, espacios y servicios de bienestar por parte de la comunidad del programa, junto con las acciones emprendidas como resultado de dicha evaluación. | G76: 4
A77: 10 | B77: FACTOR 10. MEDIOS EDUCATIVOS Y AMBIENTES DE APRENDIZAJE | C77: 0.068825911 | D77: Estrategias y recursos de apoyo a profesores | E77: 0.39855072 | F77: Demostración de los resultados y la incidencia de la implementación de las estrategias y recursos de apoyo (pedagógico-didáctico) en los contextos de actuación de los profesores para el mejoramiento de sus prácticas de enseñanza-aprendizaje teniendo en cuenta la diversidad y la inclusión. | G77: 5 | H77: =+AVERAGE(G77:G79) -> 5 | I77: =+AVERAGE(G77:G84) -> 5 | J77: =IF(I3>=4.5,"Se cumple plenamente",IF(I3>=4,"Se cumple en alto grado",IF(I3>=3.5,"Se cumple aceptablemente",IF(I3>=2.5,"Se cumple insatisfactoriamente",IF(I3>=1,"No se cumple",""))))) -> Se cumple en alto grado | K77: Moodle, Classroom, ambientes virtuales
F78: Apreciación de los profesores y los estudiantes en relación con las estrategias pedagógicas, tecnológicas y de acompañamiento dispuestas por el programa para el desarrollo de las habilidades comunicativas y de interacción de los profesores con los estudiantes, junto con las acciones emprendidas como resultado de dichas apreciaciones. | G78: 5 | K78: PlanesTIC | L78: Docentes 11
F79: En el caso de programas académicos del área de la salud, análisis de las acciones que realizan conjuntamente el programa con los escenarios de práctica, en sus procesos de certificación, acreditación, reconocimiento como hospital universitario y acciones de mejora. | K79: No aplica
D80: Estrategias y recursos de apoyo a estudiantes | E80: 0.35507246 | F80: Evidencia de la disponibilidad y capacidad de talleres, laboratorios, equipos, medios audiovisuales, sitios de práctica, estaciones y granjas experimentales, escenarios de simulación virtual, entre otros, para el adecuado desarrollo de la actividad docente, investigativa y de extensión, según requerimientos del programa. | G80: 5 | H80: =+AVERAGE(G80:G82) -> 5 | K80: Laboratorios | L80: Estudiantes 3
F81: Apreciación de los estudiantes sobre la utilidad y pertinencia de las estrategias y recursos de apoyo brindados por la institución para el desarrollo de su proceso formativo en diferentes contextos, junto con las acciones emprendidas como resultado de dichas apreciaciones. | G81: 5 | L81: Egresados 1 | M81: Egresados 3 | N81: Estudiantes 3
F82: En el caso de los programas académicos del área de la salud, evidencia de la disponibilidad de laboratorios especializados y/o de simulación en los distintos lugares de desarrollo y los escenarios de práctica, y análisis del nivel de uso por parte de profesores y estudiantes. | K82: No aplica
D83: Recursos bibliográficos y de información | E83: 0.24637681 | F83: Análisis de la correspondencia entre la inversión en recursos bibliográficos y de información, su utilización por parte de la comunidad del programa, demostrando la suficiencia y pertinencia para el desarrollo de actividades de docencia, investigación y extensión, de acuerdo con el nivel de formación y modalidad del programa. | G83: 5 | H83: =+AVERAGE(G80:G81) -> 5 | K83: bases de datos
F84: Apreciación de estudiantes y profesores acerca de la pertinencia, actualización y suficiencia del material bibliográfico con que cuenta el programa, para apoyar el desarrollo de las distintas actividades académicas, de acuerdo con su nivel de formación y modalidad, junto con las acciones emprendidas como resultado de dichas apreciaciones. | G84: 5 | K84: bases de datos | L84: Docentes 11
A85: 11 | B85: FACTOR 11. ORGANIZACIÓN, ADMINISTRACIÓN Y FINANCIACIÓN DEL PROGRAMA ACADÉMICO | C85: 0.066801619 | D85: Organización y administración | E85: 0.23015873 | F85: Evidencia de la participación de representantes de la comunidad académica, a través de estructuras organizacionales definidas por la institución, y de su contribución, en el desarrollo y mejoramiento del programa. | G85: 5 | H85: =+AVERAGE(G82:G83) -> 5 | I85: =+AVERAGE(G85:G97) -> 5 | J85: =IF(I3>=4.5,"Se cumple plenamente",IF(I3>=4,"Se cumple en alto grado",IF(I3>=3.5,"Se cumple aceptablemente",IF(I3>=2.5,"Se cumple insatisfactoriamente",IF(I3>=1,"No se cumple",""))))) -> Se cumple en alto grado | K85: Estatuto Academico
F86: Apreciación de estudiantes, profesores y egresados sobre su participación en cuerpos colegiados, y en decisiones orientadas al mejoramiento del programa, junto con las acciones emprendidas como resultado de dichas apreciaciones. | G86: 5 | K86: Estatuto Academico | L86: Docentes 12
D87: Dirección y gestión | E87: 0.21164021 | F87: Evidencia de los mecanismos existentes para la dirección y gestión del programa que contribuyen al mejoramiento de las dinámicas administrativas y académicas y al relacionamiento con los grupos de interés. | G87: 5 | H87: =+AVERAGE(G84:G85) -> 5 | K87: Estatuto Academico
F88: Apreciación de profesores y estudiantes sobre la eficiencia, eficacia y orientación de los procesos administrativos hacia el desarrollo de las labores formativas, académicas, docentes, científicas, culturales y de extensión, junto con las acciones emprendidas como resultado de dichas apreciaciones. | G88: 5 | K88: Encuestas | L88: Egresados 1
D89: Sistemas de comunicación e información | E89: 0.13227513 | F89: Presentación de estudios de satisfacción de profesores y estudiantes del programa acerca de la suficiencia y calidad de los recursos y sistemas de comunicación e información. | G89: 5 | H89: 5 | K89: Encuestas
F90: Presentación de estadísticas y análisis del uso de los sistemas de comunicación e información, y de la implementación de estrategias que garanticen la conectividad a los miembros de la comunidad académica del programa. | G90: 5 | K90: Sistemas información
F91: Evidencia de la aplicación de mecanismos de gestión documental, organización, actualización y seguridad de los registros y archivos académicos de estudiantes, profesores, personal directivo y administrativo. | G91: 5 | K91: Sistemas información
D92: Estudiantes y capacidad institucional | E92: 0.11904762 | F92: Presentación de estadísticas y análisis de las capacidades institucionales en materia de recursos humanos (planta docente y personal administrativo), técnicos, tecnológicos y financieros, que favorecen la permanencia, el desarrollo académico y la graduación de los estudiantes. | G92: 5 | H92: =+AVERAGE(G89:G90) -> 5
F93: cumplimiento del Proyecto Educativo del Programa, junto con las acciones emprendidas como resultado de dichas apreciaciones. | G93: 5 | K93: pep y registro calificado
D94: Financiación del programa académico | E94: 0.12962963 | F94: Demostración de la consistencia entre la asignación y distribución presupuestal del programa, y el desarrollo de las actividades de docencia, investigación, creación artística y cultural, deportiva, proyección social, bienestar institucional e internacionalización, y la implementación de los planes de mejoramiento. | G94: 5 | H94: =+AVERAGE(G91:G92) -> 5 | K94: Alison
F95: Presentación de la proyección y la ejecución del presupuesto de inversión y de funcionamiento del programa y los mecanismos de seguimiento y control. | G95: 5 | K95: Decanatura
D96: Aseguramiento de la alta calidad y mejora continua | E96: 0.17724868 | F96: Evidencia de la consolidación de un Sistema Interno de Aseguramiento de la Calidad que permita verificar, mediante unos procesos periódicos y participativos de autoevaluación, la alta calidad en cada uno de los factores y características del modelo del Consejo Nacional de Acreditación, en el programa. | G96: 5 | H96: =+AVERAGE(G93:G94) -> 5 | K96: Autoevación y estructura interna
F97: En el caso de los programas académicos del área de la salud, evidencia de los procesos de autoevaluación sobre el funcionamiento del convenio docencia servicio en cada uno de los escenarios de práctica y su incidencia en los procesos de mejoramiento. | K97: No aplica
A98: 12 | B98: FACTOR 12. RECURSOS FÍSICOS Y TECNOLÓGICOS | C98: 0.036437247 | D98: Recursos de infraestructura física y tecnológica | E98: 0.52380952 | F98: Demostración de la existencia de aulas, laboratorios, talleres, centros de simulación, plataformas tecnológicas, biblioteca y salas de estudio, para el cumplimiento de las labores formativas, académicas, docentes, científicas, culturales y de extensión, en coherencia con el nivel de formación y la modalidad de oferta del programa. | G98: 5 | H98: =+AVERAGE(G95:G96) -> 5 | I98: =+AVERAGE(G98:G101) -> 5 | J98: =IF(I3>=4.5,"Se cumple plenamente",IF(I3>=4,"Se cumple en alto grado",IF(I3>=3.5,"Se cumple aceptablemente",IF(I3>=2.5,"Se cumple insatisfactoriamente",IF(I3>=1,"No se cumple",""))))) -> Se cumple en alto grado | L98: Docentes 2
F99: Evidencia de planes y proyectos realizados o en ejecución, para la conservación, expansión, mejoras y mantenimiento de la planta física para el programa, de acuerdo con las normas técnicas respectivas y con el nivel de formación y la modalidad de oferta del programa. | G99: 5
D100: Recursos informáticos y de comunicación | E100: 0.47619048 | F100: Evidencia de la coherencia entre los recursos informáticos y de comunicación con las necesidades para el desarrollo y cumplimiento de las labores formativas, académicas, docentes, científicas, culturales del programa en el lugar de desarrollo y en los escenarios de práctica. | G100: 5 | H100: =+AVERAGE(G97:G98) -> 5 | K100: Laboratorios
F101: Apreciación de directivos, profesores y estudiantes del programa sobre la pertinencia, correspondencia y suficiencia de los recursos informáticos y de comunicación con que cuenta el programa. | G101: 5 | K101: Encuestas

Sheet Hoja1
A1: Encuesta | B1: Gráfico / Tema | C1: Factor CNA asociado | D1: Ubicación sugerida en Informe
A2: Docentes | B2: Años de experiencia | C2: Factor 3: Profesores (cualificación, experiencia) | D2: Cap. II – Resultados por Factor 3
B3: Reglamento | C3: Factor 3: Profesores (normatividad y condiciones de vinculación) | D3: Cap. II – Resultados por Factor 3
B4: Criterios (selección / evaluación) | C4: Factor 3: Profesores | D4: Cap. II – Resultados por Factor 3
B5: Sistemas de evaluación | C5: Factor 5: Procesos Académicos (estrategias de enseñanza, evaluación) | D5: Cap. II – Resultados por Factor 5
B6: Proceso de autorregulación | C6: Factor 8: Autoevaluación y Autorregulación | D6: Cap. II – Resultados por Factor 8
B7: Políticas, programas y servicios | C7: Factor 6: Bienestar Institucional | D7: Cap. II – Resultados por Factor 6
B8: Acompañamiento proporcionado | C8: Factor 6: Bienestar Institucional | D8: Cap. II – Resultados por Factor 6
B9: Procesos administrativos | C9: Factor 9: Organización, gestión y administración | D9: Cap. II – Resultados por Factor 9
B10: Recursos humanos | C10: Factor 9: Organización, gestión y administración | D10: Cap. II – Resultados por Factor 9
B11: Recursos informáticos | C11: Factor 6: Bienestar Institucional / Factor 11: Recursos Físicos y Financieros | D11: Cap. II – Resultados por Factor 6 o 11
B12: Asignaturas en inglés / Nivel de inglés | C12: Factor 7: Internacionalización | D12: Cap. II – Resultados por Factor 7
B13: Disposición docente (continuar, compromiso) | C13: Factor 10: Visibilidad Nacional e Internacional | D13: Cap. II – Resultados por Factor 10
A14: Egresados | B14: Edad | C14: Factor 4: Egresados e Impacto sobre el medio | D14: Cap. II – Resultados por Factor 4
B15: Relación trabajo | C15: Factor 4: Egresados e Impacto sobre el medio | D15: Cap. II – Resultados por Factor 4
B16: Oportunidades laborales | C16: Factor 4: Egresados e Impacto sobre el medio | D16: Cap. II – Resultados por Factor 4
B17: Competencias adquiridas | C17: Factor 4: Egresados / Factor 5: Procesos Académicos | D17: Cap. II – Resultados por Factor 4 y 5
B18: Influencia positiva del programa | C18: Factor 4: Egresados | D18: Cap. II – Resultados por Factor 4
B19: Estrategias de flexibilidad | C19: Factor 5: Procesos Académicos | D19: Cap. II – Resultados por Factor 5
B20: Representante estudiantil | C20: Factor 2: Estudiantes (participación) | D20: Cap. II – Resultados por Factor 2
A21: Estudiantes | B21: Rango de edad | C21: Factor 2: Estudiantes | D21: Cap. II – Resultados por Factor 2
B22: Criterios y mecanismos de admisión | C22: Factor 2: Estudiantes | D22: Cap. II – Resultados por Factor 2
B23: Estrategias de flexibilidad | C23: Factor 5: Procesos Académicos | D23: Cap. II – Resultados por Factor 5
B24: Estrategias pedagógicas | C24: Factor 5: Procesos Académicos | D24: Cap. II – Resultados por Factor 5
B25: Sistemas de evaluación | C25: Factor 5: Procesos Académicos | D25: Cap. II – Resultados por Factor 5
B26: Proceso de evaluación | C26: Factor 5: Procesos Académicos | D26: Cap. II – Resultados por Factor 5
B27: Intervenciones docentes | C27: Factor 5: Procesos Académicos | D27: Cap. II – Resultados por Factor 5
B28: Homólogos (comparación con otros programas) | C28: Factor 10: Visibilidad nacional e internacional | D28: Cap. II – Resultados por Factor 10
B29: Formación adecuada percibida | C29: Factor 5: Procesos Académicos | D29: Cap. II – Resultados por Factor 5
B30: Bienestar | C30: Factor 6: Bienestar Institucional | D30: Cap. II – Resultados por Factor 6

Sheet Hoja3
A2: FACTOR | B2: PONDERACIÓN | C2: GRADO DE CUMPLIMIENTO | D2: CALIFICACIÓN | F2: CALIFICACIÓN
D3: ACTUAL | F3: PROCESO ANTERIOR
A4: Factor 1. Proyecto Educativo del Programa e Identidad Institucional | B4: 0.12078273 | C4: Se cumple en alto grado | D4: 4 | E4: =B4*D4 -> 0.4831309 | F4: 4.4 | G4: =B4*F4 -> 0.53144399
A5: Factor 2. Estudiantes | B5: 0.12415655 | C5: Se cumple en alto grado | D5: 4.6 | E5: =B5*D5 -> 0.57112011 | F5: 4 | G5: =B5*F5 -> 0.49662618
A6: Factor 3. Profesores | B6: 0.11673414 | C6: Se cumple en alto grado | D6: 4.7 | E6: =B6*D6 -> 0.54865047 | F6: 4.2 | G6: =B6*F6 -> 0.4902834
A7: Factor 4. Egresados | B7: 0.10796221 | C7: Se cumple en alto grado | D7: 4.8 | E7: =B7*D7 -> 0.51821862 | F7: 4 | G7: =B7*F7 -> 0.43184885
A8: Factor 5. Aspectos Académicos y Resultados de Aprendizaje | B8: 0.067476383 | C8: Se cumple en alto grado | D8: 4.3 | E8: =B8*D8 -> 0.29014845 | F8: 4.2 | G8: =B8*F8 -> 0.28340081
A9: Factor 6. Permanencia y Graduación. | B9: 0.072874494 | C9: Se cumple en alto grado | D9: 5 | E9: =B9*D9 -> 0.36437247 | F9: 4 | G9: =B9*F9 -> 0.29149798
A10: Factor 7. Interacción con el Entorno Nacional e Internacional | B10: 0.10593792 | C10: Se cumple en alto grado | D10: 4.5 | E10: =B10*D10 -> 0.47672065 | F10: 4 | G10: =B10*F10 -> 0.42375169
A11: Factor 8. Aportes de la Investigación, la Innovación, el Desarrollo Tecnológico y la Creación, Asociados al Programa Académico | B11: 0.047908232 | C11: Se cumple en alto grado | D11: 4.5 | E11: =B11*D11 -> 0.21558704 | F11: 3.4 | G11: =B11*F11 -> 0.16288799
A12: Factor 9. Bienestar de la Comunidad Académica del Programa | B12: 0.064102564 | C12: Se cumple en alto grado | D12: 4.8 | E12: =B12*D12 -> 0.30769231 | F12: 4.1 | G12: =B12*F12 -> 0.26282051
A13: Factor 10. Medios Educativos Y Ambientes De Aprendizaje | B13: 0.068825911 | C13: Se cumple en alto grado | D13: 5 | E13: =B13*D13 -> 0.34412955 | F13: 4 | G13: =B13*F13 -> 0.27530364
A14: Factor 11. Organización, Administración y Financiación del Programa Académico | B14: 0.066801619 | C14: Se cumple en alto grado | D14: 5 | E14: =B14*D14 -> 0.3340081 | F14: 3.9 | G14: =B14*F14 -> 0.26052632
A15: Factor 12. Recursos Físicos y Tecnológicos | B15: 0.036437247 | C15: Se cumple en alto grado | D15: 5 | E15: =B15*D15 -> 0.18218623 | F15: 3.9 | G15: =B15*F15 -> 0.14210526
A16: JUICIO GLOBAL DE CALIDAD | B16: 1 | C16: Se cumple en alto grado | D16: =AVERAGE(D4:D15) -> 4.6833333 | E16: =SUM(E4:E15) -> 4.6359649 | F16: =AVERAGE(F4:F15) -> 4.0083333 | G16: =SUM(G4:G15) -> 4.0524966
