Workbook

Sheet DIRECTIVOS
A1: NOMBRE | B1: CORREO DIRECTIVO | C1: CORREO INSTITUCIONAL JEFE AREA | D1: CARGO
A2: GIOVANNY MAURICIO TARAZONA | B2: rectoria@udistrital.edu.co | C2: gtarazona@udistrital.edu.co | D2: RECTOR
A3: LUZ ESPERANZA BOHORQUEZ | B3: vicerrecacad@udistrital.edu.co | C3: lebohorqueza@udistrital.edu.co | D3: VICERECTORA ACADEMICA
A4: JOSE IGNACIO RODRIGUEZ MOLANO | B4: decano_ing@udistrital.edu.co | C4: jirodriguezm@udistrital.edu.co | D4: DECANO
A5: NELSON ENRIQUE VERA P | B5: direccion-cidc@udistrital.edu.co | C5: neverap@udistrital.edu.co | D5: VICERECTOR INVESTIGACIONES
A6: CESAR ANDREY PERDOMO CH. | C6: cperdomo@udistrital.edu.co | D6: DIRECTOR IDEXUD
A7: LEONARDO EMIRO CONTRERAS | B7: unidad-extension-ing@udistrital.edu.co | C7: lecontrerasb@udistrital.edu.co | D7: COORDINADOR UNIDAD DE EXTENSION
A8: BEITMANT CARDENAS QUINTERO | B8: unidad-extension-ing@udistrital.edu.co | C8: bgcardenasq@udistrital.edu.co | D8: COORDINADOR UEFI
A9: Ivette Catalina Martínez Martínez | B9: planeac@udistrital.edu.co | C9: icmartinezm@udistrital.edu.co | D9: JEFE PLANEACIÓN
A10: Lisseth Paola Salazar Narvaez | B10: sgral@udistrital.edu.co | C10: lpsalazarn@udistrital.edu.co | D10: SECRETARIA GENERAL
A11: ROBERTO PAVA | B11: curriculoposing@udistrital.edu.co | C11: rapavad@udistrital.edu.co | D11: COORDINADOR DE CURRICULO Y CALIDAD FACULTAD
A12: ALVARO ENRIQUE ORTIZ D | D12: COORDINADOR MCIC

Sheet DOCENTES
A1: DOCENTE | B1: CORREO | C1: TIPO | D1: OK
A2: JOSE ANTONIO VALERO MEDINA | B2: jvalero@udistrital.edu.co | C2: PLANTA | D2: OK
A3: MARCO AURELIO ALZATE MONROY | B3: malzate@udistrital.edu.co | C3: PLANTA | D3: OK
A4: OCTAVIO JOSE SALCEDO PARRA | B4: osalcedo@udistrital.edu.co | C4: PLANTA | E4: INTERN
A5: ALVARO ESPINEL ORTEGA | B5: aespinel@udistrital.edu.co | C5: PLANTA | D5: OK | E5: GESETIC
A6: ALVARO ENRIQUE ORTIZ DAVILA | B6: aeortizd@udistrital.edu.co | C6: PLANTA | D6: OK | E6: NIDE
A7: LEONARDO PLAZAS NOSSA | B7: lplazasn@udistrital.edu.co | C7: PLANTA | D7: OK | E7: GITEM++
A8: HENRY ALBERTO DIOSA | B8: hdiosa@udistrital.edu.co | C8: FACULTAD | D8: OK | E8: ARQUISOF
A9: JOSE ROBERTO CARDENAS CASTIBLANCO | B9: rcardenas@udistrital.edu.co | C9: PLANTA | D9: OK
A10: ALEJANDRO PAOLO DAZA CORREDOR | B10: apdazac@udistrital.edu.co | C10: FACULTAD
A11: CESAR ANDREY PERDOMO CHARRY | B11: cperdomo@udistrital.edu.co | C11: FACULTAD | E11: LASER
A12: ERNESTO GOMEZ VARGAS | B12: egomez@udistrital.edu.co | C12: FACULTAD | D12: OK
A13: ELVIS EDUARDO GAONA GARCIA | B13: egaona@udistrital.edu.co | C13: FACULTAD | E13: MULTI /
A14: HANS IGOR LOPEZ CHAVEZ | B14: hilopezc@udistrital.edu.co | C14: FACULTAD | D14: OK
A15: LUIS EDUARDO CASTILLO MENDEZ | B15: lecastillom@udistrital.edu.co | C15: FACULTAD | D15: OK | E15: GEFEM
A16: NELSON ENRIQUE VERA PARRA | B16: neverap@udistrital.edu.co | C16: FACULTAD
A17: LUZ ANGELA ROCHA SALAMANCA | B17: lrocha@udistrital.edu.co | C17: FACULTAD | D17: OK
A18: RUBEN JAVIER MEDINA DAZA | B18: rmedina@udistrital.edu.co | C18: FACULTAD | D18: OK
A19: JORGE ENRIQUE RODRIGUEZ RODRIGUEZ | B19: jerodriguezr@udistrital.edu.co | C19: FACULTAD | D19: OK | E19: IAFT
A20: MU?OZ QUI?ONES GERARDO ALCIDES | B20: gmunoz@udistrital.edu.co | C20: FACULTAD
A21: ROJAS GALEANO SERGIO ANDRES | B21: srojas@udistrital.edu.co | C21: FACULTAD | E21: LAMIC
A22: FIGUEROA GARCIA JUAN CARLOS | B22: jcfigueroag@udistrital.edu.co | C22: FACULTAD
A23: GAONA BARRERA ANDRES EDUARDO | B23: aegaonab@udistrital.edu.co | C23: FACULTAD | D23: ok
A24: CARDENAS CONTRERAS ANDRES | B24: acardenas@udistrital.edu.co | C24: FACULTAD | D24: OK
A25: Edilberto Suarez Torres | B25: esuarez@udistrital.edu.co | C25: FACULTAD
A26: Julio Baron Velandia | B26: jbaron@udistrital.edu.co | C26: FACULTAD
A27: NANCY YANETH GELVEZ | B27: nygelvezg@udistrital.edu.co | C27: FACULTAD
A28: Paulo Alonso Gaona Garcia | B28: pagaonag@udistrital.edu.co | C28: FACULTAD | D28: OK
A29: ANDRES LEONARDO JUTINICO | B29: aljutinicoa@udistrital.edu.co | C29: FACULTAD
A30: Carlos Enrique Montenegro Marin | B30: cemontenegrom@udistrital.edu.co | C30: FACULTAD | E30: MULTI
A31: Mariam Rivas | B31: mrivasd@udistrital.edu.co | C31: FACULTAD | D31: OK
A32: VICTOR HUGO MEDINA GARCIA | B32: vmedina@udistrital.edu.co | C32: FACULTAD | E32: GICOGE
A33: HECTOR JAVIER FUENTES | B33: hjfuentesl@udistrital.edu.co | C33: FACULTAD

Sheet ESTUDIANTES
A1: CODIGO | B1: NOMBRE ESTUDIANTE | C1: ESTADO | D1: ESTADOS | E1: ESTRATO | F1: CORREO INSTITUCIONAL | G1: CORREO PERSONAL | H1: ID | I1: DOCUMENTO | J1: CELULAR
K2: OK YA
A3: 20181495002 | B3: CALLE TORRES JULIAN DAVID | C3: A | D3: ACTIVO | E3: 3 | F3: jdcallet@udistrital.edu.co | G3: jdcallet@unal.edu.co | H3: CC | I3: 1014238861 | J3: 3194345874 | K3: =VLOOKUP(I3,'Estudiantes ya'!L:M,1,0) -> #N/A
A4: 20181495018 | B4: SALAMANCA VASQUEZ ESTEBAN | C4: A | D4: ACTIVO | E4: 3 | F4: esalamancav@udistrital.edu.co | G4: esalamancav@gmail.com | H4: CC | I4: 80211143 | J4: 3014939976 | K4: =VLOOKUP(I4,'Estudiantes ya'!L:M,1,0) -> #N/A
A5: 20182395007 | B5: HURTADO VASQUEZ CRISTIAN CAMILO | C5: A | D5: ACTIVO | E5: 2 | F5: cchurtadov@udistrital.edu.co | G5: cchurtadov@udistrital.edu.co | H5: CC | I5: 1026269815 | J5: 3118341177 | K5: =VLOOKUP(I5,'Estudiantes ya'!L:M,1,0) -> #N/A
A6: 20182495004 | B6: BARRAGAN SARMIENTO ANDRES MAURICIO | C6: A | D6: ACTIVO | E6: 2 | F6: ambarragans@udistrital.edu.co | G6: barragan_amb@hotmail.com | H6: CC | I6: 1110537094 | J6: 3138730050 | K6: =VLOOKUP(I6,'Estudiantes ya'!L:M,1,0) -> #N/A
A7: 20182495006 | B7: ERIRA TRUJILLO WILLIAM ALBERTO | C7: A | D7: ACTIVO | E7: 3 | F7: waerirat@udistrital.edu.co | G7: werira@hotmail.com | H7: CC | I7: 79595381 | J7: 3002064489 | K7: =VLOOKUP(I7,'Estudiantes ya'!L:M,1,0) -> #N/A
A8: 20182495011 | B8: PI?EROS RAMIREZ JEISSON RODRIGO | C8: A | D8: ACTIVO | E8: 2 | F8: jrpinerosr@udistrital.edu.co | G8: jeisson005@hotmail.com | H8: CC | I8: 1030678110 | J8: 3115339687 | K8: =VLOOKUP(I8,'Estudiantes ya'!L:M,1,0) -> #N/A
A9: 20182495014 | B9: ROMERO PINTO JAWY ANDRES | C9: A | D9: ACTIVO | E9: 3 | F9: jawaromerop@udistrital.edu.co | G9: jawy.romero@gmail.com | H9: CC | I9: 1022955756 | J9: 3208536808 | K9: =VLOOKUP(I9,'Estudiantes ya'!L:M,1,0) -> #N/A
A10: 20191195007 | B10: RENGIFO GUIZA WILMAR NEISER | C10: A | D10: ACTIVO | E10: 2 | F10: wnrengifog@udistrital.edu.co | G10: wilrengui@gmail.com | H10: CC | I10: 80248462 | J10: 3187906508 | K10: =VLOOKUP(I10,'Estudiantes ya'!L:M,1,0) -> #N/A
A11: 20191395005 | B11: LOPEZ CALLE MARIA ISABEL | C11: A | D11: ACTIVO | E11: 4 | F11: milopezc@udistrital.edu.co | G11: isalopez0216@gmail.com | H11: CC | I11: 1018483105 | J11: 3204006059 | K11: =VLOOKUP(I11,'Estudiantes ya'!L:M,1,0) -> #N/A
A12: 20191395011 | B12: SUAREZ JAIMES PAOLA ANDREA | C12: A | D12: ACTIVO | E12: 4 | F12: pasuarezj@udistrital.edu.co | G12: ingpaolasuarez@gmail.com | H12: CC | I12: 1014267962 | J12: 3157533711 | K12: =VLOOKUP(I12,'Estudiantes ya'!L:M,1,0) -> #N/A
A13: 20191495003 | B13: CARVAJAL TORRES JOSE AUGUSTO | C13: A | D13: ACTIVO | E13: 4 | F13: jacarvajalt@udistrital.edu.co | G13: jacarvajalt@correo.udistrital.edu.co | H13: CC | I13: 1026295788 | J13: 3134606915 | K13: =VLOOKUP(I13,'Estudiantes ya'!L:M,1,0) -> #N/A
A14: 20191495006 | B14: COTTA GARCIA JUAN GUILLERMO | C14: A | D14: ACTIVO | E14: 1 | F14: jgcottag@udistrital.edu.co | G14: jgcotta@hotmail.com | H14: CC | I14: 1032470566 | J14: 3057117319 | K14: =VLOOKUP(I14,'Estudiantes ya'!L:M,1,0) -> #N/A
... A20: 20191495030 | B20: QUIROGA RUIZ JAVIER ALBERTO | C20: A | D20: ACTIVO | E20: 4 | F20: jaaquirogar@udistrital.edu.co | G20: ja_quiroga@hotmail.com | H20: CC | I20: 79410997 | J20: 3208575262 | K20: =VLOOKUP(I20,'Estudiantes ya'!L:M,1,0) -> #N/A
A21: 20191495031 | B21: ESPITIA PARDO DANIEL ENRIQUE | C21: A | D21: ACTIVO | E21: NO REGISTRA | F21: deespitiap@udistrital.edu.co | G21: danielespitia63@gmail.com | H21: CC | I21: 1024478452 | J21: 3164979161 | K21: =VLOOKUP(I21,'Estudiantes ya'!L:M,1,0) -> #N/A
A22: 20192195003 | B22: ESPINEL GOMEZ DIEGO FERNANDO | C22: A | D22: ACTIVO | E22: 2 | F22: dfespinelg@udistrital.edu.co | G22: espineldago@gmail.com | H22: CC | I22: 1018470424 | J22: 3144929188 | K22: =VLOOKUP(I22,'Estudiantes ya'!L:M,1,0) -> #N/A
A23: 20192195004 | B23: PEREZ CRISTANCHO JERSON FERNANDO | C23: A | D23: ACTIVO | E23: 3 | F23: jfperezc@udistrital.edu.co | G23: injerson@gmail.com | H23: CC | I23: 74327152 | J23: 3204754652 | K23: =VLOOKUP(I23,'Estudiantes ya'!L:M,1,0) -> #N/A
A24: 20192395002 | B24: GARCIA GUZMAN PEDRO PABLO | C24: A | D24: ACTIVO | E24: 4 | F24: ggpedrop@udistrital.edu.co | G24: pedropgarciag@gmail.com | H24: CC | I24: 79365082 | J24: 3134556444 | K24: =VLOOKUP(I24,'Estudiantes ya'!L:M,1,0) -> #N/A
A25: 20192395005 | B25: CAITA SOTAQUIRA NATALIA | C25: A | D25: ACTIVO | E25: 3 | F25: ncaitas@udistrital.edu.co | G25: nati.caita@gmail.com | H25: CC | I25: 1026273952 | J25: 3192310138 | K25: =VLOOKUP(I25,'Estudiantes ya'!L:M,1,0) -> #N/A
A26: 20192395007 | B26: MALAGON MARQUEZ DIEGO ALEJANDRO | C26: A | D26: ACTIVO | E26: 3 | F26: mmdiegoa@udistrital.edu.co | G26: dalejomalagon@gmail.com | H26: CC | I26: 1022395401 | J26: 3133376495 | K26: =VLOOKUP(I26,'Estudiantes ya'!L:M,1,0) -> #N/A
A27: 20192395008 | B27: HUERTAS VARGAS KAREN ANDREA | C27: A | D27: ACTIVO | E27: 3 | F27: hvkarena@udistrital.edu.co | G27: karenahva@gmail.com | H27: CC | I27: 1023923782 | J27: 3204431938 | K27: =VLOOKUP(I27,'Estudiantes ya'!L:M,1,0) -> #N/A
A28: 20192395011 | B28: RUIZ MORALES TANIA LORENA | C28: A | D28: ACTIVO | E28: 2 | F28: tlruizm@udistrital.edu.co | G28: tlorena.icg@gmail.com | H28: CC | I28: 1018480123 | J28: 3015938056 | K28: =VLOOKUP(I28,'Estudiantes ya'!L:M,1,0) -> #N/A
A29: 20192495001 | B29: MU?OZ PENAGOS NATHALIA CATALINA | C29: A | D29: ACTIVO | E29: 4 | F29: mpnathaliac@udistrital.edu.co | G29: nathmunoz19@gmail.com | H29: CC | I29: 1032449961 | J29: 3185215312 | K29: =VLOOKUP(I29,'Estudiantes ya'!L:M,1,0) -> #N/A
A30: 20192495003 | B30: MONTENEGRO ALVARADO ANDRES DAVID | C30: A | D30: ACTIVO | E30: 2 | F30: admontenegroa@udistrital.edu.co | G30: admontenegroa@gmail.com | H30: CC | I30: 1023924156 | J30: 3505212562 | K30: =VLOOKUP(I30,'Estudiantes ya'!L:M,1,0) -> #N/A
A31: 20192495004 | B31: CASTRO CASTRO OMAR JOSE | C31: A | D31: ACTIVO | E31: 3 | F31: ccomarj@udistrital.edu.co | G31: kstroomar@yahoo.es | H31: CC | I31: 1010204406 | J31: 3008818918 | K31: =VLOOKUP(I31,'Estudiantes ya'!L:M,1,0) -> #N/A
A32: 20192495005 | B32: DAZA NARVAEZ ERIKA JUNNIETH | C32: A | D32: ACTIVO | E32: 3 | F32: dnerikaj@udistrital.edu.co | G32: ekdaza1709@gmail.com | H32: CC | I32: 1018460864 | J32: 3207553745 | K32: =VLOOKUP(I32,'Estudiantes ya'!L:M,1,0) -> #N/A
A33: 20192495013 | B33: IDROBO LOPEZ OSCAR JAVIER | C33: A | D33: ACTIVO | E33: 3 | F33: ojidrobol@udistrital.edu.co | G33: oscaridrobolopez@hotmail.com | H33: CC | I33: 1022386417 | J33: 3118649680 | K33: =VLOOKUP(I33,'Estudiantes ya'!L:M,1,0) -> #N/A
... A77: 20221395001 | B77: ANGEL VILLAREAL SERGIO LEONARDO | C77: A | D77: ACTIVO | E77: 3 | F77: slangelv@udistrital.edu.co | G77: angelvsergio@gmail.com | H77: CC | I77: 1030631243 | J77: 3204542891 | K77: =VLOOKUP(I77,'Estudiantes ya'!L:M,1,0) -> 1030631243
A78: 20221395002 | B78: CABEZAS MARTIN GONZALO | C78: A | D78: ACTIVO | E78: NO REGISTRA | F78: gcabezasm@udistrital.edu.co | G78: gonzalocabezas06@gmail.com | H78: CC | I78: 1018477001 | J78: 3219534044 | K78: =VLOOKUP(I78,'Estudiantes ya'!L:M,1,0) -> #N/A
A79: 20221395003 | B79: CUMBE LOAIZA LAURA CAMILA | C79: A | D79: ACTIVO | E79: 2 | F79: lccumbel@udistrital.edu.co | G79: cumbelc@gmail.com | H79: CC | I79: 1012391241 | J79: 3162523202 | K79: =VLOOKUP(I79,'Estudiantes ya'!L:M,1,0) -> #N/A
A80: 20221395004 | B80: GUERRERO VARONA LUIS MIGUEL | C80: A | D80: ACTIVO | E80: 3 | F80: lmguerrerov@udistrital.edu.co | G80: lmguerrerov@udistrital.edu.co | H80: CC | I80: 1030534583 | J80: 3246804677 | K80: =VLOOKUP(I80,'Estudiantes ya'!L:M,1,0) -> #N/A
A81: 20221395009 | B81: JASON MAURICIO ROMERO RIOS | C81: A | D81: ACTIVO | E81: 2 | F81: jamromeror@udistrital.edu.co | G81: jamromeror@udistrital.edu.co | H81: CC | I81: 1032501251 | J81: 3203122493 | K81: =VLOOKUP(I81,'Estudiantes ya'!L:M,1,0) -> #N/A
A82: 20221395010 | B82: ROJAS NARANJO JORGE ELIECER | C82: A | D82: ACTIVO | E82: 3 | F82: jorerojasn@udistrital.edu.co | G82: jerojasn@gmail.com | H82: CC | I82: 80903757 | J82: 3006399338 | K82: =VLOOKUP(I82,'Estudiantes ya'!L:M,1,0) -> #N/A
A83: 20221495002 | B83: BEJARANO MEDELLIN SEBASTIAN LEONARDO | C83: A | D83: ACTIVO | E83: 3 | F83: slbejaranom@udistrital.edu.co | G83: slbejaranom@gmail.com | H83: CC | I83: 1030671497 | J83: 3224093121 | K83: =VLOOKUP(I83,'Estudiantes ya'!L:M,1,0) -> #N/A
A84: 20221495005 | B84: FORERO CASTRO DIEGO DANIEL | C84: A | D84: ACTIVO | E84: 2 | F84: ddforeroc@udistrital.edu.co | G84: ddforeroc@gmail.com | H84: CC | I84: 1010219920 | J84: 3124029463 | K84: =VLOOKUP(I84,'Estudiantes ya'!L:M,1,0) -> #N/A
A85: 20221495008 | B85: PERDOMO ORJUELA LUIS EDUARDO | C85: A | D85: ACTIVO | E85: 3 | F85: leperdomoo@udistrital.edu.co | G85: luis1988perdomo@gmail.com | H85: CC | I85: 1020734582 | K85: =VLOOKUP(I85,'Estudiantes ya'!L:M,1,0) -> #N/A
A86: 20221495010 | B86: RODRIGUEZ DAZA NICOLAS | C86: A | D86: ACTIVO | E86: 3 | F86: nrodriguezd@udistrital.edu.co | G86: nicolasrd1808@gmail.com | H86: CC | I86: 1032492665 | J86: 3004183473 | K86: =VLOOKUP(I86,'Estudiantes ya'!L:M,1,0) -> #N/A
A87: 20221495012 | B87: SALAZAR ORTIZ JAIVER ESTIVEN | C87: A | D87: ACTIVO | E87: 1 | F87: jesalazaro@udistrital.edu.co | G87: jesalazaro@correo.udistrital.edu.co | H87: CC | I87: 1010226431 | J87: 3124029089 | K87: =VLOOKUP(I87,'Estudiantes ya'!L:M,1,0) -> #N/A
A88: 20221495013 | B88: SANCHEZ BOLA?OS CRISTIAN DAVID | C88: A | D88: ACTIVO | E88: 3 | F88: cdsanchezbo@udistrital.edu.co | G88: crdsanchezb@correo.udistrital.edu.co | H88: CC | I88: 1013677336 | J88: 3102196856 | K88: =VLOOKUP(I88,'Estudiantes ya'!L:M,1,0) -> #N/A
A89: 20221495016 | B89: UNIGARRO DIAZ CHRISTIAN JOSE | C89: A | D89: ACTIVO | E89: 4 | F89: cjunigarrod@udistrital.edu.co | G89: cunigarrod@gmail.com | H89: CC | I89: 1113514597 | J89: 3209040095 | K89: =VLOOKUP(I89,'Estudiantes ya'!L:M,1,0) -> #N/A
A90: 20152195007 | B90: CUELLAR SALINAS JOHAN NICOLAS | C90: A | D90: ACTIVO | E90: 1 | F90: jncuellars@udistrital.edu.co | G90: nicolascs23@gmail.com | H90: CC | I90: 1018432208 | K90: =VLOOKUP(I90,'Estudiantes ya'!L:M,1,0) -> #N/A
A91: 20161195007 | B91: GUERRERO PALMERA MIGUEL ANGEL | C91: A | D91: ACTIVO | E91: 4 | F91: miaguerrerop@udistrital.edu.co | G91: guerrero.palmera@gmail.com | H91: CC | I91: 13747816 | K91: =VLOOKUP(I91,'Estudiantes ya'!L:M,1,0) -> #N/A
A92: 20162195001 | B92: ALAYON MORA RICARDO ARTURO | C92: A | D92: ACTIVO | E92: 2 | F92: raalayonm@udistrital.edu.co | G92: ricardiyon@gmail.com | H92: CC | I92: 80813731 | K92: =VLOOKUP(I92,'Estudiantes ya'!L:M,1,0) -> #N/A
A93: 20162495009 | B93: MOLINA ESPITIA AMPARO | C93: A | D93: ACTIVO | E93: 3 | F93: amolinae@udistrital.edu.co | G93: amparo.molinae@gmail.com | H93: CC | I93: 52754073 | K93: =VLOOKUP(I93,'Estudiantes ya'!L:M,1,0) -> #N/A
A94: 20162495010 | B94: MONCADA VEGA DIEGO ANDRES | C94: A | D94: ACTIVO | E94: 2 | F94: damoncadav@udistrital.edu.co | G94: dandresmv@gmail.com | H94: CC | I94: 80777868 | K94: =VLOOKUP(I94,'Estudiantes ya'!L:M,1,0) -> #N/A
A95: 20171195003 | B95: GONZALEZ AGUIRRE FRANCISCO JAVIER | C95: A | D95: ACTIVO | E95: 3 | F95: fjgonzaleza@udistrital.edu.co | G95: frankyaz@gmail.com | H95: CC | I95: 1032367367 | K95: =VLOOKUP(I95,'Estudiantes ya'!L:M,1,0) -> #N/A
A96: 20171395001 | B96: BECERRA LOPEZ LUIS EDUARDO | C96: A | D96: ACTIVO | E96: 4 | F96: lebecerral@udistrital.edu.co | G96: luis_e_becerra@hotmail.com | H96: CC | I96: 80223922 | K96: =VLOOKUP(I96,'Estudiantes ya'!L:M,1,0) -> #N/A
A97: 20171495002 | B97: ARIAS BERNAL HENRY | C97: A | D97: ACTIVO | E97: 3 | F97: hariasb@udistrital.edu.co | G97: henryariasbernal@gmail.com | H97: CC | I97: 1030530500 | K97: =VLOOKUP(I97,'Estudiantes ya'!L:M,1,0) -> #N/A
A98: 20171495007 | B98: CARRILLO MEJIA LUIS | C98: A | D98: ACTIVO | E98: 3 | F98: lcarrillom@udistrital.edu.co | G98: Lucho1352@gmail.com | H98: CC | I98: 1016009768 | K98: =VLOOKUP(I98,'Estudiantes ya'!L:M,1,0) -> #N/A
A99: 20171495019 | B99: SALAZAR BAEZ DIANA MILENA | C99: A | D99: ACTIVO | E99: 2 | F99: dmsalazarb@udistrital.edu.co | G99: dsalaz539@gmail.com | H99: CC | I99: 1022925119 | K99: =VLOOKUP(I99,'Estudiantes ya'!L:M,1,0) -> #N/A
A100: 20171495020 | B100: SILVA ROJAS JOSE ANTONIO | C100: A | D100: ACTIVO | E100: NO REGISTRA | F100: jasilvar@udistrital.edu.co | G100: ja.silvarojas@gmail.com | H100: CC | I100: 80742478 | K100: =VLOOKUP(I100,'Estudiantes ya'!L:M,1,0) -> 80742478
A101: 20172195009 | B101: GAMBOA QUIROGA FAUSTO ALEXANDER | C101: A | D101: ACTIVO | E101: 2 | F101: fagamboaq@udistrital.edu.co | G101: leadhfg@gmail.com | H101: CC | I101: 1032419237 | K101: =VLOOKUP(I101,'Estudiantes ya'!L:M,1,0) -> #N/A
A102: 20172395001 | B102: BARBOSA PE?A JHONATAN JOSE | C102: A | D102: ACTIVO | E102: 3 | F102: jjbarbosap@udistrital.edu.co | G102: jhonatanjj.udistri@gmail.com | H102: CC | I102: 1031136781 | K102: =VLOOKUP(I102,'Estudiantes ya'!L:M,1,0) -> 1031136781
A103: 20172395007 | B103: GOMEZ RODRIGUEZ MAURICIO ALEXANDER | C103: A | D103: ACTIVO | E103: 3 | F103: mauagomezr@udistrital.edu.co | G103: maurgom39@gmail.com | H103: CC | I103: 79957100 | K103: =VLOOKUP(I103,'Estudiantes ya'!L:M,1,0) -> #N/A
A104: 20172395009 | B104: MAYORGA RONCANCIO GUSTAVO ADOLFO | C104: A | D104: ACTIVO | E104: 3 | F104: gamayorgar@udistrital.edu.co | G104: topingcivil@yahoo.es | H104: CC | I104: 80730975 | K104: =VLOOKUP(I104,'Estudiantes ya'!L:M,1,0) -> #N/A
A105: 20172495004 | B105: CUCHIA RUIZ JAIME ANDRES | C105: A | D105: ACTIVO | E105: 4 | F105: jacuchiar@udistrital.edu.co | G105: andrescuchia@gmail.com | H105: CC | I105: 1015399142 | K105: =VLOOKUP(I105,'Estudiantes ya'!L:M,1,0) -> #N/A
A106: 20172495008 | B106: GARCIA PEDROZA CESAR ALFREDO | C106: A | D106: ACTIVO | E106: NO REGISTRA | F106: ceagarciap@udistrital.edu.co | G106: cesar_garcia_ts@hotmail.com | H106: CC | I106: 13176614 | K106: =VLOOKUP(I106,'Estudiantes ya'!L:M,1,0) -> #N/A
A107: 20172495011 | B107: MUNAR SUAREZ OSCAR ENRIQUE | C107: A | D107: ACTIVO | E107: 3 | F107: oemunars@udistrital.edu.co | G107: oscar.munar.suarez@gmail.com | H107: CC | I107: 1018402781 | K107: =VLOOKUP(I107,'Estudiantes ya'!L:M,1,0) -> #N/A
A108: 20172495013 | B108: PINZON BALLESTEROS JOHAN CAMILO | C108: A | D108: ACTIVO | E108: 2 | F108: jcpinzonb@udistrital.edu.co | G108: camilion-aw7@hotmail.com | H108: CC | I108: 1030593353 | K108: =VLOOKUP(I108,'Estudiantes ya'!L:M,1,0) -> #N/A
A109: 20181195004 | B109: CRUZ CAPADOR GERSON DAVID | C109: A | D109: ACTIVO | E109: 3 | F109: gdcruzc@udistrital.edu.co | G109: gdavidcrux@gmail.com | H109: CC | I109: 80852553 | K109: =VLOOKUP(I109,'Estudiantes ya'!L:M,1,0) -> #N/A
A110: 20181195005 | B110: MONROY MACHADO DAVID | C110: A | D110: ACTIVO | E110: 4 | F110: dmonroym@udistrital.edu.co | G110: dmonroym@udistrital.edu.co | H110: CC | I110: 79854643 | K110: =VLOOKUP(I110,'Estudiantes ya'!L:M,1,0) -> #N/A
A111: 20181195011 | B111: SOLARTE ROSAS CRISTIAN JULIAN | C111: A | D111: ACTIVO | E111: NO REGISTRA | F111: cjsolarter@udistrital.edu.co | G111: cristianjulians@hotmail.com | H111: CC | I111: 10305394 | K111: =VLOOKUP(I111,'Estudiantes ya'!L:M,1,0) -> #N/A
A112: 20181395001 | B112: ACOSTA AGUDELO JULIETH NATALIA | C112: A | D112: ACTIVO | E112: 3 | F112: jnacostaa@udistrital.edu.co | G112: jnatalia09803@gmail.com | H112: CC | I112: 1074135036 | K112: =VLOOKUP(I112,'Estudiantes ya'!L:M,1,0) -> #N/A
A113: 20181395005 | B113: PUENTES CARVAJAL ANDERSON | C113: A | D113: ACTIVO | E113: 3 | F113: apuentesc@udistrital.edu.co | G113: andersonpuentesc@gmail.com | H113: CC | I113: 79986940 | K113: =VLOOKUP(I113,'Estudiantes ya'!L:M,1,0) -> #N/A
A114: 20181495009 | B114: ERAZO GUERRERO HERNAN ALVEIRO | C114: A | D114: ACTIVO | E114: 4 | F114: haerazog@udistrital.edu.co | G114: haerazogu@gmail.com | H114: CC | I114: 1088592425 | K114: =VLOOKUP(I114,'Estudiantes ya'!L:M,1,0) -> #N/A
A115: 20181495011 | B115: MORA PE?A DANNY FABIAN | C115: A | D115: ACTIVO | E115: 3 | F115: dfmorap@udistrital.edu.co | G115: dannyf620@gmail.com | H115: CC | I115: 1015438359 | K115: =VLOOKUP(I115,'Estudiantes ya'!L:M,1,0) -> #N/A
A116: 20181495015 | B116: PI?EROS HERNANDEZ JOHN FREDY | C116: A | D116: ACTIVO | E116: 2 | F116: jfpinerosh@udistrital.edu.co | G116: johnpiud@gmail.com | H116: CC | I116: 1015405675 | K116: =VLOOKUP(I116,'Estudiantes ya'!L:M,1,0) -> #N/A
A117: 20241595001 | B117: GUEVARA VALENCIA EDWIN STEVEN | C117: A | D117: ACTIVO | E117: 1 | F117: esguevarav@udistrital.edu.co | G117: edwin.guevara.valencia@gmail.com | H117: CC | I117: 1018489941 | J117: 3142873963 | K117: =VLOOKUP(I117,'Estudiantes ya'!L:M,1,0) -> 1018489941
A118: 20241595002 | B118: HERNANDEZ NAVARRETE JEISSON ANDRES | C118: A | D118: ACTIVO | E118: 2 | F118: jeahernandezn@udistrital.edu.co | G118: andrezhernandez29@yahoo.com | H118: CC | I118: 1014298952 | J118: 3209190949 | K118: =VLOOKUP(I118,'Estudiantes ya'!L:M,1,0) -> 1014298952
A119: 20241595003 | B119: HIGUERA VILLALBA ESTEBAN RICARDO | C119: A | D119: ACTIVO | E119: 3 | F119: erhiguerav@udistrital.edu.co | G119: esteban3622@gmail.com | H119: CC | I119: 1032457392 | J119: 3106291488 | K119: =VLOOKUP(I119,'Estudiantes ya'!L:M,1,0) -> 1032457392
A120: 20241595005 | B120: LEON CELIS GABRIELA | C120: A | D120: ACTIVO | E120: 3 | F120: gleonc@udistrital.edu.co | G120: gabrielaleonc@hotmail.com | H120: CC | I120: 1031170176 | J120: 3185208646 | K120: =VLOOKUP(I120,'Estudiantes ya'!L:M,1,0) -> 1031170176
A121: 20241595006 | B121: OVIEDO YATE BRAYAN STIVEN | C121: A | D121: ACTIVO | E121: NO REGISTRA | F121: bsoviedoy@udistrital.edu.co | G121: bsoviedoy98@gmail.com | H121: CC | I121: 1233492968 | J121: 3228452205 | K121: =VLOOKUP(I121,'Estudiantes ya'!L:M,1,0) -> 1233492968
A122: 20241595007 | B122: PEDRAZA HIGUERA JOSE DAVID | C122: A | D122: ACTIVO | E122: 4 | F122: jdpedrazah@udistrital.edu.co | G122: ing.david.pedraza@gmail.com | H122: CC | I122: 1026264347 | J122: 3213629835 | K122: =VLOOKUP(I122,'Estudiantes ya'!L:M,1,0) -> #N/A
A123: 20241595008 | B123: PE?A VILLAMIL JOAN CAMILO | C123: A | D123: ACTIVO | E123: 1 | F123: jucpenav@udistrital.edu.co | G123: camilop1998@gmail.com | H123: CC | I123: 1022432262 | J123: 3133851772 | K123: =VLOOKUP(I123,'Estudiantes ya'!L:M,1,0) -> 1022432262
A124: 20241595009 | B124: PEREZ DIAZ ISABEL VICTORIA | C124: A | D124: ACTIVO | E124: 3 | F124: ivperezd@udistrital.edu.co | G124: isa8.perez@gmail.com | H124: CC | I124: 1233508093 | J124: 3226074150 | K124: =VLOOKUP(I124,'Estudiantes ya'!L:M,1,0) -> 1233508093
A125: 20241595011 | B125: SANCHEZ MONTA?A VIVIAN DANIELA | C125: A | D125: ACTIVO | E125: NO REGISTRA | F125: vdsanchezm@udistrital.edu.co | G125: dani.sanchez300@gmail.com | H125: CC | I125: 1014294978 | J125: 3103375466 | K125: =VLOOKUP(I125,'Estudiantes ya'!L:M,1,0) -> 1014294978
A126: 20241595012 | B126: VELANDIA MONTA?O CRISTIAN ANDRES | C126: A | D126: ACTIVO | E126: 1 | F126: cavelandiam@udistrital.edu.co | G126: cavelandiam@gmail.com | H126: CC | I126: 1023005034 | J126: 3138065403 | K126: =VLOOKUP(I126,'Estudiantes ya'!L:M,1,0) -> #N/A
A127: 20242595001 | B127: FORERO ZAPATA SEBASTIAN | C127: A | D127: ACTIVO | E127: 2 | F127: sforeroz@udistrital.edu.co | G127: sebastian.forero.77@gmail.com | H127: CC | I127: 1000514921 | J127: 3194970523 | K127: =VLOOKUP(I127,'Estudiantes ya'!L:M,1,0) -> 1000514921
A128: 20242595002 | B128: GALINDO ARIAS LEIDY JHOANNA | C128: A | D128: ACTIVO | E128: 1 | F128: leijgalindoa@udistrital.edu.co | G128: ingjhoanna@gmail.com | H128: CC | K128: =VLOOKUP(I128,'Estudiantes ya'!L:M,1,0) -> #N/A
A129: 20242595003 | B129: HERNANDEZ RIVEROS PILLT YOJAN | C129: A | D129: ACTIVO | E129: 4 | F129: pyhernandezr@udistrital.edu.co | G129: yojanhdez@gmail.com | H129: CC | I129: 1018472591 | J129: 3216576338 | K129: =VLOOKUP(I129,'Estudiantes ya'!L:M,1,0) -> 1018472591
A130: 20242595004 | B130: MATIZ GAITAN JOHAN ANDRES | C130: A | D130: ACTIVO | E130: NO REGISTRA | F130: jamatizg@udistrital.edu.co | G130: j.matiz18@gmail.com | H130: CC | I130: 1019145200 | J130: 3143757501 | K130: =VLOOKUP(I130,'Estudiantes ya'!L:M,1,0) -> 1019145200
A131: 20242595005 | B131: ZUBIETA CORTES FERNANDO | C131: A | D131: ACTIVO | E131: 2 | F131: fzubietac@udistrital.edu.co | G131: fernandozubieta10@hotmail.com | H131: CC | I131: 1033798653 | J131: 3194467960 | K131: =VLOOKUP(I131,'Estudiantes ya'!L:M,1,0) -> 1033798653
A132: 20251595001 | B132: ALAPE AVILA CRISTIAN LEONARDO | C132: A | D132: ACTIVO | E132: 2 | F132: clalapea@udistrital.edu.co | G132: clalapea@udistrital.edu.co | H132: CC | I132: 1016060113 | J132: 3194284737 | K132: =VLOOKUP(I132,'Estudiantes ya'!L:M,1,0) -> 1016060113
A133: 20251595002 | B133: BONILLA DIAZ MARIA ALEJANDRA | C133: A | D133: ACTIVO | E133: 4 | F133: mabonillad@udistrital.edu.co | G133: mabonillad@udistrital.edu.co | H133: CC | I133: 1024543666 | J133: 3214243119 | K133: =VLOOKUP(I133,'Estudiantes ya'!L:M,1,0) -> 1024543666
A134: 20251595003 | B134: MORENO MARTINEZ IVONNE LIZETH | C134: A | D134: ACTIVO | E134: 3 | F134: ilmorenom@udistrital.edu.co | G134: imorenom@ucentral.edu.co | H134: CC | I134: 1014278347 | J134: 3202704353 | K134: =VLOOKUP(I134,'Estudiantes ya'!L:M,1,0) -> 1014278347
A135: 20251595004 | B135: ORTIZ VARGAS YOUSSEF ALEJANDRO | C135: A | D135: ACTIVO | E135: 3 | F135: yaortizv@udistrital.edu.co | G135: yaortizv@udistrital.edu.co | H135: CC | I135: 1233912172 | J135: 3174835512 | K135: =VLOOKUP(I135,'Estudiantes ya'!L:M,1,0) -> 1233912172
A136: 20251595006 | B136: ZARABANDA GUTIERREZ ALVARO ALEJANDRO | C136: A | D136: ACTIVO | E136: 3 | F136: aazarabandag@udistrital.edu.co | G136: aazarabandag@udistrital.edu.co | H136: CC | I136: 1018511461 | J136: 3223912541 | K136: =VLOOKUP(I136,'Estudiantes ya'!L:M,1,0) -> 1018511461
A137: 20161395003 | B137: CASTRO QUIROGA YUBER ALFREDO | C137: A | D137: ACTIVO | E137: 3 | F137: yacastroq@udistrital.edu.co | G137: yubercastro@gmail.com | H137: CC | I137: 79532330 | K137: =VLOOKUP(I137,'Estudiantes ya'!L:M,1,0) -> #N/A
A138: 20172495016 | B138: SCARPETTA RODRIGUEZ LAURA CAMILA | C138: A | D138: ACTIVO | E138: 3 | F138: lcscarpettar@udistrital.edu.co | G138: lcscarpettar@gmail.com | H138: CC | I138: 1019098016 | K138: =VLOOKUP(I138,'Estudiantes ya'!L:M,1,0) -> #N/A
A139: 20172495017 | B139: VARGAS MONTERO JOSE MANUEL | C139: A | D139: ACTIVO | E139: 2 | F139: jomvargasm@udistrital.edu.co | G139: jmvm1313@gmail.com | H139: CC | I139: 1032458000 | K139: =VLOOKUP(I139,'Estudiantes ya'!L:M,1,0) -> #N/A
A140: 20202395009 | B140: PULIDO ROMERO LUIS ALBERTO | C140: A | D140: ACTIVO | E140: 4 | F140: lapulidor@udistrital.edu.co | G140: guin.luis@gmail.com | H140: CC | I140: 80874095 | K140: =VLOOKUP(I140,'Estudiantes ya'!L:M,1,0) -> #N/A
A141: 20142295003 | B141: DIEGO ALEJANDRO PINZON ROBETO | C141: A | D141: ACTIVO | E141: 1 | F141: dapinzonr@udistrital.edu.co | G141: alejorobert@yahoo.es | H141: CC | I141: 86079074 | K141: =VLOOKUP(I141,'Estudiantes ya'!L:M,1,0) -> #N/A
A142: 20162495013 | B142: REY VANEGAS DIEGO ARMANDO | C142: A | D142: ACTIVO | E142: 4 | F142: dareyv@udistrital.edu.co | G142: diego.rey.vaneg@gmail.com | H142: CC | I142: 80727303 | K142: =VLOOKUP(I142,'Estudiantes ya'!L:M,1,0) -> #N/A
A143: 20171195005 | B143: QUINTERO QUINTANA MARIA CLARA | C143: A | D143: ACTIVO | E143: 5 | F143: mcquinteroq@udistrital.edu.co | G143: ing.clara.quintero@gmail.com | H143: CC | I143: 1032366625 | K143: =VLOOKUP(I143,'Estudiantes ya'!L:M,1,0) -> #N/A
A144: 20212495010 | B144: NOBOA CALDERON XAVIER ALBERTO | C144: A | D144: ACTIVO | E144: 3 | F144: xanoboac@udistrital.edu.co | G144: xanc1@hotmail.com | H144: CC | I144: 93377853 | K144: =VLOOKUP(I144,'Estudiantes ya'!L:M,1,0) -> 93377853
A145: 20161195011 | B145: MORALES RIVERA JUAN PABLO | C145: A | D145: ACTIVO | E145: 3 | F145: jpmoralesr@udistrital.edu.co | G145: juanp1116@hotmail.com | H145: CC | I145: 1019010283 | K145: =VLOOKUP(I145,'Estudiantes ya'!L:M,1,0) -> 1019010283
A146: 20211495003 | B146: HOSPITAL MELO JAVIER DUVAN | C146: A | D146: ACTIVO | E146: 3 | F146: jdhospitalm@udistrital.edu.co | G146: hoispital@gmail.com | H146: CC | I146: 1018493894 | K146: =VLOOKUP(I146,'Estudiantes ya'!L:M,1,0) -> #N/A
A147: 20162195005 | B147: GARZON CORREA MAGDA LORENA | C147: A | D147: ACTIVO | E147: 2 | F147: mlgarzonc@correo.udistrital.edu.co | G147: lorenagarzonc@gmail.com | H147: CC | I147: 52211117 | K147: =VLOOKUP(I147,'Estudiantes ya'!L:M,1,0) -> #N/A
A148: 20172495007 | B148: GARCIA FLOREZ JOSE ANDRES | C148: A | D148: ACTIVO | E148: 2 | F148: josagarciaf@udistrital.edu.co | G148: joagaflo@gmail.com | H148: CC | I148: 1014251129 | K148: =VLOOKUP(I148,'Estudiantes ya'!L:M,1,0) -> #N/A
...

Sheet Estudiantes ya
A1: Id | B1: Hora de inicio | C1: Hora de finalización | D1: Correo electrónico | E1: Nombre | F1: Total de puntos | G1: Comentarios del cuestionario | H1: Hora de publicación de la calificación | I1: ¿Cuales es su nombre? | J1: Puntos: ¿Cuales es su nombre? | K1: Comentarios: ¿Cuales es su nombre? | L1: Digite su número de cedula | M1: Puntos: Digite su número de cedula | N1: Comentarios: Digite su número de cedula | O1: ¿En que rango de edad se encuentra? | P1: Puntos: ¿En que rango de edad se encuentra? | Q1: Comentarios: ¿En que rango de edad se encuentra? | R1: Por favor actualice su número de contacto telefónico | S1: Puntos: Por favor actualice su número de contacto telefónico | T1: Comentarios: Por favor actualice su número de contacto telefónico | U1: ¿En qué año ingreso a la Maestría en Ciencias de la Información y las Comunicaciones? | V1: Puntos: ¿En qué año ingreso a la Maestría en Ciencias de la Información y las Comunicaciones? | W1: Comentarios: ¿En qué año ingreso a la Maestría en Ciencias de la Información y las Comunicaciones? | X1: ¿En qué énfasis se encuentra inscrito? | Y1: Puntos: ¿En qué énfasis se encuentra inscrito? | Z1: Comentarios: ¿En qué énfasis se encuentra inscrito? | AA1: ¿En qué Modalidad o Metodología se encuentra inscrito? | AB1: Puntos: ¿En qué Modalidad o Metodología se encuentra inscrito? | AC1: Comentarios: ¿En qué Modalidad o Metodología se encuentra inscrito? | AD1: ¿Cuáles son sus áreas de investigación? | AE1: Puntos: ¿Cuáles son sus áreas de investigación? | AF1: Comentarios: ¿Cuáles son sus áreas de investigación? | AG1: Si se ofreciera una asignatura impartida en un 50% en inglés el próximo semestre, ¿se inscribiría? | AH1: Puntos: Si se ofreciera una asignatura impartida en un 50% en inglés el próximo semestre, ¿se inscribiría? | AI1: Comentarios: Si se ofreciera una asignatura impartida en un 50% en inglés el próximo semestre, ¿se inscribiría? | AJ1: ¿Cómo cree que una asignatura en inglés podría mejorar sus oportunidades futuras? | AK1: Puntos: ¿Cómo cree que una asignatura en inglés podría mejorar sus oportunidades futuras? | AL1: Comentarios: ¿Cómo cree que una asignatura en inglés podría mejorar sus oportunidades futuras? | AM1: Considero que mi participación en actividades de investigación, desarrollo tecnológico, creación artística, culturales, deportivas y de extensión ha contribuido a mi desarrollo integral como persona, | AN1: Puntos: Considero que mi participación en actividades de investigación, desarrollo tecnológico, creación artística, culturales, deportivas y de extensión ha contribuido a mi desarrollo integral como persona, | AO1: Comentarios: Considero que mi participación en actividades de investigación, desarrollo tecnológico, creación artística, culturales, deportivas y de extensión ha contribuido a mi desarrollo integral como persona, | AP1: Por favor, proporciona ejemplos específicos de actividades de investigación en las que has participado y cómo han impactado en tu formación integral: | AQ1: Puntos: Por favor, proporciona ejemplos específicos de actividades de investigación en las que has participado y cómo han impactado en tu formación integral: | AR1: Comentarios: Por favor, proporciona ejemplos específicos de actividades de investigación en las que has participado y cómo han impactado en tu formación integral: | AS1: Considero que el reglamento estudiantil y las políticas académicas del programa son pertinentes y están actualizadas. | AT1: Puntos: Considero que el reglamento estudiantil y las políticas académicas del programa son pertinentes y están actualizadas. | AU1: Comentarios: Considero que el reglamento estudiantil y las políticas académicas del programa son pertinentes y están actualizadas. | AV1: ¿Tienes sugerencias para mejorar la divulgación y comprensión del reglamento estudiantil y las políticas académicas? | AW1: Puntos: ¿Tienes sugerencias para mejorar la divulgación y comprensión del reglamento estudiantil y las políticas académicas? | AX1: Comentarios: ¿Tienes sugerencias para mejorar la divulgación y comprensión del reglamento estudiantil y las políticas académicas? | AY1: Considero que los criterios para la concesión de estímulos académicos y apoyos socioeconómicos, son claros y justos. | AZ1: Puntos: Considero que los criterios para la concesión de estímulos académicos y apoyos socioeconómicos, son claros y justos. | BA1: Comentarios: Considero que los criterios para la concesión de estímulos académicos y apoyos socioeconómicos, son claros y justos. | BB1: ¿Qué acciones crees que la institución debería emprender para mejorar la aplicación de los estímulos académicos y apoyos socioeconómicos? | BC1: Puntos: ¿Qué acciones crees que la institución debería emprender para mejorar la aplicación de los estímulos académicos y apoyos socioeconómicos? | BD1: Comentarios: ¿Qué acciones crees que la institución debería emprender para mejorar la aplicación de los estímulos académicos y apoyos socioeconómicos? | BE1: Considero que el material académico producido por los docentes es pertinente y adecuado con las necesidades y objetivos de la Maestría en Ciencias de la Información y las Comunicaciones. | BF1: Puntos: Considero que el material académico producido por los docentes es pertinente y adecuado con las necesidades y objetivos de la Maestría en Ciencias de la Información y las Comunicaciones. | BG1: Comentarios: Considero que el material académico producido por los docentes es pertinente y adecuado con las necesidades y objetivos de la Maestría en Ciencias de la Información y las Comunicaciones. | BH1: Considero que los criterios y mecanismos utilizados para la evaluación de los profesores son transparentes, accesibles y eficaces | BI1: Puntos: Considero que los criterios y mecanismos utilizados para la evaluación de los profesores son transparentes, accesibles y eficaces | BJ1: Comentarios: Considero que los criterios y mecanismos utilizados para la evaluación de los profesores son transparentes, accesibles y eficaces | BK1: Considero que las estrategias de flexibilidad curricular me han permitido personalizar mi formación de acuerdo con mis objetivos profesionales y académicos. | BL1: Puntos: Considero que las estrategias de flexibilidad curricular me han permitido personalizar mi formación de acuerdo con mis objetivos profesionales y académicos. | BM1: Comentarios: Considero que las estrategias de flexibilidad curricular me han permitido personalizar mi formación de acuerdo con mis objetivos profesionales y académicos. | BN1: ¿Podrías proporcionar ejemplos específicos de cómo las rutas de formación alternativas te han beneficiado para tu desarrollo académico y profesional? | BO1: Puntos: ¿Podrías proporcionar ejemplos específicos de cómo las rutas de formación alternativas te han beneficiado para tu desarrollo académico y profesional? | BP1: Comentarios: ¿Podrías proporcionar ejemplos específicos de cómo las rutas de formación alternativas te han beneficiado para tu desarrollo académico y profesional? | BQ1: ¿Cómo valorarías la efectividad de los énfasis en "Teleinformática" “Ingeniería de Software”, “Geomática” y "Inteligencia Artificial" en la formación integral de los estudiantes? | BR1: Puntos: ¿Cómo valorarías la efectividad de los énfasis en "Teleinformática" “Ingeniería de Software”, “Geomática” y "Inteligencia Artificial" en la formación integral de los estudiantes? | BS1: Comentarios: ¿Cómo valorarías la efectividad de los énfasis en "Teleinformática" “Ingeniería de Software”, “Geomática” y "Inteligencia Artificial" en la formación integral de los estudiantes? | BT1: Considero que las estrategias pedagógicas y escenarios de práctica utilizadas en la Maestría en Ciencias de la Información y las Comunicaciones son coherentes y efectivas para facilitar los resultados | BU1: Puntos: Considero que las estrategias pedagógicas y escenarios de práctica utilizadas en la Maestría en Ciencias de la Información y las Comunicaciones son coherentes y efectivas para facilitar los resultados | BV1: Comentarios: Considero que las estrategias pedagógicas y escenarios de práctica utilizadas en la Maestría en Ciencias de la Información y las Comunicaciones son coherentes y efectivas para facilitar los resultados | BW1: Considero que los sistemas de evaluación de los resultados de aprendizaje permiten una realimentación efectiva que contribuye a la mejora continua de la formación en los estudiantes. | BX1: Puntos: Considero que los sistemas de evaluación de los resultados de aprendizaje permiten una realimentación efectiva que contribuye a la mejora continua de la formación en los estudiantes. | BY1: Comentarios: Considero que los sistemas de evaluación de los resultados de aprendizaje permiten una realimentación efectiva que contribuye a la mejora continua de la formación en los estudiantes. | BZ1: Considero que el proceso de evaluación y autorregulación de la Maestría en Ciencias de la Información y las Comunicaciones tiene en cuenta de manera efectiva las necesidades y expectativas de los estu | CA1: Puntos: Considero que el proceso de evaluación y autorregulación de la Maestría en Ciencias de la Información y las Comunicaciones tiene en cuenta de manera efectiva las necesidades y expectativas de los estu | CB1: Comentarios: Considero que el proceso de evaluación y autorregulación de la Maestría en Ciencias de la Información y las Comunicaciones tiene en cuenta de manera efectiva las necesidades y expectativas de los estu | CC1: Considero que las intervenciones y el apoyo proporcionados para alertarme de forma temprana, han sido útiles para mejorar mi rendimiento académico y facilitar mi progreso hacia la graduación. | CD1: Puntos: Considero que las intervenciones y el apoyo proporcionados para alertarme de forma temprana, han sido útiles para mejorar mi rendimiento académico y facilitar mi progreso hacia la graduación. | CE1: Comentarios: Considero que las intervenciones y el apoyo proporcionados para alertarme de forma temprana, han sido útiles para mejorar mi rendimiento académico y facilitar mi progreso hacia la graduación. | CF1: Considero que la interacción con homólogos nacionales e internacionales ha mejorado mis competencias académicas y científicas, así como las oportunidades de desarrollo profesional. | CG1: Puntos: Considero que la interacción con homólogos nacionales e internacionales ha mejorado mis competencias académicas y científicas, así como las oportunidades de desarrollo profesional. | CH1: Comentarios: Considero que la interacción con homólogos nacionales e internacionales ha mejorado mis competencias académicas y científicas, así como las oportunidades de desarrollo profesional. | CI1: ¿Podrías proporcionar ejemplos específicos de proyectos, investigaciones o colaboraciones exitosas que hayan resultado de la cooperación académica y científica promovida por la Maestría en Ciencias de | CJ1: Puntos: ¿Podrías proporcionar ejemplos específicos de proyectos, investigaciones o colaboraciones exitosas que hayan resultado de la cooperación académica y científica promovida por la Maestría en Ciencias de | CK1: Comentarios: ¿Podrías proporcionar ejemplos específicos de proyectos, investigaciones o colaboraciones exitosas que hayan resultado de la cooperación académica y científica promovida por la Maestría en Ciencias de | CL1: Considero que la Maestría en Ciencias de la Información y las Comunicaciones me proporciona una formación adecuada para la investigación, fomentando el desarrollo de un pensamiento crítico, creativo e | CM1: Puntos: Considero que la Maestría en Ciencias de la Información y las Comunicaciones me proporciona una formación adecuada para la investigación, fomentando el desarrollo de un pensamiento crítico, creativo e | CN1: Comentarios: Considero que la Maestría en Ciencias de la Información y las Comunicaciones me proporciona una formación adecuada para la investigación, fomentando el desarrollo de un pensamiento crítico, creativo e | CO1: ¿Podrías proporcionar ejemplos específicos de proyectos o experiencias en los que hayas participado y que hayan contribuido significativamente a tu formación en investigación y desarrollo tecnológico, | CP1: Puntos: ¿Podrías proporcionar ejemplos específicos de proyectos o experiencias en los que hayas participado y que hayan contribuido significativamente a tu formación en investigación y desarrollo tecnológico, | CQ1: Comentarios: ¿Podrías proporcionar ejemplos específicos de proyectos o experiencias en los que hayas participado y que hayan contribuido significativamente a tu formación en investigación y desarrollo tecnológico, | CR1: Considero que las políticas, programas y servicios de bienestar implementados en Maestría en Ciencias de la Información y las Comunicaciones son coherentes con las condiciones y necesidades específica | CS1: Puntos: Considero que las políticas, programas y servicios de bienestar implementados en Maestría en Ciencias de la Información y las Comunicaciones son coherentes con las condiciones y necesidades específica | CT1: Comentarios: Considero que las políticas, programas y servicios de bienestar implementados en Maestría en Ciencias de la Información y las Comunicaciones son coherentes con las condiciones y necesidades específica | CU1: Considero que el acompañamiento proporcionado en la Maestría en Ciencias de la Información y las Comunicaciones facilita una comunicación efectiva y una interacción constructiva entre profesores y est | CV1: Puntos: Considero que el acompañamiento proporcionado en la Maestría en Ciencias de la Información y las Comunicaciones facilita una comunicación efectiva y una interacción constructiva entre profesores y est | CW1: Comentarios: Considero que el acompañamiento proporcionado en la Maestría en Ciencias de la Información y las Comunicaciones facilita una comunicación efectiva y una interacción constructiva entre profesores y est | CX1: Considero que los espacios, recurso, herramientas y equipos de apoyo ofrecidos son pertinentes y se ajustan adecuadamente a mis necesidades formativas en los diferentes contextos que requiero. | CY1: Puntos: Considero que los espacios, recurso, herramientas y equipos de apoyo ofrecidos son pertinentes y se ajustan adecuadamente a mis necesidades formativas en los diferentes contextos que requiero. | CZ1: Comentarios: Considero que los espacios, recurso, herramientas y equipos de apoyo ofrecidos son pertinentes y se ajustan adecuadamente a mis necesidades formativas en los diferentes contextos que requiero. | DA1: ¿Has notado alguna mejora en las estrategias y recursos de apoyo como resultado de retroalimentaciones previas? | DB1: Puntos: ¿Has notado alguna mejora en las estrategias y recursos de apoyo como resultado de retroalimentaciones previas? | DC1: Comentarios: ¿Has notado alguna mejora en las estrategias y recursos de apoyo como resultado de retroalimentaciones previas? | DD1: Considero que el material bibliográfico y de información disponible en la Maestría en Ciencias de la Información y las Comunicaciones es pertinente y adecuado para apoyar el desarrollo de las distinta | DE1: Puntos: Considero que el material bibliográfico y de información disponible en la Maestría en Ciencias de la Información y las Comunicaciones es pertinente y adecuado para apoyar el desarrollo de las distinta | DF1: Comentarios: Considero que el material bibliográfico y de información disponible en la Maestría en Ciencias de la Información y las Comunicaciones es pertinente y adecuado para apoyar el desarrollo de las distinta | DG1: Considero que el representante estudiantil en los diferentes escenarios institucionales ha sido valorada y ha influido en las decisiones orientadas al mejoramiento de la Maestría en Ciencias de la Inf | DH1: Puntos: Considero que el representante estudiantil en los diferentes escenarios institucionales ha sido valorada y ha influido en las decisiones orientadas al mejoramiento de la Maestría en Ciencias de la Inf | DI1: Comentarios: Considero que el representante estudiantil en los diferentes escenarios institucionales ha sido valorada y ha influido en las decisiones orientadas al mejoramiento de la Maestría en Ciencias de la Inf | DJ1: Creo que los procesos administrativos están orientados adecuadamente y son eficaces para apoyar el desarrollo integral de las labores formativas, académicas, docentes, científicas, culturales y de ext | DK1: Puntos: Creo que los procesos administrativos están orientados adecuadamente y son eficaces para apoyar el desarrollo integral de las labores formativas, académicas, docentes, científicas, culturales y de ext | DL1: Comentarios: Creo que los procesos administrativos están orientados adecuadamente y son eficaces para apoyar el desarrollo integral de las labores formativas, académicas, docentes, científicas, culturales y de ext | DM1: Considero que los recursos humanos (profesores, personal administrativo, etc.) disponibles en la Maestría en Ciencias de la Información y las Comunicaciones son suficientes y adecuados para atender el | DN1: Puntos: Considero que los recursos humanos (profesores, personal administrativo, etc.) disponibles en la Maestría en Ciencias de la Información y las Comunicaciones son suficientes y adecuados para atender el | DO1: Comentarios: Considero que los recursos humanos (profesores, personal administrativo, etc.) disponibles en la Maestría en Ciencias de la Información y las Comunicaciones son suficientes y adecuados para atender el | DP1: Considero que los recursos informáticos disponibles, corresponden adecuadamente con las | DQ1: Puntos: Considero que los recursos informáticos disponibles, corresponden adecuadamente con las | DR1: Comentarios: Considero que los recursos informáticos disponibles, corresponden adecuadamente con las | DS1: ¿En qué sector se desempeña su trabajo actual? | DT1: Puntos: ¿En qué sector se desempeña su trabajo actual? | DU1: Comentarios: ¿En qué sector se desempeña su trabajo actual? | DV1: ¿El trabajo que realiza actualmente se relaciona directamente con los conocimientos adquiridos en la maestría? | DW1: Puntos: ¿El trabajo que realiza actualmente se relaciona directamente con los conocimientos adquiridos en la maestría? | DX1: Comentarios: ¿El trabajo que realiza actualmente se relaciona directamente con los conocimientos adquiridos en la maestría? | DY1: ¿Siente que la maestría te ha abierto nuevas oportunidades laborales? | DZ1: Puntos: ¿Siente que la maestría te ha abierto nuevas oportunidades laborales? | EA1: Comentarios: ¿Siente que la maestría te ha abierto nuevas oportunidades laborales? | EB1: ¿Podría indicar el nombre de la empresa/compañía con la que labora actualmente? | EC1: Puntos: ¿Podría indicar el nombre de la empresa/compañía con la que labora actualmente? | ED1: Comentarios: ¿Podría indicar el nombre de la empresa/compañía con la que labora actualmente? | EE1: Como parte del proceso de autoevaluación y Acreditación de Alta Calidad, la Universidad requiere contactar a los empleadores de nuestros estudiantes. | EF1: Puntos: Como parte del proceso de autoevaluación y Acreditación de Alta Calidad, la Universidad requiere contactar a los empleadores de nuestros estudiantes. | EG1: Comentarios: Como parte del proceso de autoevaluación y Acreditación de Alta Calidad, la Universidad requiere contactar a los empleadores de nuestros estudiantes.
DP2: necesidades tecnológicas de la Maestría en Ciencias de la Información y las Comunicaciones y de sus miembros (pr | DQ2: necesidades tecnológicas de la Maestría en Ciencias de la Información y las Comunicaciones y de sus miembros (pr | DR2: necesidades tecnológicas de la Maestría en Ciencias de la Información y las Comunicaciones y de sus miembros (pr | EE2: Por lo tanto, le solicitamos de ser posible, prop | EF2: Por lo tanto, le solicitamos de ser posible, prop | EG2: Por lo tanto, le solicitamos de ser posible, prop
A3: 1 | B3: 45719.546 | C3: 45719.549 | D3: anfpulidoc@udistrital.edu.co | E3: ANDRES FELIPE PULIDO CASTRO | I3: Andrés\ Felipe\ Pulido\ Castro | J3: 0 | L3: 1010001829 | M3: 0 | O3: 25 a 30 | P3: 0 | R3: 3118210139 | S3: 0 | U3: 2024 | V3: 0 | X3: Geomtatica | Y3: 0 | AA3: Profundización | AB3: 0 | AD3: Catastro | AE3: 0 | AG3: Si | AH3: 0 | AJ3: es\ funcional | AK3: 0 | AM3: Totalmente de acuerdo. | AN3: 0 | AP3: . | AQ3: 0 | AS3: Totalmente de acuerdo. | AT3: 0 | AV3: No | AW3: 0 | AY3: Totalmente de acuerdo. | AZ3: 0 | BB3: Ninguna | BC3: 0 | BE3: Totalmente de acuerdo. | BF3: 0 | BH3: Totalmente de acuerdo. | BI3: 0 | BK3: Totalmente de acuerdo. | BL3: 0 | BN3: . | BO3: 0 | BQ3: Muy eficiente | BR3: 0 | BT3: Totalmente de acuerdo. | BU3: 0 | BW3: Totalmente de acuerdo. | BX3: 0 | BZ3: Totalmente de acuerdo. | CA3: 0 | CC3: Totalmente de acuerdo. | CD3: 0 | CF3: Totalmente de acuerdo. | CG3: 0 | CI3: No | CJ3: 0 | CL3: Totalmente de acuerdo. | CM3: 0 | CO3: No | CP3: 0 | CR3: Totalmente de acuerdo. | CS3: 0 | CU3: Totalmente de acuerdo. | CV3: 0 | CX3: Totalmente de acuerdo. | CY3: 0 | DA3: Sí. | DB3: 0 | DD3: Totalmente de acuerdo. | DE3: 0 | DG3: Totalmente de acuerdo. | DH3: 0 | DJ3: Totalmente de acuerdo. | DK3: 0 | DM3: Totalmente de acuerdo. | DN3: 0 | DP3: Totalmente de acuerdo. | DQ3: 0 | DS3: Tecnología (desarrollo de software, IA, ciberseguridad, telecomunicaciones) | DT3: 0 | DV3: Totalmente de acuerdo. | DW3: 0 | DY3: Totalmente de acuerdo. | DZ3: 0 | EB3: IGAC | EC3: 0 | EE3: . | EF3: 0
A4: 2 | B4: 45719.569 | C4: 45719.588 | D4: clalapea@udistrital.edu.co | E4: CRISTIAN LEONARDO ALAPE AVILA ALAPE AVILA | I4: Cristian\ Leonardo\ Alape\ Avila | J4: 0 | L4: 1016060113 | M4: 0 | O4: 31 a 40 | P4: 0 | R4: 3194284737 | S4: 0 | U4: 2025 | V4: 0 | X4: Ingeniería de Software | Y4: 0 | AA4: Investigación | AB4: 0 | AD4: Inteligencia artificial, ingeniería de software | AE4: 0 | AG4: No | AH4: 0 | AJ4: Es\ cierto\ que\ la\ mayoria\ de\ referentes\ del\ estado\ del\ arte\ de\ la\ tesis\ es\tan\ en\ ingles,\ pero\ esto\ no\ es\ \inf luyente\ en\ el\ ejercicio\ academico\ de\ impartir\ una\ clase\ | AK4: 0 | AM4: Totalmente de acuerdo. | AN4: 0 | AP4: Seminarios, asistencia a ponencias y congresos en computación como por ejemplo CICOM | AQ4: 0 | AS4: Ni en acuerdo, ni en desacuerdo. | AT4: 0 | AV4: Tener públicos los criterios y resultados de de admisión | AW4: 0 | AY4: De acuerdo. | AZ4: 0 | BB4: Reducir la burocracia en estos tramites. | BC4: 0 | BE4: De acuerdo. | BF4: 0 | BH4: De acuerdo. | BI4: 0 | BK4: De acuerdo. | BL4: 0 | BN4: No conozco rutas de formación alternativas | BO4: 0 | BQ4: Claramente ofrecen la capacidad de especializarse en áreas de conocimiento profundas por medio de las asignaturas y el área de conocimiento a fin en la tesis | BR4: 0 | BT4: De acuerdo. | BU4: 0 | BW4: De acuerdo. | BX4: 0 | BZ4: Ni en acuerdo, ni en desacuerdo. | CA4: 0 | CC4: Ni en acuerdo, ni en desacuerdo. | CD4: 0 | CF4: Totalmente de acuerdo. | CG4: 0 | CI4: unos docentes de planta recientemente contratados en la planta de la ud, hicieron su tesis doctoral en continuación de su tesis de maestría y de la misma forma esta ultima en continuación de su proyecto de grado en pregrado | CJ4: 0 | CL4: Totalmente de acuerdo. | CM4: 0 | CO4: Escribir y publicar artículos con rigor investigativo en bases de datos académicas | CP4: 0 | CR4: Ni en acuerdo, ni en desacuerdo. | CS4: 0 | CU4: De acuerdo. | CV4: 0 | CX4: Totalmente de acuerdo. | CY4: 0 | DA4: Sí. | DB4: 0 | DD4: Ni en acuerdo, ni en desacuerdo. | DE4: 0 | DG4: Ni en acuerdo, ni en desacuerdo. | DH4: 0 | DJ4: Ni en acuerdo, ni en desacuerdo. | DK4: 0 | DM4: De acuerdo. | DN4: 0 | DP4: Totalmente de acuerdo. | DQ4: 0 | DS4: Tecnología (desarrollo de software, IA, ciberseguridad, telecomunicaciones) | DT4: 0 | DV4: Totalmente de acuerdo. | DW4: 0 | DY4: Totalmente de acuerdo. | DZ4: 0 | EB4: Universidad Distrital Francisco Jose de Caldas | EC4: 0 | EE4: Alejandro Daza | EF4: 0
A5: 3 | B5: 45719.713 | C5: 45719.713 | D5: wfpinedar@udistrital.edu.co | E5: WILMAR FERNANDO PINEDA ROJAS | I5: Wilmar\ Fernando\ Pineda\ Rojas | J5: 0 | L5: 1015416478 | M5: 0 | O5: 31 a 40 | P5: 0 | R5: 3017852790 | S5: 0 | U5: 2024 | V5: 0 | X5: Ingeniería de Software | Y5: 0 | AA5: Profundización | AB5: 0 | AD5: Redes complejas y sistemas de radar | AE5: 0 | AG5: Si | AH5: 0 | AJ5: Si. | AK5: 0 | AM5: Totalmente de acuerdo. | AN5: 0 | AP5: escritura de articulos, esto contribuye a extender el entendimiento de la ciencia en las areas del conocimiento en la cual me desempeño laboralmente. | AQ5: 0 | AS5: De acuerdo. | AT5: 0 | AV5: de momento no. | AW5: 0 | AY5: Ni en acuerdo, ni en desacuerdo. | AZ5: 0 | BB5: Una estrategia clara acerca de los mismos, que evite el proceso infructuoso y desgastante de los procesos para acceder a dichos estimulos que no estan debidamente reglamentados. | BC5: 0 | BE5: De acuerdo. | BF5: 0 | BH5: De acuerdo. | BI5: 0 | BK5: De acuerdo. | BL5: 0 | BN5: Por que me permiten acceder a la formación enfocada en mis objetivos. | BO5: 0 | BQ5: Estos abarcan grandes areas del conocimiento aplicable en le quehacer profesional. | BR5: 0 | BT5: De acuerdo. | BU5: 0 | BW5: De acuerdo. | BX5: 0 | BZ5: De acuerdo. | CA5: 0 | CC5: De acuerdo. | CD5: 0 | CF5: De acuerdo. | CG5: 0 | CI5: De momento no tengo ninguno en la mente. | CJ5: 0 | CL5: De acuerdo. | CM5: 0 | CO5: La lectura y desarrollo de multiples articuos y proyectos enfocados en areas del conocimiento que son diversas me ha contribuido a mejorar mi forma de investigación. | CP5: 0 | CR5: Ni en acuerdo, ni en desacuerdo. | CS5: 0 | CU5: De acuerdo. | CV5: 0 | CX5: De acuerdo. | CY5: 0 | DA5: No sabe/ No responde. | DB5: 0 | DD5: De acuerdo. | DE5: 0 | DG5: Ni en acuerdo, ni en desacuerdo. | DH5: 0 | DJ5: De acuerdo. | DK5: 0 | DM5: Ni en acuerdo, ni en desacuerdo. | DN5: 0 | DP5: Ni en acuerdo, ni en desacuerdo. | DQ5: 0 | DS5: Tecnología (desarrollo de software, IA, ciberseguridad, telecomunicaciones) | DT5: 0 | DV5: Totalmente de acuerdo. | DW5: 0 | DY5: Ni en acuerdo, ni en desacuerdo. | DZ5: 0 | EB5: Imagemaker | EC5: 0 | EE5: Actualmente no tengo jefe directo. | EF5: 0
A6: 4 | B6: 45719.912 | C6: 45719.912 | D6: lpgarciam@udistrital.edu.co | E6: LINA PAOLA GARCIA MALAGON | I6: Lina\ Paola\ García\ Malagón | J6: 0 | L6: 1075687506 | M6: 0 | O6: 25 a 30 | P6: 0 | R6: 3008450551 | S6: 0 | U6: 2024 | V6: 0 | X6: Geomtatica | Y6: 0 | AA6: Profundización | AB6: 0 | AD6: Análisis espacial - Geomática - Gestión del Riesgo | AE6: 0 | AG6: Si | AH6: 0 | AJ6: La\ incorporación\ de\ este\ idioma\ en\ una\ asignatura\ sería\ impor\tan te\ porque\ promoveria\ la\ práctica\ de\ este\ idioma\ que\ aportaría\ a\ que\ en\ la\ vida\ academica\ y\ profesional\ se\ tenga\ mejor\ manejo\ de\ este\ como\ segundo\ idioma | AK6: 0 | AM6: De acuerdo. | AN6: 0 | AP6: Participe en el Seminario en IA y Machine Learning - Posgrado Fac. Ingeniería U. Distrital y aporto bastante a mi curso de big data y al entendimiento de la inteligencia artificial y su importancia, también participe en el reto de desarrolladores el cual tuvo un nivel alto y se pudieron aplicar diversos conocimientos obtenidos a lo largo de la Maestría para brindar una solución. | AQ6: 0 | AS6: Totalmente de acuerdo. | AT6: 0 | AV6: Tal vez enviarlos por medio como el Grupo de Whatsapp en formatos como infografías | AW6: 0 | AY6: Totalmente de acuerdo. | AZ6: 0 | BB6: Me parece que la aplicación de estímulos y apoyos socioeconómicos que maneja son adecuados y de conocimiento para todo aquel que quiera optar por realizar la MCIC | BC6: 0 | BE6: Totalmente de acuerdo. | BF6: 0 | BH6: Totalmente de acuerdo. | BI6: 0 | BK6: De acuerdo. | BL6: 0 | BN6: Opte por elegir como electiva Big data en donde vimos temas de inteligencia artifical que actualmente es un tema de ínteres en el mundo al igual que en la vida profesional esta asignatura me permitió entender de una mejor manera los conceptos que muchas veces son aplicado en mi trabajo. | BO6: 0 | BQ6: Adecuada y pertinente | BR6: 0 | BT6: Totalmente de acuerdo. | BU6: 0 | BW6: Totalmente de acuerdo. | BX6: 0 | BZ6: De acuerdo. | CA6: 0 | CC6: De acuerdo. | CD6: 0 | CF6: Ni en acuerdo, ni en desacuerdo. | CG6: 0 | CI6: Tengo conocimiento que actualmente se esta manejando algunos proyectos con el IGAC, para una colaboración interinstitucional. | CJ6: 0 | CL6: De acuerdo. | CM6: 0 | CO6: El reto de desarrolladores de Esri. | CP6: 0 | CR6: De acuerdo. | CS6: 0 | CU6: De acuerdo. | CV6: 0 | CX6: Totalmente de acuerdo. | CY6: 0 | DA6: Sí. | DB6: 0 | DD6: Totalmente de acuerdo. | DE6: 0 | DG6: Totalmente en desacuerdo. | DH6: 0 | DJ6: De acuerdo. | DK6: 0 | DM6: Totalmente de acuerdo. | DN6: 0 | DP6: Totalmente de acuerdo. | DQ6: 0 | DS6: Sector público (administración pública, gobierno) | DT6: 0 | DV6: Totalmente de acuerdo. | DW6: 0 | DY6: Totalmente de acuerdo. | DZ6: 0 | EB6: Instituto Geográfico Agustín Codazzi | EC6: 0 | EE6: Johan Andres Avendaño Arias - johan.avendano@igac.gov.co | EF6: 0
A7: 5 | B7: 45720.287 | C7: 45720.299 | D7: jgonzalezs@udistrital.edu.co | E7: JHONATAN GONZALEZ SALGUERO | I7: JHONATAN\ GONZALEZ\ SALGUERO | J7: 0 | L7: 1024486322 | M7: 0 | O7: 31 a 40 | P7: 0 | R7: 3153934467 | S7: 0 | U7: 2024 | V7: 0 | X7: Geomtatica | Y7: 0 | AA7: Profundización | AB7: 0 | AD7: Machine learning | AE7: 0 | AG7: Si | AH7: 0 | AJ7: Al\ ser\ una\ materia\ impratida\ en\ inglés,\ se\ podría\ aprender\ mucho\ vocabulario\ técnico\ acorde\ a\ la\ carrea,\ a\lg o\ que\ no\ se\ ve\ en\ cursos\ normales\ de\ inglés | AK7: 0 | AM7: Ni en acuerdo, ni en desacuerdo. | AN7: 0 | AP7: Ninguna | AQ7: 0 | AS7: De acuerdo. | AT7: 0 | AV7: Podría ser en la materia de seminario de investigación dedicarle una clase inicial a reforzar esto | AW7: 0 | AY7: Ni en acuerdo, ni en desacuerdo. | AZ7: 0 | BB7: Una mayor divulgación de los mismos de manera frecuente | BC7: 0 | BE7: De acuerdo. | BF7: 0 | BH7: De acuerdo. | BI7: 0 | BK7: Ni en acuerdo, ni en desacuerdo. | BL7: 0 | BN7: Ninguna | BO7: 0 | BQ7: Muy buena | BR7: 0 | BT7: De acuerdo. | BU7: 0 | BW7: De acuerdo. | BX7: 0 | BZ7: De acuerdo. | CA7: 0 | CC7: De acuerdo. | CD7: 0 | CF7: Ni en acuerdo, ni en desacuerdo. | CG7: 0 | CI7: No tengo ningún ejemplo | CJ7: 0 | CL7: De acuerdo. | CM7: 0 | CO7: Conferencias sobre inteligencia artificial hechas en la universidad | CP7: 0 | CR7: De acuerdo. | CS7: 0 | CU7: De acuerdo. | CV7: 0 | CX7: Ni en acuerdo, ni en desacuerdo. | CY7: 0 | DA7: No. | DB7: 0 | DD7: Ni en acuerdo, ni en desacuerdo. | DE7: 0 | DG7: En desacuerdo. | DH7: 0 | DJ7: Ni en acuerdo, ni en desacuerdo. | DK7: 0 | DM7: De acuerdo. | DN7: 0 | DP7: Ni en acuerdo, ni en desacuerdo. | DQ7: 0 | DS7: Sector público (administración pública, gobierno) | DT7: 0 | DV7: Ni en acuerdo, ni en desacuerdo. | DW7: 0 | DY7: En desacuerdo. | DZ7: 0 | EB7: UT CATASTRO MULTIPROPOSITO | EC7: 0 | EE7: CARLOS ARTURO CASTELLANOS CASTILLO - 3002324325 | EF7: 0
A8: 6 | B8: 45720.497 | C8: 45720.549 | D8: fzubietac@udistrital.edu.co | E8: FERNANDO ZUBIETA CORTES | I8: Fernando Zubieta | J8: 0 | L8: 1033798653 | M8: 0 | O8: 25 a 30 | P8: 0 | R8: 3194467960 | S8: 0 | U8: 2024 | V8: 0 | X8: Geomtatica | Y8: 0 | AA8: Profundización | AB8: 0 | AD8: Geomática, Economía, SIG | AE8: 0 | AG8: Si | AH8: 0 | AJ8: Ayuda a mejorar la práctica y la dialéctica del idioma | AK8: 0 | AM8: Ni en acuerdo, ni en desacuerdo. | AN8: 0 | AP8: No he participado en el momento | AQ8: 0 | AS8: Ni en acuerdo, ni en desacuerdo. | AT8: 0 | AV8: Mejorar los canales de comunicación del programa | AW8: 0 | AY8: De acuerdo. | AZ8: 0 | BB8: Analizar los datos sociodemográficos de los aspirantes para generar matrículas más justas y acordes con la realidad económica de la población, ésto aumentaría el nivel de cobertura en posgrado | BC8: 0 | BE8: Totalmente de acuerdo. | BF8: 0 | BH8: Totalmente de acuerdo. | BI8: 0 | BK8: Ni en acuerdo, ni en desacuerdo. | BL8: 0 | BN8: No conozco rutas de formación alternativas del programa | BO8: 0 | BQ8: Acorde con la estructura tecnológica del mercado laboral | BR8: 0 | BT8: De acuerdo. | BU8: 0 | BW8: Ni en acuerdo, ni en desacuerdo. | BX8: 0 | BZ8: Ni en acuerdo, ni en desacuerdo. | CA8: 0 | CC8: De acuerdo. | CD8: 0 | CF8: Ni en acuerdo, ni en desacuerdo. | CG8: 0 | CI8: No conozco éste tipo de cooperaciones | CJ8: 0 | CL8: Totalmente de acuerdo. | CM8: 0 | CO8: Innovación del conocimiento | CP8: 0 | CR8: Ni en acuerdo, ni en desacuerdo. | CS8: 0 | CU8: En desacuerdo. | CV8: 0 | CX8: De acuerdo. | CY8: 0 | DA8: No sabe/ No responde. | DB8: 0 | DD8: Totalmente de acuerdo. | DE8: 0 | DG8: Ni en acuerdo, ni en desacuerdo. | DH8: 0 | DJ8: En desacuerdo. | DK8: 0 | DM8: De acuerdo. | DN8: 0 | DP8: Ni en acuerdo, ni en desacuerdo. | DQ8: 0 | DS8: Tecnología (desarrollo de software, IA, ciberseguridad, telecomunicaciones) | DT8: 0 | DV8: De acuerdo. | DW8: 0 | DY8: Ni en acuerdo, ni en desacuerdo. | DZ8: 0 | EB8: Simón Movilidad | EC8: 0 | EE8: No puedo dar esa información | EF8: 0
A9: 7 | B9: 45720.572 | C9: 45720.583 | D9: jecaicedon@udistrital.edu.co | E9: EDUARDO NAVARRO JOAQUIN | I9: Joaquin\ Eduardo\ Caicedo\ Navarro | J9: 0 | L9: 1024481940 | M9: 0 | O9: 31 a 40 | P9: 0 | R9: 3232898653 | S9: 0 | U9: 2020 | V9: 0 | X9: Ingeniería de Software | Y9: 0 | AA9: Investigación | AB9: 0 | AD9: Calidad de potencia, Inteligencia Artificial | AE9: 0 | AG9: Si | AH9: 0 | AJ9: Mejor\ prepararacion\ para\ trabajar\ en\ empresas\ extranjeras | AK9: 0 | AM9: Totalmente de acuerdo. | AN9: 0 | AP9: Preparación y publicación de artículos científicos. Me ha formado como investigador | AQ9: 0 | AS9: Ni en acuerdo, ni en desacuerdo. | AT9: 0 | AV9: No | AW9: 0 | AY9: Totalmente de acuerdo. | AZ9: 0 | BB9: Mayor divulgación de los posibles beneficios | BC9: 0 | BE9: De acuerdo. | BF9: 0 | BH9: De acuerdo. | BI9: 0 | BK9: Totalmente de acuerdo. | BL9: 0 | BN9: He podido participar en materias diversas, como por ejemplo, en diferentes áreas de inteligencia artificial | BO9: 0 | BQ9: Los énfasis son efectivos | BR9: 0 | BT9: De acuerdo. | BU9: 0 | BW9: De acuerdo. | BX9: 0 | BZ9: De acuerdo. | CA9: 0 | CC9: De acuerdo. | CD9: 0 | CF9: Totalmente de acuerdo. | CG9: 0 | CI9: Convocatorias de la ODI para llevar a cabo participación en conferencias académicas | CJ9: 0 | CL9: Totalmente de acuerdo. | CM9: 0 | CO9: Desarrollo de artículos de investigación como parte de la evaluación en materias como Bases de Datos, Inteligencia Computacional, Minería de datos, etc. Proyectos integradores como en las materias Tendencias en ingeniería de software y Computación en la nube | CP9: 0 | CR9: De acuerdo. | CS9: 0 | CU9: De acuerdo. | CV9: 0 | CX9: Totalmente de acuerdo. | CY9: 0 | DA9: No sabe/ No responde. | DB9: 0 | DD9: Totalmente de acuerdo. | DE9: 0 | DG9: Ni en acuerdo, ni en desacuerdo. | DH9: 0 | DJ9: De acuerdo. | DK9: 0 | DM9: Totalmente de acuerdo. | DN9: 0 | DP9: De acuerdo. | DQ9: 0 | DS9: Sector secundario (industria manufacturera, construcción, energía) | DT9: 0 | DV9: Totalmente de acuerdo. | DW9: 0 | DY9: Totalmente de acuerdo. | DZ9: 0 | EB9: Empresa de Energía de San Andrés | EC9: 0 | EE9: Wilmar Moreno (Supervisor de contrato). Email: consultenergy2021@gmail.com | EF9: 0
A10: 8 | B10: 45721.448 | C10: 45721.462 | D10: juamgarzong@udistrital.edu.co | E10: JUAN MANUEL GARZON GIL | I10: Juan\ Manuel\ Garzón\ Gil | J10: 0 | L10: 1014263322 | M10: 0 | O10: 25 a 30 | P10: 0 | R10: 3138717415 | S10: 0 | U10: 2025 | V10: 0 | X10: Geomtatica | Y10: 0 | AA10: Profundización | AB10: 0 | AD10: Calidad del aire, imágenes satelitales, vegetación urbana, ordenamiento territorial | AE10: 0 | AG10: No | AH10: 0 | AJ10: Abre\ as\ purts\ a\ un\ comercio\ internacional,\ también\ mejora\ el\ acceso\ a\ ayor\ \inf ormación\ ya\ que\ la\ comundad\ y\ los\ recursos\ es\tan\ en\ ese\ idioma | AK10: 0 | AM10: De acuerdo. | AN10: 0 | AP10: Trabaje en mi proyecto de grado en la modalidad de investigación e innovación, esta fue patrocinada por minciencias, me ayudo en procesos de redacción, manejo de datos, sustentación de hallazgos, adquisición de conocimiento en un área especifica. | AQ10: 0 | AS10: De acuerdo. | AT10: 0 | AV10: No | AW10: 0 | AY10: Ni en acuerdo, ni en desacuerdo. | AZ10: 0 | BB10: Mejorar la divulgación y que los tiempos para aplicar sean coherentes con dicha divulgación | BC10: 0 | BE10: De acuerdo. | BF10: 0 | BH10: De acuerdo. | BI10: 0 | BK10: Ni en acuerdo, ni en desacuerdo. | BL10: 0 | BN10: No tengo mayor conocimiento sobre este tema | BO10: 0 | BQ10: Considero que son adecuados. | BR10: 0 | BT10: De acuerdo. | BU10: 0 | BW10: Totalmente de acuerdo. | BX10: 0 | BZ10: De acuerdo. | CA10: 0 | CC10: De acuerdo. | CD10: 0 | CF10: Ni en acuerdo, ni en desacuerdo. | CG10: 0 | CI10: Al momento no | CJ10: 0 | CL10: Totalmente de acuerdo. | CM10: 0 | CO10: Hasta el momento solo en clases, donde la forma de exponer los temas e interactuar con los estudiantes, fomenta un pensamiento diferente sobre los temas que se ven y permiten el pensar variables para los métodos expuestos | CP10: 0 | CR10: Ni en acuerdo, ni en desacuerdo. | CS10: 0 | CU10: De acuerdo. | CV10: 0 | CX10: En desacuerdo. | CY10: 0 | DA10: No sabe/ No responde. | DB10: 0 | DD10: De acuerdo. | DE10: 0 | DG10: Ni en acuerdo, ni en desacuerdo. | DH10: 0 | DJ10: De acuerdo. | DK10: 0 | DM10: De acuerdo. | DN10: 0 | DP10: De acuerdo. | DQ10: 0 | DS10: Tecnología (desarrollo de software, IA, ciberseguridad, telecomunicaciones) | DT10: 0 | DV10: De acuerdo. | DW10: 0 | DY10: Ni en acuerdo, ni en desacuerdo. | DZ10: 0 | EB10: ETB | EC10: 0 | EE10: No me es posible | EF10: 0
A11: 9 | B11: 45721.765 | C11: 45721.771 | D11: sforeroz@udistrital.edu.co | E11: SEBASTIAN FORERO ZAPATA | I11: SEBASTIAN FORERO ZAPATA | J11: 0 | L11: 1000514921 | M11: 0 | O11: 25 a 30 | P11: 0 | R11: 3194970523 | S11: 0 | U11: 2024 | V11: 0 | X11: Geomtatica | Y11: 0 | AA11: Investigación | AB11: 0 | AD11: INTELIGENCIA ARTIFICIAL | AE11: 0 | AG11: Si | AH11: 0 | AJ11: MEJORAR IDIOMA Y ACCEDER A MEJORES OPORTUNIDADES | AK11: 0 | AM11: De acuerdo. | AN11: 0 | AP11: CHARLAS, HACKATONES, WEBINAR. AYUDAN A MEJORAR HABILIDADES TEORICAS Y TECNICAS | AQ11: 0 | AS11: De acuerdo. | AT11: 0 | AV11: NO | AW11: 0 | AY11: De acuerdo. | AZ11: 0 | BB11: INCENTIVO PERMANENCIA O APOYO | BC11: 0 | BE11: De acuerdo. | BF11: 0 | BH11: De acuerdo. | BI11: 0 | BK11: De acuerdo. | BL11: 0 | BN11: DANDO MAS OPCIONES DE MEJORA ACADEMICA | BO11: 0 | BQ11: DE ACUERDO CON LAS NECESIDADES DEL MERCADO ACTUALMENTE | BR11: 0 | BT11: De acuerdo. | BU11: 0 | BW11: De acuerdo. | BX11: 0 | BZ11: De acuerdo. | CA11: 0 | CC11: De acuerdo. | CD11: 0 | CF11: De acuerdo. | CG11: 0 | CI11: NINGUNA | CJ11: 0 | CL11: De acuerdo. | CM11: 0 | CO11: PARTICIPACION EN TALLERES CHARLAS | CP11: 0 | CR11: De acuerdo. | CS11: 0 | CU11: De acuerdo. | CV11: 0 | CX11: De acuerdo. | CY11: 0 | DA11: Sí. | DB11: 0 | DD11: De acuerdo. | DE11: 0 | DG11: De acuerdo. | DH11: 0 | DJ11: De acuerdo. | DK11: 0 | DM11: De acuerdo. | DN11: 0 | DP11: De acuerdo. | DQ11: 0 | DS11: Tecnología (desarrollo de software, IA, ciberseguridad, telecomunicaciones) | DT11: 0 | DV11: De acuerdo. | DW11: 0 | DY11: Ni en acuerdo, ni en desacuerdo. | DZ11: 0 | EB11: ESRI COLOMBIA | EC11: 0 | EE11: DEIRO GONZALEZ | EF11: 0
A12: 10 | B12: 45721.765 | C12: 45721.776 | D12: jeahernandezn@udistrital.edu.co | E12: ANDRES NAVARRETE JEISSON | I12: JEISSON\ ANDRES\ HERNANDEZ\ NAVARRETE | J12: 0 | L12: 1014298952 | M12: 0 | O12: 25 a 30 | P12: 0 | R12: 3209190949 | S12: 0 | U12: 2024 | V12: 0 | X12: Geomtatica | Y12: 0 | AA12: Investigación | AB12: 0 | AD12: Procesamiento digital de imágenes, análisis espacial, series de tiempo | AE12: 0 | AG12: Si | AH12: 0 | AJ12: Una\ asignatura\ en\ inglés\ puede\ ayudar\ a\ reforzar\ la\ comprensión\ y\ producción\ de\ conocimiento\ científico\ y\ preparar\ para\ posibles\ estudios\ posteriores. | AK12: 0 | AM12: Totalmente de acuerdo. | AN12: 0 | AP12: El desarrollo del proyecto de grado como actividad transversal al desarrollo de la maestría permite tomar los temas impartidos en las asignaturas desde un punto de vista mas crítico y enriquecedor por el lado de la investigación propia | AQ12: 0 | AS12: Totalmente de acuerdo. | AT12: 0 | AV12: No | AW12: 0 | AY12: Totalmente de acuerdo. | AZ12: 0 | BB12: NA | BC12: 0 | BE12: Totalmente de acuerdo. | BF12: 0 | BH12: Totalmente de acuerdo. | BI12: 0 | BK12: Totalmente de acuerdo. | BL12: 0 | BN12: La posibilidad de tomar asignaturas electivas de otro énfasis permite ampliar el horizonte de conocimientos e intentar aplicar metodologías diferentes para el análisis de información laboral y académica | BO12: 0 | BQ12: Desde el énfasis de geomática se obtienen conocimientos que aplican para el desarrollo de proyectos por fuera del contexto académico | BR12: 0 | BT12: De acuerdo. | BU12: 0 | BW12: De acuerdo. | BX12: 0 | BZ12: Ni en acuerdo, ni en desacuerdo. | CA12: 0 | CC12: Totalmente de acuerdo. | CD12: 0 | CF12: De acuerdo. | CG12: 0 | CI12: La participación en el reto de desarrolladores de ESRI | CJ12: 0 | CL12: De acuerdo. | CM12: 0 | CO12: El desarrollo del proyecto de grado de la maestría | CP12: 0 | CR12: Ni en acuerdo, ni en desacuerdo. | CS12: 0 | CU12: De acuerdo. | CV12: 0 | CX12: Ni en acuerdo, ni en desacuerdo. | CY12: 0 | DA12: Sí. | DB12: 0 | DD12: De acuerdo. | DE12: 0 | DG12: En desacuerdo. | DH12: 0 | DJ12: Totalmente de acuerdo. | DK12: 0 | DM12: Totalmente de acuerdo. | DN12: 0 | DP12: De acuerdo. | DQ12: 0 | DS12: Sector terciario (comercio, servicios: educación, salud, finanzas, etc.) | DT12: 0 | DV12: De acuerdo. | DW12: 0 | DY12: Ni en acuerdo, ni en desacuerdo. | DZ12: 0 | EB12: GEOS SAS | EC12: 0 | EE12: NA | EF12: 0
A13: 11 | B13: 45721.767 | C13: 45721.776 | D13: cisancheza@udistrital.edu.co | E13: CARLOS IVAN SANCHEZ ARIZA | I13: Carlos Ivan Sanchez Ariza | J13: 0 | L13: 1022377565 | M13: 0 | O13: 31 a 40 | P13: 0 | R13: 3013997773 | S13: 0 | U13: 2024 | V13: 0 | X13: Geomtatica | Y13: 0 | AA13: Profundización | AB13: 0 | AD13: Geomatica | AE13: 0 | AG13: No | AH13: 0 | AJ13: Familiarizacion con el idioma | AK13: 0 | AM13: Ni en acuerdo, ni en desacuerdo. | AN13: 0 | AP13: En impacto ambiental | AQ13: 0 | AS13: Ni en acuerdo, ni en desacuerdo. | AT13: 0 | AV13: Ninguna | AW13: 0 | AY13: De acuerdo. | AZ13: 0 | BB13: Ninguna | BC13: 0 | BE13: Ni en acuerdo, ni en desacuerdo. | BF13: 0 | BH13: Ni en acuerdo, ni en desacuerdo. | BI13: 0 | BK13: Ni en acuerdo, ni en desacuerdo. | BL13: 0 | BN13: No se entiende la pregunta | BO13: 0 | BQ13: Acertada | BR13: 0 | BT13: En desacuerdo. | BU13: 0 | BW13: Ni en acuerdo, ni en desacuerdo. | BX13: 0 | BZ13: En desacuerdo. | CA13: 0 | CC13: De acuerdo. | CD13: 0 | CF13: Ni en acuerdo, ni en desacuerdo. | CG13: 0 | CI13: modelo dinámico para analizar los factores ambientales y antropogenicos en el páramo de chingaza | CJ13: 0 | CL13: De acuerdo. | CM13: 0 | CO13: En mi proyecto de grado: modelo dinámico para analizar los factores ambientales y antropogenicos en el páramo de chingaza | CP13: 0 | CR13: En desacuerdo. | CS13: 0 | CU13: Ni en acuerdo, ni en desacuerdo. | CV13: 0 | CX13: En desacuerdo. | CY13: 0 | DA13: No sabe/ No responde. | DB13: 0 | DD13: De acuerdo. | DE13: 0 | DG13: Ni en acuerdo, ni en desacuerdo. | DH13: 0 | DJ13: De acuerdo. | DK13: 0 | DM13: Ni en acuerdo, ni en desacuerdo. | DN13: 0 | DP13: Ni en acuerdo, ni en desacuerdo. | DQ13: 0 | DS13: Otro | DT13: 0 | DV13: Ni en acuerdo, ni en desacuerdo. | DW13: 0 | DY13: Ni en acuerdo, ni en desacuerdo. | DZ13: 0 | EB13: IGAC | EC13: 0 | EE13: Recién entré entonces no tengo contacto con la persona encargada | EF13: 0
A14: 12 | B14: 45721.766 | C14: 45721.778 | D14: rvcastroa@udistrital.edu.co | E14: RUSBY VANESSA CASTRO ALFEREZ | I14: Rusby\ Vanessa\ Castro\ Alferez | J14: 0 | L14: 1030683963 | M14: 0 | O14: 25 a 30 | P14: 0 | R14: 3196297112 | S14: 0 | U14: 2024 | V14: 0 | X14: Geomtatica | Y14: 0 | AA14: Profundización | AB14: 0 | AD14: estadística, econometría | AE14: 0 | AG14: Si | AH14: 0 | AJ14: podria\ afianzar\ mis\ conocimientos\ en\ el\ idioma | AK14: 0 | AM14: Totalmente de acuerdo. | AN14: 0 | AP14: La realización de artículos de investigación en cada una de las asignaturas de la maestría con el fin de reforzar y crear conocimientos en el estudiante. | AQ14: 0 | AS14: De acuerdo. | AT14: 0 | AV14: teniendo un canal de difusión actualizado | AW14: 0 | AY14: En desacuerdo. | AZ14: 0 | BB14: No poner un limite en las notas de los estudiantes ya que muchos no cuentan con los recursos y tienen que desertar la carrera por ello | BC14: 0 | BE14: De acuerdo. | BF14: 0 | BH14: De acuerdo. | BI14: 0 | BK14: Totalmente en desacuerdo. | BL14: 0 | BN14: Quizás faltan oferta de espacios académicos de acuerdo a los énfasis de cada estudiante. | BO14: 0 | BQ14: Ayuda a enfocar al estudiante en un área de interés, sin embargo es bueno que se oferten mas electivas de acuerdo al énfasis escogido | BR14: 0 | BT14: Ni en acuerdo, ni en desacuerdo. | BU14: 0 | BW14: De acuerdo. | BX14: 0 | BZ14: De acuerdo. | CA14: 0 | CC14: De acuerdo. | CD14: 0 | CF14: Ni en acuerdo, ni en desacuerdo. | CG14: 0 | CI14: No he evidenciado estos ejemplos | CJ14: 0 | CL14: De acuerdo. | CM14: 0 | CO14: La realización de papers y artículos científicos en cada una de las asignaturas | CP14: 0 | CR14: De acuerdo. | CS14: 0 | CU14: De acuerdo. | CV14: 0 | CX14: Ni en acuerdo, ni en desacuerdo. | CY14: 0 | DA14: Sí. | DB14: 0 | DD14: Totalmente de acuerdo. | DE14: 0 | DG14: Ni en acuerdo, ni en desacuerdo. | DH14: 0 | DJ14: De acuerdo. | DK14: 0 | DM14: En desacuerdo. | DN14: 0 | DP14: De acuerdo. | DQ14: 0 | DS14: Otro | DT14: 0 | DV14: De acuerdo. | DW14: 0 | DY14: En desacuerdo. | DZ14: 0 | EB14: No cuento con empleo actualmente | EC14: 0 | EE14: No cuento con empleo actualmente | EF14: 0
... A45: 43 | B45: 45724.301 | C45: 45724.312 | D45: gleonc@udistrital.edu.co | E45: CELIS GABRIELA | I45: Gabriela León Celis | J45: 0 | L45: 1031170176 | M45: 0 | O45: 25 a 30 | P45: 0 | R45: 3185208646 | S45: 0 | U45: 2024 | V45: 0 | X45: Ingeniería de Software | Y45: 0 | AA45: Investigación | AB45: 0 | AD45: Bioingenieria, Machine Learning, Arquitectura | AE45: 0 | AG45: No | AH45: 0 | AJ45: Aprendiendo en los conceptos base de la materia y permitiendo expresarme mejor en esos términos | AK45: 0 | AM45: De acuerdo. | AN45: 0 | AP45: He participado en grupos de investigación y realizando productos científicos donde he aprendido a pulir mis habilidades de comunicación | AQ45: 0 | AS45: Ni en acuerdo, ni en desacuerdo. | AT45: 0 | AV45: N/A | AW45: 0 | AY45: De acuerdo. | AZ45: 0 | BB45: N/A | BC45: 0 | BE45: De acuerdo. | BF45: 0 | BH45: De acuerdo. | BI45: 0 | BK45: De acuerdo. | BL45: 0 | BN45: He potenciado mi entendimiento y desarrollo profesional en la comunicación en mi trabajo | BO45: 0 | BQ45: N/A | BR45: 0 | BT45: De acuerdo. | BU45: 0 | BW45: De acuerdo. | BX45: 0 | BZ45: De acuerdo. | CA45: 0 | CC45: De acuerdo. | CD45: 0 | CF45: De acuerdo. | CG45: 0 | CI45: N/A | CJ45: 0 | CL45: De acuerdo. | CM45: 0 | CO45: N\A | CP45: 0 | CR45: De acuerdo. | CS45: 0 | CU45: De acuerdo. | CV45: 0 | CX45: De acuerdo. | CY45: 0 | DA45: Sí. | DB45: 0 | DD45: De acuerdo. | DE45: 0 | DG45: De acuerdo. | DH45: 0 | DJ45: De acuerdo. | DK45: 0 | DM45: De acuerdo. | DN45: 0 | DP45: De acuerdo. | DQ45: 0 | DS45: Tecnología (desarrollo de software, IA, ciberseguridad, telecomunicaciones) | DT45: 0 | DV45: Ni en acuerdo, ni en desacuerdo. | DW45: 0 | DY45: Ni en acuerdo, ni en desacuerdo. | DZ45: 0 | EB45: Banco de Bogotá | EC45: 0 | EE45: Andrés Guzmán: AGUZMAN7@BANCODEBOGOTA.COM.CO | EF45: 0
A46: 44 | B46: 45724.3 | C46: 45724.313 | D46: erhiguerav@udistrital.edu.co | E46: RICARDO VILLALBA ESTEBAN | I46: Esteban\ Ricardo\ Higuera\ Villalba | J46: 0 | L46: 1032457392 | M46: 0 | O46: 31 a 40 | P46: 0 | R46: 3106291488 | S46: 0 | U46: 2024 | V46: 0 | X46: Inteligencia Artificial | Y46: 0 | AA46: Investigación | AB46: 0 | AD46: Machine Learning, Deep Learning, Medio Ambiente | AE46: 0 | AG46: Si | AH46: 0 | AJ46: Identificación de términos técnicos del área. | AK46: 0 | AM46: De acuerdo. | AN46: 0 | AP46: Presentación de proyectos y socialización del algunos avances del proyecto de grado. Habilidades blandas. | AQ46: 0 | AS46: De acuerdo. | AT46: 0 | AV46: NA | AW46: 0 | AY46: De acuerdo. | AZ46: 0 | BB46: NA | BC46: 0 | BE46: Totalmente de acuerdo. | BF46: 0 | BH46: Totalmente de acuerdo. | BI46: 0 | BK46: Totalmente de acuerdo. | BL46: 0 | BN46: Cómo docente universitario me ha permitido ampliar el contenido temático con los estudiantes y profundizar en áreas de aplicación | BO46: 0 | BQ46: En el caso de Inteligencia Artificial, considero que es pertinente. | BR46: 0 | BT46: Totalmente de acuerdo. | BU46: 0 | BW46: Totalmente de acuerdo. | BX46: 0 | BZ46: Totalmente de acuerdo. | CA46: 0 | CC46: Totalmente de acuerdo. | CD46: 0 | CF46: Totalmente de acuerdo. | CG46: 0 | CI46: NA | CJ46: 0 | CL46: Totalmente de acuerdo. | CM46: 0 | CO46: Actividades de elaboración de propuesta de investigación. | CP46: 0 | CR46: Totalmente de acuerdo. | CS46: 0 | CU46: Totalmente de acuerdo. | CV46: 0 | CX46: Totalmente de acuerdo. | CY46: 0 | DA46: Sí. | DB46: 0 | DD46: Totalmente de acuerdo. | DE46: 0 | DG46: De acuerdo. | DH46: 0 | DJ46: Totalmente de acuerdo. | DK46: 0 | DM46: Totalmente de acuerdo. | DN46: 0 | DP46: Totalmente de acuerdo. | DQ46: 0 | DS46: Sector terciario (comercio, servicios: educación, salud, finanzas, etc.) | DT46: 0 | DV46: Totalmente de acuerdo. | DW46: 0 | DY46: Ni en acuerdo, ni en desacuerdo. | DZ46: 0 | EB46: Fundación Universitaria Compensar | EC46: 0 | EE46: 3114273516 | EF46: 0
A47: 45 | B47: 45724.302 | C47: 45724.316 | D47: vdsanchezm@udistrital.edu.co | E47: VIVIAN DANIELA SANCHEZ MONTA�A | I47: Vivian Daniela Sánchez montaña | J47: 0 | L47: 1014294978 | M47: 0 | O47: 25 a 30 | P47: 0 | R47: 3103375466 | S47: 0 | U47: 2024 | V47: 0 | X47: Geomtatica | Y47: 0 | AA47: Investigación | AB47: 0 | AD47: SIG | AE47: 0 | AG47: Si | AH47: 0 | AJ47: Mejoraría mis habilidades en listening , lo cual es fundamental para mi trabajo | AK47: 0 | AM47: Totalmente de acuerdo. | AN47: 0 | AP47: Grupos de investigación, como la sociedad en percepción remota para America latina y el caribe - selper, donde puedo poner en marcha los conocimientos queridos en la maestría | AQ47: 0 | AS47: De acuerdo. | AT47: 0 | AV47: Continuar con la difusión de botines, noticias, ofertas de trabajo y demás a traves del r electrónico | AW47: 0 | AY47: De acuerdo. | AZ47: 0 | BB47: Mayor difusión de oportunidades por el correo y grupo de WhatsApp | BC47: 0 | BE47: De acuerdo. | BF47: 0 | BH47: De acuerdo. | BI47: 0 | BK47: De acuerdo. | BL47: 0 | BN47: La flexibilidad en los horarios, si se puede dar continuidad a la vida laboral | BO47: 0 | BQ47: Permite profundizar adecuadamente en los intereses del estudiante, adicionalmente, al de posible interactuar con estudiantes de otros énfasis mejorando los intereses académicos e investigativos | BR47: 0 | BT47: De acuerdo. | BU47: 0 | BW47: De acuerdo. | BX47: 0 | BZ47: De acuerdo. | CA47: 0 | CC47: De acuerdo. | CD47: 0 | CF47: Ni en acuerdo, ni en desacuerdo. | CG47: 0 | CI47: Durante la clase de big data, uno de los docentes nos invitó a foros donde se discutió el avance de la inteligencia artificial con múltiples académicos internacionales | CJ47: 0 | CL47: De acuerdo. | CM47: 0 | CO47: Para solucionar proyectos en mi trabajo enfocados a big data | CP47: 0 | CR47: De acuerdo. | CS47: 0 | CU47: De acuerdo. | CV47: 0 | CX47: De acuerdo. | CY47: 0 | DA47: Sí. | DB47: 0 | DD47: De acuerdo. | DE47: 0 | DG47: Ni en acuerdo, ni en desacuerdo. | DH47: 0 | DJ47: En desacuerdo. | DK47: 0 | DM47: De acuerdo. | DN47: 0 | DP47: De acuerdo. | DQ47: 0 | DS47: Tecnología (desarrollo de software, IA, ciberseguridad, telecomunicaciones) | DT47: 0 | DV47: Totalmente de acuerdo. | DW47: 0 | DY47: De acuerdo. | DZ47: 0 | EB47: Esri colombia | EC47: 0 | EE47: Paola barón - pbaron@esri.co | EF47: 0
A48: 46 | B48: 45724.298 | C48: 45724.326 | D48: jucpenav@udistrital.edu.co | E48: JOAN CAMILO PENA VILLAMIL | I48: Joan\ Camilo\ Peña\ Villamil | J48: 0 | L48: 1022432262 | M48: 0 | O48: 25 a 30 | P48: 0 | R48: 3133851772 | S48: 0 | U48: 2024 | V48: 0 | X48: Teleinformatica | Y48: 0 | AA48: Investigación | AB48: 0 | AD48: Antenas | AE48: 0 | AG48: Si | AH48: 0 | AJ48: Me\ permitiria\ mejorar\ mi\ nivel\ de\ ingles\ y\ evaluar\ que\ \tan\ preparado\ estoy\ para\ afrontar\ otro\ tipo\ de\ eventos\ academi\cos\ en\ ese\ idioma\ | AK48: 0 | AM48: Ni en acuerdo, ni en desacuerdo. | AN48: 0 | AP48: no he participado en ninguna. | AQ48: 0 | AS48: De acuerdo. | AT48: 0 | AV48: No | AW48: 0 | AY48: De acuerdo. | AZ48: 0 | BB48: Realizar actividades de divulgación en donde se de la información personalmente a los estudiantes | BC48: 0 | BE48: Totalmente de acuerdo. | BF48: 0 | BH48: De acuerdo. | BI48: 0 | BK48: Ni en acuerdo, ni en desacuerdo. | BL48: 0 | BN48: no | BO48: 0 | BQ48: Es buena ya que permite profundizar en los diferentes énfasis y son muy pertinentes en el campo laboral. | BR48: 0 | BT48: De acuerdo. | BU48: 0 | BW48: De acuerdo. | BX48: 0 | BZ48: Ni en acuerdo, ni en desacuerdo. | CA48: 0 | CC48: Ni en acuerdo, ni en desacuerdo. | CD48: 0 | CF48: Ni en acuerdo, ni en desacuerdo. | CG48: 0 | CI48: no | CJ48: 0 | CL48: De acuerdo. | CM48: 0 | CO48: no | CP48: 0 | CR48: De acuerdo. | CS48: 0 | CU48: Ni en acuerdo, ni en desacuerdo. | CV48: 0 | CX48: De acuerdo. | CY48: 0 | DA48: No. | DB48: 0 | DD48: Totalmente de acuerdo. | DE48: 0 | DG48: Ni en acuerdo, ni en desacuerdo. | DH48: 0 | DJ48: Ni en acuerdo, ni en desacuerdo. | DK48: 0 | DM48: De acuerdo. | DN48: 0 | DP48: De acuerdo. | DQ48: 0 | DS48: Sector terciario (comercio, servicios: educación, salud, finanzas, etc.) | DT48: 0 | DV48: En desacuerdo. | DW48: 0 | DY48: En desacuerdo. | DZ48: 0 | EB48: Universidad Distrital Francisco José de Caldas | EC48: 0 | EE48: Edilberto Suarez Torres , Tel: 3005635286, Correo: esuarez@udistrital.edu.co | EF48: 0
A49: 47 | B49: 45724.407 | C49: 45724.427 | D49: jjbarbosap@udistrital.edu.co | E49: JHONATAN JOSE BARBOSA PEÑA | I49: JHONATAN\ JOSE\ BARBOSA\ PEÑA | J49: 0 | L49: 1031136781 | M49: 0 | O49: 31 a 40 | P49: 0 | R49: 3158026703 | S49: 0 | U49: 2017 | V49: 0 | X49: Geomtatica | Y49: 0 | AA49: Investigación | AB49: 0 | AD49: Sistemas de información geografica y gestión de riesgo | AE49: 0 | AG49: No | AH49: 0 | AJ49: Para\ practicar\ la\ segunda\ lengua\ de\ manera\ tecnica | AK49: 0 | AM49: Totalmente de acuerdo. | AN49: 0 | AP49: Simposios, charlas tecnicas | AQ49: 0 | AS49: Totalmente de acuerdo. | AT49: 0 | AV49: No | AW49: 0 | AY49: Totalmente de acuerdo. | AZ49: 0 | BB49: Mejor divulgación | BC49: 0 | BE49: De acuerdo. | BF49: 0 | BH49: Totalmente de acuerdo. | BI49: 0 | BK49: Totalmente de acuerdo. | BL49: 0 | BN49: En mi caso, me han beneficiado al brindarme la oportunidad de acceder a distintos recursos, como materiales en línea, clases asincrónicas y herramientas interactivas, lo que me ha permitido reforzar conceptos a mi propio ritmo | BO49: 0 | BQ49: Centrándome en el énfasis de geomática abarca áreas clave de la ingeniería y la tecnología con alta demanda en el mercado laboral. | BR49: 0 | BT49: Totalmente de acuerdo. | BU49: 0 | BW49: Totalmente de acuerdo. | BX49: 0 | BZ49: De acuerdo. | CA49: 0 | CC49: Ni en acuerdo, ni en desacuerdo. | CD49: 0 | CF49: Ni en acuerdo, ni en desacuerdo. | CG49: 0 | CI49: Conozco un proyecto de la implementación de la metodología fit for purpose el cual fue con apoyo del gobierno holandés | CJ49: 0 | CL49: De acuerdo. | CM49: 0 | CO49: Cómo decía con anterioridad un proyecto de la maestría traía conocimiento del exterior para la aplicación en Colombia | CP49: 0 | CR49: Ni en acuerdo, ni en desacuerdo. | CS49: 0 | CU49: De acuerdo. | CV49: 0 | CX49: De acuerdo. | CY49: 0 | DA49: No sabe/ No responde. | DB49: 0 | DD49: Ni en acuerdo, ni en desacuerdo. | DE49: 0 | DG49: Ni en acuerdo, ni en desacuerdo. | DH49: 0 | DJ49: Totalmente de acuerdo. | DK49: 0 | DM49: De acuerdo. | DN49: 0 | DP49: De acuerdo. | DQ49: 0 | DS49: Sector primario (agricultura, ganadería, pesca, minería) | DT49: 0 | DV49: De acuerdo. | DW49: 0 | DY49: De acuerdo. | DZ49: 0 | EB49: Unidad de planificación rural agropecuaria UPRA | EC49: 0 | EE49: Supervisor Carlos Moreno | EF49: 0
A50: 48 | B50: 45725.676 | C50: 45725.69 | D50: jasilvar@udistrital.edu.co | E50: JOSE ANTONIO SILVA ROJAS | I50: José\ Antonio\ Silva\ Rojas | J50: 0 | L50: 80742478 | M50: 0 | O50: 41 a 50 | P50: 0 | R50: 3006226021 | S50: 0 | U50: 2017 | V50: 0 | X50: Ingeniería de Software | Y50: 0 | AA50: Investigación | AB50: 0 | AD50: LLM, generative AI. | AE50: 0 | AG50: Si | AH50: 0 | AJ50: Al\ mejorar\ mis\ habilidades\ en\ el\ inglés,\ podría\ postularme\ a\ c\arg os\ con\ ese\ énfasis,\ aumen\tan do\ mis\ ingresos. | AK50: 0 | AM50: Totalmente de acuerdo. | AN50: 0 | AP50: Estuve participando en un grupo de investigación en Sennova, enfocado en IoT. Esto, me permitió trabajar con sistemas embebidos y de telecomunicaciones, enfocadas en la agricultura de precisión y energías renovables. Adquiriendo conocimiento en estas tecnologías. | AQ50: 0 | AS50: Totalmente de acuerdo. | AT50: 0 | AV50: No. | AW50: 0 | AY50: Totalmente de acuerdo. | AZ50: 0 | BB50: Concursos o retos por semestre para que exista una participación activa del estudiantado y así mismo, mejore la divulgación de los mismos. | BC50: 0 | BE50: De acuerdo. | BF50: 0 | BH50: Totalmente de acuerdo. | BI50: 0 | BK50: Ni en acuerdo, ni en desacuerdo. | BL50: 0 | BN50: No las tengo claras las rutas mencionadas. | BO50: 0 | BQ50: Buena. | BR50: 0 | BT50: De acuerdo. | BU50: 0 | BW50: De acuerdo. | BX50: 0 | BZ50: De acuerdo. | CA50: 0 | CC50: De acuerdo. | CD50: 0 | CF50: Ni en acuerdo, ni en desacuerdo. | CG50: 0 | CI50: Solo cuento con información suministradas en la socialización de grupos de investigación. | CJ50: 0 | CL50: De acuerdo. | CM50: 0 | CO50: Con el manejo de IoT y de IA, me facilitaron el ingreso a un grupo de investigación del Sena, en lo recorrido del año 2022. | CP50: 0 | CR50: De acuerdo. | CS50: 0 | CU50: Ni en acuerdo, ni en desacuerdo. | CV50: 0 | CX50: De acuerdo. | CY50: 0 | DA50: Sí. | DB50: 0 | DD50: Totalmente de acuerdo. | DE50: 0 | DG50: Ni en acuerdo, ni en desacuerdo. | DH50: 0 | DJ50: De acuerdo. | DK50: 0 | DM50: De acuerdo. | DN50: 0 | DP50: De acuerdo. | DQ50: 0 | DS50: Tecnología (desarrollo de software, IA, ciberseguridad, telecomunicaciones) | DT50: 0 | DV50: De acuerdo. | DW50: 0 | DY50: De acuerdo. | DZ50: 0 | EB50: IBM | EC50: 0 | EE50: Fabian David Gil. fabian.gil@ibm.com. | EF50: 0

Sheet EGRESADOS
A1: No. | B1: NOMBRE ESTUDIANTE | C1: COD. ESTUDIANTE | D1: DOC. IDENT. | E1: TIPO IDENT. | F1: ESTADO | G1: ACTA | H1: LIBRO | I1: FOLIO | J1: REG. DIPLOMA | K1: TIT. TRABAJO DE GRADO | L1: FECHA GRADO | M1: DISTINCIÓN | N1: DIR. TRABAJO GRADO 1 | O1: DOC. DIR. TRAB. GRADO 1 | P1: DIR. TRABAJO GRADO 2 | Q1: DOC. DIR. TRAB. GRADO 2 | R1: MODALIDAD
A2: 89 | B2: RONALD YESID BUITRAGO BRAVO | C2: 20041195004 | D2: 79796071 | E2: CEDULA DE CIUDADANIA | F2: ESTUDIANTE GRADUADO | G2: 16792 | H2: 17 | I2: 108 | J2: F.I. 18851 | K2: GESTION DE LA RED DE BANCO DE OCCIDENTE COMO HERRAMIENTA DE CALIDAD DE SERVICIO | L2: 42566 | M2: APROBADO | N2: OCTAVIO JOSE SALCEDO PARRA | R2: GRADO | S2: =VLOOKUP(C2,Estados!B:J,9,0) -> rybuitrago@bancodeoccidente.com.co
A3: 90 | B3: DANILO DE JESUS ARIZA AGAMEZ | C3: 20081195002 | D3: 8740480 | E3: CEDULA DE CIUDADANIA | F3: ESTUDIANTE GRADUADO | G3: 16503 | H3: 17 | I3: 60 | J3: F.I. 18560 | K3: APROXIMACION AL MODELAMIENTO DEL ENRUTAMIENTO EN REDES GMPLS CON FINES DE OPTIMIZACION DE RECURSOS | L3: 42447 | M3: APROBADO | N3: OCTAVIO JOSE SALCEDO PARRA | O3: 79508767 | R3: GRADO | S3: =VLOOKUP(C3,Estados!B:J,9,0) -> darizaagamez@yahoo.es
A4: 91 | B4: GUSTAVO ADOLFO HIGUERA CASTRO | C4: 20111195003 | D4: 1024461077 | E4: CEDULA DE CIUDADANIA | F4: ESTUDIANTE GRADUADO | G4: 17156 | H4: 17 | I4: 169 | J4: F.I. 19215 | K4: METAMODELO PARA CONFIGURACIONES EN DISPOSITIVOS DE REDES COMO ESTANDAR SOPORTADO EN LA INGENIERIA DIRIGIDA POR MODELOS | L4: 42608 | M4: APROBADO | N4: CARLOS ENRIQUE MONTENEGRO MARIN | R4: GRADO | S4: =VLOOKUP(C4,Estados!B:J,9,0) -> gustavohigcas@yahoo.es
A5: 92 | B5: CARLOS ANDRES MARTINEZ ALAYON | C5: 20111195005 | D5: 11223363 | E5: CEDULA DE CIUDADANIA | F5: ESTUDIANTE GRADUADO | G5: 16794 | H5: 17 | I5: 109 | J5: F.I. 18853 | K5: GENERACION DE UN MODELO ESTADISTICO PARA LA ESTIMACION DEL COMPORTAMIENTO FUTURO DE PARAMETROS DE TELETRAFICO EN REDES ACADEMICAS DE NUEVA GENERACION APLICANDO SERIES DE TIEMPO TIPO ARIMA, SARIMA Y VARMA | L5: 42566 | M5: APROBADO | N5: ROBERTO FERRO ESCOBAR | O5: 79657603 | R5: GRADO | S5: =VLOOKUP(C5,Estados!B:J,9,0) -> carlosm563@gmail.com
A6: 93 | B6: RAFAEL ENRIQUE BALAGUERA HERNANDEZ | C6: 20112195002 | D6: 79283623 | E6: CEDULA DE CIUDADANIA | F6: ESTUDIANTE GRADUADO | G6: 17152 | H6: 17 | I6: 168 | J6: F.I. 19211 | K6: METODO DE DISE?O DE FILTROS BASADO EN REDES DE LINEAS DE TRANSMISION PARA UNA TOPOLOGIA MONOFASICA CON TECNOLOGIA BPL | L6: 42608 | M6: APROBADO | N6: JOSE ROBERTO CARDENAS CASTIBLANCO | O6: 19289020 | R6: GRADO | S6: =VLOOKUP(C6,Estados!B:J,9,0) -> rbalaguera@pedagogica.edu.co
A7: 94 | B7: DAVID EUGENIO FORERO MARTINEZ | C7: 20112195004 | D7: 71113015 | E7: CEDULA DE CIUDADANIA | F7: ESTUDIANTE GRADUADO | G7: 17154 | H7: 17 | I7: 169 | J7: F.I. 19213 | K7: DISE?O DEL BLOQUE DE ESTIMACION DE UN SISTEMA ADCS PARA UN PICO-SATELITE DE ESTANDAR CUBESAT UTILIZANDO FILTRO DEL PARTICULAS COMO TECNICA DE ESTIMACION | L7: 42608 | M7: APROBADO | N7: CESAR ALBERTO CASTELLANOS GARCIA | O7: 3228510 | R7: GRADO | S7: =VLOOKUP(C7,Estados!B:J,9,0) -> eug_68@hotmail.com
A8: 95 | B8: RICARDO ALFONSO GOMEZ SUAREZ | C8: 20141195001 | D8: 79430383 | E8: CEDULA DE CIUDADANIA | F8: ESTUDIANTE GRADUADO | G8: 17588 | H8: 17 | I8: 240 | J8: F.I 19647 | K8: MODELO DE ARQUITECTURA DE MIDDLEWARE PARA UN SISTEMA DE TRANSPORTE PUBLICO DE PASAJEROS EN CIUDADES BASADO EN SMART CITY | L8: 42727 | M8: APROBADO | N8: ROBERTO FERRO ESCOBAR | O8: 79657603 | R8: GRADO | S8: =VLOOKUP(C8,Estados!B:J,9,0) -> ragomezs@udistrital.edu.co
A9: 96 | B9: ALEJANDRO QUIROZ LUIS | C9: 20141195005 | D9: 79562545 | E9: CEDULA DE CIUDADANIA | F9: ESTUDIANTE GRADUADO | G9: 17305 | H9: 17 | I9: 193 | J9: F.I. 19364 | K9: PROPUESTA PARA UN MODELO DE ANTENA MICROSTRIP BASADA EN PERTURBACIONES GEOMETRICAS | L9: 42664 | M9: APROBADO | N9: JUAN CARLOS GOMEZ PAREDES | O9: 268856 | R9: GRADO | S9: =VLOOKUP(C9,Estados!B:J,9,0) -> luis.alejandro.quiroz@gmail.com
A10: 97 | B10: GONZALO JIMENEZ PINTO | C10: 20092195021 | D10: 80372346 | E10: CEDULA DE CIUDADANIA | F10: ESTUDIANTE GRADUADO | G10: 18373 | H10: 18 | I10: 137 | J10: F.I 20433 | K10: ALGORITMO DE COMPRESION PARA LA DETECCION DEL SEGMENTO ST DE UNA SE?AL ELECTROCARDIOGRAFICA FETAL BASADO EN LA TRANSFORMADA WAVELET Y UMBRALIZACION MULTINIVEL | L10: 42993 | M10: APROBADO | N10: EDWIN RIVAS TRUJILLO | S10: =VLOOKUP(C10,Estados!B:J,9,0) -> gojimenez1@hotmail.com
A11: 98 | B11: NIRIYINETH HAXBLEIDY VELASQUEZ ROMERO | C11: 20111195007 | D11: 40340112 | E11: CEDULA DE CIUDADANIA | F11: ESTUDIANTE GRADUADO | G11: 17869 | H11: 18 | I11: 45 | J11: F.I 19928 | K11: MAGISTER EN CIENCIAS DE LA INFORMACION Y LAS COMUNICACIONES | L11: 42818 | N11: OCTAVIO JOSE SALCEDO PARRA | O11: 79508767 | R11: GRADO | S11: =VLOOKUP(C11,Estados!B:J,9,0) -> niriyineth@live.com.ar
A12: 99 | B12: PEDRO ALEJANDRO MANCERA LAGOS | C12: 20112195005 | D12: 88247160 | E12: CEDULA DE CIUDADANIA | F12: ESTUDIANTE GRADUADO | G12: 18374 | H12: 18 | I12: 137 | J12: F.I 20434 | K12: INNOVACION :MODELO DEL SISTEMA DE COMUNICACIONES PARA UNA MICRORRED ELECTRICA AISLADA, BASADO EN UNA RED DE SENSORES INALAMBRICOS, PARA LA TRANSFERENCIA DE DATOS DE CONTROL | L12: 42993 | M12: APROBADO | N12: ELVIS EDUARDO GAONA GARCIA | O12: 79950025 | R12: INVESTIGACION ? INNOVACION | S12: =VLOOKUP(C12,Estados!B:J,9,0) -> pmancera@yahoo.com
A13: 100 | B13: VICTOR DANIEL ANGULO MORALES | C13: 20121195001 | D13: 1018419891 | E13: CEDULA DE CIUDADANIA | F13: ESTUDIANTE GRADUADO | G13: 18370 | H13: 18 | I13: 136 | J13: F.I 20430 | K13: INNOVACION :MODELO DE TOMA DE DECISION PARA LA GESTION DE RECURSOS EN UNA SMART GRID UTILIZANDO LA ARQUITECTURA MDA BASADA EN WSN | L13: 42993 | M13: APROBADO | N13: ELVIS EDUARDO GAONA GARCIA | O13: 79950025 | R13: INVESTIGACION ? INNOVACION | S13: =VLOOKUP(C13,Estados!B:J,9,0) -> vdangulom@correo.udistrital.edu.co
A14: 101 | B14: JESUS MANUEL PATERNINA DURAN | C14: 20151195005 | D14: 80095218 | E14: CEDULA DE CIUDADANIA | F14: ESTUDIANTE GRADUADO | G14: 18375 | H14: 18 | I14: 137 | J14: F.I 20435 | K14: INNOVACION :METOOOLOGIA PARA LA IMPLEMENTACION DE QOS EN REDES LI-FI SOBRE ENTORNOS DE 5A GENERACION | L14: 42993 | M14: APROBADO | N14: OCTAVIO JOSE SALCEDO PARRA | O14: 79508767 | R14: INVESTIGACION ? INNOVACION | S14: =VLOOKUP(C14,Estados!B:J,9,0) -> jesus_p17@yahoo.com.ar
A15: 102 | B15: ANDRES ALEXANDER RODRIGUEZ FONSECA | C15: 20151195006 | D15: 80185164 | E15: CEDULA DE CIUDADANIA | F15: ESTUDIANTE GRADUADO | G15: 17867 | H15: 18 | I15: 45 | J15: F.I 19926 | K15: MAGISTER EN CIENCIAS DE LA INFORMACION Y LAS COMUNICACIONES | L15: 42818 | N15: ROBERTO FERRO ESCOBAR | O15: 79657603 | R15: INVESTIGACION ? INNOVACION | S15: =VLOOKUP(C15,Estados!B:J,9,0) -> aarodriguezf@gmail.com
A16: 103 | B16: DIEGO FERNANDO AGUIRRE MORENO | C16: 20152195002 | D16: 3059527 | E16: CEDULA DE CIUDADANIA | F16: ESTUDIANTE GRADUADO | G16: 18026 | H16: 18 | I16: 71 | J16: F.I 19669 | K16: METODOLOGIA PARA APLICAR CALIDAD DE SERVICIO A REDES OTN | L16: 42879 | M16: APROBADO | N16: OCTAVIO JOSE SALCEDO PARRA | R16: GRADO | S16: =VLOOKUP(C16,Estados!B:J,9,0) -> diego2281@gmail.com
A17: 104 | B17: ANDRES FELIPE HERNANDEZ LEON | C17: 20152195009 | D17: 1018424588 | E17: CEDULA DE CIUDADANIA | F17: ESTUDIANTE GRADUADO | G17: 18372 | H17: 18 | I17: 137 | J17: F.I 20432 | K17: MODELO ALGORITMICO PARA LIMITAR LA CONGESTION DEL PROTOCOLO TCP EN REDES DE EXTREMO A EXTREMO | L17: 42993 | M17: APROBADO | N17: OCTAVIO JOSE SALCEDO PARRA | O17: 79508767 | S17: =VLOOKUP(C17,Estados!B:J,9,0) -> anfeherle@hotmail.com
A18: 105 | B18: EDGAR ANDRES LOPEZ SALAMANCA | C18: 20152195012 | D18: 80843494 | E18: CEDULA DE CIUDADANIA | F18: ESTUDIANTE GRADUADO | G18: 18952 | H18: 18 | I18: 253 | J18: F.I. 21012 | K18: METODOLOGIA PARA PLANIFICACION DE REDES DE TELEVISION DIGITAL TERRESTRE EN COLOMBIA | L18: 43084 | M18: APROBADO | N18: ELVIS EDUARDO GAONA GARCIA | O18: 79950025 | R18: INVESTIGACION ? INNOVACION | S18: =VLOOKUP(C18,Estados!B:J,9,0) -> andres.lopez.salamanca@gmail.com
A19: 106 | B19: FELIPE ANDRES ZARTA ESCOBAR | C19: 20152195026 | D19: 1075650800 | E19: CEDULA DE CIUDADANIA | F19: ESTUDIANTE GRADUADO | G19: 18953 | H19: 18 | I19: 253 | J19: F.I. 21013 | K19: MODELO DE AFECTACION DE CALIDAD DE SERVICIO EN REDES WI-FI EN COEXISTENCIA CON REDES LTE EN BANDA NO LICENCIADA | L19: 43084 | M19: APROBADO | N19: ELVIS EDUARDO GAONA GARCIA | O19: 79950025 | R19: MONOGRAFIA | S19: =VLOOKUP(C19,Estados!B:J,9,0) -> felipe.zarta@gmail.com
A20: 107 | B20: ADRIANA VALIENTE CRISTANCHO | C20: 20112195007 | D20: 52128254 | E20: CEDULA DE CIUDADANIA | F20: ESTUDIANTE GRADUADO | G20: 18959 | H20: 19 | I20: 1 | J20: F.I. 21020 | K20: INTEGRACION DE INTERNET DE LAS COSAS EN UN SISTEMA EMBEBIDO SYSTEM IN CHIP, HARDWARE/SOFTWARE CON APLICACION ADOMOTICA | L20: 43146 | M20: APROBADO | N20: EDUARDO ALBERTO DELGADILLO GOMEZ | R20: MONOGRAFIA | S20: =VLOOKUP(C20,Estados!B:J,9,0) -> avcristancho@gmail.com
A21: 108 | B21: HAROLD ANDREY VASQUEZ SUAREZ | C21: 20122195008 | D21: 1026258511 | E21: CEDULA DE CIUDADANIA | F21: ESTUDIANTE GRADUADO | G21: 19176 | H21: 19 | I21: 38 | J21: F.I. 21238 | K21: INNOVACION :MODELO DE HANDOFF ESPECTRAL PROACTIVO-PREDICTIVO QUE PERMITE REDUCIR EL NIVEL DE INTERFERENCIA EN REDES DE RADIO COGNITIVA. | L21: 43182 | M21: APROBADO | N21: CESAR AUGUSTO HERNANDEZ SUAREZ | O21: 86062285 | R21: INVESTIGACION ? INNOVACION | S21: =VLOOKUP(C21,Estados!B:J,9,0) -> harold869@hotmail.com
A22: 109 | B22: JULIAN ROLANDO CAMARGO LOPEZ | C22: 20152195005 | D22: 79560853 | E22: CEDULA DE CIUDADANIA | F22: ESTUDIANTE GRADUADO | G22: 19162 | H22: 19 | I22: 35 | J22: F.I. 21224 | K22: INNOVACION :MODELO PARA LA DETECCION Y CORRECION DE PROPAGACIONES ANOMALAS EN RADARES METEREOLOGICOS PARA ZONAS ECUATORIALES | L22: 43182 | M22: APROBADO | N22: ERNESTO GOMEZ VARGAS | O22: 74373175 | R22: INVESTIGACION ? INNOVACION | S22: =VLOOKUP(C22,Estados!B:J,9,0) -> jcamargo@udistrital.edu.co
A23: 110 | B23: WILSON RICARDO LOPEZ SANCHEZ | C23: 20152195013 | D23: 1026268779 | E23: CEDULA DE CIUDADANIA | F23: ESTUDIANTE GRADUADO | G23: 19700 | H23: 19 | I23: 125 | J23: F.I. 21762 | K23: MODELO PARA LA ESTIMACION DE LA CALIDAD DEL AGUA EN AFLUENTES HIDRICAS | L23: 43357 | M23: APROBADO | N23: CESAR ANDREY PERDOMO CHARRY | O23: 7724669 | S23: =VLOOKUP(C23,Estados!B:J,9,0) -> wilrilo@gmail.com
A24: 111 | B24: TATIANA MORALES VEGA | C24: 20152195014 | D24: 52779302 | E24: CEDULA DE CIUDADANIA | F24: ESTUDIANTE GRADUADO | G24: 19167 | H24: 19 | I24: 36 | J24: F.I. 21229 | K24: INNOVACION :INFRAESTRUCTURA DE MEDICION AVANZADA PARA MICRORREDES ELECTRICAS | L24: 43182 | M24: APROBADO | N24: FRANCISCO SANTAMARIA PIEDRAHIT | O24: 79853581 | R24: INVESTIGACION ? INNOVACION | S24: =VLOOKUP(C24,Estados!B:J,9,0) -> tatiana.morales@transmilenio.gov.co
A25: 112 | B25: DUVAN ARLEY PARDO CADENA | C25: 20152195019 | D25: 1018451803 | E25: CEDULA DE CIUDADANIA | F25: ESTUDIANTE GRADUADO | G25: 19169 | H25: 19 | I25: 36 | J25: F.I. 21231 | K25: INNOVACION :METODOLOGIA PARA EL DESARROLLO DE SISTEMAS EMBEBIDOS CON PRESTACION DE SERVICIOS WEB | L25: 43182 | M25: APROBADO | N25: CESAR ANDREY PERDOMO CHARRY | O25: 7724669 | R25: INVESTIGACION ? INNOVACION | S25: =VLOOKUP(C25,Estados!B:J,9,0) -> dapardoc@gmail.com
A26: 113 | B26: WILSON JAVIER PE?A CARO | C26: 20152195020 | D26: 1010175143 | E26: CEDULA DE CIUDADANIA | F26: ESTUDIANTE GRADUADO | G26: 19170 | H26: 19 | I26: 37 | J26: F.I. 21232 | K26: INNOVACION :MODELO DE ESTIMACION PARA EL USO DE AGUA DEL RIO BOGOTA, BASADO EN EL ANALISIS DE VERTIMIENTO EN AGUAS SUPERFICIES | L26: 43182 | M26: APROBADO | N26: CARLOS ENRIQUE MONTENEGRO MARIN | R26: INVESTIGACION ? INNOVACION | S26: =VLOOKUP(C26,Estados!B:J,9,0) -> wiljha@hotmail.com
A27: 114 | B27: SERGIO ALEJANDRO PEREZ ALMEIDA | C27: 20152195021 | D27: 1030584421 | E27: CEDULA DE CIUDADANIA | F27: ESTUDIANTE GRADUADO | G27: 19171 | H27: 19 | I27: 37 | J27: F.I. 21233 | K27: DISE?O DE UNA RED DE ACCESO OPTICA DE LARGA DISTANCIA Y ALTA CAPACIDAD EN CUNDINAMARCA | L27: 43182 | M27: APROBADO | N27: GUSTAVO ADOLFO PUERTO LEGUIZAMON | O27: 74184661 | R27: CREACION O INTERPRETACION | S27: =VLOOKUP(C27,Estados!B:J,9,0) -> sergio9012@hotmail.com
A28: 115 | B28: CRISTIAN CAMILO BERNAL ARIZA | C28: 20161195001 | D28: 1016015011 | E28: CEDULA DE CIUDADANIA | F28: ESTUDIANTE GRADUADO | G28: 19698 | H28: 19 | I28: 125 | J28: F.I. 21760 | K28: MODELO INTELIGENTE DE DECISION DE ESPECTRO QUE MEJORA EL DESEMPE?O EN REDES DE RADIO COGNITIVA | L28: 43357 | M28: APROBADO | N28: CESAR AUGUSTO HERNANDEZ SUAREZ | O28: 86062285 | R28: INVESTIGACION ? INNOVACION | S28: =VLOOKUP(C28,Estados!B:J,9,0) -> cristianbariza@gmail.com
A29: 116 | B29: ANA CAROLINA RODRIGUEZ CEDIEL | C29: 20162195007 | D29: 1014199332 | E29: CEDULA DE CIUDADANIA | F29: ESTUDIANTE GRADUADO | G29: 19174 | H29: 19 | I29: 37 | J29: F.I. 21236 | K29: MODELO NO INVASIVO PARA LA DETECCION DE FACTORES EXTRINSECOS DEL SIMS | L29: 43182 | M29: APROBADO | N29: ERNESTO GOMEZ VARGAS | O29: 74373175 | S29: =VLOOKUP(C29,Estados!B:J,9,0) -> anacarolinarodriguezcediel@gmail.com
A30: 117 | B30: DIEGO FELIPE SOTO CONDE | C30: 20121195014 | D30: 93453664 | E30: CEDULA DE CIUDADANIA | F30: ESTUDIANTE GRADUADO | G30: 20322 | H30: 20 | I30: 24 | J30: F.I. 22385 | K30: PROPUESTA DE UN PROTOTIPO DE ACCESO REMOTO VIRTUAL AL PROYECTO "GLOBAL ROBOTIC-TELESCOPES INTELLIGENT ARRAY" . | L30: 43546 | M30: APROBADO | N30: ROBERTO FERRO ESCOBAR | O30: 79657603 | R30: INVESTIGACION ? INNOVACION | S30: =VLOOKUP(C30,Estados!B:J,9,0) -> difeso@gmail.com
A31: 118 | B31: ADRIANA YOLANDA GUEVARA RIVEROS | C31: 20122195003 | D31: 52147162 | E31: CEDULA DE CIUDADANIA | F31: ESTUDIANTE GRADUADO | G31: 20320 | H31: 20 | I31: 24 | J31: F.I. 22383 | K31: DISE?O DE UNA ARQUITECTURA PARA EL MONITOREO DE LOS SIGNOS VITALES EN ENTORNOS RESTRINGIDOS | L31: 43546 | M31: APROBADO | N31: OCTAVIO JOSE SALCEDO PARRA | R31: INVESTIGACION ? INNOVACION | S31: =VLOOKUP(C31,Estados!B:J,9,0) -> adriveros2006@hotmail.com
A32: 119 | B32: HERRERA HERRERA HECTOR MANUEL | C32: 20142195003 | D32: 1033691855 | E32: CEDULA DE CIUDADANIA | F32: ESTUDIANTE GRADUADO | G32: 20598 | H32: 20 | I32: 70 | J32: F.I. 22661 | K32: MODELO DE OPTIMIZACION DE RENDIMIENTO EN REDES 802.11AC UTILIZANDO PROGRAMACION MULTI-OBJETIVO | L32: 43623 | M32: APROBADO | N32: OCTAVIO JOSE SALCEDO PARRA | R32: INVESTIGACION ? INNOVACION | S32: =VLOOKUP(C32,Estados!B:J,9,0) -> hetorherrera@hotmail.com
A33: 120 | B33: RODRIGUEZ GARCIA NESTOR JAVIER | C33: 20142195004 | D33: 80932160 | E33: CEDULA DE CIUDADANIA | F33: ESTUDIANTE GRADUADO | G33: 21243 | H33: 20 | I33: 178 | J33: F.I 23308 | K33: SISTEMA MODULADOR Y DEMODULADOR DE LA ESTACION TERRENA CUBESAT - UD PARA LA COMUNICACION CON LA RED SATNET | L33: 43817 | M33: APROBADO | N33: LILIA EDITH APARICIO PICO | O33: 51703985 | R33: INVESTIGACION ? INNOVACION | S33: =VLOOKUP(C33,Estados!B:J,9,0) -> ing.nestor0818@gmail.com
A34: 121 | B34: ANDRES JULIAN MORENO MORENO | C34: 20152195015 | D34: 1032431630 | E34: CEDULA DE CIUDADANIA | F34: ESTUDIANTE GRADUADO | G34: 21240 | H34: 20 | I34: 177 | J34: F.I 23305 | K34: DISE?O Y EVALUACION DE UN SISTEMA EMBEBIDO PARA CONECTAR AL CONTROL DE VUELO DE UN VANT APLICADO A LA INSPECCION DE LINEAS DE TRANSMISION | L34: 43817 | M34: APROBADO | N34: ROBERTO FERRO ESCOBAR | O34: 79657603 | S34: =VLOOKUP(C34,Estados!B:J,9,0) -> andresm2.xy@gmail.com
A35: 122 | B35: GEOVANNY RENE OTALORA RIVERO | C35: 20162195006 | D35: 79531717 | E35: CEDULA DE CIUDADANIA | F35: ESTUDIANTE GRADUADO | G35: 21241 | H35: 20 | I35: 178 | J35: F.I 23306 | K35: CONFIGURAR UN SERVICIO DE TELEVISION MOVIL EN LA RED DE TRANSMISION DIGITAL TERRESTRE DE CANAL CAPITAL | L35: 43817 | M35: APROBADO | N35: EDMUNDO VEGA OSORIO | O35: 19165408 | R35: INVESTIGACION ? INNOVACION | S35: =VLOOKUP(C35,Estados!B:J,9,0) -> gotalora68@gmail.com
A36: 123 | B36: DIEGO EDUARDO PINEDA TORRES | C36: 20171195004 | D36: 1033712950 | E36: CEDULA DE CIUDADANIA | F36: ESTUDIANTE GRADUADO | G36: 21242 | H36: 20 | I36: 178 | J36: F.I 23307 | K36: MODELO DE ASIGNACION ESPECTRAL PARA EL USO EFICIENTE DE LA BANDA DE TELEVISION DIGITAL EN LA CIUDAD DE BOGOTA A TRAVES DE LA RADIO COGNITIVA | L36: 43817 | M36: APROBADO | N36: CESAR AUGUSTO HERNANDEZ SUAREZ | R36: MONOGRAFIA | S36: =VLOOKUP(C36,Estados!B:J,9,0) -> deduardopineda@gmail.com
A37: 124 | B37: GABRIEL ANDRES ALZATE ACU?A | C37: 20152195003 | D37: 80259743 | E37: CEDULA DE CIUDADANIA | F37: ESTUDIANTE GRADUADO | G37: 22160 | H37: 21 | I37: 144 | J37: F.I 24226 | K37: INVESTIGACION E INNOVACION: DISE?O DE UN SISTEMA DE RIEGO PARA GRANJA INTELIGENTE BASADO EN INTERNET DE LAS COSAS. | L37: 44188 | M37: APROBADO | N37: ROBERTO FERRO ESCOBAR | O37: 79657603 | R37: INVESTIGACION ? INNOVACION | S37: =VLOOKUP(C37,Estados!B:J,9,0) -> gabriel.andres.alzate@gmail.com
A38: 125 | B38: JUAN CARLOS CARRE?O PEREZ | C38: 20161195002 | D38: 80215759 | E38: CEDULA DE CIUDADANIA | F38: ESTUDIANTE GRADUADO | G38: 21681 | H38: 21 | I38: 64 | J38: F.I 23747 | K38: METODOLOGIA PARA EVALUACION DE CIBER VULNERABILIDAD EN SISTEMAS DE TRANSMISION DE ENERGIA ELECTRICA ?EVULCIB?, ESTUDIO DE CASO SUBESTACION ELECTRICA DE 230KV UBICADA EN LA CIUDAD DE BOGOTA-COLOMBIA | L38: 44063 | N38: ALVARO ESPINEL ORTEGA | O38: 19483708 | R38: ESPACIOS ACADEMICOS DE PROFUNDIZACION | S38: =VLOOKUP(C38,Estados!B:J,9,0) -> juan_carlos_carreno@hotmail.com
A39: 126 | B39: LEWYS CORREA SANCHEZ | C39: 20161195003 | D39: 1067906153 | E39: CEDULA DE CIUDADANIA | F39: ESTUDIANTE GRADUADO | G39: 21667 | H39: 21 | I39: 61 | J39: F.I 23733 | K39: INVESTIGACION E INNOVACION : MODELO ARQUITECTONICO PARA LA INTERCONECTIVIDAD DE REDES VANET UTILIZANDO INTERNET DE LAS COSAS | L39: 44046 | M39: APROBADO | N39: OCTAVIO JOSE SALCEDO PARRA | R39: INVESTIGACION ? INNOVACION | S39: =VLOOKUP(C39,Estados!B:J,9,0) -> lew.correa@gmail.com
A40: 127 | B40: YOHEL RENE SERRANO MOLINA | C40: 20161195015 | D40: 14013612 | E40: CEDULA DE CIUDADANIA | F40: ESTUDIANTE GRADUADO | G40: 21671 | H40: 21 | I40: 62 | J40: F.I 23737 | K40: GUIA PARA DEL USO DE CLOUD COMPUTING COMO MECANISMO DE RECUPERACION ANTE DESASTRES TECNOLOGICOS EN PYMES COLOMBIANAS | L40: 44046 | M40: APROBADO | N40: JOSE NELSON PEREZ CASTILLO | R40: ESPACIOS ACADEMICOS DE PROFUNDIZACION | S40: =VLOOKUP(C40,Estados!B:J,9,0) -> yorry_12@hotmail.com
A41: 128 | B41: CAMILO ANDRES TORRES CASTILLO | C41: 20162195010 | D41: 1072640773 | E41: CEDULA DE CIUDADANIA | F41: ESTUDIANTE GRADUADO | G41: 22161 | H41: 21 | I41: 144 | J41: F.I 24227 | K41: INVESTIGACION E INNOVACION: MODELO DE SINTESIS DE DIAGRAMAS DE RADIACION EN AGRUPACIONES LINEALES DE ANTENAS PARA APLICACIONES EN ESTACIONES BASE DE TELEFONIA CELULAR. | L41: 44188 | M41: APROBADO | N41: CARLOS ARTURO SUAREZ FAJARDO | R41: INVESTIGACION ? INNOVACION | S41: =VLOOKUP(C41,Estados!B:J,9,0) -> camito113@gmail.com
A42: 129 | B42: NATALIA ANDREA RAMIREZ PEREZ | C42: 20181195009 | D42: 1015443760 | E42: CEDULA DE CIUDADANIA | F42: ESTUDIANTE GRADUADO | G42: 21669 | H42: 21 | I42: 62 | J42: F.I 23735 | K42: INVESTIGACION E INNOVACION : MODELO DE CLASIFICACION AUTOMATICA DE IMAGENES DE RESONANCIA MAGNETICA PARA EL DIAGNOSTICO DEL CANCER DE PROSTATA | L42: 44046 | M42: APROBADO | N42: LILIA EDITH APARICIO PICO | O42: 51703985 | R42: INVESTIGACION ? INNOVACION | S42: =VLOOKUP(C42,Estados!B:J,9,0) -> nata.r_1212@hotmail.com
A43: 130 | B43: EDUARDO ALFONSO DIAZ CARRETERO | C43: 20181395003 | D43: 1022386838 | E43: CEDULA DE CIUDADANIA | F43: ESTUDIANTE GRADUADO | G43: 21668 | H43: 21 | I43: 62 | J43: F.I 23734 | K43: PASANTIA: DISE?O DE UNA OFICINA DE DIRECCION DE PROYECTOS (PMO), CON ENFOQUE EN PROYECTOS DE INVESTIGACION EN LA RED DE INVESTIGACIONES DE TECNOLOGIA AVANZADA DE LA UNIVERSIDAD DISTRITAL | L43: 44046 | M43: APROBADO | N43: ROBERTO FERRO ESCOBAR | O43: 79657603 | R43: PASANTIA | S43: =VLOOKUP(C43,Estados!B:J,9,0) -> eadiaz96@gmail.com
A44: 131 | B44: LUZ YAMILE REYES BONILLA | C44: 20122195005 | D44: 30230686 | E44: CEDULA DE CIUDADANIA | F44: ESTUDIANTE GRADUADO | G44: 22257 | H44: 22 | I44: 16 | J44: F.I 24323 | K44: PASANTIA: DESARROLLO DE UN SISTEMA DE INFORMACION GEORREFERENCIADO PARA EL SEGUIMIENTO A LA ESTABILIDAD DE OBRAS DE ESPACIO PUBLICO, MALLA VIAL Y DE TRANSPORTE | L44: 44251 | M44: APROBADO | N44: ROBERTO FERRO ESCOBAR | O44: 79657603 | R44: PASANTIA | S44: =VLOOKUP(C44,Estados!B:J,9,0) -> luzyare@gmail.com
A45: 132 | B45: DELGADILLO BELTRAN JUAN CARLOS | C45: 20142195001 | D45: 79576961 | E45: CEDULA DE CIUDADANIA | F45: ESTUDIANTE GRADUADO | G45: 22421 | H45: 22 | I45: 43 | J45: F.I 24488 | K45: PASANTIA: CREACION DE UN LABORATORIO DE SEGURIDAD EN REDES | L45: 44292 | M45: APROBADO | N45: ROBERTO FERRO ESCOBAR | O45: 79657603 | R45: PASANTIA | S45: =VLOOKUP(C45,Estados!B:J,9,0) -> ingjuandel@gmail.com
A46: 133 | B46: FIGUEREDO RODRIGUEZ WILMER ALBERTO | C46: 20142195002 | D46: 1010175883 | E46: CEDULA DE CIUDADANIA | F46: ESTUDIANTE GRADUADO | G46: 22852 | H46: 22 | I46: 115 | J46: F.I 24919 | K46: INVESTIGACION: MODELO DE TRANSFERENCIA DE TELEMETRIA EN REDES Y SISTEMAS SATELITALES CUBESAT | L46: 44484 | M46: APROBADO | N46: LILIA EDITH APARICIO PICO | O46: 51703985 | R46: INVESTIGACION ? INNOVACION | S46: =VLOOKUP(C46,Estados!B:J,9,0) -> wilmerfr@gmail.com
A47: 134 | B47: NELSON GIOVANNI AGUDELO CRISTANCHO | C47: 20152195001 | D47: 80051486 | E47: CEDULA DE CIUDADANIA | F47: ESTUDIANTE GRADUADO | G47: 23026 | H47: 22 | I47: 145 | J47: F.I 25095 | K47: INVESTIGACION E INNOVACION: SISTEMA DE INTEROPERABILIDAD PARA TECNOLOGIAS CELULARES E INALAMBRICAS ESTABLECIDAS EN LOS ESTANDARES IEEE 802.15.1, IEEE 802.15.4, IEEE 802.11 | L47: 44552 | M47: APROBADO | N47: OCTAVIO JOSE SALCEDO PARRA | R47: INVESTIGACION ? INNOVACION | S47: =VLOOKUP(C47,Estados!B:J,9,0) -> nelsongiovani@gmail.com
A48: 135 | B48: MIGUEL ANGEL DAVILA ROJAS | C48: 20161195005 | D48: 1018436623 | E48: CEDULA DE CIUDADANIA | F48: ESTUDIANTE GRADUADO | G48: 23030 | H48: 22 | I48: 145 | J48: F.I 25099 | K48: INVESTIGACION E INNOVACION: DESARROLLO DE UN ALGORITMO DE GESTION DE LA DEMANDA ENERGETICA DE UN CARGADOR RESIDENCIAL DE BATERIAS PARA VEHICULOS ELECTRICOS EN UN ESCENARIO DE TARIFICACION EN TIEMPO REAL | L48: 44552 | M48: APROBADO | N48: CESAR TRUJILLO | R48: INVESTIGACION ? INNOVACION | S48: =VLOOKUP(C48,Estados!B:J,9,0) -> miadavilar@correo.udistrital.edu.co
A49: 136 | B49: JAIRO CESAR GOMEZ ACERO | C49: 20161195009 | D49: 79049409 | E49: CEDULA DE CIUDADANIA | F49: ESTUDIANTE GRADUADO | G49: 22572 | H49: 22 | I49: 69 | J49: F.I 24639 | K49: PASANTIA: DISE?O E IMPLEMENTACION DE LA POLITICA DE GOBIERNO DE TECNOLOGIAS DE INFORMACION Y COMUNICACION. | L49: 44357 | M49: APROBADO | N49: JUAN CARLOS GOMEZ PAREDES | R49: PASANTIA | S49: =VLOOKUP(C49,Estados!B:J,9,0) -> jacegom@gmail.com
A50: 137 | B50: RAFAEL ORLANDO CUBILLOS SANCHEZ | C50: 20162195004 | D50: 79578336 | E50: CEDULA DE CIUDADANIA | F50: ESTUDIANTE GRADUADO | G50: 22420 | H50: 22 | I50: 43 | J50: F.I 24487 | K50: MODELO DE DETECCION Y ELIMINACION DE ECOS TERRESTRES EN IMAGENES DE RADARES METEOROLOGICOS | L50: 44292 | M50: APROBADO | N50: ERNESTO GOMEZ VARGAS | R50: MONOGRAFIA | S50: =VLOOKUP(C50,Estados!B:J,9,0) -> rafacubillos@gmail.com
A51: 138 | B51: MARCO ALEXANDER SUAREZ ROLDAN | C51: 20181195012 | D51: 1110505909 | E51: CEDULA DE CIUDADANIA | F51: ESTUDIANTE GRADUADO | G51: 22423 | H51: 22 | I51: 44 | J51: F.I 24490 | K51: PASANTIA: DESARROLLO DE UNA APLICACION MOVIL INTELIGENTE PARA PROMOCIONAR Y COMERCIALIZAR LOS PRODUCTOS AGRICOLAS OFERTADOS POR LOS PRODUCTORES RURALES EN LAS AREAS DE INFLUENCIA DE LA CIUDAD DE IBAGUE. | L51: 44292 | M51: APROBADO | N51: OCTAVIO JOSE SALCEDO PARRA | R51: PASANTIA | S51: =VLOOKUP(C51,Estados!B:J,9,0) -> masuarez90@misena.edu.co
A52: 139 | B52: JUAN SEBASTIAN SUAREZ ROLDAN | C52: 20181195013 | D52: 1110505907 | E52: CEDULA DE CIUDADANIA | F52: ESTUDIANTE GRADUADO | G52: 22424 | H52: 22 | I52: 44 | J52: F.I 24491 | K52: PASANTIA: DESARROLLO DE UNA APLICACION MOVIL INTELIGENTE PARA LA PROMOCION Y COMERCIALIZACION DE LAS EXPERIENCIAS TURISTICAS DEL CA?ON DEL COMBEIMA DE LA CIUDAD DE IBAGUE. | L52: 44292 | M52: APROBADO | N52: OCTAVIO JOSE SALCEDO PARRA | R52: PASANTIA | S52: =VLOOKUP(C52,Estados!B:J,9,0) -> sebas.suarez.roldan@gmail.com
A53: 140 | B53: FABIAN DAVID BARRETO SANCHEZ | C53: 20182195002 | D53: 1118559031 | E53: CEDULA DE CIUDADANIA | F53: ESTUDIANTE GRADUADO | G53: 23027 | H53: 22 | I53: 145 | J53: F.I 25096 | K53: INVESTIGACION E INNOVACION: MODELO HIBRIDO DE CONTROL CON SE?ALES MIOELECTRICA Y ENCEFALOGRAFICA PARA LA IDENTIFICACION DE GESTOS EN MIEMBRO SUPERIOR | L53: 44552 | M53: APROBADO | N53: CESAR ANDREY PERDOMO CHARRY | R53: INVESTIGACION ? INNOVACION | S53: =VLOOKUP(C53,Estados!B:J,9,0) -> fabibeto11@hotmail.com
A54: 141 | B54: JAIRO ANTONIO NUVAN HURTADO | C54: 20051195015 | D54: 9396968 | E54: CEDULA DE CIUDADANIA | F54: ESTUDIANTE GRADUADO | G54: 23460 | H54: 23 | I54: 71 | J54: F.I 25529 | K54: PASANTIA: ESTRUCTURACION DE UN LABORATORIO DE PRUEBAS REDES INALAMBRICAS LAN CON ENFASIS EN WIFI 6 PARA LA UNIVERSIDAD DISTRITAL FRANCISCO JOSE DE CALDAS | L54: 44736 | M54: APROBADO | N54: ROBERTO FERRO ESCOBAR | O54: 79657603 | R54: PASANTIA | S54: =VLOOKUP(C54,Estados!B:J,9,0) -> januvan@hotmail.com
A55: 142 | B55: HANS RODRIGUEZ COSSIO | C55: 20061195014 | D55: 79999284 | E55: CEDULA DE CIUDADANIA | F55: ESTUDIANTE GRADUADO | G55: 23462 | H55: 23 | I55: 71 | J55: F.I 25531 | K55: PASANTIA: ANALISIS, DEFINICION E IMPLEMENTACION DE UNA PLATAFORMA DE PRUEBAS IOT PARA EL SEMILLERO DE INVESTIGACION SCISEN | L55: 44736 | M55: APROBADO | N55: ROBERTO FERRO ESCOBAR | O55: 79657603 | R55: PASANTIA | S55: =VLOOKUP(C55,Estados!B:J,9,0) -> hansrodriguez@gmail.com
A56: 143 | B56: GUSTAVO ALONSO RODRIGUEZ RODRIGUEZ | C56: 20162195008 | D56: 79797927 | E56: CEDULA DE CIUDADANIA | F56: ESTUDIANTE GRADUADO | G56: 23269 | H56: 23 | I56: 39 | J56: F.I 25338 | K56: PASANTIA: DESARROLLO DE UNA APLICACION SOFTWARE CON INTERFAZ DE COMUNICACIONES PARA LA ADQUISICION Y PROCESAMIENTO DE SE?ALES USADAS EN SISTEMAS PARA REHABILITACION DEL CAMINAR | L56: 44638 | M56: APROBADO | N56: ANDRES LEONARDO JUTINICO | R56: PASANTIA | S56: =VLOOKUP(C56,Estados!B:J,9,0) -> garcaj@hotmail.com
A57: 144 | B57: GUSTAVO ALEJANDRO ROBAYO MENDEZ | C57: 20171195006 | D57: 1026251289 | E57: CEDULA DE CIUDADANIA | F57: ESTUDIANTE GRADUADO | G57: 23780 | H57: 23 | I57: 124 | J57: F.I 25851 | K57: DESARROLLO DE UN SIMULADOR DE DATOS DE RADAR METEOROLOGICO DE POLARIZACION DUAL PARA ZONAS ECUATORIALES | L57: 44827 | N57: ERNESTO GOMEZ VARGAS | R57: ESPACIOS ACADEMICOS DE PROFUNDIZACION | S57: =VLOOKUP(C57,Estados!B:J,9,0) -> tavoalejo@gmail.com
A58: 145 | B58: EDWARD LENIN CASTA?EDA MOSCOSO | C58: 20172195005 | D58: 80007028 | E58: CEDULA DE CIUDADANIA | F58: ESTUDIANTE GRADUADO | G58: 23268 | H58: 23 | I58: 39 | J58: F.I 25337 | K58: DISE?O DE ARQUITECTURAS CONVERGENTES PARA INFRAESTRUCTURA TECNOLOGICA DE NUBE PRIVADA | L58: 44638 | M58: APROBADO | N58: OCTAVIO JOSE SALCEDO PARRA | R58: ESPACIOS ACADEMICOS DE PROFUNDIZACION | S58: =VLOOKUP(C58,Estados!B:J,9,0) -> boogiedca@gmail.com
A59: 146 | B59: ARTURO VERBEL DE LEON | C59: 20172195007 | D59: 1143355214 | E59: CEDULA DE CIUDADANIA | F59: ESTUDIANTE GRADUADO | G59: 23465 | H59: 23 | I59: 71 | J59: F.I 25534 | K59: INVESTIGACION E INNOVACION: ACTUALIZACION DE TODOS LOS CAMINOS MAS CORTOS EN GRAFOS DINAMICOS CON INSERCION DE ARCOS | L59: 44736 | M59: APROBADO | N59: SERGIO ANDRES ROJAS GALEANO | R59: INVESTIGACION ? INNOVACION | S59: =VLOOKUP(C59,Estados!B:J,9,0) -> arturo.verbel@gmail.com
A60: 147 | B60: JUAN DAVID ARIAS FORERO | C60: 20181195002 | D60: 1022374793 | E60: CEDULA DE CIUDADANIA | F60: ESTUDIANTE GRADUADO | G60: 23267 | H60: 23 | I60: 38 | J60: F.I 25336 | K60: PASANTIA: ANALISIS E IMPLEMENTACION DE ARQUITECTURA PARA MONITOREO DE USO DE TABLEROS EN QUICKSIGHT AWS. CASO DE ESTUDIO - BLACKBOARD DATA. | L60: 44638 | M60: APROBADO | N60: GUSTAVO ADOLFO PUERTO LEGUIZAMON | R60: PASANTIA | S60: =VLOOKUP(C60,Estados!B:J,9,0) -> jdariasforero2008@gmail.com
A61: 148 | B61: NARVAEZ JARAMILLO LUIS ALFREDO | C61: 20181195007 | D61: 1030597409 | E61: CEDULA DE CIUDADANIA | F61: ESTUDIANTE GRADUADO | G61: 23777 | H61: 23 | I61: 124 | J61: F.I 25848 | K61: INVESTIGACION E INNOVACION: MODELO DE OPTIMIZACION PARA LA CALIDAD DEL SERVICIO (QUALITY OF SERVICE, QOS) EN REDES WI-FI (802.11AX) APLICANDO PROGRAMACION MULTIOBJETIVO | L61: 44827 | N61: OCTAVIO JOSE SALCEDO PARRA | R61: INVESTIGACION ? INNOVACION | S61: =VLOOKUP(C61,Estados!B:J,9,0) -> lnarvaezj@hotmail.com
A62: 149 | B62: JUAN DIEGO CASTILLO CRUZ | C62: 20202195002 | D62: 1101759682 | E62: CEDULA DE CIUDADANIA | F62: ESTUDIANTE GRADUADO | G62: 23774 | H62: 23 | I62: 123 | J62: F.I 25845 | K62: PASANTIA: CONSTRUCCION DE UN ESPACIO VIRTUAL CON TUTORIALES DE MACHINE LEARNING E INTELIGENCIA COMPUTACIONAL | L62: 44827 | N62: CESAR ANDREY PERDOMO CHARRY | O62: 7724669 | R62: PASANTIA | S62: =VLOOKUP(C62,Estados!B:J,9,0) -> judcastilloc@correo.udistrital.edu.co
A63: 150 | B63: JAIME ANTONIO AVILA SANCHEZ | C63: 20121195003 | D63: 7174732 | E63: CEDULA DE CIUDADANIA | F63: ESTUDIANTE GRADUADO | G63: 24226 | H63: 24 | I63: 42 | J63: F.I. 26298 | K63: OPTIMIZACION DE LA OPERACION DE UNA MICRORRED RURAL AISLADA ENFOCADA EN COSTOS | L63: 45016 | M63: APROBADO | N63: ELVIS EDUARDO GAONA GARCIA | R63: INVESTIGACION ? INNOVACION | S63: =VLOOKUP(C63,Estados!B:J,9,0) -> jaimejaas@gmail.com
A64: 151 | B64: YENY KATHERINE MU?OZ NU?EZ | C64: 20152195016 | D64: 1032432662 | E64: CEDULA DE CIUDADANIA | F64: ESTUDIANTE GRADUADO | G64: 24424 | H64: 24 | I64: 75 | J64: F.I. 26496 | K64: ANALISIS Y DISE?O DE UNA RED DE SENSORES OPTICOS DISTRIBUIDOS DE LARGA DISTANCIA BASADA EN RED DE DIFRACCION DE BRAGG | L64: 45107 | M64: APROBADO | N64: GUSTAVO ADOLFO PUERTO LEGUIZAMON | R64: INVESTIGACION ? INNOVACION | S64: =VLOOKUP(C64,Estados!B:J,9,0) -> yekamunu@gmail.com
A65: 152 | B65: FREDY ALEXANDER GONZALEZ PRIETO | C65: 20161195008 | D65: 1049612843 | E65: CEDULA DE CIUDADANIA | F65: ESTUDIANTE GRADUADO | G65: 24422 | H65: 24 | I65: 75 | J65: F.I. 26494 | K65: DISE?O E IMPLEMENTACION DE UN ENTORNO IOT EN CULTIVOS DE FEIJOA, EN LA VEREDA DE PIEDRA-LARGA DEL MUNICIPIO DE CIENEGA - BOYACA | L65: 45107 | M65: APROBADO | N65: OCTAVIO JOSE SALCEDO PARRA | O65: 79508767 | R65: MONOGRAFIA | S65: =VLOOKUP(C65,Estados!B:J,9,0) -> fredyagonzalez@hotmail.com
A66: 153 | B66: JORGE ELIECER BELTRAN GARCIA | C66: 20162195003 | D66: 11255923 | E66: CEDULA DE CIUDADANIA | F66: ESTUDIANTE GRADUADO | G66: 24790 | H66: 24 | I66: 136 | J66: F.I. 26862 | K66: DISE?O DE UNA INTERFAZ DIGITAL INTERPRETADORA DE BRAILLE PARA FACILITAR LA COMUNICACION EFECTIVA DOCENTE-ALUMNO-DOCENTE EN LA INSTITUCION EDUCATIVA TECNOLOGICO DE MADRID | L66: 45275 | M66: APROBADO | N66: EDMUNDO VEGA OSORIO | O66: 19165408 | R66: INVESTIGACION, INVESTIGACION ? CREACION, INNOVACION | S66: =VLOOKUP(C66,Estados!B:J,9,0) -> jotaebeltrangarcia@gmail.com
A67: 154 | B67: MIGUEL ANGEL CORZO MU?OZ | C67: 20181195003 | D67: 79907126 | E67: CEDULA DE CIUDADANIA | F67: ESTUDIANTE GRADUADO | G67: 24791 | H67: 24 | I67: 136 | J67: F.I. 26863 | K67: PRONOSTICO DE CONTAMINACION POR MATERIAL PARTICULADO MEDIANTE REDES NEURONALES ARTIFICIALES PARA GENERAR UN SISTEMA DE ALARMAS AMBIENTALES | L67: 45275 | M67: APROBADO | N67: OCTAVIO JOSE SALCEDO PARRA | R67: INVESTIGACION ? INNOVACION | S67: =VLOOKUP(C67,Estados!B:J,9,0) -> mcorzom@gmail.com
A68: 155 | B68: BRAYAN ANDRES BERMUDEZ BUCURU | C68: 20182195005 | D68: 1010221959 | E68: CEDULA DE CIUDADANIA | F68: ESTUDIANTE GRADUADO | G68: 24227 | H68: 24 | I68: 42 | J68: F.I. 26299 | K68: IMPLEMENTACION DE UNA PLATAFORMA PARA INTERNET DE LAS COSAS DE LA NUBE DE AMAZON WEB SERVICES EN UN SISTEMA EMBEBIDO PARA LA ADQUISICION Y PROCESAMIENTO DE DATOS | L68: 45016 | M68: APROBADO | N68: CESAR ANDREY PERDOMO CHARRY | O68: 7724669 | S68: =VLOOKUP(C68,Estados!B:J,9,0) -> babermudezb1@gmail.com
A69: 156 | B69: ANDRES CAMILO LOPEZ GARCIA | C69: 20191195005 | D69: 1022395511 | E69: CEDULA DE CIUDADANIA | F69: ESTUDIANTE GRADUADO | G69: 24228 | H69: 24 | I69: 42 | J69: F.I. 26300 | K69: DISE?O E IMPLEMENTACION DE UN ALGORITMO Y UNA PLATAFORMA PARA EL ANALISIS DESCRIPTIVO Y PREDICTIVO DE LA PRODUCCION ENERGETICA DE LA TURBINA HAWT-VG BIOINSPIRADA EN PLUMAS DORSALES DE HALCON PEREGRINO | L69: 45016 | M69: APROBADO | N69: ELVIS EDUARDO GAONA GARCIA | O69: 79950025 | R69: INVESTIGACION ? INNOVACION | S69: =VLOOKUP(C69,Estados!B:J,9,0) -> anclopezg@correo.udistrital.edu.co
A70: 157 | B70: STIVEN ORLANDO ROJAS PULIDO | C70: 20161195013 | D70: 80865137 | E70: CEDULA DE CIUDADANIA | F70: ESTUDIANTE GRADUADO | G70: 25099 | H70: 25 | I70: 50 | J70: F.I. 27171 | K70: DISE?O DE UN SISTEMA DE SUPERVISION Y MONITOREO EN TIEMPO REAL PARA AGENTES CONTAMINANTES EN EL AIRE, APLICADO A LA VEREDA MOCHUELO ALTO ALEDA?A AL RELLENO SANITARIO DO?A JUANA (RSDJ) EN BOGOTA - COLOMBIA | L70: 45373 | M70: APROBADO | N70: ALVARO ESPINEL ORTEGA | R70: INVESTIGACION ? INNOVACION | S70: =VLOOKUP(C70,Estados!B:J,9,0) -> sorojasp@udistrital.edu.co
A71: 158 | B71: AREVALO SILVA JOSE AGUSTIN | C71: 20171195001 | D71: 79956049 | E71: CEDULA DE CIUDADANIA | F71: ESTUDIANTE GRADUADO | G71: 25213 | H71: 25 | I71: 69 | J71: F.I. 27285 | K71: DESARROLLO DE UN PROTOTIPO DE SISTEMA PARA EL APOYO EN LA MOVILIDAD AUTONOMA DE PERSONAS INVIDENTES EN EXTERIORES | L71: 45457 | M71: APROBADO | N71: CARLOS ENRIQUE MONTENEGRO MARIN | R71: INVESTIGACION ? INNOVACION | S71: =VLOOKUP(C71,Estados!B:J,9,0) -> agustin.arevalo@gmail.com
A72: 159 | B72: MARIA ALEJANDRA QUEVEDO VERA | C72: 20172195014 | D72: 1032358776 | E72: CEDULA DE CIUDADANIA | F72: ESTUDIANTE GRADUADO | G72: 25499 | H72: 25 | I72: 117 | J72: F.I. 27571 | K72: MODELO DE ARQUITECTURA IOT PARA UN SISTEMA DE MONITOREO DE TEMPERATURA DE PERSONAS DE LA TERCERA EDAD Y LACTANTES | L72: 45562 | M72: APROBADO | N72: ROBERTO FERRO ESCOBAR | O72: 79657603 | S72: =VLOOKUP(C72,Estados!B:J,9,0) -> alejandra.quevedo85@gmail.com
A73: 160 | B73: SANTIAGO ANDRES PE?A ARISMENDI | C73: 20181195008 | D73: 1026284597 | E73: CEDULA DE CIUDADANIA | F73: ESTUDIANTE GRADUADO | G73: 25497 | H73: 25 | I73: 116 | J73: F.I. 27569 | K73: DESARROLLO DE UN SISTEMA DE IOT CON MACHINE LEARNING PARA LA DETECCION TEMPRANA DE CRISIS EPILEPTICAS | L73: 45562 | M73: APROBADO | N73: OCTAVIO JOSE SALCEDO PARRA | R73: INVESTIGACION, INVESTIGACION ? CREACION, INNOVACION | S73: =VLOOKUP(C73,Estados!B:J,9,0) -> saapenaa@correo.udistrital.edu.co
A74: 161 | B74: RAUL ROMERO ORTEGA | C74: 20181195010 | D74: 80205440 | E74: CEDULA DE CIUDADANIA | F74: ESTUDIANTE GRADUADO | G74: 25501 | H74: 25 | I74: 117 | J74: F.I. 27573 | K74: MODELO PARA CLASIFICACION DE PRECIPITACIONES ESTRATIFORMES Y CONVECTIVAS EN ZONA ECUATORIAL USANDO DATOS DE RADARES METEOROLOGICOS | L74: 45562 | M74: APROBADO | N74: CESAR ANDREY PERDOMO CHARRY | R74: INVESTIGACION ? INNOVACION | S74: =VLOOKUP(C74,Estados!B:J,9,0) -> rromeroo7519@gmail.com
A75: 162 | B75: IVAN DARIO BELLO GONZALEZ | C75: 20191195002 | D75: 1031138497 | E75: CEDULA DE CIUDADANIA | F75: ESTUDIANTE GRADUADO | G75: 25608 | H75: 25 | I75: 135 | J75: F.I. 27680 | K75: METODOLOGIA PARA LA ELECCION DE MODELOS DE LENGUAJE DE GRAN TAMA?O (LLMS) EN APLICACIONES DE PREDICCION METEREOLOGICAS A TRAVES DE ALGORITMOS DE APRENDIZAJE AUTOMATICO SOBRE ENTORNOS DE COMPUTACION EN LA NUBE Y CAPTURAS DE DATOS A TRAVES DE IOT | L75: 45639 | M75: APROBADO | N75: ELVIS EDUARDO GAONA GARCIA | R75: INVESTIGACION, INVESTIGACION ? CREACION, INNOVACION | S75: =VLOOKUP(C75,Estados!B:J,9,0) -> idbellog@gmail.com
A76: 163 | B76: ANGIE PATRICIA RODRIGUEZ HERNANDEZ | C76: 20201195007 | D76: 1032484102 | E76: CEDULA DE CIUDADANIA | F76: ESTUDIANTE GRADUADO | G76: 25612 | H76: 25 | I76: 136 | J76: F.I. 27684 | K76: MECANISMO DE CLASIFICACION DE PAISAJES BASADO EN MUESTREO MULTIESCALA Y APRENDIZAJE AUTOMATICO | L76: 45639 | M76: APROBADO | N76: MIGUEL ALBERTO MELGAREJO REY | O76: 79974515 | R76: INVESTIGACION, INVESTIGACION ? CREACION, INNOVACION | S76: =VLOOKUP(C76,Estados!B:J,9,0) -> anprodriguezh@udistrital.edu.co
A77: 164 | B77: MANUEL ROMERO PE?A | C77: 20201195009 | D77: 1019112068 | E77: CEDULA DE CIUDADANIA | F77: ESTUDIANTE GRADUADO | G77: 25100 | H77: 25 | I77: 50 | J77: F.I. 27172 | K77: MODELO DE PERFIL DE INDICE PARA FIBRA OPTICA DE POCOS MODOS | L77: 45373 | M77: APROBADO | N77: GUSTAVO ADOLFO PUERTO LEGUIZAMON | R77: MONOGRAFIA | S77: =VLOOKUP(C77,Estados!B:J,9,0) -> mromerop@correo.udistrital.edu.co
A78: 165 | B78: JOHN NEIVER BOJACA CABRA | C78: 20211195001 | D78: 81720127 | E78: CEDULA DE CIUDADANIA | F78: ESTUDIANTE GRADUADO | G78: 25496 | H78: 25 | I78: 116 | J78: F.I. 27568 | K78: NETWORK SLICING EN REDES 5G PARA TRAFICO STREAMING APLICANDO DEEP LEARNING | L78: 45562 | M78: APROBADO | N78: OCTAVIO JOSE SALCEDO PARRA | R78: ESPACIOS ACADEMICOS DE PROFUNDIZACION | S78: =VLOOKUP(C78,Estados!B:J,9,0) -> john.bojaca@gmail.com
A79: 2 | B79: BIBIANA ROCIO RIVERA GUERRERO | C79: 20101295013 | D79: 53120508 | E79: CEDULA DE CIUDADANIA | F79: ESTUDIANTE GRADUADO | G79: 16985 | H79: 17 | I79: 141 | J79: F.I. 19044 | K79: CLASIFICACION DE COBERTURA DEL SUELO SOBRE AREA URBANA A PARTIR DE IMAGENES SATELITALES DE MEDIANA RESOLUCION EMPLEANDO REGRESION-KRIGING: UNA COMPARACION CON OTROS METODOS NO CONVENCIONALES | L79: 42586 | M79: APROBADO | N79: CARLOS EDUARDO MELO MARTINEZ | O79: 79591170 | R79: GRADO | S79: =VLOOKUP(C79,Estados!B:J,9,0) -> bibianarocio1984@gmail.com
A80: 3 | B80: ISMAEL OSORIO BAQUERO | C80: 20121395011 | D80: 14235383 | E80: CEDULA DE CIUDADANIA | F80: ESTUDIANTE GRADUADO | G80: 16505 | H80: 17 | I80: 60 | J80: F.I. 18562 | K80: ESTUDIO DE LA VARIABLE ALTIMETRICA (Z) SOBRE UN MODELO DIGITAL DE ELEVACION (MDE) POR MEDIO DE TECNOLOGIA LIDAR TERRESTRE | L80: 42447 | M80: APROBADO | N80: OMAR FRANCISCO PATI?O SILVA | O80: 79357153 | R80: GRADO | S80: =VLOOKUP(C80,Estados!B:J,9,0) -> iosoriob@udistrital.edu.co
A81: 4 | B81: INDIRA PAOLA PACHON CENDALES | C81: 20121395012 | D81: 53091016 | E81: CEDULA DE CIUDADANIA | F81: ESTUDIANTE GRADUADO | G81: 16984 | H81: 17 | I81: 140 | J81: F.I. 19043 | K81: EVALUACION DE LA CONDICION DE ENVEJECIMIENTO EN PAVIMENTOS FLEXIBLES MEDIANTE TECNICAS DE ESPECTRORADIOMETRIA Y CLASIFICACION EN IMAGENES MULTIESPECTRALES | L81: 42586 | M81: APROBADO | N81: WILMAR DARIO FERNANDEZ | O81: 79494815 | R81: GRADO | S81: =VLOOKUP(C81,Estados!B:J,9,0) -> indira197@gmail.com
A82: 5 | B82: MAURICIO FERNANDO ROCHA SALAMANCA | C82: 20122395008 | D82: 79625956 | E82: CEDULA DE CIUDADANIA | F82: ESTUDIANTE GRADUADO | G82: 17158 | H82: 17 | I82: 169 | J82: F.I. 19217 | K82: INTERPOLACION ESPACIAL EN 3 DOMINIOS (3D) DE DATOS SISMICOS DE REFLEXION EN EL BLOQUE LLANOS 26, CUENCA DE LOS LLANOS ORIENTALES, COLOMBIA | L82: 42608 | M82: APROBADO | N82: ABDALA FRANCISCO VILLA ELJACH | O82: 7437464 | R82: GRADO | S82: =VLOOKUP(C82,Estados!B:J,9,0) -> mrocha73@gmail.com
A83: 6 | B83: IVAN ANDRES REYES GOMEZ | C83: 20121395017 | D83: 80803723 | E83: CEDULA DE CIUDADANIA | F83: ESTUDIANTE GRADUADO | G83: 17866 | H83: 18 | I83: 45 | J83: F.I 19925 | K83: MAGISTER EN CIENCIAS DE LA INFORMACION Y LAS COMUNICACIONES | L83: 42818 | M83: APROBADO | N83: ORLANDO RIA?O MELO | O83: 19350861 | R83: GRADO | S83: =VLOOKUP(C83,Estados!B:J,9,0) -> iareyesgomez@gmail.com
A84: 7 | B84: OSCAR JAVIER ESPEJO VALERO | C84: 20122395004 | D84: 80725497 | E84: CEDULA DE CIUDADANIA | F84: ESTUDIANTE GRADUADO | G84: 18371 | H84: 18 | I84: 137 | J84: F.I 20431 | K84: DESARROLLO DE UNA METODOLOGIA PARA ESTIMACION DE LA DEFORESTACION MEDIANTE EL ANALISIS MULTITEMPORAL DE IMAGENES MULTIESPECTRALES EN UN ENTORNO DE ANALISIS BASADO EN OBJETOS GEOGRAFICOS (GEOBIA) | L84: 42993 | M84: APROBADO | N84: WILLIAN BARRAGAN ZAQUE | O84: 79873683 | R84: MONOGRAFIA | S84: =VLOOKUP(C84,Estados!B:J,9,0) -> ojespejo@gmail.com
A85: 8 | B85: DAVID DONCEL BALLEN | C85: 20121395003 | D85: 80202521 | E85: CEDULA DE CIUDADANIA | F85: ESTUDIANTE GRADUADO | G85: 19526 | H85: 19 | I85: 96 | J85: F.I. 21588 | K85: INNOVACION :ESTIMACION DE IRRADIANCIA SOLAR APLICANDO EL ALGORITMO HELIOSAT 1 CON IMAGENES SATELITALES GOES EN LA REGION CUNDIBOYACENSE PARA EL A?O 2011 | L85: 43259 | M85: APROBADO | N85: RUBEN JAVIER MEDINA DAZA | O85: 79572003 | R85: INVESTIGACION ? INNOVACION | S85: =VLOOKUP(C85,Estados!B:J,9,0) -> ddoncelb@gmail.com
A86: 9 | B86: MARIAM RIVAS DIAZGRANADOS | C86: 20121395014 | D86: 53107576 | E86: CEDULA DE CIUDADANIA | F86: ESTUDIANTE GRADUADO | G86: 19173 | H86: 19 | I86: 37 | J86: F.I. 21235 | K86: INNOVACION :EVALUACION DE LA TEXTURA Y LA RUGOSIDAD DE PAVIMENTOS FLEXIBLES MEDIANTE IMAGENES TOMADAS A PARTIR DE CAMARA NO METRICA NIKON COOLPIX S2900 | L86: 43182 | M86: APROBADO | N86: WILSON VARGAS VARGAS | O86: 79892283 | R86: INVESTIGACION ? INNOVACION | S86: =VLOOKUP(C86,Estados!B:J,9,0) -> mariam_rivas@hotmail.com
A87: 10 | B87: LA ROSA LORENA LIZETH HERRERA DE | C87: 20122395006 | D87: 1026274281 | E87: CEDULA DE CIUDADANIA | F87: ESTUDIANTE GRADUADO | G87: 19699 | H87: 19 | I87: 125 | J87: F.I. 21761 | K87: MODELAMIENTO ESTADISTICO PARA LA PRECISION DE UN ESCANER LASER TERRESTRE | L87: 43357 | M87: APROBADO | N87: WILLIAN BARRAGAN ZAQUE | O87: 79873683 | R87: INVESTIGACION ? INNOVACION | S87: =VLOOKUP(C87,Estados!B:J,9,0) -> lorenadelarosa2@hotmail.com
A88: 11 | B88: JAVIER FELIPE MONCADA SANCHEZ | C88: 20122395007 | D88: 79754586 | E88: CEDULA DE CIUDADANIA | F88: ESTUDIANTE GRADUADO | G88: 19398 | H88: 19 | I88: 75 | J88: F.I. 21460 | K88: DISE?O Y DESARROLLO DE UN FRAMEWORK PARA EL ANALISIS DE REDES EN HERRAMIENTAS SIG, IMPLEMENTANDO EL ALGORITMO DE DIJKSTRA QUE SOPORTE LA IMPEDANCIA DE GIROS | L88: 43203 | M88: APROBADO | N88: CARLOS ENRIQUE MONTENEGRO MARIN | O88: 80093200 | S88: =VLOOKUP(C88,Estados!B:J,9,0) -> jfmoncadas@gmail.com
A89: 12 | B89: OMAR CASTRILLON OSORIO | C89: 20131395002 | D89: 75107270 | E89: CEDULA DE CIUDADANIA | F89: ESTUDIANTE GRADUADO | G89: 19163 | H89: 19 | I89: 35 | J89: F.I. 21225 | K89: INNOVACION :METODOLOGIA PARA EL ANALISIS DE LA INVASION DEL ESPACIO PUBLICO EN LA CIUDAD DE BOGOTA, UTILIZANDO COLABORACION CIUDADANA (CROWDSOURCING), ZONA DE ESTUDIO CHAPINERO | L89: 43182 | M89: APROBADO | N89: LUZ ANGELA ROCHA SALAMANCA | O89: 51610577 | R89: INVESTIGACION ? INNOVACION | S89: =VLOOKUP(C89,Estados!B:J,9,0) -> oco1117@gmail.com
A90: 13 | B90: JHON CAMILO MATIZ LEON | C90: 20141395003 | D90: 80075955 | E90: CEDULA DE CIUDADANIA | F90: ESTUDIANTE GRADUADO | G90: 19165 | H90: 19 | I90: 36 | J90: F.I. 21227 | K90: INNOVACION :METODOLOGIA PARA DETERMINAR EL MODELO ESPACIAL DEL GRADIENTE GEOTERMICO EN LAS CUENCAS SEDIMENTARIAS DEL VALLE MEDIO DEL MAGDALENA, CORDILLERA ORIENTAL Y LLANOS ORIENTALES EN COLOMBIA | L90: 43182 | M90: APROBADO | N90: ANDRES CARDENAS CONTRERAS | O90: 79752717 | R90: INVESTIGACION ? INNOVACION | S90: =VLOOKUP(C90,Estados!B:J,9,0) -> ing.camilo.matiz@gmail.com
A91: 14 | B91: RAUL ALEJANDRO MURILLO CASTA?EDA | C91: 20151295009 | D91: 1070951512 | E91: CEDULA DE CIUDADANIA | F91: ESTUDIANTE GRADUADO | G91: 20090 | I91: 190 | J91: F.I. 22152 | K91: IMPLEMENTACION DEL METODO MAQUINAS DE SOPORTE VECTORIAL EN BASES DE DATOS ESPACIALES PARA ANALISIS DE CLASIFICACION SUPERVISADA EN IMAGENES DE SENSORES REMOTOS. | L91: 43441 | M91: APROBADO | N91: ALVARO ENRIQUE ORTIZ DAVILA | S91: =VLOOKUP(C91,Estados!B:J,9,0) -> alejomurillo7@hotmail.com
A92: 15 | B92: LAURA ANGELICA CADENA CONTRERAS | C92: 20162395002 | D92: 1013648575 | E92: CEDULA DE CIUDADANIA | F92: ESTUDIANTE GRADUADO | G92: 19161 | H92: 19 | I92: 35 | J92: F.I. 21223 | K92: MODELO DE CLASIFICACION DE HIDROMETEOROS PARA ZONAS ECUATORIALES A PARTIR DE OBSERVABLES DE RADAR METEOROLOGICO | L92: 43182 | M92: APROBADO | N92: ERNESTO GOMEZ VARGAS | O92: 74373175 | R92: MONOGRAFIA | S92: =VLOOKUP(C92,Estados!B:J,9,0) -> lacadenacontreras@gmail.com
A93: 16 | B93: DIANA CAROLINA FIGUEROA CEFERINO | C93: 20121395004 | D93: 52884117 | E93: CEDULA DE CIUDADANIA | F93: ESTUDIANTE GRADUADO | G93: 20877 | H93: 20 | I93: 117 | J93: F.I. 22941 | K93: METODOLOGIA PARA LA TRANSFORMACION DE DATOS GEOGRAFICOS A RECURSOS RDF | L93: 43728 | M93: APROBADO | N93: CESAR ANDREY PERDOMO CHARRY | R93: INVESTIGACION ? INNOVACION | S93: =VLOOKUP(C93,Estados!B:J,9,0) -> carofc@gmail.com
A94: 17 | B94: YENNY ESPINOSA GOMEZ | C94: 20122395005 | D94: 52379603 | E94: CEDULA DE CIUDADANIA | F94: ESTUDIANTE GRADUADO | G94: 20599 | H94: 20 | I94: 70 | J94: F.I. 22662 | K94: "DESARROLLO DE UN LENGUAJE DE DOMINIO ESPECIFICO (DSL) GRAFICO PARA EL MODELAMIENTO DE BASES DE DATOS ESPACIALES" | L94: 43623 | M94: APROBADO | N94: JAVIER FELIPE MONCADA SANCHEZ | R94: MONOGRAFIA | S94: =VLOOKUP(C94,Estados!B:J,9,0) -> yespinosa@udistrital.edu.co
A95: 18 | B95: ROJAS BARBOSA SERGIO ALEJANDRO | C95: 20142395004 | D95: 80896709 | E95: CEDULA DE CIUDADANIA | F95: ESTUDIANTE GRADUADO | G95: 20878 | H95: 20 | I95: 117 | J95: F.I. 22942 | K95: DESARROLLO Y PROPUESTA METODOLOGICA PARA EL EMPLEO DE LOS CAMPOS ALEATORIOS DE MARKOV APLICADOS A TECNICAS DE CLASIFICACION DE COBERTURAS EN IMAGENES DE LA SUPERFICIE TERRESTRE | L95: 43728 | M95: APROBADO | N95: RUBEN JAVIER MEDINA DAZA | R95: INVESTIGACION ? INNOVACION | S95: =VLOOKUP(C95,Estados!B:J,9,0) -> seralejo2004@gmail.com
A96: 19 | B96: ANDRES CAMILO FLOREZ GARCIA | C96: 20161395006 | D96: 1018454644 | E96: CEDULA DE CIUDADANIA | F96: ESTUDIANTE GRADUADO | G96: 22134 | H96: 21 | I96: 139 | J96: F.I 24200 | K96: PREDICCION ESPACIAL DE PROCESOS DE REMOCION EN MASA A PARTIR DE LA CONSTRUCCION DE UN MODELO HIBRIDO DE APRENDIZAJE DE MAQUINA BASADO EN ESTRUCTURAS DE DEPENDENCIA ESPACIO-TEMPORALES | L96: 44174 | M96: APROBADO | N96: JOSE NELSON PEREZ CASTILLO | R96: INVESTIGACION ? INNOVACION | S96: =VLOOKUP(C96,Estados!B:J,9,0) -> andrescfg@gmail.com
A97: 20 | B97: IVAN DARIO CARRILLO DURAN | C97: 20171395005 | D97: 1002021534 | E97: CEDULA DE CIUDADANIA | F97: ESTUDIANTE GRADUADO | G97: 21971 | H97: 21 | I97: 112 | J97: F.I 24037 | K97: INVESTIGACION E INNOVACION: ELABORACION DE UN ALGORITMO APLICADO A IMAGENES OBTENIDAS POR DRON PARA LA CUANTIFICACION DE FITOPLANCTON. | L97: 44118 | M97: APROBADO | N97: RUBEN JAVIER MEDINA DAZA | O97: 79572003 | R97: INVESTIGACION ? INNOVACION | S97: =VLOOKUP(C97,Estados!B:J,9,0) -> ivancho4321@hotmail.com
A98: 21 | B98: CAROLINA GIRON LEON | C98: 20172395006 | D98: 53014101 | E98: CEDULA DE CIUDADANIA | F98: ESTUDIANTE GRADUADO | G98: 22081 | H98: 21 | I98: 130 | J98: F.I 24147 | K98: MODELO DE ARQUITECTURA EMPRESARIAL ORIENTADO A LAS EMPRESAS PRIVADAS COLOMBIANAS DEL SECTOR DE OBRAS CIVILES | L98: 44161 | M98: APROBADO | N98: GUSTAVO ADOLFO PUERTO LEGUIZAMON | R98: ESPACIOS ACADEMICOS DE PROFUNDIZACION | S98: =VLOOKUP(C98,Estados!B:J,9,0) -> cleongiron@gmail.com
A99: 22 | B99: WILMER HARVEY VALLEJO AREVALO | C99: 20172395020 | D99: 1018442787 | E99: CEDULA DE CIUDADANIA | F99: ESTUDIANTE GRADUADO | G99: 21534 | H99: 21 | I99: 39 | J99: F.I 23600 | K99: INVESTIGACION E INNOVACION: GENERACION DE UN MODELO DE PREDICCION ESPACIAL DE LA DEFORESTACION EN LA JURISDICCION DE CORPOCHIVOR PARA EL PERIODO 2017-2047 BASADO EN MAPAS DE COBERTURA Y ANALISIS DE VARIABLES ESPACIALES CON DINAMICA EGO | L99: 43994 | M99: APROBADO | N99: RUBEN JAVIER MEDINA DAZA | O99: 79572003 | R99: INVESTIGACION ? INNOVACION | S99: =VLOOKUP(C99,Estados!B:J,9,0) -> whvallejoa@gmail.com
A100: 23 | B100: JHON FREDY LOPEZ LOPEZ | C100: 20131395007 | D100: 1023863636 | E100: CEDULA DE CIUDADANIA | F100: ESTUDIANTE GRADUADO | G100: 23032 | H100: 22 | I100: 146 | J100: F.I 25101 | K100: PASANTIA: GENERACION DE MODELOS DIGITALES DEL TERRENO DE ALTA PRECISION, EN LA PRIMERA CIUDAD ESPA?OLA FUNDADA EN TIERRA FIRME DE AMERICA | L100: 44552 | M100: APROBADO | N100: WILLIAN BARRAGAN ZAQUE | R100: PASANTIA | S100: =VLOOKUP(C100,Estados!B:J,9,0) -> jfredyl@gmail.com
...

Sheet Egresado ya
A1: Id | B1: Hora de inicio | C1: Hora de finalización | D1: Correo electrónico | E1: Nombre | F1: Total de puntos | G1: Comentarios del cuestionario | H1: Hora de publicación de la calificación | I1: Indique su nombre completo | J1: Puntos: Indique su nombre completo | K1: Comentarios: Indique su nombre completo | L1: Digite su número de cedula | M1: Puntos: Digite su número de cedula | N1: Comentarios: Digite su número de cedula | O1: ¿En que rango de edad se encuentra? | P1: Puntos: ¿En que rango de edad se encuentra? | Q1: Comentarios: ¿En que rango de edad se encuentra? | R1: Por favor actualice su número de contacto telefónico | S1: Puntos: Por favor actualice su número de contacto telefónico | T1: Comentarios: Por favor actualice su número de contacto telefónico | U1: ¿En qué énfasis se encuentra inscrito? | V1: Puntos: ¿En qué énfasis se encuentra inscrito? | W1: Comentarios: ¿En qué énfasis se encuentra inscrito? | X1: ¿En qué Modalidad o Metodología se encuentra inscrito? | Y1: Puntos: ¿En qué Modalidad o Metodología se encuentra inscrito? | Z1: Comentarios: ¿En qué Modalidad o Metodología se encuentra inscrito? | AA1: Las competencias adquiridas durante mi formación en la maestría (técnicas, investigativas, pedagógicas, etc.) han sido suficientes y relevantes para mi desarrollo profesional. | AB1: Puntos: Las competencias adquiridas durante mi formación en la maestría (técnicas, investigativas, pedagógicas, etc.) han sido suficientes y relevantes para mi desarrollo profesional. | AC1: Comentarios: Las competencias adquiridas durante mi formación en la maestría (técnicas, investigativas, pedagógicas, etc.) han sido suficientes y relevantes para mi desarrollo profesional. | AD1: Considero que mi formación en la maestría ha influido positivamente en mi desarrollo profesional, así como en la mejora de oportunidades en mi campo laboral. | AE1: Puntos: Considero que mi formación en la maestría ha influido positivamente en mi desarrollo profesional, así como en la mejora de oportunidades en mi campo laboral. | AF1: Comentarios: Considero que mi formación en la maestría ha influido positivamente en mi desarrollo profesional, así como en la mejora de oportunidades en mi campo laboral. | AG1: ¿Qué aspectos de la Maestría en Ciencias de la Información y las Comunicaciones considerarías mejorar para incrementar la pertinencia del perfil de formación y las competencias adquiridas para el desa | AH1: Puntos: ¿Qué aspectos de la Maestría en Ciencias de la Información y las Comunicaciones considerarías mejorar para incrementar la pertinencia del perfil de formación y las competencias adquiridas para el desa | AI1: Comentarios: ¿Qué aspectos de la Maestría en Ciencias de la Información y las Comunicaciones considerarías mejorar para incrementar la pertinencia del perfil de formación y las competencias adquiridas para el desa | AJ1: Considero que las estrategias de flexibilidad curricular me permitieron personalizar mi formación de acuerdo con mis objetivos profesionales y académicos. | AK1: Puntos: Considero que las estrategias de flexibilidad curricular me permitieron personalizar mi formación de acuerdo con mis objetivos profesionales y académicos. | AL1: Comentarios: Considero que las estrategias de flexibilidad curricular me permitieron personalizar mi formación de acuerdo con mis objetivos profesionales y académicos. | AM1: ¿Podrías proporcionar ejemplos específicos de cómo las rutas de formación alternativas te beneficiaron para tu desarrollo académico y profesional? | AN1: Puntos: ¿Podrías proporcionar ejemplos específicos de cómo las rutas de formación alternativas te beneficiaron para tu desarrollo académico y profesional? | AO1: Comentarios: ¿Podrías proporcionar ejemplos específicos de cómo las rutas de formación alternativas te beneficiaron para tu desarrollo académico y profesional? | AP1: Considero que la interacción con homólogos nacionales e internacionales me permitió mejorar mis competencias académicas y científicas, así como las oportunidades de desarrollo profesional. | AQ1: Puntos: Considero que la interacción con homólogos nacionales e internacionales me permitió mejorar mis competencias académicas y científicas, así como las oportunidades de desarrollo profesional. | AR1: Comentarios: Considero que la interacción con homólogos nacionales e internacionales me permitió mejorar mis competencias académicas y científicas, así como las oportunidades de desarrollo profesional. | AS1: ¿Podrías proporcionar ejemplos específicos de proyectos, investigaciones o colaboraciones exitosas que resultaron de la cooperación académica y científica promovida por la Maestría en Ciencias de la I | AT1: Puntos: ¿Podrías proporcionar ejemplos específicos de proyectos, investigaciones o colaboraciones exitosas que resultaron de la cooperación académica y científica promovida por la Maestría en Ciencias de la I | AU1: Comentarios: ¿Podrías proporcionar ejemplos específicos de proyectos, investigaciones o colaboraciones exitosas que resultaron de la cooperación académica y científica promovida por la Maestría en Ciencias de la I | AV1: Considero que el representante estudiantil y de egresados en los diferentes escenarios institucionales, ha sido valorada y ha influido en las decisiones orientadas al mejoramiento de la Maestría en Ci | AW1: Puntos: Considero que el representante estudiantil y de egresados en los diferentes escenarios institucionales, ha sido valorada y ha influido en las decisiones orientadas al mejoramiento de la Maestría en Ci | AX1: Comentarios: Considero que el representante estudiantil y de egresados en los diferentes escenarios institucionales, ha sido valorada y ha influido en las decisiones orientadas al mejoramiento de la Maestría en Ci | AY1: ¿Cuál es su campo laboral actual? | AZ1: Puntos: ¿Cuál es su campo laboral actual? | BA1: Comentarios: ¿Cuál es su campo laboral actual? | BB1: ¿En qué sector se desempeña su trabajo actual? | BC1: Puntos: ¿En qué sector se desempeña su trabajo actual? | BD1: Comentarios: ¿En qué sector se desempeña su trabajo actual? | BE1: ¿El trabajo que realiza actualmente se relaciona directamente con los conocimientos adquiridos en la maestría? | BF1: Puntos: ¿El trabajo que realiza actualmente se relaciona directamente con los conocimientos adquiridos en la maestría? | BG1: Comentarios: ¿El trabajo que realiza actualmente se relaciona directamente con los conocimientos adquiridos en la maestría? | BH1: ¿Siente que la maestría te ha abierto nuevas oportunidades laborales? | BI1: Puntos: ¿Siente que la maestría te ha abierto nuevas oportunidades laborales? | BJ1: Comentarios: ¿Siente que la maestría te ha abierto nuevas oportunidades laborales? | BK1: ¿Podría indicar el nombre de la empresa/compañía con la que labora actualmente? | BL1: Puntos: ¿Podría indicar el nombre de la empresa/compañía con la que labora actualmente? | BM1: Comentarios: ¿Podría indicar el nombre de la empresa/compañía con la que labora actualmente? | BN1: Como parte del proceso de autoevaluación y Acreditación de Alta Calidad, la Universidad requiere contactar a los empleadores de nuestros estudiantes. | BO1: Puntos: Como parte del proceso de autoevaluación y Acreditación de Alta Calidad, la Universidad requiere contactar a los empleadores de nuestros estudiantes. | BP1: Comentarios: Como parte del proceso de autoevaluación y Acreditación de Alta Calidad, la Universidad requiere contactar a los empleadores de nuestros estudiantes.
BN2: Por lo tanto, le solicitamos de ser posible, prop | BO2: Por lo tanto, le solicitamos de ser posible, prop | BP2: Por lo tanto, le solicitamos de ser posible, prop
A3: 1 | B3: 45719.517 | C3: 45719.518 | D3: anonymous | I3: Julio Armando Cuellar Gutierrez | J3: 0 | L3: 1032423220 | M3: 0 | O3: 31 a 40 | P3: 0 | R3: 34634043974 | S3: 0 | U3: Geomtatica | V3: 0 | X3: Investigación | Y3: 0 | AA3: Totalmente de acuerdo. | AB3: 0 | AD3: Totalmente de acuerdo. | AE3: 0 | AG3: Profesionales excelente profesores | AH3: 0 | AJ3: Totalmente de acuerdo. | AK3: 0 | AM3: Es flexible | AN3: 0 | AP3: Totalmente de acuerdo. | AQ3: 0 | AS3: Estoy haciendo el doctorado fuera del país | AT3: 0 | AV3: Totalmente de acuerdo. | AW3: 0 | AY3: Ingeniera | AZ3: 0 | BB3: Sector primario (agricultura, ganadería, pesca, minería) | BC3: 0 | BE3: Totalmente de acuerdo. | BF3: 0 | BH3: Totalmente de acuerdo. | BI3: 0 | BK3: Faro | BL3: 0 | BN3: Shawn Smith | BO3: 0
A4: 2 | B4: 45719.518 | C4: 45719.521 | D4: anonymous | I4: José Daniel Peña Meneses | J4: 0 | L4: 80111613 | M4: 0 | O4: 41 a 50 | P4: 0 | R4: 3163944253 | S4: 0 | U4: Ingeniería de Software | V4: 0 | X4: Profundización | Y4: 0 | AA4: En desacuerdo. | AB4: 0 | AD4: De acuerdo. | AE4: 0 | AG4: Darle un enfoque más hacia lo gerencia que lo técnico | AH4: 0 | AJ4: De acuerdo. | AK4: 0 | AM4: Me permitió escoger las areas de mi preferencia. | AN4: 0 | AP4: Ni en acuerdo, ni en desacuerdo. | AQ4: 0 | AS4: Ninguna | AT4: 0 | AV4: Totalmente en desacuerdo. | AW4: 0 | AY4: Arquitecto de soluciones | AZ4: 0 | BB4: Tecnología (desarrollo de software, IA, ciberseguridad, telecomunicaciones) | BC4: 0 | BE4: De acuerdo. | BF4: 0 | BH4: De acuerdo. | BI4: 0 | BK4: PersonalSoft | BL4: 0 | BN4: NA | BO4: 0
A5: 3 | B5: 45719.518 | C5: 45719.521 | D5: anonymous | I5: Justo Reinaldo Arias omaña | J5: 0 | L5: 88197450 | M5: 0 | O5: 51 o más | P5: 0 | R5: 3133680989 | S5: 0 | U5: Sistemas de información | V5: 0 | X5: Investigación | Y5: 0 | AA5: Totalmente de acuerdo. | AB5: 0 | AD5: Totalmente de acuerdo. | AE5: 0 | AG5: Más énfasis en AI | AH5: 0 | AJ5: Totalmente de acuerdo. | AK5: 0 | AM5: Variedad de tópicos de TI de punta | AN5: 0 | AP5: Totalmente de acuerdo. | AQ5: 0 | AS5: NA | AT5: 0 | AV5: Totalmente de acuerdo. | AW5: 0 | AY5: Docencia | AZ5: 0 | BB5: Sector terciario (comercio, servicios: educación, salud, finanzas, etc.) | BC5: 0 | BE5: Totalmente de acuerdo. | BF5: 0 | BH5: Totalmente de acuerdo. | BI5: 0 | BK5: Prefiero no incluirlo | BL5: 0 | BN5: Prefiero no participar | BO5: 0
A6: 4 | B6: 45719.517 | C6: 45719.521 | D6: anonymous | I6: Wilmer Alberto Figueredo Rodríguez | J6: 0 | L6: 1010175883 | M6: 0 | O6: 31 a 40 | P6: 0 | R6: 3112110231 | S6: 0 | U6: Teleinformatica | V6: 0 | X6: Investigación | Y6: 0 | AA6: Totalmente de acuerdo. | AB6: 0 | AD6: Ni en acuerdo, ni en desacuerdo. | AE6: 0 | AG6: Plan de integración en proyectos de investigación post académica | AH6: 0 | AJ6: Totalmente de acuerdo. | AK6: 0 | AN6: 0 | AP6: De acuerdo. | AQ6: 0 | AT6: 0 | AV6: De acuerdo. | AW6: 0 | AY6: Ingeniería de telecomunicaciones, ventas | AZ6: 0 | BB6: Tecnología (desarrollo de software, IA, ciberseguridad, telecomunicaciones) | BC6: 0 | BE6: Ni en acuerdo, ni en desacuerdo. | BF6: 0 | BH6: Ni en acuerdo, ni en desacuerdo. | BI6: 0 | BK6: HP INC | BL6: 0 | BO6: 0
A7: 5 | B7: 45719.519 | C7: 45719.522 | D7: anonymous | I7: IVAN ANDRES REYES GOMEZ | J7: 0 | L7: 80803723 | M7: 0 | O7: 31 a 40 | P7: 0 | R7: 3134264500 | S7: 0 | U7: Geomtatica | V7: 0 | X7: Investigación | Y7: 0 | AA7: Totalmente de acuerdo. | AB7: 0 | AD7: Totalmente de acuerdo. | AE7: 0 | AG7: Programación | AH7: 0 | AJ7: Ni en acuerdo, ni en desacuerdo. | AK7: 0 | AM7: Se tienen diferentes enfoques de un mismo problema y se puede tomar la decisión más adecuada | AN7: 0 | AP7: De acuerdo. | AQ7: 0 | AS7: No | AT7: 0 | AV7: Ni en acuerdo, ni en desacuerdo. | AW7: 0 | AY7: SIG y análisis de datos | AZ7: 0 | BB7: Sector público (administración pública, gobierno) | BC7: 0 | BE7: De acuerdo. | BF7: 0 | BH7: Ni en acuerdo, ni en desacuerdo. | BI7: 0 | BK7: Empresa de Acueducto y Alcantarillado de Bogotá | BL7: 0 | BN7: No | BO7: 0
A8: 6 | B8: 45719.528 | C8: 45719.531 | D8: anonymous | I8: J. Camilo Matiz Leon | J8: 0 | L8: 80075955 | M8: 0 | O8: 31 a 40 | P8: 0 | R8: 3002902743 | S8: 0 | U8: Geomtatica | V8: 0 | X8: Investigación | Y8: 0 | AA8: De acuerdo. | AB8: 0 | AD8: De acuerdo. | AE8: 0 | AG8: Mejorar la interacción con instituciones, asesores, expertos, entre otros, en funión del tema central seleccionado para la tesis, y la oferte de asignaturas que contribuyan | AH8: 0 | AJ8: En desacuerdo. | AK8: 0 | AM8: No me beneficieron debido a que solcitie asignaturas que me ayudarian en mi propuesta de investigación pero no fue posible abrirlas por que esta materia sería dictada solo para 1 estudiante | AN8: 0 | AP8: De acuerdo. | AQ8: 0 | AS8: De acuerdo con la afirmación pero en mi periodo de estudiante no hubo un interlocutar en el tema de mi propuesta de investigación que me proporcionara la Maestría o la Universidad | AT8: 0 | AV8: Ni en acuerdo, ni en desacuerdo. | AW8: 0 | AY8: Investigador en Geotermia | AZ8: 0 | BB8: Sector público (administración pública, gobierno) | BC8: 0 | BE8: De acuerdo. | BF8: 0 | BH8: Ni en acuerdo, ni en desacuerdo. | BI8: 0 | BK8: UIS, UPTC, ANH | BL8: 0 | BN8: N/A | BO8: 0
A9: 7 | B9: 45719.536 | C9: 45719.542 | D9: anonymous | I9: Daniela Martin Vega | J9: 0 | L9: 1018465807 | M9: 0 | O9: 31 a 40 | P9: 0 | R9: 3059399347 | S9: 0 | U9: Ingeniería de Software | V9: 0 | X9: Investigación | Y9: 0 | AA9: De acuerdo. | AB9: 0 | AD9: Totalmente de acuerdo. | AE9: 0 | AG9: Cursos más actualizados y profundos en el área de aprendizaje de máquina | AH9: 0 | AJ9: Totalmente de acuerdo. | AK9: 0 | AM9: - | AN9: 0 | AP9: De acuerdo. | AQ9: 0 | AS9: - | AT9: 0 | AV9: Ni en acuerdo, ni en desacuerdo. | AW9: 0 | AY9: Investigación en ciencias de la computación - visión por computador | AZ9: 0 | BB9: Tecnología (desarrollo de software, IA, ciberseguridad, telecomunicaciones) | BC9: 0 | BE9: Totalmente de acuerdo. | BF9: 0 | BH9: Totalmente de acuerdo. | BI9: 0 | BK9: University of Delaware | BL9: 0 | BN9: Mi jefe no habla español. Si igual lo quieren contactar háganme saber por correo | BO9: 0
A10: 8 | B10: 45719.544 | C10: 45719.55 | D10: anonymous | I10: Jesús Manuel Paternina Durán | J10: 0 | L10: 80095218 | M10: 0 | O10: 41 a 50 | P10: 0 | R10: 3112655969 | S10: 0 | U10: Teleinformatica | V10: 0 | X10: Investigación | Y10: 0 | AA10: Totalmente de acuerdo. | AB10: 0 | AD10: Totalmente de acuerdo. | AE10: 0 | AG10: Hubiera sido bueno incluir en las materias temáticas asociadas con seguridad de la información. | AH10: 0 | AJ10: Totalmente de acuerdo. | AK10: 0 | AM10: El relacionamiento con los grupos de investigación me permitieron fortalecer proyectos de los que, hasta el día de hoy, continúan aportando a mi ejercicio profesional. | AN10: 0 | AP10: Totalmente de acuerdo. | AQ10: 0 | AS10: Publicaciones y oportunidades profesionales. | AT10: 0 | AV10: De acuerdo. | AW10: 0 | AY10: Ingeniería de telecomunicaciones, software y seguridad de la información. Adicionalmente promuevo la integración entre la ingeniería y la cultura a través de la literatura. | AZ10: 0 | BB10: Tecnología (desarrollo de software, IA, ciberseguridad, telecomunicaciones) | BC10: 0 | BE10: Totalmente de acuerdo. | BF10: 0 | BH10: Totalmente de acuerdo. | BI10: 0 | BK10: Universidad Distrital Francisco José de Caldas, Universidad Católica de Colombia, ESTIC de la Policía Nacional y Calixta Editores. | BL10: 0 | BN10: Coordinación tecnología en sistematización datos e ingeniería - tecsistematizaciondatos@udistrital.edu.co | BO10: 0
A11: 9 | B11: 45719.557 | C11: 45719.564 | D11: anonymous | I11: John Jairo Daza Rojas | J11: 0 | L11: 1024496366 | M11: 0 | O11: 31 a 40 | P11: 0 | R11: 3012145332 | S11: 0 | U11: Ingeniería de Software | V11: 0 | X11: Profundización | Y11: 0 | AA11: En desacuerdo. | AB11: 0 | AD11: En desacuerdo. | AE11: 0 | AG11: Muchas, la maestría tiene un programa académico obsoleto ,desactualizado y desalineado con las tecnologías que se demandan actualmente en el mercado laboral | AH11: 0 | AJ11: En desacuerdo. | AK11: 0 | AM11: La maestría no está formando para las tendencias actuales, está muy atrás de los enfoques académicos que tienen otras universidades , la asesoría y acompañamiento que la maestría brinda a los estudiantes no es suficiente ,desde mi punto de vista está muy alejada de la realidad de las necesidades de las empresas | AN11: 0 | AP11: Totalmente en desacuerdo. | AQ11: 0 | AS11: Ninguna | AT11: 0 | AV11: Totalmente en desacuerdo. | AW11: 0 | AY11: Arquitectura de software | AZ11: 0 | BB11: Tecnología (desarrollo de software, IA, ciberseguridad, telecomunicaciones) | BC11: 0 | BE11: De acuerdo. | BF11: 0 | BH11: En desacuerdo. | BI11: 0 | BK11: Confidencial | BL11: 0 | BN11: Confidencial | BO11: 0
A12: 10 | B12: 45719.567 | C12: 45719.572 | D12: anonymous | I12: María Alejandra Quevedo Vera | J12: 0 | L12: 1032358776 | M12: 0 | O12: 31 a 40 | P12: 0 | R12: 3008751301 | S12: 0 | U12: Teleinformatica | V12: 0 | X12: Investigación | Y12: 0 | AA12: Totalmente de acuerdo. | AB12: 0 | AD12: Totalmente de acuerdo. | AE12: 0 | AG12: En general solo mejoraría la parte administrativa, el contacto con el estudiante deja mucho que desear y francamente es lo único que me detiene para cursar otros estudios de nuevo en la UD. | AH12: 0 | AJ12: Totalmente de acuerdo. | AK12: 0 | AM12: Pude elegir materias de mi interés que se complementaban y que pude poner en práctica no sólo en el desarrollo de mi tesis sino en mi día a día laboral. | AN12: 0 | AP12: Ni en acuerdo, ni en desacuerdo. | AQ12: 0 | AS12: No tuve oportunidad de tener la experiencia con homólogos nacionales ni internacionales pero seguramente quienes sí, habrán tenido una experiencia enriquecedora | AT12: 0 | AV12: De acuerdo. | AW12: 0 | AY12: Trabajo en una empresa de servicios financieros y yo estoy en la dirección de medios de pago, como liderazgo técnico de proyectos | AZ12: 0 | BB12: Sector terciario (comercio, servicios: educación, salud, finanzas, etc.) | BC12: 0 | BE12: De acuerdo. | BF12: 0 | BH12: De acuerdo. | BI12: 0 | BK12: Davivienda | BL12: 0 | BN12: No es posible | BO12: 0
A13: 11 | B13: 45719.535 | C13: 45719.573 | D13: anonymous | I13: Hernán Darío Zárate Arévalo | J13: 0 | L13: 79992153 | M13: 0 | O13: 41 a 50 | P13: 0 | R13: 3177825051 | S13: 0 | U13: Geomtatica | V13: 0 | X13: Investigación | Y13: 0 | AA13: Totalmente de acuerdo. | AB13: 0 | AD13: Totalmente de acuerdo. | AE13: 0 | AG13: Poder conservar el correo institucional ya que lo serraron sin previo aviso y se perdió informscion | AH13: 0 | AJ13: De acuerdo. | AK13: 0 | AM13: No | AN13: 0 | AP13: Totalmente de acuerdo. | AQ13: 0 | AS13: No | AT13: 0 | AV13: En desacuerdo. | AW13: 0 | AY13: Ambiental | AZ13: 0 | BB13: Sector público (administración pública, gobierno) | BC13: 0 | BE13: De acuerdo. | BF13: 0 | BH13: De acuerdo. | BI13: 0 | BK13: Goberncion del huila | BL13: 0 | BN13: No | BO13: 0
A14: 12 | B14: 45719.581 | C14: 45719.587 | D14: anonymous | I14: Jorge Fernando Soler Lopez | J14: 0 | L14: 74085494 | M14: 0 | O14: 31 a 40 | P14: 0 | R14: 3002577463 | S14: 0 | U14: Ingeniería de Software | V14: 0 | X14: Investigación | Y14: 0 | AA14: Totalmente de acuerdo. | AB14: 0 | AD14: Totalmente de acuerdo. | AE14: 0 | AG14: Articulación de la Maestría con el Doctorado | AH14: 0 | AJ14: Totalmente de acuerdo. | AK14: 0 | AM14: Pertenecer el Grupo de Investigación GICOGE me ayudo a enfocar y publicar un artículo científico en una revista internacional | AN14: 0 | AP14: Totalmente de acuerdo. | AQ14: 0 | AS14: Publicación del articulo “CAMBIO DE PARADIGMAS EN INGENIERIA DE REQUISITOS DESDE EL ENFOQUE DE BPM” (authors: Jorge Fernando Soler López, José Nelson Pérez Castillo) en RISTI y presentación oral | AT14: 0 | AV14: Totalmente de acuerdo. | AW14: 0 | AY14: Servidor Publico del Estado Colombiano | AZ14: 0 | BB14: Sector público (administración pública, gobierno) | BC14: 0 | BE14: De acuerdo. | BF14: 0 | BH14: Totalmente de acuerdo. | BI14: 0 | BK14: Departamento Administrativo para la Prosperidad Social | BL14: 0 | BN14: No me encuentro autorizado para brindar dicha información | BO14: 0
A15: 13 | B15: 45719.577 | C15: 45719.589 | D15: anonymous | I15: SEBASTIAN CAMILO VANEGAS AYALA | J15: 0 | L15: 1026591661 | M15: 0 | O15: 25 a 30 | P15: 0 | R15: 3174849419 | S15: 0 | U15: Ingeniería de Software | V15: 0 | X15: Investigación | Y15: 0 | AA15: Totalmente de acuerdo. | AB15: 0 | AD15: Totalmente de acuerdo. | AE15: 0 | AG15: Revisar el enfoque de vinculación entre pregado y doctorado, en el enfasís de investigación, orientandolo a una articulación completa de saberes y espacios que apoyen el trabajo de investigación, de esta forma reducir los tiempos de permanencia por trabajo de grado | AH15: 0 | AJ15: Ni en acuerdo, ni en desacuerdo. | AK15: 0 | AM15: La ruta de formación en ingeniería de software reforzo los conocimientos necesarios para el proyecto investigativo. | AN15: 0 | AP15: Ni en acuerdo, ni en desacuerdo. | AQ15: 0 | AS15: No existio en pandemía mucho desarrollo en este campo. | AT15: 0 | AV15: Ni en acuerdo, ni en desacuerdo. | AW15: 0 | AY15: Docente | AZ15: 0 | BB15: Sector terciario (comercio, servicios: educación, salud, finanzas, etc.) | BC15: 0 | BE15: Totalmente de acuerdo. | BF15: 0 | BH15: Totalmente de acuerdo. | BI15: 0 | BK15: Universidad Distrital Francisco José de Caldas | BL15: 0 | BN15: decano_ing@udistrital.edu.co | BO15: 0
A16: 14 | B16: 45719.588 | C16: 45719.594 | D16: anonymous | I16: Hans Rodríguez Cossio | J16: 0 | L16: 79999284 | M16: 0 | O16: 41 a 50 | P16: 0 | R16: 3138706113 | S16: 0 | U16: Teleinformatica | V16: 0 | X16: Profundización | Y16: 0 | AA16: Totalmente de acuerdo. | AB16: 0 | AD16: De acuerdo. | AE16: 0 | AG16: Foco hacia IA, ML y analitica a los temas de redes y telecomunicaciones | AH16: 0 | AJ16: Totalmente de acuerdo. | AK16: 0 | AM16: Durante la pandemia la opción no presencial me permitió concluir mis estudios de maestría, pese a vivir fuera de Bogotá. | AN16: 0 | AP16: Ni en acuerdo, ni en desacuerdo. | AQ16: 0 | AS16: No tuve la interacción que mencionan. | AT16: 0 | AV16: Ni en acuerdo, ni en desacuerdo. | AW16: 0 | AY16: Ingeniería en telecomunicaciones | AZ16: 0 | BB16: Tecnología (desarrollo de software, IA, ciberseguridad, telecomunicaciones) | BC16: 0 | BE16: Totalmente de acuerdo. | BF16: 0 | BH16: De acuerdo. | BI16: 0 | BK16: Claro | BL16: 0 | BN16: Julio Zabaleta - Gerente de planeación evolución y estrategia - julio.zabaleta@claro.com.co - 3135321456 | BO16: 0
A17: 15 | B17: 45719.608 | C17: 45719.611 | D17: anonymous | I17: Manuel Antonio Vargas Anzola | J17: 0 | L17: 79810570 | M17: 0 | O17: 41 a 50 | P17: 0 | R17: 3118112951 | S17: 0 | U17: Ingeniería de Software | V17: 0 | X17: Profundización | Y17: 0 | AA17: De acuerdo. | AB17: 0 | AD17: De acuerdo. | AE17: 0 | AG17: Actualizar el pensum, incluir contenidos acordes a las tendencias actuales. Ya algunos están quedando obsoletos. | AH17: 0 | AJ17: De acuerdo. | AK17: 0 | AM17: Profundizacion en ing de software. | AN17: 0 | AP17: Ni en acuerdo, ni en desacuerdo. | AQ17: 0 | AS17: NA | AT17: 0 | AV17: Ni en acuerdo, ni en desacuerdo. | AW17: 0 | AY17: Industria del desarrollo de software. | AZ17: 0 | BB17: Tecnología (desarrollo de software, IA, ciberseguridad, telecomunicaciones) | BC17: 0 | BE17: Ni en acuerdo, ni en desacuerdo. | BF17: 0 | BH17: Ni en acuerdo, ni en desacuerdo. | BI17: 0 | BK17: Globant | BL17: 0 | BN17: N/A | BO17: 0
A18: 16 | B18: 45719.612 | C18: 45719.617 | D18: anonymous | I18: Juan Carlos Delgadillo Beltran | J18: 0 | L18: 79576961 | M18: 0 | O18: 51 o más | P18: 0 | R18: 3108599918 | S18: 0 | U18: Teleinformatica | V18: 0 | X18: Profundización | Y18: 0 | AA18: Totalmente de acuerdo. | AB18: 0 | AD18: Totalmente de acuerdo. | AE18: 0 | AG18: realizar enfoque con el fin que desde el comienzo de la maestría sea direccionado para la investigación o profundización | AH18: 0 | AJ18: Totalmente de acuerdo. | AK18: 0 | AM18: telecomunicacion | AN18: 0 | AP18: De acuerdo. | AQ18: 0 | AS18: investigación de 5g | AT18: 0 | AV18: De acuerdo. | AW18: 0 | AY18: Ingeniero sistemas | AZ18: 0 | BB18: Sector público (administración pública, gobierno) | BC18: 0 | BE18: De acuerdo. | BF18: 0 | BH18: De acuerdo. | BI18: 0 | BK18: Rama Judicial | BL18: 0 | BN18: Diego Victorino | BO18: 0
... A24: 22 | B24: 45722.61 | C24: 45722.617 | D24: anonymous | I24: Javier Orlando Fernández Campos | J24: 0 | L24: 1077147477 | M24: 0 | O24: 31 a 40 | P24: 0 | R24: 3503380110 | S24: 0 | U24: Geomtatica | V24: 0 | X24: Investigación | Y24: 0 | AA24: Totalmente de acuerdo. | AB24: 0 | AD24: Totalmente de acuerdo. | AE24: 0 | AG24: Considero pertinente incrementar las materias relacionadas con Inteligencia Artificial (IA) y desarrollo de software, con un enfoque específico en el análisis y procesamiento de datos espaciales, dentro del plan de estudios de la Maestría en Ciencias de la Información y las Comunicaciones. El auge de tecnologías como la teledetección, los sistemas de información geográfica (SIG) y el análisis geoespacial en diversas industrias hace necesario fortalecer la formación en estas áreas. Incluir asignaturas sobre modelado y análisis de datos espaciales, machine learning aplicado a geodatos, desarrollo de software para SIG y visualización avanzada de datos geoespaciales permitiría a los egresados desarrollar competencias más alineadas con las necesidades del mercado. | AH24: 0 | AJ24: Totalmente de acuerdo. | AK24: 0 | AM24: Dentro de mi formación, la posibilidad de cursar materias de distintas profundizaciones me permitió conocer más sobre aspectos relevantes para mi tema de investigación. Esta flexibilidad académica me ayudó a complementar mi enfoque principal con conocimientos de otras áreas, enriqueciendo mi comprensión y permitiéndome abordar mi investigación desde una perspectiva más amplia e interdisciplinaria. | AN24: 0 | AP24: Totalmente de acuerdo. | AQ24: 0 | AS24: Tuve la oportunidad de realizar mi investigación en colaboración con profesionales expertos en Bélgica y otros países, gracias a la posibilidad de nombrarlos como codirectores de investigación dentro de la Maestría en Ciencias de la Información y las Comunicaciones. Esta cooperación académica y científica me permitió enriquecer mi trabajo con enfoques y metodologías innovadoras, además de acceder a redes de conocimiento internacional. | AT24: 0 | AV24: Ni en acuerdo, ni en desacuerdo. | AW24: 0 | AY24: Mi campo laboral actual se centra en el análisis de datos espaciales y temas relacionados con la geomática. Trabajo con herramientas y metodologías avanzadas para el procesamiento, modelado y visualización de información geoespacial, aplicando técnicas de análisis en diversos sectores como la planificación territorial, la gestión ambiental y la movilidad urbana. Además, utilizo sistemas de información geográfica (SIG), inteligencia artificial y bases de datos espaciales para extraer conocimiento a partir de grandes volúmenes de datos georreferenciados. Esta combinación de tecnologías y enfoques me permite desarrollar soluciones innovadoras para la toma de decisiones basadas en información geoespacial precisa y actualizada. | AZ24: 0 | BB24: Sector público (administración pública, gobierno) | BC24: 0 | BE24: Totalmente de acuerdo. | BF24: 0 | BH24: De acuerdo. | BI24: 0 | BK24: Alcaldía de Bogotá D.C | BL24: 0 | BN24: - | BO24: 0

Sheet Estados
A1: Estado | B1: E - ESTUDIANTE GRADUADO
A2: PROYECTO CURRICULAR | B2: MAESTRIA EN TELEINFORMATICA
A3: No. | B3: COD. ESTUDIANTE | C3: NOMBRE ESTUDIANTE | D3: COD. PROYECTO | E3: PROYECTO CURRICULAR | F3: ESTADO | G3: DESCRIPCIÓN | H3: ESTRATO | I3: CORREO INSTITUCIONAL | J3: CORREO PERSONAL | K3: TIP. DOC. | L3: DOCUMENTO | M3: ULTIMA MATRICULA
A4: 1 | B4: 8929519 | C4: SOLER LOPEZ FERNANDO | D4: 95 | E4: MAESTRIA EN TELEINFORMATICA | F4: E | G4: ESTUDIANTE GRADUADO | H4: NO REGISTRA | K4: CC | L4: 19056999 | M4: -
A5: 2 | B5: 8939501 | C5: AHUMADA VALDERRAMA HERNANDO JOSE | D5: 95 | E5: MAESTRIA EN TELEINFORMATICA | F5: E | G5: ESTUDIANTE GRADUADO | H5: NO REGISTRA | K5: CC | L5: 19073527 | M5: -
A6: 3 | B6: 8939503 | C6: APARICIO PICO LILIA EDITH | D6: 95 | E6: MAESTRIA EN TELEINFORMATICA | F6: E | G6: ESTUDIANTE GRADUADO | H6: NO REGISTRA | J6: medicina@udistrital.edu.co | K6: CC | L6: 51703985 | M6: -
A7: 4 | B7: 8939504 | C7: BARRIOS CANO JOSE ADAN | D7: 95 | E7: MAESTRIA EN TELEINFORMATICA | F7: E | G7: ESTUDIANTE GRADUADO | H7: NO REGISTRA | K7: CC | L7: 19082081 | M7: -
A8: 5 | B8: 8939506 | C8: CAMERANO FUENTES RAFAEL A. | D8: 95 | E8: MAESTRIA EN TELEINFORMATICA | F8: E | G8: ESTUDIANTE GRADUADO | H8: NO REGISTRA | K8: CC | L8: 7464009 | M8: -
A9: 6 | B9: 8939507 | C9: CARDENAS CASTIBLANCO JOSE ROBERTO | D9: 95 | E9: MAESTRIA EN TELEINFORMATICA | F9: E | G9: ESTUDIANTE GRADUADO | H9: NO REGISTRA | K9: CC | L9: 19289020 | M9: -
A10: 7 | B10: 8939511 | C10: NARVAEZ RIVAS HEIBER | D10: 95 | E10: MAESTRIA EN TELEINFORMATICA | F10: E | G10: ESTUDIANTE GRADUADO | H10: NO REGISTRA | K10: CC | L10: 19085510 | M10: -
A11: 8 | B11: 8939512 | C11: ORTIZ DIAZ DELIA CONSUELO | D11: 95 | E11: MAESTRIA EN TELEINFORMATICA | F11: E | G11: ESTUDIANTE GRADUADO | H11: NO REGISTRA | K11: CC | L11: 51764305 | M11: -
A12: 9 | B12: 8939513 | C12: PE?A VILLAMIL HERNANDO JOSE | D12: 95 | E12: MAESTRIA EN TELEINFORMATICA | F12: E | G12: ESTUDIANTE GRADUADO | H12: NO REGISTRA | I12: hjpenav@correo.udistrital.edu.co | J12: hjpenav@correo.udistrital.edu.co | K12: CC | L12: 19257223 | M12: -
A13: 10 | B13: 8939514 | C13: PEREZ CASTILLO JOSE NELSON | D13: 95 | E13: MAESTRIA EN TELEINFORMATICA | F13: E | G13: ESTUDIANTE GRADUADO | H13: NO REGISTRA | K13: CC | L13: 197019 | M13: -
A14: 11 | B14: 8939517 | C14: RAMIREZ ARTUNDUAGA JAIME | D14: 95 | E14: MAESTRIA EN TELEINFORMATICA | F14: E | G14: ESTUDIANTE GRADUADO | H14: NO REGISTRA | K14: CC | L14: 17153528 | M14: -
A15: 12 | B15: 8939518 | C15: RUIZ PLAZA NANCY | D15: 95 | E15: MAESTRIA EN TELEINFORMATICA | F15: E | G15: ESTUDIANTE GRADUADO | H15: NO REGISTRA | K15: CC | L15: 51765701 | M15: -
A16: 13 | B16: 8939520 | C16: TARRIFA AREVALO ALEXIS RAFAEL | D16: 95 | E16: MAESTRIA EN TELEINFORMATICA | F16: E | G16: ESTUDIANTE GRADUADO | H16: NO REGISTRA | I16: artarrifaa@correo.udistrital.edu.co | J16: artarrifaa@correo.udistrital.edu.co | K16: CC | L16: 79343019 | M16: -
A17: 14 | B17: 8939521 | C17: VELASCO PATINO ROBERTO | D17: 95 | E17: MAESTRIA EN TELEINFORMATICA | F17: E | G17: ESTUDIANTE GRADUADO | H17: NO REGISTRA | K17: CC | L17: 2945746 | M17: -
A18: 15 | B18: 8939522 | C18: VELASCO SALAZAR ANGELA MARLENY | D18: 95 | E18: MAESTRIA EN TELEINFORMATICA | F18: E | G18: ESTUDIANTE GRADUADO | H18: NO REGISTRA | K18: CC | L18: 41715029 | M18: -
A19: 16 | B19: 8939523 | C19: CLAVIJO VILLALOBOS EDGAR O. | D19: 95 | E19: MAESTRIA EN TELEINFORMATICA | F19: E | G19: ESTUDIANTE GRADUADO | H19: NO REGISTRA | J19: edgclavijo@hotmail.com | K19: CC | L19: 79383764 | M19: -
A20: 17 | B20: 8949507 | C20: MANUEL ERNESTO PEREZ VELASCO | D20: 95 | E20: MAESTRIA EN TELEINFORMATICA | F20: E | G20: ESTUDIANTE GRADUADO | H20: NO REGISTRA | K20: CC | L20: 19188812 | M20: -
A21: 18 | B21: 9019511 | C21: MENDOZA GARZON SONIA ADRIANA | D21: 95 | E21: MAESTRIA EN TELEINFORMATICA | F21: E | G21: ESTUDIANTE GRADUADO | H21: NO REGISTRA | K21: CC | L21: 51765224 | M21: -
A22: 19 | B22: 9019512 | C22: MORENO ARENAS CARLOS A. | D22: 95 | E22: MAESTRIA EN TELEINFORMATICA | F22: E | G22: ESTUDIANTE GRADUADO | H22: NO REGISTRA | K22: CC | L22: 17322117 | M22: -
A23: 20 | B23: 9019519 | C23: PARDO RODRIGUEZ MARIO CESAR | D23: 95 | E23: MAESTRIA EN TELEINFORMATICA | F23: E | G23: ESTUDIANTE GRADUADO | H23: NO REGISTRA | K23: CC | L23: 19220073 | M23: -
A24: 21 | B24: 9019526 | C24: SANTACRUZ GARZON RICARDO JAIME | D24: 95 | E24: MAESTRIA EN TELEINFORMATICA | F24: E | G24: ESTUDIANTE GRADUADO | H24: NO REGISTRA | K24: CC | L24: 79292064 | M24: -
A25: 22 | B25: 9019527 | C25: SANTOS HOMEZ LUZ MARY | D25: 95 | E25: MAESTRIA EN TELEINFORMATICA | F25: E | G25: ESTUDIANTE GRADUADO | H25: NO REGISTRA | K25: CC | L25: 65496815 | M25: -
A26: 23 | B26: 9029506 | C26: QUIROGA ARIZA PEDRO LUIS | D26: 95 | E26: MAESTRIA EN TELEINFORMATICA | F26: E | G26: ESTUDIANTE GRADUADO | H26: NO REGISTRA | K26: CC | L26: 79261374 | M26: -
A27: 24 | B27: 9039503 | C27: CAMERANO SALCEDO CLIMACO | D27: 95 | E27: MAESTRIA EN TELEINFORMATICA | F27: E | G27: ESTUDIANTE GRADUADO | H27: NO REGISTRA | K27: CC | L27: 73110505 | M27: -
A28: 25 | B28: 9119514 | C28: VALERO MEDINA JOSE ANTONIO | D28: 95 | E28: MAESTRIA EN TELEINFORMATICA | F28: E | G28: ESTUDIANTE GRADUADO | H28: NO REGISTRA | K28: CC | L28: 79390069 | M28: -
A29: 26 | B29: 9139509 | C29: LIBIA AURORA TALERO CASTA?EDA | D29: 95 | E29: MAESTRIA EN TELEINFORMATICA | F29: E | G29: ESTUDIANTE GRADUADO | H29: NO REGISTRA | K29: CC | L29: 35404784 | M29: -
A30: 27 | B30: 9219501 | C30: ACOSTA LOPEZ ALBERTO | D30: 95 | E30: MAESTRIA EN TELEINFORMATICA | F30: E | G30: ESTUDIANTE GRADUADO | H30: NO REGISTRA | K30: CC | L30: 19483959 | M30: -
A31: 28 | B31: 9219504 | C31: NESTOR ENRIQUE CERON CORREA | D31: 95 | E31: MAESTRIA EN TELEINFORMATICA | F31: E | G31: ESTUDIANTE GRADUADO | H31: NO REGISTRA | K31: CC | L31: 19447443 | M31: -
... A34: 31 | B34: 9319508 | C34: RODRIGO JAVIER HERRERA GARCIA | D34: 95 | E34: MAESTRIA EN TELEINFORMATICA | F34: E | G34: ESTUDIANTE GRADUADO | H34: NO REGISTRA | K34: CC | L34: 19316812 | M34: -
A35: 32 | B35: 9329503 | C35: CARDENAS FORONDA SANDRA MIREYA | D35: 95 | E35: MAESTRIA EN TELEINFORMATICA | F35: E | G35: ESTUDIANTE GRADUADO | H35: NO REGISTRA | I35: smcardenasf@correo.udistrital.edu.co | J35: smcardenasf@estudiante.udistrital.edu.co | K35: CC | L35: 51866543 | M35: 2003-3
A36: 33 | B36: 9329505 | C36: CORDOBA NIETO JOSE MARIA | D36: 95 | E36: MAESTRIA EN TELEINFORMATICA | F36: E | G36: ESTUDIANTE GRADUADO | H36: NO REGISTRA | K36: CC | L36: 12109273 | M36: -
A37: 34 | B37: 9329509 | C37: DIOSSA HENRY ALBERTO | D37: 95 | E37: MAESTRIA EN TELEINFORMATICA | F37: E | G37: ESTUDIANTE GRADUADO | H37: NO REGISTRA | K37: CC | L37: 80264735 | M37: -
A38: 35 | B38: 9329517 | C38: SOLIS MENDEZ DIEGO JAVIER | D38: 95 | E38: MAESTRIA EN TELEINFORMATICA | F38: E | G38: ESTUDIANTE GRADUADO | H38: NO REGISTRA | K38: CC | L38: 79367799 | M38: -
A39: 36 | B39: 9329518 | C39: TOLOSA PENA CARLOS JULIAN | D39: 95 | E39: MAESTRIA EN TELEINFORMATICA | F39: E | G39: ESTUDIANTE GRADUADO | H39: NO REGISTRA | K39: CC | L39: 79428567 | M39: -
A40: 37 | B40: 9329521 | C40: LESMES ACOSTA MAURICIO | D40: 95 | E40: MAESTRIA EN TELEINFORMATICA | F40: E | G40: ESTUDIANTE GRADUADO | H40: NO REGISTRA | I40: mlesmesa@correo.udistrital.edu.co | J40: mlesmesa@estudiante.udistrital.edu.co | K40: CC | L40: 19422855 | M40: 2003-3
A41: 38 | B41: 9519504 | C41: GONZALEZ CHAVEZ ERIKA MARITZA | D41: 95 | E41: MAESTRIA EN TELEINFORMATICA | F41: E | G41: ESTUDIANTE GRADUADO | H41: NO REGISTRA | I41: emgonzalezc@correo.udistrital.edu.co | J41: emgonzalezc@estudiante.udistrital.edu.co | K41: CC | L41: 51911517 | M41: 2002-1
A42: 39 | B42: 9519509 | C42: MEJIA FAJARDO ANGELA MARCELA | D42: 95 | E42: MAESTRIA EN TELEINFORMATICA | F42: E | G42: ESTUDIANTE GRADUADO | H42: NO REGISTRA | K42: CC | L42: 52005831 | M42: -
A43: 40 | B43: 9519510 | C43: HAROLD ALEXANDER MENDEZ GUEVARA | D43: 95 | E43: MAESTRIA EN TELEINFORMATICA | F43: E | G43: ESTUDIANTE GRADUADO | H43: NO REGISTRA | I43: hamendezg@udistrital.edu.co | J43: haroldmendezg@hotmail.com | K43: CC | L43: 93355909 | M43: -
A44: 41 | B44: 9519519 | C44: SALCEDO PARRA OCTAVIO JOSE | D44: 95 | E44: MAESTRIA EN TELEINFORMATICA | F44: E | G44: ESTUDIANTE GRADUADO | H44: NO REGISTRA | K44: CC | L44: 79508767 | M44: -
A45: 42 | B45: 9519520 | C45: VELOZA CORTES NELSY | D45: 95 | E45: MAESTRIA EN TELEINFORMATICA | F45: E | G45: ESTUDIANTE GRADUADO | H45: NO REGISTRA | K45: CC | L45: 51594578 | M45: -
A46: 43 | B46: 9619508 | C46: IVAN FERNANDO GONZALEZ RODRIGUEZ | D46: 95 | E46: MAESTRIA EN TELEINFORMATICA | F46: E | G46: ESTUDIANTE GRADUADO | H46: NO REGISTRA | K46: CC | L46: 79456915 | M46: -
A47: 44 | B47: 9629507 | C47: FLOREZ ABRIL SANDRA YAZMIN | D47: 95 | E47: MAESTRIA EN TELEINFORMATICA | F47: E | G47: ESTUDIANTE GRADUADO | H47: NO REGISTRA | K47: CC | L47: 52046061 | M47: -
A48: 45 | B48: 9629508 | C48: GALINDO PULIDO FRANCISCO | D48: 95 | E48: MAESTRIA EN TELEINFORMATICA | F48: E | G48: ESTUDIANTE GRADUADO | H48: NO REGISTRA | K48: CC | L48: 79615199 | M48: 2003-3
A49: 46 | B49: 9629510 | C49: LUNA CEBALLOS MARTHA | D49: 95 | E49: MAESTRIA EN TELEINFORMATICA | F49: E | G49: ESTUDIANTE GRADUADO | H49: NO REGISTRA | K49: CC | L49: 499769060 | M49: -
A50: 47 | B50: 9629516 | C50: RUIZ PERALTA JOSE ALFREDO | D50: 95 | E50: MAESTRIA EN TELEINFORMATICA | F50: E | G50: ESTUDIANTE GRADUADO | H50: NO REGISTRA | K50: CC | L50: 79290893 | M50: 2003-3
A51: 48 | B51: 9719507 | C51: EDGAR AUGUSTO FUERTES PUERTO | D51: 95 | E51: MAESTRIA EN TELEINFORMATICA | F51: E | G51: ESTUDIANTE GRADUADO | H51: NO REGISTRA | K51: CC | L51: 79054250 | M51: -
A52: 49 | B52: 9719510 | C52: MANRIQUE ESPINDOLA HERNAN DE JESUS | D52: 95 | E52: MAESTRIA EN TELEINFORMATICA | F52: E | G52: ESTUDIANTE GRADUADO | H52: NO REGISTRA | K52: CC | L52: 4258816 | M52: -
A53: 50 | B53: 9719517 | C53: SYLVIA ZARAFYAN MANOYAN | D53: 95 | E53: MAESTRIA EN TELEINFORMATICA | F53: E | G53: ESTUDIANTE GRADUADO | H53: NO REGISTRA | K53: CE | L53: 183204 | M53: -
A54: 51 | B54: 9729504 | C54: JOSE ENRIQUE TORRES HERRADA | D54: 95 | E54: MAESTRIA EN TELEINFORMATICA | F54: E | G54: ESTUDIANTE GRADUADO | H54: NO REGISTRA | K54: CC | L54: 11315064 | M54: -
A55: 52 | B55: 9729507 | C55: PULIDO GRANADOS ELKIN RENE | D55: 95 | E55: MAESTRIA EN TELEINFORMATICA | F55: E | G55: ESTUDIANTE GRADUADO | H55: NO REGISTRA | I55: erpulidog@correo.udistrital.edu.co | J55: erpulido@gmail.com | K55: CC | L55: 9397924 | M55: 2007-3
A56: 53 | B56: 9729515 | C56: ORTEGON BOLIVAR JAIRO AUGUSTO | D56: 95 | E56: MAESTRIA EN TELEINFORMATICA | F56: E | G56: ESTUDIANTE GRADUADO | H56: NO REGISTRA | K56: CC | L56: 19194712 | M56: -
A57: 54 | B57: 9729517 | C57: POVEDA ZAFRA JOSE NOE | D57: 95 | E57: MAESTRIA EN TELEINFORMATICA | F57: E | G57: ESTUDIANTE GRADUADO | H57: NO REGISTRA | K57: CC | L57: 74301090 | M57: -
A58: 55 | B58: 9729518 | C58: SANCHEZ CARDOZO JULIO ENRIQUE | D58: 95 | E58: MAESTRIA EN TELEINFORMATICA | F58: E | G58: ESTUDIANTE GRADUADO | H58: NO REGISTRA | I58: jesanchezc@correo.udistrital.edu.co | J58: jesanchezc@estudiante.udistrital.edu.co | K58: CC | L58: 19242921 | M58: 2005-1
A59: 56 | B59: 9729520 | C59: RODRIGUEZ MUJICA LEONARDO | D59: 95 | E59: MAESTRIA EN TELEINFORMATICA | F59: E | G59: ESTUDIANTE GRADUADO | H59: NO REGISTRA | I59: lrodriguezm@correo.udistrital.edu.co | J59: lrodriguezm@estudiante.udistrital.edu.co | K59: CC | L59: 79418086 | M59: 2003-3
A60: 57 | B60: 9819501 | C60: JOSE TOBIAS AGUDELO GUTIERREZ | D60: 95 | E60: MAESTRIA EN TELEINFORMATICA | F60: E | G60: ESTUDIANTE GRADUADO | H60: NO REGISTRA | I60: jtagudelog@correo.udistrital.edu.co | J60: jtagudelog@estudiante.udistrital.edu.co | K60: CC | L60: 3015842 | M60: 2004-3
A61: 58 | B61: 9819506 | C61: PEDRO ALEXANDER DIAZ QUIROGA | D61: 95 | E61: MAESTRIA EN TELEINFORMATICA | F61: E | G61: ESTUDIANTE GRADUADO | H61: NO REGISTRA | J61: pdiazq@hotmail.com | K61: CC | L61: 91291853 | M61: -
A62: 59 | B62: 9819510 | C62: JARAMILLO MORENO BEATRIZ ELISA | D62: 95 | E62: MAESTRIA EN TELEINFORMATICA | F62: E | G62: ESTUDIANTE GRADUADO | H62: NO REGISTRA | I62: bejaramillom@correo.udistrital.edu.co | J62: bjaramillo@udistrital.edu.co | K62: CC | L62: 52204982 | M62: 2009-1
A63: 60 | B63: 9819512 | C63: MANTILLA BAUTISTA EDGAR JAVIER | D63: 95 | E63: MAESTRIA EN TELEINFORMATICA | F63: E | G63: ESTUDIANTE GRADUADO | H63: NO REGISTRA | I63: ejmantillab@correo.udistrital.edu.co | J63: ejmantillab@estudiante.udistrital.edu.co | K63: CC | L63: 19483215 | M63: -
A64: 61 | B64: 9819513 | C64: MARTINEZ BARRERA CRISMAN | D64: 95 | E64: MAESTRIA EN TELEINFORMATICA | F64: E | G64: ESTUDIANTE GRADUADO | H64: NO REGISTRA | K64: CC | L64: 79555268 | M64: -
A65: 62 | B65: 9819522 | C65: JOSE FELIX VEGA STAVRO | D65: 95 | E65: MAESTRIA EN TELEINFORMATICA | F65: E | G65: ESTUDIANTE GRADUADO | H65: NO REGISTRA | I65: jfvegas@correo.udistrital.edu.co | J65: jfvegas@estudiante.udistrital.edu.co | K65: CC | L65: 79602747 | M65: 2003-1
A66: 63 | B66: 9819523 | C66: BOLA?OS CASTRO SANDRO JAVIER | D66: 95 | E66: MAESTRIA EN TELEINFORMATICA | F66: E | G66: ESTUDIANTE GRADUADO | H66: NO REGISTRA | I66: sbolanos@udistrital.edu.co | J66: sbolanos@udistrital.edu.co | K66: CC | L66: 12237136 | M66: -
A67: 64 | B67: 9819530 | C67: FLOREZ BAEZ JULIO CESAR | D67: 95 | E67: MAESTRIA EN TELEINFORMATICA | F67: E | G67: ESTUDIANTE GRADUADO | H67: NO REGISTRA | K67: CC | L67: 19308520 | M67: -
A68: 65 | B68: 9819548 | C68: ZAMORA NAVARRO FRANCISCO | D68: 95 | E68: MAESTRIA EN TELEINFORMATICA | F68: E | G68: ESTUDIANTE GRADUADO | H68: NO REGISTRA | J68: fzamora@udistrital.edu.co | K68: CC | L68: 79471198 | M68: 2016-1
A69: 66 | B69: 9829503 | C69: FUQUENE ARDILA HECTOR JULIO | D69: 95 | E69: MAESTRIA EN TELEINFORMATICA | F69: E | G69: ESTUDIANTE GRADUADO | H69: NO REGISTRA | K69: CC | L69: 79369589 | M69: 2002-1
A70: 67 | B70: 9829513 | C70: SUAREZ OSCAR JARDEY | D70: 95 | E70: MAESTRIA EN TELEINFORMATICA | F70: E | G70: ESTUDIANTE GRADUADO | H70: NO REGISTRA | I70: ojardeys@correo.udistrital.edu.co | J70: ojardeys@correo.udistrital.edu.co | K70: CC | L70: 79516670 | M70: -
A71: 68 | B71: 9829516 | C71: CELY PULIDO JOHN WILLIAM | D71: 95 | E71: MAESTRIA EN TELEINFORMATICA | F71: E | G71: ESTUDIANTE GRADUADO | H71: NO REGISTRA | K71: CC | L71: 79610220 | M71: -
A72: 69 | B72: 9829519 | C72: MEDINA DAZA RUBEN JAVIER | D72: 95 | E72: MAESTRIA EN TELEINFORMATICA | F72: E | G72: ESTUDIANTE GRADUADO | H72: NO REGISTRA | K72: CC | L72: 79572003 | M72: -
A73: 70 | B73: 9829522 | C73: RUIZ CAMPOS WILLIAM ENRIQUE | D73: 95 | E73: MAESTRIA EN TELEINFORMATICA | F73: E | G73: ESTUDIANTE GRADUADO | H73: NO REGISTRA | K73: CC | L73: 79488800 | M73: 2002-1
A74: 71 | B74: 9829529 | C74: RAMIREZ ESCOBAR JORGE FEDERICO | D74: 95 | E74: MAESTRIA EN TELEINFORMATICA | F74: E | G74: ESTUDIANTE GRADUADO | H74: NO REGISTRA | K74: CC | L74: 79459303 | M74: -
A75: 72 | B75: 9919510 | C75: LADINO VEGA IVAN DARIO | D75: 95 | E75: MAESTRIA EN TELEINFORMATICA | F75: E | G75: ESTUDIANTE GRADUADO | H75: NO REGISTRA | I75: idladinov@correo.udistrital.edu.co | J75: ivan.ladino@hotmail.com | K75: CC | L75: 79400101 | M75: 2016-1
A76: 73 | B76: 9919527 | C76: JUAN MANUEL VELASQUEZ CHAVES | D76: 95 | E76: MAESTRIA EN TELEINFORMATICA | F76: E | G76: ESTUDIANTE GRADUADO | H76: NO REGISTRA | K76: CC | L76: 80422803 | M76: 2002-1
A77: 74 | B77: 9919530 | C77: REYES MONCAYO HECTOR IVAN | D77: 95 | E77: MAESTRIA EN TELEINFORMATICA | F77: E | G77: ESTUDIANTE GRADUADO | H77: NO REGISTRA | I77: hireyesm@correo.udistrital.edu.co | J77: hireyesm@estudiante.udistrital.edu.co | K77: CC | L77: 79661721 | M77: 2002-1
A78: 75 | B78: 9929505 | C78: JUAN CARLOS DAVILA MESA | D78: 95 | E78: MAESTRIA EN TELEINFORMATICA | F78: E | G78: ESTUDIANTE GRADUADO | H78: NO REGISTRA | K78: CC | L78: 9399093 | M78: 2002-1
A79: 76 | B79: 9929507 | C79: FERRO ESCOBAR ROBERTO | D79: 95 | E79: MAESTRIA EN TELEINFORMATICA | F79: E | G79: ESTUDIANTE GRADUADO | H79: NO REGISTRA | K79: CC | L79: 79657603 | M79: 2002-1
A80: 77 | B80: 9929508 | C80: GARCIA CABRERA ALEXANDER | D80: 95 | E80: MAESTRIA EN TELEINFORMATICA | F80: E | G80: ESTUDIANTE GRADUADO | H80: NO REGISTRA | I80: agarciac@correo.udistrital.edu.co | J80: alexgarc@gmail.com | K80: CC | L80: 79714942 | M80: 2015-3
A81: 78 | B81: 9929509 | C81: GUILLEN PINTO EDWARD PAUL | D81: 95 | E81: MAESTRIA EN TELEINFORMATICA | F81: E | G81: ESTUDIANTE GRADUADO | H81: NO REGISTRA | I81: epguillenp@correo.udistrital.edu.co | J81: epguillenp@estudiante.udistrital.edu.co | K81: CC | L81: 79643855 | M81: -
A82: 79 | B82: 9929517 | C82: RAMOS LINARES CARLOS OMAR | D82: 95 | E82: MAESTRIA EN TELEINFORMATICA | F82: E | G82: ESTUDIANTE GRADUADO | H82: NO REGISTRA | I82: coramosl@correo.udistrital.edu.co | J82: coramosl@estudiante.udistrital.edu.co | K82: CC | L82: 19335124 | M82: -
A83: 80 | B83: 9929519 | C83: NUBIA XIOMARA SEPULVEDA MENDOZA | D83: 95 | E83: MAESTRIA EN TELEINFORMATICA | F83: E | G83: ESTUDIANTE GRADUADO | H83: NO REGISTRA | I83: nxsepulvedam@correo.udistrital.edu.co | J83: nxsepulvedam@estudiante.udistrital.edu.co | K83: CC | L83: 60341094 | M83: -
A84: 81 | B84: 9929524 | C84: FERNANDEZ IBARRA LUZ MYRIAM | D84: 95 | E84: MAESTRIA EN TELEINFORMATICA | F84: E | G84: ESTUDIANTE GRADUADO | H84: NO REGISTRA | I84: lmfernandezi@correo.udistrital.edu.co | J84: luzferi@gmail.com | K84: CC | L84: 52348279 | M84: 2016-1
A85: 82 | B85: 9929532 | C85: PAZ PENAGOS HERNAN | D85: 95 | E85: MAESTRIA EN TELEINFORMATICA | F85: E | G85: ESTUDIANTE GRADUADO | H85: NO REGISTRA | K85: CC | L85: 10484025 | M85: -
A86: 83 | B86: 9969503 | C86: MURILLO DUARTE HERNANDO | D86: 95 | E86: MAESTRIA EN TELEINFORMATICA | F86: E | G86: ESTUDIANTE GRADUADO | H86: NO REGISTRA | I86: hmurillod@correo.udistrital.edu.co | J86: hmurillod@estudiante.udistrital.edu.co | K86: CC | L86: 79494853 | M86: 2005-3
A87: 84 | B87: 9969504 | C87: JAVIER ALARCON BARRERA | D87: 95 | E87: MAESTRIA EN TELEINFORMATICA | F87: E | G87: ESTUDIANTE GRADUADO | H87: NO REGISTRA | I87: jalarconb@correo.udistrital.edu.co | J87: jalarconb@estudiante.udistrital.edu.co | K87: CC | L87: 74180565 | M87: 2002-1
A88: 85 | B88: 9969508 | C88: ESPINEL ORTEGA ALVARO | D88: 95 | E88: MAESTRIA EN TELEINFORMATICA | F88: E | G88: ESTUDIANTE GRADUADO | H88: NO REGISTRA | K88: CC | L88: 19483708 | M88: 2002-1
A89: 86 | B89: 9969514 | C89: VELANDIA JULIO BARON | D89: 95 | E89: MAESTRIA EN TELEINFORMATICA | F89: E | G89: ESTUDIANTE GRADUADO | H89: NO REGISTRA | I89: jbaronv@correo.udistrital.edu.co | J89: juliobaron@gmail.com | K89: CC | L89: 79866835 | M89: 2013-3
A90: 87 | B90: 9969516 | C90: OSPINA LOPEZ JAVIER DAVID | D90: 95 | E90: MAESTRIA EN TELEINFORMATICA | F90: E | G90: ESTUDIANTE GRADUADO | H90: NO REGISTRA | I90: jdospinal@correo.udistrital.edu.co | J90: jdospinal@estudiante.udistrital.edu.co | K90: CC | L90: 79526297 | M90: 2002-1
A91: 88 | B91: 9969525 | C91: CRUZ RODRIGUEZ CARLOS ANDRES | D91: 95 | E91: MAESTRIA EN TELEINFORMATICA | F91: E | G91: ESTUDIANTE GRADUADO | H91: NO REGISTRA | I91: cacruzr@correo.udistrital.edu.co | J91: cacruzr@estudiante.udistrital.edu.co | K91: CC | L91: 79803278 | M91: 2002-1
A92: 89 | B92: 9969531 | C92: MOYANO ACEVEDO NELSON RAUL | D92: 95 | E92: MAESTRIA EN TELEINFORMATICA | F92: E | G92: ESTUDIANTE GRADUADO | H92: NO REGISTRA | I92: nrmoyanoa@correo.udistrital.edu.co | J92: nrmoyanoa@estudiante.udistrital.edu.co | K92: CC | L92: 19242769 | M92: 2002-1
A93: 90 | B93: 20002095003 | C93: SAMUEL BARRETO MELO | D93: 95 | E93: MAESTRIA EN TELEINFORMATICA | F93: E | G93: ESTUDIANTE GRADUADO | H93: NO REGISTRA | I93: sbarretom@correo.udistrital.edu.co | J93: sbarretom@estudiante.udistrital.edu.co | K93: CC | L93: 17312219 | M93: 2002-3
A94: 91 | B94: 20002095006 | C94: CASTANG MONTIEL GERARDO ALBERTO | D94: 95 | E94: MAESTRIA EN TELEINFORMATICA | F94: E | G94: ESTUDIANTE GRADUADO | H94: NO REGISTRA | I94: gacastangm@correo.udistrital.edu.co | J94: gacastangm@estudiante.udistrital.edu.co | K94: CC | L94: 79799595 | M94: 2003-1
A95: 92 | B95: 20002095011 | C95: LOPEZ ORTEGA DIANA LUZ | D95: 95 | E95: MAESTRIA EN TELEINFORMATICA | F95: E | G95: ESTUDIANTE GRADUADO | H95: NO REGISTRA | I95: dllopezo@correo.udistrital.edu.co | J95: dllopezo@estudiante.udistrital.edu.co | K95: CC | L95: 51936731 | M95: 2002-3
A96: 93 | B96: 20002095016 | C96: SOTO VARGAS JAVIER EVANDRO | D96: 95 | E96: MAESTRIA EN TELEINFORMATICA | F96: E | G96: ESTUDIANTE GRADUADO | H96: NO REGISTRA | I96: jesotov@correo.udistrital.edu.co | J96: jesotov@estudiante.udistrital.edu.co | K96: CC | L96: 79944644 | M96: 2002-3
A97: 94 | B97: 20011095004 | C97: DE DIEGO PALAENCIA ALEXANDRA | D97: 95 | E97: MAESTRIA EN TELEINFORMATICA | F97: E | G97: ESTUDIANTE GRADUADO | H97: NO REGISTRA | K97: CC | L97: 52420706 | M97: 2002-3
A98: 95 | B98: 20011095005 | C98: FERNANDEZ IBARRA RAFAEL ALBERTO | D98: 95 | E98: MAESTRIA EN TELEINFORMATICA | F98: E | G98: ESTUDIANTE GRADUADO | H98: NO REGISTRA | I98: rafernandezi@correo.udistrital.edu.co | J98: rfernandeztalkpro@gmail.com | K98: CC | L98: 79624214 | M98: 2015-1
A99: 96 | B99: 20011095006 | C99: GIRALDO PE?ARANDA LEONEL | D99: 95 | E99: MAESTRIA EN TELEINFORMATICA | F99: E | G99: ESTUDIANTE GRADUADO | H99: NO REGISTRA | K99: CC | L99: 79375917 | M99: 2003-3
A100: 97 | B100: 20011095028 | C100: JAIME VITOLA OYAGA | D100: 95 | E100: MAESTRIA EN TELEINFORMATICA | F100: E | G100: ESTUDIANTE GRADUADO | H100: NO REGISTRA | I100: jvitolao@correo.udistrital.edu.co | J100: jvitolao@estudiante.udistrital.edu.co | K100: CC | L100: 79569346 | M100: 2003-3
A101: 98 | B101: 20012095001 | C101: ANDRES ACU?A CANO | D101: 95 | E101: MAESTRIA EN TELEINFORMATICA | F101: E | G101: ESTUDIANTE GRADUADO | H101: NO REGISTRA | I101: aacunac@correo.udistrital.edu.co | J101: aacunac@estudiante.udistrital.edu.co | K101: CC | L101: 4287757 | M101: 2004-3
A102: 99 | B102: 20012095003 | C102: DARIO ORLANDO BECERRA ERAZO | D102: 95 | E102: MAESTRIA EN TELEINFORMATICA | F102: E | G102: ESTUDIANTE GRADUADO | H102: NO REGISTRA | I102: dobecerrae@correo.udistrital.edu.co | J102: dario.becerra@gmail.com | K102: CC | L102: 94460645 | M102: 2009-3
...

Sheet EMPLEADORES
